Workbook
Name beef: #REF!
Name beef: #REF!
Name beef: #REF!
Name beef: #REF!
Name beef: #REF!
Name cocoa: #REF!
Name cocoa: #REF!
Name cocoa: #REF!
Name cocoa: #REF!
Name cocoa: #REF!
Name cocoa2: #REF!
Name cocoa2: #REF!
Name cocoa2: #REF!
Name cocoa2: #REF!
Name cocoa2: #REF!
Name coil: #REF!
Name coil: #REF!
Name coil: #REF!
Name coil: #REF!
Name coil: #REF!
Name DATES_A: #REF!
Name DATES_A: #REF!
Name DATES_A: #REF!
Name DATES_A: #REF!
Name DATES_A: #REF!
Name Donor_Rev1: [1]Budget_Donor!$A$1:$O$652
Name e: #REF!
Name e: #REF!
Name e: #REF!
Name e: #REF!
Name e: #REF!
Name ex: #REF!
Name ex: #REF!
Name ex: #REF!
Name ex: #REF!
Name ex: #REF!
Name Exp: [2]Budget!$A$1:$O$5890
Name exr: #REF!
Name exr: #REF!
Name exr: #REF!
Name exr: #REF!
Name exr: #REF!
Name Fund: [3]tbl_Funding_Source!$A$2:$B$53
Name Funding_Source: [4]Funding_Source!$A$1:$D$54
Name ge: #REF!
Name ge: #REF!
Name ge: #REF!
Name ge: #REF!
Name ge: #REF!
Name Item: [3]tbl_Item_Code!$A$2:$B$395
Name Location: [3]tbl_Location!$A$2:$B$9
Name NAMES_A: #REF!
Name NAMES_A: #REF!
Name NAMES_A: #REF!
Name NAMES_A: #REF!
Name NAMES_A: #REF!
Name PRINT_AREA_MI: #REF!
Name PRINT_AREA_MI: #REF!
Name PRINT_AREA_MI: #REF!
Name PRINT_AREA_MI: #REF!

Sheet GFS 2025_26 Budget
B1: 0 | C1: =1189-600 -> 589 | D1: Discrepancies | E1: =Sum_Bud_data!N9 -> Actual FY2025 | F1: Budget Estimate 2025/26 | G1: =Sum_Bud_data!P9 -> Budget Outturn FY2026 | H1: =Sum_Bud_data!Q9 -> Budget Statement 2026/27 (Recurrent) | I1: =Sum_Bud_data!R9 -> Budget Statement 2026/27 (Budget Support) | J1: =Sum_Bud_data!S9 -> Budget Statement 2026/27 (Development Cash) | K1: =Sum_Bud_data!T9 -> Budget Statement 2026/27 (In-kind) | L1: =Sum_Bud_data!U9 -> Budget Estimate 2026/27 | M1: =Sum_Bud_data!V9 -> Budget Statement 2027/28 (Recurrent) | N1: =Sum_Bud_data!W9 -> Budget Statement 2027/28 (Budget Support) | ... V1: =Sum_Bud_data!AE9 -> Budget Estimate 2028/29
B2: =IFERROR(LEFT(C2,1),"") | D2: Total Receipts (TR) | E2: =SUMIFS(E$6:E$1018, $B6:$B1018, "0") -> 8.3754088e+08 | F2: =SUMIFS(F$6:F$1018, $B6:$B1018, "0") -> 993780200 | G2: =SUMIFS(G$6:G$1018, $B6:$B1018, "0") -> 825726700 | H2: =SUMIFS(H$6:H$1018, $B6:$B1018, "0") -> 481018400 | I2: =SUMIFS(I$6:I$1018, $B6:$B1018, "0") -> 118010900 | J2: =SUMIFS(J$6:J$1018, $B6:$B1018, "0") -> 133083800 | K2: =SUMIFS(K$6:K$1018, $B6:$B1018, "0") -> 214157200 | L2: =SUMIFS(L$6:L$1018, $B6:$B1018, "0") -> 946270300 | ... V2: =SUMIFS(V$6:V$1018, $B6:$B1018, "0") -> 760201900
B3: =IFERROR(LEFT(C3,1),"") | D3: Total Payments (TP) | E3: =SUMIFS(E$6:E$1000, $B6:$B1000, "1")+SUMIFS(E$6:E$1000, $B6:$B1000, "2") -> 8.6433646e+08 | F3: =SUMIFS(F$6:F$1000, $B6:$B1000, "1")+SUMIFS(F$6:F$1000, $B6:$B1000, "2") -> 992831600 | G3: =SUMIFS(G$6:G$1018, $B6:$B1018, "1")+SUMIFS(G$6:G$1018, $B6:$B1018, "2") -> 824334500 | H3: =SUMIFS(H$6:H$1018, $B6:$B1018, "1")+SUMIFS(H$6:H$1018, $B6:$B1018, "2") -> 484154600 | I3: =SUMIFS(I$6:I$1018, $B6:$B1018, "1")+SUMIFS(I$6:I$1018, $B6:$B1018, "2") -> 118010900 | J3: =SUMIFS(J$6:J$1018, $B6:$B1018, "1")+SUMIFS(J$6:J$1018, $B6:$B1018, "2") -> 133083800 | K3: =SUMIFS(K$6:K$1018, $B6:$B1018, "1")+SUMIFS(K$6:K$1018, $B6:$B1018, "2") -> 214157200 | L3: =SUMIFS(L$6:L$1018, $B6:$B1018, "1")+SUMIFS(L$6:L$1018, $B6:$B1018, "2") -> 949406500 | M3: =SUMIFS(M$6:M$1018, $B6:$B1018, "1")+SUMIFS(M$6:M$1018, $B6:$B1018, "2") -> 486046300 | N3: =SUMIFS(N$6:N$1018, $B6:$B1018, "1")+SUMIFS(N$6:N$1018, $B6:$B1018, "2") -> 86953000 | ... V3: =SUMIFS(V$6:V$1018, $B6:$B1018, "1")+SUMIFS(V$6:V$1018, $B6:$B1018, "2") -> 761439900
B4: =IFERROR(LEFT(C4,1),"") | D4: Receipts less Payments | E4: =E2-E3 -> -26795589 | F4: =F2-F3 -> 948600 | G4: =G2-G3 -> 1392200 | H4: =H2-H3 -> -3136200 | I4: =I2-I3 -> 0 | J4: =J2-J3 -> 0 | K4: =K2-K3 -> 0 | L4: =L2-L3 -> -3136200 | ... V4: =V2-V3 -> -1238000
A5: GFSM 2001 Code | B5: =IFERROR(LEFT(C5,1),"") -> I | C5: Item Code | D5: Statement of Government Operations ($m) | E5: =E1 -> Actual FY2025 | F5: =F1 -> Budget Estimate 2025/26 | G5: =G1 -> Budget Outturn FY2026 | H5: =H1 -> Budget Statement 2026/27 (Recurrent) | I5: =I1 -> Budget Statement 2026/27 (Budget Support) | J5: =J1 -> Budget Statement 2026/27 (Development Cash) | K5: =K1 -> Budget Statement 2026/27 (In-kind) | L5: =L1 -> Budget Estimate 2026/27 | ... V5: =V1 -> Budget Estimate 2028/29
A6: 1 | B6: =IFERROR(LEFT(C6,1),"") | D6: REVENUE | E6: =SUM(E7,E139,E156,E269) -> 8.1096293e+08 | F6: =SUM(F7,F139,F156,F269) -> 929756100 | G6: =SUM(G7,G139,G156,G269) -> 791356900 | H6: =SUM(H7,H139,H156,H269) -> 412146400 | I6: =SUM(I7,I139,I156,I269) -> 118010900 | J6: =SUM(J7,J139,J156,J269) -> 133083800 | K6: =SUM(K7,K139,K156,K269) -> 214157200 | L6: =IFERROR(SUM(H6:K6),"") -> 877398300 | M6: =SUM(M7,M139,M156,M269) -> 459512900 | N6: =SUM(N7,N139,N156,N269) -> 86953000 | O6: =SUM(O7,O139,O156,O269) -> 105835800 | P6: =SUM(P7,P139,P156,P269) -> 233839500 | Q6: =IFERROR(SUM(M6:P6),"") -> 886141200 | R6: =SUM(R7,R139,R156,R269) -> 483292700 | S6: =SUM(S7,S139,S156,S269) -> 47529100 | T6: =SUM(T7,T139,T156,T269) -> 79504600 | U6: =SUM(U7,U139,U156,U269) -> 143848800 | V6: =IFERROR(SUM(R6:U6),"") -> 754175200
A7: 11 | B7: =IFERROR(LEFT(C7,1),"") | D7: Taxes | E7: =SUM(E8,E27,E30,E53,E111,E133) -> 3.2847224e+08 | F7: =SUM(F8,F27,F30,F53,F111,F133) -> 347077400 | G7: =SUM(G8,G27,G30,G53,G111,G133) -> 342804700 | H7: =SUM(H8,H27,H30,H53,H111,H133) -> 351914600 | I7: =SUM(I8,I27,I30,I53,I111,I133) -> 0 | J7: =SUM(J8,J27,J30,J53,J111,J133) -> 0 | K7: =SUM(K8,K27,K30,K53,K111,K133) -> 0 | L7: =IFERROR(SUM(H7:K7),"") -> 351914600 | M7: =SUM(M8,M27,M30,M53,M111,M133) -> 394737300 | N7: =SUM(N8,N27,N30,N53,N111,N133) -> 0 | O7: =SUM(O8,O27,O30,O53,O111,O133) -> 0 | P7: =SUM(P8,P27,P30,P53,P111,P133) -> 0 | Q7: =IFERROR(SUM(M7:P7),"") -> 394737300 | R7: =SUM(R8,R27,R30,R53,R111,R133) -> 414770900 | S7: =SUM(S8,S27,S30,S53,S111,S133) -> 0 | T7: =SUM(T8,T27,T30,T53,T111,T133) -> 0 | U7: =SUM(U8,U27,U30,U53,U111,U133) -> 0 | V7: =IFERROR(SUM(R7:U7),"") -> 414770900
A8: 111 | B8: =IFERROR(LEFT(C8,1),"") | D8: Taxes on income, profits, and capital gains | E8: =SUM(E12,E21) -> 76885797 | F8: =SUM(F12,F21) -> 78699500 | G8: =SUM(G12,G21) -> 78663200 | H8: =SUM(H12,H21) -> 81751200 | I8: =SUM(I12,I21) -> 0 | J8: =SUM(J12,J21) -> 0 | K8: =SUM(K12,K21) -> 0 | L8: =IFERROR(SUM(H8:K8),"") -> 81751200 | M8: =SUM(M12,M21) -> 89777000 | N8: =SUM(N12,N21) -> 0 | O8: =SUM(O12,O21) -> 0 | P8: =SUM(P12,P21) -> 0 | Q8: =IFERROR(SUM(M8:P8),"") -> 89777000 | R8: =SUM(R12,R21) -> 94209800 | S8: =SUM(S12,S21) -> 0 | T8: =SUM(T12,T21) -> 0 | U8: =SUM(U12,U21) -> 0 | V8: =IFERROR(SUM(R8:U8),"") -> 94209800
A9: 1111 | B9: =IFERROR(LEFT(C9,1),"") | D9: Payable by individuals
A10: 1111 | B10: =IFERROR(LEFT(C10,1),"") -> 0 | C10: 0001 | D10: PAYE Tax - Government (Small Business) | E10: =IFERROR(VLOOKUP($C10,'[8]Total Inflows'!$AE$4:$AH$165,2,0),"") -> 12324076 | F10: =IFERROR(VLOOKUP($C10,'[8]Total Inflows'!$AE$4:$AH$165,3,0),"") -> 11681600 | G10: =IFERROR(VLOOKUP($C10,'[8]Total Inflows'!$AE$4:$AH$165,4,0),"") -> 13386200 | H10: =IFERROR(VLOOKUP($C10,'[8]Total Inflows'!$AJ$4:$AM$110,2,0),"") -> 14303000 | I10: =IFERROR(VLOOKUP($C10,'[8]Total Inflows'!$AO$4:$AR$10,2,0),"") -> 0 | J10: =IFERROR(VLOOKUP($C10,'[8]Total Inflows'!$AU$4:$AX$54,2,0),"") -> 0 | K10: =IFERROR(VLOOKUP($C10,'[8]Total Inflows'!$AZ$4:$BC$30,2,0),"") | L10: =IFERROR(SUM(H10:K10),"") -> 14303000 | M10: =IFERROR(VLOOKUP($C10,'[8]Total Inflows'!$AJ$4:$AM$110,3,0),"") -> 15277400 | N10: =IFERROR(VLOOKUP($C10,'[8]Total Inflows'!$AO$4:$AR$10,3,0),"") -> 0 | O10: =IFERROR(VLOOKUP($C10,'[8]Total Inflows'!$AU$4:$AX$54,3,0),"") -> 0 | P10: =IFERROR(VLOOKUP($C10,'[8]Total Inflows'!$AZ$4:$BC$30,3,0),"") | Q10: =IFERROR(SUM(M10:P10),"") -> 15277400 | R10: =IFERROR(VLOOKUP($C10,'[8]Total Inflows'!$AJ$4:$AM$110,4,0),"") -> 16372000 | S10: =IFERROR(VLOOKUP($C10,'[8]Total Inflows'!$AO$4:$AR$10,4,0),"") -> 0 | T10: =IFERROR(VLOOKUP($C10,'[8]Total Inflows'!$AU$4:$AX$54,4,0),"") -> 0 | U10: =IFERROR(VLOOKUP($C10,'[8]Total Inflows'!$AZ$4:$BC$30,4,0),"") | V10: =IFERROR(SUM(R10:U10),"") -> 16372000
A11: 1111 | B11: =IFERROR(LEFT(C11,1),"") -> 0 | C11: 0002 | D11: PAYE Tax - Non-Government (Large / Small Business) | E11: =IFERROR(VLOOKUP($C11,'[8]Total Inflows'!$AE$4:$AH$165,2,0),"") -> 16454602 | F11: =IFERROR(VLOOKUP($C11,'[8]Total Inflows'!$AE$4:$AH$165,3,0),"") -> 17090300 | G11: =IFERROR(VLOOKUP($C11,'[8]Total Inflows'!$AE$4:$AH$165,4,0),"") -> 16802800 | H11: =IFERROR(VLOOKUP($C11,'[8]Total Inflows'!$AJ$4:$AM$110,2,0),"") -> 17953800 | I11: =IFERROR(VLOOKUP($C11,'[8]Total Inflows'!$AO$4:$AR$10,2,0),"") | J11: =IFERROR(VLOOKUP($C11,'[8]Total Inflows'!$AU$4:$AX$54,2,0),"") | K11: =IFERROR(VLOOKUP($C11,'[8]Total Inflows'!$AZ$4:$BC$30,2,0),"") | L11: =IFERROR(SUM(H11:K11),"") -> 17953800 | M11: =IFERROR(VLOOKUP($C11,'[9]Total Inflows'!$AI$4:$AL$110,3,0),"") -> 19176800 | N11: =IFERROR(VLOOKUP($C11,'[8]Total Inflows'!$AO$4:$AR$10,3,0),"") | O11: =IFERROR(VLOOKUP($C11,'[8]Total Inflows'!$AU$4:$AX$54,3,0),"") | P11: =IFERROR(VLOOKUP($C11,'[8]Total Inflows'!$AZ$4:$BC$30,3,0),"") | Q11: =IFERROR(SUM(M11:P11),"") -> 19176800 | R11: =IFERROR(VLOOKUP($C11,'[9]Total Inflows'!$AI$4:$AL$110,4,0),"") -> 19550900 | S11: =IFERROR(VLOOKUP($C11,'[8]Total Inflows'!$AO$4:$AR$10,4,0),"") | T11: =IFERROR(VLOOKUP($C11,'[8]Total Inflows'!$AU$4:$AX$54,4,0),"") | U11: =IFERROR(VLOOKUP($C11,'[8]Total Inflows'!$AZ$4:$BC$30,4,0),"") | V11: =IFERROR(SUM(R11:U11),"") -> 19550900
B12: =IFERROR(LEFT(C12,1),"") | E12: =SUM(E10:E11) -> 28778678 | F12: =SUM(F10:F11) -> 28771900 | G12: =SUM(G10:G11) -> 30189000 | H12: =SUM(H10:H11) -> 32256800 | I12: =SUM(I10:I11) -> 0 | J12: =SUM(J10:J11) -> 0 | K12: =SUM(K10:K11) -> 0 | L12: =IFERROR(SUM(H12:K12),"") -> 32256800 | M12: =SUM(M10:M11) -> 34454200 | N12: =SUM(N10:N11) -> 0 | O12: =SUM(O10:O11) -> 0 | P12: =SUM(P10:P11) -> 0 | Q12: =IFERROR(SUM(M12:P12),"") -> 34454200 | R12: =SUM(R10:R11) -> 35922900 | S12: =SUM(S10:S11) -> 0 | T12: =SUM(T10:T11) -> 0 | U12: =SUM(U10:U11) -> 0 | V12: =IFERROR(SUM(R12:U12),"") -> 35922900
B13: =IFERROR(LEFT(C13,1),"")
B14: =IFERROR(LEFT(C14,1),"")
A15: 1112 | B15: =IFERROR(LEFT(C15,1),"") | D15: Payable by corporations and other enterprises
A16: 1112 | B16: =IFERROR(LEFT(C16,1),"") -> 0 | C16: 0003 | D16: Corporate Tax - Small Business | E16: =IFERROR(VLOOKUP($C16,'[8]Total Inflows'!$AE$4:$AH$165,2,0),"") -> 1161421.7 | F16: =IFERROR(VLOOKUP($C16,'[8]Total Inflows'!$AE$4:$AH$165,3,0),"") -> 1399400 | G16: =IFERROR(VLOOKUP($C16,'[8]Total Inflows'!$AE$4:$AH$165,4,0),"") -> 930400 | H16: =IFERROR(VLOOKUP($C16,'[8]Total Inflows'!$AJ$4:$AM$110,2,0),"") -> 894100 | I16: =IFERROR(VLOOKUP($C16,'[8]Total Inflows'!$AO$4:$AR$10,2,0),"") | J16: =IFERROR(VLOOKUP($C16,'[8]Total Inflows'!$AU$4:$AX$54,2,0),"") | K16: =IFERROR(VLOOKUP($C16,'[8]Total Inflows'!$AZ$4:$BC$30,2,0),"") | L16: =IFERROR(SUM(H16:K16),"") -> 894100 | M16: =IFERROR(VLOOKUP($C16,'[9]Total Inflows'!$AI$4:$AL$110,3,0),"") -> 1061800 | N16: =IFERROR(VLOOKUP($C16,'[8]Total Inflows'!$AO$4:$AR$10,3,0),"") | O16: =IFERROR(VLOOKUP($C16,'[8]Total Inflows'!$AU$4:$AX$54,3,0),"") | P16: =IFERROR(VLOOKUP($C16,'[8]Total Inflows'!$AZ$4:$BC$30,3,0),"") | Q16: =IFERROR(SUM(M16:P16),"") -> 1061800 | R16: =IFERROR(VLOOKUP($C16,'[9]Total Inflows'!$AI$4:$AL$110,4,0),"") -> 1137900 | S16: =IFERROR(VLOOKUP($C16,'[8]Total Inflows'!$AO$4:$AR$10,4,0),"") | T16: =IFERROR(VLOOKUP($C16,'[8]Total Inflows'!$AU$4:$AX$54,4,0),"") | U16: =IFERROR(VLOOKUP($C16,'[8]Total Inflows'!$AZ$4:$BC$30,4,0),"") | V16: =IFERROR(SUM(R16:U16),"") -> 1137900
A17: 1112 | B17: =IFERROR(LEFT(C17,1),"") -> 0 | C17: 0004 | D17: Corporate Tax - Large Business | E17: =IFERROR(VLOOKUP($C17,'[8]Total Inflows'!$AE$4:$AH$165,2,0),"") -> 25009988 | F17: =IFERROR(VLOOKUP($C17,'[8]Total Inflows'!$AE$4:$AH$165,3,0),"") -> 24262700 | G17: =IFERROR(VLOOKUP($C17,'[8]Total Inflows'!$AE$4:$AH$165,4,0),"") -> 24889900 | H17: =IFERROR(VLOOKUP($C17,'[8]Total Inflows'!$AJ$4:$AM$110,2,0),"") -> 25394800 | I17: =IFERROR(VLOOKUP($C17,'[8]Total Inflows'!$AO$4:$AR$10,2,0),"") | J17: =IFERROR(VLOOKUP($C17,'[8]Total Inflows'!$AU$4:$AX$54,2,0),"") | K17: =IFERROR(VLOOKUP($C17,'[8]Total Inflows'!$AZ$4:$BC$30,2,0),"") | L17: =IFERROR(SUM(H17:K17),"") -> 25394800 | M17: =IFERROR(VLOOKUP($C17,'[9]Total Inflows'!$AI$4:$AL$110,3,0),"") -> 28406500 | N17: =IFERROR(VLOOKUP($C17,'[8]Total Inflows'!$AO$4:$AR$10,3,0),"") | O17: =IFERROR(VLOOKUP($C17,'[8]Total Inflows'!$AU$4:$AX$54,3,0),"") | P17: =IFERROR(VLOOKUP($C17,'[8]Total Inflows'!$AZ$4:$BC$30,3,0),"") | Q17: =IFERROR(SUM(M17:P17),"") -> 28406500 | R17: =IFERROR(VLOOKUP($C17,'[9]Total Inflows'!$AI$4:$AL$110,4,0),"") -> 30441900 | S17: =IFERROR(VLOOKUP($C17,'[8]Total Inflows'!$AO$4:$AR$10,4,0),"") | T17: =IFERROR(VLOOKUP($C17,'[8]Total Inflows'!$AU$4:$AX$54,4,0),"") | U17: =IFERROR(VLOOKUP($C17,'[8]Total Inflows'!$AZ$4:$BC$30,4,0),"") | V17: =IFERROR(SUM(R17:U17),"") -> 30441900
A18: 1112 | B18: =IFERROR(LEFT(C18,1),"") -> 0 | C18: 0005 | D18: Witholding Tax (residents) | E18: =IFERROR(VLOOKUP($C18,'[8]Total Inflows'!$AE$4:$AH$165,2,0),"") -> 637133.23 | F18: =IFERROR(VLOOKUP($C18,'[8]Total Inflows'!$AE$4:$AH$165,3,0),"") -> 670500 | G18: =IFERROR(VLOOKUP($C18,'[8]Total Inflows'!$AE$4:$AH$165,4,0),"") -> 719200 | H18: =IFERROR(VLOOKUP($C18,'[8]Total Inflows'!$AJ$4:$AM$110,2,0),"") -> 668400 | I18: =IFERROR(VLOOKUP($C18,'[8]Total Inflows'!$AO$4:$AR$10,2,0),"") | J18: =IFERROR(VLOOKUP($C18,'[8]Total Inflows'!$AU$4:$AX$54,2,0),"") | K18: =IFERROR(VLOOKUP($C18,'[8]Total Inflows'!$AZ$4:$BC$30,2,0),"") | L18: =IFERROR(SUM(H18:K18),"") -> 668400 | M18: =IFERROR(VLOOKUP($C18,'[9]Total Inflows'!$AI$4:$AL$110,3,0),"") -> 820800 | N18: =IFERROR(VLOOKUP($C18,'[8]Total Inflows'!$AO$4:$AR$10,3,0),"") | O18: =IFERROR(VLOOKUP($C18,'[8]Total Inflows'!$AU$4:$AX$54,3,0),"") | P18: =IFERROR(VLOOKUP($C18,'[8]Total Inflows'!$AZ$4:$BC$30,3,0),"") | Q18: =IFERROR(SUM(M18:P18),"") -> 820800 | R18: =IFERROR(VLOOKUP($C18,'[9]Total Inflows'!$AI$4:$AL$110,4,0),"") -> 879600 | S18: =IFERROR(VLOOKUP($C18,'[8]Total Inflows'!$AO$4:$AR$10,4,0),"") | T18: =IFERROR(VLOOKUP($C18,'[8]Total Inflows'!$AU$4:$AX$54,4,0),"") | U18: =IFERROR(VLOOKUP($C18,'[8]Total Inflows'!$AZ$4:$BC$30,4,0),"") | V18: =IFERROR(SUM(R18:U18),"") -> 879600
A19: 1112 | B19: =IFERROR(LEFT(C19,1),"") -> 0 | C19: 0006 | D19: Witholding Tax (non-residents) | E19: =IFERROR(VLOOKUP($C19,'[8]Total Inflows'!$AE$4:$AH$165,2,0),"") -> 16757774 | F19: =IFERROR(VLOOKUP($C19,'[8]Total Inflows'!$AE$4:$AH$165,3,0),"") -> 18375100 | G19: =IFERROR(VLOOKUP($C19,'[8]Total Inflows'!$AE$4:$AH$165,4,0),"") -> 18558300 | H19: =IFERROR(VLOOKUP($C19,'[8]Total Inflows'!$AJ$4:$AM$110,2,0),"") -> 18929400 | I19: =IFERROR(VLOOKUP($C19,'[8]Total Inflows'!$AO$4:$AR$10,2,0),"") | J19: =IFERROR(VLOOKUP($C19,'[8]Total Inflows'!$AU$4:$AX$54,2,0),"") | K19: =IFERROR(VLOOKUP($C19,'[8]Total Inflows'!$AZ$4:$BC$30,2,0),"") | L19: =IFERROR(SUM(H19:K19),"") -> 18929400 | M19: =IFERROR(VLOOKUP($C19,'[9]Total Inflows'!$AI$4:$AL$110,3,0),"") -> 21180200 | N19: =IFERROR(VLOOKUP($C19,'[8]Total Inflows'!$AO$4:$AR$10,3,0),"") | O19: =IFERROR(VLOOKUP($C19,'[8]Total Inflows'!$AU$4:$AX$54,3,0),"") | P19: =IFERROR(VLOOKUP($C19,'[8]Total Inflows'!$AZ$4:$BC$30,3,0),"") | Q19: =IFERROR(SUM(M19:P19),"") -> 21180200 | R19: =IFERROR(VLOOKUP($C19,'[9]Total Inflows'!$AI$4:$AL$110,4,0),"") -> 21697900 | S19: =IFERROR(VLOOKUP($C19,'[8]Total Inflows'!$AO$4:$AR$10,4,0),"") | T19: =IFERROR(VLOOKUP($C19,'[8]Total Inflows'!$AU$4:$AX$54,4,0),"") | U19: =IFERROR(VLOOKUP($C19,'[8]Total Inflows'!$AZ$4:$BC$30,4,0),"") | V19: =IFERROR(SUM(R19:U19),"") -> 21697900
A20: 1112 | B20: =IFERROR(LEFT(C20,1),"") -> 0 | C20: 0010 | D20: Tax Debts Recovered (Corporate) | E20: =IFERROR(VLOOKUP($C20,'[8]Total Inflows'!$AE$4:$AH$165,2,0),"") -> 4540802.2 | F20: =IFERROR(VLOOKUP($C20,'[8]Total Inflows'!$AE$4:$AH$165,3,0),"") -> 5219900 | G20: =IFERROR(VLOOKUP($C20,'[8]Total Inflows'!$AE$4:$AH$165,4,0),"") -> 3376400 | H20: =IFERROR(VLOOKUP($C20,'[8]Total Inflows'!$AJ$4:$AM$110,2,0),"") -> 3607700 | I20: =IFERROR(VLOOKUP($C20,'[8]Total Inflows'!$AO$4:$AR$10,2,0),"") | J20: =IFERROR(VLOOKUP($C20,'[8]Total Inflows'!$AU$4:$AX$54,2,0),"") | K20: =IFERROR(VLOOKUP($C20,'[8]Total Inflows'!$AZ$4:$BC$30,2,0),"") | L20: =IFERROR(SUM(H20:K20),"") -> 3607700 | M20: =IFERROR(VLOOKUP($C20,'[9]Total Inflows'!$AI$4:$AL$110,3,0),"") -> 3853500 | N20: =IFERROR(VLOOKUP($C20,'[8]Total Inflows'!$AO$4:$AR$10,3,0),"") | O20: =IFERROR(VLOOKUP($C20,'[8]Total Inflows'!$AU$4:$AX$54,3,0),"") | P20: =IFERROR(VLOOKUP($C20,'[8]Total Inflows'!$AZ$4:$BC$30,3,0),"") | Q20: =IFERROR(SUM(M20:P20),"") -> 3853500 | R20: =IFERROR(VLOOKUP($C20,'[9]Total Inflows'!$AI$4:$AL$110,4,0),"") -> 4129600 | S20: =IFERROR(VLOOKUP($C20,'[8]Total Inflows'!$AO$4:$AR$10,4,0),"") | T20: =IFERROR(VLOOKUP($C20,'[8]Total Inflows'!$AU$4:$AX$54,4,0),"") | U20: =IFERROR(VLOOKUP($C20,'[8]Total Inflows'!$AZ$4:$BC$30,4,0),"") | V20: =IFERROR(SUM(R20:U20),"") -> 4129600
B21: =IFERROR(LEFT(C21,1),"") | E21: =SUM(E16:E20) -> 48107118 | F21: =SUM(F16:F20) -> 49927600 | G21: =SUM(G16:G20) -> 48474200 | H21: =SUM(H16:H20) -> 49494400 | I21: =SUM(I16:I20) -> 0 | J21: =SUM(J16:J20) -> 0 | K21: =SUM(K16:K20) -> 0 | L21: =IFERROR(SUM(H21:K21),"") -> 49494400 | M21: =SUM(M16:M20) -> 55322800 | N21: =SUM(N16:N20) -> 0 | O21: =SUM(O16:O20) -> 0 | P21: =SUM(P16:P20) -> 0 | Q21: =IFERROR(SUM(M21:P21),"") -> 55322800 | R21: =SUM(R16:R20) -> 58286900 | S21: =SUM(S16:S20) -> 0 | T21: =SUM(T16:T20) -> 0 | U21: =SUM(U16:U20) -> 0 | V21: =IFERROR(SUM(R21:U21),"") -> 58286900
B22: =IFERROR(LEFT(C22,1),"") | E22: =IFERROR(SUM(#REF!),"")
B23: =IFERROR(LEFT(C23,1),"") | E23: =IFERROR(SUM(#REF!),"")
A24: 1113 | B24: =IFERROR(LEFT(C24,1),"") | D24: Unallocable taxes on income, profits, and capital gains | E24: =IFERROR(SUM(#REF!),"")
B25: =IFERROR(LEFT(C25,1),"") | E25: =IFERROR(SUM(#REF!),"")
B26: =IFERROR(LEFT(C26,1),"") | E26: =IFERROR(SUM(#REF!),"")
A27: 112 | B27: =IFERROR(LEFT(C27,1),"") | D27: Taxes on payroll and workforce | E27: =IFERROR(SUM(#REF!),"")
B28: =IFERROR(LEFT(C28,1),"") | E28: =IFERROR(SUM(#REF!),"")
B29: =IFERROR(LEFT(C29,1),"") | E29: =IFERROR(SUM(#REF!),"")
A30: 113 | B30: =IFERROR(LEFT(C30,1),"") | D30: Taxes on property | E30: =SUM(E35,E38,E41,E44,E47,E50) -> 345427.41 | F30: =SUM(F35,F38,F41,F44,F47,F50) -> 392100 | G30: =SUM(G35,G38,G41,G44,G47,G50) -> 402900 | H30: =SUM(H35,H38,H41,H44,H47,H50) -> 1630500 | I30: =SUM(I35,I38,I41,I44,I47,I50) -> 0 | J30: =SUM(J35,J38,J41,J44,J47,J50) -> 0 | K30: =SUM(K35,K38,K41,K44,K47,K50) -> 0 | L30: =IFERROR(SUM(H30:K30),"") -> 1630500 | M30: =SUM(M35,M38,M41,M44,M47,M50) -> 1659800 | N30: =SUM(N35,N38,N41,N44,N47,N50) -> 0 | O30: =SUM(O35,O38,O41,O44,O47,O50) -> 0 | P30: =SUM(P35,P38,P41,P44,P47,P50) -> 0 | Q30: =IFERROR(SUM(M30:P30),"") -> 1659800 | R30: =SUM(R35,R38,R41,R44,R47,R50) -> 1692700 | S30: =SUM(S35,S38,S41,S44,S47,S50) -> 0 | T30: =SUM(T35,T38,T41,T44,T47,T50) -> 0 | U30: =SUM(U35,U38,U41,U44,U47,U50) -> 0 | V30: =IFERROR(SUM(R30:U30),"") -> 1692700
A31: 1131 | B31: =IFERROR(LEFT(C31,1),"") | D31: Recurrent taxes on immovable property | E31: =IFERROR(SUM(#REF!),"")
A32: 1131 | B32: =IFERROR(LEFT(C32,1),"") -> 0 | C32: 0469 | D32: Poundage Land Rental | E32: =IFERROR(VLOOKUP($C32,'[8]Total Inflows'!$AE$4:$AH$165,2,0),"") -> 171483.18 | F32: =IFERROR(VLOOKUP($C32,'[8]Total Inflows'!$AE$4:$AH$165,3,0),"") -> 178500 | G32: =IFERROR(VLOOKUP($C32,'[8]Total Inflows'!$AE$4:$AH$165,4,0),"") -> 197800 | H32: =IFERROR(VLOOKUP($C32,'[8]Total Inflows'!$AJ$4:$AM$110,2,0),"") -> 1411300 | I32: =IFERROR(VLOOKUP($C32,'[8]Total Inflows'!$AO$4:$AR$10,2,0),"") | J32: =IFERROR(VLOOKUP($C32,'[8]Total Inflows'!$AU$4:$AX$54,2,0),"") | K32: =IFERROR(VLOOKUP($C32,'[8]Total Inflows'!$AZ$4:$BC$30,2,0),"") | L32: =IFERROR(SUM(H32:K32),"") -> 1411300 | M32: =IFERROR(VLOOKUP($C32,'[9]Total Inflows'!$AI$4:$AL$110,3,0),"") -> 1425700 | N32: =IFERROR(VLOOKUP($C32,'[8]Total Inflows'!$AO$4:$AR$10,3,0),"") | O32: =IFERROR(VLOOKUP($C32,'[8]Total Inflows'!$AU$4:$AX$54,3,0),"") | P32: =IFERROR(VLOOKUP($C32,'[8]Total Inflows'!$AZ$4:$BC$30,3,0),"") | Q32: =IFERROR(SUM(M32:P32),"") -> 1425700 | R32: =IFERROR(VLOOKUP($C32,'[9]Total Inflows'!$AI$4:$AL$110,4,0),"") -> 1441900 | S32: =IFERROR(VLOOKUP($C32,'[8]Total Inflows'!$AO$4:$AR$10,4,0),"") | T32: =IFERROR(VLOOKUP($C32,'[8]Total Inflows'!$AU$4:$AX$54,4,0),"") | U32: =IFERROR(VLOOKUP($C32,'[8]Total Inflows'!$AZ$4:$BC$30,4,0),"") | V32: =IFERROR(SUM(R32:U32),"") -> 1441900
A33: 1131 | B33: =IFERROR(LEFT(C33,1),"") -> 0 | C33: 0470 | D33: Rent on Tax Allotment | E33: =IFERROR(VLOOKUP($C33,'[8]Total Inflows'!$AE$4:$AH$165,2,0),"") -> 3939.23 | F33: =IFERROR(VLOOKUP($C33,'[8]Total Inflows'!$AE$4:$AH$165,3,0),"") -> 2200 | G33: =IFERROR(VLOOKUP($C33,'[8]Total Inflows'!$AE$4:$AH$165,4,0),"") -> 6200 | H33: =IFERROR(VLOOKUP($C33,'[8]Total Inflows'!$AJ$4:$AM$110,2,0),"") -> 6700 | I33: =IFERROR(VLOOKUP($C33,'[8]Total Inflows'!$AO$4:$AR$10,2,0),"") | J33: =IFERROR(VLOOKUP($C33,'[8]Total Inflows'!$AU$4:$AX$54,2,0),"") | K33: =IFERROR(VLOOKUP($C33,'[8]Total Inflows'!$AZ$4:$BC$30,2,0),"") | L33: =IFERROR(SUM(H33:K33),"") -> 6700 | M33: =IFERROR(VLOOKUP($C33,'[9]Total Inflows'!$AI$4:$AL$110,3,0),"") -> 7100 | N33: =IFERROR(VLOOKUP($C33,'[8]Total Inflows'!$AO$4:$AR$10,3,0),"") | O33: =IFERROR(VLOOKUP($C33,'[8]Total Inflows'!$AU$4:$AX$54,3,0),"") | P33: =IFERROR(VLOOKUP($C33,'[8]Total Inflows'!$AZ$4:$BC$30,3,0),"") | Q33: =IFERROR(SUM(M33:P33),"") -> 7100 | R33: =IFERROR(VLOOKUP($C33,'[9]Total Inflows'!$AI$4:$AL$110,4,0),"") -> 7600 | S33: =IFERROR(VLOOKUP($C33,'[8]Total Inflows'!$AO$4:$AR$10,4,0),"") | T33: =IFERROR(VLOOKUP($C33,'[8]Total Inflows'!$AU$4:$AX$54,4,0),"") | U33: =IFERROR(VLOOKUP($C33,'[8]Total Inflows'!$AZ$4:$BC$30,4,0),"") | V33: =IFERROR(SUM(R33:U33),"") -> 7600
A34: 1131 | B34: =IFERROR(LEFT(C34,1),"") -> 0 | C34: 0481 | D34: Industrial Properties Registration | E34: =IFERROR(VLOOKUP($C34,'[8]Total Inflows'!$AE$4:$AH$165,2,0),"") -> 170005 | F34: =IFERROR(VLOOKUP($C34,'[8]Total Inflows'!$AE$4:$AH$165,3,0),"") -> 211400 | G34: =IFERROR(VLOOKUP($C34,'[8]Total Inflows'!$AE$4:$AH$165,4,0),"") -> 198900 | H34: =IFERROR(VLOOKUP($C34,'[8]Total Inflows'!$AJ$4:$AM$110,2,0),"") -> 212500 | I34: =IFERROR(VLOOKUP($C34,'[8]Total Inflows'!$AO$4:$AR$10,2,0),"") | J34: =IFERROR(VLOOKUP($C34,'[8]Total Inflows'!$AU$4:$AX$54,2,0),"") | K34: =IFERROR(VLOOKUP($C34,'[8]Total Inflows'!$AZ$4:$BC$30,2,0),"") | L34: =IFERROR(SUM(H34:K34),"") -> 212500 | M34: =IFERROR(VLOOKUP($C34,'[9]Total Inflows'!$AI$4:$AL$110,3,0),"") -> 227000 | N34: =IFERROR(VLOOKUP($C34,'[8]Total Inflows'!$AO$4:$AR$10,3,0),"") | O34: =IFERROR(VLOOKUP($C34,'[8]Total Inflows'!$AU$4:$AX$54,3,0),"") | P34: =IFERROR(VLOOKUP($C34,'[8]Total Inflows'!$AZ$4:$BC$30,3,0),"") | Q34: =IFERROR(SUM(M34:P34),"") -> 227000 | R34: =IFERROR(VLOOKUP($C34,'[9]Total Inflows'!$AI$4:$AL$110,4,0),"") -> 243200 | S34: =IFERROR(VLOOKUP($C34,'[8]Total Inflows'!$AO$4:$AR$10,4,0),"") | T34: =IFERROR(VLOOKUP($C34,'[8]Total Inflows'!$AU$4:$AX$54,4,0),"") | U34: =IFERROR(VLOOKUP($C34,'[8]Total Inflows'!$AZ$4:$BC$30,4,0),"") | V34: =IFERROR(SUM(R34:U34),"") -> 243200
B35: =IFERROR(LEFT(C35,1),"") | E35: =SUM(E32:E34) -> 345427.41 | F35: =SUM(F32:F34) -> 392100 | G35: =SUM(G32:G34) -> 402900 | H35: =SUM(H32:H34) -> 1630500 | I35: =SUM(I32:I34) -> 0 | J35: =SUM(J32:J34) -> 0 | K35: =SUM(K32:K34) -> 0 | L35: =IFERROR(SUM(H35:K35),"") -> 1630500 | M35: =SUM(M32:M34) -> 1659800 | N35: =SUM(N32:N34) -> 0 | O35: =SUM(O32:O34) -> 0 | P35: =SUM(P32:P34) -> 0 | Q35: =IFERROR(SUM(M35:P35),"") -> 1659800 | R35: =SUM(R32:R34) -> 1692700 | S35: =SUM(S32:S34) -> 0 | T35: =SUM(T32:T34) -> 0 | U35: =SUM(U32:U34) -> 0 | V35: =IFERROR(SUM(R35:U35),"") -> 1692700
B36: =IFERROR(LEFT(C36,1),"") | E36: =IFERROR(SUM(#REF!),"")
B37: =IFERROR(LEFT(C37,1),"") | E37: =IFERROR(SUM(#REF!),"")
A38: 1132 | B38: =IFERROR(LEFT(C38,1),"") | D38: Recurrent taxes on net wealth | E38: =IFERROR(SUM(#REF!),"")
B39: =IFERROR(LEFT(C39,1),"") | E39: =IFERROR(SUM(#REF!),"")
B40: =IFERROR(LEFT(C40,1),"") | E40: =IFERROR(SUM(#REF!),"")
A41: 1133 | B41: =IFERROR(LEFT(C41,1),"") | D41: Estate, inheritance, and gift taxes | E41: =IFERROR(SUM(#REF!),"")
B42: =IFERROR(LEFT(C42,1),"") | E42: =IFERROR(SUM(#REF!),"")
B43: =IFERROR(LEFT(C43,1),"") | E43: =IFERROR(SUM(#REF!),"")
A44: 1134 | B44: =IFERROR(LEFT(C44,1),"") | D44: Taxes on financial and capital transactions | E44: =IFERROR(SUM(#REF!),"")
B45: =IFERROR(LEFT(C45,1),"") | E45: =IFERROR(SUM(#REF!),"")
B46: =IFERROR(LEFT(C46,1),"") | E46: =IFERROR(SUM(#REF!),"")
A47: 1135 | B47: =IFERROR(LEFT(C47,1),"") | D47: Other nonrecurrent taxes on property | E47: =IFERROR(SUM(#REF!),"")
B48: =IFERROR(LEFT(C48,1),"") | E48: =IFERROR(SUM(#REF!),"")
B49: =IFERROR(LEFT(C49,1),"") | E49: =IFERROR(SUM(#REF!),"")
A50: 1136 | B50: =IFERROR(LEFT(C50,1),"") | D50: Other recurrent taxes on property | E50: =IFERROR(SUM(#REF!),"")
B51: =IFERROR(LEFT(C51,1),"") | E51: =IFERROR(SUM(#REF!),"")
B52: =IFERROR(LEFT(C52,1),"") | E52: =IFERROR(SUM(#REF!),"")
A53: 114 | B53: =IFERROR(LEFT(C53,1),"") | D53: Taxes on goods and services | E53: =SUM(E54,E71,E83,E104) -> 2.1806865e+08 | F53: =SUM(F54,F71,F83,F104) -> 228323300 | G53: =SUM(G54,G71,G83,G104) -> 229595000 | H53: =SUM(H54,H71,H83,H104) -> 235250600 | I53: =SUM(I54,I71,I83,I104) -> 0 | J53: =SUM(J54,J71,J83,J104) -> 0 | K53: =SUM(K54,K71,K83,K104) -> 0 | L53: =IFERROR(SUM(H53:K53),"") -> 235250600 | M53: =SUM(M54,M71,M83,M104) -> 264333000 | N53: =SUM(N54,N71,N83,N104) -> 0 | O53: =SUM(O54,O71,O83,O104) -> 0 | P53: =SUM(P54,P71,P83,P104) -> 0 | Q53: =IFERROR(SUM(M53:P53),"") -> 264333000 | R53: =SUM(R54,R71,R83,R104) -> 278108800 | S53: =SUM(S54,S71,S83,S104) -> 0 | T53: =SUM(T54,T71,T83,T104) -> 0 | U53: =SUM(U54,U71,U83,U104) -> 0 | V53: =IFERROR(SUM(R53:U53),"") -> 278108800
A54: 1141 | B54: =IFERROR(LEFT(C54,1),"") | D54: General taxes on goods and services | E54: =E60 -> 1.4293908e+08 | F54: =F60 -> 145036800 | G54: =G60 -> 152011700 | H54: =H60 -> 160853300 | I54: =I60 -> 0 | J54: =J60 -> 0 | K54: =K60 -> 0 | L54: =IFERROR(SUM(H54:K54),"") -> 160853300 | M54: =M60 -> 175288900 | N54: =N60 -> 0 | O54: =O60 -> 0 | P54: =P60 -> 0 | Q54: =IFERROR(SUM(M54:P54),"") -> 175288900 | R54: =R60 -> 184719900 | S54: =S60 -> 0 | T54: =T60 -> 0 | U54: =U60 -> 0 | V54: =IFERROR(SUM(R54:U54),"") -> 184719900
A55: 11411 | B55: =IFERROR(LEFT(C55,1),"") | D55: Value-added taxes | E55: =IFERROR(SUM(#REF!),"") | L55: =IFERROR(SUM(H55:K55),"") -> 0 | Q55: =IFERROR(SUM(M55:P55),"") -> 0 | V55: =IFERROR(SUM(R55:U55),"") -> 0
A56: 11411 | B56: =IFERROR(LEFT(C56,1),"") -> 0 | C56: 0201 | D56: Consumption Tax - Import | E56: =IFERROR(VLOOKUP($C56,'[8]Total Inflows'!$AE$4:$AH$165,2,0),"") -> 1.0843444e+08 | F56: =IFERROR(VLOOKUP($C56,'[8]Total Inflows'!$AE$4:$AH$165,3,0),"") -> 111116600 | G56: =IFERROR(VLOOKUP($C56,'[8]Total Inflows'!$AE$4:$AH$165,4,0),"") -> 112147700 | H56: =IFERROR(VLOOKUP($C56,'[8]Total Inflows'!$AJ$4:$AM$110,2,0),"") -> 119829200 | I56: =IFERROR(VLOOKUP($C56,'[8]Total Inflows'!$AO$4:$AR$10,2,0),"") | J56: =IFERROR(VLOOKUP($C56,'[8]Total Inflows'!$AU$4:$AX$54,2,0),"") -> 0 | K56: =IFERROR(VLOOKUP($C56,'[8]Total Inflows'!$AZ$4:$BC$30,2,0),"") | L56: =IFERROR(SUM(H56:K56),"") -> 119829200 | M56: =IFERROR(VLOOKUP($C56,'[9]Total Inflows'!$AI$4:$AL$110,3,0),"") -> 127992200 | N56: =IFERROR(VLOOKUP($C56,'[8]Total Inflows'!$AO$4:$AR$10,3,0),"") | O56: =IFERROR(VLOOKUP($C56,'[8]Total Inflows'!$AU$4:$AX$54,3,0),"") -> 0 | P56: =IFERROR(VLOOKUP($C56,'[8]Total Inflows'!$AZ$4:$BC$30,3,0),"") | Q56: =IFERROR(SUM(M56:P56),"") -> 127992200 | R56: =IFERROR(VLOOKUP($C56,'[9]Total Inflows'!$AI$4:$AL$110,4,0),"") -> 135163300 | S56: =IFERROR(VLOOKUP($C56,'[8]Total Inflows'!$AO$4:$AR$10,4,0),"") | T56: =IFERROR(VLOOKUP($C56,'[8]Total Inflows'!$AU$4:$AX$54,4,0),"") -> 0 | U56: =IFERROR(VLOOKUP($C56,'[8]Total Inflows'!$AZ$4:$BC$30,4,0),"") | V56: =IFERROR(SUM(R56:U56),"") -> 135163300
A57: 11411 | B57: =IFERROR(LEFT(C57,1),"") -> 0 | C57: 0202 | D57: Consumption Tax - Domestic | E57: =IFERROR(VLOOKUP($C57,'[8]Total Inflows'!$AE$4:$AH$165,2,0),"") -> 29732782 | F57: =IFERROR(VLOOKUP($C57,'[8]Total Inflows'!$AE$4:$AH$165,3,0),"") -> 31086300 | G57: =IFERROR(VLOOKUP($C57,'[8]Total Inflows'!$AE$4:$AH$165,4,0),"") -> 37708000 | H57: =IFERROR(VLOOKUP($C57,'[8]Total Inflows'!$AJ$4:$AM$110,2,0),"") -> 38720500 | I57: =IFERROR(VLOOKUP($C57,'[8]Total Inflows'!$AO$4:$AR$10,2,0),"") | J57: =IFERROR(VLOOKUP($C57,'[8]Total Inflows'!$AU$4:$AX$54,2,0),"") -> 0 | K57: =IFERROR(VLOOKUP($C57,'[8]Total Inflows'!$AZ$4:$BC$30,2,0),"") | L57: =IFERROR(SUM(H57:K57),"") -> 38720500 | M57: =IFERROR(VLOOKUP($C57,'[9]Total Inflows'!$AI$4:$AL$110,3,0),"") -> 44836100 | N57: =IFERROR(VLOOKUP($C57,'[8]Total Inflows'!$AO$4:$AR$10,3,0),"") | O57: =IFERROR(VLOOKUP($C57,'[8]Total Inflows'!$AU$4:$AX$54,3,0),"") -> 0 | P57: =IFERROR(VLOOKUP($C57,'[8]Total Inflows'!$AZ$4:$BC$30,3,0),"") | Q57: =IFERROR(SUM(M57:P57),"") -> 44836100 | R57: =IFERROR(VLOOKUP($C57,'[9]Total Inflows'!$AI$4:$AL$110,4,0),"") -> 46919700 | S57: =IFERROR(VLOOKUP($C57,'[8]Total Inflows'!$AO$4:$AR$10,4,0),"") | T57: =IFERROR(VLOOKUP($C57,'[8]Total Inflows'!$AU$4:$AX$54,4,0),"") -> 0 | U57: =IFERROR(VLOOKUP($C57,'[8]Total Inflows'!$AZ$4:$BC$30,4,0),"") | V57: =IFERROR(SUM(R57:U57),"") -> 46919700
A58: 11411 | B58: =IFERROR(LEFT(C58,1),"") -> 0 | C58: 0203 | D58: Tukuhau Ngaue'aki Pule'anga (Government Consumptio | E58: =IFERROR(VLOOKUP($C58,'[8]Total Inflows'!$AE$4:$AH$165,2,0),"") -> 1716701 | F58: =IFERROR(VLOOKUP($C58,'[8]Total Inflows'!$AE$4:$AH$165,3,0),"") -> 0 | G58: =IFERROR(VLOOKUP($C58,'[8]Total Inflows'!$AE$4:$AH$165,4,0),"") -> 0 | H58: =IFERROR(VLOOKUP($C58,'[8]Total Inflows'!$AJ$4:$AM$110,2,0),"") -> 0 | I58: =IFERROR(VLOOKUP($C58,'[8]Total Inflows'!$AO$4:$AR$10,2,0),"") | J58: =IFERROR(VLOOKUP($C58,'[8]Total Inflows'!$AU$4:$AX$54,2,0),"") | K58: =IFERROR(VLOOKUP($C58,'[8]Total Inflows'!$AZ$4:$BC$30,2,0),"") | L58: =IFERROR(SUM(H58:K58),"") -> 0 | M58: =IFERROR(VLOOKUP($C58,'[9]Total Inflows'!$AI$4:$AL$110,3,0),"") -> 0 | N58: =IFERROR(VLOOKUP($C58,'[8]Total Inflows'!$AO$4:$AR$10,3,0),"") | O58: =IFERROR(VLOOKUP($C58,'[8]Total Inflows'!$AU$4:$AX$54,3,0),"") | P58: =IFERROR(VLOOKUP($C58,'[8]Total Inflows'!$AZ$4:$BC$30,3,0),"") | Q58: =IFERROR(SUM(M58:P58),"") -> 0 | R58: =IFERROR(VLOOKUP($C58,'[9]Total Inflows'!$AI$4:$AL$110,4,0),"") -> 0 | S58: =IFERROR(VLOOKUP($C58,'[8]Total Inflows'!$AO$4:$AR$10,4,0),"") | T58: =IFERROR(VLOOKUP($C58,'[8]Total Inflows'!$AU$4:$AX$54,4,0),"") | U58: =IFERROR(VLOOKUP($C58,'[8]Total Inflows'!$AZ$4:$BC$30,4,0),"") | V58: =IFERROR(SUM(R58:U58),"") -> 0
A59: 11411 | B59: =IFERROR(LEFT(C59,1),"") -> 0 | C59: 0210 | D59: Tax Debts Recovered (CT) | E59: =IFERROR(VLOOKUP($C59,'[8]Total Inflows'!$AE$4:$AH$165,2,0),"") -> 3055150.7 | F59: =IFERROR(VLOOKUP($C59,'[8]Total Inflows'!$AE$4:$AH$165,3,0),"") -> 2833900 | G59: =IFERROR(VLOOKUP($C59,'[8]Total Inflows'!$AE$4:$AH$165,4,0),"") -> 2156000 | H59: =IFERROR(VLOOKUP($C59,'[8]Total Inflows'!$AJ$4:$AM$110,2,0),"") -> 2303600 | I59: =IFERROR(VLOOKUP($C59,'[8]Total Inflows'!$AO$4:$AR$10,2,0),"") | J59: =IFERROR(VLOOKUP($C59,'[8]Total Inflows'!$AU$4:$AX$54,2,0),"") | K59: =IFERROR(VLOOKUP($C59,'[8]Total Inflows'!$AZ$4:$BC$30,2,0),"") | L59: =IFERROR(SUM(H59:K59),"") -> 2303600 | M59: =IFERROR(VLOOKUP($C59,'[9]Total Inflows'!$AI$4:$AL$110,3,0),"") -> 2460600 | N59: =IFERROR(VLOOKUP($C59,'[8]Total Inflows'!$AO$4:$AR$10,3,0),"") | O59: =IFERROR(VLOOKUP($C59,'[8]Total Inflows'!$AU$4:$AX$54,3,0),"") | P59: =IFERROR(VLOOKUP($C59,'[8]Total Inflows'!$AZ$4:$BC$30,3,0),"") | Q59: =IFERROR(SUM(M59:P59),"") -> 2460600 | R59: =IFERROR(VLOOKUP($C59,'[9]Total Inflows'!$AI$4:$AL$110,4,0),"") -> 2636900 | S59: =IFERROR(VLOOKUP($C59,'[8]Total Inflows'!$AO$4:$AR$10,4,0),"") | T59: =IFERROR(VLOOKUP($C59,'[8]Total Inflows'!$AU$4:$AX$54,4,0),"") | U59: =IFERROR(VLOOKUP($C59,'[8]Total Inflows'!$AZ$4:$BC$30,4,0),"") | V59: =IFERROR(SUM(R59:U59),"") -> 2636900
B60: =IFERROR(LEFT(C60,1),"") | E60: =SUM(E56:E59) -> 1.4293908e+08 | F60: =SUM(F56:F59) -> 145036800 | G60: =SUM(G56:G59) -> 152011700 | H60: =SUM(H56:H59) -> 160853300 | I60: =SUM(I56:I59) -> 0 | J60: =SUM(J56:J59) -> 0 | K60: =SUM(K56:K59) -> 0 | L60: =IFERROR(SUM(H60:K60),"") -> 160853300 | M60: =SUM(M56:M59) -> 175288900 | N60: =SUM(N56:N59) -> 0 | O60: =SUM(O56:O59) -> 0 | P60: =SUM(P56:P59) -> 0 | Q60: =IFERROR(SUM(M60:P60),"") -> 175288900 | R60: =SUM(R56:R59) -> 184719900 | S60: =SUM(S56:S59) -> 0 | T60: =SUM(T56:T59) -> 0 | U60: =SUM(U56:U59) -> 0 | V60: =IFERROR(SUM(R60:U60),"") -> 184719900
B61: =IFERROR(LEFT(C61,1),"") | E61: =IFERROR(SUM(#REF!),"")
B62: =IFERROR(LEFT(C62,1),"") | E62: =IFERROR(SUM(#REF!),"")
A63: 11412 | B63: =IFERROR(LEFT(C63,1),"") | D63: Sales taxes | E63: =IFERROR(SUM(#REF!),"")
B64: =IFERROR(LEFT(C64,1),"") | E64: =IFERROR(SUM(#REF!),"")
A65: 11413 | B65: =IFERROR(LEFT(C65,1),"") | D65: Turnover and other general taxes on goods and services | E65: =IFERROR(SUM(#REF!),"")
B66: =IFERROR(LEFT(C66,1),"") | E66: =IFERROR(SUM(#REF!),"")
A67: 1142 | B67: =IFERROR(LEFT(C67,1),"") | D67: Excises | E67: =IFERROR(SUM(#REF!),"")
B68: =IFERROR(LEFT(C68,1),"") | E68: =IFERROR(SUM(#REF!),"")
A69: 1142 | B69: =IFERROR(LEFT(C69,1),"") -> 0 | C69: 0301 | D69: Excise Tax | E69: =IFERROR(VLOOKUP($C69,'[8]Total Inflows'!$AE$4:$AH$165,2,0),"") -> 67723324 | F69: =IFERROR(VLOOKUP($C69,'[8]Total Inflows'!$AE$4:$AH$165,3,0),"") -> 71114900 | G69: =IFERROR(VLOOKUP($C69,'[8]Total Inflows'!$AE$4:$AH$165,4,0),"") -> 69584400 | H69: =IFERROR(VLOOKUP($C69,'[8]Total Inflows'!$AJ$4:$AM$110,2,0),"") -> 65350600 | I69: =IFERROR(VLOOKUP($C69,'[8]Total Inflows'!$AO$4:$AR$10,2,0),"") | J69: =IFERROR(VLOOKUP($C69,'[8]Total Inflows'!$AU$4:$AX$54,2,0),"") -> 0 | K69: =IFERROR(VLOOKUP($C69,'[8]Total Inflows'!$AZ$4:$BC$30,2,0),"") | L69: =IFERROR(SUM(H69:K69),"") -> 65350600 | M69: =IFERROR(VLOOKUP($C69,'[9]Total Inflows'!$AI$4:$AL$110,3,0),"") -> 79415500 | N69: =IFERROR(VLOOKUP($C69,'[8]Total Inflows'!$AO$4:$AR$10,3,0),"") | O69: =IFERROR(VLOOKUP($C69,'[8]Total Inflows'!$AU$4:$AX$54,3,0),"") -> 0 | P69: =IFERROR(VLOOKUP($C69,'[8]Total Inflows'!$AZ$4:$BC$30,3,0),"") | Q69: =IFERROR(SUM(M69:P69),"") -> 79415500 | R69: =IFERROR(VLOOKUP($C69,'[9]Total Inflows'!$AI$4:$AL$110,4,0),"") -> 83105900 | S69: =IFERROR(VLOOKUP($C69,'[8]Total Inflows'!$AO$4:$AR$10,4,0),"") | T69: =IFERROR(VLOOKUP($C69,'[8]Total Inflows'!$AU$4:$AX$54,4,0),"") -> 0 | U69: =IFERROR(VLOOKUP($C69,'[8]Total Inflows'!$AZ$4:$BC$30,4,0),"") | V69: =IFERROR(SUM(R69:U69),"") -> 83105900
A70: 1142 | B70: =IFERROR(LEFT(C70,1),"") -> 0 | C70: 0302 | D70: Excise Tax - Government | E70: =IFERROR(VLOOKUP($C70,'[8]Total Inflows'!$AE$4:$AH$165,2,0),"") -> 2245.5 | F70: =IFERROR(VLOOKUP($C70,'[8]Total Inflows'!$AE$4:$AH$165,3,0),"") -> 500 | G70: =IFERROR(VLOOKUP($C70,'[8]Total Inflows'!$AE$4:$AH$165,4,0),"") -> 2700 | H70: =IFERROR(VLOOKUP($C70,'[8]Total Inflows'!$AJ$4:$AM$110,2,0),"") -> 2800 | I70: =IFERROR(VLOOKUP($C70,'[8]Total Inflows'!$AO$4:$AR$10,2,0),"") | J70: =IFERROR(VLOOKUP($C70,'[8]Total Inflows'!$AU$4:$AX$54,2,0),"") | K70: =IFERROR(VLOOKUP($C70,'[8]Total Inflows'!$AZ$4:$BC$30,2,0),"") | L70: =IFERROR(SUM(H70:K70),"") -> 2800 | M70: =IFERROR(VLOOKUP($C70,'[9]Total Inflows'!$AI$4:$AL$110,3,0),"") -> 3000 | N70: =IFERROR(VLOOKUP($C70,'[8]Total Inflows'!$AO$4:$AR$10,3,0),"") | O70: =IFERROR(VLOOKUP($C70,'[8]Total Inflows'!$AU$4:$AX$54,3,0),"") | P70: =IFERROR(VLOOKUP($C70,'[8]Total Inflows'!$AZ$4:$BC$30,3,0),"") | Q70: =IFERROR(SUM(M70:P70),"") -> 3000 | R70: =IFERROR(VLOOKUP($C70,'[9]Total Inflows'!$AI$4:$AL$110,4,0),"") -> 3300 | S70: =IFERROR(VLOOKUP($C70,'[8]Total Inflows'!$AO$4:$AR$10,4,0),"") | T70: =IFERROR(VLOOKUP($C70,'[8]Total Inflows'!$AU$4:$AX$54,4,0),"") | U70: =IFERROR(VLOOKUP($C70,'[8]Total Inflows'!$AZ$4:$BC$30,4,0),"") | V70: =IFERROR(SUM(R70:U70),"") -> 3300
B71: =IFERROR(LEFT(C71,1),"") | E71: =SUM(E69:E70) -> 67725569 | F71: =SUM(F69:F70) -> 71115400 | G71: =SUM(G69:G70) -> 69587100 | H71: =SUM(H69:H70) -> 65353400 | I71: =SUM(I69:I70) -> 0 | J71: =SUM(J69:J70) -> 0 | K71: =SUM(K69:K70) -> 0 | L71: =IFERROR(SUM(H71:K71),"") -> 65353400 | M71: =SUM(M69:M70) -> 79418500 | N71: =SUM(N69:N70) -> 0 | O71: =SUM(O69:O70) -> 0 | P71: =SUM(P69:P70) -> 0 | Q71: =IFERROR(SUM(M71:P71),"") -> 79418500 | R71: =SUM(R69:R70) -> 83109200 | S71: =SUM(S69:S70) -> 0 | T71: =SUM(T69:T70) -> 0 | U71: =SUM(U69:U70) -> 0 | V71: =IFERROR(SUM(R71:U71),"") -> 83109200
B72: =IFERROR(LEFT(C72,1),"") | E72: =IFERROR(SUM(#REF!),"") | L72: =IFERROR(SUM(H72:K72),"") -> 0 | Q72: =IFERROR(SUM(M72:P72),"") -> 0 | V72: =IFERROR(SUM(R72:U72),"") -> 0
B73: =IFERROR(LEFT(C73,1),"") | E73: =IFERROR(SUM(#REF!),"") | L73: =IFERROR(SUM(H73:K73),"") -> 0 | Q73: =IFERROR(SUM(M73:P73),"") -> 0 | V73: =IFERROR(SUM(R73:U73),"") -> 0
A74: 1143 | B74: =IFERROR(LEFT(C74,1),"") | D74: Profits of fiscal monopolies | E74: =IFERROR(SUM(#REF!),"") | L74: =IFERROR(SUM(H74:K74),"") -> 0 | Q74: =IFERROR(SUM(M74:P74),"") -> 0 | V74: =IFERROR(SUM(R74:U74),"") -> 0
B75: =IFERROR(LEFT(C75,1),"") | E75: =IFERROR(SUM(#REF!),"") | L75: =IFERROR(SUM(H75:K75),"") -> 0 | Q75: =IFERROR(SUM(M75:P75),"") -> 0 | V75: =IFERROR(SUM(R75:U75),"") -> 0
B76: =IFERROR(LEFT(C76,1),"") | E76: =IFERROR(SUM(#REF!),"") | L76: =IFERROR(SUM(H76:K76),"") -> 0 | Q76: =IFERROR(SUM(M76:P76),"") -> 0 | V76: =IFERROR(SUM(R76:U76),"") -> 0
A77: 1144 | B77: =IFERROR(LEFT(C77,1),"") | D77: Taxes on specific services | E77: =IFERROR(SUM(#REF!),"")
B78: =IFERROR(LEFT(C78,1),"") | E78: =IFERROR(SUM(#REF!),"")
A79: 1145 | B79: =IFERROR(LEFT(C79,1),"") | D79: Taxes on use of goods and on permission to use goods or perform activities | E79: =SUM(E83,E104) -> 7404007.5 | F79: =SUM(F83,F104) -> 12171100 | G79: =SUM(G83,G104) -> 7996200 | H79: =SUM(H83,H104) -> 9043900 | I79: =SUM(I83,I104) -> 0 | J79: =SUM(J83,J104) -> 0 | K79: =SUM(K83,K104) -> 0 | L79: =IFERROR(SUM(H79:K79),"") -> 9043900 | M79: =SUM(M83,M104) -> 9625600 | N79: =SUM(N83,N104) -> 0 | O79: =SUM(O83,O104) -> 0 | P79: =SUM(P83,P104) -> 0 | Q79: =IFERROR(SUM(M79:P79),"") -> 9625600 | R79: =SUM(R83,R104) -> 10279700 | S79: =SUM(S83,S104) -> 0 | T79: =SUM(T83,T104) -> 0 | U79: =SUM(U83,U104) -> 0 | V79: =IFERROR(SUM(R79:U79),"") -> 10279700
A80: 11451 | B80: =IFERROR(LEFT(C80,1),"") | D80: Motor vehicles taxes | E80: =IFERROR(SUM(#REF!),"") | L80: =IFERROR(SUM(H80:K80),"") -> 0 | Q80: =IFERROR(SUM(M80:P80),"") -> 0 | V80: =IFERROR(SUM(R80:U80),"") -> 0
A81: 11451 | B81: =IFERROR(LEFT(C81,1),"") -> 0 | C81: 0462 | D81: Motor Licences & Registration | E81: =IFERROR(VLOOKUP($C81,'[8]Total Inflows'!$AE$4:$AH$165,2,0),"") -> 2915151.4 | F81: =IFERROR(VLOOKUP($C81,'[8]Total Inflows'!$AE$4:$AH$165,3,0),"") -> 5518300 | G81: =IFERROR(VLOOKUP($C81,'[8]Total Inflows'!$AE$4:$AH$165,4,0),"") -> 2908200 | H81: =IFERROR(VLOOKUP($C81,'[8]Total Inflows'!$AJ$4:$AM$110,2,0),"") -> 3307400 | I81: =IFERROR(VLOOKUP($C81,'[8]Total Inflows'!$AO$4:$AR$10,2,0),"") | J81: =IFERROR(VLOOKUP($C81,'[8]Total Inflows'!$AU$4:$AX$54,2,0),"") -> 0 | K81: =IFERROR(VLOOKUP($C81,'[8]Total Inflows'!$AZ$4:$BC$30,2,0),"") | L81: =IFERROR(SUM(H81:K81),"") -> 3307400 | M81: =IFERROR(VLOOKUP($C81,'[9]Total Inflows'!$AI$4:$AL$110,3,0),"") -> 3519000 | N81: =IFERROR(VLOOKUP($C81,'[8]Total Inflows'!$AO$4:$AR$10,3,0),"") | O81: =IFERROR(VLOOKUP($C81,'[8]Total Inflows'!$AU$4:$AX$54,3,0),"") -> 0 | P81: =IFERROR(VLOOKUP($C81,'[8]Total Inflows'!$AZ$4:$BC$30,3,0),"") | Q81: =IFERROR(SUM(M81:P81),"") -> 3519000 | R81: =IFERROR(VLOOKUP($C81,'[9]Total Inflows'!$AI$4:$AL$110,4,0),"") -> 3757000 | S81: =IFERROR(VLOOKUP($C81,'[8]Total Inflows'!$AO$4:$AR$10,4,0),"") | T81: =IFERROR(VLOOKUP($C81,'[8]Total Inflows'!$AU$4:$AX$54,4,0),"") -> 0 | U81: =IFERROR(VLOOKUP($C81,'[8]Total Inflows'!$AZ$4:$BC$30,4,0),"") | V81: =IFERROR(SUM(R81:U81),"") -> 3757000
A82: 11451 | B82: =IFERROR(LEFT(C82,1),"") -> 0 | C82: 0464 | D82: Annual Motor Vehicle Examination | E82: =IFERROR(VLOOKUP($C82,'[8]Total Inflows'!$AE$4:$AH$165,2,0),"") -> 2363926.1 | F82: =IFERROR(VLOOKUP($C82,'[8]Total Inflows'!$AE$4:$AH$165,3,0),"") -> 3736500 | G82: =IFERROR(VLOOKUP($C82,'[8]Total Inflows'!$AE$4:$AH$165,4,0),"") -> 2535500 | H82: =IFERROR(VLOOKUP($C82,'[8]Total Inflows'!$AJ$4:$AM$110,2,0),"") -> 2909100 | I82: =IFERROR(VLOOKUP($C82,'[8]Total Inflows'!$AO$4:$AR$10,2,0),"") | J82: =IFERROR(VLOOKUP($C82,'[8]Total Inflows'!$AU$4:$AX$54,2,0),"") -> 0 | K82: =IFERROR(VLOOKUP($C82,'[8]Total Inflows'!$AZ$4:$BC$30,2,0),"") | L82: =IFERROR(SUM(H82:K82),"") -> 2909100 | M82: =IFERROR(VLOOKUP($C82,'[9]Total Inflows'!$AI$4:$AL$110,3,0),"") -> 3093700 | N82: =IFERROR(VLOOKUP($C82,'[8]Total Inflows'!$AO$4:$AR$10,3,0),"") | O82: =IFERROR(VLOOKUP($C82,'[8]Total Inflows'!$AU$4:$AX$54,3,0),"") -> 0 | P82: =IFERROR(VLOOKUP($C82,'[8]Total Inflows'!$AZ$4:$BC$30,3,0),"") | Q82: =IFERROR(SUM(M82:P82),"") -> 3093700 | R82: =IFERROR(VLOOKUP($C82,'[9]Total Inflows'!$AI$4:$AL$110,4,0),"") -> 3300900 | S82: =IFERROR(VLOOKUP($C82,'[8]Total Inflows'!$AO$4:$AR$10,4,0),"") | T82: =IFERROR(VLOOKUP($C82,'[8]Total Inflows'!$AU$4:$AX$54,4,0),"") -> 0 | U82: =IFERROR(VLOOKUP($C82,'[8]Total Inflows'!$AZ$4:$BC$30,4,0),"") | V82: =IFERROR(SUM(R82:U82),"") -> 3300900
B83: =IFERROR(LEFT(C83,1),"") | E83: =SUM(E81:E82) -> 5279077.5 | F83: =SUM(F81:F82) -> 9254800 | G83: =SUM(G81:G82) -> 5443700 | H83: =SUM(H81:H82) -> 6216500 | I83: =SUM(I81:I82) -> 0 | J83: =SUM(J81:J82) -> 0 | K83: =SUM(K81:K82) -> 0 | L83: =IFERROR(SUM(H83:K83),"") -> 6216500 | M83: =SUM(M81:M82) -> 6612700 | N83: =SUM(N81:N82) -> 0 | O83: =SUM(O81:O82) -> 0 | P83: =SUM(P81:P82) -> 0 | Q83: =IFERROR(SUM(M83:P83),"") -> 6612700 | R83: =SUM(R81:R82) -> 7057900 | S83: =SUM(S81:S82) -> 0 | T83: =SUM(T81:T82) -> 0 | U83: =SUM(U81:U82) -> 0 | V83: =IFERROR(SUM(R83:U83),"") -> 7057900
B84: =IFERROR(LEFT(C84,1),"") | E84: =IFERROR(SUM(#REF!),"")
B85: =IFERROR(LEFT(C85,1),"") | E85: =IFERROR(SUM(#REF!),"")
A86: 11452 | B86: =IFERROR(LEFT(C86,1),"") | D86: Other taxes on use of goods and on permission to use goods or perform activities | E86: =IFERROR(SUM(#REF!),"")
A87: 11452 | B87: =IFERROR(LEFT(C87,1),"") -> 0 | C87: 0411 | D87: Communications Individual Lic | E87: =IFERROR(VLOOKUP($C87,'[8]Total Inflows'!$AE$4:$AH$165,2,0),"") -> 1063246.9 | F87: =IFERROR(VLOOKUP($C87,'[8]Total Inflows'!$AE$4:$AH$165,3,0),"") -> 1900800 | G87: =IFERROR(VLOOKUP($C87,'[8]Total Inflows'!$AE$4:$AH$165,4,0),"") -> 1410300 | H87: =IFERROR(VLOOKUP($C87,'[8]Total Inflows'!$AJ$4:$AM$110,2,0),"") -> 1606900 | I87: =IFERROR(VLOOKUP($C87,'[8]Total Inflows'!$AO$4:$AR$10,2,0),"") | J87: =IFERROR(VLOOKUP($C87,'[8]Total Inflows'!$AU$4:$AX$54,2,0),"") | K87: =IFERROR(VLOOKUP($C87,'[8]Total Inflows'!$AZ$4:$BC$30,2,0),"") | L87: =IFERROR(SUM(H87:K87),"") -> 1606900 | M87: =IFERROR(VLOOKUP($C87,'[9]Total Inflows'!$AI$4:$AL$110,3,0),"") -> 1709500 | N87: =IFERROR(VLOOKUP($C87,'[8]Total Inflows'!$AO$4:$AR$10,3,0),"") | O87: =IFERROR(VLOOKUP($C87,'[8]Total Inflows'!$AU$4:$AX$54,3,0),"") | P87: =IFERROR(VLOOKUP($C87,'[8]Total Inflows'!$AZ$4:$BC$30,3,0),"") | Q87: =IFERROR(SUM(M87:P87),"") -> 1709500 | R87: =IFERROR(VLOOKUP($C87,'[9]Total Inflows'!$AI$4:$AL$110,4,0),"") -> 1824900 | S87: =IFERROR(VLOOKUP($C87,'[8]Total Inflows'!$AO$4:$AR$10,4,0),"") | T87: =IFERROR(VLOOKUP($C87,'[8]Total Inflows'!$AU$4:$AX$54,4,0),"") | U87: =IFERROR(VLOOKUP($C87,'[8]Total Inflows'!$AZ$4:$BC$30,4,0),"") | V87: =IFERROR(SUM(R87:U87),"") -> 1824900
A88: 11452 | B88: =IFERROR(LEFT(C88,1),"") -> 0 | C88: 0418 | D88: Arms Trading & Gun Licences | E88: =IFERROR(VLOOKUP($C88,'[8]Total Inflows'!$AE$4:$AH$165,2,0),"") -> 9233 | F88: =IFERROR(VLOOKUP($C88,'[8]Total Inflows'!$AE$4:$AH$165,3,0),"") -> 9700 | G88: =IFERROR(VLOOKUP($C88,'[8]Total Inflows'!$AE$4:$AH$165,4,0),"") -> 12200 | H88: =IFERROR(VLOOKUP($C88,'[8]Total Inflows'!$AJ$4:$AM$110,2,0),"") -> 13000 | I88: =IFERROR(VLOOKUP($C88,'[8]Total Inflows'!$AO$4:$AR$10,2,0),"") | J88: =IFERROR(VLOOKUP($C88,'[8]Total Inflows'!$AU$4:$AX$54,2,0),"") | K88: =IFERROR(VLOOKUP($C88,'[8]Total Inflows'!$AZ$4:$BC$30,2,0),"") | L88: =IFERROR(SUM(H88:K88),"") -> 13000 | M88: =IFERROR(VLOOKUP($C88,'[9]Total Inflows'!$AI$4:$AL$110,3,0),"") -> 13900 | N88: =IFERROR(VLOOKUP($C88,'[8]Total Inflows'!$AO$4:$AR$10,3,0),"") | O88: =IFERROR(VLOOKUP($C88,'[8]Total Inflows'!$AU$4:$AX$54,3,0),"") | P88: =IFERROR(VLOOKUP($C88,'[8]Total Inflows'!$AZ$4:$BC$30,3,0),"") | Q88: =IFERROR(SUM(M88:P88),"") -> 13900 | R88: =IFERROR(VLOOKUP($C88,'[9]Total Inflows'!$AI$4:$AL$110,4,0),"") -> 14900 | S88: =IFERROR(VLOOKUP($C88,'[8]Total Inflows'!$AO$4:$AR$10,4,0),"") | T88: =IFERROR(VLOOKUP($C88,'[8]Total Inflows'!$AU$4:$AX$54,4,0),"") | U88: =IFERROR(VLOOKUP($C88,'[8]Total Inflows'!$AZ$4:$BC$30,4,0),"") | V88: =IFERROR(SUM(R88:U88),"") -> 14900
A89: 11452 | B89: =IFERROR(LEFT(C89,1),"") -> 0 | C89: 0420 | D89: Entertainment Licences Fees | E89: =IFERROR(VLOOKUP($C89,'[8]Total Inflows'!$AE$4:$AH$165,2,0),"") -> 61840.12 | F89: =IFERROR(VLOOKUP($C89,'[8]Total Inflows'!$AE$4:$AH$165,3,0),"") -> 28300 | G89: =IFERROR(VLOOKUP($C89,'[8]Total Inflows'!$AE$4:$AH$165,4,0),"") -> 68200 | H89: =IFERROR(VLOOKUP($C89,'[8]Total Inflows'!$AJ$4:$AM$110,2,0),"") -> 72800 | I89: =IFERROR(VLOOKUP($C89,'[8]Total Inflows'!$AO$4:$AR$10,2,0),"") | J89: =IFERROR(VLOOKUP($C89,'[8]Total Inflows'!$AU$4:$AX$54,2,0),"") | K89: =IFERROR(VLOOKUP($C89,'[8]Total Inflows'!$AZ$4:$BC$30,2,0),"") | L89: =IFERROR(SUM(H89:K89),"") -> 72800 | M89: =IFERROR(VLOOKUP($C89,'[9]Total Inflows'!$AI$4:$AL$110,3,0),"") -> 77800 | N89: =IFERROR(VLOOKUP($C89,'[8]Total Inflows'!$AO$4:$AR$10,3,0),"") | O89: =IFERROR(VLOOKUP($C89,'[8]Total Inflows'!$AU$4:$AX$54,3,0),"") | P89: =IFERROR(VLOOKUP($C89,'[8]Total Inflows'!$AZ$4:$BC$30,3,0),"") | Q89: =IFERROR(SUM(M89:P89),"") -> 77800 | R89: =IFERROR(VLOOKUP($C89,'[9]Total Inflows'!$AI$4:$AL$110,4,0),"") -> 83400 | S89: =IFERROR(VLOOKUP($C89,'[8]Total Inflows'!$AO$4:$AR$10,4,0),"") | T89: =IFERROR(VLOOKUP($C89,'[8]Total Inflows'!$AU$4:$AX$54,4,0),"") | U89: =IFERROR(VLOOKUP($C89,'[8]Total Inflows'!$AZ$4:$BC$30,4,0),"") | V89: =IFERROR(SUM(R89:U89),"") -> 83400
A90: 11452 | B90: =IFERROR(LEFT(C90,1),"") -> 0 | C90: 0435 | D90: Business License | E90: =IFERROR(VLOOKUP($C90,'[8]Total Inflows'!$AE$4:$AH$165,2,0),"") -> 289734.03 | F90: =IFERROR(VLOOKUP($C90,'[8]Total Inflows'!$AE$4:$AH$165,3,0),"") -> 319500 | G90: =IFERROR(VLOOKUP($C90,'[8]Total Inflows'!$AE$4:$AH$165,4,0),"") -> 320200 | H90: =IFERROR(VLOOKUP($C90,'[8]Total Inflows'!$AJ$4:$AM$110,2,0),"") -> 342100 | I90: =IFERROR(VLOOKUP($C90,'[8]Total Inflows'!$AO$4:$AR$10,2,0),"") | J90: =IFERROR(VLOOKUP($C90,'[8]Total Inflows'!$AU$4:$AX$54,2,0),"") | K90: =IFERROR(VLOOKUP($C90,'[8]Total Inflows'!$AZ$4:$BC$30,2,0),"") | L90: =IFERROR(SUM(H90:K90),"") -> 342100 | M90: =IFERROR(VLOOKUP($C90,'[9]Total Inflows'!$AI$4:$AL$110,3,0),"") -> 365400 | N90: =IFERROR(VLOOKUP($C90,'[8]Total Inflows'!$AO$4:$AR$10,3,0),"") | O90: =IFERROR(VLOOKUP($C90,'[8]Total Inflows'!$AU$4:$AX$54,3,0),"") | P90: =IFERROR(VLOOKUP($C90,'[8]Total Inflows'!$AZ$4:$BC$30,3,0),"") | Q90: =IFERROR(SUM(M90:P90),"") -> 365400 | R90: =IFERROR(VLOOKUP($C90,'[9]Total Inflows'!$AI$4:$AL$110,4,0),"") -> 391600 | S90: =IFERROR(VLOOKUP($C90,'[8]Total Inflows'!$AO$4:$AR$10,4,0),"") | T90: =IFERROR(VLOOKUP($C90,'[8]Total Inflows'!$AU$4:$AX$54,4,0),"") | U90: =IFERROR(VLOOKUP($C90,'[8]Total Inflows'!$AZ$4:$BC$30,4,0),"") | V90: =IFERROR(SUM(R90:U90),"") -> 391600
A91: 11452 | B91: =IFERROR(LEFT(C91,1),"") -> 0 | C91: 0436 | D91: Spirituous Liquor Licences | E91: =IFERROR(VLOOKUP($C91,'[8]Total Inflows'!$AE$4:$AH$165,2,0),"") -> 273521.91 | F91: =IFERROR(VLOOKUP($C91,'[8]Total Inflows'!$AE$4:$AH$165,3,0),"") -> 294900 | G91: =IFERROR(VLOOKUP($C91,'[8]Total Inflows'!$AE$4:$AH$165,4,0),"") -> 256200 | H91: =IFERROR(VLOOKUP($C91,'[8]Total Inflows'!$AJ$4:$AM$110,2,0),"") -> 273800 | I91: =IFERROR(VLOOKUP($C91,'[8]Total Inflows'!$AO$4:$AR$10,2,0),"") | J91: =IFERROR(VLOOKUP($C91,'[8]Total Inflows'!$AU$4:$AX$54,2,0),"") | K91: =IFERROR(VLOOKUP($C91,'[8]Total Inflows'!$AZ$4:$BC$30,2,0),"") | L91: =IFERROR(SUM(H91:K91),"") -> 273800 | M91: =IFERROR(VLOOKUP($C91,'[9]Total Inflows'!$AI$4:$AL$110,3,0),"") -> 292400 | N91: =IFERROR(VLOOKUP($C91,'[8]Total Inflows'!$AO$4:$AR$10,3,0),"") | O91: =IFERROR(VLOOKUP($C91,'[8]Total Inflows'!$AU$4:$AX$54,3,0),"") | P91: =IFERROR(VLOOKUP($C91,'[8]Total Inflows'!$AZ$4:$BC$30,3,0),"") | Q91: =IFERROR(SUM(M91:P91),"") -> 292400 | R91: =IFERROR(VLOOKUP($C91,'[9]Total Inflows'!$AI$4:$AL$110,4,0),"") -> 313400 | S91: =IFERROR(VLOOKUP($C91,'[8]Total Inflows'!$AO$4:$AR$10,4,0),"") | T91: =IFERROR(VLOOKUP($C91,'[8]Total Inflows'!$AU$4:$AX$54,4,0),"") | U91: =IFERROR(VLOOKUP($C91,'[8]Total Inflows'!$AZ$4:$BC$30,4,0),"") | V91: =IFERROR(SUM(R91:U91),"") -> 313400
A92: 11452 | B92: =IFERROR(LEFT(C92,1),"") -> 0 | C92: 0456 | D92: Coastal Licences | E92: =IFERROR(VLOOKUP($C92,'[8]Total Inflows'!$AE$4:$AH$165,2,0),"") -> 13106.49 | F92: =IFERROR(VLOOKUP($C92,'[8]Total Inflows'!$AE$4:$AH$165,3,0),"") -> 12300 | G92: =IFERROR(VLOOKUP($C92,'[8]Total Inflows'!$AE$4:$AH$165,4,0),"") -> 2100 | H92: =IFERROR(VLOOKUP($C92,'[8]Total Inflows'!$AJ$4:$AM$110,2,0),"") -> 2300 | I92: =IFERROR(VLOOKUP($C92,'[8]Total Inflows'!$AO$4:$AR$10,2,0),"") | J92: =IFERROR(VLOOKUP($C92,'[8]Total Inflows'!$AU$4:$AX$54,2,0),"") | K92: =IFERROR(VLOOKUP($C92,'[8]Total Inflows'!$AZ$4:$BC$30,2,0),"") | L92: =IFERROR(SUM(H92:K92),"") -> 2300 | M92: =IFERROR(VLOOKUP($C92,'[9]Total Inflows'!$AI$4:$AL$110,3,0),"") -> 2400 | N92: =IFERROR(VLOOKUP($C92,'[8]Total Inflows'!$AO$4:$AR$10,3,0),"") | O92: =IFERROR(VLOOKUP($C92,'[8]Total Inflows'!$AU$4:$AX$54,3,0),"") | P92: =IFERROR(VLOOKUP($C92,'[8]Total Inflows'!$AZ$4:$BC$30,3,0),"") | Q92: =IFERROR(SUM(M92:P92),"") -> 2400 | R92: =IFERROR(VLOOKUP($C92,'[9]Total Inflows'!$AI$4:$AL$110,4,0),"") -> 2600 | S92: =IFERROR(VLOOKUP($C92,'[8]Total Inflows'!$AO$4:$AR$10,4,0),"") | T92: =IFERROR(VLOOKUP($C92,'[8]Total Inflows'!$AU$4:$AX$54,4,0),"") | U92: =IFERROR(VLOOKUP($C92,'[8]Total Inflows'!$AZ$4:$BC$30,4,0),"") | V92: =IFERROR(SUM(R92:U92),"") -> 2600
A93: 11452 | B93: =IFERROR(LEFT(C93,1),"") -> 0 | C93: 0457 | D93: Pilotage | E93: =IFERROR(VLOOKUP($C93,'[8]Total Inflows'!$AE$4:$AH$165,2,0),"") -> 50941.08 | F93: =IFERROR(VLOOKUP($C93,'[8]Total Inflows'!$AE$4:$AH$165,3,0),"") -> 41500 | G93: =IFERROR(VLOOKUP($C93,'[8]Total Inflows'!$AE$4:$AH$165,4,0),"") -> 56800 | H93: =IFERROR(VLOOKUP($C93,'[8]Total Inflows'!$AJ$4:$AM$110,2,0),"") -> 60700 | I93: =IFERROR(VLOOKUP($C93,'[8]Total Inflows'!$AO$4:$AR$10,2,0),"") | J93: =IFERROR(VLOOKUP($C93,'[8]Total Inflows'!$AU$4:$AX$54,2,0),"") | K93: =IFERROR(VLOOKUP($C93,'[8]Total Inflows'!$AZ$4:$BC$30,2,0),"") | L93: =IFERROR(SUM(H93:K93),"") -> 60700 | M93: =IFERROR(VLOOKUP($C93,'[9]Total Inflows'!$AI$4:$AL$110,3,0),"") -> 64800 | N93: =IFERROR(VLOOKUP($C93,'[8]Total Inflows'!$AO$4:$AR$10,3,0),"") | O93: =IFERROR(VLOOKUP($C93,'[8]Total Inflows'!$AU$4:$AX$54,3,0),"") | P93: =IFERROR(VLOOKUP($C93,'[8]Total Inflows'!$AZ$4:$BC$30,3,0),"") | Q93: =IFERROR(SUM(M93:P93),"") -> 64800 | R93: =IFERROR(VLOOKUP($C93,'[9]Total Inflows'!$AI$4:$AL$110,4,0),"") -> 69500 | S93: =IFERROR(VLOOKUP($C93,'[8]Total Inflows'!$AO$4:$AR$10,4,0),"") | T93: =IFERROR(VLOOKUP($C93,'[8]Total Inflows'!$AU$4:$AX$54,4,0),"") | U93: =IFERROR(VLOOKUP($C93,'[8]Total Inflows'!$AZ$4:$BC$30,4,0),"") | V93: =IFERROR(SUM(R93:U93),"") -> 69500
A94: 11452 | B94: =IFERROR(LEFT(C94,1),"") -> 0 | C94: 0458 | D94: Light Dues | E94: =IFERROR(VLOOKUP($C94,'[8]Total Inflows'!$AE$4:$AH$165,2,0),"") -> 35169.99 | F94: =IFERROR(VLOOKUP($C94,'[8]Total Inflows'!$AE$4:$AH$165,3,0),"") -> 20300 | G94: =IFERROR(VLOOKUP($C94,'[8]Total Inflows'!$AE$4:$AH$165,4,0),"") -> 28400 | H94: =IFERROR(VLOOKUP($C94,'[8]Total Inflows'!$AJ$4:$AM$110,2,0),"") -> 30400 | I94: =IFERROR(VLOOKUP($C94,'[8]Total Inflows'!$AO$4:$AR$10,2,0),"") | J94: =IFERROR(VLOOKUP($C94,'[8]Total Inflows'!$AU$4:$AX$54,2,0),"") | K94: =IFERROR(VLOOKUP($C94,'[8]Total Inflows'!$AZ$4:$BC$30,2,0),"") | L94: =IFERROR(SUM(H94:K94),"") -> 30400 | M94: =IFERROR(VLOOKUP($C94,'[9]Total Inflows'!$AI$4:$AL$110,3,0),"") -> 32400 | N94: =IFERROR(VLOOKUP($C94,'[8]Total Inflows'!$AO$4:$AR$10,3,0),"") | O94: =IFERROR(VLOOKUP($C94,'[8]Total Inflows'!$AU$4:$AX$54,3,0),"") | P94: =IFERROR(VLOOKUP($C94,'[8]Total Inflows'!$AZ$4:$BC$30,3,0),"") | Q94: =IFERROR(SUM(M94:P94),"") -> 32400 | R94: =IFERROR(VLOOKUP($C94,'[9]Total Inflows'!$AI$4:$AL$110,4,0),"") -> 34700 | S94: =IFERROR(VLOOKUP($C94,'[8]Total Inflows'!$AO$4:$AR$10,4,0),"") | T94: =IFERROR(VLOOKUP($C94,'[8]Total Inflows'!$AU$4:$AX$54,4,0),"") | U94: =IFERROR(VLOOKUP($C94,'[8]Total Inflows'!$AZ$4:$BC$30,4,0),"") | V94: =IFERROR(SUM(R94:U94),"") -> 34700
A95: 11452 | B95: =IFERROR(LEFT(C95,1),"") -> 0 | C95: 0459 | D95: Harbour Dues | E95: =IFERROR(VLOOKUP($C95,'[8]Total Inflows'!$AE$4:$AH$165,2,0),"") -> 51082.37 | F95: =IFERROR(VLOOKUP($C95,'[8]Total Inflows'!$AE$4:$AH$165,3,0),"") -> 42200 | G95: =IFERROR(VLOOKUP($C95,'[8]Total Inflows'!$AE$4:$AH$165,4,0),"") -> 59400 | H95: =IFERROR(VLOOKUP($C95,'[8]Total Inflows'!$AJ$4:$AM$110,2,0),"") -> 63400 | I95: =IFERROR(VLOOKUP($C95,'[8]Total Inflows'!$AO$4:$AR$10,2,0),"") | J95: =IFERROR(VLOOKUP($C95,'[8]Total Inflows'!$AU$4:$AX$54,2,0),"") | K95: =IFERROR(VLOOKUP($C95,'[8]Total Inflows'!$AZ$4:$BC$30,2,0),"") | L95: =IFERROR(SUM(H95:K95),"") -> 63400 | M95: =IFERROR(VLOOKUP($C95,'[9]Total Inflows'!$AI$4:$AL$110,3,0),"") -> 67700 | N95: =IFERROR(VLOOKUP($C95,'[8]Total Inflows'!$AO$4:$AR$10,3,0),"") | O95: =IFERROR(VLOOKUP($C95,'[8]Total Inflows'!$AU$4:$AX$54,3,0),"") | P95: =IFERROR(VLOOKUP($C95,'[8]Total Inflows'!$AZ$4:$BC$30,3,0),"") | Q95: =IFERROR(SUM(M95:P95),"") -> 67700 | R95: =IFERROR(VLOOKUP($C95,'[9]Total Inflows'!$AI$4:$AL$110,4,0),"") -> 72600 | S95: =IFERROR(VLOOKUP($C95,'[8]Total Inflows'!$AO$4:$AR$10,4,0),"") | T95: =IFERROR(VLOOKUP($C95,'[8]Total Inflows'!$AU$4:$AX$54,4,0),"") | U95: =IFERROR(VLOOKUP($C95,'[8]Total Inflows'!$AZ$4:$BC$30,4,0),"") | V95: =IFERROR(SUM(R95:U95),"") -> 72600
A96: 11452 | B96: =IFERROR(LEFT(C96,1),"") -> 0 | C96: 0460 | D96: Tonnage | E96: =IFERROR(VLOOKUP($C96,'[8]Total Inflows'!$AE$4:$AH$165,2,0),"") -> 86769.01 | F96: =IFERROR(VLOOKUP($C96,'[8]Total Inflows'!$AE$4:$AH$165,3,0),"") -> 66400 | G96: =IFERROR(VLOOKUP($C96,'[8]Total Inflows'!$AE$4:$AH$165,4,0),"") -> 135600 | H96: =IFERROR(VLOOKUP($C96,'[8]Total Inflows'!$AJ$4:$AM$110,2,0),"") -> 144900 | I96: =IFERROR(VLOOKUP($C96,'[8]Total Inflows'!$AO$4:$AR$10,2,0),"") | J96: =IFERROR(VLOOKUP($C96,'[8]Total Inflows'!$AU$4:$AX$54,2,0),"") | K96: =IFERROR(VLOOKUP($C96,'[8]Total Inflows'!$AZ$4:$BC$30,2,0),"") | L96: =IFERROR(SUM(H96:K96),"") -> 144900 | M96: =IFERROR(VLOOKUP($C96,'[9]Total Inflows'!$AI$4:$AL$110,3,0),"") -> 154800 | N96: =IFERROR(VLOOKUP($C96,'[8]Total Inflows'!$AO$4:$AR$10,3,0),"") | O96: =IFERROR(VLOOKUP($C96,'[8]Total Inflows'!$AU$4:$AX$54,3,0),"") | P96: =IFERROR(VLOOKUP($C96,'[8]Total Inflows'!$AZ$4:$BC$30,3,0),"") | Q96: =IFERROR(SUM(M96:P96),"") -> 154800 | R96: =IFERROR(VLOOKUP($C96,'[9]Total Inflows'!$AI$4:$AL$110,4,0),"") -> 165800 | S96: =IFERROR(VLOOKUP($C96,'[8]Total Inflows'!$AO$4:$AR$10,4,0),"") | T96: =IFERROR(VLOOKUP($C96,'[8]Total Inflows'!$AU$4:$AX$54,4,0),"") | U96: =IFERROR(VLOOKUP($C96,'[8]Total Inflows'!$AZ$4:$BC$30,4,0),"") | V96: =IFERROR(SUM(R96:U96),"") -> 165800
A97: 11452 | B97: =IFERROR(LEFT(C97,1),"") -> 0 | C97: 0465 | D97: Bicycle Licences | E97: =IFERROR(VLOOKUP($C97,'[8]Total Inflows'!$AE$4:$AH$165,2,0),"") | F97: =IFERROR(VLOOKUP($C97,'[8]Total Inflows'!$AE$4:$AH$165,3,0),"") | G97: =IFERROR(VLOOKUP($C97,'[8]Total Inflows'!$AE$4:$AH$165,4,0),"") | H97: =IFERROR(VLOOKUP($C97,'[8]Total Inflows'!$AJ$4:$AM$110,2,0),"") | I97: =IFERROR(VLOOKUP($C97,'[8]Total Inflows'!$AO$4:$AR$10,2,0),"") | J97: =IFERROR(VLOOKUP($C97,'[8]Total Inflows'!$AU$4:$AX$54,2,0),"") | K97: =IFERROR(VLOOKUP($C97,'[8]Total Inflows'!$AZ$4:$BC$30,2,0),"") | L97: =IFERROR(SUM(H97:K97),"") -> 0 | M97: =IFERROR(VLOOKUP($C97,'[9]Total Inflows'!$AI$4:$AL$110,3,0),"") | N97: =IFERROR(VLOOKUP($C97,'[8]Total Inflows'!$AO$4:$AR$10,3,0),"") | O97: =IFERROR(VLOOKUP($C97,'[8]Total Inflows'!$AU$4:$AX$54,3,0),"") | P97: =IFERROR(VLOOKUP($C97,'[8]Total Inflows'!$AZ$4:$BC$30,3,0),"") | Q97: =IFERROR(SUM(M97:P97),"") -> 0 | R97: =IFERROR(VLOOKUP($C97,'[9]Total Inflows'!$AI$4:$AL$110,4,0),"") | S97: =IFERROR(VLOOKUP($C97,'[8]Total Inflows'!$AO$4:$AR$10,4,0),"") | T97: =IFERROR(VLOOKUP($C97,'[8]Total Inflows'!$AU$4:$AX$54,4,0),"") | U97: =IFERROR(VLOOKUP($C97,'[8]Total Inflows'!$AZ$4:$BC$30,4,0),"") | V97: =IFERROR(SUM(R97:U97),"") -> 0
A98: 11452 | B98: =IFERROR(LEFT(C98,1),"") -> 0 | C98: 0473 | D98: Laiseni fefakatau'aki (Trading Licences) | E98: =IFERROR(VLOOKUP($C98,'[8]Total Inflows'!$AE$4:$AH$165,2,0),"") | F98: =IFERROR(VLOOKUP($C98,'[8]Total Inflows'!$AE$4:$AH$165,3,0),"") | G98: =IFERROR(VLOOKUP($C98,'[8]Total Inflows'!$AE$4:$AH$165,4,0),"") | H98: =IFERROR(VLOOKUP($C98,'[8]Total Inflows'!$AJ$4:$AM$110,2,0),"") | I98: =IFERROR(VLOOKUP($C98,'[8]Total Inflows'!$AO$4:$AR$10,2,0),"") | J98: =IFERROR(VLOOKUP($C98,'[8]Total Inflows'!$AU$4:$AX$54,2,0),"") | K98: =IFERROR(VLOOKUP($C98,'[8]Total Inflows'!$AZ$4:$BC$30,2,0),"") | L98: =IFERROR(SUM(H98:K98),"") -> 0 | M98: =IFERROR(VLOOKUP($C98,'[9]Total Inflows'!$AI$4:$AL$110,3,0),"") | N98: =IFERROR(VLOOKUP($C98,'[8]Total Inflows'!$AO$4:$AR$10,3,0),"") | O98: =IFERROR(VLOOKUP($C98,'[8]Total Inflows'!$AU$4:$AX$54,3,0),"") | P98: =IFERROR(VLOOKUP($C98,'[8]Total Inflows'!$AZ$4:$BC$30,3,0),"") | Q98: =IFERROR(SUM(M98:P98),"") -> 0 | R98: =IFERROR(VLOOKUP($C98,'[9]Total Inflows'!$AI$4:$AL$110,4,0),"") | S98: =IFERROR(VLOOKUP($C98,'[8]Total Inflows'!$AO$4:$AR$10,4,0),"") | T98: =IFERROR(VLOOKUP($C98,'[8]Total Inflows'!$AU$4:$AX$54,4,0),"") | U98: =IFERROR(VLOOKUP($C98,'[8]Total Inflows'!$AZ$4:$BC$30,4,0),"") | V98: =IFERROR(SUM(R98:U98),"") -> 0
... A103: 11452 | B103: =IFERROR(LEFT(C103,1),"") -> 0 | C103: 0494 | D103: Certificate of Competency | E103: =IFERROR(VLOOKUP($C103,'[8]Total Inflows'!$AE$4:$AH$165,2,0),"") | F103: =IFERROR(VLOOKUP($C103,'[8]Total Inflows'!$AE$4:$AH$165,3,0),"") | G103: =IFERROR(VLOOKUP($C103,'[8]Total Inflows'!$AE$4:$AH$165,4,0),"") | H103: =IFERROR(VLOOKUP($C103,'[8]Total Inflows'!$AJ$4:$AM$110,2,0),"") | I103: =IFERROR(VLOOKUP($C103,'[8]Total Inflows'!$AO$4:$AR$10,2,0),"") | J103: =IFERROR(VLOOKUP($C103,'[8]Total Inflows'!$AU$4:$AX$54,2,0),"") | K103: =IFERROR(VLOOKUP($C103,'[8]Total Inflows'!$AZ$4:$BC$30,2,0),"") | L103: =IFERROR(SUM(H103:K103),"") -> 0 | M103: =IFERROR(VLOOKUP($C103,'[9]Total Inflows'!$AI$4:$AL$110,3,0),"") | N103: =IFERROR(VLOOKUP($C103,'[8]Total Inflows'!$AO$4:$AR$10,3,0),"") | O103: =IFERROR(VLOOKUP($C103,'[8]Total Inflows'!$AU$4:$AX$54,3,0),"") | P103: =IFERROR(VLOOKUP($C103,'[8]Total Inflows'!$AZ$4:$BC$30,3,0),"") | Q103: =IFERROR(SUM(M103:P103),"") -> 0 | R103: =IFERROR(VLOOKUP($C103,'[9]Total Inflows'!$AI$4:$AL$110,4,0),"") | S103: =IFERROR(VLOOKUP($C103,'[8]Total Inflows'!$AO$4:$AR$10,4,0),"") | T103: =IFERROR(VLOOKUP($C103,'[8]Total Inflows'!$AU$4:$AX$54,4,0),"") | U103: =IFERROR(VLOOKUP($C103,'[8]Total Inflows'!$AZ$4:$BC$30,4,0),"") | V103: =IFERROR(SUM(R103:U103),"") -> 0
B104: =IFERROR(LEFT(C104,1),"") | E104: =SUM(E87:E103) -> 2124930 | F104: =SUM(F87:F103) -> 2916300 | G104: =SUM(G87:G103) -> 2552500 | H104: =SUM(H87:H103) -> 2827400 | I104: =SUM(I87:I103) -> 0 | J104: =SUM(J87:J103) -> 0 | K104: =SUM(K87:K103) -> 0 | L104: =IFERROR(SUM(H104:K104),"") -> 2827400 | M104: =SUM(M87:M103) -> 3012900 | N104: =SUM(N87:N103) -> 0 | O104: =SUM(O87:O103) -> 0 | P104: =SUM(P87:P103) -> 0 | Q104: =IFERROR(SUM(M104:P104),"") -> 3012900 | R104: =SUM(R87:R103) -> 3221800 | S104: =SUM(S87:S103) -> 0 | T104: =SUM(T87:T103) -> 0 | U104: =SUM(U87:U103) -> 0 | V104: =IFERROR(SUM(R104:U104),"") -> 3221800
...

Sheet Ls_AgXLB_WorkbookFile

Sheet Sheet2
B4: 1712 | C4: Public Debt Principal Repayment Domestic | D4: 13566000 | E4: 19872000 | F4: 15100000
C6: Budget | D6: 15.5 | E6: 21.8 | F6: 17

Sheet Sum_Bud_data
B3: Actual 2018/19 | C3: Budget Estimate 2019/20 | D3: Est Outturn 2019/20 | E3: Budget Estimate 2019/20 | F3: Budget Estimate 2020/21 | G3: Budget Estimate 2021/22 | M3: Total Receipts (TR)
M4: Total Payments (TP)
A5: Revenue | B5: =B6+B11 -> #REF! | C5: =C6+C11 -> #REF! | D5: =D6+D11 -> #REF! | E5: =E6+E11 -> #REF! | F5: =F6+F11 -> #REF! | G5: =G6+G11 -> #REF! | M5: Receipts less Payments
A6: Taxes | B6: =B7+#REF! -> #REF! | C6: =C7+#REF! -> #REF! | D6: =D7+#REF! -> #REF! | E6: =E7+#REF! -> #REF! | F6: =F7+#REF! -> #REF! | G6: =G7+#REF! -> #REF! | M6: TR+TP
A7: Current revenue | B7: =B8+#REF! -> #REF! | C7: =C8+#REF! -> #REF! | D7: =D8+#REF! -> #REF! | E7: =E8+#REF! -> #REF! | F7: =F8+#REF! -> #REF! | G7: =G8+#REF! -> #REF!
A8: Tax revenue | B8: ='[18]Revenue T3'!G6 -> 116.24163 | C8: ='[18]Revenue T3'!H6 -> 112.65597 | D8: ='[18]Revenue T3'!I6 -> 115.0186 | E8: ='[18]Revenue T3'!M6 -> 115.8743 | F8: ='[18]Revenue T3'!N6 -> 118.35372 | G8: ='[18]Revenue T3'!O6 -> 118.3537
A9: Trade taxes | B9: ='[18]Revenue T3'!G12 -> 14.935478 | C9: ='[18]Revenue T3'!H12 -> 14.579595 | D9: ='[18]Revenue T3'!I12 -> 13.179244 | E9: ='[18]Revenue T3'!M12 -> 12.72232 | F9: ='[18]Revenue T3'!N12 -> 12.918094 | G9: ='[18]Revenue T3'!O12 -> 12.918091 | J9: GFSM 2001 Code | L9: Item Code | M9: GFSM2014 | N9: Actual FY2025 | O9: ='GFS 2025_26 Budget'!F1 -> Budget Estimate 2025/26 | P9: Budget Outturn FY2026 | Q9: Budget Statement 2026/27 (Recurrent) | R9: Budget Statement 2026/27 (Budget Support) | S9: Budget Statement 2026/27 (Development Cash) | T9: Budget Statement 2026/27 (In-kind) | U9: Budget Estimate 2026/27 | V9: Budget Statement 2027/28 (Recurrent) | W9: Budget Statement 2027/28 (Budget Support) | X9: Budget Statement 2027/28 (Development Cash) | Y9: Budget Statement 2027/28 (In-kind) | Z9: Budget Estimate 2027/28 | AA9: Budget Statement 2028/29 (Recurrent) | AB9: Budget Statement 2028/29 (Budget Support) | AC9: Budget Statement 2028/29 (Development Cash) | AD9: Budget Statement 2028/29 (In-kind) | AE9: Budget Estimate 2028/29
J10: 1 | M10: REVENUE | N10: =SUM(N11,N20,N21,N31) -> 810.96293 | O10: =SUM(O11,O20,O21,O31) -> 929.7561 | P10: =SUM(P11,P20,P21,P31) -> 791.3569 | Q10: =SUM(Q11,Q20,Q21,Q31) -> 412.1464 | R10: =SUM(R11,R20,R21,R31) -> 118.0109 | S10: =SUM(S11,S20,S21,S31) -> 133.0838 | T10: =SUM(T11,T20,T21,T31) -> 214.1572 | U10: =IFERROR(SUM(Q10:T10),"") -> 877.3983 | V10: =SUM(V11,V20,V21,V31) -> 459.5129 | W10: =SUM(W11,W20,W21,W31) -> 86.953 | X10: =SUM(X11,X20,X21,X31) -> 105.8358 | Y10: =SUM(Y11,Y20,Y21,Y31) -> 233.8395 | Z10: =IFERROR(SUM(V10:Y10),"") -> 886.1412 | AA10: =SUM(AA11,AA20,AA21,AA31) -> 483.2927 | AB10: =SUM(AB11,AB20,AB21,AB31) -> 47.5291 | AC10: =SUM(AC11,AC20,AC21,AC31) -> 79.5046 | AD10: =SUM(AD11,AD20,AD21,AD31) -> 143.8488 | AE10: =IFERROR(SUM(AA10:AD10),"") -> 754.1752
A11: Grants (in cash) | B11: ='[18]Revenue T3'!G24 -> 39.164689 | C11: ='[18]Revenue T3'!H24 -> 60.864747 | D11: ='[18]Revenue T3'!I24 -> 47.700687 | E11: ='[18]Revenue T3'!M24 -> 53.180303 | F11: ='[18]Revenue T3'!N24 -> 42.798625 | G11: ='[18]Revenue T3'!O24 -> 42.798615 | J11: 11 | M11: Taxes | N11: =SUM(N12,N13,N14,N18,N19) -> 328.47224 | O11: =SUM(O12,O13,O14,O18,O19) -> 347.0774 | P11: =SUM(P12,P13,P14,P18,P19) -> 342.8047 | Q11: =SUM(Q12,Q13,Q14,Q18,Q19) -> 351.9146 | R11: =SUM(R12,R13,R14,R18,R19) -> 0 | S11: =SUM(S12,S13,S14,S18,S19) -> 0 | T11: =SUM(T12,T13,T14,T18,T19) -> 0 | U11: =IFERROR(SUM(Q11:T11),"") -> 351.9146 | V11: =SUM(V12,V13,V14,V18,V19) -> 394.7373 | W11: =SUM(W12,W13,W14,W18,W19) -> 0 | X11: =SUM(X12,X13,X14,X18,X19) -> 0 | Y11: =SUM(Y12,Y13,Y14,Y18,Y19) -> 0 | Z11: =IFERROR(SUM(V11:Y11),"") -> 394.7373 | AA11: =SUM(AA12,AA13,AA14,AA18,AA19) -> 414.7709 | AB11: =SUM(AB12,AB13,AB14,AB18,AB19) -> 0 | AC11: =SUM(AC12,AC13,AC14,AC18,AC19) -> 0 | AD11: =SUM(AD12,AD13,AD14,AD18,AD19) -> 0 | AE11: =IFERROR(SUM(AA11:AD11),"") -> 414.7709
J12: 111 | M12: Taxes on income, profits, n capital gains | N12: ='GFS 2025_26 Budget'!E8/10^6 -> 76.885797 | O12: ='GFS 2025_26 Budget'!F8/10^6 -> 78.6995 | P12: ='GFS 2025_26 Budget'!G8/10^6 -> 78.6632 | Q12: ='GFS 2025_26 Budget'!H8/10^6 -> 81.7512 | R12: ='GFS 2025_26 Budget'!I8/10^6 -> 0 | S12: ='GFS 2025_26 Budget'!J8/10^6 -> 0 | T12: ='GFS 2025_26 Budget'!K8/10^6 -> 0 | U12: =IFERROR(SUM(Q12:T12),"") -> 81.7512 | V12: ='GFS 2025_26 Budget'!M8/10^6 -> 89.777 | W12: ='GFS 2025_26 Budget'!N8/10^6 -> 0 | X12: ='GFS 2025_26 Budget'!O8/10^6 -> 0 | Y12: ='GFS 2025_26 Budget'!P8/10^6 -> 0 | Z12: =IFERROR(SUM(V12:Y12),"") -> 89.777 | AA12: ='GFS 2025_26 Budget'!R8/10^6 -> 94.2098 | AB12: ='GFS 2025_26 Budget'!S8/10^6 -> 0 | AC12: ='GFS 2025_26 Budget'!T8/10^6 -> 0 | AD12: ='GFS 2025_26 Budget'!U8/10^6 -> 0 | AE12: =IFERROR(SUM(AA12:AD12),"") -> 94.2098
A13: Total expenditure | B13: =B14+#REF! -> #REF! | C13: =C14+#REF! -> #REF! | D13: =D14+#REF! -> #REF! | E13: =E14+#REF! -> #REF! | F13: =F14+#REF! -> #REF! | G13: =G14+#REF! -> #REF! | J13: 113 | M13: Taxes on property | N13: ='GFS 2025_26 Budget'!E30/10^6 -> 0.34542741 | O13: ='GFS 2025_26 Budget'!F30/10^6 -> 0.3921 | P13: ='GFS 2025_26 Budget'!G30/10^6 -> 0.4029 | Q13: ='GFS 2025_26 Budget'!H30/10^6 -> 1.6305 | R13: ='GFS 2025_26 Budget'!I30/10^6 -> 0 | S13: ='GFS 2025_26 Budget'!J30/10^6 -> 0 | T13: ='GFS 2025_26 Budget'!K30/10^6 -> 0 | U13: =IFERROR(SUM(Q13:T13),"") -> 1.6305 | V13: ='GFS 2025_26 Budget'!M30/10^6 -> 1.6598 | W13: ='GFS 2025_26 Budget'!N30/10^6 -> 0 | X13: ='GFS 2025_26 Budget'!O30/10^6 -> 0 | Y13: ='GFS 2025_26 Budget'!P30/10^6 -> 0 | Z13: =IFERROR(SUM(V13:Y13),"") -> 1.6598 | AA13: ='GFS 2025_26 Budget'!R30/10^6 -> 1.6927 | AB13: ='GFS 2025_26 Budget'!S30/10^6 -> 0 | AC13: ='GFS 2025_26 Budget'!T30/10^6 -> 0 | AD13: ='GFS 2025_26 Budget'!U30/10^6 -> 0 | AE13: =IFERROR(SUM(AA13:AD13),"") -> 1.6927
A14: Current expenditure | B14: =SUM(B18:B20) -> 269.05647 | C14: =SUM(C18:C20) -> 271.55381 | D14: =SUM(D18:D20) -> 254.16626 | E14: =SUM(E18:E20) -> 270.31585 | F14: =SUM(F18:F20) -> 263.01278 | G14: =SUM(G18:G20) -> 260.08224 | J14: 114 | M14: Taxes on goods and services | N14: =SUM(N15:N17) -> 218.06865 | O14: =SUM(O15:O17) -> 228.3233 | P14: =SUM(P15:P17) -> 229.595 | Q14: =SUM(Q15:Q17) -> 235.2506 | R14: =SUM(R15:R17) -> 0 | S14: =SUM(S15:S17) -> 0 | T14: =SUM(T15:T17) -> 0 | U14: =IFERROR(SUM(Q14:T14),"") -> 235.2506 | V14: =SUM(V15:V17) -> 264.333 | W14: =SUM(W15:W17) -> 0 | X14: =SUM(X15:X17) -> 0 | Y14: =SUM(Y15:Y17) -> 0 | Z14: =IFERROR(SUM(V14:Y14),"") -> 264.333 | AA14: =SUM(AA15:AA17) -> 278.1088 | AB14: =SUM(AB15:AB17) -> 0 | AC14: =SUM(AC15:AC17) -> 0 | AD14: =SUM(AD15:AD17) -> 0 | AE14: =IFERROR(SUM(AA14:AD14),"") -> 278.1088
M15: ='GFS 2025_26 Budget'!D54 -> General taxes on goods and services | N15: ='GFS 2025_26 Budget'!E54/10^6 -> 142.93908 | O15: ='GFS 2025_26 Budget'!F54/10^6 -> 145.0368 | P15: ='GFS 2025_26 Budget'!G54/10^6 -> 152.0117 | Q15: ='GFS 2025_26 Budget'!H54/10^6 -> 160.8533 | R15: ='GFS 2025_26 Budget'!I54/10^6 -> 0 | S15: ='GFS 2025_26 Budget'!J54/10^6 -> 0 | T15: ='GFS 2025_26 Budget'!K54/10^6 -> 0 | U15: =IFERROR(SUM(Q15:T15),"") -> 160.8533 | V15: ='GFS 2025_26 Budget'!M54/10^6 -> 175.2889 | W15: ='GFS 2025_26 Budget'!N54/10^6 -> 0 | X15: ='GFS 2025_26 Budget'!O54/10^6 -> 0 | Y15: ='GFS 2025_26 Budget'!P54/10^6 -> 0 | Z15: =IFERROR(SUM(V15:Y15),"") -> 175.2889 | AA15: ='GFS 2025_26 Budget'!R54/10^6 -> 184.7199 | AB15: ='GFS 2025_26 Budget'!S54/10^6 -> 0 | AC15: ='GFS 2025_26 Budget'!T54/10^6 -> 0 | AD15: ='GFS 2025_26 Budget'!U54/10^6 -> 0 | AE15: =IFERROR(SUM(AA15:AD15),"") -> 184.7199
M16: ='GFS 2025_26 Budget'!D67 -> Excises | N16: ='GFS 2025_26 Budget'!E71/10^6 -> 67.725569 | O16: ='GFS 2025_26 Budget'!F71/10^6 -> 71.1154 | P16: ='GFS 2025_26 Budget'!G71/10^6 -> 69.5871 | Q16: ='GFS 2025_26 Budget'!H71/10^6 -> 65.3534 | R16: ='GFS 2025_26 Budget'!I71/10^6 -> 0 | S16: ='GFS 2025_26 Budget'!J71/10^6 -> 0 | T16: ='GFS 2025_26 Budget'!K71/10^6 -> 0 | U16: =IFERROR(SUM(Q16:T16),"") -> 65.3534 | V16: ='GFS 2025_26 Budget'!M71/10^6 -> 79.4185 | W16: ='GFS 2025_26 Budget'!N71/10^6 -> 0 | X16: ='GFS 2025_26 Budget'!O71/10^6 -> 0 | Y16: ='GFS 2025_26 Budget'!P71/10^6 -> 0 | Z16: =IFERROR(SUM(V16:Y16),"") -> 79.4185 | AA16: ='GFS 2025_26 Budget'!R71/10^6 -> 83.1092 | AB16: ='GFS 2025_26 Budget'!S71/10^6 -> 0 | AC16: ='GFS 2025_26 Budget'!T71/10^6 -> 0 | AD16: ='GFS 2025_26 Budget'!U71/10^6 -> 0 | AE16: =IFERROR(SUM(AA16:AD16),"") -> 83.1092
M17: ='GFS 2025_26 Budget'!D79 -> Taxes on use of goods and on permission to use goods or perform activities | N17: ='GFS 2025_26 Budget'!E79/10^6 -> 7.4040075 | O17: ='GFS 2025_26 Budget'!F79/10^6 -> 12.1711 | P17: ='GFS 2025_26 Budget'!G79/10^6 -> 7.9962 | Q17: ='GFS 2025_26 Budget'!H79/10^6 -> 9.0439 | R17: ='GFS 2025_26 Budget'!I79/10^6 -> 0 | S17: ='GFS 2025_26 Budget'!J79/10^6 -> 0 | T17: ='GFS 2025_26 Budget'!K79/10^6 -> 0 | U17: =IFERROR(SUM(Q17:T17),"") -> 9.0439 | V17: ='GFS 2025_26 Budget'!M79/10^6 -> 9.6256 | W17: ='GFS 2025_26 Budget'!N79/10^6 -> 0 | X17: ='GFS 2025_26 Budget'!O79/10^6 -> 0 | Y17: ='GFS 2025_26 Budget'!P79/10^6 -> 0 | Z17: =IFERROR(SUM(V17:Y17),"") -> 9.6256 | AA17: ='GFS 2025_26 Budget'!R79/10^6 -> 10.2797 | AB17: ='GFS 2025_26 Budget'!S79/10^6 -> 0 | AC17: ='GFS 2025_26 Budget'!T79/10^6 -> 0 | AD17: ='GFS 2025_26 Budget'!U79/10^6 -> 0 | AE17: =IFERROR(SUM(AA17:AD17),"") -> 10.2797
A18: Wages and salaries | B18: ='[18]Expenditure T13'!G6 -> 82.731045 | C18: ='[18]Expenditure T13'!H6 -> 81.694613 | D18: ='[18]Expenditure T13'!I6 -> 85.748415 | E18: ='[18]Expenditure T13'!L6 -> 85.487247 | F18: ='[18]Expenditure T13'!M6 -> 85.212324 | G18: ='[18]Expenditure T13'!N6 -> 85.21863 | J18: 115 | M18: Taxes on international trade n transactions | N18: ='GFS 2025_26 Budget'!E111/10^6 -> 33.172365 | O18: ='GFS 2025_26 Budget'!F111/10^6 -> 39.6625 | P18: ='GFS 2025_26 Budget'!G111/10^6 -> 34.1436 | Q18: ='GFS 2025_26 Budget'!H111/10^6 -> 33.2823 | R18: ='GFS 2025_26 Budget'!I111/10^6 -> 0 | S18: ='GFS 2025_26 Budget'!J111/10^6 -> 0 | T18: ='GFS 2025_26 Budget'!K111/10^6 -> 0 | U18: =IFERROR(SUM(Q18:T18),"") -> 33.2823 | V18: ='GFS 2025_26 Budget'!M111/10^6 -> 38.9675 | W18: ='GFS 2025_26 Budget'!N111/10^6 -> 0 | X18: ='GFS 2025_26 Budget'!O111/10^6 -> 0 | Y18: ='GFS 2025_26 Budget'!P111/10^6 -> 0 | Z18: =IFERROR(SUM(V18:Y18),"") -> 38.9675 | AA18: ='GFS 2025_26 Budget'!R111/10^6 -> 40.7596 | AB18: ='GFS 2025_26 Budget'!S111/10^6 -> 0 | AC18: ='GFS 2025_26 Budget'!T111/10^6 -> 0 | AD18: ='GFS 2025_26 Budget'!U111/10^6 -> 0 | AE18: =IFERROR(SUM(AA18:AD18),"") -> 40.7596
A19: Other expenditures | B19: ='[18]Expenditure T13'!G5-'[18]Expenditure T13'!G6 -> 101.1068 | C19: ='[18]Expenditure T13'!H5-'[18]Expenditure T13'!H6 -> 104.64057 | D19: ='[18]Expenditure T13'!I5-'[18]Expenditure T13'!I6 -> 83.199216 | E19: ='[18]Expenditure T13'!L5-'[18]Expenditure T13'!L6 -> 99.609972 | F19: ='[18]Expenditure T13'!M5-'[18]Expenditure T13'!M6 -> 92.581832 | G19: ='[18]Expenditure T13'!N5-'[18]Expenditure T13'!N6 -> 89.64498 | J19: 116 | M19: Other taxes | N19: ='GFS 2025_26 Budget'!E133 -> 0 | O19: ='GFS 2025_26 Budget'!F133 -> 0 | P19: ='GFS 2025_26 Budget'!G133 -> 0 | Q19: ='GFS 2025_26 Budget'!H133 -> 0 | R19: ='GFS 2025_26 Budget'!I133 -> 0 | S19: ='GFS 2025_26 Budget'!J133 -> 0 | T19: ='GFS 2025_26 Budget'!K133 -> 0 | U19: =IFERROR(SUM(Q19:T19),"") -> 0 | V19: ='GFS 2025_26 Budget'!M133 -> 0 | W19: ='GFS 2025_26 Budget'!N133 -> 0 | X19: ='GFS 2025_26 Budget'!O133 -> 0 | Y19: ='GFS 2025_26 Budget'!P133 -> 0 | Z19: =IFERROR(SUM(V19:Y19),"") -> 0 | AA19: ='GFS 2025_26 Budget'!R133 -> 0 | AB19: ='GFS 2025_26 Budget'!S133 -> 0 | AC19: ='GFS 2025_26 Budget'!T133 -> 0 | AD19: ='GFS 2025_26 Budget'!U133 -> 0 | AE19: =IFERROR(SUM(AA19:AD19),"") -> 0
A20: Additional expenditures | B20: ='[18]Expenditure T13'!G10 -> 85.218628 | C20: ='[18]Expenditure T13'!H10 -> 85.218628 | D20: ='[18]Expenditure T13'!I10 -> 85.218628 | E20: ='[18]Expenditure T13'!L10 -> 85.218628 | F20: ='[18]Expenditure T13'!M10 -> 85.218628 | G20: ='[18]Expenditure T13'!N10 -> 85.218628 | J20: 12 | M20: Social contributions [GFS] | N20: ='GFS 2025_26 Budget'!E139/10^6 -> 0 | O20: ='GFS 2025_26 Budget'!F139/10^6 -> 0 | P20: ='GFS 2025_26 Budget'!G139/10^6 -> 0 | Q20: ='GFS 2025_26 Budget'!H139/10^6 -> 0 | R20: ='GFS 2025_26 Budget'!I139/10^6 -> 0 | S20: ='GFS 2025_26 Budget'!J139/10^6 -> 0 | T20: ='GFS 2025_26 Budget'!K139/10^6 -> 0 | U20: =IFERROR(SUM(Q20:T20),"") -> 0 | V20: ='GFS 2025_26 Budget'!M139/10^6 -> 0 | W20: ='GFS 2025_26 Budget'!N139/10^6 -> 0 | X20: ='GFS 2025_26 Budget'!O139/10^6 -> 0 | Y20: ='GFS 2025_26 Budget'!P139/10^6 -> 0 | Z20: =IFERROR(SUM(V20:Y20),"") -> 0 | AA20: ='GFS 2025_26 Budget'!R139/10^6 -> 0 | AB20: ='GFS 2025_26 Budget'!S139/10^6 -> 0 | AC20: ='GFS 2025_26 Budget'!T139/10^6 -> 0 | AD20: ='GFS 2025_26 Budget'!U139/10^6 -> 0 | AE20: =IFERROR(SUM(AA20:AD20),"") -> 0
J21: 13 | M21: Grants | N21: =SUM(N24,N27,N30) -> 426.62162 | O21: =SUM(O24,O27,O30) -> 509.2681 | P21: =SUM(P24,P27,P30) -> 386.8363 | Q21: =SUM(Q24,Q27,Q30) -> 0 | R21: =SUM(R24,R27,R30) -> 118.0109 | S21: =SUM(S24,S27,S30) -> 133.0793 | T21: =SUM(T24,T27,T30) -> 212.6572 | U21: =IFERROR(SUM(Q21:T21),"") -> 463.7474 | V21: =SUM(V24,V27,V30) -> 0 | W21: =SUM(W24,W27,W30) -> 86.953 | X21: =SUM(X24,X27,X30) -> 105.8357 | Y21: =SUM(Y24,Y27,Y30) -> 232.3395 | Z21: =IFERROR(SUM(V21:Y21),"") -> 425.1282 | AA21: =SUM(AA24,AA27,AA30) -> 0 | AB21: =SUM(AB24,AB27,AB30) -> 47.5291 | AC21: =SUM(AC24,AC27,AC30) -> 79.5045 | AD21: =SUM(AD24,AD27,AD30) -> 142.3488 | AE21: =IFERROR(SUM(AA21:AD21),"") -> 269.3824
M22: Current | N22: =ROUND(SUM('GFS 2025_26 Budget'!E167,'GFS 2025_26 Budget'!E212)/10^6,1) -> 91.6 | O22: =ROUND(SUM('GFS 2025_26 Budget'!F167,'GFS 2025_26 Budget'!F212)/10^6,1) -> 120.2 | P22: =ROUND(SUM('GFS 2025_26 Budget'!G167,'GFS 2025_26 Budget'!G212)/10^6,1) -> 109.5 | Q22: =ROUND(SUM('GFS 2025_26 Budget'!H167,'GFS 2025_26 Budget'!H212)/10^6,1) -> 0 | R22: =ROUND(SUM('GFS 2025_26 Budget'!I167,'GFS 2025_26 Budget'!I212)/10^6,1) -> 115 | S22: =ROUND(SUM('GFS 2025_26 Budget'!J167,'GFS 2025_26 Budget'!J212)/10^6,1) -> 0 | T22: =ROUND(SUM('GFS 2025_26 Budget'!K167,'GFS 2025_26 Budget'!K212)/10^6,1) -> 0 | U22: =IFERROR(SUM(Q22:T22),"") -> 115 | V22: =ROUND(SUM('GFS 2025_26 Budget'!M167,'GFS 2025_26 Budget'!M212)/10^6,1) -> 0 | W22: =ROUND(SUM('GFS 2025_26 Budget'!N167,'GFS 2025_26 Budget'!N212)/10^6,1) -> 84 | X22: =ROUND(SUM('GFS 2025_26 Budget'!O167,'GFS 2025_26 Budget'!O212)/10^6,1) -> 0 | Y22: =ROUND(SUM('GFS 2025_26 Budget'!P167,'GFS 2025_26 Budget'!P212)/10^6,1) -> 0 | Z22: =IFERROR(SUM(V22:Y22),"") -> 84 | AA22: =ROUND(SUM('GFS 2025_26 Budget'!R167,'GFS 2025_26 Budget'!R212)/10^6,1) -> 0 | AB22: =ROUND(SUM('GFS 2025_26 Budget'!S167,'GFS 2025_26 Budget'!S212)/10^6,1) -> 44.5 | AC22: =ROUND(SUM('GFS 2025_26 Budget'!T167,'GFS 2025_26 Budget'!T212)/10^6,1) -> 0 | AD22: =ROUND(SUM('GFS 2025_26 Budget'!U167,'GFS 2025_26 Budget'!U212)/10^6,1) -> 0 | AE22: =IFERROR(SUM(AA22:AD22),"") -> 44.5
M23: Capital | N23: =ROUND(SUM('GFS 2025_26 Budget'!E203,'GFS 2025_26 Budget'!E257)/10^6,1) -> 335 | O23: =ROUND(SUM('GFS 2025_26 Budget'!F203,'GFS 2025_26 Budget'!F257)/10^6,1) -> 389 | P23: =ROUND(SUM('GFS 2025_26 Budget'!G203,'GFS 2025_26 Budget'!G257)/10^6,1) -> 277.3 | Q23: =ROUND(SUM('GFS 2025_26 Budget'!H203,'GFS 2025_26 Budget'!H257)/10^6,1) -> 0 | R23: =ROUND(SUM('GFS 2025_26 Budget'!I203,'GFS 2025_26 Budget'!I257)/10^6,1) -> 3 | S23: =ROUND(SUM('GFS 2025_26 Budget'!J203,'GFS 2025_26 Budget'!J257)/10^6,1) -> 133.1 | T23: =ROUND(SUM('GFS 2025_26 Budget'!K203,'GFS 2025_26 Budget'!K257)/10^6,1) -> 212.7 | U23: =IFERROR(SUM(Q23:T23),"") -> 348.8 | V23: =ROUND(SUM('GFS 2025_26 Budget'!M203,'GFS 2025_26 Budget'!M257)/10^6,1) -> 0 | W23: =ROUND(SUM('GFS 2025_26 Budget'!N203,'GFS 2025_26 Budget'!N257)/10^6,1) -> 3 | X23: =ROUND(SUM('GFS 2025_26 Budget'!O203,'GFS 2025_26 Budget'!O257)/10^6,1) -> 105.8 | Y23: =ROUND(SUM('GFS 2025_26 Budget'!P203,'GFS 2025_26 Budget'!P257)/10^6,1) -> 232.3 | Z23: =IFERROR(SUM(V23:Y23),"") -> 341.1 | AA23: =ROUND(SUM('GFS 2025_26 Budget'!R203,'GFS 2025_26 Budget'!R257)/10^6,1) -> 0 | AB23: =ROUND(SUM('GFS 2025_26 Budget'!S203,'GFS 2025_26 Budget'!S257)/10^6,1) -> 3 | AC23: =ROUND(SUM('GFS 2025_26 Budget'!T203,'GFS 2025_26 Budget'!T257)/10^6,1) -> 79.5 | AD23: =ROUND(SUM('GFS 2025_26 Budget'!U203,'GFS 2025_26 Budget'!U257)/10^6,1) -> 142.3 | AE23: =IFERROR(SUM(AA23:AD23),"") -> 224.8
A24: Overall deficit/surplus | B24: =B5-#REF! -> #REF! | C24: =C5-#REF! -> #REF! | D24: =D5-#REF! -> #REF! | E24: =E5-#REF! -> #REF! | F24: =F5-#REF! -> #REF! | G24: =G5-#REF! -> #REF! | J24: 131 | M24: From foreign governments | N24: ='GFS 2025_26 Budget'!E157/10^6 -> 234.76038 | O24: ='GFS 2025_26 Budget'!F157/10^6 -> 289.2048 | P24: ='GFS 2025_26 Budget'!G157/10^6 -> 204.0416 | Q24: ='GFS 2025_26 Budget'!H157/10^6 -> 0 | R24: ='GFS 2025_26 Budget'!I157/10^6 -> 65.7721 | S24: ='GFS 2025_26 Budget'!J157/10^6 -> 44.66 | T24: ='GFS 2025_26 Budget'!K157/10^6 -> 89.21 | U24: =IFERROR(SUM(Q24:T24),"") -> 199.6421 | V24: ='GFS 2025_26 Budget'!M157/10^6 -> 0 | W24: ='GFS 2025_26 Budget'!N157/10^6 -> 57.2226 | X24: ='GFS 2025_26 Budget'!O157/10^6 -> 16.9615 | Y24: ='GFS 2025_26 Budget'!P157/10^6 -> 102.851 | Z24: =IFERROR(SUM(V24:Y24),"") -> 177.0351 | AA24: ='GFS 2025_26 Budget'!R157/10^6 -> 0 | AB24: ='GFS 2025_26 Budget'!S157/10^6 -> 17.7987 | AC24: ='GFS 2025_26 Budget'!T157/10^6 -> 16.2655 | AD24: ='GFS 2025_26 Budget'!U157/10^6 -> 79.6583 | AE24: =IFERROR(SUM(AA24:AD24),"") -> 113.7225
M25: current | N25: ='GFS 2025_26 Budget'!E167/10^6 -> 59.687538 | O25: ='GFS 2025_26 Budget'!F167/10^6 -> 81.6734 | P25: ='GFS 2025_26 Budget'!G167/10^6 -> 82.2195 | Q25: ='GFS 2025_26 Budget'!H167/10^6 -> 0 | R25: ='GFS 2025_26 Budget'!I167/10^6 -> 65.7721 | S25: ='GFS 2025_26 Budget'!J167/10^6 -> 0 | T25: ='GFS 2025_26 Budget'!K167/10^6 -> 0 | U25: =IFERROR(SUM(Q25:T25),"") -> 65.7721 | V25: ='GFS 2025_26 Budget'!M167/10^6 -> 0 | W25: ='GFS 2025_26 Budget'!N167/10^6 -> 57.2226 | X25: ='GFS 2025_26 Budget'!O167/10^6 -> 0 | Y25: ='GFS 2025_26 Budget'!P167/10^6 -> 0 | Z25: =IFERROR(SUM(V25:Y25),"") -> 57.2226 | AA25: ='GFS 2025_26 Budget'!R167/10^6 -> 0 | AB25: ='GFS 2025_26 Budget'!S167/10^6 -> 17.7987 | AC25: ='GFS 2025_26 Budget'!T167/10^6 -> 0 | AD25: ='GFS 2025_26 Budget'!U167/10^6 -> 0 | AE25: =IFERROR(SUM(AA25:AD25),"") -> 17.7987
M26: capital | N26: ='GFS 2025_26 Budget'!E203/10^6 -> 175.07284 | O26: ='GFS 2025_26 Budget'!F203/10^6 -> 207.5314 | P26: ='GFS 2025_26 Budget'!G203/10^6 -> 121.8221 | Q26: ='GFS 2025_26 Budget'!H203/10^6 -> 0 | R26: ='GFS 2025_26 Budget'!I203/10^6 -> 0 | S26: ='GFS 2025_26 Budget'!J203/10^6 -> 44.66 | T26: ='GFS 2025_26 Budget'!K203/10^6 -> 89.21 | U26: =IFERROR(SUM(Q26:T26),"") -> 133.87 | V26: ='GFS 2025_26 Budget'!M203/10^6 -> 0 | W26: ='GFS 2025_26 Budget'!N203/10^6 -> 0 | X26: ='GFS 2025_26 Budget'!O203/10^6 -> 16.9615 | Y26: ='GFS 2025_26 Budget'!P203/10^6 -> 102.851 | Z26: =IFERROR(SUM(V26:Y26),"") -> 119.8125 | AA26: ='GFS 2025_26 Budget'!R203/10^6 -> 0 | AB26: ='GFS 2025_26 Budget'!S203/10^6 -> 0 | AC26: ='GFS 2025_26 Budget'!T203/10^6 -> 16.2655 | AD26: ='GFS 2025_26 Budget'!U203/10^6 -> 79.6583 | AE26: =IFERROR(SUM(AA26:AD26),"") -> 95.9238
J27: 132 | M27: From international organizations | N27: ='GFS 2025_26 Budget'!E206/10^6 -> 191.86124 | O27: ='GFS 2025_26 Budget'!F206/10^6 -> 220.0633 | P27: ='GFS 2025_26 Budget'!G206/10^6 -> 182.7947 | Q27: ='GFS 2025_26 Budget'!H206/10^6 -> 0 | R27: ='GFS 2025_26 Budget'!I206/10^6 -> 52.2388 | S27: ='GFS 2025_26 Budget'!J206/10^6 -> 88.4193 | T27: ='GFS 2025_26 Budget'!K206/10^6 -> 123.4472 | U27: =IFERROR(SUM(Q27:T27),"") -> 264.1053 | V27: ='GFS 2025_26 Budget'!M206/10^6 -> 0 | W27: ='GFS 2025_26 Budget'!N206/10^6 -> 29.7304 | X27: ='GFS 2025_26 Budget'!O206/10^6 -> 88.8742 | Y27: ='GFS 2025_26 Budget'!P206/10^6 -> 129.4885 | Z27: =IFERROR(SUM(V27:Y27),"") -> 248.0931 | AA27: ='GFS 2025_26 Budget'!R206/10^6 -> 0 | AB27: ='GFS 2025_26 Budget'!S206/10^6 -> 29.7304 | AC27: ='GFS 2025_26 Budget'!T206/10^6 -> 63.239 | AD27: ='GFS 2025_26 Budget'!U206/10^6 -> 62.6905 | AE27: =IFERROR(SUM(AA27:AD27),"") -> 155.6599
M28: current | N28: ='GFS 2025_26 Budget'!E212/10^6 -> 31.890486 | O28: ='GFS 2025_26 Budget'!F212/10^6 -> 38.5626 | P28: ='GFS 2025_26 Budget'!G212/10^6 -> 27.3164 | Q28: ='GFS 2025_26 Budget'!H212/10^6 -> 0 | R28: ='GFS 2025_26 Budget'!I212/10^6 -> 49.2388 | S28: ='GFS 2025_26 Budget'!J212/10^6 -> 0 | T28: ='GFS 2025_26 Budget'!K212/10^6 -> 0 | U28: =IFERROR(SUM(Q28:T28),"") -> 49.2388 | V28: ='GFS 2025_26 Budget'!M212/10^6 -> 0 | W28: ='GFS 2025_26 Budget'!N212/10^6 -> 26.7304 | X28: ='GFS 2025_26 Budget'!O212/10^6 -> 0 | Y28: ='GFS 2025_26 Budget'!P212/10^6 -> 0 | Z28: =IFERROR(SUM(V28:Y28),"") -> 26.7304 | AA28: ='GFS 2025_26 Budget'!R212/10^6 -> 0 | AB28: ='GFS 2025_26 Budget'!S212/10^6 -> 26.7304 | AC28: ='GFS 2025_26 Budget'!T212/10^6 -> 0 | AD28: ='GFS 2025_26 Budget'!U212/10^6 -> 0 | AE28: =IFERROR(SUM(AA28:AD28),"") -> 26.7304
M29: capital | N29: ='GFS 2025_26 Budget'!E257/10^6 -> 159.97075 | O29: ='GFS 2025_26 Budget'!F257/10^6 -> 181.5007 | P29: ='GFS 2025_26 Budget'!G257/10^6 -> 155.4783 | Q29: ='GFS 2025_26 Budget'!H257/10^6 -> 0 | R29: ='GFS 2025_26 Budget'!I257/10^6 -> 3 | S29: ='GFS 2025_26 Budget'!J257/10^6 -> 88.4193 | T29: ='GFS 2025_26 Budget'!K257/10^6 -> 123.4472 | U29: =IFERROR(SUM(Q29:T29),"") -> 214.8665 | V29: ='GFS 2025_26 Budget'!M257/10^6 -> 0 | W29: ='GFS 2025_26 Budget'!N257/10^6 -> 3 | X29: ='GFS 2025_26 Budget'!O257/10^6 -> 88.8742 | Y29: ='GFS 2025_26 Budget'!P257/10^6 -> 129.4885 | Z29: =IFERROR(SUM(V29:Y29),"") -> 221.3627 | AA29: ='GFS 2025_26 Budget'!R257/10^6 -> 0 | AB29: ='GFS 2025_26 Budget'!S257/10^6 -> 3 | AC29: ='GFS 2025_26 Budget'!T257/10^6 -> 63.239 | AD29: ='GFS 2025_26 Budget'!U257/10^6 -> 62.6905 | AE29: =IFERROR(SUM(AA29:AD29),"") -> 128.9295
J30: 133 | M30: From other general government units | N30: ='GFS 2025_26 Budget'!E259 | O30: ='GFS 2025_26 Budget'!F259 -> 0 | P30: ='GFS 2025_26 Budget'!G259 -> 0 | Q30: ='GFS 2025_26 Budget'!H259 -> 0 | R30: ='GFS 2025_26 Budget'!I259 -> 0 | S30: ='GFS 2025_26 Budget'!J259 -> 0 | T30: ='GFS 2025_26 Budget'!K259 -> 0 | U30: =IFERROR(SUM(Q30:T30),"") -> 0 | V30: ='GFS 2025_26 Budget'!M259 -> 0 | W30: ='GFS 2025_26 Budget'!N259 -> 0 | X30: ='GFS 2025_26 Budget'!O259 -> 0 | Y30: ='GFS 2025_26 Budget'!P259 -> 0 | Z30: =IFERROR(SUM(V30:Y30),"") -> 0 | AA30: ='GFS 2025_26 Budget'!R259 -> 0 | AB30: ='GFS 2025_26 Budget'!S259 -> 0 | AC30: ='GFS 2025_26 Budget'!T259 -> 0 | AD30: ='GFS 2025_26 Budget'!U259 -> 0 | AE30: =IFERROR(SUM(AA30:AD30),"") -> 0 | AN30: FY2019 Est Outturn | AO30: Budget Estimate 2019/20 | AP30: Actual Jul_Jan 2019/20 | AQ30: 2019/20 Total Est Outturn | AR30: 2020/21 Total Est | AS30: Budget Estimate for 2021/22 | AT30: Budget Estimates for for 2022/23
J31: 14 | M31: Other revenue | N31: =SUM(N32,N33,N34,N35) -> 55.869071 | O31: =SUM(O32,O33,O34,O35) -> 73.4106 | P31: =SUM(P32,P33,P34,P35) -> 61.7159 | Q31: =SUM(Q32,Q33,Q34,Q35) -> 60.2318 | R31: =SUM(R32,R33,R34,R35) -> 0 | S31: =SUM(S32,S33,S34,S35) -> 0.0045 | T31: =SUM(T32,T33,T34,T35) -> 1.5 | U31: =IFERROR(SUM(Q31:T31),"") -> 61.7363 | V31: =SUM(V32,V33,V34,V35) -> 64.7756 | W31: =SUM(W32,W33,W34,W35) -> 0 | X31: =SUM(X32,X33,X34,X35) -> 0.0001 | Y31: =SUM(Y32,Y33,Y34,Y35) -> 1.5 | Z31: =IFERROR(SUM(V31:Y31),"") -> 66.2757 | AA31: =SUM(AA32,AA33,AA34,AA35) -> 68.5218 | AB31: =SUM(AB32,AB33,AB34,AB35) -> 0 | AC31: =SUM(AC32,AC33,AC34,AC35) -> 0.0001 | AD31: =SUM(AD32,AD33,AD34,AD35) -> 1.5 | AE31: =IFERROR(SUM(AA31:AD31),"") -> 70.0219
A32: Total financing | B32: =0-B24 -> #REF! | C32: =0-C24 -> #REF! | D32: =0-D24 -> #REF! | E32: =0-E24 -> #REF! | F32: =0-F24 -> #REF! | G32: =0-G24 -> #REF! | J32: 141 | M32: Property income [GFS] | N32: ='GFS 2025_26 Budget'!E270/10^6 -> 35.204181 | O32: ='GFS 2025_26 Budget'!F270/10^6 -> 41.8929 | P32: ='GFS 2025_26 Budget'!G270/10^6 -> 39.4128 | Q32: ='GFS 2025_26 Budget'!H270/10^6 -> 36.0685 | R32: ='GFS 2025_26 Budget'!I270/10^6 -> 0 | S32: ='GFS 2025_26 Budget'!J270/10^6 -> 0 | T32: ='GFS 2025_26 Budget'!K270/10^6 -> 0 | U32: =IFERROR(SUM(Q32:T32),"") -> 36.0685 | V32: ='GFS 2025_26 Budget'!M270/10^6 -> 38.9881 | W32: ='GFS 2025_26 Budget'!N270/10^6 -> 0 | X32: ='GFS 2025_26 Budget'!O270/10^6 -> 0 | Y32: ='GFS 2025_26 Budget'!P270/10^6 -> 0 | Z32: =IFERROR(SUM(V32:Y32),"") -> 38.9881 | AA32: ='GFS 2025_26 Budget'!R270/10^6 -> 40.911 | AB32: ='GFS 2025_26 Budget'!S270/10^6 -> 0 | AC32: ='GFS 2025_26 Budget'!T270/10^6 -> 0 | AD32: ='GFS 2025_26 Budget'!U270/10^6 -> 0 | AE32: =IFERROR(SUM(AA32:AD32),"") -> 40.911
A33: External financing | B33: =B34-B35 -> 31.703562 | C33: =C34-C35 -> 22.319517 | D33: =D34-D35 -> -5.933052 | E33: =E34-E35 -> -6.648 | F33: =F34-F35 -> 8.70902 | G33: =G34-G35 -> 5.089983 | J33: 142 | M33: Sales of goods and services | N33: ='GFS 2025_26 Budget'!E306/10^6 -> 19.617804 | O33: ='GFS 2025_26 Budget'!F306/10^6 -> 29.9278 | P33: ='GFS 2025_26 Budget'!G306/10^6 -> 21.2942 | Q33: ='GFS 2025_26 Budget'!H306/10^6 -> 22.9853 | R33: ='GFS 2025_26 Budget'!I306/10^6 -> 0 | S33: ='GFS 2025_26 Budget'!J306/10^6 -> 0 | T33: ='GFS 2025_26 Budget'!K306/10^6 -> 0 | U33: =IFERROR(SUM(Q33:T33),"") -> 22.9853 | V33: ='GFS 2025_26 Budget'!M306/10^6 -> 24.536 | W33: ='GFS 2025_26 Budget'!N306/10^6 -> 0 | X33: ='GFS 2025_26 Budget'!O306/10^6 -> 0 | Y33: ='GFS 2025_26 Budget'!P306/10^6 -> 0 | Z33: =IFERROR(SUM(V33:Y33),"") -> 24.536 | AA33: ='GFS 2025_26 Budget'!R306/10^6 -> 26.2769 | AB33: ='GFS 2025_26 Budget'!S306/10^6 -> 0 | AC33: ='GFS 2025_26 Budget'!T306/10^6 -> 0 | AD33: ='GFS 2025_26 Budget'!U306/10^6 -> 0 | AE33: =IFERROR(SUM(AA33:AD33),"") -> 26.2769 | AM33: Compensation of Employees ($m) | AN33: 134.34065 | AO33: 162.2079 | AP33: 83.597862 | AQ33: 152.35776 | AR33: 158.7634 | AS33: 158.449 | AT33: 158.449
A34: Disbursements | B34: ='[18]Balance and Financing T1&T5'!H81 -> 36.28256 | C34: ='[18]Balance and Financing T1&T5'!I81 -> 30.15 | D34: =[18]RawGFS!L850/1000000 -> 0 | E34: =[18]RawGFS!O850/1000000 -> 0 | F34: ='[18]Balance and Financing T1&T5'!R81 -> 15.35702 | G34: ='[18]Balance and Financing T1&T5'!S81 -> 11.737983 | J34: 143 | M34: Fines, penalties, and forfeits | N34: ='GFS 2025_26 Budget'!E398/10^6 -> 0.9320862 | O34: ='GFS 2025_26 Budget'!F398/10^6 -> 0.8066 | P34: ='GFS 2025_26 Budget'!G398/10^6 -> 1.0089 | Q34: ='GFS 2025_26 Budget'!H398/10^6 -> 1.178 | R34: 0 | S34: 0 | T34: 0 | U34: =IFERROR(SUM(Q34:T34),"") -> 1.178 | V34: ='GFS 2025_26 Budget'!M398/10^6 -> 1.2515 | W34: 0 | X34: 0 | Y34: 0 | Z34: =IFERROR(SUM(V34:Y34),"") -> 1.2515 | AA34: ='GFS 2025_26 Budget'!R398/10^6 -> 1.3339 | AB34: 0 | AC34: 0 | AD34: 0 | AE34: =IFERROR(SUM(AA34:AD34),"") -> 1.3339 | AM34: Total Domestic Revenue ($m) | AN34: 271.53355 | AO34: 305.6131 | AP34: 158.21095 | AQ34: 290.15221 | AR34: 306.0364 | AS34: 306.027 | AT34: 306.0176
A35: Repayments | B35: ='[18]Balance and Financing T1&T5'!H83 -> 4.578998 | C35: ='[18]Balance and Financing T1&T5'!I83 -> 7.830483 | D35: =[18]RawGFS!L855/1000000 -> 5.933052 | E35: ='[18]Balance and Financing T1&T5'!N83 -> 6.648 | F35: ='[18]Balance and Financing T1&T5'!R83 -> 6.648 | G35: ='[18]Balance and Financing T1&T5'!S83 -> 6.648 | J35: 144 | M35: ='GFS 2025_26 Budget'!D401 -> Transfer not elswhere | N35: ='GFS 2025_26 Budget'!E401/10^6 -> 0.115 | O35: ='GFS 2025_26 Budget'!F401/10^6 -> 0.7833 | P35: ='GFS 2025_26 Budget'!G401/10^6 -> 0 | Q35: ='GFS 2025_26 Budget'!H401/10^6 -> 0 | R35: ='GFS 2025_26 Budget'!I401/10^6 -> 0 | S35: ='GFS 2025_26 Budget'!J401/10^6 -> 0.0045 | T35: ='GFS 2025_26 Budget'!K401/10^6 -> 1.5 | U35: =IFERROR(SUM(Q35:T35),"") -> 1.5045 | V35: ='GFS 2025_26 Budget'!M401/10^6 -> 0 | W35: ='GFS 2025_26 Budget'!N401/10^6 -> 0 | X35: ='GFS 2025_26 Budget'!O401/10^6 -> 0.0001 | Y35: ='GFS 2025_26 Budget'!P401/10^6 -> 1.5 | Z35: =IFERROR(SUM(V35:Y35),"") -> 1.5001 | AA35: ='GFS 2025_26 Budget'!R401/10^6 -> 0 | AB35: ='GFS 2025_26 Budget'!S401/10^6 -> 0 | AC35: ='GFS 2025_26 Budget'!T401/10^6 -> 0.0001 | AD35: ='GFS 2025_26 Budget'!U401/10^6 -> 1.5 | AE35: =IFERROR(SUM(AA35:AD35),"") -> 1.5001 | AM35: Wage Bill Fiscal anchor 53%> | AN35: =AN33/AN34 -> 0.49474791 | AO35: =AO33/AO34 -> 0.53076226 | AP35: =AP33/AP34 -> 0.52839491 | AQ35: =AQ33/AQ34 -> 0.525096 | AR35: =AR33/AR34 -> 0.51877293 | AS35: =AS33/AS34 -> 0.5177615 | AT35: =AT33/AT34 -> 0.51777741
A36: of which: Bonds | B36: ='[18]Balance and Financing T1&T5'!H86 -> 14.603 | C36: ='[18]Balance and Financing T1&T5'!I86 -> 3.36 | D36: ='[18]Balance and Financing T1&T5'!J86 -> 10.36 | E36: ='[18]Balance and Financing T1&T5'!N86 -> 3 | F36: ='[18]Balance and Financing T1&T5'!R86 -> 7.109088 | G36: ='[18]Balance and Financing T1&T5'!S86 -> 6 | AM36: Domestic revenue Fiscal anchor >23% | AN36: =AN34/#REF! -> #REF! | AQ36: =AQ34/#REF! -> #REF! | AR36: =AR34/#REF! -> #REF! | AS36: =AS34/#REF! -> #REF! | AT36: =AT34/#REF! -> #REF!
A37: Repayments | B37: ='[18]Balance and Financing T1&T5'!H87 -> 6.891255 | C37: ='[18]Balance and Financing T1&T5'!I87 -> 6.96 | D37: ='[18]Balance and Financing T1&T5'!J87 -> 10.36 | E37: ='[18]Balance and Financing T1&T5'!N87 -> 3 | F37: ='[18]Balance and Financing T1&T5'!R87 -> 3 | G37: ='[18]Balance and Financing T1&T5'!S87 -> 3 | J37: 2 | M37: EXPENSE | N37: =SUM(N38,N41,N42,N46,N49,N53,N54) -> 541.08415 | O37: =SUM(O38,O41,O42,O46,O49,O53,O54) -> 617.421 | P37: =SUM(P38,P41,P42,P46,P49,P53,P54) -> 519.7125 | Q37: =SUM(Q38,Q41,Q42,Q46,Q49,Q53,Q54) -> 368.1625 | R37: =SUM(R38,R41,R42,R46,R49,R53,R54) -> 104.4969 | S37: =SUM(S38,S41,S42,S46,S49,S53,S54) -> 76.135002 | T37: =SUM(T38,T41,T42,T46,T49,T53,T54) -> 61.035003 | U37: =IFERROR(SUM(Q37:T37),"") -> 609.82941 | V37: =SUM(V38,V41,V42,V46,V49,V53,V54) -> 385.1246 | W37: =SUM(W38,W41,W42,W46,W49,W53,W54) -> 77.239001 | X37: =SUM(X38,X41,X42,X46,X49,X53,X54) -> 48.889202 | Y37: =SUM(Y38,Y41,Y42,Y46,Y49,Y53,Y54) -> 73.115503 | Z37: =IFERROR(SUM(V37:Y37),"") -> 584.36831 | AA37: =SUM(AA38,AA41,AA42,AA46,AA49,AA53,AA54) -> 409.2277 | AB37: =SUM(AB38,AB41,AB42,AB46,AB49,AB53,AB54) -> 46.815101 | AC37: =SUM(AC38,AC41,AC42,AC46,AC49,AC53,AC54) -> 48.063302 | AD37: =SUM(AD38,AD41,AD42,AD46,AD49,AD53,AD54) -> 72.494403 | AE37: =IFERROR(SUM(AA37:AD37),"") -> 576.60051
A38: Net Changes in Government Investment / Bank Balance | B38: =((B33+#REF!)-B32) -> #REF! | C38: =((C33+#REF!)-C32) -> #REF! | D38: =((D33+#REF!)-D32) -> #REF! | E38: =((E33+#REF!)-E32) -> #REF! | F38: =((F33+#REF!)-F32) -> #REF! | G38: =((G33+#REF!)-G32) -> #REF! | J38: 21 | M38: Compensation of employees | N38: =SUM(N39,N40) -> 184.19837 | O38: =SUM(O39,O40) -> 193.8232 | P38: =SUM(P39,P40) -> 191.9193 | Q38: =SUM(Q39,Q40) -> 194.5455 | R38: =SUM(R39,R40) -> 15.5414 | S38: =SUM(S39,S40) -> 0.3666 | T38: =SUM(T39,T40) -> 0.2937 | U38: =IFERROR(SUM(Q38:T38),"") -> 210.7472 | V38: =SUM(V39,V40) -> 200.1715 | W38: =SUM(W39,W40) -> 6.1546 | X38: =SUM(X39,X40) -> 0.2396 | Y38: =SUM(Y39,Y40) -> 0.4137 | Z38: =IFERROR(SUM(V38:Y38),"") -> 206.9794 | AA38: =SUM(AA39,AA40) -> 203.2172 | AB38: =SUM(AB39,AB40) -> 0.2882 | AC38: =SUM(AC39,AC40) -> 0.2436 | AD38: =SUM(AD39,AD40) -> 0.4137 | AE38: =IFERROR(SUM(AA38:AD38),"") -> 204.1627
A39: Others: Treasury Deposit at NRBT | J39: 211 | M39: Wages and salaries | N39: ='GFS 2025_26 Budget'!E418/10^6 -> 171.21795 | O39: ='GFS 2025_26 Budget'!F418/10^6 -> 178.8978 | P39: ='GFS 2025_26 Budget'!G418/10^6 -> 178.4581 | Q39: ='GFS 2025_26 Budget'!H418/10^6 -> 179.4057 | R39: ='GFS 2025_26 Budget'!I418/10^6 -> 15.5152 | S39: ='GFS 2025_26 Budget'!J418/10^6 -> 0.3666 | T39: ='GFS 2025_26 Budget'!K418/10^6 -> 0.2937 | U39: =IFERROR(SUM(Q39:T39),"") -> 195.5812 | V39: ='GFS 2025_26 Budget'!M418/10^6 -> 185.0317 | W39: ='GFS 2025_26 Budget'!N418/10^6 -> 6.1284 | X39: ='GFS 2025_26 Budget'!O418/10^6 -> 0.2396 | Y39: ='GFS 2025_26 Budget'!P418/10^6 -> 0.4137 | Z39: =IFERROR(SUM(V39:Y39),"") -> 191.8134 | AA39: ='GFS 2025_26 Budget'!R418/10^6 -> 188.0774 | AB39: ='GFS 2025_26 Budget'!S418/10^6 -> 0.262 | AC39: ='GFS 2025_26 Budget'!T418/10^6 -> 0.2436 | AD39: ='GFS 2025_26 Budget'!U418/10^6 -> 0.4137 | AE39: =IFERROR(SUM(AA39:AD39),"") -> 188.9967
A40: ADB Urban Development Loan | J40: 212 | M40: Social contributions | N40: ='GFS 2025_26 Budget'!E450/10^6 -> 12.98042 | O40: ='GFS 2025_26 Budget'!F450/10^6 -> 14.9254 | P40: ='GFS 2025_26 Budget'!G450/10^6 -> 13.4612 | Q40: ='GFS 2025_26 Budget'!H450/10^6 -> 15.1398 | R40: ='GFS 2025_26 Budget'!I450/10^6 -> 0.0262 | S40: ='GFS 2025_26 Budget'!J450/10^6 -> 0 | T40: ='GFS 2025_26 Budget'!K450/10^6 -> 0 | U40: =IFERROR(SUM(Q40:T40),"") -> 15.166 | V40: ='GFS 2025_26 Budget'!M450/10^6 -> 15.1398 | W40: ='GFS 2025_26 Budget'!N450/10^6 -> 0.0262 | X40: ='GFS 2025_26 Budget'!O450/10^6 -> 0 | Y40: ='GFS 2025_26 Budget'!P450/10^6 -> 0 | Z40: =IFERROR(SUM(V40:Y40),"") -> 15.166 | AA40: ='GFS 2025_26 Budget'!R450/10^6 -> 15.1398 | AB40: ='GFS 2025_26 Budget'!S450/10^6 -> 0.0262 | AC40: ='GFS 2025_26 Budget'!T450/10^6 -> 0 | AD40: ='GFS 2025_26 Budget'!U450/10^6 -> 0 | AE40: =IFERROR(SUM(AA40:AD40),"") -> 15.166
J41: 22 | M41: Use of goods and services | N41: ='GFS 2025_26 Budget'!E579/10^6 -> 237.3093 | O41: ='GFS 2025_26 Budget'!F579/10^6 -> 313.3205 | P41: ='GFS 2025_26 Budget'!G579/10^6 -> 238.3413 | Q41: ='GFS 2025_26 Budget'!H579/10^6 -> 124.0289 | R41: ='GFS 2025_26 Budget'!I579/10^6 -> 32.7086 | S41: ='GFS 2025_26 Budget'!J579/10^6 -> 57.1428 | T41: ='GFS 2025_26 Budget'!K579/10^6 -> 41.735 | U41: =IFERROR(SUM(Q41:T41),"") -> 255.6153 | V41: ='GFS 2025_26 Budget'!M579/10^6 -> 136.1874 | W41: ='GFS 2025_26 Budget'!N579/10^6 -> 19.1151 | X41: ='GFS 2025_26 Budget'!O579/10^6 -> 43.5361 | Y41: ='GFS 2025_26 Budget'!P579/10^6 -> 55.2753 | Z41: =IFERROR(SUM(V41:Y41),"") -> 254.1139 | AA41: ='GFS 2025_26 Budget'!R579/10^6 -> 139.7958 | AB41: ='GFS 2025_26 Budget'!S579/10^6 -> 15.5067 | AC41: ='GFS 2025_26 Budget'!T579/10^6 -> 42.55525 | AD41: ='GFS 2025_26 Budget'!U579/10^6 -> 54.6542 | AE41: =IFERROR(SUM(AA41:AD41),"") -> 252.51195
A42: Discrepancy | J42: 24 | M42: Interest | N42: =SUM(N43,N44,N45) -> 6.9135733 | O42: =SUM(O43,O44,O45) -> 5.9091 | P42: =SUM(P43,P44,P45) -> 5.9278 | Q42: =SUM(Q43,Q44,Q45) -> 6.369 | R42: =SUM(R43,R44,R45) -> 1e-06 | S42: =SUM(S43,S44,S45) -> 2e-06 | T42: =SUM(T43,T44,T45) -> 3e-06 | U42: =IFERROR(SUM(Q42:T42),"") -> 6.369006 | V42: =SUM(V43,V44,V45) -> 6.369 | W42: =SUM(W43,W44,W45) -> 1e-06 | X42: =SUM(X43,X44,X45) -> 2e-06 | Y42: =SUM(Y43,Y44,Y45) -> 3e-06 | Z42: =IFERROR(SUM(V42:Y42),"") -> 6.369006 | AA42: =SUM(AA43,AA44,AA45) -> 6.369 | AB42: =SUM(AB43,AB44,AB45) -> 1e-06 | AC42: =SUM(AC43,AC44,AC45) -> 2e-06 | AD42: =SUM(AD43,AD44,AD45) -> 3e-06 | AE42: =IFERROR(SUM(AA42:AD42),"") -> 6.369006
J43: 241 | M43: To nonresidents | N43: ='GFS 2025_26 Budget'!E585/10^6 -> 4.8582383 | O43: ='GFS 2025_26 Budget'!F585/10^6 -> 3.9807 | P43: ='GFS 2025_26 Budget'!G585/10^6 -> 4.2079 | Q43: ='GFS 2025_26 Budget'!H585/10^6 -> 3.633 | R43: 0 | S43: 0 | T43: 0 | U43: =IFERROR(SUM(Q43:T43),"") -> 3.633 | V43: ='GFS 2025_26 Budget'!M585/10^6 -> 3.633 | W43: 0 | X43: 0 | Y43: 0 | Z43: =IFERROR(SUM(V43:Y43),"") -> 3.633 | AA43: ='GFS 2025_26 Budget'!R585/10^6 -> 3.633 | AB43: 0 | AC43: 0 | AD43: 0 | AE43: =IFERROR(SUM(AA43:AD43),"") -> 3.633
J44: 242 | M44: To residents other than general government | N44: ='GFS 2025_26 Budget'!E590/10^6 -> 2.055335 | O44: ='GFS 2025_26 Budget'!F590/10^6 -> 1.9284 | P44: ='GFS 2025_26 Budget'!G590/10^6 -> 1.7199 | Q44: ='GFS 2025_26 Budget'!H590/10^6 -> 2.736 | R44: ='GFS 2025_26 Budget'!I590/10^6 -> 0 | S44: ='GFS 2025_26 Budget'!J590/10^6 -> 0 | T44: ='GFS 2025_26 Budget'!K590/10^6 -> 0 | U44: =IFERROR(SUM(Q44:T44),"") -> 2.736 | V44: ='GFS 2025_26 Budget'!M590/10^6 -> 2.736 | W44: ='GFS 2025_26 Budget'!N590/10^6 -> 0 | X44: ='GFS 2025_26 Budget'!O590/10^6 -> 0 | Y44: ='GFS 2025_26 Budget'!P590/10^6 -> 0 | Z44: =IFERROR(SUM(V44:Y44),"") -> 2.736 | AA44: ='GFS 2025_26 Budget'!R590/10^6 -> 2.736 | AB44: ='GFS 2025_26 Budget'!S590/10^6 -> 0 | AC44: ='GFS 2025_26 Budget'!T590/10^6 -> 0 | AD44: ='GFS 2025_26 Budget'!U590/10^6 -> 0 | AE44: =IFERROR(SUM(AA44:AD44),"") -> 2.736
A45: Sources: Ministry of Finance. | J45: 243 | M45: To other general government units | N45: ='GFS 2025_26 Budget'!E592/10^6 -> 0 | O45: ='GFS 2025_26 Budget'!F592/10^6 -> 0 | P45: ='GFS 2025_26 Budget'!G592/10^6 -> 0 | Q45: ='GFS 2025_26 Budget'!H592/10^6 -> 0 | R45: ='GFS 2025_26 Budget'!I592/10^6 -> 1e-06 | S45: ='GFS 2025_26 Budget'!J592/10^6 -> 2e-06 | T45: ='GFS 2025_26 Budget'!K592/10^6 -> 3e-06 | U45: =IFERROR(SUM(Q45:T45),"") -> 6e-06 | V45: ='GFS 2025_26 Budget'!M592/10^6 -> 0 | W45: ='GFS 2025_26 Budget'!N592/10^6 -> 1e-06 | X45: ='GFS 2025_26 Budget'!O592/10^6 -> 2e-06 | Y45: ='GFS 2025_26 Budget'!P592/10^6 -> 3e-06 | Z45: =IFERROR(SUM(V45:Y45),"") -> 6e-06 | AA45: ='GFS 2025_26 Budget'!R592/10^6 -> 0 | AB45: ='GFS 2025_26 Budget'!S592/10^6 -> 1e-06 | AC45: ='GFS 2025_26 Budget'!T592/10^6 -> 2e-06 | AD45: ='GFS 2025_26 Budget'!U592/10^6 -> 3e-06 | AE45: =IFERROR(SUM(AA45:AD45),"") -> 6e-06
J46: 25 | M46: Subsidies | N46: =SUM(N47,N48) -> 16.59997 | O46: =SUM(O47,O48) -> 15.9138 | P46: =SUM(P47,P48) -> 18.8417 | Q46: =SUM(Q47,Q48) -> 15.8764 | R46: =SUM(R47,R48) -> 23.5137 | S46: =SUM(S47,S48) -> 0 | T46: =SUM(T47,T48) -> 0 | U46: =IFERROR(SUM(Q46:T46),"") -> 39.3901 | V46: =SUM(V47,V48) -> 11.7939 | W46: =SUM(W47,W48) -> 23.3962 | X46: =SUM(X47,X48) -> 0 | Y46: =SUM(Y47,Y48) -> 0 | Z46: =IFERROR(SUM(V46:Y46),"") -> 35.1901 | AA46: =SUM(AA47,AA48) -> 18.7346 | AB46: =SUM(AB47,AB48) -> 12.9554 | AC46: =SUM(AC47,AC48) -> 0 | AD46: =SUM(AD47,AD48) -> 0 | AE46: =IFERROR(SUM(AA46:AD46),"") -> 31.69
J47: 251 | M47: Subsidies to public corporations | N47: ='GFS 2025_26 Budget'!E597/1000000 -> 16.59997 | O47: ='GFS 2025_26 Budget'!F597/1000000 -> 15.9138 | P47: ='GFS 2025_26 Budget'!G597/1000000 -> 18.8417 | Q47: ='GFS 2025_26 Budget'!H597/10^6 -> 15.8764 | R47: ='GFS 2025_26 Budget'!I597/10^6 -> 23.5137 | S47: ='GFS 2025_26 Budget'!J597/10^6 -> 0 | T47: ='GFS 2025_26 Budget'!K597/10^6 -> 0 | U47: =IFERROR(SUM(Q47:T47),"") -> 39.3901 | V47: ='GFS 2025_26 Budget'!M597/10^6 -> 11.7939 | W47: ='GFS 2025_26 Budget'!N597/10^6 -> 23.3962 | X47: ='GFS 2025_26 Budget'!O597/10^6 -> 0 | Y47: ='GFS 2025_26 Budget'!P597/10^6 -> 0 | Z47: =IFERROR(SUM(V47:Y47),"") -> 35.1901 | AA47: ='GFS 2025_26 Budget'!R597/10^6 -> 18.7346 | AB47: ='GFS 2025_26 Budget'!S597/10^6 -> 12.9554 | AC47: ='GFS 2025_26 Budget'!T597/10^6 -> 0 | AD47: ='GFS 2025_26 Budget'!U597/10^6 -> 0 | AE47: =IFERROR(SUM(AA47:AD47),"") -> 31.69
J48: 252 | M48: Subsidies to private enterprises | N48: ='GFS 2025_26 Budget'!E609/10^6 -> 0 | O48: ='GFS 2025_26 Budget'!F609/10^6 -> 0 | P48: ='GFS 2025_26 Budget'!G609/10^6 -> 0 | Q48: ='GFS 2025_26 Budget'!H609/10^6 -> 0 | R48: ='GFS 2025_26 Budget'!I609/10^6 -> 0 | S48: ='GFS 2025_26 Budget'!J609/10^6 -> 0 | T48: ='GFS 2025_26 Budget'!K609/10^6 -> 0 | U48: =IFERROR(SUM(Q48:T48),"") -> 0 | V48: ='GFS 2025_26 Budget'!M609/10^6 -> 0 | W48: ='GFS 2025_26 Budget'!N609/10^6 -> 0 | X48: ='GFS 2025_26 Budget'!O609/10^6 -> 0 | Y48: ='GFS 2025_26 Budget'!P609/10^6 -> 0 | Z48: =IFERROR(SUM(V48:Y48),"") -> 0 | AA48: ='GFS 2025_26 Budget'!R609/10^6 -> 0 | AB48: ='GFS 2025_26 Budget'!S609/10^6 -> 0 | AC48: ='GFS 2025_26 Budget'!T609/10^6 -> 0 | AD48: ='GFS 2025_26 Budget'!U609/10^6 -> 0 | AE48: =IFERROR(SUM(AA48:AD48),"") -> 0
J49: 26 | M49: Grants | N49: =SUM(N50,N51,N52) -> 51.080591 | O49: =SUM(O50,O51,O52) -> 38.4148 | P49: =SUM(P50,P51,P52) -> 20.3225 | Q49: =SUM(Q50,Q51,Q52) -> 7.3763 | R49: =SUM(R50,R51,R52) -> 13.6406 | S49: =SUM(S50,S51,S52) -> 17.5117 | T49: =SUM(T50,T51,T52) -> 2.8701 | U49: =IFERROR(SUM(Q49:T49),"") -> 41.3987 | V49: =SUM(V50,V51,V52) -> 11.5364 | W49: =SUM(W50,W51,W52) -> 9.4805 | X49: =SUM(X50,X51,X52) -> 4.1 | Y49: =SUM(Y50,Y51,Y52) -> 3.1951 | Z49: =IFERROR(SUM(V49:Y49),"") -> 28.312 | AA49: =SUM(AA50,AA51,AA52) -> 18.6349 | AB49: =SUM(AB50,AB51,AB52) -> 2.382 | AC49: =SUM(AC50,AC51,AC52) -> 4.1 | AD49: =SUM(AD50,AD51,AD52) -> 3.1951 | AE49: =IFERROR(SUM(AA49:AD49),"") -> 28.312
J50: 261 | M50: To foreign governments | N50: ='GFS 2025_26 Budget'!E619 -> 0 | O50: ='GFS 2025_26 Budget'!F619 -> 0 | P50: ='GFS 2025_26 Budget'!G619 -> 0 | Q50: ='GFS 2025_26 Budget'!H619 -> 0 | R50: ='GFS 2025_26 Budget'!I619 -> 0 | S50: ='GFS 2025_26 Budget'!J619 -> 0 | T50: ='GFS 2025_26 Budget'!K619 -> 0 | U50: =IFERROR(SUM(Q50:T50),"") -> 0 | V50: ='GFS 2025_26 Budget'!M619 -> 0 | W50: ='GFS 2025_26 Budget'!N619 -> 0 | X50: ='GFS 2025_26 Budget'!O619 -> 0 | Y50: ='GFS 2025_26 Budget'!P619 -> 0 | Z50: =IFERROR(SUM(V50:Y50),"") -> 0 | AA50: ='GFS 2025_26 Budget'!R619 -> 0 | AB50: ='GFS 2025_26 Budget'!S619 -> 0 | AC50: ='GFS 2025_26 Budget'!T619 -> 0 | AD50: ='GFS 2025_26 Budget'!U619 -> 0 | AE50: =IFERROR(SUM(AA50:AD50),"") -> 0
J51: 262 | M51: To international organizations | N51: ='GFS 2025_26 Budget'!E626/10^6 -> 51.080591 | O51: ='GFS 2025_26 Budget'!F626/10^6 -> 38.4148 | P51: ='GFS 2025_26 Budget'!G626/10^6 -> 20.3225 | Q51: ='GFS 2025_26 Budget'!H626/10^6 -> 7.3763 | R51: ='GFS 2025_26 Budget'!I626/10^6 -> 13.6406 | S51: ='GFS 2025_26 Budget'!J626/10^6 -> 17.5117 | T51: ='GFS 2025_26 Budget'!K626/10^6 -> 2.8701 | U51: =IFERROR(SUM(Q51:T51),"") -> 41.3987 | V51: ='GFS 2025_26 Budget'!M626/10^6 -> 11.5364 | W51: ='GFS 2025_26 Budget'!N626/10^6 -> 9.4805 | X51: ='GFS 2025_26 Budget'!O626/10^6 -> 4.1 | Y51: ='GFS 2025_26 Budget'!P626/10^6 -> 3.1951 | Z51: =IFERROR(SUM(V51:Y51),"") -> 28.312 | AA51: ='GFS 2025_26 Budget'!R626/10^6 -> 18.6349 | AB51: ='GFS 2025_26 Budget'!S626/10^6 -> 2.382 | AC51: ='GFS 2025_26 Budget'!T626/10^6 -> 4.1 | AD51: ='GFS 2025_26 Budget'!U626/10^6 -> 3.1951 | AE51: =IFERROR(SUM(AA51:AD51),"") -> 28.312
J52: 263 | M52: To other general government units | N52: ='GFS 2025_26 Budget'!E636 | O52: ='GFS 2025_26 Budget'!F636 -> 0 | P52: ='GFS 2025_26 Budget'!G636 -> 0 | Q52: ='GFS 2025_26 Budget'!H636 -> 0 | R52: ='GFS 2025_26 Budget'!I636 -> 0 | S52: ='GFS 2025_26 Budget'!J636 -> 0 | T52: ='GFS 2025_26 Budget'!K636 -> 0 | U52: =IFERROR(SUM(Q52:T52),"") -> 0 | V52: ='GFS 2025_26 Budget'!M636 -> 0 | W52: ='GFS 2025_26 Budget'!N636 -> 0 | X52: ='GFS 2025_26 Budget'!O636 -> 0 | Y52: ='GFS 2025_26 Budget'!P636 -> 0 | Z52: =IFERROR(SUM(V52:Y52),"") -> 0 | AA52: ='GFS 2025_26 Budget'!R636 -> 0 | AB52: ='GFS 2025_26 Budget'!S636 -> 0 | AC52: ='GFS 2025_26 Budget'!T636 -> 0 | AD52: ='GFS 2025_26 Budget'!U636 -> 0 | AE52: =IFERROR(SUM(AA52:AD52),"") -> 0
J53: 27 | M53: Social benefits | N53: ='GFS 2025_26 Budget'!E643/10^6 -> 31.482897 | O53: ='GFS 2025_26 Budget'!F643/10^6 -> 32.214 | P53: ='GFS 2025_26 Budget'!G643/10^6 -> 26.998 | Q53: ='GFS 2025_26 Budget'!H643/10^6 -> 6.5805 | R53: ='GFS 2025_26 Budget'!I643/10^6 -> 16.0308 | S53: ='GFS 2025_26 Budget'!J643/10^6 -> 0.5027 | T53: ='GFS 2025_26 Budget'!K643/10^6 -> 15.1362 | U53: =IFERROR(SUM(Q53:T53),"") -> 38.2502 | V53: ='GFS 2025_26 Budget'!M643/10^6 -> 5.6805 | W53: ='GFS 2025_26 Budget'!N643/10^6 -> 16.0308 | X53: ='GFS 2025_26 Budget'!O643/10^6 -> 0.9935 | Y53: ='GFS 2025_26 Budget'!P643/10^6 -> 13.2314 | Z53: =IFERROR(SUM(V53:Y53),"") -> 35.9362 | AA53: ='GFS 2025_26 Budget'!R643/10^6 -> 9.0285 | AB53: ='GFS 2025_26 Budget'!S643/10^6 -> 12.6828 | AC53: ='GFS 2025_26 Budget'!T643/10^6 -> 1.14445 | AD53: ='GFS 2025_26 Budget'!U643/10^6 -> 13.2314 | AE53: =IFERROR(SUM(AA53:AD53),"") -> 36.08715
J54: 28 | M54: Other expense | N54: =SUM(N55,N56) -> 13.49945 | O54: =SUM(O55,O56) -> 17.8256 | P54: =SUM(P55,P56) -> 17.3619 | Q54: =SUM(Q55,Q56) -> 13.3859 | R54: =SUM(R55,R56) -> 3.0618 | S54: =SUM(S55,S56) -> 0.6112 | T54: =SUM(T55,T56) -> 1 | U54: =IFERROR(SUM(Q54:T54),"") -> 18.0589 | V54: =SUM(V55,V56) -> 13.3859 | W54: =SUM(W55,W56) -> 3.0618 | X54: =SUM(X55,X56) -> 0.02 | Y54: =SUM(Y55,Y56) -> 1 | Z54: =IFERROR(SUM(V54:Y54),"") -> 17.4677 | AA54: =SUM(AA55,AA56) -> 13.4477 | AB54: =SUM(AB55,AB56) -> 3 | AC54: =SUM(AC55,AC56) -> 0.02 | AD54: =SUM(AD55,AD56) -> 1 | AE54: =IFERROR(SUM(AA54:AD54),"") -> 17.4677
J55: 281 | M55: Property expense other than interest | N55: ='GFS 2025_26 Budget'!E661 | O55: ='GFS 2025_26 Budget'!F661 -> 0 | P55: ='GFS 2025_26 Budget'!G661 -> 0 | Q55: ='GFS 2025_26 Budget'!H661 -> 0 | R55: ='GFS 2025_26 Budget'!I661 -> 0 | S55: ='GFS 2025_26 Budget'!J661 -> 0 | T55: ='GFS 2025_26 Budget'!K661 -> 0 | U55: =IFERROR(SUM(Q55:T55),"") -> 0 | V55: ='GFS 2025_26 Budget'!M661 -> 0 | W55: ='GFS 2025_26 Budget'!N661 -> 0 | X55: ='GFS 2025_26 Budget'!O661 -> 0 | Y55: ='GFS 2025_26 Budget'!P661 -> 0 | Z55: =IFERROR(SUM(V55:Y55),"") -> 0 | AA55: ='GFS 2025_26 Budget'!R661 -> 0 | AB55: ='GFS 2025_26 Budget'!S661 -> 0 | AC55: ='GFS 2025_26 Budget'!T661 -> 0 | AD55: ='GFS 2025_26 Budget'!U661 -> 0 | AE55: =IFERROR(SUM(AA55:AD55),"") -> 0
J56: 282 | M56: Transfer not elswhere | N56: ='GFS 2025_26 Budget'!E674/10^6 -> 13.49945 | O56: ='GFS 2025_26 Budget'!F674/10^6 -> 17.8256 | P56: ='GFS 2025_26 Budget'!G674/10^6 -> 17.3619 | Q56: ='GFS 2025_26 Budget'!H674/10^6 -> 13.3859 | R56: ='GFS 2025_26 Budget'!I674/10^6 -> 3.0618 | S56: ='GFS 2025_26 Budget'!J674/10^6 -> 0.6112 | T56: ='GFS 2025_26 Budget'!K674/10^6 -> 1 | U56: =IFERROR(SUM(Q56:T56),"") -> 18.0589 | V56: ='GFS 2025_26 Budget'!M674/10^6 -> 13.3859 | W56: ='GFS 2025_26 Budget'!N674/10^6 -> 3.0618 | X56: ='GFS 2025_26 Budget'!O674/10^6 -> 0.02 | Y56: ='GFS 2025_26 Budget'!P674/10^6 -> 1 | Z56: =IFERROR(SUM(V56:Y56),"") -> 17.4677 | AA56: ='GFS 2025_26 Budget'!R674/10^6 -> 13.4477 | AB56: ='GFS 2025_26 Budget'!S674/10^6 -> 3 | AC56: ='GFS 2025_26 Budget'!T674/10^6 -> 0.02 | AD56: ='GFS 2025_26 Budget'!U674/10^6 -> 1 | AE56: =IFERROR(SUM(AA56:AD56),"") -> 17.4677
U57: =IFERROR(SUM(Q57:T57),"") -> 0 | Z57: =IFERROR(SUM(V57:Y57),"") -> 0 | AE57: =IFERROR(SUM(AA57:AD57),"") -> 0
M58: Total Domestic Revenue | N58: =SUM(N31,N11) -> 384.34132 | O58: =SUM(O31,O11) -> 420.488 | P58: =SUM(P31,P11) -> 404.5206 | Q58: =SUM(Q31,Q11) -> 412.1464 | R58: =SUM(R31,R11) -> 0 | S58: =SUM(S31,S11) -> 0.0045 | T58: =SUM(T31,T11) -> 1.5 | U58: =IFERROR(SUM(Q58:T58),"") -> 413.6509 | V58: =SUM(V31,V11) -> 459.5129 | W58: =SUM(W31,W11) -> 0 | X58: =SUM(X31,X11) -> 0.0001 | Y58: =SUM(Y31,Y11) -> 1.5 | Z58: =IFERROR(SUM(V58:Y58),"") -> 461.013 | AA58: =SUM(AA31,AA11) -> 483.2927 | AB58: =SUM(AB31,AB11) -> 0 | AC58: =SUM(AC31,AC11) -> 0.0001 | AD58: =SUM(AD31,AD11) -> 1.5 | AE58: =IFERROR(SUM(AA58:AD58),"") -> 484.7928
M59: GROSS OPERATING BALANCE | N59: =N10-N37 -> 269.87878 | O59: =O10-O37 -> 312.3351 | P59: =P10-P37 -> 271.6444 | Q59: =Q10-Q37 -> 43.9839 | R59: =R10-R37 -> 13.513999 | S59: =S10-S37 -> 56.948798 | T59: =T10-T37 -> 153.1222 | U59: =IFERROR(SUM(Q59:T59),"") -> 267.56889 | V59: =V10-V37 -> 74.3883 | W59: =W10-W37 -> 9.713999 | X59: =X10-X37 -> 56.946598 | Y59: =Y10-Y37 -> 160.724 | Z59: =IFERROR(SUM(V59:Y59),"") -> 301.77289 | AA59: =AA10-AA37 -> 74.065 | AB59: =AB10-AB37 -> 0.713999 | AC59: =AC10-AC37 -> 31.441298 | AD59: =AD10-AD37 -> 71.354397 | AE59: =IFERROR(SUM(AA59:AD59),"") -> 177.57469
U60: =IFERROR(SUM(Q60:T60),"") -> 0 | Z60: =IFERROR(SUM(V60:Y60),"") -> 0 | AE60: =IFERROR(SUM(AA60:AD60),"") -> 0
J61: 31 | M61: NET ACQUISITION OF NONFINANCIAL ASSETS | N61: =SUM(N64,N69) -> 250.30083 | O61: =SUM(O64,O69) -> 256.8693 | P61: =SUM(P64,P69) -> 215.4902 | Q61: =SUM(Q64,Q69) -> 44.2652 | R61: =SUM(R64,R69) -> 13.513999 | S61: =SUM(S64,S69) -> 56.948798 | T61: =SUM(T64,T69) -> 153.1222 | U61: =IFERROR(SUM(Q61:T61),"") -> 267.85019 | V61: =SUM(V64,V69) -> 33.958 | W61: =SUM(W64,W69) -> 9.713999 | X61: =SUM(X64,X69) -> 56.946598 | Y61: =SUM(Y64,Y69) -> 160.724 | Z61: =IFERROR(SUM(V61:Y61),"") -> 261.34259 | AA61: =SUM(AA64,AA69) -> 23.9481 | AB61: =SUM(AB64,AB69) -> 0.713999 | AC61: =SUM(AC64,AC69) -> 31.441298 | AD61: =SUM(AD64,AD69) -> 71.354397 | AE61: =IFERROR(SUM(AA61:AD61),"") -> 127.45779
M62: Inflow | N62: =ROUND('GFS 2025_26 Budget'!E697/10^6,1) -> 246.7 | O62: =ROUND('GFS 2025_26 Budget'!F697/10^6,1) -> 252.8 | P62: =ROUND('GFS 2025_26 Budget'!G697/10^6,1) -> 213.5 | Q62: =ROUND('GFS 2025_26 Budget'!H697/10^6,1) -> 42.8 | R62: =ROUND('GFS 2025_26 Budget'!I697/10^6,1) -> 13.5 | S62: =ROUND('GFS 2025_26 Budget'!J697/10^6,1) -> 56.9 | T62: =ROUND('GFS 2025_26 Budget'!K697/10^6,1) -> 153.1 | U62: =IFERROR(SUM(Q62:T62),"") -> 266.3 | V62: =ROUND('GFS 2025_26 Budget'!M697/10^6,1) -> 32.5 | W62: =ROUND('GFS 2025_26 Budget'!N697/10^6,1) -> 9.7 | X62: =ROUND('GFS 2025_26 Budget'!O697/10^6,1) -> 56.9 | Y62: =ROUND('GFS 2025_26 Budget'!P697/10^6,1) -> 160.7 | Z62: =IFERROR(SUM(V62:Y62),"") -> 259.8 | AA62: =ROUND('GFS 2025_26 Budget'!R697/10^6,1) -> 22.5 | AB62: =ROUND('GFS 2025_26 Budget'!S697/10^6,1) -> 0.7 | AC62: =ROUND('GFS 2025_26 Budget'!T697/10^6,1) -> 31.4 | AD62: =ROUND('GFS 2025_26 Budget'!U697/10^6,1) -> 71.4 | AE62: =IFERROR(SUM(AA62:AD62),"") -> 126
M63: Outflow | N63: =ROUND('GFS 2025_26 Budget'!E698/10^6,1) -> 0.1 | O63: =ROUND('GFS 2025_26 Budget'!F698/10^6,1) -> 0.1 | P63: =ROUND('GFS 2025_26 Budget'!G698/10^6,1) -> 0.1 | Q63: =ROUND('GFS 2025_26 Budget'!H698/10^6,1) -> 0.1 | R63: =ROUND('GFS 2025_26 Budget'!I698/10^6,1) -> 0 | S63: =ROUND('GFS 2025_26 Budget'!J698/10^6,1) -> 0 | T63: =ROUND('GFS 2025_26 Budget'!K698/10^6,1) -> 0 | U63: =IFERROR(SUM(Q63:T63),"") -> 0.1 | V63: =ROUND('GFS 2025_26 Budget'!M698/10^6,1) -> 0.1 | W63: =ROUND('GFS 2025_26 Budget'!N698/10^6,1) -> 0 | X63: =ROUND('GFS 2025_26 Budget'!O698/10^6,1) -> 0 | Y63: =ROUND('GFS 2025_26 Budget'!P698/10^6,1) -> 0 | Z63: =IFERROR(SUM(V63:Y63),"") -> 0.1 | AA63: =ROUND('GFS 2025_26 Budget'!R698/10^6,1) -> 0.1 | AB63: =ROUND('GFS 2025_26 Budget'!S698/10^6,1) -> 0 | AC63: =ROUND('GFS 2025_26 Budget'!T698/10^6,1) -> 0 | AD63: =ROUND('GFS 2025_26 Budget'!U698/10^6,1) -> 0 | AE63: =IFERROR(SUM(AA63:AD63),"") -> 0.1
J64: 311 | M64: Fixed assets (net) | N64: =SUM(N65:N67) -> 246.6411 | O64: =SUM(O65:O67) -> 252.7791 | P64: =SUM(P65:P67) -> 213.3672 | Q64: =SUM(Q65:Q67) -> 42.6501 | R64: =SUM(R65:R67) -> 13.514 | S64: =SUM(S65:S67) -> 56.9488 | T64: =SUM(T65:T67) -> 153.1222 | U64: =IFERROR(SUM(Q64:T64),"") -> 266.2351 | V64: =SUM(V65:V67) -> 32.3429 | W64: =SUM(W65:W67) -> 9.714 | X64: =SUM(X65:X67) -> 56.9466 | Y64: =SUM(Y65:Y67) -> 160.724 | Z64: =IFERROR(SUM(V64:Y64),"") -> 259.7275 | AA64: =SUM(AA65:AA67) -> 22.333 | AB64: =SUM(AB65:AB67) -> 0.714 | AC64: =SUM(AC65:AC67) -> 31.4413 | AD64: =SUM(AD65:AD67) -> 71.3544 | AE64: =IFERROR(SUM(AA64:AD64),"") -> 125.8427
M65: Building and structures (net) | N65: ='GFS 2025_26 Budget'!E699/10^6 -> 133.43278 | O65: ='GFS 2025_26 Budget'!F699/10^6 -> 145.2934 | P65: ='GFS 2025_26 Budget'!G699/10^6 -> 150.4788 | Q65: ='GFS 2025_26 Budget'!H699/10^6 -> 30.0563 | R65: ='GFS 2025_26 Budget'!I699/10^6 -> 12.91 | S65: ='GFS 2025_26 Budget'!J699/10^6 -> 48.9034 | T65: ='GFS 2025_26 Budget'!K699/10^6 -> 134.5218 | U65: =IFERROR(SUM(Q65:T65),"") -> 226.3915 | V65: ='GFS 2025_26 Budget'!M699/10^6 -> 16.1406 | W65: ='GFS 2025_26 Budget'!N699/10^6 -> 9.11 | X65: ='GFS 2025_26 Budget'!O699/10^6 -> 47.7477 | Y65: ='GFS 2025_26 Budget'!P699/10^6 -> 127.1755 | Z65: =IFERROR(SUM(V65:Y65),"") -> 200.1738 | AA65: ='GFS 2025_26 Budget'!R699/10^6 -> 5.6406 | AB65: ='GFS 2025_26 Budget'!S699/10^6 -> 0.61 | AC65: ='GFS 2025_26 Budget'!T699/10^6 -> 24.7476 | AD65: ='GFS 2025_26 Budget'!U699/10^6 -> 47.5148 | AE65: =IFERROR(SUM(AA65:AD65),"") -> 78.513
M66: Machinery and equipment (net) | N66: ='GFS 2025_26 Budget'!E716/10^6-'GFS 2025_26 Budget'!E737/10^6 -> 81.905013 | O66: ='GFS 2025_26 Budget'!F716/10^6-'GFS 2025_26 Budget'!F737/10^6 -> 102.5068 | P66: ='GFS 2025_26 Budget'!G716/10^6-'GFS 2025_26 Budget'!G737/10^6 -> 57.898 | Q66: ='GFS 2025_26 Budget'!H716/10^6-'GFS 2025_26 Budget'!H737/10^6 -> 7.9949 | R66: ='GFS 2025_26 Budget'!I716/10^6-'GFS 2025_26 Budget'!I737/10^6 -> 0.5 | S66: ='GFS 2025_26 Budget'!J716/10^6-'GFS 2025_26 Budget'!J737/10^6 -> 6.0881 | T66: ='GFS 2025_26 Budget'!K716/10^6-'GFS 2025_26 Budget'!K737/10^6 -> 15.4609 | U66: =IFERROR(SUM(Q66:T66),"") -> 30.0439 | V66: ='GFS 2025_26 Budget'!M716/10^6-'GFS 2025_26 Budget'!M737/10^6 -> 11.6034 | W66: ='GFS 2025_26 Budget'!N716/10^6-'GFS 2025_26 Budget'!N737/10^6 -> 0.5 | X66: ='GFS 2025_26 Budget'!O716/10^6-'GFS 2025_26 Budget'!O737/10^6 -> 7.2416 | Y66: ='GFS 2025_26 Budget'!P716/10^6-'GFS 2025_26 Budget'!P737/10^6 -> 32.341 | Z66: =IFERROR(SUM(V66:Y66),"") -> 51.686 | AA66: ='GFS 2025_26 Budget'!R716/10^6-'GFS 2025_26 Budget'!R737/10^6 -> 12.0935 | AB66: ='GFS 2025_26 Budget'!S716/10^6-'GFS 2025_26 Budget'!S737/10^6 -> 0 | AC66: ='GFS 2025_26 Budget'!T716/10^6-'GFS 2025_26 Budget'!T737/10^6 -> 4.7364 | AD66: ='GFS 2025_26 Budget'!U716/10^6-'GFS 2025_26 Budget'!U737/10^6 -> 23.8396 | AE66: =IFERROR(SUM(AA66:AD66),"") -> 40.6695
M67: Other fixed assets (net) | N67: ='GFS 2025_26 Budget'!E746/10^6 -> 31.303315 | O67: ='GFS 2025_26 Budget'!F746/10^6 -> 4.9789 | P67: ='GFS 2025_26 Budget'!G746/10^6 -> 4.9904 | Q67: ='GFS 2025_26 Budget'!H746/10^6 -> 4.5989 | R67: ='GFS 2025_26 Budget'!I746/10^6 -> 0.104 | S67: ='GFS 2025_26 Budget'!J746/10^6 -> 1.9573 | T67: ='GFS 2025_26 Budget'!K746/10^6 -> 3.1395 | U67: =IFERROR(SUM(Q67:T67),"") -> 9.7997 | V67: ='GFS 2025_26 Budget'!M746/10^6 -> 4.5989 | W67: ='GFS 2025_26 Budget'!N746/10^6 -> 0.104 | X67: ='GFS 2025_26 Budget'!O746/10^6 -> 1.9573 | Y67: ='GFS 2025_26 Budget'!P746/10^6 -> 1.2075 | Z67: =IFERROR(SUM(V67:Y67),"") -> 7.8677 | AA67: ='GFS 2025_26 Budget'!R746/10^6 -> 4.5989 | AB67: ='GFS 2025_26 Budget'!S746/10^6 -> 0.104 | AC67: ='GFS 2025_26 Budget'!T746/10^6 -> 1.9573 | AD67: ='GFS 2025_26 Budget'!U746/10^6 -> 0 | AE67: =IFERROR(SUM(AA67:AD67),"") -> 6.6602
U68: =IFERROR(SUM(Q68:T68),"") -> 0 | Z68: =IFERROR(SUM(V68:Y68),"") -> 0 | AE68: =IFERROR(SUM(AA68:AD68),"") -> 0
J69: 314 | M69: Nonproduced assets (net) | N69: =SUM('GFS 2025_26 Budget'!E766-'GFS 2025_26 Budget'!E774)/10^6 -> 3.6597241 | O69: =SUM('GFS 2025_26 Budget'!F766-'GFS 2025_26 Budget'!F774)/10^6 -> 4.0902 | P69: =SUM('GFS 2025_26 Budget'!G766-'GFS 2025_26 Budget'!G774)/10^6 -> 2.123 | Q69: =SUM('GFS 2025_26 Budget'!H766-'GFS 2025_26 Budget'!H774)/10^6 -> 1.6151 | R69: =SUM('GFS 2025_26 Budget'!I766-'GFS 2025_26 Budget'!I774)/10^6 -> -1e-06 | S69: =SUM('GFS 2025_26 Budget'!J766-'GFS 2025_26 Budget'!J774)/10^6 -> -2e-06 | T69: =SUM('GFS 2025_26 Budget'!K766-'GFS 2025_26 Budget'!K774)/10^6 -> -3e-06 | U69: =IFERROR(SUM(Q69:T69),"") -> 1.615094 | V69: =SUM('GFS 2025_26 Budget'!M766-'GFS 2025_26 Budget'!M774)/10^6 -> 1.6151 | W69: =SUM('GFS 2025_26 Budget'!N766-'GFS 2025_26 Budget'!N774)/10^6 -> -1e-06 | X69: =SUM('GFS 2025_26 Budget'!O766-'GFS 2025_26 Budget'!O774)/10^6 -> -2e-06 | Y69: =SUM('GFS 2025_26 Budget'!P766-'GFS 2025_26 Budget'!P774)/10^6 -> -3e-06 | Z69: =IFERROR(SUM(V69:Y69),"") -> 1.615094 | AA69: =SUM('GFS 2025_26 Budget'!R766-'GFS 2025_26 Budget'!R774)/10^6 -> 1.6151 | AB69: =SUM('GFS 2025_26 Budget'!S766-'GFS 2025_26 Budget'!S774)/10^6 -> -1e-06 | AC69: =SUM('GFS 2025_26 Budget'!T766-'GFS 2025_26 Budget'!T774)/10^6 -> -2e-06 | AD69: =SUM('GFS 2025_26 Budget'!U766-'GFS 2025_26 Budget'!U774)/10^6 -> -3e-06 | AE69: =IFERROR(SUM(AA69:AD69),"") -> 1.615094
M70: Inflow | N70: ='GFS 2025_26 Budget'!E763/10^6 -> 3.6597241 | O70: ='GFS 2025_26 Budget'!F763/10^6 -> 4.0902 | P70: ='GFS 2025_26 Budget'!G763/10^6 -> 2.123 | Q70: ='GFS 2025_26 Budget'!H763/10^6 -> 1.6151 | R70: ='GFS 2025_26 Budget'!I763/10^6 -> 0 | S70: ='GFS 2025_26 Budget'!J763/10^6 -> 0 | T70: ='GFS 2025_26 Budget'!K763/10^6 -> 0 | U70: =IFERROR(SUM(Q70:T70),"") -> 1.6151 | V70: =ROUND('GFS 2025_26 Budget'!M763/10^6,1) -> 1.6 | W70: =ROUND('GFS 2025_26 Budget'!N763/10^6,1) -> 0 | X70: =ROUND('GFS 2025_26 Budget'!O763/10^6,1) -> 0 | Y70: =ROUND('GFS 2025_26 Budget'!P763/10^6,1) -> 0 | Z70: =IFERROR(SUM(V70:Y70),"") -> 1.6 | AA70: =ROUND('GFS 2025_26 Budget'!R763/10^6,1) -> 1.6 | AB70: =ROUND('GFS 2025_26 Budget'!S763/10^6,1) -> 0 | AC70: =ROUND('GFS 2025_26 Budget'!T763/10^6,1) -> 0 | AD70: =ROUND('GFS 2025_26 Budget'!U763/10^6,1) -> 0 | AE70: =IFERROR(SUM(AA70:AD70),"") -> 1.6
M71: Outflow | N71: =ROUND('GFS 2025_26 Budget'!E764/10^6,1) -> 0 | O71: =ROUND('GFS 2025_26 Budget'!F764/10^6,1) -> 0 | P71: =ROUND('GFS 2025_26 Budget'!G764/10^6,1) -> 0 | Q71: =ROUND('GFS 2025_26 Budget'!H764/10^6,1) -> 0 | R71: =ROUND('GFS 2025_26 Budget'!I764/10^6,1) -> 0 | S71: =ROUND('GFS 2025_26 Budget'!J764/10^6,1) -> 0 | T71: =ROUND('GFS 2025_26 Budget'!K764/10^6,1) -> 0 | U71: =IFERROR(SUM(Q71:T71),"") -> 0 | V71: =ROUND('GFS 2025_26 Budget'!M764/10^6,1) -> 0 | W71: =ROUND('GFS 2025_26 Budget'!N764/10^6,1) -> 0 | X71: =ROUND('GFS 2025_26 Budget'!O764/10^6,1) -> 0 | Y71: =ROUND('GFS 2025_26 Budget'!P764/10^6,1) -> 0 | Z71: =IFERROR(SUM(V71:Y71),"") -> 0 | AA71: =ROUND('GFS 2025_26 Budget'!R764/10^6,1) -> 0 | AB71: =ROUND('GFS 2025_26 Budget'!S764/10^6,1) -> 0 | AC71: =ROUND('GFS 2025_26 Budget'!T764/10^6,1) -> 0 | AD71: =ROUND('GFS 2025_26 Budget'!U764/10^6,1) -> 0 | AE71: =IFERROR(SUM(AA71:AD71),"") -> 0
M72: Total Expenditures | N72: =SUM(N37,N62) -> 787.78415 | O72: =SUM(O37,O62) -> 870.221 | P72: =SUM(P37,P62) -> 733.2125 | Q72: =SUM(Q37,Q62) -> 410.9625 | R72: =SUM(R37,R62) -> 117.9969 | S72: =SUM(S37,S62) -> 133.035 | T72: =SUM(T37,T62) -> 214.135 | U72: =IFERROR(SUM(Q72:T72),"") -> 876.12941 | V72: =SUM(V37,V62) -> 417.6246 | W72: =SUM(W37,W62) -> 86.939001 | X72: =SUM(X37,X62) -> 105.7892 | Y72: =SUM(Y37,Y62) -> 233.8155 | Z72: =IFERROR(SUM(V72:Y72),"") -> 844.16831 | AA72: =SUM(AA37,AA62) -> 431.7277 | AB72: =SUM(AB37,AB62) -> 47.515101 | AC72: =SUM(AC37,AC62) -> 79.463302 | AD72: =SUM(AD37,AD62) -> 143.8944 | AE72: =IFERROR(SUM(AA72:AD72),"") -> 702.60051
M73: NET LENDING/BORROWING REQUIREMENT | N73: ='GFS 2025_26 Budget'!E810/10^6 -> 19.577951 | O73: ='GFS 2025_26 Budget'!F810/10^6 -> 55.4658 | P73: ='GFS 2025_26 Budget'!G810/10^6 -> 56.1542 | Q73: ='GFS 2025_26 Budget'!H810/10^6 -> -0.2813 | R73: ='GFS 2025_26 Budget'!I810/10^6 -> 0 | S73: ='GFS 2025_26 Budget'!J810/10^6 -> 0 | T73: ='GFS 2025_26 Budget'!K810/10^6 -> 0 | U73: =IFERROR(SUM(Q73:T73),"") -> -0.2813 | V73: ='GFS 2025_26 Budget'!M810/10^6 -> 40.4303 | W73: ='GFS 2025_26 Budget'!N810/10^6 -> 0 | X73: ='GFS 2025_26 Budget'!O810/10^6 -> 0 | Y73: ='GFS 2025_26 Budget'!P810/10^6 -> 0 | Z73: =IFERROR(SUM(V73:Y73),"") -> 40.4303 | AA73: ='GFS 2025_26 Budget'!R810/10^6 -> 50.1169 | AB73: ='GFS 2025_26 Budget'!S810/10^6 -> 0 | AC73: ='GFS 2025_26 Budget'!T810/10^6 -> 0 | AD73: ='GFS 2025_26 Budget'!U810/10^6 -> 0 | AE73: =IFERROR(SUM(AA73:AD73),"") -> 50.1169
N74: 0 | O74: =O73+O75 -> 0 | P74: 0 | Q74: =Q73+Q75 -> 0 | R74: =R73+R75 -> 0 | S74: =S73+S75 -> 0 | T74: =T73+T75 -> 0 | U74: =IFERROR(SUM(Q74:T74),"") -> 0 | V74: =V73+V75 -> 0 | W74: =W73+W75 -> 0 | X74: =X73+X75 -> 0 | Y74: =Y73+Y75 -> 0 | Z74: =IFERROR(SUM(V74:Y74),"") -> 0 | AA74: =AA73+AA75 -> 0 | AB74: =AB73+AB75 -> 0 | AC74: =AC73+AC75 -> 0 | AD74: =AD73+AD75 -> 0 | AE74: =IFERROR(SUM(AA74:AD74),"") -> 0
M75: NET ACQ. OF FINANCIAL ASSETS & LIABILITIES (FINANCING) | N75: ='GFS 2025_26 Budget'!E812/10^6 -> -19.577951 | O75: ='GFS 2025_26 Budget'!F812/10^6 -> -55.4658 | P75: ='GFS 2025_26 Budget'!G812/10^6 -> -56.1542 | Q75: ='GFS 2025_26 Budget'!H812/10^6 -> 0.2813 | R75: ='GFS 2025_26 Budget'!I812/10^6 -> 0 | S75: ='GFS 2025_26 Budget'!J812/10^6 -> 0 | T75: ='GFS 2025_26 Budget'!K812/10^6 -> 0 | U75: =IFERROR(SUM(Q75:T75),"") -> 0.2813 | V75: ='GFS 2025_26 Budget'!M812/10^6 -> -40.4303 | W75: ='GFS 2025_26 Budget'!N812/10^6 -> 0 | X75: ='GFS 2025_26 Budget'!O812/10^6 -> 0 | Y75: ='GFS 2025_26 Budget'!P812/10^6 -> 0 | Z75: =IFERROR(SUM(V75:Y75),"") -> -40.4303 | AA75: ='GFS 2025_26 Budget'!R812/10^6 -> -50.1169 | AB75: ='GFS 2025_26 Budget'!S812/10^6 -> 0 | AC75: ='GFS 2025_26 Budget'!T812/10^6 -> 0 | AD75: ='GFS 2025_26 Budget'!U812/10^6 -> 0 | AE75: =IFERROR(SUM(AA75:AD75),"") -> -50.1169
U76: =IFERROR(SUM(Q76:T76),"") -> 0 | Z76: =IFERROR(SUM(V76:Y76),"") -> 0 | AE76: =IFERROR(SUM(AA76:AD76),"") -> 0
J77: 32 | M77: NET ACQUISITION OF FINANCIAL ASSETS | N77: =SUM(N78,N83) -> 28.527509 | O77: =SUM(O78,O83) -> -37.0588 | P77: =SUM(P78,P83) -> -27.6333 | Q77: =SUM(Q78,Q83) -> 16.507 | R77: =SUM(R78,R83) -> 0 | S77: =SUM(S78,S83) -> 0 | T77: =SUM(T78,T83) -> 0 | U77: =IFERROR(SUM(Q77:T77),"") -> 16.507 | V77: =SUM(V78,V83) -> 4.7954 | W77: =SUM(W78,W83) -> 0 | X77: =SUM(X78,X83) -> 0 | Y77: =SUM(Y78,Y83) -> 0 | Z77: =IFERROR(SUM(V77:Y77),"") -> 4.7954 | AA77: =SUM(AA78,AA83) -> 1.1088 | AB77: =SUM(AB78,AB83) -> 0 | AC77: =SUM(AC78,AC83) -> 0 | AD77: =SUM(AD78,AD83) -> 0 | AE77: =IFERROR(SUM(AA77:AD77),"") -> 1.1088
J78: 321 | M78: Domestic | N78: =SUM(N79:N82) -> 28.527509 | O78: =SUM(O79:O82) -> -37.0588 | P78: =SUM(P79:P82) -> -27.6333 | Q78: =SUM(Q79:Q82) -> 16.507 | R78: =SUM(R79:R82) -> 0 | S78: =SUM(S79:S82) -> 0 | T78: =SUM(T79:T82) -> 0 | U78: =IFERROR(SUM(Q78:T78),"") -> 16.507 | V78: =SUM(V79:V82) -> 4.7954 | W78: =SUM(W79:W82) -> 0 | X78: =SUM(X79:X82) -> 0 | Y78: =SUM(Y79:Y82) -> 0 | Z78: =IFERROR(SUM(V78:Y78),"") -> 4.7954 | AA78: =SUM(AA79:AA82) -> 1.1088 | AB78: =SUM(AB79:AB82) -> 0 | AC78: =SUM(AC79:AC82) -> 0 | AD78: =SUM(AD79:AD82) -> 0 | AE78: =IFERROR(SUM(AA78:AD78),"") -> 1.1088
M79: Currency and deposits | N79: ='GFS 2025_26 Budget'!E816/10^6 -> 19.529362 | O79: ='GFS 2025_26 Budget'!F816/10^6 -> -57.3486 | P79: ='GFS 2025_26 Budget'!G816/10^6 -> -27.9922 | Q79: ='GFS 2025_26 Budget'!H816/10^6 -> 2.7362 | R79: ='GFS 2025_26 Budget'!I816/10^6 -> 0 | S79: ='GFS 2025_26 Budget'!J816/10^6 -> 0 | T79: ='GFS 2025_26 Budget'!K816/10^6 -> 0 | U79: =IFERROR(SUM(Q79:T79),"") -> 2.7362 | V79: ='GFS 2025_26 Budget'!M816/10^6 -> 4.5246 | W79: ='GFS 2025_26 Budget'!N816/10^6 -> 0 | X79: ='GFS 2025_26 Budget'!O816/10^6 -> 0 | Y79: ='GFS 2025_26 Budget'!P816/10^6 -> 0 | Z79: =IFERROR(SUM(V79:Y79),"") -> 4.5246 | AA79: ='GFS 2025_26 Budget'!R816/10^6 -> 0.838 | AB79: ='GFS 2025_26 Budget'!S816/10^6 -> 0 | AC79: ='GFS 2025_26 Budget'!T816/10^6 -> 0 | AD79: ='GFS 2025_26 Budget'!U816/10^6 -> 0 | AE79: =IFERROR(SUM(AA79:AD79),"") -> 0.838
M80: Debt securities | N80: ='GFS 2025_26 Budget'!E871/10^6 -> 0 | O80: ='GFS 2025_26 Budget'!F871/10^6 -> 0 | P80: ='GFS 2025_26 Budget'!G871/10^6 -> 0 | U80: =IFERROR(SUM(Q80:T80),"") -> 0 | Z80: =IFERROR(SUM(V80:Y80),"") -> 0 | AE80: =IFERROR(SUM(AA80:AD80),"") -> 0
M81: Loans | N81: ='GFS 2025_26 Budget'!E879/10^6 -> 11.498147 | O81: ='GFS 2025_26 Budget'!F879/10^6 -> 20.3898 | P81: ='GFS 2025_26 Budget'!G879/10^6 -> 0.3889 | Q81: ='GFS 2025_26 Budget'!H879/10^6 -> 13.8708 | R81: ='GFS 2025_26 Budget'!I879/10^6 -> 0 | S81: ='GFS 2025_26 Budget'!J879/10^6 -> 0 | T81: ='GFS 2025_26 Budget'!K879/10^6 -> 0 | U81: =IFERROR(SUM(Q81:T81),"") -> 13.8708 | V81: ='GFS 2025_26 Budget'!M879/10^6 -> 0.3708 | W81: ='GFS 2025_26 Budget'!N879/10^6 -> 0 | X81: ='GFS 2025_26 Budget'!O879/10^6 -> 0 | Y81: ='GFS 2025_26 Budget'!P879/10^6 -> 0 | Z81: =IFERROR(SUM(V81:Y81),"") -> 0.3708 | AA81: ='GFS 2025_26 Budget'!R879/10^6 -> 0.3708 | AB81: ='GFS 2025_26 Budget'!S879/10^6 -> 0 | AC81: ='GFS 2025_26 Budget'!T879/10^6 -> 0 | AD81: ='GFS 2025_26 Budget'!U879/10^6 -> 0 | AE81: =IFERROR(SUM(AA81:AD81),"") -> 0.3708
M82: Equity and inveestment fund shares | N82: ='GFS 2025_26 Budget'!E887/10^6 -> -2.5 | O82: ='GFS 2025_26 Budget'!F887/10^6 -> -0.1 | P82: ='GFS 2025_26 Budget'!G887/10^6 -> -0.03 | Q82: ='GFS 2025_26 Budget'!H887/10^6 -> -0.1 | R82: ='GFS 2025_26 Budget'!I887/10^6 -> 0 | S82: ='GFS 2025_26 Budget'!J887/10^6 -> 0 | T82: ='GFS 2025_26 Budget'!K887/10^6 -> 0 | U82: =IFERROR(SUM(Q82:T82),"") -> -0.1 | V82: ='GFS 2025_26 Budget'!M887/10^6 -> -0.1 | W82: ='GFS 2025_26 Budget'!N887/10^6 -> 0 | X82: ='GFS 2025_26 Budget'!O887/10^6 -> 0 | Y82: ='GFS 2025_26 Budget'!P887/10^6 -> 0 | Z82: =IFERROR(SUM(V82:Y82),"") -> -0.1 | AA82: ='GFS 2025_26 Budget'!R887/10^6 -> -0.1 | AB82: ='GFS 2025_26 Budget'!S887/10^6 -> 0 | AC82: ='GFS 2025_26 Budget'!T887/10^6 -> 0 | AD82: ='GFS 2025_26 Budget'!U887/10^6 -> 0 | AE82: =IFERROR(SUM(AA82:AD82),"") -> -0.1
J83: 322 | M83: External | N83: ='GFS 2025_26 Budget'!E906 | O83: ='GFS 2025_26 Budget'!F906 -> 0 | P83: ='GFS 2025_26 Budget'!G906 -> 0 | Q83: ='GFS 2025_26 Budget'!H906 -> 0 | R83: ='GFS 2025_26 Budget'!I906 -> 0 | S83: ='GFS 2025_26 Budget'!J906 -> 0 | T83: ='GFS 2025_26 Budget'!K906 -> 0 | U83: =IFERROR(SUM(Q83:T83),"") -> 0 | V83: ='GFS 2025_26 Budget'!M906 -> 0 | W83: ='GFS 2025_26 Budget'!N906 -> 0 | X83: ='GFS 2025_26 Budget'!O906 -> 0 | Y83: ='GFS 2025_26 Budget'!P906 -> 0 | Z83: =IFERROR(SUM(V83:Y83),"") -> 0 | AA83: ='GFS 2025_26 Budget'!R906 -> 0 | AB83: ='GFS 2025_26 Budget'!S906 -> 0 | AC83: ='GFS 2025_26 Budget'!T906 -> 0 | AD83: ='GFS 2025_26 Budget'!U906 -> 0 | AE83: =IFERROR(SUM(AA83:AD83),"") -> 0
J84: 33 | M84: NET INCURRENCE OF LIABILITIES | N84: =SUM(N85,N89) -> -48.105461 | O84: =SUM(O85,O89) -> -18.407 | P84: =SUM(P85,P89) -> -28.5209 | Q84: =SUM(Q85,Q89) -> -16.2257 | R84: =SUM(R85,R89) -> 0 | S84: =SUM(S85,S89) -> 0 | T84: =SUM(T85,T89) -> 0 | U84: =IFERROR(SUM(Q84:T84),"") -> -16.2257 | V84: =SUM(V85,V89) -> -45.2257 | W84: =SUM(W85,W89) -> 0 | X84: =SUM(X85,X89) -> 0 | Y84: =SUM(Y85,Y89) -> 0 | Z84: =IFERROR(SUM(V84:Y84),"") -> -45.2257 | AA84: =SUM(AA85,AA89) -> -51.2257 | AB84: =SUM(AB85,AB89) -> 0 | AC84: =SUM(AC85,AC89) -> 0 | AD84: =SUM(AD85,AD89) -> 0 | AE84: =IFERROR(SUM(AA84:AD84),"") -> -51.2257
J85: 331 | M85: Domestic | N85: ='GFS 2025_26 Budget'!E948/10^6 -> -1.809 | O85: ='GFS 2025_26 Budget'!F948/10^6 -> 30 | P85: ='GFS 2025_26 Budget'!G948/10^6 -> 20.295 | Q85: ='GFS 2025_26 Budget'!H948/10^6 -> 35 | R85: ='GFS 2025_26 Budget'!I948/10^6 -> 0 | S85: ='GFS 2025_26 Budget'!J948/10^6 -> 0 | T85: ='GFS 2025_26 Budget'!K948/10^6 -> 0 | U85: =IFERROR(SUM(Q85:T85),"") -> 35 | V85: ='GFS 2025_26 Budget'!M948/10^6 -> 6 | W85: ='GFS 2025_26 Budget'!N948/10^6 -> 0 | X85: ='GFS 2025_26 Budget'!O948/10^6 -> 0 | Y85: ='GFS 2025_26 Budget'!P948/10^6 -> 0 | Z85: =IFERROR(SUM(V85:Y85),"") -> 6 | AA85: ='GFS 2025_26 Budget'!R948/10^6 -> 0 | AB85: ='GFS 2025_26 Budget'!S948/10^6 -> 0 | AC85: ='GFS 2025_26 Budget'!T948/10^6 -> 0 | AD85: ='GFS 2025_26 Budget'!U948/10^6 -> 0 | AE85: =IFERROR(SUM(AA85:AD85),"") -> 0
M86: Debt securities | N86: ='GFS 2025_26 Budget'!E957/10^6 -> 15 | O86: ='GFS 2025_26 Budget'!F957/10^6 -> 43.566 | P86: ='GFS 2025_26 Budget'!G957/10^6 -> 33.86 | Q86: ='GFS 2025_26 Budget'!H957/10^6 -> 54.872 | R86: ='GFS 2025_26 Budget'!I957/10^6 -> 0 | S86: ='GFS 2025_26 Budget'!J957/10^6 -> 0 | T86: ='GFS 2025_26 Budget'!K957/10^6 -> 0 | U86: =IFERROR(SUM(Q86:T86),"") -> 54.872 | V86: ='GFS 2025_26 Budget'!M957/10^6 -> 21.1 | W86: ='GFS 2025_26 Budget'!N957/10^6 -> 0 | X86: ='GFS 2025_26 Budget'!O957/10^6 -> 0 | Y86: ='GFS 2025_26 Budget'!P957/10^6 -> 0 | Z86: =IFERROR(SUM(V86:Y86),"") -> 21.1 | AA86: ='GFS 2025_26 Budget'!R957/10^6 -> 5.508 | AB86: ='GFS 2025_26 Budget'!S957/10^6 -> 0 | AC86: ='GFS 2025_26 Budget'!T957/10^6 -> 0 | AD86: ='GFS 2025_26 Budget'!U957/10^6 -> 0 | AE86: =IFERROR(SUM(AA86:AD86),"") -> 5.508
M87: Loans | N87: =SUM('GFS 2025_26 Budget'!E960:E961)/10^6 -> 0 | O87: =SUM('GFS 2025_26 Budget'!F960:F961)/10^6 -> 0 | P87: =SUM('GFS 2025_26 Budget'!G960:G961)/10^6 -> 0 | Q87: =SUM('GFS 2025_26 Budget'!H960:H961)/10^6 -> 0 | R87: =SUM('GFS 2025_26 Budget'!I960:I961)/10^6 -> 0 | S87: =SUM('GFS 2025_26 Budget'!J960:J961)/10^6 -> 0 | T87: =SUM('GFS 2025_26 Budget'!K960:K961)/10^6 -> 0 | U87: =IFERROR(SUM(Q87:T87),"") -> 0 | V87: =SUM('GFS 2025_26 Budget'!M960:M961)/10^6 -> 0 | W87: =SUM('GFS 2025_26 Budget'!N960:N961)/10^6 -> 0 | X87: =SUM('GFS 2025_26 Budget'!O960:O961)/10^6 -> 0 | Y87: =SUM('GFS 2025_26 Budget'!P960:P961)/10^6 -> 0 | Z87: =IFERROR(SUM(V87:Y87),"") -> 0 | AA87: =SUM('GFS 2025_26 Budget'!R960:R961)/10^6 -> 0 | AB87: =SUM('GFS 2025_26 Budget'!S960:S961)/10^6 -> 0 | AC87: =SUM('GFS 2025_26 Budget'!T960:T961)/10^6 -> 0 | AD87: =SUM('GFS 2025_26 Budget'!U960:U961)/10^6 -> 0 | AE87: =IFERROR(SUM(AA87:AD87),"") -> 0
M88: Repayments | N88: =SUM('GFS 2025_26 Budget'!E962:E963)/10^6 -> 16.809 | O88: =SUM('GFS 2025_26 Budget'!F962:F963)/10^6 -> 13.566 | P88: =SUM('GFS 2025_26 Budget'!G962:G963)/10^6 -> 13.565 | Q88: =SUM('GFS 2025_26 Budget'!H962:H963)/10^6 -> 19.872 | R88: =SUM('GFS 2025_26 Budget'!I962:I963)/10^6 -> 0 | S88: =SUM('GFS 2025_26 Budget'!J962:J963)/10^6 -> 0 | T88: =SUM('GFS 2025_26 Budget'!K962:K963)/10^6 -> 0 | U88: =IFERROR(SUM(Q88:T88),"") -> 19.872 | V88: =SUM('GFS 2025_26 Budget'!M962:M963)/10^6 -> 15.1 | W88: =SUM('GFS 2025_26 Budget'!N962:N963)/10^6 -> 0 | X88: =SUM('GFS 2025_26 Budget'!O962:O963)/10^6 -> 0 | Y88: =SUM('GFS 2025_26 Budget'!P962:P963)/10^6 -> 0 | Z88: =IFERROR(SUM(V88:Y88),"") -> 15.1 | AA88: =SUM('GFS 2025_26 Budget'!R962:R963)/10^6 -> 5.508 | AB88: =SUM('GFS 2025_26 Budget'!S962:S963)/10^6 -> 0 | AC88: =SUM('GFS 2025_26 Budget'!T962:T963)/10^6 -> 0 | AD88: =SUM('GFS 2025_26 Budget'!U962:U963)/10^6 -> 0 | AE88: =IFERROR(SUM(AA88:AD88),"") -> 5.508
J89: 332 | M89: External | N89: ='GFS 2025_26 Budget'!E979/10^6 -> -46.296461 | O89: ='GFS 2025_26 Budget'!F979/10^6 -> -48.407 | P89: ='GFS 2025_26 Budget'!G979/10^6 -> -48.8159 | Q89: ='GFS 2025_26 Budget'!H979/10^6 -> -51.2257 | R89: ='GFS 2025_26 Budget'!I979/10^6 -> 0 | S89: ='GFS 2025_26 Budget'!J979/10^6 -> 0 | T89: ='GFS 2025_26 Budget'!K979/10^6 -> 0 | U89: =IFERROR(SUM(Q89:T89),"") -> -51.2257 | V89: ='GFS 2025_26 Budget'!M979/10^6 -> -51.2257 | W89: ='GFS 2025_26 Budget'!N979/10^6 -> 0 | X89: ='GFS 2025_26 Budget'!O979/10^6 -> 0 | Y89: ='GFS 2025_26 Budget'!P979/10^6 -> 0 | Z89: =IFERROR(SUM(V89:Y89),"") -> -51.2257 | AA89: ='GFS 2025_26 Budget'!R979/10^6 -> -51.2257 | AB89: ='GFS 2025_26 Budget'!S979/10^6 -> 0 | AC89: ='GFS 2025_26 Budget'!T979/10^6 -> 0 | AD89: ='GFS 2025_26 Budget'!U979/10^6 -> 0 | AE89: =IFERROR(SUM(AA89:AD89),"") -> -51.2257
M90: Loans | N90: =SUM('GFS 2025_26 Budget'!E991:E997)/10^6 -> 0 | O90: =SUM('GFS 2025_26 Budget'!F991:F997)/10^6 -> 0 | P90: =SUM('GFS 2025_26 Budget'!G991:G997)/10^6 -> 0 | Q90: =SUM('GFS 2025_26 Budget'!H991:H997)/10^6 -> 0 | R90: =SUM('GFS 2025_26 Budget'!I991:I997)/10^6 -> 0 | S90: =SUM('GFS 2025_26 Budget'!J991:J997)/10^6 -> 0 | T90: =SUM('GFS 2025_26 Budget'!K991:K997)/10^6 -> 0 | U90: =IFERROR(SUM(Q90:T90),"") -> 0 | V90: =SUM('GFS 2025_26 Budget'!M991:M997)/10^6 -> 0 | W90: =SUM('GFS 2025_26 Budget'!N991:N997)/10^6 -> 0 | X90: =SUM('GFS 2025_26 Budget'!O991:O997)/10^6 -> 0 | Y90: =SUM('GFS 2025_26 Budget'!P991:P997)/10^6 -> 0 | Z90: =IFERROR(SUM(V90:Y90),"") -> 0 | AA90: =SUM('GFS 2025_26 Budget'!R991:R997)/10^6 -> 0 | AB90: =SUM('GFS 2025_26 Budget'!S991:S997)/10^6 -> 0 | AC90: =SUM('GFS 2025_26 Budget'!T991:T997)/10^6 -> 0 | AD90: =SUM('GFS 2025_26 Budget'!U991:U997)/10^6 -> 0 | AE90: =IFERROR(SUM(AA90:AD90),"") -> 0
M91: Repayments | N91: =SUM('GFS 2025_26 Budget'!E999:E1000)/10^6 -> 46.296461 | O91: =SUM('GFS 2025_26 Budget'!F999:F1000)/10^6 -> 48.407 | P91: =SUM('GFS 2025_26 Budget'!G999:G1000)/10^6 -> 48.8159 | Q91: =SUM('GFS 2025_26 Budget'!H999:H1000)/10^6 -> 51.2257 | R91: =SUM('GFS 2025_26 Budget'!I999:I1000)/10^6 -> 0 | S91: =SUM('GFS 2025_26 Budget'!J999:J1000)/10^6 -> 0 | T91: =SUM('GFS 2025_26 Budget'!K999:K1000)/10^6 -> 0 | U91: =IFERROR(SUM(Q91:T91),"") -> 51.2257 | V91: =SUM('GFS 2025_26 Budget'!M999:M1000)/10^6 -> 51.2257 | W91: =SUM('GFS 2025_26 Budget'!N999:N1000)/10^6 -> 0 | X91: =SUM('GFS 2025_26 Budget'!O999:O1000)/10^6 -> 0 | Y91: =SUM('GFS 2025_26 Budget'!P999:P1000)/10^6 -> 0 | Z91: =IFERROR(SUM(V91:Y91),"") -> 51.2257 | AA91: =SUM('GFS 2025_26 Budget'!R999:R1000)/10^6 -> 51.2257 | AB91: =SUM('GFS 2025_26 Budget'!S999:S1000)/10^6 -> 0 | AC91: =SUM('GFS 2025_26 Budget'!T999:T1000)/10^6 -> 0 | AD91: =SUM('GFS 2025_26 Budget'!U999:U1000)/10^6 -> 0 | AE91: =IFERROR(SUM(AA91:AD91),"") -> 51.2257
M95: Note: Payments associated with the acquisition of nonfinancial assets with the amounts in the GFS reports, the amount of the estimated receipts from the sale of capital items needs to be deducted from the figures in this table.
P96: 15/16 | Q96: 16/17 | Z96: 17/18 | AA96: 18/19 | AB96: 19/20 actual | AC96: 20/21 estimate | AD96: 20/21 | AE96: 21/22 est | AF96: FY27/28 (f)
M97: Real GDP (growth rate) | Z97: 0.3 | AA97: 0.7 | AB97: 0.5 | AC97: -2.7 | AD97: -2.7 | AE97: -0.4 | AF97: 2.9
M98: GDP nominal ($m) | N98: 797.19245 | O98: 849.14681 | P98: 932.58986 | Q98: 1017.6681 | Z98: 1073.284 | AA98: 1163.2 | AB98: 1119.9 | AC98: 1068.8 | AD98: 1188.7 | AE98: 1340.4 | AF98: 1418.7
M99: CPI (%) | Z99: 60 | AA99: 60 | AB99: 60 | AC99: 60
Z100: 0.053 | AA100: 0.04 | AB100: 0.002 | AC100: =AC99/AC98 -> 0.056137725 | AD100: 1.4
M101: Total Domestic Revenue ($m) | N101: =SUM(#REF!,#REF!) -> #REF! | O101: =SUM(#REF!,#REF!) -> #REF! | P101: =SUM(#REF!,#REF!) -> #REF! | Q101: =SUM(#REF!,#REF!) -> #REF! | Z101: =SUM(#REF!,#REF!) -> #REF! | AA101: =SUM(#REF!,#REF!) -> #REF! | AB101: =SUM(#REF!,#REF!) -> #REF! | AC101: =SUM(#REF!,#REF!) -> #REF! | AD101: =SUM(#REF!,#REF!) -> #REF! | AE101: =SUM(#REF!,#REF!) -> #REF! | AF101: =SUM(#REF!,#REF!) -> #REF! | AG101: =#REF!-AE101 -> #REF! | AH101: =(#REF!/AE101-1)*100 -> #REF!
M102: Compensation of Employees ($m) | O102: =O109-N109 -> -0.68617005 | P102: =P109-O109 -> 2.9279 | Q102: =Q109-P109 -> -2.9653 | Z102: =Z46 -> 35.1901 | AA102: =AA46 -> 18.7346 | AB102: =AB46 -> 12.9554 | AC102: =AC46 -> 0 | AD102: =AD46 -> 0 | AE102: =AE46 -> 31.69 | AF102: =AF46 -> 0
M103: % growth | O103: =O109/N109-1 -> -0.04133562 | P103: =P109/O109-1 -> 0.18398497 | Q103: =Q109/P109-1 -> -0.15737964 | Z103: =Z109/Q109-1 -> #REF! | AA103: =AA109/Z109-1 -> #REF! | AB103: =AB109/AA109-1 -> #REF! | AC103: =AC109/AB109-1 -> #REF! | AD103: =AD109/AC109-1 -> #REF! | AE103: =AE109/AD109-1 -> #REF! | AF103: =AF109/#REF!-1 -> #REF!
M104: Total Domestic Revenue ($m) | O104: =O101-N101 -> #REF! | P104: =P101-O101 -> #REF! | Q104: =Q101-P101 -> #REF! | Z104: =Z101-Q101 -> #REF! | AA104: =AA101-Z101 -> #REF! | AB104: =AB101-AA101 -> #REF! | AC104: =AC101-AB101 -> #REF! | AD104: =AD101-AC101 -> #REF! | AE104: =AE101-AD101 -> #REF! | AF104: =AF101-#REF! -> #REF!
M105: % growth | O105: =P101/N101-1 -> #REF! | P105: =Q101/O101-1 -> #REF! | Q105: =Z101/P101-1 -> #REF! | Z105: =AA101/Q101-1 -> #REF! | AA105: =AB101/Z101-1 -> #REF! | AB105: =AB101/AA101-1 -> #REF! | AC105: =AC101/AB101-1 -> #REF! | AD105: =AD101/AC101-1 -> #REF! | AE105: =AE101/AD101-1 -> #REF! | AF105: =AF101/#REF!-1 -> #REF!
...

Sheet Tables
B2: Table 2: Government Finance Statistics (GFS) Summary Table | AD2: Tepile 13: Fakamatala Ngaahi Ngaue 'a e Pule'anga ($m) | AU2: Table 13: Statement of Government Operations (% change)
C3: 2013/14 Actual | D3: 2014/15 Actual | E3: 2015/16 Actual | F3: 2016/17 Actual | G3: =G196 -> 2017/18 Actual | H3: =H196 -> 2018/19 Actual | I3: =I196 -> 2019/20 Actual | J3: =J196 -> 2020/21 Actual | K3: =K196 -> 2021/22 Actual | L3: =L196 -> Budget Estimate 2022/23 | M3: =M196 -> Actual FY2025 | N3: =N196 -> Budget Estimate 2025/26 | O3: Revised Estimate 2024/25 | P3: =P196 -> Budget Estimate 2026/27 | Q3: =Q196 -> Budget Estimate 2027/28 | R3: =R196 -> Budget Estimate 2028/29 | AE3: 2013/14 Ola | AF3: 2014/15 Ola | AG3: 2015/16 Ola | AH3: 2016/17 Ola | AI3: =AI46 -> 2017/18 Ola | AJ3: =AJ46 -> 2018/19 Ola | AK3: =AK46 -> 2019/20 Ola | AL3: =AL46 -> 2020/21 Ola | AM3: =AM46 -> 2021/22 Ola | AN3: =AN46 -> 2022/23 Patiseti | AO3: =AO46 -> 2024/25 Ola Fakaangaanga | AP3: =AP46 -> 2025/26 Patiseti | ... AT3: =AT46 -> 2028/29 Patiseti Fakaangaanga | AV3: 2020/21 Estimated Outturn From Budget Estimate 20/21 | AW3: $m change | AX3: 2020/21 Estimated to Budget 2021/22 | AY3: $m change | AZ3: 2020/21 Estimated Outturn to Budget 2021/22 | BA3: $m change | BB3: Estimate 2020/22 from 2019/20 Actual % | BC3: $m change | BE3: A 2019/20 to BE 2020/21 | BF3: A 2019/20 to EO 2020/21 | BG3: BE 2020/21 to EO 2020/21 | BH3: EO 2020/21 to BE 2021/22 | BN3: long term rules thereshold 50%
B5: Revenue | C5: =SUM(C6:C7) -> 160.98098 | D5: =SUM(D6:D7) -> 185.08488 | E5: =SUM(E6:E7) -> 209.38357 | F5: =SUM(F6:F7) -> 239.29201 | G5: =SUM(G6:G7) -> 261.63971 | H5: =SUM(H6:H7) -> 481.76119 | I5: =SUM(I6:I7) -> 482.37442 | J5: =SUM(J6:J7) -> 512.2005 | ... R5: =SUM(R6:R7) -> 754.0928 | S5: =IFERROR(M5/L5-1,"") -> 0.17410742 | T5: =IFERROR(P5/O5-1,"") -> 0.10884375 | U5: =IFERROR(P5-O5,"") -> 86.1303 | V5: =U5/$O$5 -> 0.10884375 | W5: =IFERROR(Q5/P5-1,"") -> 0.0098718914 | X5: =IFERROR(R5/Q5-1,"") -> -0.148988 | Y5: 741.9 | Z5: =Y5-N5 -> -187.788 | AD5: Pa'anga Humai | AE5: =C5 -> 160.98098 | AF5: =D5 -> 185.08488 | AG5: =E5 -> 209.38357 | AH5: =F5 -> 239.29201 | AI5: =G5 -> 261.63971 | AJ5: =H5 -> 481.76119 | AK5: =I5 -> 482.37442 | AL5: =J5 -> 512.2005 | ... AT5: =R5 -> 754.0928 | AU5: Revenue | AV5: =IFERROR(#REF!/#REF!*100-100,"") | AW5: =#REF!-#REF! -> #REF! | AX5: =IFERROR(#REF!/#REF!*100-100,"") | AY5: =#REF!-#REF! -> #REF! | AZ5: =IFERROR(#REF!/#REF!*100-100,"") | BA5: =#REF!-#REF! -> #REF! | BB5: =IFERROR(#REF!/I5*100-100,"") | BC5: =#REF!-I5 -> #REF! | BE5: =#REF!-I5 -> #REF! | BF5: =#REF!-I5 -> #REF! | BG5: =#REF!-#REF! -> #REF! | BH5: =#REF!-#REF! -> #REF!
B6: Tax and Non-tax Revenue | C6: =SUM(C198,C207) -> 160.98098 | D6: =SUM(D198,D207) -> 185.08488 | E6: =SUM(E198,E207) -> 209.38357 | F6: =SUM(F198,F207) -> 239.29201 | G6: =SUM(G198,G207) -> 261.63971 | H6: =SUM(H198,H207) -> 269.26378 | I6: =SUM(I198,I207) -> 268.70115 | J6: =SUM(J198,J207) -> 272.67335 | ... R6: =SUM(R198,R207) -> 484.7928 | S6: =IFERROR(M6/L6-1,"") -> 0.36490901 | T6: =IFERROR(P6/O6-1,"") -> 0.022570668 | U6: =IFERROR(P6-O6,"") -> 9.1303 | V6: =U6/$O$5 -> 0.011538054 | W6: =IFERROR(Q6/P6-1,"") -> 0.11449776 | X6: =IFERROR(R6/Q6-1,"") -> 0.051581626 | AD6: Pa'anga Humai Mei he Tukuhau | AE6: =C6 -> 160.98098 | AF6: =D6 -> 185.08488 | AG6: =E6 -> 209.38357 | AH6: =F6 -> 239.29201 | AI6: =G6 -> 261.63971 | AJ6: =H6 -> 269.26378 | AK6: =I6 -> 268.70115 | AL6: =J6 -> 272.67335 | ... AT6: =R6 -> 484.7928 | AU6: Tax and Non-tax Revenue | AV6: =IFERROR(#REF!/#REF!*100-100,"") | AW6: =#REF!-#REF! -> #REF! | AX6: =IFERROR(#REF!/#REF!*100-100,"") | AY6: =#REF!-#REF! -> #REF! | AZ6: =IFERROR(#REF!/#REF!*100-100,"") | BA6: =#REF!-#REF! -> #REF! | BB6: =IFERROR(#REF!/I6*100-100,"") | BC6: =#REF!-I6 -> #REF! | BE6: =#REF!-I6 -> #REF! | BF6: =#REF!-I6 -> #REF! | BG6: =#REF!-#REF! -> #REF! | BH6: =#REF!-#REF! -> #REF!
B7: Grants | C7: =SUM(C8:C9) -> 0 | D7: =SUM(D8:D9) -> 0 | E7: =SUM(E8:E9) -> 0 | F7: =SUM(F8:F9) -> 0 | G7: =SUM(G8:G9) -> 0 | H7: =SUM(H8:H9) -> 212.49741 | I7: =SUM(I8:I9) -> 213.67327 | J7: =SUM(J8:J9) -> 239.52715 | ... R7: =SUM(R8:R9) -> 269.3 | S7: =IFERROR(M7/L7-1,"") -> 0.042776827 | T7: =IFERROR(P7/O7-1,"") -> 0.19906929 | U7: =IFERROR(P7-O7,"") -> 77 | V7: =U7/$O$5 -> 0.097305694 | W7: =IFERROR(Q7/P7-1,"") -> -0.083441138 | X7: =IFERROR(R7/Q7-1,"") -> -0.366502 | AD7: Ngaahi tokoni fakapa'anga | AE7: =C7 -> 0 | AF7: =D7 -> 0 | AG7: =E7 -> 0 | AH7: =F7 -> 0 | AI7: =G7 -> 0 | AJ7: =H7 -> 212.49741 | AK7: =I7 -> 213.67327 | AL7: =J7 -> 239.52715 | ... AT7: =R7 -> 269.3 | AU7: Grants | AV7: =IFERROR(#REF!/#REF!*100-100,"") | AW7: =#REF!-#REF! -> #REF! | AX7: =IFERROR(#REF!/#REF!*100-100,"") | AY7: =#REF!-#REF! -> #REF! | AZ7: =IFERROR(#REF!/#REF!*100-100,"") | BA7: =#REF!-#REF! -> #REF! | BB7: =IFERROR(#REF!/I7*100-100,"") | BC7: =#REF!-I7 -> #REF! | BE7: =#REF!-I7 -> #REF! | BF7: =#REF!-I7 -> #REF! | BG7: =#REF!-#REF! -> #REF! | BH7: =#REF!-#REF! -> #REF!
B8: Current | C8: =C205 -> n.a | D8: =D205 -> n.a | E8: =E205 -> n.a | F8: =F205 -> n.a | G8: =G205 -> n.a | H8: =H205 -> 34.906637 | I8: =I205 -> 37.566851 | J8: =J205 -> 27.208098 | ... R8: =R205 -> 44.5 | S8: =IFERROR(M8/L8-1,"") -> 0.12392638 | T8: =IFERROR(P8/O8-1,"") -> 0.050228311 | U8: =IFERROR(P8-O8,"") -> 5.5 | V8: =U8/$O$5 -> 0.0069504067 | W8: =IFERROR(Q8/P8-1,"") -> -0.26956522 | X8: =IFERROR(R8/Q8-1,"") -> -0.4702381 | AD8: Tokoni ki he Ngaahi Fakamole hono fakalele 'o e Pule'anga | AE8: =C8 -> n.a | AF8: =D8 -> n.a | AG8: =E8 -> n.a | AH8: =F8 -> n.a | AI8: =G8 -> n.a | AJ8: =H8 -> 34.906637 | AK8: =I8 -> 37.566851 | AL8: =J8 -> 27.208098 | ... AT8: =R8 -> 44.5 | AU8: Current | AV8: =IFERROR(#REF!/#REF!*100-100,"") | AW8: =#REF!-#REF! -> #REF! | AX8: =IFERROR(#REF!/#REF!*100-100,"") | AY8: =#REF!-#REF! -> #REF! | AZ8: =IFERROR(#REF!/#REF!*100-100,"") | BA8: =#REF!-#REF! -> #REF! | BB8: =IFERROR(#REF!/I8*100-100,"") | BC8: =#REF!-I8 -> #REF! | BE8: =#REF!-I8 -> #REF! | BF8: =#REF!-I8 -> #REF! | BG8: =#REF!-#REF! -> #REF! | BH8: =#REF!-#REF! -> #REF!
B9: Capital | C9: =C206 -> n.a | D9: =D206 -> n.a | E9: =E206 -> n.a | F9: =F206 -> n.a | G9: =G206 -> n.a | H9: =H206 -> 177.59078 | I9: =I206 -> 176.10642 | J9: =J206 -> 212.31905 | ... R9: =R206 -> 224.8 | S9: =IFERROR(P9/O9-1,"") -> 0.25784349 | T9: =IFERROR(P9/O9-1,"") -> 0.25784349 | U9: =IFERROR(P9-O9,"") -> 71.5 | V9: =U9/$O$5 -> 0.090355287 | W9: =IFERROR(Q9/P9-1,"") -> -0.022075688 | X9: =IFERROR(R9/Q9-1,"") -> -0.34095573 | AD9: Tokoni ki he Ngaahi Ngaue Lalahi | AE9: =C9 -> n.a | AF9: =D9 -> n.a | AG9: =E9 -> n.a | AH9: =F9 -> n.a | AI9: =G9 -> n.a | AJ9: =H9 -> 177.59078 | AK9: =I9 -> 176.10642 | AL9: =J9 -> 212.31905 | ... AT9: =R9 -> 224.8 | AU9: Capital | AV9: =IFERROR(#REF!/#REF!*100-100,"") | AW9: =#REF!-#REF! -> #REF! | AX9: =IFERROR(#REF!/#REF!*100-100,"") | AY9: =#REF!-#REF! -> #REF! | AZ9: =IFERROR(#REF!/#REF!*100-100,"") | BA9: =#REF!-#REF! -> #REF! | BB9: =IFERROR(#REF!/I9*100-100,"") | BC9: =#REF!-I9 -> #REF! | BE9: =#REF!-I9 -> #REF! | BF9: =#REF!-I9 -> #REF! | BG9: =#REF!-#REF! -> #REF! | BH9: =#REF!-#REF! -> #REF!
S10: =IFERROR(M10/L10-1,"") | T10: =IFERROR(P10/O10-1,"") | U10: =IFERROR(P10-O10,"") -> 0 | V10: =U10/$O$5 -> 0 | W10: =IFERROR(Q10/P10-1,"") | X10: =IFERROR(R10/Q10-1,"") | AV10: =IFERROR(#REF!/#REF!*100-100,"") | AW10: =#REF!-#REF! -> #REF! | AX10: =IFERROR(#REF!/#REF!*100-100,"") | AY10: =#REF!-#REF! -> #REF! | AZ10: =IFERROR(#REF!/#REF!*100-100,"") | BA10: =#REF!-#REF! -> #REF! | BB10: =IFERROR(#REF!/I10*100-100,"") | BC10: =#REF!-I10 -> #REF! | BE10: =#REF!-I10 -> #REF! | BF10: =#REF!-I10 -> #REF! | BG10: =#REF!-#REF! -> #REF! | BH10: =#REF!-#REF! -> #REF!
B11: Expense | C11: =C213 -> 330.11347 | D11: =D213 -> 368.28063 | E11: =E213 -> 250.26112 | F11: =F213 -> 203.56715 | G11: =G213 -> 336.47458 | H11: =H213 -> 352.22797 | I11: =I213 -> 376.90192 | J11: =J213 -> 367.91324 | ... R11: =R213 -> 576.6005 | S11: =IFERROR(M11/L11-1,"") -> -0.02866317 | T11: =IFERROR(P11/O11-1,"") -> 0.1733976 | U11: =IFERROR(P11-O11,"") -> 90.1169 | V11: =U11/$O$11 -> 0.1733976 | W11: =IFERROR(Q11/P11-1,"") -> -0.041751185 | X11: =IFERROR(R11/Q11-1,"") -> -0.013292644 | Y11: 514.8 | Z11: =Y11-N11 -> -102.621 | AD11: Ngaahi Fakamole | AE11: =C11 -> 330.11347 | AF11: =D11 -> 368.28063 | AG11: =E11 -> 250.26112 | AH11: =F11 -> 203.56715 | AI11: =G11 -> 336.47458 | AJ11: =H11 -> 352.22797 | AK11: =I11 -> 376.90192 | AL11: =J11 -> 367.91324 | ... AT11: =R11 -> 576.6005 | AU11: Expense | AV11: =IFERROR(#REF!/#REF!*100-100,"") | AW11: =#REF!-#REF! -> #REF! | AX11: =IFERROR(#REF!/#REF!*100-100,"") | AY11: =#REF!-#REF! -> #REF! | AZ11: =IFERROR(#REF!/#REF!*100-100,"") | BA11: =#REF!-#REF! -> #REF! | BB11: =IFERROR(#REF!/I11*100-100,"") | BC11: =#REF!-I11 -> #REF! | BE11: =#REF!-I11 -> #REF! | BF11: =#REF!-I11 -> #REF! | BG11: =#REF!-#REF! -> #REF! | BH11: =#REF!-#REF! -> #REF!
B12: Compensation of employees | C12: =C115 -> 101.37979 | D12: =D115 -> 116.84684 | E12: =E115 -> 127.25817 | F12: =F115 -> 129.60077 | G12: =G115 -> 127.54825 | H12: =H115 -> 134.50866 | I12: =I115 -> 148.68345 | J12: =J115 -> 160.21209 | ... R12: =R115 -> 204.1627 | S12: =IFERROR(M12/L12-1,"") -> 0.088112287 | T12: =IFERROR(P12/O12-1,"") -> 0.098103213 | U12: =IFERROR(P12-O12,"") -> 18.8279 | V12: =U12/$O$11 -> 0.03622753 | W12: =IFERROR(Q12/P12-1,"") -> -0.017878292 | X12: =IFERROR(R12/Q12-1,"") -> -0.013608601 | AD12: Fakamole ki he kau Ngaue | AE12: =C12 -> 101.37979 | AF12: =D12 -> 116.84684 | AG12: =E12 -> 127.25817 | AH12: =F12 -> 129.60077 | AI12: =G12 -> 127.54825 | AJ12: =H12 -> 134.50866 | AK12: =I12 -> 148.68345 | AL12: =J12 -> 160.21209 | ... AT12: =R12 -> 204.1627 | AU12: Compensation of employees | AV12: =IFERROR(#REF!/#REF!*100-100,"") | AW12: =#REF!-#REF! -> #REF! | AX12: =IFERROR(#REF!/#REF!*100-100,"") | AY12: =#REF!-#REF! -> #REF! | AZ12: =IFERROR(#REF!/#REF!*100-100,"") | BA12: =#REF!-#REF! -> #REF! | BB12: =IFERROR(#REF!/I12*100-100,"") | BC12: =#REF!-I12 -> #REF! | BE12: =#REF!-I12 -> #REF! | BF12: =#REF!-I12 -> #REF! | BG12: =#REF!-#REF! -> #REF! | BH12: =#REF!-#REF! -> #REF!
B13: Use of goods and services | C13: =C116 -> 194.923 | D13: =D116 -> 211.64955 | E13: =E116 -> 80.693983 | F13: =F116 -> 29.987996 | G13: =G116 -> 152.3425 | H13: =H116 -> 151.00338 | I13: =I116 -> 169.68852 | J13: =J116 -> 182.53745 | ... R13: =R116 -> 252.51195 | S13: =IFERROR(M13/L13-1,"") -> -0.23396868 | T13: =IFERROR(P13/O13-1,"") -> 0.072475899 | U13: =IFERROR(P13-O13,"") -> 17.274 | V13: =U13/$O$11 -> 0.033237607 | W13: =IFERROR(Q13/P13-1,"") -> -0.0058736703 | X13: =IFERROR(R13/Q13-1,"") -> -0.0063040629 | AD13: Ngaue'aki 'o e Koloa mo e Ngaue | AE13: =C13 -> 194.923 | AF13: =D13 -> 211.64955 | AG13: =E13 -> 80.693983 | AH13: =F13 -> 29.987996 | AI13: =G13 -> 152.3425 | AJ13: =H13 -> 151.00338 | AK13: =I13 -> 169.68852 | AL13: =J13 -> 182.53745 | ... AT13: =R13 -> 252.51195 | AU13: Use of goods and services | AV13: =IFERROR(#REF!/#REF!*100-100,"") | AW13: =#REF!-#REF! -> #REF! | AX13: =IFERROR(#REF!/#REF!*100-100,"") | AY13: =#REF!-#REF! -> #REF! | AZ13: =IFERROR(#REF!/#REF!*100-100,"") | BA13: =#REF!-#REF! -> #REF! | BB13: =IFERROR(#REF!/I13*100-100,"") | BC13: =#REF!-I13 -> #REF! | BE13: =#REF!-I13 -> #REF! | BF13: =#REF!-I13 -> #REF! | BG13: =#REF!-#REF! -> #REF! | BH13: =#REF!-#REF! -> #REF!
B14: Interest | C14: =C117 -> 7.1441045 | D14: =D117 -> 7.1753021 | E14: =E117 -> 7.8585005 | F14: =F117 -> 8.2692306 | G14: =G117 -> 8.2716359 | H14: =H117 -> 8.0189433 | I14: =I117 -> 8.2292158 | J14: =J117 -> 4.120336 | ... R14: =R117 -> 6.369 | S14: =IFERROR(M14/L14-1,"") -> -0.12927289 | T14: =IFERROR(P14/O14-1,"") -> 0.074428962 | U14: =IFERROR(P14-O14,"") -> 0.4412 | V14: =U14/$O$11 -> 0.0008489309 | W14: =IFERROR(Q14/P14-1,"") -> 0 | X14: =IFERROR(R14/Q14-1,"") -> 0 | AD14: Totongi Tupu | AE14: =C14 -> 7.1441045 | AF14: =D14 -> 7.1753021 | AG14: =E14 -> 7.8585005 | AH14: =F14 -> 8.2692306 | AI14: =G14 -> 8.2716359 | AJ14: =H14 -> 8.0189433 | AK14: =I14 -> 8.2292158 | AL14: =J14 -> 4.120336 | ... AT14: =R14 -> 6.369 | AU14: Interest | AV14: =IFERROR(#REF!/#REF!*100-100,"") | AW14: =#REF!-#REF! -> #REF! | AX14: =IFERROR(#REF!/#REF!*100-100,"") | AY14: =#REF!-#REF! -> #REF! | AZ14: =IFERROR(#REF!/#REF!*100-100,"") | BA14: =#REF!-#REF! -> #REF! | BB14: =IFERROR(#REF!/I14*100-100,"") | BC14: =#REF!-I14 -> #REF! | BE14: =#REF!-I14 -> #REF! | BF14: =#REF!-I14 -> #REF! | BG14: =#REF!-#REF! -> #REF! | BH14: =#REF!-#REF! -> #REF!
B15: Subsidies | C15: =C118 -> 0.07498125 | D15: =D118 -> 0.07837965 | E15: =E118 -> 0.63866555 | F15: =F118 -> 0.80846416 | G15: =G118 -> 0.8010717 | H15: =H118 -> 0.85881345 | I15: =I118 -> 0.8373947 | J15: =J118 -> 0.81310089 | ... R15: =R118 -> 31.69 | S15: =IFERROR(M15/L15-1,"") -> 11.769208 | T15: =IFERROR(P15/O15-1,"") -> 1.090581 | U15: =IFERROR(P15-O15,"") -> 20.5484 | V15: =U15/$O$11 -> 0.039538014 | W15: =IFERROR(Q15/P15-1,"") -> -0.10662578 | X15: =IFERROR(R15/Q15-1,"") -> -0.099462633 | AD15: Ngaahi Tokoni Me'a'ofa | AE15: =C15 -> 0.07498125 | AF15: =D15 -> 0.07837965 | AG15: =E15 -> 0.63866555 | AH15: =F15 -> 0.80846416 | AI15: =G15 -> 0.8010717 | AJ15: =H15 -> 0.85881345 | AK15: =I15 -> 0.8373947 | AL15: =J15 -> 0.81310089 | ... AT15: =R15 -> 31.69 | AU15: Subsidies | AV15: =IFERROR(#REF!/#REF!*100-100,"") | AW15: =#REF!-#REF! -> #REF! | AX15: =IFERROR(#REF!/#REF!*100-100,"") | AY15: =#REF!-#REF! -> #REF! | AZ15: =IFERROR(#REF!/#REF!*100-100,"") | BA15: =#REF!-#REF! -> #REF! | BB15: =IFERROR(#REF!/I15*100-100,"") | BC15: =#REF!-I15 -> #REF! | BE15: =#REF!-I15 -> #REF! | BF15: =#REF!-I15 -> #REF! | BG15: =#REF!-#REF! -> #REF! | BH15: =#REF!-#REF! -> #REF!
B16: Grants | C16: =C119 -> 3.1344312 | D16: =D119 -> 3.7251119 | E16: =E119 -> 3.6892579 | F16: =F119 -> 3.2156034 | G16: =G119 -> 5.149925 | H16: =H119 -> 2.9362986 | I16: =I119 -> 3.740601 | J16: =J119 -> 0 | ... R16: =R119 -> 28.312 | S16: =IFERROR(M16/L16-1,"") -> 2.9754217 | T16: =IFERROR(P16/O16-1,"") -> 1.037087 | U16: =IFERROR(P16-O16,"") -> 21.0762 | V16: =U16/$O$11 -> 0.040553575 | W16: =IFERROR(Q16/P16-1,"") -> -0.31611379 | X16: =IFERROR(R16/Q16-1,"") -> 0 | AD16: Ngaahi Tokoni Fakapa'anga | AE16: =C16 -> 3.1344312 | AF16: =D16 -> 3.7251119 | AG16: =E16 -> 3.6892579 | AH16: =F16 -> 3.2156034 | AI16: =G16 -> 5.149925 | AJ16: =H16 -> 2.9362986 | AK16: =I16 -> 3.740601 | AL16: =J16 -> 0 | ... AT16: =R16 -> 28.312 | AU16: Grants | AV16: =IFERROR(#REF!/#REF!*100-100,"") | AW16: =#REF!-#REF! -> #REF! | AX16: =IFERROR(#REF!/#REF!*100-100,"") | AY16: =#REF!-#REF! -> #REF! | AZ16: =IFERROR(#REF!/#REF!*100-100,"") | BA16: =#REF!-#REF! -> #REF! | BB16: =IFERROR(#REF!/I16*100-100,"") | BC16: =#REF!-I16 -> #REF! | BE16: =#REF!-I16 -> #REF! | BF16: =#REF!-I16 -> #REF! | BG16: =#REF!-#REF! -> #REF! | BH16: =#REF!-#REF! -> #REF!
B17: Social benefits | C17: =C120 -> 10.507974 | D17: =D120 -> 13.676273 | E17: =E120 -> 13.21045 | F17: =F120 -> 13.640681 | G17: =G120 -> 22.985101 | H17: =H120 -> 25.268289 | I17: =I120 -> 22.293981 | J17: =J120 -> 20.230267 | ... R17: =R120 -> 36.08715 | S17: =IFERROR(M17/L17-1,"") -> 0.23261254 | T17: =IFERROR(P17/O17-1,"") -> 0.41677902 | U17: =IFERROR(P17-O17,"") -> 11.2522 | V17: =U17/$O$11 -> 0.021650817 | W17: =IFERROR(Q17/P17-1,"") -> -0.060496416 | X17: =IFERROR(R17/Q17-1,"") -> 0.0042004998 | AD17: Ngaahi Monu'ia Fakasosiale | AE17: =C17 -> 10.507974 | AF17: =D17 -> 13.676273 | AG17: =E17 -> 13.21045 | AH17: =F17 -> 13.640681 | AI17: =G17 -> 22.985101 | AJ17: =H17 -> 25.268289 | AK17: =I17 -> 22.293981 | AL17: =J17 -> 20.230267 | ... AT17: =R17 -> 36.08715 | AU17: Social benefits | AV17: =IFERROR(#REF!/#REF!*100-100,"") | AW17: =#REF!-#REF! -> #REF! | AX17: =IFERROR(#REF!/#REF!*100-100,"") | AY17: =#REF!-#REF! -> #REF! | AZ17: =IFERROR(#REF!/#REF!*100-100,"") | BA17: =#REF!-#REF! -> #REF! | BB17: =IFERROR(#REF!/I17*100-100,"") | BC17: =#REF!-I17 -> #REF! | BE17: =#REF!-I17 -> #REF! | BF17: =#REF!-I17 -> #REF! | BG17: =#REF!-#REF! -> #REF! | BH17: =#REF!-#REF! -> #REF!
B18: Other expense | C18: =C121 -> 12.949185 | D18: =D121 -> 15.129184 | E18: =E121 -> 16.912092 | F18: =F121 -> 18.044409 | G18: =G121 -> 19.376089 | H18: =H121 -> 29.633586 | I18: =I121 -> 23.428761 | J18: =J121 -> 0 | ... R18: =R121 -> 17.4677 | S18: =IFERROR(M18/L18-1,"") -> -0.55516654 | T18: =IFERROR(P18/O18-1,"") -> 0.040145376 | U18: =IFERROR(P18-O18,"") -> 0.697 | V18: =U18/$O$11 -> 0.0013411261 | W18: =IFERROR(Q18/P18-1,"") -> -0.032737321 | X18: =IFERROR(R18/Q18-1,"") -> 0 | AD18: Ngaahi Fakamole Kehe | AE18: =C18 -> 12.949185 | AF18: =D18 -> 15.129184 | AG18: =E18 -> 16.912092 | AH18: =F18 -> 18.044409 | AI18: =G18 -> 19.376089 | AJ18: =H18 -> 29.633586 | AK18: =I18 -> 23.428761 | AL18: =J18 -> 0 | ... AT18: =R18 -> 17.4677 | AU18: Other expense | AV18: =IFERROR(#REF!/#REF!*100-100,"") | AW18: =#REF!-#REF! -> #REF! | AX18: =IFERROR(#REF!/#REF!*100-100,"") | AY18: =#REF!-#REF! -> #REF! | AZ18: =IFERROR(#REF!/#REF!*100-100,"") | BA18: =#REF!-#REF! -> #REF! | BB18: =IFERROR(#REF!/I18*100-100,"") | BC18: =#REF!-I18 -> #REF! | BE18: =#REF!-I18 -> #REF! | BF18: =#REF!-I18 -> #REF! | BG18: =#REF!-#REF! -> #REF! | BH18: =#REF!-#REF! -> #REF!
B19: Gross Operating Balance | C19: =C228 -> -99.481461 | D19: =D228 -> -135.61429 | E19: =E228 -> 14.136589 | F19: =F228 -> 105.67514 | G19: =G228 -> 115.94273 | H19: =H228 -> 129.53322 | I19: =I228 -> 105.4725 | J19: =J228 -> 144.28726 | ... R19: =R228 -> 177.4923 | S19: =IFERROR(M19/L19-1,"") -> 1.0193373 | T19: =IFERROR(P19/O19-1,"") -> -0.014677766 | U19: =IFERROR(P19-O19,"") -> -3.9866 | V19: =U19/$O$19 -> -0.014677766 | W19: =IFERROR(Q19/P19-1,"") -> 0.12750545 | X19: =IFERROR(R19/Q19-1,"") -> -0.41177989 | AD19: Palanisi | AE19: =C19 -> -99.481461 | AF19: =D19 -> -135.61429 | AG19: =E19 -> 14.136589 | AH19: =F19 -> 105.67514 | AI19: =G19 -> 115.94273 | AJ19: =H19 -> 129.53322 | AK19: =I19 -> 105.4725 | AL19: =J19 -> 144.28726 | ... AT19: =R19 -> 177.4923 | AU19: Gross Operating Balance | AV19: =IFERROR(#REF!/#REF!*100-100,"") | AW19: =#REF!-#REF! -> #REF! | AX19: =IFERROR(#REF!/#REF!*100-100,"") | AY19: =#REF!-#REF! -> #REF! | AZ19: =IFERROR(#REF!/#REF!*100-100,"") | BA19: =#REF!-#REF! -> #REF! | BB19: =IFERROR(#REF!/I19*100-100,"") | BC19: =#REF!-I19 -> #REF! | BE19: =#REF!-I19 -> #REF! | BF19: =#REF!-I19 -> #REF! | BG19: =#REF!-#REF! -> #REF! | BH19: =#REF!-#REF! -> #REF!
T20: =IFERROR(P20/O20-1,"") | U20: =IFERROR(P20-O20,"") -> 0 | W20: =IFERROR(Q20/P20-1,"") | X20: =IFERROR(R20/Q20-1,"")
B21: Net Acquisition Of Nonfinancial Assets | C21: =C230 -> 194.10428 | D21: =D230 -> 85.992378 | E21: =E230 -> 9.1538968 | F21: =F230 -> 4.6552523 | G21: =G230 -> 89.352866 | H21: =H230 -> 96.138286 | I21: =I230 -> 57.825259 | J21: =J230 -> 100.96056 | ... R21: =R230 -> 127.4427 | S21: =IFERROR(M21/L21-1,"") -> 0.55420209 | T21: =IFERROR(P21/O21-1,"") -> 0.24298089 | U21: =IFERROR(P21-O21,"") -> 52.36 | V21: =IFERROR(N21-M21,"") -> 6.568472 | W21: =IFERROR(Q21/P21-1,"") -> -0.024352045 | X21: =IFERROR(R21/Q21-1,"") -> -0.51232572 | AD21: Fakatau mai 'o e Ngaahi Koloa Lalahi | AE21: =C21 -> 194.10428 | AF21: =D21 -> 85.992378 | AG21: =E21 -> 9.1538968 | AH21: =F21 -> 4.6552523 | AI21: =G21 -> 89.352866 | AJ21: =H21 -> 96.138286 | AK21: =I21 -> 57.825259 | AL21: =J21 -> 100.96056 | ... AT21: =R21 -> 127.4427 | AU21: Net Acquisition Of Nonfinancial Assets | AV21: =IFERROR(#REF!/#REF!*100-100,"") | AW21: =#REF!-#REF! -> #REF! | AX21: =IFERROR(#REF!/#REF!*100-100,"") | AY21: =#REF!-#REF! -> #REF! | AZ21: =IFERROR(#REF!/#REF!*100-100,"") | BA21: =#REF!-#REF! -> #REF! | BB21: =IFERROR(#REF!/I21*100-100,"") | BC21: =#REF!-I21 -> #REF! | BE21: =#REF!-I21 -> #REF! | BF21: =#REF!-I21 -> #REF! | BG21: =#REF!-#REF! -> #REF! | BH21: =#REF!-#REF! -> #REF!
B22: Net Lending/Borrowing Requirement | C22: =C238 -> -293.58574 | D22: =D238 -> -221.60667 | E22: =E238 -> 4.9826922 | F22: =F238 -> 101.01988 | G22: =G238 -> 26.589863 | H22: =H238 -> 33.394933 | I22: =I238 -> 47.647243 | J22: =J238 -> 43.326696 | ... R22: =R238 -> 50.1496 | S22: =IFERROR(M22/L22-1,"") -> -1.7134406 | T22: =IFERROR(P22/O22-1,"") -> -1.0058469 | U22: =IFERROR(P22-O22,"") -> -56.5466 | V22: =IFERROR(N22-M22,"") -> 35.941365 | AD22: Tupu/Fe'amokaki | AE22: =C22 -> -293.58574 | AF22: =D22 -> -221.60667 | AG22: =E22 -> 4.9826922 | AH22: =F22 -> 101.01988 | AI22: =G22 -> 26.589863 | AJ22: =H22 -> 33.394933 | AK22: =I22 -> 47.647243 | AL22: =J22 -> 43.326696 | ... AT22: =R22 -> 50.1496 | AU22: Net Lending/Borrowing Requirement | AV22: =IFERROR(#REF!/#REF!*100-100,"") | AW22: =#REF!-#REF! -> #REF! | AX22: =IFERROR(#REF!/#REF!*100-100,"") | AY22: =#REF!-#REF! -> #REF! | AZ22: =IFERROR(#REF!/#REF!*100-100,"") | BA22: =#REF!-#REF! -> #REF! | BB22: =IFERROR(#REF!/I22*100-100,"") | BC22: =#REF!-I22 -> #REF! | BE22: =#REF!-I22 -> #REF! | BF22: =#REF!-I22 -> #REF! | BG22: =#REF!-#REF! -> #REF! | BH22: =#REF!-#REF! -> #REF!
S23: =IFERROR(M23/L23-1,"") | T23: =IFERROR(P23/O23-1,"") | U23: =IFERROR(P23-O23,"") -> 0 | V23: =IFERROR(N23-M23,"") -> 0 | AV23: =IFERROR(#REF!/#REF!*100-100,"") | AW23: =#REF!-#REF! -> #REF! | AX23: =IFERROR(#REF!/#REF!*100-100,"") | AY23: =#REF!-#REF! -> #REF! | AZ23: =IFERROR(#REF!/#REF!*100-100,"") | BA23: =#REF!-#REF! -> #REF! | BB23: =IFERROR(#REF!/I23*100-100,"") | BC23: =#REF!-I23 -> #REF!
B24: =B240 -> Net Acquisition Of Financial Assets And Liabilities (Financing) | C24: =C240 -> 18.6274 | D24: =D240 -> 198.3844 | E24: =E240 -> 9.4890785 | F24: =F240 -> 22.9 | G24: =G240 -> 22.9 | H24: =H240 -> -36.802273 | I24: =I240 -> -59.720145 | ... R24: =R240 -> -50.1169 | S24: =IFERROR(M24/L24-1,"") -> -1.8602994 | T24: =IFERROR(P24/O24-1,"") -> -1.0050094 | U24: =IFERROR(P24-O24,"") -> 56.4355 | V24: =IFERROR(N24-M24,"") -> -35.887849 | AD24: Fakakatoa 'o e Koloa moe Mo'ua Fakapa'anga | AE24: =C24 -> 18.6274 | AF24: =D24 -> 198.3844 | AG24: =E24 -> 9.4890785 | AH24: =F24 -> 22.9 | AI24: =G24 -> 22.9 | AJ24: =H24 -> -36.802273 | AK24: =I24 -> -59.720145 | AL24: =J24 -> 9.7837983 | ... AT24: =R24 -> -50.1169 | AU24: =AU240 -> Net Acquisition Of Financial Assets And Liabilities (Financing) | AV24: =IFERROR(#REF!/#REF!*100-100,"") | AW24: =#REF!-#REF! -> #REF! | AX24: =IFERROR(#REF!/#REF!*100-100,"") | AY24: =#REF!-#REF! -> #REF! | AZ24: =IFERROR(#REF!/#REF!*100-100,"") | BA24: =#REF!-#REF! -> #REF! | BB24: =IFERROR(#REF!/I24*100-100,"") | BC24: =#REF!-I24 -> #REF! | BE24: =#REF!-I24 -> #REF! | BF24: =#REF!-I24 -> #REF! | BG24: =#REF!-#REF! -> #REF! | BH24: =#REF!-#REF! -> #REF!
B25: =B241 | S25: =IFERROR(M25/L25-1,"") | T25: =IFERROR(P25/O25-1,"") | U25: =IFERROR(P25-O25,"") -> 0 | V25: =IFERROR(N25-M25,"") -> 0 | AE25: =C25 -> 0 | AF25: =D25 -> 0 | AG25: =E25 -> 0 | AH25: =F25 -> 0 | AI25: =G25 -> 0 | AJ25: =H25 -> 0 | AK25: =I25 -> 0 | AL25: =J25 -> 0 | ... AT25: =R25 -> 0 | AU25: =AU241 | AV25: =IFERROR(#REF!/#REF!*100-100,"") | AW25: =#REF!-#REF! -> #REF! | AX25: =IFERROR(#REF!/#REF!*100-100,"") | AY25: =#REF!-#REF! -> #REF! | AZ25: =IFERROR(#REF!/#REF!*100-100,"") | BA25: =#REF!-#REF! -> #REF! | BB25: =IFERROR(#REF!/I25*100-100,"") | BC25: =#REF!-I25 -> #REF!
B26: =B242 -> Financial Assets | C26: =C242 -> 23.3 | D26: =D242 -> 23.3 | E26: =E242 -> 22.9 | F26: =F242 -> 22.9 | G26: =G242 -> 22.9 | H26: =H242 -> -23.391351 | I26: =I242 -> -61.464912 | ... R26: =R242 -> 1.1088 | S26: =IFERROR(M26/L26-1,"") -> 0.3661202 | T26: =IFERROR(P26/O26-1,"") -> -1.597359 | U26: =IFERROR(P26-O26,"") -> 44.1403 | V26: =IFERROR(N26-M26,"") -> -65.586309 | AD26: Ngaahi Koloa Fakapa'anga | AE26: =C26 -> 23.3 | AF26: =D26 -> 23.3 | AG26: =E26 -> 22.9 | AH26: =F26 -> 22.9 | AI26: =G26 -> 22.9 | AJ26: =H26 -> -23.391351 | AK26: =I26 -> -61.464912 | AL26: =J26 -> -4.2645628 | ... AT26: =R26 -> 1.1088 | AU26: =AU242 -> Financial Assets | AV26: =IFERROR(#REF!/#REF!*100-100,"") | AW26: =#REF!-#REF! -> #REF! | AX26: =IFERROR(#REF!/#REF!*100-100,"") | AY26: =#REF!-#REF! -> #REF! | AZ26: =IFERROR(#REF!/#REF!*100-100,"") | BA26: =#REF!-#REF! -> #REF! | BB26: =IFERROR(#REF!/I26*100-100,"") | BC26: =#REF!-I26 -> #REF! | BE26: =#REF!-I26 -> #REF! | BF26: =#REF!-I26 -> #REF! | BG26: =#REF!-#REF! -> #REF! | BH26: =#REF!-#REF! -> #REF!
B27: =B243 -> Domestic | C27: =C243 -> 23.3 | D27: =D243 -> 23.3 | E27: =E243 -> 22.9 | F27: =F243 -> 22.9 | G27: =G243 -> 22.9 | H27: =H243 -> -23.391351 | I27: =SUM(I28:I30) -> -61.464912 | J27: =SUM(J28:J30) -> -4.2645628 | K27: =SUM(K28:K30) -> 22.800025 | L27: =SUM(L28:L30) -> 20.882137 | M27: =SUM(M28:M30) -> 28.527509 | N27: =SUM(N28:N30) -> -37.0588 | O27: =SUM(O28:O30) -> -27.6333 | P27: =SUM(P28:P30) -> 16.507 | ... R27: =SUM(R28:R30) -> 1.1088 | S27: =IFERROR(M27/L27-1,"") -> 0.3661202 | T27: =IFERROR(P27/O27-1,"") -> -1.597359 | U27: =IFERROR(P27-O27,"") -> 44.1403 | V27: =IFERROR(N27-M27,"") -> -65.586309 | AD27: Fakalotofonua | AE27: =C27 -> 23.3 | AF27: =D27 -> 23.3 | AG27: =E27 -> 22.9 | AH27: =F27 -> 22.9 | AI27: =G27 -> 22.9 | AJ27: =H27 -> -23.391351 | AK27: =I27 -> -61.464912 | AL27: =J27 -> -4.2645628 | ... AT27: =R27 -> 1.1088 | AU27: =AU243 -> Domestic | AV27: =IFERROR(#REF!/#REF!*100-100,"") | AW27: =#REF!-#REF! -> #REF! | AX27: =IFERROR(#REF!/#REF!*100-100,"") | AY27: =#REF!-#REF! -> #REF! | AZ27: =IFERROR(#REF!/#REF!*100-100,"") | BA27: =#REF!-#REF! -> #REF! | BB27: =IFERROR(#REF!/I27*100-100,"") | BC27: =#REF!-I27 -> #REF! | BE27: =#REF!-I27 -> #REF! | BF27: =#REF!-I27 -> #REF! | BG27: =#REF!-#REF! -> #REF! | BH27: =#REF!-#REF! -> #REF!
B28: =B244 -> Currency and deposits | C28: =C244 -> 15.8 | D28: =D244 -> 15.8 | E28: =E244 -> 15.8 | F28: =F244 -> 15.8 | G28: =G244 -> 15.8 | H28: =H244 -> -16.27208 | I28: =I244 -> -61.698662 | ... R28: =R244 -> 0.838 | S28: =IFERROR(M28/L28-1,"") -> -0.051292807 | T28: =IFERROR(P28/O28-1,"") -> -1.0977487 | U28: =IFERROR(P28-O28,"") -> 30.7284 | V28: =IFERROR(N28-M28,"") -> -76.877962 | AD28: Pa'anga moe Fakahu pa'anga | AE28: =C28 -> 15.8 | AF28: =D28 -> 15.8 | AG28: =E28 -> 15.8 | AH28: =F28 -> 15.8 | AI28: =G28 -> 15.8 | AJ28: =H28 -> -16.27208 | AK28: =I28 -> -61.698662 | AL28: =J28 -> -4.0200312 | ... AT28: =R28 -> 0.838 | AU28: =AU244 -> Currency and deposits | AV28: =IFERROR(#REF!/#REF!*100-100,"") | AW28: =#REF!-#REF! -> #REF! | AX28: =IFERROR(#REF!/#REF!*100-100,"") | AY28: =#REF!-#REF! -> #REF! | AZ28: =IFERROR(#REF!/#REF!*100-100,"") | BA28: =#REF!-#REF! -> #REF! | BB28: =IFERROR(#REF!/I28*100-100,"") | BC28: =#REF!-I28 -> #REF! | BE28: =#REF!-I28 -> #REF! | BF28: =#REF!-I28 -> #REF! | BG28: =#REF!-#REF! -> #REF! | BH28: =#REF!-#REF! -> #REF!
B29: =B246 -> Loans | C29: =C246 -> 7.1 | D29: =D246 -> 7.1 | E29: =E246 -> 7.1 | F29: =F246 -> 7.1 | G29: =G246 -> 7.1 | H29: =H246 -> -7.1192713 | I29: =I246 -> 0.23375012 | ... R29: =R246 -> 0.3708 | S29: =IFERROR(M29/L29-1,"") -> -17.353501 | T29: =IFERROR(P29/O29-1,"") -> 34.666752 | U29: =IFERROR(P29-O29,"") -> 13.4819 | V29: =IFERROR(N29-M29,"") -> 8.8916532 | AD29: No atu | AE29: =C29 -> 7.1 | AF29: =D29 -> 7.1 | AG29: =E29 -> 7.1 | AH29: =F29 -> 7.1 | AI29: =G29 -> 7.1 | AJ29: =H29 -> -7.1192713 | AK29: =I29 -> 0.23375012 | AL29: =J29 -> -0.24453162 | ... AT29: =R29 -> 0.3708 | AU29: =AU246 -> Loans | AV29: =IFERROR(#REF!/#REF!*100-100,"") | AW29: =#REF!-#REF! -> #REF! | AX29: =IFERROR(#REF!/#REF!*100-100,"") | AY29: =#REF!-#REF! -> #REF! | AZ29: =IFERROR(#REF!/#REF!*100-100,"") | BA29: =#REF!-#REF! -> #REF! | BB29: =IFERROR(#REF!/I29*100-100,"") | BC29: =#REF!-I29 -> #REF! | BE29: =#REF!-I29 -> #REF! | BF29: =#REF!-I29 -> #REF! | BG29: =#REF!-#REF! -> #REF! | BH29: =#REF!-#REF! -> #REF!
B30: =B247 -> Equity and inveestment fund shares | C30: =C247 -> 0.4 | D30: =D247 -> 0.4 | E30: =E247 -> 0 | F30: =F247 -> 0 | G30: =G247 -> 0 | H30: =H247 -> 0 | I30: =I247 -> 0 | ... R30: =R247 -> -0.1 | S30: =IFERROR(M30/L30-1,"") -> -3.5 | T30: =IFERROR(P30/O30-1,"") -> 2.3333333 | U30: =IFERROR(P30-O30,"") -> -0.07 | V30: =IFERROR(N30-M30,"") -> 2.4 | AD30: Ngaahi 'Inasi | AE30: =C30 -> 0.4 | AF30: =D30 -> 0.4 | AG30: =E30 -> 0 | AH30: =F30 -> 0 | AI30: =G30 -> 0 | AJ30: =H30 -> 0 | AK30: =I30 -> 0 | AL30: =J30 -> 0 | ... AT30: =R30 -> -0.1 | AU30: =AU247 -> Shares and other equity | AV30: =IFERROR(#REF!/#REF!*100-100,"") | AW30: =#REF!-#REF! -> #REF! | AX30: =IFERROR(#REF!/#REF!*100-100,"") | AY30: =#REF!-#REF! -> #REF! | AZ30: =IFERROR(#REF!/#REF!*100-100,"") | BA30: =#REF!-#REF! -> #REF! | BB30: =IFERROR(#REF!/I30*100-100,"") | BC30: =#REF!-I30 -> #REF! | BE30: =#REF!-I30 -> #REF! | BF30: =#REF!-I30 -> #REF! | BG30: =#REF!-#REF! -> #REF! | BH30: =#REF!-#REF! -> #REF!
B31: =B248 -> Financial Liabilities | C31: =C248 -> -4.6726 | D31: =D248 -> 175.0844 | E31: =E248 -> -13.410921 | F31: =F248 -> 0 | G31: =G248 -> 0 | H31: =H248 -> -13.410921 | I31: =I248 -> 1.9447665 | ... R31: =R248 -> -51.2257 | S31: =IFERROR(M31/L31-1,"") -> -26.656246 | T31: =IFERROR(P31/O31-1,"") -> -0.43109439 | U31: =IFERROR(P31-O31,"") -> 12.2952 | V31: =IFERROR(N31-M31,"") -> 29.698461 | AC31: 43.9 | AD31: Ngaahi Mo'ua Fakapa'anga | AE31: =C31 -> -4.6726 | AF31: =D31 -> 175.0844 | AG31: =E31 -> -13.410921 | AH31: =F31 -> 0 | AI31: =G31 -> 0 | AJ31: =H31 -> -13.410921 | AK31: =I31 -> 1.9447665 | AL31: =J31 -> 14.048361 | ... AT31: =R31 -> -51.2257 | AU31: =AU248 -> Financial Liabilities | AV31: =IFERROR(#REF!/#REF!*100-100,"") | AW31: =#REF!-#REF! -> #REF! | AX31: =IFERROR(#REF!/#REF!*100-100,"") | AY31: =#REF!-#REF! -> #REF! | AZ31: =IFERROR(#REF!/#REF!*100-100,"") | BA31: =#REF!-#REF! -> #REF! | BB31: =IFERROR(#REF!/I31*100-100,"") | BC31: =#REF!-I31 -> #REF! | BE31: =#REF!-I31 -> #REF! | BF31: =#REF!-I31 -> #REF! | BG31: =#REF!-#REF! -> #REF! | BH31: =#REF!-#REF! -> #REF!
B32: =B249 -> Domestic | C32: =C249 -> 0.874 | D32: =D249 -> 1.9 | E32: =E249 -> 0.0006 | F32: =F249 -> 0 | G32: =G249 -> 0 | H32: =H249 -> 0.0006 | I32: =I249 -> 12.860428 | ... R32: =R249 -> 0 | S32: =IFERROR(M32/L32-1,"") -> 20.282353 | T32: =IFERROR(P32/O32-1,"") -> 0.7245627 | U32: =IFERROR(P32-O32,"") -> 14.705 | V32: =IFERROR(N32-M32,"") -> 31.809 | AD32: Fakalotofonua | AE32: =C32 -> 0.874 | AF32: =D32 -> 1.9 | AG32: =E32 -> 0.0006 | AH32: =F32 -> 0 | AI32: =G32 -> 0 | AJ32: =H32 -> 0.0006 | AK32: =I32 -> 12.860428 | AL32: =J32 -> -2.639 | ... AT32: =R32 -> 0 | AU32: =AU249 -> Domestic | AV32: =IFERROR(#REF!/#REF!*100-100,"") | AW32: =#REF!-#REF! -> #REF! | AX32: =IFERROR(#REF!/#REF!*100-100,"") | AY32: =#REF!-#REF! -> #REF! | AZ32: =IFERROR(#REF!/#REF!*100-100,"") | BA32: =#REF!-#REF! -> #REF! | BB32: =IFERROR(#REF!/I32*100-100,"") | BC32: =#REF!-I32 -> #REF! | BE32: =#REF!-I32 -> #REF! | BF32: =#REF!-I32 -> #REF! | BG32: =#REF!-#REF! -> #REF! | BH32: =#REF!-#REF! -> #REF!
B33: =B251 -> Loans | C33: =C251 -> 16.074 | D33: =D251 -> 17.1 | E33: =E251 -> 15.1536 | F33: =F251 -> 0 | G33: =G251 -> 0 | H33: =H251 -> 15.1536 | I33: =I251 -> 31.860428 | ... R33: =R251 -> 0 | S33: =IFERROR(M33/L33-1,"") -> -1 | T33: =IFERROR(P33/O33-1,"") | U33: =IFERROR(P33-O33,"") -> 0 | V33: =IFERROR(N33-M33,"") -> 0 | AD33: Ngaahi No | AE33: =C33 -> 16.074 | AF33: =D33 -> 17.1 | AG33: =E33 -> 15.1536 | AH33: =F33 -> 0 | AI33: =G33 -> 0 | AJ33: =H33 -> 15.1536 | AK33: =I33 -> 31.860428 | AL33: =J33 -> 12.376 | ... AT33: =R33 -> 0 | AU33: =AU251 -> Loans | AV33: =IFERROR(#REF!/#REF!*100-100,"") | AW33: =#REF!-#REF! -> #REF! | AX33: =IFERROR(#REF!/#REF!*100-100,"") | AY33: =#REF!-#REF! -> #REF! | AZ33: =IFERROR(#REF!/#REF!*100-100,"") | BA33: =#REF!-#REF! -> #REF! | BB33: =IFERROR(#REF!/I33*100-100,"") | BC33: =#REF!-I33 -> #REF! | BE33: =#REF!-I33 -> #REF! | BF33: =#REF!-I33 -> #REF! | BG33: =#REF!-#REF! -> #REF! | BH33: =#REF!-#REF! -> #REF!
B34: =B252 -> Repayments | C34: =C252 -> 15.2 | D34: =D252 -> 15.2 | E34: =E252 -> 15.153 | F34: =F252 -> 0 | G34: =G252 -> 0 | H34: =H252 -> 15.153 | I34: =I252 -> 19 | ... R34: =R252 -> 5.508 | S34: =IFERROR(M34/L34-1,"") -> 0.11317881 | T34: =IFERROR(P34/O34-1,"") -> 0.46494655 | U34: =IFERROR(P34-O34,"") -> 6.307 | V34: =IFERROR(N34-M34,"") -> -3.243 | AD34: Totongi Fakafoki 'o e No | AE34: =C34 -> 15.2 | AF34: =D34 -> 15.2 | AG34: =E34 -> 15.153 | AH34: =F34 -> 0 | AI34: =G34 -> 0 | AJ34: =H34 -> 15.153 | AK34: =I34 -> 19 | AL34: =J34 -> 15.015 | ... AT34: =R34 -> 5.508 | AU34: =AU252 -> Repayments | AV34: =IFERROR(#REF!/#REF!*100-100,"") | AW34: =#REF!-#REF! -> #REF! | AX34: =IFERROR(#REF!/#REF!*100-100,"") | AY34: =#REF!-#REF! -> #REF! | AZ34: =IFERROR(#REF!/#REF!*100-100,"") | BA34: =#REF!-#REF! -> #REF! | BB34: =IFERROR(#REF!/I34*100-100,"") | BC34: =#REF!-I34 -> #REF! | BE34: =#REF!-I34 -> #REF! | BF34: =#REF!-I34 -> #REF! | BG34: =#REF!-#REF! -> #REF! | BH34: =#REF!-#REF! -> #REF!
B35: =B253 -> External | C35: =C253 -> -5.5466 | D35: =D253 -> -14.9156 | E35: =E253 -> -13.411521 | F35: =F253 -> 0 | G35: =G253 -> 0 | H35: =H253 -> -13.411521 | I35: =I253 -> -10.915661 | ... R35: =R253 -> -51.2257 | S35: =IFERROR(M35/L35-1,"") -> -24.620643 | T35: =IFERROR(P35/O35-1,"") -> 0.049365063 | U35: =IFERROR(P35-O35,"") -> -2.4098 | V35: =IFERROR(N35-M35,"") -> -2.1105394 | AD35: Tu'apule'anga | AE35: =C35 -> -5.5466 | AF35: =D35 -> -14.9156 | AG35: =E35 -> -13.411521 | AH35: =F35 -> 0 | AI35: =G35 -> 0 | AJ35: =H35 -> -13.411521 | AK35: =I35 -> -10.915661 | AL35: =J35 -> 16.687361 | ... AT35: =R35 -> -51.2257 | AU35: =AU253 -> Foreign | AV35: =IFERROR(#REF!/#REF!*100-100,"") | AW35: =#REF!-#REF! -> #REF! | AX35: =IFERROR(#REF!/#REF!*100-100,"") | AY35: =#REF!-#REF! -> #REF! | AZ35: =IFERROR(#REF!/#REF!*100-100,"") | BA35: =#REF!-#REF! -> #REF! | BB35: =IFERROR(#REF!/I35*100-100,"") | BC35: =#REF!-I35 -> #REF! | BE35: =#REF!-I35 -> #REF! | BF35: =#REF!-I35 -> #REF! | BG35: =#REF!-#REF! -> #REF! | BH35: =#REF!-#REF! -> #REF!
B36: =B254 -> Loans | C36: =C254 -> 12.7545 | D36: =D254 -> 0 | E36: =E254 -> 0 | F36: =F254 -> 0 | G36: =G254 -> 0 | H36: =H254 -> 0 | I36: =I254 -> 0 | ... R36: =R254 -> 0 | S36: =IFERROR(M36/L36-1,"") -> -1 | T36: =IFERROR(P36/O36-1,"") | U36: =IFERROR(P36-O36,"") -> 0 | V36: =IFERROR(N36-M36,"") -> 0 | AD36: Ngaahi No | AE36: =C36 -> 12.7545 | AF36: =D36 -> 0 | AG36: =E36 -> 0 | AH36: =F36 -> 0 | AI36: =G36 -> 0 | AJ36: =H36 -> 0 | AK36: =I36 -> 0 | AL36: =J36 -> 22.947534 | ... AT36: =R36 -> 0 | AU36: =AU254 -> Loans | AV36: =IFERROR(#REF!/#REF!*100-100,"") | AW36: =#REF!-#REF! -> #REF! | AX36: =IFERROR(#REF!/#REF!*100-100,"") | AY36: =#REF!-#REF! -> #REF! | AZ36: =IFERROR(#REF!/#REF!*100-100,"") | BA36: =#REF!-#REF! -> #REF! | BB36: =IFERROR(#REF!/I36*100-100,"") | BC36: =#REF!-I36 -> #REF! | BE36: =#REF!-I36 -> #REF! | BF36: =#REF!-I36 -> #REF! | BG36: =#REF!-#REF! -> #REF! | BH36: =#REF!-#REF! -> #REF!
B37: =B255 -> Repayments | C37: =C255 -> -18.3011 | D37: =D255 -> -14.9156 | E37: =E255 -> -13.411521 | F37: =F255 -> 0 | G37: =G255 -> 0 | H37: =H255 -> 13.411521 | I37: =I255 -> 10.915661 | ... R37: =R255 -> 51.2257 | S37: =IFERROR(M37/L37-1,"") -> 1.3102026 | T37: =IFERROR(P37/O37-1,"") -> 0.049365063 | U37: =IFERROR(P37-O37,"") -> 2.4098 | V37: =IFERROR(N37-M37,"") -> 2.1105394 | AD37: Totongi Fakafoki 'o e No | AE37: =C37 -> -18.3011 | AF37: =D37 -> -14.9156 | AG37: =E37 -> -13.411521 | AH37: =F37 -> 0 | AI37: =G37 -> 0 | AJ37: =H37 -> 13.411521 | AK37: =I37 -> 10.915661 | AL37: =J37 -> 6.2601733 | ... AT37: =R37 -> 51.2257 | AU37: =AU255 -> Repayments | AV37: =IFERROR(#REF!/#REF!*100-100,"") | AW37: =#REF!-#REF! -> #REF! | AX37: =IFERROR(#REF!/#REF!*100-100,"") | AY37: =#REF!-#REF! -> #REF! | AZ37: =IFERROR(#REF!/#REF!*100-100,"") | BA37: =#REF!-#REF! -> #REF! | BB37: =IFERROR(#REF!/I37*100-100,"") | BC37: =#REF!-I37 -> #REF! | BE37: =#REF!-I37 -> #REF! | BF37: =#REF!-I37 -> #REF! | BG37: =#REF!-#REF! -> #REF! | BH37: =#REF!-#REF! -> #REF!
T38: =IFERROR(N38/M38-1,"")
B39: Memorandum | AV39: =IFERROR(#REF!/#REF!*100-100,"") | AW39: =#REF!-#REF! -> #REF! | AX39: =IFERROR(#REF!/#REF!*100-100,"") | AY39: =#REF!-#REF! -> #REF! | AZ39: =IFERROR(#REF!/#REF!*100-100,"") | BA39: =#REF!-#REF! -> #REF! | BB39: =IFERROR(#REF!/I39*100-100,"") | BC39: =#REF!-I39 -> #REF! | BE39: =#REF!-I39 -> #REF! | BF39: =#REF!-I39 -> #REF! | BG39: =#REF!-#REF! -> #REF! | BH39: =#REF!-#REF! -> #REF!
B40: additional information | C40: =C196 -> 2013/14 Actual | D40: =D196 -> 2014/15 Actual | E40: =E196 -> 2015/16 Actual | F40: =F196 -> 2016/17 Actual | G40: =G196 -> 2017/18 Actual | H40: =H196 -> 2018/19 Actual | I40: =I196 -> 2019/20 Actual | J40: =J196 -> 2020/21 Actual | ... R40: =R196 -> Budget Estimate 2028/29
B41: Principal Repayment | C41: =C37+C34 -> -3.1011 | D41: =D37+D34 -> 0.2844 | E41: =E37+E34 -> 1.7414785 | F41: =F37+F34 -> 0 | G41: =G37+G34 -> 0 | H41: =H37+H34 -> 28.564521 | I41: =I37+I34 -> 29.915661 | J41: =J37+J34 -> 21.275173 | ... R41: =R37+R34 -> 56.7337
B42: interest | C42: -2.37 | D42: -1.37 | E42: -0.37 | F42: 0.63 | G42: 1.63 | H42: 2.63 | I42: 3.63 | J42: 4.63 | K42: 5.63 | L42: 6.63 | M42: 7.63 | N42: 6.84 | O42: 7.84 | P42: 6.84 | Q42: 6.84 | R42: 7.84
B43: Total | C43: =SUM(C41:C42) -> -5.4711 | D43: =SUM(D41:D42) -> -1.0856 | E43: =SUM(E41:E42) -> 1.3714785 | F43: =SUM(F41:F42) -> 0.63 | G43: =SUM(G41:G42) -> 1.63 | H43: =SUM(H41:H42) -> 31.194521 | I43: =SUM(I41:I42) -> 33.545661 | J43: =SUM(J41:J42) -> 25.905173 | ... R43: =SUM(R41:R42) -> 64.5737 | AV43: =IFERROR(#REF!/#REF!*100-100,"") | AW43: =#REF!-#REF! -> #REF! | AX43: =IFERROR(#REF!/#REF!*100-100,"") | AY43: =#REF!-#REF! -> #REF! | AZ43: =IFERROR(#REF!/#REF!*100-100,"") | BA43: =#REF!-#REF! -> #REF! | BB43: =IFERROR(#REF!/I43*100-100,"") | BC43: =#REF!-I43 -> #REF! | BE43: =#REF!-I43 -> #REF! | BF43: =#REF!-I43 -> #REF! | BG43: =#REF!-#REF! -> #REF! | BH43: =#REF!-#REF! -> #REF!
B45: Table 14: Total Revenues ($m) | AD45: Tepile 14: Fakakatoa Pa'anga humai ($m) | AU45: Table 14: Total Revenues (% change) | AV45: =IFERROR(#REF!/#REF!*100-100,"") | AW45: =#REF!-#REF! -> #REF! | AX45: =IFERROR(#REF!/#REF!*100-100,"") | AY45: =#REF!-#REF! -> #REF! | AZ45: =IFERROR(#REF!/#REF!*100-100,"") | BA45: =#REF!-#REF! -> #REF! | BB45: =IFERROR(#REF!/I45*100-100,"") | BC45: =#REF!-I45 -> #REF!
C46: =C3 -> 2013/14 Actual | D46: =D3 -> 2014/15 Actual | E46: =E3 -> 2015/16 Actual | F46: =F3 -> 2016/17 Actual | G46: =G196 -> 2017/18 Actual | H46: =H196 -> 2018/19 Actual | I46: =I196 -> 2019/20 Actual | J46: =J196 -> 2020/21 Actual | K46: =K196 -> 2021/22 Actual | L46: =L196 -> Budget Estimate 2022/23 | M46: =M196 -> Actual FY2025 | N46: =N196 -> Budget Estimate 2025/26 | ... R46: =R196 -> Budget Estimate 2028/29 | S46: growth | T46: growth | U46: variance | V46: variance | AE46: =AE3 -> 2013/14 Ola | AF46: =AF3 -> 2014/15 Ola | AG46: =AG3 -> 2015/16 Ola | AH46: =AH3 -> 2016/17 Ola | AI46: =AI61 -> 2017/18 Ola | AJ46: =AJ61 -> 2018/19 Ola | AK46: =AK61 -> 2019/20 Ola | AL46: =AL61 -> 2020/21 Ola | AM46: 2021/22 Ola | AN46: 2022/23 Patiseti | AO46: 2024/25 Ola Fakaangaanga | AP46: 2025/26 Patiseti | AQ46: 25/26 Esitimeti Liliu | AR46: 2026/27 Patiseti Fakaangaanga | AS46: 2027/28 Patiseti Fakaangaanga | AT46: 2028/29 Patiseti Fakaangaanga | AV46: =IFERROR(#REF!/#REF!*100-100,"") | AW46: =#REF!-#REF! -> #REF! | AX46: =IFERROR(#REF!/#REF!*100-100,"") | AY46: =#REF!-#REF! -> #REF! | AZ46: =IFERROR(#REF!/#REF!*100-100,"") | BA46: =#REF!-#REF! -> #REF! | BB46: =IFERROR(#REF!/I46*100-100,"") | BC46: =#REF!-I46 -> #REF!
B47: Revenue | AD47: Pa'anga Humai | AU47: Revenue | AV47: =IFERROR(#REF!/#REF!*100-100,"") | AW47: =#REF!-#REF! -> #REF! | AX47: =IFERROR(#REF!/#REF!*100-100,"") | AY47: =#REF!-#REF! -> #REF! | AZ47: =IFERROR(#REF!/#REF!*100-100,"") | BA47: =#REF!-#REF! -> #REF! | BB47: =IFERROR(#REF!/I47*100-100,"") | BC47: =#REF!-I47 -> #REF!
B48: Taxes | C48: =C198 -> 136.70375 | D48: =D198 -> 158.80394 | E48: =E198 -> 180.20929 | F48: =F198 -> 211.64654 | G48: =G198 -> 235.38101 | H48: =H198 -> 243.03983 | I48: =I198 -> 238.58682 | J48: =J198 -> 244.80973 | ... R48: =R198 -> 414.7709 | S48: =O48/N48-1 -> -0.012310511 | T48: =IFERROR(P48/O48-1,"") -> 0.026574606 | U48: =N48-O48 -> 4.2727 | V48: =P48-O48 -> 9.1099 | AD48: Pa'anga Humai Mei he Tukuhau | AE48: =AE198 -> 136.70375 | AF48: =AF198 -> 158.80394 | AG48: =AG198 -> 180.20929 | AH48: =AH198 -> 211.64654 | AI48: =G48 -> 235.38101 | AJ48: =H48 -> 243.03983 | AK48: =I48 -> 238.58682 | AL48: =J48 -> 244.80973 | AM48: =K48 -> 257.92941 | AN48: =L48 -> 253.3142 | AO48: =M48 -> 328.47224 | AP48: =N48 -> 347.0774 | ... AT48: =R48 -> 414.7709 | AU48: Taxes | AV48: =IFERROR(#REF!/#REF!*100-100,"") | AW48: =#REF!-#REF! -> #REF! | AX48: =IFERROR(#REF!/#REF!*100-100,"") | AY48: =#REF!-#REF! -> #REF! | AZ48: =IFERROR(#REF!/#REF!*100-100,"") | BA48: =#REF!-#REF! -> #REF! | BB48: =IFERROR(#REF!/I48*100-100,"") | BC48: =#REF!-I48 -> #REF! | BE48: =#REF!-I48 -> #REF! | BF48: =#REF!-I48 -> #REF! | BG48: =#REF!-#REF! -> #REF! | BH48: =#REF!-#REF! -> #REF!
B49: Grants | C49: =C204 -> 69.651027 | D49: =D204 -> 47.581465 | E49: =E204 -> 55.014133 | F49: =F204 -> 69.950284 | G49: =G204 -> 190.7776 | H49: =H204 -> 212.49741 | I49: =I204 -> 213.67327 | J49: =J204 -> 239.52715 | ... R49: =R204 -> 269.3 | S49: =O49/N49-1 -> -0.24037706 | T49: =IFERROR(P49/O49-1,"") -> 0.19906929 | U49: =N49-O49 -> 122.4 | V49: =P49-O49 -> 77 | AD49: Ngaahi tokoni fakapa'anga | AE49: =AE204 -> 69.651027 | AF49: =AF204 -> 47.581465 | AG49: =AG204 -> 55.014133 | AH49: =AH204 -> 69.950284 | AI49: =G49 -> 190.7776 | AJ49: =H49 -> 212.49741 | AK49: =I49 -> 213.67327 | AL49: =J49 -> 239.52715 | AM49: =K49 -> 279.8 | AN49: =L49 -> 409.1 | AO49: =M49 -> 426.6 | AP49: =N49 -> 509.2 | ... AT49: =R49 -> 269.3 | AU49: Grants | AV49: =IFERROR(#REF!/#REF!*100-100,"") | AW49: =#REF!-#REF! -> #REF! | AX49: =IFERROR(#REF!/#REF!*100-100,"") | AY49: =#REF!-#REF! -> #REF! | AZ49: =IFERROR(#REF!/#REF!*100-100,"") | BA49: =#REF!-#REF! -> #REF! | BB49: =IFERROR(#REF!/I49*100-100,"") | BC49: =#REF!-I49 -> #REF! | BE49: =#REF!-I49 -> #REF! | BF49: =#REF!-I49 -> #REF! | BG49: =#REF!-#REF! -> #REF! | BH49: =#REF!-#REF! -> #REF!
B50: Non-tax or Other revenue | C50: =C207 -> 24.277237 | D50: =D207 -> 26.280934 | E50: =E207 -> 29.174282 | F50: =F207 -> 27.645465 | G50: =G207 -> 26.258695 | H50: =H207 -> 26.223942 | I50: =I207 -> 30.11433 | J50: =J207 -> 27.863622 | ... R50: =R207 -> 70.0219 | S50: =O50/N50-1 -> -0.15930533 | T50: =IFERROR(P50/O50-1,"") -> 0.00033054691 | U50: =N50-O50 -> 11.6947 | V50: =P50-O50 -> 0.0204 | AD50: Pa'anga Humai Makehe | AE50: =AE207 -> 24.277237 | AF50: =AF207 -> 26.280934 | AG50: =AG207 -> 29.174282 | AH50: =AH207 -> 27.645465 | AI50: =G50 -> 26.258695 | AJ50: =H50 -> 26.223942 | AK50: =I50 -> 30.11433 | AL50: =J50 -> 27.863622 | AM50: =K50 -> 22.460016 | AN50: =L50 -> 28.2733 | AO50: =M50 -> 55.869071 | AP50: =N50 -> 73.4106 | ... AT50: =R50 -> 70.0219 | AU50: Non-tax or Other revenue | AV50: =IFERROR(#REF!/#REF!*100-100,"") | AW50: =#REF!-#REF! -> #REF! | AX50: =IFERROR(#REF!/#REF!*100-100,"") | AY50: =#REF!-#REF! -> #REF! | AZ50: =IFERROR(#REF!/#REF!*100-100,"") | BA50: =#REF!-#REF! -> #REF! | BB50: =IFERROR(#REF!/I50*100-100,"") | BC50: =#REF!-I50 -> #REF! | BE50: =#REF!-I50 -> #REF! | BF50: =#REF!-I50 -> #REF! | BG50: =#REF!-#REF! -> #REF! | BH50: =#REF!-#REF! -> #REF!
B51: Total | C51: =SUM(C48:C50) -> 230.63201 | D51: =SUM(D48:D50) -> 232.66634 | E51: =SUM(E48:E50) -> 264.39771 | F51: =SUM(F48:F50) -> 309.24229 | G51: =SUM(G48:G50) -> 452.41731 | H51: =SUM(H48:H50) -> 481.76119 | I51: =SUM(I48:I50) -> 482.37442 | J51: =SUM(J48:J50) -> 512.2005 | ... R51: =SUM(R48:R50) -> 754.0928 | S51: =O51/N51-1 -> -0.14883208 | T51: =IFERROR(P51/O51-1,"") -> 0.10884375 | U51: =N51-O51 -> 138.3674 | V51: =P51-O51 -> 86.1303 | AD51: Fakakatoa | AE51: =SUM(AE48:AE50) -> 230.63201 | AF51: =SUM(AF48:AF50) -> 232.66634 | AG51: =SUM(AG48:AG50) -> 264.39771 | AH51: =SUM(AH48:AH50) -> 309.24229 | AI51: =G51 -> 452.41731 | AJ51: =H51 -> 481.76119 | AK51: =I51 -> 482.37442 | AL51: =J51 -> 512.2005 | AM51: =K51 -> 560.18942 | AN51: =L51 -> 690.6875 | AO51: =M51 -> 810.94132 | AP51: =N51 -> 929.688 | ... AT51: =R51 -> 754.0928 | AU51: Total | AV51: =IFERROR(#REF!/#REF!*100-100,"") | AW51: =#REF!-#REF! -> #REF! | AX51: =IFERROR(#REF!/#REF!*100-100,"") | AY51: =#REF!-#REF! -> #REF! | AZ51: =IFERROR(#REF!/#REF!*100-100,"") | BA51: =#REF!-#REF! -> #REF! | BB51: =IFERROR(#REF!/I51*100-100,"") | BC51: =#REF!-I51 -> #REF!
AX52: =IFERROR(#REF!/#REF!*100-100,"") | AY52: =#REF!-#REF! -> #REF! | BB52: =IFERROR(#REF!/I52*100-100,"") | BC52: =#REF!-I52 -> #REF!
AX53: =IFERROR(#REF!/#REF!*100-100,"") | AY53: =#REF!-#REF! -> #REF! | BB53: =IFERROR(#REF!/I53*100-100,"") | BC53: =#REF!-I53 -> #REF!
B54: Revenue to GDP | C54: =C196 -> 2013/14 Actual | D54: =D196 -> 2014/15 Actual | E54: =E196 -> 2015/16 Actual | F54: =F196 -> 2016/17 Actual | G54: =G196 -> 2017/18 Actual | H54: =H196 -> 2018/19 Actual | I54: =I196 -> 2019/20 Actual | J54: =J196 -> 2020/21 Actual | ... R54: =R196 -> Budget Estimate 2028/29 | AX54: =IFERROR(#REF!/#REF!*100-100,"") | AY54: =#REF!-#REF! -> #REF! | BB54: =IFERROR(#REF!/I54*100-100,"") | BC54: =#REF!-I54 -> #REF!
B55: Taxes | C55: =C48/C$268 -> 0.17148149 | D55: =D48/D$268 -> 0.18701589 | E55: =E48/E$268 -> 0.19323531 | F55: =F48/F$268 -> 0.20797208 | G55: =G48/G$268 -> 0.21930917 | H55: =H48/H$268 -> 0.20894071 | I55: =I48/I$268 -> 0.21304297 | J55: =J48/J$268 -> 0.22905102 | ... R55: =R48/R$268 -> 0.1966298 | AJ55: =AJ48/AJ$268 -> 0.20894071 | AK55: =AK48/AK$268 -> 0.21304297 | AL55: =AL48/AL$268 -> #REF! | AM55: =AM48/AM$268 -> #REF! | AX55: =IFERROR(#REF!/#REF!*100-100,"") | AY55: =#REF!-#REF! -> #REF! | BB55: =IFERROR(#REF!/I55*100-100,"") | BC55: =#REF!-I55 -> #REF!
B56: Grants | C56: =C49/C$268 -> 0.087370405 | D56: =D49/D$268 -> 0.056034439 | E56: =E49/E$268 -> 0.058990705 | F56: =F49/F$268 -> 0.068735855 | G56: =G49/G$268 -> 0.17775128 | H56: =H49/H$268 -> 0.18268347 | I56: =I49/I$268 -> 0.19079674 | J56: =J49/J$268 -> 0.22410849 | ... R56: =R49/R$268 -> 0.12766664 | AJ56: =AJ49/AJ$268 -> 0.18268347 | AK56: =AK49/AK$268 -> 0.19079674 | AL56: =AL49/AL$268 -> #REF! | AM56: =AM49/AM$268 -> #REF! | AV56: =IFERROR(#REF!/#REF!*100-100,"") | AW56: =#REF!-#REF! -> #REF! | AX56: =IFERROR(#REF!/#REF!*100-100,"") | AY56: =#REF!-#REF! -> #REF! | AZ56: =IFERROR(#REF!/#REF!*100-100,"") | BA56: =#REF!-#REF! -> #REF! | BB56: =IFERROR(#REF!/I56*100-100,"") | BC56: =#REF!-I56 -> #REF!
B57: Non-tax or Other revenue | C57: =C50/C$268 -> 0.030453421 | D57: =D50/D$268 -> 0.030949812 | E57: =E50/E$268 -> 0.031283078 | F57: =F50/F$268 -> 0.027165503 | G57: =G50/G$268 -> 0.024465748 | H57: =H50/H$268 -> 0.022544655 | I57: =I50/I$268 -> 0.026890196 | J57: =J50/J$268 -> 0.026070005 | ... R57: =R50/R$268 -> 0.033195174 | AJ57: =AJ50/AJ$268 -> 0.022544655 | AK57: =AK50/AK$268 -> 0.026890196 | AL57: =AL50/AL$268 -> #REF! | AM57: =AM50/AM$268 -> #REF! | AV57: =IFERROR(#REF!/#REF!*100-100,"") | AW57: =#REF!-#REF! -> #REF! | AX57: =IFERROR(#REF!/#REF!*100-100,"") | AY57: =#REF!-#REF! -> #REF! | AZ57: =IFERROR(#REF!/#REF!*100-100,"") | BA57: =#REF!-#REF! -> #REF! | BB57: =IFERROR(#REF!/I57*100-100,"") | BC57: =#REF!-I57 -> #REF!
B58: Total | C58: =C51/C$268 -> 0.28930531 | D58: =D51/D$268 -> 0.27400014 | E58: =E51/E$268 -> 0.2835091 | F58: =F51/F$268 -> 0.30387344 | G58: =G51/G$268 -> 0.4215262 | H58: =H51/H$268 -> 0.41416884 | I58: =I51/I$268 -> 0.43072991 | J58: =J51/J$268 -> 0.47922951 | ... R58: =R51/R$268 -> 0.35749161 | AJ58: =AJ51/AJ$268 -> 0.41416884 | AK58: =AK51/AK$268 -> 0.43072991 | AL58: =AL51/AL$268 -> #REF! | AM58: =AM51/AM$268 -> #REF! | AV58: =IFERROR(#REF!/#REF!*100-100,"") | AW58: =#REF!-#REF! -> #REF! | AX58: =IFERROR(#REF!/#REF!*100-100,"") | AY58: =#REF!-#REF! -> #REF! | AZ58: =IFERROR(#REF!/#REF!*100-100,"") | BA58: =#REF!-#REF! -> #REF! | BB58: =IFERROR(#REF!/I58*100-100,"") | BC58: =#REF!-I58 -> #REF!
B60: Table 15: Tax Revenues ($m) | AD60: Tepile 15: Tukuhau Humai ($m) | AU60: Table 15: Tax Revenues (% change) | AV60: =IFERROR(#REF!/#REF!*100-100,"") | AW60: =#REF!-#REF! -> #REF! | AX60: =IFERROR(#REF!/#REF!*100-100,"") | AY60: =#REF!-#REF! -> #REF! | AZ60: =IFERROR(#REF!/#REF!*100-100,"") | BA60: =#REF!-#REF! -> #REF! | BB60: =IFERROR(#REF!/I60*100-100,"") | BC60: =#REF!-I60 -> #REF!
C61: =C3 -> 2013/14 Actual | D61: =D3 -> 2014/15 Actual | E61: =E3 -> 2015/16 Actual | F61: =F3 -> 2016/17 Actual | G61: =G196 -> 2017/18 Actual | H61: =H196 -> 2018/19 Actual | I61: =I196 -> 2019/20 Actual | J61: =J196 -> 2020/21 Actual | K61: =K196 -> 2021/22 Actual | L61: =L196 -> Budget Estimate 2022/23 | M61: =M196 -> Actual FY2025 | N61: =N196 -> Budget Estimate 2025/26 | ... R61: =R196 -> Budget Estimate 2028/29 | AE61: =AE3 -> 2013/14 Ola | AF61: =AF3 -> 2014/15 Ola | AG61: =AG3 -> 2015/16 Ola | AH61: =AH3 -> 2016/17 Ola | AI61: =AI78 -> 2017/18 Ola | AJ61: =AJ78 -> 2018/19 Ola | AK61: =AK78 -> 2019/20 Ola | AL61: =AL78 -> 2020/21 Ola | AM61: 2021/22 Ola | AN61: 2022/23 Patiseti | AO61: =AO3 -> 2024/25 Ola Fakaangaanga | AP61: =AP3 -> 2025/26 Patiseti | AQ61: =AQ3 -> 25/26 Esitimeti Liliu | AR61: =AR3 -> 2026/27 Patiseti Fakaangaanga | AS61: =AS3 -> 2027/28 Patiseti Fakaangaanga | AT61: =AT3 -> 2028/29 Patiseti Fakaangaanga | AV61: =IFERROR(#REF!/#REF!*100-100,"") | AW61: =#REF!-#REF! -> #REF! | AX61: =IFERROR(#REF!/#REF!*100-100,"") | AY61: =#REF!-#REF! -> #REF! | AZ61: =IFERROR(#REF!/#REF!*100-100,"") | BA61: =#REF!-#REF! -> #REF! | BB61: =IFERROR(#REF!/I61*100-100,"") | BC61: =#REF!-I61 -> #REF!
B62: Taxes | S62: growth | T62: growth | U62: variance | V62: contribution | AD62: Pa'anga Humai Mei he Tukuhau | AU62: Taxes | AV62: =IFERROR(#REF!/#REF!*100-100,"") | AW62: =#REF!-#REF! -> #REF! | AX62: =IFERROR(#REF!/#REF!*100-100,"") | AY62: =#REF!-#REF! -> #REF! | AZ62: =IFERROR(#REF!/#REF!*100-100,"") | BA62: =#REF!-#REF! -> #REF! | BB62: =IFERROR(#REF!/I62*100-100,"") | BC62: =#REF!-I62 -> #REF!
B63: Taxes on income, profits, and capital gains | C63: =C199 -> 28.752785 | D63: =D199 -> 37.430367 | E63: =E199 -> 35.778118 | F63: =F199 -> 46.107332 | G63: =G199 -> 48.843712 | H63: =H199 -> 55.230931 | I63: =I199 -> 52.469914 | J63: =J199 -> 48.570386 | ... R63: =R199 -> 94.2098 | S63: =O63/N63-1 -> -0.00046124817 | T63: =P63/O63-1 -> 0.039255967 | U63: =P63-O63 -> 3.088 | V63: =U63/$O$68 -> 0.0090080445 | AD63: Tukuhau vahenga moe tupu | AE63: =AE199 -> 28.752785 | AF63: =AF199 -> 37.430367 | AG63: =AG199 -> 35.778118 | AH63: =AH199 -> 46.107332 | AI63: =G63 -> 48.843712 | AJ63: =H63 -> 55.230931 | AK63: =I63 -> 52.469914 | AL63: =J63 -> 48.570386 | AM63: =K63 -> 55.576485 | AN63: =L63 -> 48.1527 | AO63: =M63 -> 76.885797 | AP63: =N63 -> 78.6995 | ... AT63: =R63 -> 94.2098 | AU63: Taxes on income, profits, and capital gains | AV63: =IFERROR(#REF!/#REF!*100-100,"") | AW63: =#REF!-#REF! -> #REF! | AX63: =IFERROR(#REF!/#REF!*100-100,"") | AY63: =#REF!-#REF! -> #REF! | AZ63: =IFERROR(#REF!/#REF!*100-100,"") | BA63: =#REF!-#REF! -> #REF! | BB63: =IFERROR(#REF!/I63*100-100,"") | BC63: =#REF!-I63 -> #REF! | BE63: =#REF!-I63 -> #REF! | BF63: =#REF!-I63 -> #REF! | BG63: =#REF!-#REF! -> #REF! | BH63: =#REF!-#REF! -> #REF!
B64: Taxes on property | C64: =C200 -> 0.11525238 | D64: =D200 -> 0.22751999 | E64: =E200 -> 0.30050338 | F64: =F200 -> 0.25042598 | G64: =G200 -> 0.28723159 | H64: =H200 -> 0.33722479 | I64: =I200 -> 0.3701936 | J64: =J200 -> 0.3296449 | ... R64: =R200 -> 1.6927 | S64: =O64/N64-1 -> 0.027543994 | T64: =P64/O64-1 -> 3.0469099 | U64: =P64-O64 -> 1.2276 | V64: =U64/$O$68 -> 0.0035810478 | AD64: Tukuhau 'o e koloa | AE64: =AE200 -> 0.11525238 | AF64: =AF200 -> 0.22751999 | AG64: =AG200 -> 0.30050338 | AH64: =AH200 -> 0.25042598 | AI64: =G64 -> 0.28723159 | AJ64: =H64 -> 0.33722479 | AK64: =I64 -> 0.3701936 | AL64: =J64 -> 0.3296449 | AM64: =K64 -> 0.29065711 | AN64: =L64 -> 0.3146 | AO64: =M64 -> 0.34542741 | AP64: =N64 -> 0.3921 | ... AT64: =R64 -> 1.6927 | AU64: Taxes on property | AV64: =IFERROR(#REF!/#REF!*100-100,"") | AW64: =#REF!-#REF! -> #REF! | AX64: =IFERROR(#REF!/#REF!*100-100,"") | AY64: =#REF!-#REF! -> #REF! | AZ64: =IFERROR(#REF!/#REF!*100-100,"") | BA64: =#REF!-#REF! -> #REF! | BB64: =IFERROR(#REF!/I64*100-100,"") | BC64: =#REF!-I64 -> #REF! | BE64: =#REF!-I64 -> #REF! | BF64: =#REF!-I64 -> #REF! | BG64: =#REF!-#REF! -> #REF! | BH64: =#REF!-#REF! -> #REF!
B65: Taxes on goods and services | C65: =C201 -> 92.747783 | D65: =D201 -> 103.57042 | E65: =E201 -> 124.31042 | F65: =F201 -> 141.29087 | G65: =G201 -> 157.5651 | H65: =H201 -> 155.26591 | I65: =I201 -> 160.72583 | J65: =J201 -> 173.35952 | ... R65: =R201 -> 278.1088 | S65: =O65/N65-1 -> 0.0055697338 | T65: =P65/O65-1 -> 0.024632941 | U65: =P65-O65 -> 5.6556 | V65: =U65/$O$68 -> 0.016498024 | AD65: Tukuhau 'o e koloa mo e ngaahi ngaue | AE65: =AE201 -> 92.747783 | AF65: =AF201 -> 103.57042 | AG65: =AG201 -> 124.31042 | AH65: =AH201 -> 141.29087 | AI65: =G65 -> 157.5651 | AJ65: =H65 -> 155.26591 | AK65: =I65 -> 160.72583 | AL65: =J65 -> 173.35952 | AM65: =K65 -> 177.15036 | AN65: =L65 -> 176.3755 | AO65: =M65 -> 218.06865 | AP65: =N65 -> 228.3233 | ... AT65: =R65 -> 278.1088 | AU65: Taxes on goods and services | AV65: =IFERROR(#REF!/#REF!*100-100,"") | AW65: =#REF!-#REF! -> #REF! | AX65: =IFERROR(#REF!/#REF!*100-100,"") | AY65: =#REF!-#REF! -> #REF! | AZ65: =IFERROR(#REF!/#REF!*100-100,"") | BA65: =#REF!-#REF! -> #REF! | BB65: =IFERROR(#REF!/I65*100-100,"") | BC65: =#REF!-I65 -> #REF! | BE65: =#REF!-I65 -> #REF! | BF65: =#REF!-I65 -> #REF! | BG65: =#REF!-#REF! -> #REF! | BH65: =#REF!-#REF! -> #REF!
B66: Taxes on international trade and transactions | C66: =C202 -> 15.087925 | D66: =D202 -> 17.57564 | E66: =E202 -> 19.820255 | F66: =F202 -> 23.997916 | G66: =G202 -> 28.684972 | H66: =H202 -> 32.205773 | I66: =I202 -> 25.020882 | J66: =J202 -> 22.550179 | ... R66: =R202 -> 40.7596 | S66: =O66/N66-1 -> -0.13914655 | T66: =P66/O66-1 -> -0.025225811 | U66: =P66-O66 -> -0.8613 | V66: =U66/$O$68 -> -0.0025125093 | AD66: Tukuhau mei he Fefakatau'aki | AE66: =AE202 -> 15.087925 | AF66: =AF202 -> 17.57564 | AG66: =AG202 -> 19.820255 | AH66: =AH202 -> 23.997916 | AI66: =G66 -> 28.684972 | AJ66: =H66 -> 32.205773 | AK66: =I66 -> 25.020882 | AL66: =J66 -> 22.550179 | AM66: =K66 -> 24.911905 | AN66: =L66 -> 28.4714 | AO66: =M66 -> 33.172365 | AP66: =N66 -> 39.6625 | ... AT66: =R66 -> 40.7596 | AU66: Taxes on international trade and transactions | AV66: =IFERROR(#REF!/#REF!*100-100,"") | AW66: =#REF!-#REF! -> #REF! | AX66: =IFERROR(#REF!/#REF!*100-100,"") | AY66: =#REF!-#REF! -> #REF! | AZ66: =IFERROR(#REF!/#REF!*100-100,"") | BA66: =#REF!-#REF! -> #REF! | BB66: =IFERROR(#REF!/I66*100-100,"") | BC66: =#REF!-I66 -> #REF! | BE66: =#REF!-I66 -> #REF! | BF66: =#REF!-I66 -> #REF! | BG66: =#REF!-#REF! -> #REF! | BH66: =#REF!-#REF! -> #REF!
B67: Other taxes | C67: =C203 | D67: =D203 | E67: =E203 | F67: =F203 | G67: =G203 | H67: =H203 -> 0 | I67: =I203 -> 0 | J67: =J203 -> 0 | ... R67: =R203 -> 0 | U67: =P67-O67 -> 0 | V67: =U67/$O$68 -> 0 | AD67: Ngaahi Tukuhau kehe | AE67: =AE203 | AF67: =AF203 | AG67: =AG203 | AH67: =AH203 | AI67: =G67 | AJ67: =H67 -> 0 | AK67: =I67 -> 0 | AL67: =J67 -> 0 | AM67: =K67 -> 0 | AN67: =L67 -> 0 | AO67: =M67 -> 0 | AP67: =N67 -> 0 | ... AT67: =R67 -> 0 | AU67: Other taxes | AV67: =IFERROR(#REF!/#REF!*100-100,"") | AW67: =#REF!-#REF! -> #REF! | AX67: =IFERROR(#REF!/#REF!*100-100,"") | AY67: =#REF!-#REF! -> #REF! | AZ67: =IFERROR(#REF!/#REF!*100-100,"") | BA67: =#REF!-#REF! -> #REF! | BB67: =IFERROR(#REF!/I67*100-100,"") | BC67: =#REF!-I67 -> #REF! | BE67: =#REF!-I67 -> #REF! | BF67: =#REF!-I67 -> #REF! | BG67: =#REF!-#REF! -> #REF! | BH67: =#REF!-#REF! -> #REF!
B68: Total | C68: =SUM(C63:C67) -> 136.70375 | D68: =SUM(D63:D67) -> 158.80394 | E68: =SUM(E63:E67) -> 180.20929 | F68: =SUM(F63:F67) -> 211.64654 | G68: =SUM(G63:G67) -> 235.38101 | H68: =SUM(H63:H67) -> 243.03983 | I68: =SUM(I63:I67) -> 238.58682 | J68: =SUM(J63:J67) -> 244.80973 | ... R68: =SUM(R63:R67) -> 414.7709 | S68: =O68/N68-1 -> -0.012310511 | T68: =P68/O68-1 -> 0.026574606 | U68: =P68-O68 -> 9.1099 | V68: =U68/$O$68 -> 0.026574606 | AD68: Fakakatoa | AE68: =SUM(AE63:AE67) -> 136.70375 | AF68: =SUM(AF63:AF67) -> 158.80394 | AG68: =SUM(AG63:AG67) -> 180.20929 | AH68: =SUM(AH63:AH67) -> 211.64654 | AI68: =G68 -> 235.38101 | AJ68: =H68 -> 243.03983 | AK68: =I68 -> 238.58682 | AL68: =J68 -> 244.80973 | AM68: =K68 -> 257.92941 | AN68: =L68 -> 253.3142 | AO68: =M68 -> 328.47224 | AP68: =N68 -> 347.0774 | ... AT68: =R68 -> 414.7709 | AU68: Total | AV68: =IFERROR(#REF!/#REF!*100-100,"") | AW68: =#REF!-#REF! -> #REF! | AX68: =IFERROR(#REF!/#REF!*100-100,"") | AY68: =#REF!-#REF! -> #REF! | AZ68: =IFERROR(#REF!/#REF!*100-100,"") | BA68: =#REF!-#REF! -> #REF! | BB68: =IFERROR(#REF!/I68*100-100,"") | BC68: =#REF!-I68 -> #REF!
AV69: =IFERROR(#REF!/#REF!*100-100,"") | AW69: =#REF!-#REF! -> #REF! | AX69: =IFERROR(#REF!/#REF!*100-100,"") | AY69: =#REF!-#REF! -> #REF! | AZ69: =IFERROR(#REF!/#REF!*100-100,"") | BA69: =#REF!-#REF! -> #REF! | BB69: =IFERROR(#REF!/I69*100-100,"") | BC69: =#REF!-I69 -> #REF!
C70: =C196 -> 2013/14 Actual | D70: =D196 -> 2014/15 Actual | E70: =E196 -> 2015/16 Actual | F70: =F196 -> 2016/17 Actual | G70: =G196 -> 2017/18 Actual | H70: =H196 -> 2018/19 Actual | I70: =I196 -> 2019/20 Actual | J70: =J196 -> 2020/21 Actual | ... R70: =R196 -> Budget Estimate 2028/29 | S70: growth | T70: growth | U70: variance | V70: variance | AX70: =IFERROR(#REF!/#REF!*100-100,"") | AY70: =#REF!-#REF! -> #REF! | BB70: =IFERROR(#REF!/I70*100-100,"") | BC70: =#REF!-I70 -> #REF!
B71: Taxes on income, profits, and capital gains | C71: =C63/C$68 -> 0.21032917 | D71: =D63/D$68 -> 0.23570175 | E71: =E63/E$68 -> 0.19853647 | F71: =F63/F$68 -> 0.21785063 | G71: =G63/G$68 -> 0.20750914 | H71: =H63/H$68 -> 0.22725053 | I71: =I63/I$68 -> 0.21991958 | J71: =J63/J$68 -> 0.19840056 | ... R71: =R63/R$68 -> 0.22713696 | S71: =O71/N71-1 -> 0.011996951 | T71: =P71/O71-1 -> 0.012353082 | U71: =N71-O71 -> -0.0027202983 | V71: =P71-O71 -> 0.0028346548 | AX71: =IFERROR(#REF!/#REF!*100-100,"") | AY71: =#REF!-#REF! -> #REF! | BB71: =IFERROR(#REF!/I71*100-100,"") | BC71: =#REF!-I71 -> #REF!
B72: Taxes on property | C72: =C64/C$68 -> 0.00084308136 | D72: =D64/D$68 -> 0.0014327099 | E72: =E64/E$68 -> 0.0016675243 | F72: =F64/F$68 -> 0.0011832274 | G72: =G64/G$68 -> 0.0012202836 | H72: =H64/H$68 -> 0.0013875289 | I72: =I64/I$68 -> 0.0015516096 | J72: =J64/J$68 -> 0.0013465351 | ... R72: =R64/R$68 -> 0.0040810481 | S72: =O72/N72-1 -> 0.040351249 | T72: =P72/O72-1 -> 2.9421488 | U72: =N72-O72 -> -4.558558e-05 | V72: =P72-O72 -> 0.0034579216 | AX72: =IFERROR(#REF!/#REF!*100-100,"") | AY72: =#REF!-#REF! -> #REF! | BB72: =IFERROR(#REF!/I72*100-100,"") | BC72: =#REF!-I72 -> #REF!
B73: Taxes on goods and services | C73: =C65/C$68 -> 0.67845825 | D73: =D65/D$68 -> 0.65219046 | E73: =E65/E$68 -> 0.68981136 | F73: =F65/F$68 -> 0.66757938 | G73: =G65/G$68 -> 0.66940445 | H73: =H65/H$68 -> 0.63884962 | I73: =I65/I$68 -> 0.67365763 | J73: =J65/J$68 -> 0.70813982 | ... R73: =R65/R$68 -> 0.67051184 | S73: =O73/N73-1 -> 0.018103103 | T73: =P73/O73-1 -> -0.0018914026 | U73: =N73-O73 -> -0.011909044 | V73: =P73-O73 -> -0.0012667754 | AX73: =IFERROR(#REF!/#REF!*100-100,"") | AY73: =#REF!-#REF! -> #REF! | BB73: =IFERROR(#REF!/I73*100-100,"") | BC73: =#REF!-I73 -> #REF!
B74: Taxes on international trade and transactions | C74: =C66/C$68 -> 0.1103695 | D74: =D66/D$68 -> 0.11067508 | E74: =E66/E$68 -> 0.10998464 | F74: =F66/F$68 -> 0.11338676 | G74: =G66/G$68 -> 0.12186613 | H74: =H66/H$68 -> 0.13251232 | I74: =I66/I$68 -> 0.10487118 | J74: =J66/J$68 -> 0.092113084 | ... R74: =R66/R$68 -> 0.098270153 | S74: =O74/N74-1 -> -0.12841692 | T74: =P74/O74-1 -> -0.050459477 | U74: =N74-O74 -> 0.014674928 | V74: =P74-O74 -> -0.005025801 | AX74: =IFERROR(#REF!/#REF!*100-100,"") | AY74: =#REF!-#REF! -> #REF! | BB74: =IFERROR(#REF!/I74*100-100,"") | BC74: =#REF!-I74 -> #REF!
B75: Other taxes | C75: =C67/C$68 -> #VALUE! | D75: =D67/D$68 -> #VALUE! | E75: =E67/E$68 -> #VALUE! | F75: =F67/F$68 -> #VALUE! | G75: =G67/G$68 -> #VALUE! | H75: =H67/H$68 -> 0 | I75: =I67/I$68 -> 0 | J75: =J67/J$68 -> 0 | ... R75: =R67/R$68 -> 0 | S75: =O75/N75-1 -> #DIV/0! | T75: =P75/O75-1 -> #DIV/0! | U75: =N75-O75 -> 0 | V75: =P75-O75 -> 0 | AX75: =IFERROR(#REF!/#REF!*100-100,"") | AY75: =#REF!-#REF! -> #REF! | BB75: =IFERROR(#REF!/I75*100-100,"") | BC75: =#REF!-I75 -> #REF!
B76: Total | C76: =C68/C$68 -> 1 | D76: =D68/D$68 -> 1 | E76: =E68/E$68 -> 1 | F76: =F68/F$68 -> 1 | G76: =G68/G$68 -> 1 | H76: =H68/H$68 -> 1 | I76: =I68/I$68 -> 1 | J76: =J68/J$68 -> 1 | ... R76: =R68/R$68 -> 1 | S76: =O76/N76-1 -> 0 | T76: =P76/O76-1 -> 0 | U76: =N76-O76 -> 0 | V76: =P76-O76 -> 0 | AX76: =IFERROR(#REF!/#REF!*100-100,"") | AY76: =#REF!-#REF! -> #REF! | BB76: =IFERROR(#REF!/I76*100-100,"") | BC76: =#REF!-I76 -> #REF!
AX77: =IFERROR(#REF!/#REF!*100-100,"") | AY77: =#REF!-#REF! -> #REF! | BB77: =IFERROR(#REF!/I77*100-100,"") | BC77: =#REF!-I77 -> #REF!
C78: =C3 -> 2013/14 Actual | D78: =D3 -> 2014/15 Actual | E78: =E3 -> 2015/16 Actual | F78: =F3 -> 2016/17 Actual | G78: =G196 -> 2017/18 Actual | H78: =H196 -> 2018/19 Actual | I78: =I196 -> 2019/20 Actual | J78: =J196 -> 2020/21 Actual | K78: =K196 -> 2021/22 Actual | L78: =L196 -> Budget Estimate 2022/23 | M78: =M196 -> Actual FY2025 | N78: =N196 -> Budget Estimate 2025/26 | ... R78: =R196 -> Budget Estimate 2028/29 | AE78: =AE3 -> 2013/14 Ola | AF78: =AF3 -> 2014/15 Ola | AG78: =AG3 -> 2015/16 Ola | AH78: =AH3 -> 2016/17 Ola | AI78: =AI86 -> 2017/18 Ola | AJ78: =AJ86 -> 2018/19 Ola | AK78: =AK86 -> 2019/20 Ola | AL78: =AL86 -> 2020/21 Ola | AM78: 2021/22 Ola | AN78: 2022/23 Patiseti | AO78: =AO3 -> 2024/25 Ola Fakaangaanga | AP78: =AP3 -> 2025/26 Patiseti | AQ78: =AQ3 -> 25/26 Esitimeti Liliu | AR78: =AR3 -> 2026/27 Patiseti Fakaangaanga | AS78: =AS3 -> 2027/28 Patiseti Fakaangaanga | AT78: =AT3 -> 2028/29 Patiseti Fakaangaanga | AV78: =IFERROR(#REF!/#REF!*100-100,"") | AW78: =#REF!-#REF! -> #REF! | AX78: =IFERROR(#REF!/#REF!*100-100,"") | AY78: =#REF!-#REF! -> #REF! | AZ78: =IFERROR(#REF!/#REF!*100-100,"") | BA78: =#REF!-#REF! -> #REF! | BB78: =IFERROR(#REF!/I78*100-100,"") | BC78: =#REF!-I78 -> #REF!
B79: Taxes on goods and services | S79: growth | T79: growth | U79: variance | V79: variance | AD79: Tukuhau 'o e koloa mo e ngaahi ngaue | AU79: Taxes on goods and services | AV79: =IFERROR(#REF!/#REF!*100-100,"") | AW79: =#REF!-#REF! -> #REF! | AX79: =IFERROR(#REF!/#REF!*100-100,"") | AY79: =#REF!-#REF! -> #REF! | AZ79: =IFERROR(#REF!/#REF!*100-100,"") | BA79: =#REF!-#REF! -> #REF! | BB79: =IFERROR(#REF!/I79*100-100,"") | BC79: =#REF!-I79 -> #REF!
B80: General taxes on goods and services | C80: ='[6]GFS 2022_23 Budget'!E69/10^6 -> 60.740294 | D80: ='[6]GFS 2022_23 Budget'!F69/10^6 -> 64.945756 | E80: ='[6]GFS 2022_23 Budget'!G69/10^6 -> 74.890797 | F80: ='[6]GFS 2022_23 Budget'!H69/10^6 -> 83.380473 | G80: ='[6]GFS 2022_23 Budget'!I69/10^6 -> 93.158292 | H80: ='[6]GFS 2022_23 Budget'!O69/10^6 -> 94.773254 | I80: ='[6]GFS 2022_23 Budget'!BD69/10^6 -> 95.014441 | J80: ='[6]GFS 2022_23 Budget'!BJ69/10^6 -> 99.1399 | K80: =[7]Sum_Bud_data!BH15 -> 109.12051 | L80: =[7]Sum_Bud_data!BM15 -> 106.609 | M80: =[7]Sum_Bud_data!BR15 -> 132.60738 | N80: =[7]Sum_Bud_data!BW15 -> 139.2747 | O80: =[7]Sum_Bud_data!CB15 -> 142.93717 | P80: =[7]Sum_Bud_data!CG15 -> 145.0368 | Q80: =[7]Sum_Bud_data!CL15 -> 152.4829 | R80: =[7]Sum_Bud_data!CQ15 -> 154.2305 | S80: =O80/N80-1 -> 0.026296714 | T80: =P80/O80-1 -> 0.014689203 | U80: =N80-O80 -> -3.662467 | V80: =P80-O80 -> 2.099633 | AD80: Ngaahi Tukuhau he Koloa mo e Ngaue | AE80: =C80 -> 60.740294 | AF80: =D80 -> 64.945756 | AG80: =E80 -> 74.890797 | AH80: =F80 -> 83.380473 | AI80: =G80 -> 93.158292 | AJ80: =H80 -> 94.773254 | AK80: =I80 -> 95.014441 | AL80: =J80 -> 99.1399 | ... AT80: =R80 -> 154.2305 | AU80: General taxes on goods and services | AV80: =IFERROR(#REF!/#REF!*100-100,"") | AW80: =#REF!-#REF! -> #REF! | AX80: =IFERROR(#REF!/#REF!*100-100,"") | AY80: =#REF!-#REF! -> #REF! | AZ80: =IFERROR(#REF!/#REF!*100-100,"") | BA80: =#REF!-#REF! -> #REF! | BB80: =IFERROR(#REF!/I80*100-100,"") | BC80: =#REF!-I80 -> #REF! | BE80: =#REF!-I80 -> #REF! | BF80: =#REF!-I80 -> #REF! | BG80: =#REF!-#REF! -> #REF! | BH80: =#REF!-#REF! -> #REF!
