Workbook

Sheet Data
A1: Fiscal Indicators
B3: FY2018 | C3: FY2019 | D3: FY2020 | E3: FY2021 | F3: FY2022 | G3: FY2023 | H3: FY2024 | I3: FY2025 | J3: FY2026 | K3: FY2027 | L3: FY2028 | M3: FY2029
B4: 1998/99 | C4: 1999/00 | D4: 2000/01 | E4: 2001/02 | F4: 2002/03 | G4: 2003/04 | H4: 2004/05 | I4: 2005/06 | J4: 2006/07 | K4: 2007/08 | L4: 2008/09 | M4: 2009/10 | N4: 2010/11 | O4: 2011/12 | P4: 2012/13 | Q4: 2013/14 | R4: 2014/15 | S4: 2015/16 | T4: 2016/17 | U4: 2017/18 | V4: 2018/19 | W4: 2019/20 | X4: 2020/21 | Y4: 2021/22 | Z4: 2022/23 | AA4: 2023/24 | AB4: 2024/25 | AC4: 2025/26 | AD4: 2026/27 | AE4: 2027/28 | AF4: 2028/29
A5: Nominal GDP | B5: {=GDP!H30:R30} -> 849.27589 | C5: 851.8788 | D5: 872.3634 | E5: 871.52186 | F5: 845.38451 | G5: 845.02152 | H5: 856.58691 | I5: 894.93264 | J5: 936.61967 | K5: 978.86661 | L5: 1030.4138 | O5: =GDP!B33 -> 892.85834 | P5: =GDP!C33 -> 896.23017 | Q5: =GDP!D33 -> 914.06999 | R5: =GDP!E33 -> 924.25039 | S5: =GDP!F33 -> 985.23894 | T5: =GDP!G33 -> 1016.7894 | U5: =GDP!H33 -> 1023.7803 | V5: =GDP!I33 -> 1021.6464 | ... AE5: =GDP!R33 -> 1211.4138
A6: Real GDP | B6: {=GDP!H39:R39} -> 0.5 | C6: -0.3 | D6: 1.8 | E6: -0.9 | F6: -2.1 | G6: 2.8 | H6: 1.7 | I6: 2.7 | J6: 3.4 | K6: 3.7 | L6: 3.9 | U6: {=GDP!AA39:AK39} -> 0 | V6: 0 | W6: 0 | X6: 0 | Y6: 0 | Z6: 0 | AA6: 0 | AB6: 0 | AC6: 0 | AD6: 0 | AE6: 0
A9: Exports
A10: Imports
A13: Monetary Indicators
B16: 1998/99 | C16: 1999/00 | D16: 2000/01 | E16: 2001/02 | F16: 2002/03 | G16: 2003/04 | H16: 2004/05 | I16: 2005/06 | J16: 2006/07 | K16: 2007/08 | L16: 2008/09 | M16: 2009/10 | N16: 2010/11 | O16: 2011/12 | P16: 2012/13 | Q16: 2013/14 | R16: 2014/15 | S16: 2015/16 | T16: 2016/17 | U16: 2017/18 | V16: 2018/19 | W16: 2019/20 | X16: 2020/21 | Y16: 2021/22 | Z16: 2022/23 | AA16: 2023/24 | AB16: 2024/25 | AC16: 2025/26 | AD16: 2026/27 | AE16: 2027/28 | AF16: 2028/29
A17: Total private | B17: 290.46 | C17: 358.9 | D17: 393.93 | E17: 432.39 | F17: 429.38 | G17: 430.29 | H17: 426.02 | I17: 470/68 | J17: 499.7
A18: Housing | B18: 126.92 | C18: 170.65 | D18: 190.83 | E18: 201.21 | F18: 204.63 | G18: 206.26 | H18: 201.24 | I18: 197.44 | J18: 204.36
A19: Personal | B19: 56.72
A20: Business | B20: 93.3
A21: Agriculture | B21: 9.6 | M21: =204.36+66.7+211.1+17.5+0.1 -> 499.76
A22: Other | B22: =B17-SUM(B18:B21) -> 3.92 | M22: =197.44+58.29+196+18.9+0.1 -> 470.73
A23: Remmittances | M23: =170.65+57.58+117.3+12.1+1.2 -> 358.83
A24: Inflation
A25: Foreign Reserves
B27: 1998/99 | C27: 1999/00 | D27: 2000/01 | E27: 2001/02 | F27: 2002/03 | G27: 2003/04 | H27: 2004/05 | I27: 2005/06 | J27: 2006/07 | K27: 2007/08 | L27: 2008/09 | M27: 2009/10 | N27: 2010/11 | O27: 2011/12 | P27: 2012/13 | Q27: 2013/14 | R27: 2014/15 | S27: 2015/16 | T27: 2016/17 | U27: 2017/18 | V27: 2018/19 | W27: 2019/20 | X27: 2020/21 | Y27: 2021/22 | Z27: 2022/23 | AA27: 2023/24 | AB27: 2024/25 | AC27: 2025/26 | AD27: 2026/27 | AE27: 2027/28 | AF27: 2028/29

Sheet Sheet1
B2: AUD | C2: CAD | D2: CHF | E2: EUR | F2: FJD | G2: GBP | H2: JPY | I2: NZD | J2: SEK | K2: SGD | L2: USD | M2: WST | N2: CNY
A3: 44197 | B3: 0.5658 | C3: 0.5574 | D3: 0.3864 | E3: 0.3594 | F3: 0.868 | G3: 0.3206 | H3: 45.3713 | I3: 0.6085 | J3: 3.6319 | K3: 0.5835 | L3: 0.4386 | M3: 1.0277 | N3: 2.8532 | P3: =1/B3 -> 1.767409
A4: 44228 | B4: 0.5605 | C4: 0.5531 | D4: 0.3886 | E4: 0.3594 | F4: 0.8597 | G4: 0.3136 | H4: 45.7801 | I4: 0.6009 | J4: 3.6279 | K4: 0.5808 | L4: 0.4358 | M4: 1.0181 | N4: 2.8352
A5: 44256 | B5: 0.5677 | C5: 0.5518 | D5: 0.405 | E5: 0.3677 | F5: 0.868 | G5: 0.3157 | H5: 47.5581 | I5: 0.6134 | J5: 3.741 | K5: 0.5918 | L5: 0.439 | M5: 1.03 | N5: 2.8562
A6: 44287 | B6: 0.5697 | C6: 0.55 | D6: 0.4034 | E6: 0.3667 | F6: 0.8706 | G6: 0.317 | H6: 47.8379 | I6: 0.616 | J6: 3.7332 | K6: 0.5892 | L6: 0.4401 | M6: 1.0352 | N6: 2.8632
B9: =1/B3 -> 1.767409 | C9: =1/C3 -> 1.7940438 | D9: =1/D3 -> 2.5879917 | E9: =1/E3 -> 2.7824151 | F9: =1/F3 -> 1.1520737 | G9: =1/G3 -> 3.1191516 | H9: =1/H3 -> 0.022040365 | I9: =1/I3 -> 1.6433854 | ... N9: =1/N3 -> 0.35048367
B10: =1/B4 -> 1.7841213 | C10: =1/C4 -> 1.8079913 | D10: =1/D4 -> 2.5733402 | E10: =1/E4 -> 2.7824151 | F10: =1/F4 -> 1.1631965 | G10: =1/G4 -> 3.1887755 | H10: =1/H4 -> 0.021843552 | I10: =1/I4 -> 1.6641704 | ... N10: =1/N4 -> 0.3527088
B11: =1/B5 -> 1.7614937 | C11: =1/C5 -> 1.8122508 | D11: =1/D5 -> 2.4691358 | E11: =1/E5 -> 2.7196084 | F11: =1/F5 -> 1.1520737 | G11: =1/G5 -> 3.1675641 | H11: =1/H5 -> 0.021026912 | I11: =1/I5 -> 1.6302576 | ... N11: =1/N5 -> 0.35011554
A13: 45170 | B13: 0.6487 | C13: 0.5653 | D13: 0.3729 | E13: 0.3899 | F13: 0.9315 | G13: 0.3354 | H13: 61.5089 | I13: 0.7032 | J13: 4.6265 | K13: 0.5728 | L13: 0.4174 | M13: 1.1568 | N13: 3.0456
A14: 45200 | B14: 0.6542 | C14: 0.5702 | D14: 0.3742 | E14: 0.3933 | F14: 0.9358 | G14: 0.3409 | H14: 62.1124 | I14: 0.7034 | J14: 4.5847 | K14: 0.5736 | L14: 0.4163 | M14: 1.1574 | N14: 3.0422
A15: 45231 | B15: 0.6447 | C15: 0.5753 | D15: 0.3718 | E15: 0.3871 | F15: 0.9354 | G15: 0.3367 | H15: 62.7441 | I15: 0.6991 | J15: 4.4789 | K15: 0.5694 | L15: 0.4191 | M15: 1.1559 | N15: 3.0292
A16: 45261 | B16: 0.6348 | C16: 0.5709 | D16: 0.3661 | E16: 0.3887 | F16: 0.9335 | G16: 0.3347 | H16: 61.13 | I16: 0.6827 | J16: 4.3659 | K16: 0.57 | L16: 0.4246 | M16: 1.1526 | N16: 3.0335
B18: =1/B13 -> 1.5415446 | C18: =1/C13 -> 1.7689722 | D18: =1/D13 -> 2.6816841 | E18: =1/E13 -> 2.5647602 | F18: =1/F13 -> 1.0735373 | G18: =1/G13 -> 2.9815146 | H18: =1/H13 -> 0.01625781 | I18: =1/I13 -> 1.4220705 | ... N18: =1/N13 -> 0.32834253
B19: =1/B14 -> 1.5285845 | C19: =1/C14 -> 1.7537706 | D19: =1/D14 -> 2.6723677 | E19: =1/E14 -> 2.5425884 | F19: =1/F14 -> 1.0686044 | G19: =1/G14 -> 2.9334116 | H19: =1/H14 -> 0.016099845 | I19: =1/I14 -> 1.4216662 | ... N19: =1/N14 -> 0.32870949
B20: =1/B16 -> 1.5752993 | C20: =1/C16 -> 1.7516202 | D20: =1/D16 -> 2.7314941 | E20: =1/E16 -> 2.5726782 | F20: =1/F16 -> 1.0712373 | G20: =1/G16 -> 2.9877502 | H20: =1/H16 -> 0.01635858 | I20: =1/I16 -> 1.4647722 | ... N20: =1/N16 -> 0.32965222
A30: 44228 | B30: 0.5605 | C30: 0.5531 | D30: 0.3886 | E30: 0.3594 | F30: 0.8597 | G30: 0.3136 | H30: 45.7801 | I30: 0.6009 | J30: 3.6279 | K30: 0.5808 | L30: 0.4358 | M30: 1.0181 | N30: 2.8352
A31: 44256 | B31: 0.5677 | C31: 0.5518 | D31: 0.405 | E31: 0.3677 | F31: 0.868 | G31: 0.3157 | H31: 47.5581 | I31: 0.6134 | J31: 3.741 | K31: 0.5918 | L31: 0.439 | M31: 1.03 | N31: 2.8562
A32: 44287 | B32: 0.5697 | C32: 0.55 | D32: 0.4034 | E32: 0.3667 | F32: 0.8706 | G32: 0.317 | H32: 47.8379 | I32: 0.616 | J32: 3.7332 | K32: 0.5892 | L32: 0.4401 | M32: 1.0352 | N32: 2.8632
A33: 44317 | B33: 0.5712 | C33: 0.5388 | D33: 0.399 | E33: 0.3653 | F33: 0.8745 | G33: 0.315 | H33: 48.3874 | I33: 0.6142 | J33: 3.711 | K33: 0.5932 | L33: 0.4445 | M33: 1.0425 | N33: 2.8915
A34: 44348 | B34: 0.584 | C34: 0.5465 | D34: 0.4039 | E34: 0.3706 | F34: 0.8867 | G34: 0.3181 | H34: 49.1279 | I34: 0.6282 | J34: 3.7539 | K34: 0.5989 | L34: 0.4476 | M34: 1.0566 | N34: 2.9122
A35: 44378 | B35: 0.5955 | C35: 0.5548 | D35: 0.4047 | E35: 0.374 | F35: 0.889 | G35: 0.3199 | H35: 48.7389 | I35: 0.6335 | J35: 3.8198 | K35: 0.6029 | L35: 0.4432 | M35: 1.0594 | N35: 2.8834
A36: 44409 | B36: 0.6035 | C36: 0.556 | D36: 0.4015 | E36: 0.3745 | F36: 0.8913 | G36: 0.319 | H36: 48.3948 | I36: 0.6324 | J36: 3.8311 | K36: 0.6023 | L36: 0.4419 | M36: 1.0593 | N36: 2.875
A37: 44440 | B37: 0.6048 | C37: 0.562 | D37: 0.407 | E37: 0.3761 | F37: 0.8932 | G37: 0.3219 | H37: 48.7442 | I37: 0.6276 | J37: 3.8332 | K37: 0.6018 | L37: 0.444 | M37: 1.0613 | N37: 2.8886
A38: 44470 | B38: 0.5992 | C38: 0.5527 | D38: 0.4079 | E38: 0.382 | F38: 0.8975 | G38: 0.3235 | H38: 50.0625 | I38: 0.6292 | J38: 3.85 | K38: 0.6037 | L38: 0.4442 | M38: 1.1322 | N38: 2.8901
A39: 44501 | B39: 0.6039 | C39: 0.5559 | D39: 0.4061 | E39: 0.3873 | F39: 0.9032 | G39: 0.3278 | H39: 50.4136 | I39: 0.6296 | J39: 3.8977 | K39: 0.6045 | L39: 0.4431 | M39: 1.1776 | N39: 2.8826
A40: 44531 | B40: 0.6103 | C40: 0.5602 | D40: 0.4012 | E40: 0.3866 | F40: 0.9065 | G40: 0.3281 | H40: 49.7068 | I40: 0.6441 | J40: 3.9739 | K40: 0.6005 | L40: 0.4379 | M40: 1.1822 | N40: 2.8492
A41: 44562 | B41: 0.6068 | C41: 0.5531 | D41: 0.4001 | E41: 0.3855 | F41: 0.9091 | G41: 0.3216 | H41: 50.2553 | I41: 0.6457 | J41: 3.9733 | K41: 0.5965 | L41: 0.4392 | M41: 1.1786 | N41: 2.8574
... A64: 45261 | B64: 0.6348 | C64: 0.5709 | D64: 0.3661 | E64: 0.3887 | F64: 0.9335 | G64: 0.3347 | H64: 61.13 | I64: 0.6827 | J64: 4.3659 | K64: 0.57 | L64: 0.4246 | M64: 1.1526 | N64: 3.0335

Sheet GDP
B1: 2011/12 | C1: 2012/13 | D1: 2013/14 | E1: 2014/15 | F1: 2015/16 | G1: 2016/17 | H1: 2017/18 | I1: 2018/19 | J1: 2019/20r | K1: 2020/21 | L1: 2021/22 | M1: 2022/23 | N1: 2023/24f | O1: 2024/25f | P1: 2025/26f | Q1: 2026/27f | R1: 2027/28f
A2: GDP at constant prices (2016/17 prices TOPm) | B2: 11/12 | C2: 12/13 | D2: 13/14 | E2: 014/15 | F2: 15/16 | G2: 16/17 | H2: 17/18 | I2: 18/19 | J2: 19/20r | K2: 20/21 | L2: 21/22 | M2: 22/23p | N2: 23/24f | O2: 24/25f | P2: 25/26f | Q2: 26/27f | R2: 27/28f
A3: Primary Sector | B3: 169.69859 | C3: 176.41022 | D3: 180.81959 | E3: 177.66615 | F3: 175.43017 | G3: 171.01764 | H3: 175.43083 | I3: 184.61732 | J3: 190.34761 | K3: 188.66465 | L3: 193.96019 | M3: 225.76517 | N3: 205.3844 | O3: 211.75576 | P3: 218.84543 | Q3: 223.23684 | R3: 227.582
A4: Fishing | B4: 19.882251 | C4: 18.789285 | D4: 19.401575 | E4: 21.515773 | F4: 26.284896 | G4: 19.275379 | H4: 16.902112 | I4: 20.017383 | J4: 24.180957 | K4: 21.479261 | L4: 20.08561 | M4: 22.005838 | N4: 20.323987 | O4: 20.951918 | P4: 21.685634 | Q4: 22.521142 | R4: 23.46703
A5: Agriculture sector | B5: =B3-B4 -> 149.81634 | C5: =C3-C4 -> 157.62094 | D5: =D3-D4 -> 161.41802 | E5: =E3-E4 -> 156.15038 | F5: =F3-F4 -> 149.14528 | G5: =G3-G4 -> 151.74226 | H5: =H3-H4 -> 158.52872 | I5: =I3-I4 -> 164.59993 | ... R5: =R3-R4 -> 204.11497
A7: Industrial Sector | B7: 147.37107 | C7: 126.11531 | D7: 136.14788 | E7: 135.4453 | F7: 152.30931 | G7: 166.96926 | H7: 142.39497 | I7: 148.97079 | J7: 150.07564 | K7: 178.55675 | L7: 156.67568 | M7: 139.22309 | N7: 148.38986 | O7: 156.22828 | P7: 165.6293 | Q7: 176.26813 | R7: 188.4493
A8: Mining and Quarrying | B8: 8.3748478 | C8: 6.2277372 | D8: 6.5018693 | E8: 6.5964839 | F8: 5.8829426 | G8: 6.0752275 | H8: 6.7012654 | I8: 4.07248 | J8: 3.582104 | K8: 3.8959102 | L8: 4.1629465 | M8: 3.1365906 | N8: 3.4661345 | O8: 3.742383 | P8: 4.0685145 | Q8: 4.4472404 | R8: 4.8901624
A9: Manufacturing | B9: 52.579929 | C9: 53.620971 | D9: 54.105167 | E9: 55.742488 | F9: 59.881518 | G9: 60.803691 | H9: 59.722468 | I9: 56.849823 | J9: 58.88822 | K9: 63.242166 | L9: 50.450671 | M9: 43.844426 | N9: 44.219703 | O9: 44.743526 | P9: 45.577923 | Q9: 46.669029 | R9: 48.119752
A10: Electricity, water and waste | B10: 19.182777 | C10: 19.968971 | D10: 20.672116 | E10: 21.032341 | F10: 22.600144 | G10: 24.670702 | H10: 24.959273 | I10: 27.186355 | J10: 29.580339 | K10: 29.81205 | L10: 31.140483 | M10: 32.849121 | N10: 34.470554 | O10: 35.857304 | P10: 37.611802 | Q10: 39.403252 | R10: 41.251593
A11: Construction with PG | B11: 67.23352 | C11: 46.297629 | D11: 54.868731 | E11: 52.07399 | F11: 63.944706 | G11: 75.41964 | H11: 51.011965 | I11: 60.86213 | J11: 58.024978 | K11: 81.606622 | L11: 70.921576 | M11: 59.392947 | N11: 66.233466 | O11: 71.885067 | P11: 78.371059 | Q11: 85.748612 | R11: 94.187788
A13: Services | B13: 462.77236 | C13: 478.94222 | D13: 473.85559 | E13: 479.52048 | F13: 506.13364 | G13: 514.32219 | H13: 531.45008 | I13: 518.2907 | J13: 531.94016 | K13: 504.30046 | L13: 494.74864 | M13: 480.03326 | N13: 502.81265 | O13: 526.9486 | P13: 552.14494 | Q13: 579.36163 | R13: 614.38254
A14: Wholesale and retail | B14: 85.622069 | C14: 85.890326 | D14: 83.220297 | E14: 85.403676 | F14: 98.05526 | G14: 100.57109 | H14: 106.83039 | I14: 107.28075 | J14: 109.9771 | K14: 95.342798 | L14: 94.480372 | M14: 98.027347 | N14: 103.96124 | O14: 113.08472 | P14: 120.44521 | Q14: 128.28478 | R14: 141.766
A15: Transport and stroage | B15: 26.502738 | C15: 28.73089 | D15: 30.113165 | E15: 31.6649 | F15: 31.04777 | G15: 36.307791 | H15: 37.83137 | I15: 35.803383 | J15: 31.581557 | K15: 20.697273 | L15: 27.928567 | M15: 26.693429 | N15: 27.686276 | O15: 28.755321 | P15: 29.971259 | Q15: 31.281275 | R15: 32.736331
A16: Accommodation and food services | B16: 16.397103 | C16: 23.0714 | D16: 22.110733 | E16: 23.722849 | F16: 27.660261 | G16: 30.039452 | H16: 32.26387 | I16: 31.204923 | J16: 22.636194 | K16: 9.6439821 | L16: 9.2481585 | M16: 22.896288 | N16: 28.981748 | O16: 31.509971 | P16: 34.247998 | Q16: 37.513236 | R16: 41.40666
A17: Information and communication | B17: 23.965787 | C17: 24.623403 | D17: 19.694139 | E17: 22.221173 | F17: 22.696005 | G17: 22.541018 | H17: 24.644849 | I17: 24.515023 | J17: 31.979585 | K17: 28.384082 | L17: 33.523449 | M17: 26.693429 | N17: 27.686276 | O17: 28.755321 | P17: 29.971259 | Q17: 31.281275 | R17: 32.736331
A18: Financial and insurance activities | B18: 51.565478 | C18: 49.954849 | D18: 50.521214 | E18: 46.339033 | F18: 50.133918 | G18: 48.000121 | H18: 50.141445 | I18: 50.215538 | J18: 52.714182 | K18: 51.086318 | L18: 45.328479 | M18: 51.338974 | N18: 53.191208 | O18: 55.219836 | P18: 58.348185 | Q18: 61.458669 | R18: 64.749817
A19: Real estate activities | B19: 89.851459 | C19: 91.181959 | D19: 90.65428 | E19: 92.446127 | F19: 92.024895 | G19: 93.156887 | H19: 91.58141 | I19: 82.754757 | J19: 91.229375 | K19: 92.221385 | L19: 69.589777 | M19: 57.635425 | N19: 58.498389 | O19: 59.447125 | P19: 60.371771 | Q19: 61.373632 | R19: 62.489311
... A28: Other service activities | B28: 15.622307 | C28: 16.946642 | D28: 18.004236 | E28: 17.277097 | F28: 17.493388 | G28: 16.892726 | H28: 17.491225 | I28: 16.944047 | J28: 16.867938 | K28: 15.142074 | L28: 13.078175 | M28: 11.599664 | N28: 11.911286 | O28: 12.295455 | P28: 12.764931 | Q28: 13.309675 | R28: 14.184604
A30: GDP at factor cost | B30: =SUM(B3,B7,B13) -> 779.84202 | C30: =SUM(C3,C7,C13) -> 781.46775 | D30: =SUM(D3,D7,D13) -> 790.82306 | E30: =SUM(E3,E7,E13) -> 792.63194 | F30: =SUM(F3,F7,F13) -> 833.87312 | G30: =SUM(G3,G7,G13) -> 852.30909 | H30: =SUM(H3,H7,H13) -> 849.27589 | I30: =SUM(I3,I7,I13) -> 851.8788 | ... R30: =SUM(R3,R7,R13) -> 1030.4138
A31: add taxes (VAT, excise) | B31: 113.40877 | C31: 115.73105 | D31: 123.33268 | E31: 131.70366 | F31: 152.04009 | G31: 165.28878 | H31: 175.26784 | I31: 170.54906 | J31: 168.26164 | K31: 172.83243 | L31: 175.00135 | M31: 196.81656 | N31: 203.5 | O31: 194 | P31: 190 | Q31: 189 | R31: 183
A32: less subsidies on products | B32: 0.39245479 | C32: 0.96864186 | D32: 0.085755992 | E32: 0.085210143 | F32: 0.67427298 | G32: 0.80846416 | H32: 0.76338098 | I32: 0.78145856 | J32: 0.7586428 | K32: 0.71732133 | L32: 0.85543941 | M32: 1.0590751 | N32: 1.1 | O32: 1.1 | P32: 2 | Q32: 2 | R32: 2
A33: GDP at market prices | B33: =SUM(B30:B31)-B32 -> 892.85834 | C33: =SUM(C30:C31)-C32 -> 896.23017 | D33: =SUM(D30:D31)-D32 -> 914.06999 | E33: =SUM(E30:E31)-E32 -> 924.25039 | F33: =SUM(F30:F31)-F32 -> 985.23894 | G33: =SUM(G30:G31)-G32 -> 1016.7894 | H33: =SUM(H30:H31)-H32 -> 1023.7803 | I33: =SUM(I30:I31)-I32 -> 1021.6464 | ... R33: =SUM(R30:R31)-R32 -> 1211.4138
B37: 11/12 | C37: 12/13 | D37: 13/14 | E37: 014/15 | F37: 15/16 | G37: 16/17 | H37: 17/18 | I37: 18/19 | J37: 19/20r | K37: 20/21 | L37: 21/22 | M37: 22/23p | N37: 23/24f | O37: 24/25f | P37: 25/26f | Q37: 26/27f | R37: 27/28f
A38: GDP growth | C38: =(C33/B33-1)*100 -> 0.37764393 | D38: =(D33/C33-1)*100 -> 1.9905402 | E38: =(E33/D33-1)*100 -> 1.1137441 | F38: =(F33/E33-1)*100 -> 6.5987044 | G38: =(G33/F33-1)*100 -> 3.2023165 | H38: =(H33/G33-1)*100 -> 0.68755058 | I38: =(I33/H33-1)*100 -> -0.20843749 | J38: =(J33/I33-1)*100 -> 1.7833949 | ... R38: =(R33/Q33-1)*100 -> 3.9067272
A39: MOF GDP | H39: 0.5 | I39: -0.3 | J39: 1.8 | K39: -0.9 | L39: -2.1 | M39: 2.8 | N39: 1.7 | O39: 2.7 | P39: 3.4 | Q39: 3.7 | R39: 3.9
A40: IMF GDP | L40: -2.3 | M40: 2.1 | N40: 2.7 | O40: 2.3
A41: NRBT | F41: 6.6 | G41: 3.2 | H41: 0.53 | I41: -0.29 | J41: 1.81 | K41: -0.93 | L41: -2.13 | M41: 2.79 | N41: 1.72 | O41: 2.65 | P41: 2.45
A42: Statistics | D42: 1.9905402 | E42: 1.1137441 | F42: 6.5987044 | G42: 3.2023165 | H42: 0.52782727 | I42: -0.28520879 | J42: 1.8061874 | K42: -0.9349263 | L42: -2.1285445 | M42: 2.7901437 | N42: 1.7165411
A44: Primary
A45: Secondary
A46: Tertiary

Sheet Monthly indicators
B1: 37987 | C1: 38018 | D1: 38047 | E1: 38078 | F1: 38108 | G1: 38139 | H1: 38169 | I1: 38200 | J1: 38231 | K1: 38261 | L1: 38292 | M1: 38322 | N1: 38353 | O1: 38384 | P1: 38412 | Q1: 38443 | R1: 38473 | S1: 38504 | T1: 38534 | U1: 38565 | V1: 38596 | W1: 38626 | X1: 38657 | Y1: 38687 | Z1: 38718 | AA1: 38749 | AB1: 38777 | AC1: 38808 | AD1: 38838 | AE1: 38869 | AF1: 38899 | AG1: 38930 | AH1: 38961 | AI1: 38991 | AJ1: 39022 | AK1: 39052 | AL1: 39083 | AM1: 39114 | AN1: 39142 | AO1: 39173 | AP1: 39203 | AQ1: 39234 | AR1: 39264 | AS1: 39295 | AT1: 39326 | AU1: 39356 | AV1: 39387 | AW1: 39417 | AX1: 39448 | AY1: 39479 | AZ1: 39508 | BA1: 39539 | BB1: 39569 | BC1: 39600 | BD1: 39630 | BE1: 39661 | BF1: 39692 | BG1: 39722 | BH1: 39753 | BI1: 39783 | BJ1: 39814 | BK1: 39845 | BL1: 39873 | BM1: 39904 | BN1: 39934 | BO1: 39965 | BP1: 39995 | BQ1: 40026 | BR1: 40057 | BS1: 40087 | BT1: 40118 | BU1: 40148 | BV1: 40179 | BW1: 40210 | BX1: 40238 | BY1: 40269 | BZ1: 40299 | CA1: 40330 | CB1: 40360 | CC1: 40391 | CD1: 40422 | CE1: 40452 | CF1: 40483 | CG1: 40513 | CH1: 40544 | CI1: 40575 | CJ1: 40603 | CK1: 40634 | CL1: 40664 | CM1: 40695 | CN1: 40725 | CO1: 40756 | CP1: 40787 | CQ1: 40817 | CR1: 40848 | CS1: 40878 | CT1: 40909 | CU1: 40940 | CV1: 40969 | CW1: 41000 | CX1: 41030 | CY1: 41061 | CZ1: 41091 | DA1: 41122 | DB1: 41153 | DC1: 41183 | DD1: 41214 | DE1: 41244 | DF1: 41275 | DG1: 41306 | DH1: 41334 | DI1: 41365 | DJ1: 41395 | DK1: 41426 | DL1: 41456 | DM1: 41487 | DN1: 41518 | DO1: 41548 | DP1: 41579 | DQ1: 41609 | DR1: 41640 | DS1: 41671 | DT1: 41699 | DU1: 41730 | DV1: 41760 | DW1: 41791 | DX1: 41821 | DY1: 41852 | DZ1: 41883 | EA1: 41913 | EB1: 41944 | EC1: 41974 | ED1: 42005 | EE1: 42036 | EF1: 42064 | EG1: 42095 | EH1: 42125 | EI1: 42156 | EJ1: 42186 | EK1: 42217 | EL1: 42248 | EM1: 42278 | EN1: 42309 | EO1: 42339 | EP1: 42370 | EQ1: 42401 | ER1: 42430 | ES1: 42461 | ET1: 42491 | EU1: 42522 | EV1: 42552 | EW1: 42583 | EX1: 42614 | EY1: 42644 | EZ1: 42675 | FA1: 42705 | FB1: 42736 | FC1: 42767 | FD1: 42795 | FE1: 42826 | FF1: 42856 | FG1: 42887 | FH1: 42917 | FI1: 42948 | FJ1: 42979 | FK1: 43009 | FL1: 43040 | FM1: 43070 | FN1: 43101 | FO1: 43132 | FP1: 43160 | FQ1: 43191 | FR1: 43221 | FS1: 43252 | FT1: 43282 | FU1: 43313 | FV1: 43344 | FW1: 43374 | FX1: 43405 | FY1: 43435 | FZ1: 43466 | GA1: 43497 | GB1: 43525 | GC1: 43556 | GD1: 43586 | GE1: 43617 | GF1: 43647 | GG1: 43678 | GH1: 43709 | GI1: 43739 | GJ1: 43770 | GK1: 43800 | GL1: 43831 | GM1: 43862 | GN1: 43891 | GO1: 43922 | GP1: 43952 | GQ1: 43983 | GR1: 44013 | GS1: 44044 | GT1: 44075 | GU1: 44105 | GV1: 44136 | GW1: 44166 | GX1: 44197 | GY1: 44228 | GZ1: 44256 | HA1: 44287 | HB1: 44317 | HC1: 44348 | HD1: 44378 | HE1: 44409 | HF1: 44440 | HG1: 44470 | HH1: 44501 | HI1: 44531 | HJ1: 44562 | HK1: 44593 | HL1: 44621 | HM1: 44652 | HN1: 44682 | HO1: 44713 | HP1: 44743 | HQ1: 44774 | HR1: 44805 | HS1: 44835 | HT1: 44866 | HU1: 44896 | HV1: 44927 | HW1: 44958 | HX1: 44986 | HY1: 45017 | HZ1: 45047 | IA1: 45078 | IB1: 45108 | IC1: 45139 | ID1: 45170 | IE1: 45200 | IF1: 45231 | IG1: 45261 | IH1: 45292 | II1: 45323 | IJ1: 45352 | IK1: 45383 | IL1: 45413 | IM1: 45444 | IN1: 45474 | IO1: 45505 | IP1: 45536 | IQ1: 45566 | IR1: 45597 | IS1: 45627 | IT1: 45658 | IU1: 45689 | IV1: 45717 | IW1: 45748 | IX1: 45778 | IY1: 45809 | IZ1: 45839 | JA1: 45870 | JB1: 45901 | JC1: 45931 | JD1: 45962 | JE1: 45992 | JF1: 46023 | JG1: 46054 | JH1: 46082 | JI1: 46113 | JJ1: 46143 | JK1: 46174
A2: Foreign Reserves | B2: 54.9 | C2: 54.3 | D2: 56.3 | E2: 60.4 | F2: 63.9 | G2: 89.7 | H2: 89.5 | I2: 78.4 | J2: 79 | K2: 87.1 | L2: 91.5 | M2: 93.4 | N2: 87.1 | O2: 85.4 | P2: 80.9 | Q2: 83.2 | R2: 85.9 | S2: 82.121 | T2: 80.694 | U2: 81.5 | V2: 82.8 | W2: 82.4 | X2: 81.8 | Y2: 85.7 | Z2: 87.2 | AA2: 82.4 | AB2: 77.4 | AC2: 83.9 | AD2: 84.2 | AE2: 83.2 | AF2: 86.3 | AG2: 85.7 | AH2: 85.3 | AI2: 89.2 | AJ2: 84.6 | AK2: 84.2 | AL2: 85.4 | AM2: 84.2 | AN2: 90.4 | AO2: 80.6 | AP2: 84.9 | AQ2: 91.6 | AR2: 90.3 | AS2: 97.7 | AT2: 104.8 | AU2: 109 | AV2: 94.8 | AW2: 114.6 | AX2: 113.1 | AY2: 101.8 | AZ2: 96.3 | BA2: 89.7 | BB2: 89.5 | BC2: 89.1 | BD2: 86.2 | BE2: 91.3 | BF2: 128.5 | BG2: 121.6 | BH2: 122.7 | BI2: 123.9 | BJ2: 130.4 | BK2: 131.1 | BL2: 130.6 | BM2: 132.6 | BN2: 132.1 | BO2: 136.3 | BP2: 139.4 | BQ2: 159.2 | BR2: 163.3 | BS2: 160.7 | BT2: 159.9 | BU2: 160.4 | BV2: 160.8 | BW2: 153.5 | BX2: 155.5 | BY2: 161.4 | BZ2: 166.7 | CA2: 170.5 | CB2: 178 | CC2: 174.1 | CD2: 172.7 | CE2: 176.5 | CF2: 168 | CG2: 177.5 | CH2: 165.2 | CI2: 158.8 | CJ2: 157.1 | CK2: 160.1 | CL2: 170.2 | CM2: 203.8 | CN2: 197.6 | CO2: 212.4 | CP2: 208.1 | CQ2: 213.9 | CR2: 212.9 | CS2: 226 | CT2: 229.5 | CU2: 230.6 | CV2: 239.2 | CW2: 240.3 | CX2: 245 | CY2: 246.1 | CZ2: 251.1 | DA2: 252.7 | DB2: 247.9 | DC2: 246.2 | DD2: 253.7 | DE2: 257.3 | DF2: 260.3 | DG2: 258 | DH2: 244.8 | DI2: 258.4 | DJ2: 259.2 | DK2: 263.3 | DL2: 252.69805 | DM2: 256.2 | DN2: 254.2 | DO2: 260.6 | DP2: 265.4 | DQ2: 271.8 | DR2: 276.7 | DS2: 281.1 | DT2: 274.8 | DU2: 267.9 | DV2: 266.8 | DW2: 274.4 | DX2: 280.4 | DY2: 283.9 | DZ2: 270.9 | EA2: 271.5 | EB2: 267.9 | EC2: 293.6 | ED2: 287.2 | EE2: 281.3 | EF2: 270.2 | EG2: 272.1 | EH2: 281.1 | EI2: 289.7 | EJ2: 302.6 | EK2: 310.9 | EL2: 311.7 | EM2: 315.8 | EN2: 319 | EO2: 327.8 | EP2: 326.3 | EQ2: 328.5 | ER2: 317.3 | ES2: 322.9 | ET2: 330.7 | EU2: 354.9 | EV2: 367.4 | EW2: 366.3 | EX2: 363.7 | EY2: 367 | EZ2: 360.9 | FA2: 378.8 | FB2: 380.8 | FC2: 377.7 | FD2: 366 | FE2: 371.7 | FF2: 392.3 | FG2: 407.9 | FH2: 408.9 | FI2: 405 | FJ2: 403 | FK2: 413.6 | FL2: 424.8 | FM2: 422.6 | FN2: 424.1 | FO2: 448 | FP2: 447.7 | FQ2: 445.9 | FR2: 441.9 | FS2: 468.7 | FT2: 476.5 | FU2: 475 | FV2: 452.2 | FW2: 457.3 | FX2: 468.7 | FY2: 478.5 | FZ2: 478.9 | GA2: 473.5 | GB2: 465 | GC2: 464.2 | GD2: 468.3 | GE2: 484.3 | GF2: 492.9 | GG2: 491.8 | GH2: 490.8 | GI2: 489.3 | GJ2: 489.5 | GK2: 487.4 | GL2: 482.9 | GM2: 479.8 | GN2: 457.5 | GO2: 475.1 | GP2: 489.6 | GQ2: 543.8 | GR2: 555.9 | GS2: 556.1 | GT2: 576.5 | GU2: 581.6 | GV2: 590.2 | GW2: 675.6 | GX2: 705.3 | GY2: 692.4 | GZ2: 685.7 | HA2: 679.7 | HB2: 689.5 | HC2: 715.2 | HD2: 704.8 | HE2: 751.7 | HF2: 757 | HG2: 757 | HH2: 783.9 | HI2: 817.5 | HJ2: 856.1 | HK2: 867.3 | HL2: 861.4 | HM2: 884 | HN2: 880.4 | HO2: 871.2 | HP2: 884.8 | HQ2: 871 | HR2: 895.3 | HS2: 877 | HT2: 866.2 | HU2: 868.9 | HV2: 911.1 | HW2: 911.2 | HX2: 883.7 | HY2: 860.5 | HZ2: 864.8 | IA2: 921.4 | IB2: 945.2 | IC2: 920 | ID2: 886.1 | IE2: 891.2 | IF2: 892 | IG2: 901.7 | IH2: 894.7 | II2: 891.4 | IJ2: 868.7 | IK2: 904.8 | IL2: 893 | IM2: 924.3 | IN2: 909.1 | IO2: 905.5 | IP2: 887.4 | IQ2: 898.2 | IR2: 892.2 | IS2: 889.1 | IT2: 878 | IU2: 865.4 | IV2: 842.6 | IW2: 867.6 | IX2: 871.5 | IY2: 925.1 | IZ2: 921 | JA2: 921.1 | JB2: 897.2 | JC2: 939.5 | JD2: 940.3
A3: Import cover | B3: 3.3 | C3: 3.4 | D3: 3.4 | E3: 3.6 | F3: 3.9 | G3: 5.4 | H3: 5.5 | I3: 4.8 | J3: 4.8 | K3: 5.4 | L3: 5.3 | M3: 5.4 | N3: 5 | O3: 4.8 | P3: 4.5 | Q3: 4.7 | R3: 4.7 | S3: 4.4 | T3: 4.3 | U3: 4.3 | V3: 4.3 | W3: 4.2 | X3: 4.2 | Y3: 4.4 | Z3: 4.5 | AA3: 4.3 | AB3: 3.9 | AC3: 4.2 | AD3: 4.3 | AE3: 4.3 | AF3: 4.4 | AG3: 4.3 | AH3: 4.2 | AI3: 4.4 | AJ3: 4.3 | AK3: 4.3 | AL3: 4.3 | AM3: 4.2 | AN3: 4.5 | AO3: 4 | AP3: 4.1 | AQ3: 4.4 | AR3: 4.2 | AS3: 4.4 | AT3: 4.8 | AU3: 4.8 | AV3: 4 | AW3: 4.9 | AX3: 4.8 | AY3: 4.6 | AZ3: 4.1 | BA3: 3.6 | BB3: 3.6 | BC3: 3.5 | BD3: 3.3 | BE3: 3.6 | BF3: 5 | BG3: 4.8 | BH3: 4.9 | BI3: 4.6 | BJ3: 4.8 | BK3: 4.9 | BL3: 4.9 | BM3: 5.1 | BN3: 5 | BO3: 5.3 | BP3: 5.6 | BQ3: 6.5 | BR3: 6.7 | BS3: 6.7 | BT3: 6.7 | BU3: 6.8 | BV3: 6.6 | BW3: 6.2 | BX3: 6.2 | BY3: 6.3 | BZ3: 6.6 | CA3: 7.1 | CB3: 7.4144921 | CC3: 7.1968389 | CD3: 7.0980639 | CE3: 7.2389723 | CF3: 6.8364944 | CG3: 7.0582376 | CH3: 6.5 | CI3: 6.2 | CJ3: 6.0948848 | CK3: 6.3 | CL3: 6.5009958 | CM3: 7.6934505 | CN3: 7.5069763 | CO3: 8.0659795 | CP3: 7.8 | CQ3: 8 | CR3: 7.8 | CS3: 8.2 | CT3: 8.2 | CU3: 8.2 | CV3: 8.6 | CW3: 8.4916067 | CX3: 8.4708495 | CY3: 8.5494487 | CZ3: 8.6405513 | DA3: 8.5746951 | DB3: 8.511346 | DC3: 8.5 | DD3: 8.8 | DE3: 9 | DF3: 9.1 | DG3: 8.9 | DH3: 8.5 | DI3: 9 | DJ3: 9.1 | DK3: 9.1 | DL3: 8.8 | DM3: 9 | DN3: 8.9 | DO3: 8.9 | DP3: 9 | DQ3: 9.3 | DR3: 9.4 | DS3: 9.4 | DT3: 9.1 | DU3: 8.9 | DV3: 8.9 | DW3: 9.1 | DX3: 9.1 | DY3: 9.1 | DZ3: 8.4 | EA3: 8.2 | EB3: 8 | EC3: 8.7 | ED3: 8.5 | EE3: 8.3 | EF3: 7.9 | EG3: 7.9 | EH3: 8 | EI3: 8.1 | EJ3: 8.5 | EK3: 8.6 | EL3: 8.6 | EM3: 8.8 | EN3: 8.9 | EO3: 8.9 | EP3: 8.8 | EQ3: 7.1 | ER3: 6.7 | ES3: 6.7 | ET3: 6.8 | EU3: 7.2 | EV3: 7.4 | EW3: 7.2 | EX3: 6.9 | EY3: 7 | EZ3: 6.7 | FA3: 7.1 | FB3: 7.1 | FC3: 6.9 | FD3: 6.7 | FE3: 6.7 | FF3: 7.1 | FG3: 7.5 | FH3: 7.5 | FI3: 7.4 | FJ3: 7.3 | FK3: 7.5 | FL3: 7.7 | FM3: 7.6 | FN3: 7.4 | FO3: 7.9 | FP3: 7.8 | FQ3: 8 | FR3: 7.5 | FS3: 8 | FT3: 8.2 | FU3: 8.1 | FV3: 7.8 | FW3: 7.7 | FX3: 8.2 | FY3: 8.4 | FZ3: 8.1 | GA3: 7.9 | GB3: 7.8 | GC3: 7.5 | GD3: 7.5 | GE3: 7.9 | GF3: 8 | GG3: 8.1 | GH3: 8 | GI3: 7.5 | GJ3: 7.4 | GK3: 7.4 | GL3: 7.4 | GM3: 7.4 | GN3: 7.1 | GO3: 7.7 | GP3: 8.2 | GQ3: 9.2 | GR3: 9.5 | GS3: 9.6 | GT3: 10 | GU3: 9.7 | GV3: 10.9 | GW3: 12.5 | GX3: 12 | GY3: 11.7 | GZ3: 12.2 | HA3: 11.9 | HB3: 14.7 | HC3: 11.8 | HD3: 11.5 | HE3: 12.1 | HF3: 12.4 | HG3: 12.8 | HH3: 13 | HI3: 13.4 | HJ3: 13.9 | HK3: 14.4 | HL3: 14.5 | HM3: 14.9 | HN3: 14.7 | HO3: 14.4 | HP3: 14.4 | HQ3: 14 | HR3: 13.7 | HS3: 13.9 | HT3: 12.6 | HU3: 13.4 | HV3: 12.8 | HW3: 12.6 | HX3: 12 | HY3: 11.4 | HZ3: 11.5 | IA3: 12 | IB3: 12.3 | IC3: 11.9 | ID3: 11.4 | IE3: 11.4 | IF3: 11.4 | IG3: 11.6 | IH3: 11.5 | II3: 11.5 | IJ3: 11.1 | IK3: 11.6 | IL3: 11.5 | IM3: 11.9 | IN3: 11.5 | IO3: 10.4 | IP3: 10.2 | IQ3: 10.3 | IR3: 10.3 | IS3: 10.2 | IT3: 10.1 | IU3: 9.9 | IV3: 9.7 | IW3: 10 | IX3: 10 | IY3: 10.6 | IZ3: 10.7 | JA3: 10.7 | JB3: 10.4 | JC3: 10.9 | JD3: 10.9
JC5: *IMF's recommended threshold for MOI is 7.5
A19: Remittances | ED19: 14.54 | EE19: 28.52 | EF19: 45.08 | EG19: 61.34 | EH19: 81.19 | EI19: 100.4 | EJ19: 122.24 | EK19: 144.96 | EL19: 164.34 | EM19: 186.31 | EN19: 204.986 | EO19: 232.076 | EP19: 234.836 | EQ19: 239.406 | ER19: 242.256 | ES19: 246.376 | ET19: 251.246 | EU19: 256.176 | EV19: 256.472 | EW19: 258.542 | EX19: 262.092 | EY19: 263.322 | EZ19: 266.906 | FA19: 269.826 | FB19: 273.752 | FC19: 273.837 | FD19: 276.847 | FE19: 277.987 | FF19: 281.767 | FG19: 284.167 | FH19: 287.491 | FI19: 291.117 | FJ19: 294.177 | FK19: 299.177 | FL19: 303.597 | FM19: 307.147 | FN19: 311.021 | FO19: 316.566 | FP19: 322.196 | FQ19: 326.876 | FR19: 333.636 | FS19: 337.896 | FT19: 342.536 | FU19: 345.72 | FV19: 347.43 | FW19: 347.43 | FX19: 351.35 | FY19: 350.39 | FZ19: 350.19 | GA19: 350.21 | GB19: 349.56 | GC19: 350.86 | GD19: 350.4 | GE19: 346.6 | GF19: 348.7 | GG19: 349.9 | GH19: 348.7 | GI19: 349.9 | GJ19: 348.4 | GK19: 348.2 | GL19: 350.4 | GM19: 351 | GN19: 349.7 | GO19: 345.7 | GP19: 345.9 | GQ19: 350.8 | GR19: 356.1 | GS19: 359.7 | GT19: 369.2 | GU19: 378.5 | GV19: 386.5 | GW19: 397.9 | GX19: 403.2 | GY19: 411.2 | GZ19: 428.6 | HA19: 447.6 | HB19: 455.3 | HC19: 461.1 | HD19: 465.5 | HE19: 472.33 | HF19: 480.43 | HG19: 485.63 | HH19: 490.04 | HI19: 498.19 | HJ19: 494.85 | HK19: 489.73 | HL19: 478.62 | HM19: 474.86 | HN19: 471.85 | HO19: 472.34 | HP19: 472.5 | HQ19: 476.85 | HR19: 476.41 | HS19: 473.6 | HT19: 474.58 | HU19: 475.18 | HV19: 484.1 | HW19: 494.12 | HX19: 506.22 | HY19: 507.31 | HZ19: 517.99 | IA19: 528.93 | IB19: 537.04 | IC19: 537.68 | ID19: 537.12 | IE19: 539.03 | IF19: 539.74 | IG19: 538.09 | IH19: 536.46729 | II19: 533.62339 | IJ19: 529.40825 | IK19: 529.65436 | IL19: 523.65573 | IM19: 521.13351 | IN19: 520.59376 | IO19: 521.44853 | IP19: 520.58334 | IQ19: 524.22649 | IR19: 524.91648 | IS19: 524.76839 | IT19: 527.80401 | IU19: 530.61651 | IV19: 533.68455 | IW19: 536.65648 | IX19: 541.74616 | IY19: 540.65693 | IZ19: 543.79448 | JA19: 546.9236
EN21: 42309 | EO21: 42339 | EP21: 42370 | EQ21: 42401 | ER21: 42430 | ES21: 42461 | ET21: 42491 | EU21: 42522 | EV21: 42552 | EW21: 42583 | EX21: 42614 | EY21: 42644 | EZ21: 42675 | FA21: 42705 | FB21: 42736 | FC21: 42767 | FD21: 42795 | FE21: 42826 | FF21: 42856 | FG21: 42887 | FH21: 42917 | FI21: 42948 | FJ21: 42979 | FK21: 43009 | FL21: 43040 | FM21: 43070 | FN21: 43101 | FO21: 43132 | FP21: 43160 | FQ21: 43191 | FR21: 43221 | FS21: 43252 | FT21: 43282 | FU21: 43313 | FV21: 43344 | FW21: 43374 | FX21: 43405 | FY21: 43435 | FZ21: 43466 | GA21: 43497 | GB21: 43525 | GC21: 43556 | GD21: 43586 | GE21: 43617 | GF21: 43647 | GG21: 43678 | GH21: 43709 | GI21: 43739 | GJ21: 43770 | GK21: 43800 | GL21: 43831 | GM21: 43862 | GN21: 43891 | GO21: 43922 | GP21: 43952 | GQ21: 43983 | GR21: 44013 | GS21: 44044 | GT21: 44075 | GU21: 44105 | GV21: 44136 | GW21: 44166 | GX21: 44197 | GY21: 44228 | GZ21: 44256 | HA21: 44287 | HB21: 44317 | HC21: 44348 | HD21: 44378 | HE21: 44409 | HF21: 44440 | HG21: 44470 | HH21: 44501 | HI21: 44531 | HJ21: 44562 | HK21: 44593 | HL21: 44621 | HM21: 44652 | HN21: 44682 | HO21: 44713 | HP21: 44743 | HQ21: 44774 | HR21: 44805 | HS21: 44835 | HT21: 44866 | HU21: 44896 | HV21: 44927 | HW21: 44958 | HX21: 44986 | HY21: 45017 | HZ21: 45047 | IA21: 45078 | IB21: 45108 | IC21: 45139 | ID21: 45170 | IE21: 45200 | IF21: 45231 | IG21: 45261 | IH21: 45292 | II21: 45323 | IJ21: 45352 | IK21: 45383 | IL21: 45413 | IM21: 45444 | IN21: 45474 | IO21: 45505 | IP21: 45536 | IQ21: 45566 | IR21: 45597 | IS21: 45627 | IT21: 45658 | IU21: 45689 | IV21: 45717 | IW21: 45748 | IX21: 45778 | IY21: 45809 | IZ21: 45839 | JA21: 45870 | JB21: 45901 | JC21: 45931 | JD21: 45962
EM22: Foreign Reserves | EN22: 319 | EO22: 327.8 | EP22: 326.3 | EQ22: 328.5 | ER22: 317.3 | ES22: 322.9 | ET22: 330.7 | EU22: 354.9 | EV22: 367.4 | EW22: 366.3 | EX22: 363.7 | EY22: 367 | EZ22: 360.9 | FA22: 378.8 | FB22: 380.8 | FC22: 377.7 | FD22: 366 | FE22: 371.7 | FF22: 392.3 | FG22: 407.9 | FH22: 408.9 | FI22: 405 | FJ22: 403 | FK22: 413.6 | FL22: 424.8 | FM22: 422.6 | FN22: 424.1 | FO22: 448 | FP22: 447.7 | FQ22: 445.9 | FR22: 441.9 | FS22: 468.7 | FT22: 476.5 | FU22: 475 | FV22: 452.2 | FW22: 457.3 | FX22: 468.7 | FY22: 478.5 | FZ22: 478.9 | GA22: 473.5 | GB22: 465 | GC22: 464.2 | GD22: 468.3 | GE22: 484.3 | GF22: 492.9 | GG22: 491.8 | GH22: 490.8 | GI22: 489.3 | GJ22: 489.5 | GK22: 487.4 | GL22: 482.9 | GM22: 479.8 | GN22: 457.5 | GO22: 475.1 | GP22: 489.6 | GQ22: 543.8 | GR22: 555.9 | GS22: 556.1 | GT22: 576.5 | GU22: 581.6 | GV22: 590.2 | GW22: 675.6 | GX22: 705.3 | GY22: 692.4 | GZ22: 685.7 | HA22: 679.7 | HB22: 689.5 | HC22: 715.2 | HD22: 704.8 | HE22: 751.7 | HF22: 757 | HG22: 757 | HH22: 783.9 | HI22: 817.5 | HJ22: 856.1 | HK22: 867.3 | HL22: 861.4 | HM22: 884 | HN22: 880.4 | HO22: 871.2 | HP22: 884.8 | HQ22: 871 | HR22: 895.3 | HS22: 877 | HT22: 866.2 | HU22: 868.9 | HV22: 911.1 | HW22: 911.2 | HX22: 883.7 | HY22: 860.5 | HZ22: 864.8 | IA22: 921.4 | IB22: 945.2 | IC22: 920 | ID22: 886.1 | IE22: 891.2 | IF22: 892 | IG22: 901.7 | IH22: 894.7 | II22: 891.4 | IJ22: 868.7 | IK22: 904.8 | IL22: 893 | IM22: 924.3 | IN22: 909.1 | IO22: 905.5 | IP22: 887.4 | IQ22: 898.2 | IR22: 892.2 | IS22: 889.1 | IT22: 878 | IU22: 865.4 | IV22: 842.6 | IW22: 867.6 | IX22: 871.5 | IY22: 925.1 | IZ22: 921 | JA22: 921.1 | JB22: 897.2 | JC22: 939.5 | JD22: 940.3
EM23: Import Cover | EN23: 8.9 | EO23: 8.9 | EP23: 8.8 | EQ23: 7.1 | ER23: 6.7 | ES23: 6.7 | ET23: 6.8 | EU23: 7.2 | EV23: 7.4 | EW23: 7.2 | EX23: 6.9 | EY23: 7 | EZ23: 6.7 | FA23: 7.1 | FB23: 7.1 | FC23: 6.9 | FD23: 6.7 | FE23: 6.7 | FF23: 7.1 | FG23: 7.5 | FH23: 7.5 | FI23: 7.4 | FJ23: 7.3 | FK23: 7.5 | FL23: 7.7 | FM23: 7.6 | FN23: 7.4 | FO23: 7.9 | FP23: 7.8 | FQ23: 8 | FR23: 7.5 | FS23: 8 | FT23: 8.2 | FU23: 8.1 | FV23: 7.8 | FW23: 7.7 | FX23: 8.2 | FY23: 8.4 | FZ23: 8.1 | GA23: 7.9 | GB23: 7.8 | GC23: 7.5 | GD23: 7.5 | GE23: 7.9 | GF23: 8 | GG23: 8.1 | GH23: 8 | GI23: 7.5 | GJ23: 7.4 | GK23: 7.4 | GL23: 7.4 | GM23: 7.4 | GN23: 7.1 | GO23: 7.7 | GP23: 8.2 | GQ23: 9.2 | GR23: 9.5 | GS23: 9.6 | GT23: 10 | GU23: 9.7 | GV23: 10.9 | GW23: 12.5 | GX23: 12 | GY23: 11.7 | GZ23: 12.2 | HA23: 11.9 | HB23: 14.7 | HC23: 11.8 | HD23: 11.5 | HE23: 12.1 | HF23: 12.4 | HG23: 12.8 | HH23: 13 | HI23: 13.4 | HJ23: 13.9 | HK23: 14.4 | HL23: 14.5 | HM23: 14.9 | HN23: 14.7 | HO23: 14.4 | HP23: 14.4 | HQ23: 14 | HR23: 13.7 | HS23: 13.9 | HT23: 12.6 | HU23: 13.4 | HV23: 12.8 | HW23: 12.6 | HX23: 12 | HY23: 11.4 | HZ23: 11.5 | IA23: 12 | IB23: 12.3 | IC23: 11.9 | ID23: 11.4 | IE23: 11.4 | IF23: 11.4 | IG23: 11.6 | IH23: 11.5 | II23: 11.5 | IJ23: 11.1 | IK23: 11.6 | IL23: 11.5 | IM23: 11.9 | IN23: 11.5 | IO23: 10.4 | IP23: 10.2 | IQ23: 10.3 | IR23: 10.3 | IS23: 10.2 | IT23: 10.1 | IU23: 9.9 | IV23: 9.7 | IW23: 10 | IX23: 10 | IY23: 10.6 | IZ23: 10.7 | JA23: 10.7 | JB23: 10.4 | JC23: 10.9
EN24: 12.4 | EO24: 12.5 | EP24: 12.6 | EQ24: 9.7 | ER24: 9.3 | ES24: 9.4 | ET24: 9.5 | EU24: 10.1 | EV24: 10.4 | EW24: 10.2 | EX24: 10 | EY24: 10 | EZ24: 9.7 | FA24: 10.1 | FB24: 10.1 | FC24: 9.8 | FD24: 9.4 | FE24: 9.4 | FF24: 9.8 | FG24: 10.1 | FH24: 10 | FI24: 9.9 | FJ24: 9.7 | FK24: 9.9 | FL24: 10.1 | FM24: 9.9 | FN24: 9.9 | FO24: 10.3 | FP24: 10.2 | FQ24: 10.1 | FR24: 9.9 | FS24: 10.4 | FT24: 10.5 | FU24: 10.3 | FV24: 9.7 | FW24: 9.7 | FX24: 9.9 | FY24: 10 | FZ24: 9.9 | GA24: 9.6 | GB24: 9.4 | GC24: 9.3 | GD24: 9.3 | GE24: 9.6 | GF24: 9.7 | GG24: 9.6 | GH24: 9.6 | GI24: 9.5 | GJ24: 9.6 | GK24: 9.5 | GL24: 9.4 | GM24: 9.4 | GN24: 9 | GO24: 9.4 | GP24: 9.7 | GQ24: 10.8 | GR24: 9.6 | GS24: 9.7 | GT24: 10.1 | GU24: 9.8 | GV24: 9 | GW24: 14.1 | GX24: 14.8 | GY24: 14.6 | GZ24: 14.6 | HA24: 14.5 | HB24: 11.6 | HC24: 15.3 | HD24: 15 | HE24: 15.9 | HF24: 15.9 | HG24: 9.3 | HH24: 16.1 | HI24: 16.5 | HJ24: 17 | HK24: 17.1 | HL24: 16.8 | HM24: 17.1 | HN24: 16.8 | HO24: 16.4 | HP24: 16.4 | HQ24: 16 | HR24: 16.2 | HS24: 15.6 | HT24: 15.2 | HU24: 15 | HV24: 15.4 | HW24: 15 | HX24: 14.2 | HY24: 13.5 | HZ24: 13.2 | IA24: 13.8 | IB24: 13.8 | IC24: 13.2 | ID24: 12.4 | IE24: 12.3 | IF24: 12.1 | IG24: 12 | IH24: 11.8 | II24: 11.6 | IJ24: 11.2 | IK24: 11.6 | IL24: 11.4 | IM24: 11.7 | IN24: 11.5 | IO24: 11.4 | IP24: 11.1 | IQ24: 11.2 | IR24: 11.1 | IS24: 11 | IT24: 10.8 | IU24: 10.6 | IV24: 10.2 | IW24: 10.5 | IX24: 10.5 | IY24: 11 | IZ24: 10.9 | JA24: 10.8 | JB24: 10.4 | JC24: 10.9 | JD24: 10.9
