Workbook

Sheet Consolidation

Sheet Data
A1: Fiscal Indicators
B3: FY2018 | C3: FY2019 | D3: FY2020 | E3: FY2021 | F3: FY2022 | G3: FY2023 | H3: FY2024 | I3: FY2025 | J3: FY2026 | K3: FY2027 | L3: FY2028 | M3: FY2029
B4: 1998/99 | C4: 1999/00 | D4: 2000/01 | E4: 2001/02 | F4: 2002/03 | G4: 2003/04 | H4: 2004/05 | I4: 2005/06 | J4: 2006/07 | K4: 2007/08 | L4: 2008/09 | M4: 2009/10 | N4: 2010/11 | O4: 2011/12 | P4: 2012/13 | Q4: 2013/14 | R4: 2014/15 | S4: 2015/16 | T4: 2016/17 | U4: 2017/18 | V4: 2018/19 | W4: 2019/20 | X4: 2020/21 | Y4: 2021/22 | Z4: 2022/23 | AA4: 2023/24 | AB4: 2024/25 | AC4: 2025/26 | AD4: 2026/27 | AE4: 2027/28 | AF4: 2028/29
A5: Nominal GDP | B5: {=GDP!H30:R30} -> 849.27589 | C5: 851.8788 | D5: 872.3634 | E5: 871.52186 | F5: 845.38451 | G5: 845.02152 | H5: 856.58691 | I5: 894.93264 | J5: 936.61967 | K5: 978.86661 | L5: 1030.4138 | O5: =GDP!B33 -> 892.85834 | P5: =GDP!C33 -> 896.23017 | Q5: =GDP!D33 -> 914.06999 | R5: =GDP!E33 -> 924.25039 | S5: =GDP!F33 -> 985.23894 | T5: =GDP!G33 -> 1016.7894 | U5: =GDP!H33 -> 1023.7803 | V5: =GDP!I33 -> 1021.6464 | ... AE5: =GDP!R33 -> 1211.4138
A6: Real GDP | B6: {=GDP!H39:R39} -> 0.5 | C6: -0.3 | D6: 1.8 | E6: -0.9 | F6: -2.1 | G6: 2.8 | H6: 1.7 | I6: 2.7 | J6: 3.4 | K6: 3.7 | L6: 3.9 | U6: {=GDP!AA39:AK39} -> 0 | V6: 0 | W6: 0 | X6: 0 | Y6: 0 | Z6: 0 | AA6: 0 | AB6: 0 | AC6: 0 | AD6: 0 | AE6: 0
A9: Exports
A10: Imports
A13: Monetary Indicators
B16: 1998/99 | C16: 1999/00 | D16: 2000/01 | E16: 2001/02 | F16: 2002/03 | G16: 2003/04 | H16: 2004/05 | I16: 2005/06 | J16: 2006/07 | K16: 2007/08 | L16: 2008/09 | M16: 2009/10 | N16: 2010/11 | O16: 2011/12 | P16: 2012/13 | Q16: 2013/14 | R16: 2014/15 | S16: 2015/16 | T16: 2016/17 | U16: 2017/18 | V16: 2018/19 | W16: 2019/20 | X16: 2020/21 | Y16: 2021/22 | Z16: 2022/23 | AA16: 2023/24 | AB16: 2024/25 | AC16: 2025/26 | AD16: 2026/27 | AE16: 2027/28 | AF16: 2028/29
A17: Total private | B17: 290.46 | C17: 358.9 | D17: 393.93 | E17: 432.39 | F17: 429.38 | G17: 430.29 | H17: 426.02 | I17: 470/68 | J17: 499.7
A18: Housing | B18: 126.92 | C18: 170.65 | D18: 190.83 | E18: 201.21 | F18: 204.63 | G18: 206.26 | H18: 201.24 | I18: 197.44 | J18: 204.36
A19: Personal | B19: 56.72
A20: Business | B20: 93.3
A21: Agriculture | B21: 9.6 | M21: =204.36+66.7+211.1+17.5+0.1 -> 499.76
A22: Other | B22: =B17-SUM(B18:B21) -> 3.92 | M22: =197.44+58.29+196+18.9+0.1 -> 470.73
A23: Remmittances | M23: =170.65+57.58+117.3+12.1+1.2 -> 358.83
A24: Inflation
A25: Foreign Reserves
B27: 1998/99 | C27: 1999/00 | D27: 2000/01 | E27: 2001/02 | F27: 2002/03 | G27: 2003/04 | H27: 2004/05 | I27: 2005/06 | J27: 2006/07 | K27: 2007/08 | L27: 2008/09 | M27: 2009/10 | N27: 2010/11 | O27: 2011/12 | P27: 2012/13 | Q27: 2013/14 | R27: 2014/15 | S27: 2015/16 | T27: 2016/17 | U27: 2017/18 | V27: 2018/19 | W27: 2019/20 | X27: 2020/21 | Y27: 2021/22 | Z27: 2022/23 | AA27: 2023/24 | AB27: 2024/25 | AC27: 2025/26 | AD27: 2026/27 | AE27: 2027/28 | AF27: 2028/29

Sheet Monetary Policy Data
B2: AUD | C2: CAD | D2: CHF | E2: EUR | F2: FJD | G2: GBP | H2: JPY | I2: NZD | J2: SEK | K2: SGD | L2: USD | M2: WST | N2: CNY
A3: 44197 | B3: 0.5658 | C3: 0.5574 | D3: 0.3864 | E3: 0.3594 | F3: 0.868 | G3: 0.3206 | H3: 45.3713 | I3: 0.6085 | J3: 3.6319 | K3: 0.5835 | L3: 0.4386 | M3: 1.0277 | N3: 2.8532 | P3: =1/B3 -> 1.767409
A4: 44228 | B4: 0.5605 | C4: 0.5531 | D4: 0.3886 | E4: 0.3594 | F4: 0.8597 | G4: 0.3136 | H4: 45.7801 | I4: 0.6009 | J4: 3.6279 | K4: 0.5808 | L4: 0.4358 | M4: 1.0181 | N4: 2.8352
A5: 44256 | B5: 0.5677 | C5: 0.5518 | D5: 0.405 | E5: 0.3677 | F5: 0.868 | G5: 0.3157 | H5: 47.5581 | I5: 0.6134 | J5: 3.741 | K5: 0.5918 | L5: 0.439 | M5: 1.03 | N5: 2.8562
A6: 44287 | B6: 0.5697 | C6: 0.55 | D6: 0.4034 | E6: 0.3667 | F6: 0.8706 | G6: 0.317 | H6: 47.8379 | I6: 0.616 | J6: 3.7332 | K6: 0.5892 | L6: 0.4401 | M6: 1.0352 | N6: 2.8632
B9: =1/B3 -> 1.767409 | C9: =1/C3 -> 1.7940438 | D9: =1/D3 -> 2.5879917 | E9: =1/E3 -> 2.7824151 | F9: =1/F3 -> 1.1520737 | G9: =1/G3 -> 3.1191516 | H9: =1/H3 -> 0.022040365 | I9: =1/I3 -> 1.6433854 | ... N9: =1/N3 -> 0.35048367
B10: =1/B4 -> 1.7841213 | C10: =1/C4 -> 1.8079913 | D10: =1/D4 -> 2.5733402 | E10: =1/E4 -> 2.7824151 | F10: =1/F4 -> 1.1631965 | G10: =1/G4 -> 3.1887755 | H10: =1/H4 -> 0.021843552 | I10: =1/I4 -> 1.6641704 | ... N10: =1/N4 -> 0.3527088
B11: =1/B5 -> 1.7614937 | C11: =1/C5 -> 1.8122508 | D11: =1/D5 -> 2.4691358 | E11: =1/E5 -> 2.7196084 | F11: =1/F5 -> 1.1520737 | G11: =1/G5 -> 3.1675641 | H11: =1/H5 -> 0.021026912 | I11: =1/I5 -> 1.6302576 | ... N11: =1/N5 -> 0.35011554
A13: 45170 | B13: 0.6487 | C13: 0.5653 | D13: 0.3729 | E13: 0.3899 | F13: 0.9315 | G13: 0.3354 | H13: 61.5089 | I13: 0.7032 | J13: 4.6265 | K13: 0.5728 | L13: 0.4174 | M13: 1.1568 | N13: 3.0456
A14: 45200 | B14: 0.6542 | C14: 0.5702 | D14: 0.3742 | E14: 0.3933 | F14: 0.9358 | G14: 0.3409 | H14: 62.1124 | I14: 0.7034 | J14: 4.5847 | K14: 0.5736 | L14: 0.4163 | M14: 1.1574 | N14: 3.0422
A15: 45231 | B15: 0.6447 | C15: 0.5753 | D15: 0.3718 | E15: 0.3871 | F15: 0.9354 | G15: 0.3367 | H15: 62.7441 | I15: 0.6991 | J15: 4.4789 | K15: 0.5694 | L15: 0.4191 | M15: 1.1559 | N15: 3.0292
A16: 45261 | B16: 0.6348 | C16: 0.5709 | D16: 0.3661 | E16: 0.3887 | F16: 0.9335 | G16: 0.3347 | H16: 61.13 | I16: 0.6827 | J16: 4.3659 | K16: 0.57 | L16: 0.4246 | M16: 1.1526 | N16: 3.0335
B18: =1/B13 -> 1.5415446 | C18: =1/C13 -> 1.7689722 | D18: =1/D13 -> 2.6816841 | E18: =1/E13 -> 2.5647602 | F18: =1/F13 -> 1.0735373 | G18: =1/G13 -> 2.9815146 | H18: =1/H13 -> 0.01625781 | I18: =1/I13 -> 1.4220705 | ... N18: =1/N13 -> 0.32834253
B19: =1/B14 -> 1.5285845 | C19: =1/C14 -> 1.7537706 | D19: =1/D14 -> 2.6723677 | E19: =1/E14 -> 2.5425884 | F19: =1/F14 -> 1.0686044 | G19: =1/G14 -> 2.9334116 | H19: =1/H14 -> 0.016099845 | I19: =1/I14 -> 1.4216662 | ... N19: =1/N14 -> 0.32870949
B20: =1/B16 -> 1.5752993 | C20: =1/C16 -> 1.7516202 | D20: =1/D16 -> 2.7314941 | E20: =1/E16 -> 2.5726782 | F20: =1/F16 -> 1.0712373 | G20: =1/G16 -> 2.9877502 | H20: =1/H16 -> 0.01635858 | I20: =1/I16 -> 1.4647722 | ... N20: =1/N16 -> 0.32965222
B29: AUD | C29: CAD | D29: CHF | E29: EUR | F29: FJD | G29: GBP | H29: JPY | I29: NZD | J29: SEK | K29: SGD | L29: USD | M29: WST | N29: CNY
A30: 42005 | B30: 0.6245 | C30: 0.6126 | D30: 0.7389 | E30: 0.4354 | F30: 0.9716 | G30: 0.3343 | H30: 60.1133 | I30: 0.6594 | J30: 4.1108 | K30: 0.6801 | L30: 0.5069 | M30: 1.1824 | N30: 3.1508 | V30: AUD | W30: CAD | X30: CHF | Y30: EUR | Z30: FJD | AA30: GBP | AB30: JPY | AC30: NZD | AD30: SEK | AE30: SGD | AF30: USD | AG30: WST | AH30: CNY | AO30: NEER | AP30: REER | AT30: Broad money | AY30: Import Prices | BD30: Brent Oil Price
A31: 42036 | B31: 0.639 | C31: 0.6269 | D31: 0.7328 | E31: 0.4404 | F31: 0.9783 | G31: 0.3264 | H31: 59.2652 | I31: 0.6692 | J31: 4.1826 | K31: 0.6801 | L31: 0.4999 | M31: 1.1799 | N31: 3.1253 | U31: 42005 | V31: =1/B30 -> 1.601281 | W31: =1/C30 -> 1.6323865 | X31: =1/D30 -> 1.3533631 | Y31: =1/E30 -> 2.2967386 | Z31: =1/F30 -> 1.0292301 | AA31: =1/G30 -> 2.9913252 | AB31: =1/H30 -> 0.016635254 | AC31: =1/I30 -> 1.5165302 | ... AH31: =1/N30 -> 0.31737971 | AN31: 40238 | AO31: 101.3 | AP31: 112.3 | AS31: 40238 | AT31: 284.7
A32: 42064 | B32: 0.6405 | C32: 0.628 | D32: 0.7432 | E32: 0.4593 | F32: 0.9757 | G32: 0.3322 | H32: 59.8198 | I32: 0.6635 | J32: 4.2519 | K32: 0.6875 | L32: 0.4974 | M32: 1.1621 | N32: 3.1038 | U32: 42036 | V32: =1/B31 -> 1.5649452 | W32: =1/C31 -> 1.5951507 | X32: =1/D31 -> 1.3646288 | Y32: =1/E31 -> 2.270663 | Z32: =1/F31 -> 1.0221813 | AA32: =1/G31 -> 3.0637255 | AB32: =1/H31 -> 0.016873308 | AC32: =1/I31 -> 1.4943216 | ... AH32: =1/N31 -> 0.31996928 | AN32: 40269 | AO32: 99.3 | AP32: 111.1 | AS32: 40269 | AT32: 285.1
A33: 42095 | B33: 0.6428 | C33: 0.6173 | D33: 0.7419 | E33: 0.4631 | F33: 0.9777 | G33: 0.3341 | H33: 59.6417 | I33: 0.6549 | J33: 4.3296 | K33: 0.6767 | L33: 0.4992 | M33: 1.1735 | N33: 3.0962 | U33: 42064 | V33: =1/B32 -> 1.5612802 | W33: =1/C32 -> 1.5923567 | X33: =1/D32 -> 1.3455328 | Y33: =1/E32 -> 2.1772262 | Z33: =1/F32 -> 1.0249052 | AA33: =1/G32 -> 3.0102348 | AB33: =1/H32 -> 0.016716873 | AC33: =1/I32 -> 1.507159 | ... AH33: =1/N32 -> 0.32218571 | AN33: 40299 | AO33: 99 | AP33: 112 | AS33: 40299 | AT33: 289.1
A34: 42125 | B34: 0.6242 | C34: 0.6035 | D34: 0.7303 | E34: 0.4437 | F34: 0.9643 | G34: 0.3206 | H34: 59.6931 | I34: 0.6662 | J34: 4.1347 | K34: 0.6632 | L34: 0.4954 | M34: 1.1735 | N34: 3.0979 | U34: 42095 | V34: =1/B33 -> 1.5556938 | W34: =1/C33 -> 1.6199579 | X34: =1/D33 -> 1.3478906 | Y34: =1/E33 -> 2.1593608 | Z34: =1/F33 -> 1.0228086 | AA34: =1/G33 -> 2.9931158 | AB34: =1/H33 -> 0.016766792 | AC34: =1/I33 -> 1.5269507 | ... AH34: =1/N33 -> 0.32297655 | AN34: 40330 | AO34: 101.1 | AP34: 112.2 | AS34: 40330 | AT34: 291.5
A35: 42156 | B35: 0.6175 | C35: 0.5928 | D35: 0.7225 | E35: 0.4269 | F35: 0.9484 | G35: 0.3077 | H35: 59.1901 | I35: 0.6807 | J35: 3.9651 | K35: 0.6468 | L35: 0.4792 | M35: 1.1421 | N35: 2.9736 | U35: 42125 | V35: =1/B34 -> 1.6020506 | W35: =1/C34 -> 1.6570008 | X35: =1/D34 -> 1.3693003 | Y35: =1/E34 -> 2.2537751 | Z35: =1/F34 -> 1.0370217 | AA35: =1/G34 -> 3.1191516 | AB35: =1/H34 -> 0.016752355 | AC35: =1/I34 -> 1.5010507 | ... AH35: =1/N34 -> 0.32279932 | AN35: 40360 | AO35: 99.9 | AP35: 114.8 | AS35: 40360 | AT35: 291.2
A36: 42186 | B36: 0.6232 | C36: 0.5972 | D36: 0.7209 | E36: 0.4226 | F36: 0.9436 | G36: 0.2987 | H36: 57.1985 | I36: 0.6954 | J36: 3.9645 | K36: 0.6351 | L36: 0.4645 | M36: 1.1463 | N36: 2.8838 | U36: 42156 | V36: =1/B35 -> 1.6194332 | W36: =1/C35 -> 1.6869096 | X36: =1/D35 -> 1.384083 | Y36: =1/E35 -> 2.342469 | Z36: =1/F35 -> 1.0544074 | AA36: =1/G35 -> 3.2499188 | AB36: =1/H35 -> 0.016894717 | AC36: =1/I35 -> 1.469076 | ... AH36: =1/N35 -> 0.33629271 | AN36: 40391 | AO36: 98.5 | AP36: 115.2 | AS36: 40391 | AT36: 288.9
A37: 42217 | B37: 0.6253 | C37: 0.6039 | D37: 0.7215 | E37: 0.4117 | F37: 0.9372 | G37: 0.294 | H37: 56.4637 | I37: 0.6971 | J37: 3.9313 | K37: 0.643 | L37: 0.4586 | M37: 1.1609 | N37: 2.904 | U37: 42186 | V37: =1/B36 -> 1.6046213 | W37: =1/C36 -> 1.6744809 | X37: =1/D36 -> 1.3871549 | Y37: =1/E36 -> 2.3663038 | Z37: =1/F36 -> 1.0597711 | AA37: =1/G36 -> 3.3478406 | AB37: =1/H36 -> 0.017482976 | AC37: =1/I36 -> 1.4380213 | ... AH37: =1/N36 -> 0.34676469 | AN37: 40422 | AO37: 99.2 | AP37: 115.7 | AS37: 40422 | AT37: 286.8
A38: 42248 | B38: 0.6327 | C38: 0.5948 | D38: 0.434 | E38: 0.3976 | F38: 0.9252 | G38: 0.2924 | H38: 53.7337 | I38: 0.7043 | J38: 3.7557 | K38: 0.6362 | L38: 0.4476 | M38: 1.1543 | N38: 2.8514 | U38: 42217 | V38: =1/B37 -> 1.5992324 | W38: =1/C37 -> 1.6559033 | X38: =1/D37 -> 1.3860014 | Y38: =1/E37 -> 2.4289531 | Z38: =1/F37 -> 1.0670081 | AA38: =1/G37 -> 3.4013605 | AB38: =1/H37 -> 0.017710494 | AC38: =1/I37 -> 1.4345144 | ... AH38: =1/N37 -> 0.34435262 | AN38: 40452 | AO38: 99.5 | AP38: 115.2 | AS38: 40452 | AT38: 302.5
A39: 42278 | B39: 0.6264 | C39: 0.5931 | D39: 0.4616 | E39: 0.4024 | F39: 0.923 | G39: 0.2954 | H39: 54.3409 | I39: 0.6759 | J39: 3.779 | K39: 0.6368 | L39: 0.453 | M39: 1.1496 | N39: 2.8751 | U39: 42248 | V39: =1/B38 -> 1.5805279 | W39: =1/C38 -> 1.6812374 | X39: =1/D38 -> 2.3041475 | Y39: =1/E38 -> 2.5150905 | Z39: =1/F38 -> 1.0808474 | AA39: =1/G38 -> 3.4199726 | AB39: =1/H38 -> 0.018610295 | AC39: =1/I38 -> 1.4198495 | ... AH39: =1/N38 -> 0.35070492 | AN39: 40483 | AO39: 100.7 | AP39: 114.6 | AS39: 40483 | AT39: 297.3
A40: 42309 | B40: 0.6244 | C40: 0.595 | D40: 0.4504 | E40: 0.4163 | F40: 0.9262 | G40: 0.2943 | H40: 54.8451 | I40: 0.6804 | J40: 3.8956 | K40: 0.6354 | L40: 0.4476 | M40: 1.14 | N40: 2.8507 | U40: 42278 | V40: =1/B39 -> 1.596424 | W40: =1/C39 -> 1.6860563 | X40: =1/D39 -> 2.1663778 | Y40: =1/E39 -> 2.4850895 | Z40: =1/F39 -> 1.0834236 | AA40: =1/G39 -> 3.3852404 | AB40: =1/H39 -> 0.018402345 | AC40: =1/I39 -> 1.4795088 | ... AH40: =1/N39 -> 0.34781399 | AN40: 40513 | AO40: 101.2 | AP40: 114.6 | AS40: 40513 | AT40: 305.5
A41: 42339 | B41: 0.6185 | C41: 0.6174 | D41: 0.4468 | E41: 0.4125 | F41: 0.921 | G41: 0.2997 | H41: 54.7296 | I41: 0.6656 | J41: 3.8346 | K41: 0.6359 | L41: 0.4498 | M41: 1.1385 | N41: 2.9009 | U41: 42309 | V41: =1/B40 -> 1.6015375 | W41: =1/C40 -> 1.6806723 | X41: =1/D40 -> 2.2202487 | Y41: =1/E40 -> 2.4021139 | Z41: =1/F40 -> 1.0796804 | AA41: =1/G40 -> 3.3978933 | AB41: =1/H40 -> 0.018233169 | AC41: =1/I40 -> 1.4697237 | ... AH41: =1/N40 -> 0.35079103 | AN41: 40544 | AO41: 100.9 | AP41: 116.5 | AS41: 40544 | AT41: 297.5
A42: 42370 | B42: 0.6295 | C42: 0.6304 | D42: 0.444 | E42: 0.4062 | F42: 0.9181 | G42: 0.3069 | H42: 52.3113 | I42: 0.675 | J42: 3.7882 | K42: 0.6365 | L42: 0.4424 | M42: 1.1294 | N42: 2.9064 | U42: 42339 | V42: =1/B41 -> 1.6168149 | W42: =1/C41 -> 1.6196955 | X42: =1/D41 -> 2.2381379 | Y42: =1/E41 -> 2.4242424 | Z42: =1/F41 -> 1.0857763 | AA42: =1/G41 -> 3.33667 | AB42: =1/H41 -> 0.018271648 | AC42: =1/I41 -> 1.5024038 | ... AH42: =1/N41 -> 0.3447206 | AN42: 40575 | AO42: 101.2 | AP42: 116 | AS42: 40575 | AT42: 287.9
... A48: 42552 | B48: 0.6018 | C48: 0.5926 | D48: 0.4447 | E48: 0.4096 | F48: 0.9149 | G48: 0.345 | H48: 47.2661 | I48: 0.639 | J48: 3.8962 | K48: 0.6154 | L48: 0.4537 | M48: 1.117 | N48: 3.0312 | U48: 42522 | V48: =1/B47 -> 1.6498928 | W48: =1/C47 -> 1.7208742 | X48: =1/D47 -> 2.2977941 | Y48: =1/E47 -> 2.5018764 | Z48: =1/F47 -> 1.0940919 | AA48: =1/G47 -> 3.1555696 | AB48: =1/H47 -> 0.021039167 | AC48: =1/I47 -> 1.5573898 | ... AH48: =1/N47 -> 0.33735915 | AN48: 40756 | AO48: 108 | AP48: 122.2 | AS48: 40756 | AT48: 294.2
A49: 42583 | B49: 0.5967 | C49: N/A | D49: N/A | E49: 0.4054 | F49: 0.9087 | G49: 0.3469 | H49: 46.0817 | I49: 0.6317 | J49: N/A | K49: N/A | L49: 0.4555 | M49: 1.1321 | N49: 3.0273 | U49: 42552 | V49: =1/B48 -> 1.6616816 | W49: =1/C48 -> 1.6874789 | X49: =1/D48 -> 2.248707 | Y49: =1/E48 -> 2.4414062 | Z49: =1/F48 -> 1.0930156 | AA49: =1/G48 -> 2.8985507 | AB49: =1/H48 -> 0.021156812 | AC49: =1/I48 -> 1.5649452 | ... AH49: =1/N48 -> 0.32990235 | AN49: 40787 | AO49: 106.9 | AP49: 120.7 | AS49: 40787 | AT49: 289.6
A50: 42614 | B50: 0.6045 | C50: 0.6009 | D50: 0.4452 | E50: 0.408 | F50: 0.9199 | G50: 0.348 | H50: 46.7263 | I50: 0.6282 | J50: 3.9189 | K50: 0.6275 | L50: 0.4588 | M50: 1.1468 | N50: 3.0607 | U50: 42583 | V50: =1/B49 -> 1.675884 | W50: =1/C49 -> #VALUE! | X50: =1/D49 -> #VALUE! | Y50: =1/E49 -> 2.4666996 | Z50: =1/F49 -> 1.1004732 | AA50: =1/G49 -> 2.8826751 | AB50: =1/H49 -> 0.021700588 | AC50: =1/I49 -> 1.5830299 | ... AH50: =1/N49 -> 0.33032735 | AN50: 40817 | AO50: 105.5 | AP50: 118.1 | AS50: 40817 | AT50: 296.2
A51: 42644 | U51: 42614 | V51: =1/B50 -> 1.6542597 | W51: =1/C50 -> 1.6641704 | X51: =1/D50 -> 2.2461815 | Y51: =1/E50 -> 2.4509804 | Z51: =1/F50 -> 1.0870747 | AA51: =1/G50 -> 2.8735632 | AB51: =1/H50 -> 0.021401224 | AC51: =1/I50 -> 1.5918497 | ... AH51: =1/N50 -> 0.32672265 | AN51: 40848 | AO51: 105.5 | AP51: 117.3 | AS51: 40848 | AT51: 295.15042
A52: 42675 | B52: 0.6027 | C52: 0.6105 | D52: 0.4506 | E52: 0.4196 | F52: 0.9215 | G52: 0.3652 | H52: 49.2301 | I52: 0.6367 | J52: 4.1488 | K52: 0.6425 | L52: 0.454 | M52: 1.1432 | N52: 3.1068 | U52: 42644 | V52: =V51+0.0012 -> 1.6554597 | W52: =W51+0.0012 -> 1.6653704 | X52: =X51+0.0012 -> 2.2473815 | Y52: =Y51+0.0012 -> 2.4521804 | Z52: =Z51+0.0012 -> 1.0882747 | AA52: =AA51+0.0012 -> 2.8747632 | AB52: =AB51+0.0012 -> 0.022601224 | AC52: =AC51+0.0012 -> 1.5930497 | ... AH52: =AH51+0.0012 -> 0.32792265 | AN52: 40878 | AO52: 105.1 | AP52: 116 | AS52: 40878 | AT52: 299.88445
A53: 42705 | B53: 0.6103 | C53: 0.599 | D53: 0.4561 | E53: 0.4247 | F53: 0.927 | G53: 0.359 | H53: 52.1237 | I53: 0.6384 | J53: 4.1439 | K53: 0.6489 | L53: 0.4492 | M53: 1.1366 | N53: 3.1082 | U53: 42675 | V53: =1/B52 -> 1.6592003 | W53: =1/C52 -> 1.6380016 | X53: =1/D52 -> 2.2192632 | Y53: =1/E52 -> 2.3832221 | Z53: =1/F52 -> 1.0851872 | AA53: =1/G52 -> 2.7382256 | AB53: =1/H52 -> 0.020312776 | AC53: =1/I52 -> 1.5705984 | ... AH53: =1/N52 -> 0.3218746 | AN53: 40909 | AO53: 104.9 | AP53: 117.9 | AS53: 40909 | AT53: 289.8532
A54: 42736 | B54: 0.603 | C54: 0.5943 | D54: 0.4518 | E54: 0.422 | F54: 0.9221 | G54: 0.3645 | H54: 51.7174 | I54: 0.6325 | J54: 4.0318 | K54: 0.6468 | L54: 0.4497 | M54: 1.1409 | N54: 3.1009 | U54: 42705 | V54: =1/B53 -> 1.6385384 | W54: =1/C53 -> 1.6694491 | X54: =1/D53 -> 2.1925016 | Y54: =1/E53 -> 2.3546032 | Z54: =1/F53 -> 1.0787487 | AA54: =1/G53 -> 2.7855153 | AB54: =1/H53 -> 0.019185131 | AC54: =1/I53 -> 1.566416 | ... AH54: =1/N53 -> 0.32172962 | AN54: 40940 | AO54: 105 | AP54: 118.5 | AS54: 40940 | AT54: 277.76306
A55: 42767 | B55: 0.594 | C55: 0.5967 | D55: 0.4541 | E55: 0.4262 | F55: 0.9213 | G55: 0.3637 | H55: 51.5245 | I55: 0.6301 | J55: 4.0538 | K55: 0.648 | L55: 0.4553 | M55: 1.1415 | N55: 3.1296 | U55: 42736 | V55: =1/B54 -> 1.6583748 | W55: =1/C54 -> 1.6826519 | X55: =1/D54 -> 2.2133687 | Y55: =1/E54 -> 2.3696682 | Z55: =1/F54 -> 1.0844811 | AA55: =1/G54 -> 2.7434842 | AB55: =1/H54 -> 0.019335852 | AC55: =1/I54 -> 1.5810277 | ... AH55: =1/N54 -> 0.32248702 | AN55: 40969 | AO55: 104.7 | AP55: 119.9 | AS55: 40969 | AT55: 283.5471
A56: 42795 | B56: 0.5888 | C56: 0.6016 | D56: 0.4484 | E56: 0.4192 | F56: 0.9154 | G56: 0.3635 | H56: 50.8292 | I56: 0.6417 | J56: 4.0089 | K56: 0.6353 | L56: 0.4492 | M56: 1.135 | N56: 3.098 | U56: 42767 | V56: =1/B55 -> 1.6835017 | W56: =1/C55 -> 1.675884 | X56: =1/D55 -> 2.2021581 | Y56: =1/E55 -> 2.3463163 | Z56: =1/F55 -> 1.0854228 | AA56: =1/G55 -> 2.7495188 | AB56: =1/H55 -> 0.019408243 | AC56: =1/I55 -> 1.5870497 | ... AH56: =1/N55 -> 0.31952965 | AN56: 41000 | AO56: 104.2 | AP56: 120.3 | AS56: 41000 | AT56: 288.69166
A57: 42826 | B57: 0.5914 | C57: 0.5993 | D57: 0.4448 | E57: 0.4155 | F57: 0.9128 | G57: 0.3528 | H57: 49.1894 | I57: 0.6404 | J57: 4.004 | K57: 0.6281 | L57: 0.4462 | M57: 1.1344 | N57: 3.0744 | U57: 42795 | V57: =1/B56 -> 1.6983696 | W57: =1/C56 -> 1.662234 | X57: =1/D56 -> 2.2301517 | Y57: =1/E56 -> 2.3854962 | Z57: =1/F56 -> 1.0924186 | AA57: =1/G56 -> 2.7510316 | AB57: =1/H56 -> 0.019673731 | AC57: =1/I56 -> 1.5583606 | ... AH57: =1/N56 -> 0.3227889 | AN57: 41030 | AO57: 103.5 | AP57: 118.5 | AS57: 41030 | AT57: 294.25329
A58: 42856 | B58: 0.5956 | C58: 0.6036 | D58: 0.4361 | E58: 0.401 | F58: 0.9034 | G58: 0.3427 | H58: 49.7221 | I58: 0.6396 | J58: 3.8989 | K58: 0.622 | L58: 0.4434 | M58: 1.0896 | N58: 3.0545 | U58: 42826 | V58: =1/B57 -> 1.6909029 | W58: =1/C57 -> 1.6686134 | X58: =1/D57 -> 2.2482014 | Y58: =1/E57 -> 2.4067389 | Z58: =1/F57 -> 1.0955302 | AA58: =1/G57 -> 2.8344671 | AB58: =1/H57 -> 0.020329583 | AC58: =1/I57 -> 1.561524 | ... AH58: =1/N57 -> 0.32526672 | AN58: 41061 | AO58: 103.3 | AP58: 121.7 | AS58: 41061 | AT58: 293.22898
A59: 42887 | B59: 0.597 | C59: 0.6012 | D59: 0.4356 | E59: 0.4018 | F59: 0.9055 | G59: 0.3522 | H59: 50.0129 | I59: 0.6258 | J59: 3.9267 | K59: 0.6277 | L59: 0.4515 | M59: 1.0586 | N59: 3.0746 | U59: 42856 | V59: =1/B58 -> 1.6789792 | W59: =1/C58 -> 1.6567263 | X59: =1/D58 -> 2.2930521 | Y59: =1/E58 -> 2.4937656 | Z59: =1/F58 -> 1.1069294 | AA59: =1/G58 -> 2.9180041 | AB59: =1/H58 -> 0.020111781 | AC59: =1/I58 -> 1.5634772 | ... AH59: =1/N58 -> 0.32738582 | AN59: 41091 | AO59: 103.5 | AP59: 111.5 | AS59: 41091 | AT59: 304.73567
A60: 42917 | B60: 0.5894 | C60: 0.5846 | D60: 0.4395 | E60: 0.3989 | F60: 0.9099 | G60: 0.3534 | H60: 51.6383 | I60: 0.6258 | J60: 3.8313 | K60: 0.6334 | L60: 0.4599 | M60: 1.0669 | N60: 3.1153 | U60: 42887 | V60: =1/B59 -> 1.6750419 | W60: =1/C59 -> 1.66334 | X60: =1/D59 -> 2.2956841 | Y60: =1/E59 -> 2.4888004 | Z60: =1/F59 -> 1.1043622 | AA60: =1/G59 -> 2.8392959 | AB60: =1/H59 -> 0.019994841 | AC60: =1/I59 -> 1.5979546 | ... AH60: =1/N59 -> 0.32524556 | AN60: 41122 | AO60: 102.5 | AP60: 111.1 | AS60: 41122 | AT60: 308.23201
A61: 42948 | B61: 0.5847 | C61: 0.5845 | D61: 0.4457 | E61: 0.3919 | F61: 0.9106 | G61: 0.3566 | H61: 50.7998 | I61: 0.634 | J61: 3.7489 | K61: 0.6332 | L61: 0.4634 | M61: 1.0685 | N61: 3.0929 | U61: 42917 | V61: =1/B60 -> 1.6966407 | W61: =1/C60 -> 1.7105713 | X61: =1/D60 -> 2.2753129 | Y61: =1/E60 -> 2.506894 | Z61: =1/F60 -> 1.0990219 | AA61: =1/G60 -> 2.8296548 | AB61: =1/H60 -> 0.019365471 | AC61: =1/I60 -> 1.5979546 | ... AH61: =1/N60 -> 0.32099637 | AN61: 41153 | AO61: 103.2 | AP61: 110.4 | AS61: 41153 | AT61: 306.76097
A62: 42979 | B62: 0.5799 | C62: 0.5693 | D62: 0.4432 | E62: 0.3884 | F62: 0.9108 | G62: 0.3481 | H62: 51.147 | I62: 0.6392 | J62: 3.7054 | K62: 0.6275 | L62: 0.4625 | M62: 1.0704 | N62: 3.0378 | U62: 42948 | V62: =1/B61 -> 1.7102788 | W62: =1/C61 -> 1.710864 | X62: =1/D61 -> 2.2436617 | Y62: =1/E61 -> 2.5516713 | Z62: =1/F61 -> 1.098177 | AA62: =1/G61 -> 2.8042625 | AB62: =1/H61 -> 0.019685117 | AC62: =1/I61 -> 1.5772871 | ... AH62: =1/N61 -> 0.32332115 | AN62: 41183 | AO62: 101.8 | AP62: 110.1 | AS62: 41183 | AT62: 302.26363
A63: 43009 | B63: 0.5841 | C63: 0.5737 | D63: 0.4453 | E63: 0.3875 | F63: 0.9106 | G63: 0.3445 | H63: 51.4244 | I63: 0.6467 | J63: 3.7271 | K63: 0.6226 | L63: 0.456 | M63: 1.0697 | N63: 3.022 | U63: 42979 | V63: =1/B62 -> 1.7244352 | W63: =1/C62 -> 1.7565431 | X63: =1/D62 -> 2.2563177 | Y63: =1/E62 -> 2.5746653 | Z63: =1/F62 -> 1.0979359 | AA63: =1/G62 -> 2.8727377 | AB63: =1/H62 -> 0.019551489 | AC63: =1/I62 -> 1.5644556 | ... AH63: =1/N62 -> 0.32918559 | AN63: 41214 | AO63: 101.6 | AP63: 109.7 | AS63: 41214 | AT63: 307.37866
A64: 43040 | B64: 0.5884 | C64: 0.5736 | D64: 0.4438 | E64: 0.3826 | F64: 0.9053 | G64: 0.3393 | H64: 50.649 | I64: 0.6531 | J64: 3.7671 | K64: 0.612 | L64: 0.4494 | M64: 1.0673 | N64: 2.9766 | U64: 43009 | V64: =1/B63 -> 1.7120356 | W64: =1/C63 -> 1.7430713 | X64: =1/D63 -> 2.2456771 | Y64: =1/E63 -> 2.5806452 | Z64: =1/F63 -> 1.098177 | AA64: =1/G63 -> 2.9027576 | AB64: =1/H63 -> 0.019446022 | AC64: =1/I63 -> 1.546312 | ... AH64: =1/N63 -> 0.33090668 | AN64: 41244 | AO64: 101.5 | AP64: 110.6 | AS64: 41244 | AT64: 317.12564
... A115: 44621 | B115: 0.5989 | C115: 0.5591 | D115: 0.4083 | E115: 0.3996 | F115: 0.909 | G115: 0.3341 | H115: 52.1145 | I115: 0.6435 | J115: 4.2234 | K115: 0.6038 | L115: 0.4418 | M115: 1.181 | N115: 2.8026 | U115: 44593 | V115: =1/B114 -> 1.6428454 | W115: =1/C114 -> 1.8021265 | X115: =1/D114 -> 2.4956326 | Y115: =1/E114 -> 2.6205451 | Z115: =1/F114 -> 1.096852 | AA115: =1/G114 -> 3.1104199 | AB115: =1/H114 -> 0.019964065 | AC115: =1/I114 -> 1.5288182 | ... AH115: =1/N114 -> 0.3523484 | AN115: 42795 | AO115: 91.41 | AP115: 104.18 | AS115: 42795 | AT115: 503.6
A116: 44652 | B116: 0.5953 | C116: 0.5553 | D116: 0.4128 | E116: 0.4058 | F116: 0.9096 | G116: 0.3389 | H116: 55.2994 | I116: 0.6488 | J116: 4.2011 | K116: 0.6052 | L116: 0.4407 | M116: 1.1844 | N116: 2.8287 | U116: 44621 | V116: =1/B115 -> 1.6697278 | W116: =1/C115 -> 1.7885888 | X116: =1/D115 -> 2.4491795 | Y116: =1/E115 -> 2.5025025 | Z116: =1/F115 -> 1.10011 | AA116: =1/G115 -> 2.9931158 | AB116: =1/H115 -> 0.019188518 | AC116: =1/I115 -> 1.5540016 | ... AH116: =1/N115 -> 0.35681153 | AN116: 42826 | AO116: 91.21 | AP116: 103.79 | AS116: 42826 | AT116: 509.9 | AU116: m3 used in 2017 before
A117: 44682 | B117: 0.6093 | C117: 0.5536 | D117: 0.4195 | E117: 0.4066 | F117: 0.9156 | G117: 0.3448 | H117: 55.3629 | I117: 0.6715 | J117: 4.2735 | K117: 0.5992 | L117: 0.431 | M117: 1.1808 | N117: 2.8854 | U117: 44652 | V117: =1/B116 -> 1.6798253 | W117: =1/C116 -> 1.8008284 | X117: =1/D116 -> 2.4224806 | Y117: =1/E116 -> 2.4642681 | Z117: =1/F116 -> 1.0993843 | AA117: =1/G116 -> 2.9507229 | AB117: =1/H116 -> 0.018083379 | AC117: =1/I116 -> 1.541307 | ... AH117: =1/N116 -> 0.35351928 | AN117: 42856 | AO117: 90.77 | AP117: 103.63 | AS117: 42856 | AT117: 517.6
A118: 44713 | B118: 0.6096 | C118: 0.5499 | D118: 0.4146 | E118: 0.4054 | F118: 0.9133 | G118: 0.3471 | H118: 57.3795 | I118: 0.6746 | J118: 4.3023 | K118: 0.5978 | L118: 0.4296 | M118: 1.1777 | N118: 2.8767 | U118: 44682 | V118: =1/B117 -> 1.6412276 | W118: =1/C117 -> 1.8063584 | X118: =1/D117 -> 2.3837902 | Y118: =1/E117 -> 2.4594196 | Z118: =1/F117 -> 1.09218 | AA118: =1/G117 -> 2.900232 | AB118: =1/H117 -> 0.018062638 | AC118: =1/I117 -> 1.4892033 | ... AH118: =1/N117 -> 0.3465724 | AN118: 42887 | AO118: 91.28 | AP118: 104.92 | AS118: 42887 | AT118: 534.9
A119: 44743 | B119: 0.6185 | C119: 0.55 | D119: 0.4102 | E119: 0.4167 | F119: 0.9182 | G119: 0.3534 | H119: 58.0608 | I119: 0.6849 | J119: 4.4135 | K119: 0.5972 | L119: 0.4254 | M119: 1.1877 | N119: 2.865 | U119: 44713 | V119: =1/B118 -> 1.6404199 | W119: =1/C118 -> 1.8185125 | X119: =1/D118 -> 2.4119633 | Y119: =1/E118 -> 2.4666996 | Z119: =1/F118 -> 1.0949305 | AA119: =1/G118 -> 2.8810141 | AB119: =1/H118 -> 0.017427827 | AC119: =1/I118 -> 1.4823599 | ... AH119: =1/N118 -> 0.34762054 | AN119: 42917 | AO119: 91.39 | AP119: 104.54 | AS119: 42917 | AT119: 533.2
A120: 44774 | B120: 0.6126 | C120: 0.5513 | D120: 0.4065 | E120: 0.421 | F120: 0.9156 | G120: 0.3551 | H120: 57.6226 | I120: 0.681 | J120: 4.4252 | K120: 0.595 | L120: 0.4276 | M120: 1.188 | N120: 2.9053 | U120: 44743 | V120: =1/B119 -> 1.6168149 | W120: =1/C119 -> 1.8181818 | X120: =1/D119 -> 2.4378352 | Y120: =1/E119 -> 2.399808 | Z120: =1/F119 -> 1.0890873 | AA120: =1/G119 -> 2.8296548 | AB120: =1/H119 -> 0.017223325 | AC120: =1/I119 -> 1.4600672 | ... AH120: =1/N119 -> 0.34904014 | AN120: 42948 | AO120: 91.79 | AP120: 104.68 | AS120: 42948 | AT120: 552.3
A121: 44805 | B121: 0.6249 | C121: 0.5572 | D121: 0.4055 | E121: 0.4218 | F121: 0.918 | G121: 0.3685 | H121: 59.757 | I121: 0.7041 | J121: 4.5563 | K121: 0.5954 | L121: 0.4192 | M121: 1.1897 | N121: 2.9371 | U121: 44774 | V121: =1/B120 -> 1.6323865 | W121: =1/C120 -> 1.8138944 | X121: =1/D120 -> 2.4600246 | Y121: =1/E120 -> 2.3752969 | Z121: =1/F120 -> 1.09218 | AA121: =1/G120 -> 2.8161081 | AB121: =1/H120 -> 0.017354302 | AC121: =1/I120 -> 1.4684288 | ... AH121: =1/N120 -> 0.34419853 | AN121: 42979 | AO121: 91.88 | AP121: 104.67 | AS121: 42979 | AT121: 549.7
A122: 44835 | B122: 0.6437 | C122: 0.5626 | D122: 0.4063 | E122: 0.4164 | F122: 0.9247 | G122: 0.3624 | H122: 60.2 | I122: 0.7204 | J122: 4.5656 | K122: 0.5885 | L122: 0.4108 | M122: 1.2018 | N122: 2.9508 | U122: 44805 | V122: =1/B121 -> 1.600256 | W122: =1/C121 -> 1.7946877 | X122: =1/D121 -> 2.4660912 | Y122: =1/E121 -> 2.3707918 | Z122: =1/F121 -> 1.0893246 | AA122: =1/G121 -> 2.7137042 | AB122: =1/H121 -> 0.016734441 | AC122: =1/I121 -> 1.4202528 | ... AH122: =1/N121 -> 0.34047189 | AN122: 43009 | AO122: 91.99 | AP122: 104.38 | AS122: 43009 | AT122: 553.6
A123: 44866 | B123: 0.6345 | C123: 0.5636 | D123: 0.4024 | E123: 0.4105 | F123: 0.9238 | G123: 0.3562 | H123: 59.5709 | I123: 0.6909 | J123: 4.4743 | K123: 0.5855 | L123: 0.4197 | M123: 1.1973 | N123: 3.0138 | U123: 44835 | V123: =1/B122 -> 1.5535187 | W123: =1/C122 -> 1.7774618 | X123: =1/D122 -> 2.4612355 | Y123: =1/E122 -> 2.401537 | Z123: =1/F122 -> 1.0814318 | AA123: =1/G122 -> 2.7593819 | AB123: =1/H122 -> 0.016611296 | AC123: =1/I122 -> 1.3881177 | ... AH123: =1/N122 -> 0.33889115 | AN123: 43040 | AO123: 91.54 | AP123: 103.07 | AS123: 43040 | AT123: 553.3
A124: 44896 | B124: 0.6306 | C124: 0.5796 | D124: 0.3957 | E124: 0.4023 | F124: 0.9257 | G124: 0.3493 | H124: 57.5987 | I124: 0.6701 | J124: 4.4281 | K124: 0.5805 | L124: 0.4265 | M124: 1.1951 | N124: 2.9767 | U124: 44866 | V124: =1/B123 -> 1.5760441 | W124: =1/C123 -> 1.774308 | X124: =1/D123 -> 2.4850895 | Y124: =1/E123 -> 2.4360536 | Z124: =1/F123 -> 1.0824854 | AA124: =1/G123 -> 2.8074116 | AB124: =1/H123 -> 0.01678672 | AC124: =1/I123 -> 1.4473875 | ... AH124: =1/N123 -> 0.33180702 | AN124: 43070 | AO124: 91.26 | AP124: 103.3 | AS124: 43070 | AT124: 560.6
A125: 44927 | B125: 0.6172 | C125: 0.5769 | D125: 0.3948 | E125: 0.3979 | F125: 0.9198 | G125: 0.3502 | H125: 55.8699 | I125: 0.6698 | J125: 4.4617 | K125: 0.5734 | L125: 0.4298 | M125: 1.1931 | N125: 2.9218 | U125: 44896 | V125: =1/B124 -> 1.5857913 | W125: =1/C124 -> 1.7253278 | X125: =1/D124 -> 2.527167 | Y125: =1/E124 -> 2.4857072 | Z125: =1/F124 -> 1.0802636 | AA125: =1/G124 -> 2.8628686 | AB125: =1/H124 -> 0.017361503 | AC125: =1/I124 -> 1.4923146 | ... AH125: =1/N124 -> 0.33594249 | AN125: 43101 | AO125: 90.56 | AP125: 102.99 | AS125: 43101 | AT125: 552.5
A126: 44958 | B126: 0.617 | C126: 0.5743 | D126: 0.3929 | E126: 0.3981 | F126: 0.9163 | G126: 0.3525 | H126: 56.6779 | I126: 0.6774 | J126: 4.4617 | K126: 0.5727 | L126: 0.4279 | M126: 1.1941 | N126: 2.9229 | U126: 44927 | V126: =1/B125 -> 1.6202203 | W126: =1/C125 -> 1.7334027 | X126: =1/D125 -> 2.5329281 | Y126: =1/E125 -> 2.5131943 | Z126: =1/F125 -> 1.0871929 | AA126: =1/G125 -> 2.8555111 | AB126: =1/H125 -> 0.017898725 | AC126: =1/I125 -> 1.492983 | ... AH126: =1/N125 -> 0.34225477 | AN126: 43132 | AO126: 90.32 | AP126: 103.49 | AS126: 43132 | AT126: 558.2
A127: 44986 | B127: 0.6335 | C127: 0.5802 | D127: 0.3907 | E127: 0.3955 | F127: 0.9194 | G127: 0.3484 | H127: 56.548 | I127: 0.6824 | J127: 4.4428 | K127: 0.5725 | L127: 0.4243 | M127: 1.198 | N127: 2.9261 | U127: 44958 | V127: =1/B126 -> 1.6207455 | W127: =1/C126 -> 1.7412502 | X127: =1/D126 -> 2.5451769 | Y127: =1/E126 -> 2.5119317 | Z127: =1/F126 -> 1.0913456 | AA127: =1/G126 -> 2.8368794 | AB127: =1/H126 -> 0.017643561 | AC127: =1/I126 -> 1.4762327 | ... AH127: =1/N126 -> 0.34212597 | AN127: 43160 | AO127: 90.15 | AP127: 103.4 | AS127: 43160 | AT127: 558.7
A128: 45017 | B128: 0.6325 | C128: 0.5722 | D128: 0.3798 | E128: 0.3869 | F128: 0.9194 | G128: 0.3405 | H128: 56.5395 | I128: 0.6826 | J128: 4.3918 | K128: 0.5692 | L128: 0.4249 | M128: 1.1983 | N128: 2.9267 | U128: 44986 | V128: =1/B127 -> 1.578532 | W128: =1/C127 -> 1.7235436 | X128: =1/D127 -> 2.5595086 | Y128: =1/E127 -> 2.528445 | Z128: =1/F127 -> 1.0876659 | AA128: =1/G127 -> 2.8702641 | AB128: =1/H127 -> 0.017684091 | AC128: =1/I127 -> 1.4654162 | ... AH128: =1/N127 -> 0.34175182 | AN128: 43191 | AO128: 90.45 | AP128: 105.35 | AS128: 43191 | AT128: 547.1
... A144: 45505 | B144: 0.6344 | C144: 0.5772 | D144: 0.3603 | E144: 0.3826 | F144: 0.9348 | G144: 0.3255 | H144: 61.6889 | I144: 0.6943 | J144: 4.39 | K144: 0.5597 | L144: 0.4226 | M144: 1.1538 | N144: 3.0232 | U144: 45474 | V144: =1/B143 -> 1.5852885 | W144: =1/C143 -> 1.7298045 | X144: =1/D143 -> 2.6723677 | Y144: =1/E143 -> 2.5773196 | Z144: =1/F143 -> 1.0687186 | AA144: =1/G143 -> 3.058104 | AB144: =1/H143 -> 0.015037933 | AC144: =1/I143 -> 1.43287 | ... AH144: =1/N143 -> 0.32628557 | AN144: 43678 | AO144: 92.41 | AP144: 108.61 | AS144: 43678 | AT144: 608.6
A145: 45536 | B145: 0.6288 | C145: 0.5766 | D145: 0.3588 | E145: 0.3829 | F145: 0.9319 | G145: 0.3216 | H145: 60.96 | I145: 0.6837 | J145: 4.357 | K145: 0.5563 | L145: 0..4263 | M145: 1.1518 | N145: 3.0185 | U145: 45505 | V145: =1/B144 -> 1.5762926 | W145: =1/C144 -> 1.7325017 | X145: =1/D144 -> 2.7754649 | Y145: =1/E144 -> 2.6136958 | Z145: =1/F144 -> 1.0697475 | AA145: =1/G144 -> 3.0721966 | AB145: =1/H144 -> 0.016210372 | AC145: =1/I144 -> 1.4402996 | ... AH145: =1/N144 -> 0.33077534 | AN145: 43709 | AO145: 92.58 | AP145: 108.65 | AS145: 43709 | AT145: 594.5
A146: 45566 | B146: 0.6295 | C146: 0.5815 | D146: 0.3621 | E146: 0.3872 | F146: 0.9317 | G146: 0.323 | H146: 63.1907 | I146: 0.6935 | J146: 4.4233 | K146: 0.5578 | L146: 0.4236 | M146: 1.157 | N146: 3.0008 | U146: 45536 | V146: =1/B145 -> 1.5903308 | W146: =1/C145 -> 1.7343045 | X146: =1/D145 -> 2.787068 | Y146: =1/E145 -> 2.6116479 | Z146: =1/F145 -> 1.0730765 | AA146: =1/G145 -> 3.1094527 | AB146: =1/H145 -> 0.016404199 | AC146: =1/I145 -> 1.4626298 | ... AE146: =1/K145 -> 1.7975912 | AF146: =AF145+0.0002 -> 2.3665038 | AG146: =1/M145 -> 0.86820629 | AH146: =1/N145 -> 0.33129038 | AN146: 43739 | AO146: 92.29 | AP146: 108.52 | AS146: 43739 | AT146: 592.5
A147: 45597 | B147: 0.6393 | C147: 0.584 | D147: 0.3662 | E147: 0.3927 | F147: 0.9335 | G147: 0.3271 | H147: 64.1782 | I147: 0.7064 | J147: 4.5562 | K147: 0.5628 | L147: 0.4186 | M147: 1.1578 | N147: 3.0172 | U147: 45566 | V147: =1/B146 -> 1.5885624 | W147: =1/C146 -> 1.7196905 | X147: =1/D146 -> 2.761668 | Y147: =1/E146 -> 2.5826446 | Z147: =1/F146 -> 1.0733069 | AA147: =1/G146 -> 3.0959752 | AB147: =1/H146 -> 0.015825114 | AC147: =1/I146 -> 1.4419611 | ... AH147: =1/N146 -> 0.33324447 | AN147: 43770 | AO147: 92.15 | AP147: 107.65 | AS147: 43770 | AT147: 605.6
A148: 45627 | B148: 0.6513 | C148: 0.5887 | D148: 0.3661 | E148: 0.3939 | F148: 0.9363 | G148: 0.3259 | H148: 63.3787 | I148: 0.7172 | J148: 4.5391 | K148: 0.5622 | L148: 0.4139 | M148: 1.1545 | N148: 3.0134 | U148: 45597 | V148: =1/B147 -> 1.5642109 | W148: =1/C147 -> 1.7123288 | X148: =1/D147 -> 2.7307482 | Y148: =1/E147 -> 2.5464731 | Z148: =1/F147 -> 1.0712373 | AA148: =1/G147 -> 3.0571691 | AB148: =1/H147 -> 0.015581615 | AC148: =1/I147 -> 1.4156285 | ... AH148: =1/N147 -> 0.33143312 | AN148: 43800 | AO148: 91.49 | AP148: 107.13 | AS148: 43800 | AT148: 602.2
A149: 45658 | B149: 0.6572 | C149: 0.5896 | D149: 0.3705 | E149: 0.395 | F149: 0.9378 | G149: 0.3308 | H149: 64.0725 | I149: 0.7265 | J149: 4.5373 | K149: 0.5618 | L149: 0.4103 | M149: 1.1554 | N149: 2.9954 | U149: 45627 | V149: =1/B148 -> 1.5353908 | W149: =1/C148 -> 1.6986581 | X149: =1/D148 -> 2.7314941 | Y149: =1/E148 -> 2.5387154 | Z149: =1/F148 -> 1.0680337 | AA149: =1/G148 -> 3.0684259 | AB149: =1/H148 -> 0.015778172 | AC149: =1/I148 -> 1.3943112 | ... AH149: =1/N148 -> 0.33185107 | AN149: 43831 | AO149: 91.7 | AP149: 106.25 | AS149: 43831 | AT149: 592.5
A150: 45689 | B150: 0.6526 | C150: 0.5889 | D150: 0.3699 | E150: 0.3945 | F150: 0.9363 | G150: 0.3275 | H150: 62.3546 | I150: 0.7232 | J150: 4.4499 | K150: 0.5583 | L150: 0.412 | M150: 1.153 | N150: 2.9962 | U150: 45658 | V150: =1/B149 -> 1.5216068 | W150: =1/C149 -> 1.6960651 | X150: =1/D149 -> 2.6990553 | Y150: =1/E149 -> 2.5316456 | Z150: =1/F149 -> 1.0663254 | AA150: =1/G149 -> 3.0229746 | AB150: =1/H149 -> 0.01560732 | AC150: =1/I149 -> 1.3764625 | ... AH150: =1/N149 -> 0.33384523 | AN150: 43862 | AO150: 93.17 | AP150: 108.56 | AS150: 43862 | AT150: 590.2
A151: 45717 | B151: 0.6536 | C151: 0.5925 | D151: 0.3627 | E151: 0.3816 | F151: 0.9367 | G151: 0.3187 | H151: 61.4091 | I151: 0.7193 | J151: 4.191 | K151: 0.555 | L151: 0.4129 | M151: 1.1532 | N151: 2.9941 | U151: 45689 | V151: =1/B150 -> 1.5323322 | W151: =1/C150 -> 1.6980812 | X151: =1/D150 -> 2.7034334 | Y151: =1/E150 -> 2.5348542 | Z151: =1/F150 -> 1.0680337 | AA151: =1/G150 -> 3.0534351 | AB151: =1/H150 -> 0.016037309 | AC151: =1/I150 -> 1.3827434 | ... AH151: =1/N150 -> 0.33375609 | AN151: 43891 | AO151: 94.85 | AP151: 110.86 | AS151: 43891 | AT151: 596.4
A152: 45748 | B152: 0.6579 | C152: 0.5798 | D152: 0.3449 | E152: 0.3695 | F152: 0.9368 | G152: 0.3146 | H152: 59.8139 | I152: 0.7111 | J152: 4.0552 | K152: 0.5525 | L152: 0.4137 | M152: 1.1505 | N152: 3.0186 | U152: 45717 | V152: =1/B151 -> 1.5299878 | W152: =1/C151 -> 1.6877637 | X152: =1/D151 -> 2.7570995 | Y152: =1/E151 -> 2.6205451 | Z152: =1/F151 -> 1.0675777 | AA152: =1/G151 -> 3.1377471 | AB152: =1/H151 -> 0.016284231 | AC152: =1/I151 -> 1.3902405 | ... AH152: =1/N151 -> 0.33399018 | AN152: 43922 | AO152: 94.67 | AP152: 110.48 | AS152: 43922 | AT152: 581.6
A153: 45778 | B153: 0.6469 | C153: 0.5781 | D153: 0.3438 | E153: 0.3691 | F153: 0.9326 | G153: 0.3112 | H153: 60.2441 | I153: 0.7015 | J153: 4.0252 | K153: 0.544 | L153: 0.4173 | M153: 1.1475 | N153: 3.0127 | U153: 45748 | V153: =1/B152 -> 1.5199878 | W153: =1/C152 -> 1.7247327 | X153: =1/D152 -> 2.8993911 | Y153: =1/E152 -> 2.7063599 | Z153: =1/F152 -> 1.0674637 | AA153: =1/G152 -> 3.1786395 | AB153: =1/H152 -> 0.016718522 | AC153: =1/I152 -> 1.406272 | ... AH153: =1/N152 -> 0.3312794 | AN153: 43952 | AO153: 94.82 | AP153: 110.33 | AS153: 43952 | AT153: 592.2
A154: 45809 | B154: 0.6438 | C154: 0.5732 | D154: 0.3393 | E154: 0.3632 | F154: 0.9331 | G154: 0.3083 | H154: 60.4743 | I154: 0.6945 | J154: 4.0047 | K154: 0.518 | L154: 0.4195 | M154: 1.1447 | N154: 3.0127 | U154: 45778 | V154: =1/B153 -> 1.545834 | W154: =1/C153 -> 1.7298045 | X154: =1/D153 -> 2.9086678 | Y154: =1/E153 -> 2.7092929 | Z154: =1/F153 -> 1.0722711 | AA154: =1/G153 -> 3.2133676 | AB154: =1/H153 -> 0.016599136 | AC154: =1/I153 -> 1.4255167 | ... AH154: =1/N153 -> 0.33192817 | AN154: 43983 | AO154: 92.88 | AP154: 106.74 | AS154: 43983 | AT154: 607.1
A155: 45839 | B155: 0.6391 | C155: 0.5729 | D155: 0.332 | E155: 0.3575 | F155: 0.9323 | G155: 0.309 | H155: 61.3836 | I155: 0.6967 | J155: 4.0095 | K155: 0.5402 | L155: 0.4191 | M155: 1.1433 | N155: 3.006 | U155: 45809 | V155: =1/B154 -> 1.5532774 | W155: =1/C154 -> 1.7445918 | X155: =1/D154 -> 2.9472443 | Y155: =1/E154 -> 2.753304 | Z155: =1/F154 -> 1.0716965 | AA155: =1/G154 -> 3.2435939 | AB155: =1/H154 -> 0.01653595 | AC155: =1/I154 -> 1.4398848 | ... AH155: =1/N154 -> 0.33192817 | AN155: 44013 | AO155: 91.21 | AP155: 104.8 | AS155: 44013 | AT155: 616.9
A156: 45870 | B156: 0.6402 | C156: 0.5744 | D156: 0.3334 | E156: 0.3569 | F156: 0.9317 | G156: 0.3086 | H156: 61.3236 | I156: 0.704 | J156: 3.9889 | K156: 0.5388 | L156: 0.4165 | M156: 1.1391 | N156: 2.9887 | U156: 45839 | V156: =1/B155 -> 1.5647004 | W156: =1/C155 -> 1.7455053 | X156: =1/D155 -> 3.0120482 | Y156: =1/E155 -> 2.7972028 | Z156: =1/F155 -> 1.0726161 | AA156: =1/G155 -> 3.236246 | AB156: =1/H155 -> 0.016290996 | AC156: =1/I155 -> 1.435338 | ... AH156: =1/N155 -> 0.332668 | AN156: 44044 | AO156: 90.77 | AP156: 104.23 | AS156: 44044 | AT156: 624.7
A157: 45901 | B157: 0.632 | C157: 0.5764 | D157: 0.3301 | E157: 0.3548 | F157: 0.9296 | G157: 0.3079 | H157: 61.5641 | I157: 0.7074 | J157: 3.9084 | K157: 0.5396 | L157: 0.4173 | M157: 1.1464 | N157: 2.9737 | U157: 45870 | V157: =1/B156 -> 1.5620119 | W157: =1/C156 -> 1.7409471 | X157: =1/D156 -> 2.9994001 | Y157: =1/E156 -> 2.8019053 | Z157: =1/F156 -> 1.0733069 | AA157: =1/G156 -> 3.2404407 | AB157: =1/H156 -> 0.016306936 | AC157: =1/I156 -> 1.4204545 | ... AH157: =1/N156 -> 0.33459364 | AN157: 44075 | AO157: 90.14 | AP157: 103.91 | AS157: 44075 | AT157: 640.8
A158: 45931 | B158: 0.6318 | C158: 0.5793 | D158: 0.3284 | E158: 0.3549 | F158: 0.9272 | G158: 0.3089 | H158: 62.5025 | I158: 0.7174 | J158: 3.9041 | K158: 0.5404 | L158: 0.4145 | M158: 1.1489 | N158: 2.9517 | U158: 45901 | V158: =1/B157 -> 1.5822785 | W158: =1/C157 -> 1.7349063 | X158: =1/D157 -> 3.029385 | Y158: =1/E157 -> 2.8184893 | Z158: =1/F157 -> 1.0757315 | AA158: =1/G157 -> 3.2478077 | AB158: =1/H157 -> 0.016243233 | AC158: =1/I157 -> 1.4136274 | ... AH158: =1/N157 -> 0.3362814 | AN158: 44105 | AO158: 89.06 | AP158: 102.54 | AS158: 44105 | AT158: 655.2
... A205: 45505 | B205: 0.6344 | C205: 0.5772 | D205: 0.3603 | E205: 0.3826 | F205: 0.9348 | G205: 0.3255 | H205: 61.6889 | I205: 0.6943 | J205: 4.39 | K205: 0.5597 | L205: 0.4226 | M205: 1.1538 | N205: 3.0232 | U205: 45474 | V205: =1/B204 -> 1.5852885 | W205: =1/C204 -> 1.7298045 | X205: =1/D204 -> 2.6723677 | Y205: =1/E204 -> 2.5773196 | Z205: =1/F204 -> 1.0687186 | AA205: =1/G204 -> 3.058104 | AB205: =1/H204 -> 0.015037933 | AC205: =1/I204 -> 1.43287 | ... AH205: =1/N204 -> 0.32628557 | AN205: 45536 | AO205: 93.95 | AP205: 117.25 | AS205: 45536 | AT205: 901.6
A206: 45536 | B206: 0.6288 | C206: 0.5766 | D206: 0.3588 | E206: 0.3829 | F206: 0.9319 | G206: 0.3216 | H206: 60.96 | I206: 0.6837 | J206: 4.357 | K206: 0.5563 | L206: 0..4263 | M206: 1.1518 | N206: 3.0185 | U206: 45505 | V206: =1/B205 -> 1.5762926 | W206: =1/C205 -> 1.7325017 | X206: =1/D205 -> 2.7754649 | Y206: =1/E205 -> 2.6136958 | Z206: =1/F205 -> 1.0697475 | AA206: =1/G205 -> 3.0721966 | AB206: =1/H205 -> 0.016210372 | AC206: =1/I205 -> 1.4402996 | ... AH206: =1/N205 -> 0.33077534 | AN206: 45566 | AO206: 95.45 | AP206: 119.88 | AS206: 45566 | AT206: 906.3
A207: 45566 | B207: 0.6295 | C207: 0.5815 | D207: 0.3621 | E207: 0.3872 | F207: 0.9317 | G207: 0.323 | H207: 63.1907 | I207: 0.6935 | J207: 4.4233 | K207: 0.5578 | L207: 0.4236 | M207: 1.157 | N207: 3.0008 | U207: 45536 | V207: =1/B206 -> 1.5903308 | W207: =1/C206 -> 1.7343045 | X207: =1/D206 -> 2.787068 | Y207: =1/E206 -> 2.6116479 | Z207: =1/F206 -> 1.0730765 | AA207: =1/G206 -> 3.1094527 | AB207: =1/H206 -> 0.016404199 | AC207: =1/I206 -> 1.4626298 | ... AH207: =1/N206 -> 0.33129038 | AN207: 45597 | AO207: 95.74 | AP207: 119.2 | AS207: 45597 | AT207: 910.7
A208: 45597 | B208: 0.6393 | C208: 0.584 | D208: 0.3662 | E208: 0.3927 | F208: 0.9335 | G208: 0.3271 | H208: 64.1782 | I208: 0.7064 | J208: 4.5562 | K208: 0.5628 | L208: 0.4186 | M208: 1.1578 | N208: 3.0172 | U208: 45566 | V208: =1/B207 -> 1.5885624 | W208: =1/C207 -> 1.7196905 | X208: =1/D207 -> 2.761668 | Y208: =1/E207 -> 2.5826446 | Z208: =1/F207 -> 1.0733069 | AA208: =1/G207 -> 3.0959752 | AB208: =1/H207 -> 0.015825114 | AC208: =1/I207 -> 1.4419611 | ... AH208: =1/N207 -> 0.33324447 | AN208: 45627 | AO208: 96.61 | AP208: 122.89 | AS208: 45627 | AT208: 937.5
A209: 45627 | B209: 0.6513 | C209: 0.5887 | D209: 0.3661 | E209: 0.3939 | F209: 0.9363 | G209: 0.3259 | H209: 63.3787 | I209: 0.7172 | J209: 4.5391 | K209: 0.5622 | L209: 0.4139 | M209: 1.1545 | N209: 3.0134 | U209: 45597 | V209: =1/B208 -> 1.5642109 | W209: =1/C208 -> 1.7123288 | X209: =1/D208 -> 2.7307482 | Y209: =1/E208 -> 2.5464731 | Z209: =1/F208 -> 1.0712373 | AA209: =1/G208 -> 3.0571691 | AB209: =1/H208 -> 0.015581615 | AC209: =1/I208 -> 1.4156285 | ... AH209: =1/N208 -> 0.33143312 | AN209: 45658 | AO209: 96.38 | AP209: 128.34 | AS209: 45658 | AT209: 922.5
A210: 45658 | B210: 0.6572 | C210: 0.5896 | D210: 0.3705 | E210: 0.395 | F210: 0.9378 | G210: 0.3308 | H210: 64.0725 | I210: 0.7265 | J210: 4.5373 | K210: 0.5618 | L210: 0.4103 | M210: 1.1554 | N210: 2.9954 | U210: 45627 | V210: =1/B209 -> 1.5353908 | W210: =1/C209 -> 1.6986581 | X210: =1/D209 -> 2.7314941 | Y210: =1/E209 -> 2.5387154 | Z210: =1/F209 -> 1.0680337 | AA210: =1/G209 -> 3.0684259 | AB210: =1/H209 -> 0.015778172 | AC210: =1/I209 -> 1.3943112 | ... AH210: =1/N209 -> 0.33185107 | AN210: 45689 | AO210: 96.25 | AP210: 126.94 | AS210: 45689 | AT210: 914.8
A211: 45689 | B211: 0.6526 | C211: 0.5889 | D211: 0.3699 | E211: 0.3945 | F211: 0.9363 | G211: 0.3275 | H211: 62.3546 | I211: 0.7232 | J211: 4.4499 | K211: 0.5583 | L211: 0.412 | M211: 1.153 | N211: 2.9962 | U211: 45658 | V211: =1/B210 -> 1.5216068 | W211: =1/C210 -> 1.6960651 | X211: =1/D210 -> 2.6990553 | Y211: =1/E210 -> 2.5316456 | Z211: =1/F210 -> 1.0663254 | AA211: =1/G210 -> 3.0229746 | AB211: =1/H210 -> 0.01560732 | AC211: =1/I210 -> 1.3764625 | ... AH211: =1/N210 -> 0.33384523 | AN211: 45717 | AO211: 96 | AP211: 126.31 | AS211: 45717 | AT211: 914.1
A212: 45717 | B212: 0.6536 | C212: 0.5925 | D212: 0.3627 | E212: 0.3816 | F212: 0.9367 | G212: 0.3187 | H212: 61.4091 | I212: 0.7193 | J212: 4.191 | K212: 0.555 | L212: 0.4129 | M212: 1.1532 | N212: 2.9941 | U212: 45689 | V212: =1/B211 -> 1.5323322 | W212: =1/C211 -> 1.6980812 | X212: =1/D211 -> 2.7034334 | Y212: =1/E211 -> 2.5348542 | Z212: =1/F211 -> 1.0680337 | AA212: =1/G211 -> 3.0534351 | AB212: =1/H211 -> 0.016037309 | AC212: =1/I211 -> 1.3827434 | ... AH212: =1/N211 -> 0.33375609 | AN212: 45748 | AO212: 94.97 | AP212: 123.72 | AS212: 45748 | AT212: 914.6
A213: 45748 | B213: 0.6579 | C213: 0.5798 | D213: 0.3449 | E213: 0.3695 | F213: 0.9368 | G213: 0.3146 | H213: 59.8139 | I213: 0.7111 | J213: 4.0552 | K213: 0.5525 | L213: 0.4137 | M213: 1.1505 | N213: 3.0186 | U213: 45717 | V213: =1/B212 -> 1.5299878 | W213: =1/C212 -> 1.6877637 | X213: =1/D212 -> 2.7570995 | Y213: =1/E212 -> 2.6205451 | Z213: =1/F212 -> 1.0675777 | AA213: =1/G212 -> 3.1377471 | AB213: =1/H212 -> 0.016284231 | AC213: =1/I212 -> 1.3902405 | ... AH213: =1/N212 -> 0.33399018 | AN213: 45778 | AO213: 94.88 | AP213: 124.55 | AS213: 45778 | AT213: 931.9
A214: 45778 | B214: 0.6469 | C214: 0.5781 | D214: 0.3438 | E214: 0.3691 | F214: 0.9326 | G214: 0.3112 | H214: 60.2441 | I214: 0.7015 | J214: 4.0252 | K214: 0.544 | L214: 0.4173 | M214: 1.1475 | N214: 3.0127 | U214: 45748 | V214: =1/B213 -> 1.5199878 | W214: =1/C213 -> 1.7247327 | X214: =1/D213 -> 2.8993911 | Y214: =1/E213 -> 2.7063599 | Z214: =1/F213 -> 1.0674637 | AA214: =1/G213 -> 3.1786395 | AB214: =1/H213 -> 0.016718522 | AC214: =1/I213 -> 1.406272 | ... AH214: =1/N213 -> 0.3312794 | AN214: 45809 | AO214: 94.65 | AP214: 125.04 | AS214: 45809 | AT214: 945.8
A215: 45809 | B215: 0.6438 | C215: 0.5732 | D215: 0.3393 | E215: 0.3632 | F215: 0.9331 | G215: 0.3083 | H215: 60.4743 | I215: 0.6945 | J215: 4.0047 | K215: 0.518 | L215: 0.4195 | M215: 1.1447 | N215: 3.0127 | U215: 45778 | V215: =1/B214 -> 1.545834 | W215: =1/C214 -> 1.7298045 | X215: =1/D214 -> 2.9086678 | Y215: =1/E214 -> 2.7092929 | Z215: =1/F214 -> 1.0722711 | AA215: =1/G214 -> 3.2133676 | AB215: =1/H214 -> 0.016599136 | AC215: =1/I214 -> 1.4255167 | ... AH215: =1/N214 -> 0.33192817 | AN215: 45839 | AO215: 95.12 | AP215: 123.77 | AS215: 45839 | AT215: 950.3 | AU215: =(AT215/AT203-1)*100 -> 7.3057814
A216: 45839 | B216: 0.6391 | C216: 0.5729 | D216: 0.332 | E216: 0.3575 | F216: 0.9323 | G216: 0.309 | H216: 61.3836 | I216: 0.6967 | J216: 4.0095 | K216: 0.5402 | L216: 0.4191 | M216: 1.1433 | N216: 3.006 | U216: 45809 | V216: =1/B215 -> 1.5532774 | W216: =1/C215 -> 1.7445918 | X216: =1/D215 -> 2.9472443 | Y216: =1/E215 -> 2.753304 | Z216: =1/F215 -> 1.0716965 | AA216: =1/G215 -> 3.2435939 | AB216: =1/H215 -> 0.01653595 | AC216: =1/I215 -> 1.4398848 | ... AH216: =1/N215 -> 0.33192817 | AN216: 45870 | AO216: 94.98 | AP216: 124.61 | AS216: 45870 | AT216: 955.3 | AU216: =(AT216/AT204-1)*100 -> 6.9525302
A217: 45870 | B217: 0.6402 | C217: 0.5744 | D217: 0.3334 | E217: 0.3569 | F217: 0.9317 | G217: 0.3086 | H217: 61.3236 | I217: 0.704 | J217: 3.9889 | K217: 0.5388 | L217: 0.4165 | M217: 1.1391 | N217: 2.9887 | U217: 45839 | V217: =1/B216 -> 1.5647004 | W217: =1/C216 -> 1.7455053 | X217: =1/D216 -> 3.0120482 | Y217: =1/E216 -> 2.7972028 | Z217: =1/F216 -> 1.0726161 | AA217: =1/G216 -> 3.236246 | AB217: =1/H216 -> 0.016290996 | AC217: =1/I216 -> 1.435338 | ... AH217: =1/N216 -> 0.332668 | AN217: 45901 | AO217: 95.26 | AP217: 123.06 | AS217: 45901 | AT217: 964.2 | AU217: =(AT217/AT205-1)*100 -> 6.9432121
A218: 45901 | B218: 0.632 | C218: 0.5764 | D218: 0.3301 | E218: 0.3548 | F218: 0.9296 | G218: 0.3079 | H218: 61.5641 | I218: 0.7074 | J218: 3.9084 | K218: 0.5396 | L218: 0.4173 | M218: 1.1464 | N218: 2.9737 | U218: 45870 | V218: =1/B217 -> 1.5620119 | W218: =1/C217 -> 1.7409471 | X218: =1/D217 -> 2.9994001 | Y218: =1/E217 -> 2.8019053 | Z218: =1/F217 -> 1.0733069 | AA218: =1/G217 -> 3.2404407 | AB218: =1/H217 -> 0.016306936 | AC218: =1/I217 -> 1.4204545 | ... AH218: =1/N217 -> 0.33459364 | AN218: 45931 | AO218: 95.51 | AP218: 123.52 | AS218: 45931 | AT218: 999 | AU218: =(AT218/AT206-1)*100 -> 10.228401
A219: 45931 | B219: 0.6318 | C219: 0.5793 | D219: 0.3284 | E219: 0.3549 | F219: 0.9272 | G219: 0.3089 | H219: 62.5025 | I219: 0.7174 | J219: 3.9041 | K219: 0.5404 | L219: 0.4145 | M219: 1.1489 | N219: 2.9517 | U219: 45901 | V219: =1/B218 -> 1.5822785 | W219: =1/C218 -> 1.7349063 | X219: =1/D218 -> 3.029385 | Y219: =1/E218 -> 2.8184893 | Z219: =1/F218 -> 1.0757315 | AA219: =1/G218 -> 3.2478077 | AB219: =1/H218 -> 0.016243233 | AC219: =1/I218 -> 1.4136274 | ... AH219: =1/N218 -> 0.3362814 | AN219: 45962 | AO219: 95.62 | AP219: 126.62 | AS219: 45962 | AT219: =AT195*(1+AU219/100) -> 942.1257 | AU219: 10.1
A220: 45962 | B220: 0.6323 | C220: 0.5787 | D220: 0.3287 | E220: 0.3554 | F220: 0.929 | G220: 0.3124 | H220: 63.7896 | I220: 0.7276 | J220: 3.913 | K220: 0.5404 | L220: 0.4121 | M220: 1.151 | N220: 2.9292 | U220: 45931 | V220: =1/B219 -> 1.5827794 | W220: =1/C219 -> 1.7262213 | X220: =1/D219 -> 3.045067 | Y220: =1/E219 -> 2.8176951 | Z220: =1/F219 -> 1.078516 | AA220: =1/G219 -> 3.2372936 | AB220: =1/H219 -> 0.01599936 | AC220: =1/I219 -> 1.3939225 | ... AH220: =1/N219 -> 0.33878782 | AN220: 45992 | AO220: 95.31 | AP220: 128.68 | AS220: 45992 | AT220: =AT208*(1+AU220/100) -> 971.25 | AU220: 3.6
A221: 45992 | B221: 0.6249 | C221: 0.5736 | D221: 0.329 | E221: 0.354 | F221: 0.9298 | G221: 0.3095 | H221: 64.6472 | I221: 0.7168 | J221: 3.8614 | K221: 0.5401 | L221: 0.4156 | M221: 1.1475 | N221: 2.9291 | U221: 45962 | V221: =1/B220 -> 1.5815278 | W221: =1/C220 -> 1.7280111 | X221: =1/D220 -> 3.0422878 | Y221: =1/E220 -> 2.813731 | Z221: =1/F220 -> 1.0764263 | AA221: =1/G220 -> 3.2010243 | AB221: =1/H220 -> 0.015676537 | AC221: =1/I220 -> 1.3743815 | ... AH221: =1/N220 -> 0.34139014 | AN221: 46023 | AO221: 94.48 | AP221: 127.21 | AS221: 46023 | AT221: =AT209*(1+AU221/100) -> 988.92 | AU221: 7.2
U222: 45992 | V222: =1/B221 -> 1.600256 | W222: =1/C221 -> 1.7433752 | X222: =1/D221 -> 3.0395137 | Y222: =1/E221 -> 2.8248588 | Z222: =1/F221 -> 1.0755001 | AA222: =1/G221 -> 3.2310178 | AB222: =1/H221 -> 0.015468574 | AC222: =1/I221 -> 1.3950893 | ... AH222: =1/N221 -> 0.3414018 | AN222: 46054 | AO222: 94.65 | AP222: 124.93 | AS222: 46054 | AT222: =AT210*(1+AU222/100) -> 993.4728 | AU222: 8.6
AN223: 46082 | AO223: 95.52 | AP223: 127.79 | AS223: 46082 | AT223: 1004.2 | AU223: 9.8 | AV223: =AT199*(1+AU223/100) -> 936.594
AS224: 46113 | AT224: 998.3

Sheet GDP
B1: 2011/12 | C1: 2012/13 | D1: 2013/14 | E1: 2014/15 | F1: 2015/16 | G1: 2016/17 | H1: 2017/18 | I1: 2018/19 | J1: 2019/20r | K1: 2020/21 | L1: 2021/22 | M1: 2022/23 | N1: 2023/24f | O1: 2024/25f | P1: 2025/26f | Q1: 2026/27f | R1: 2027/28f
A2: GDP at constant prices (2016/17 prices TOPm) | B2: 11/12 | C2: 12/13 | D2: 13/14 | E2: 014/15 | F2: 15/16 | G2: 16/17 | H2: 17/18 | I2: 18/19 | J2: 19/20r | K2: 20/21 | L2: 21/22 | M2: 22/23p | N2: 23/24f | O2: 24/25f | P2: 25/26f | Q2: 26/27f | R2: 27/28f
A3: Primary Sector | B3: 169.69859 | C3: 176.41022 | D3: 180.81959 | E3: 177.66615 | F3: 175.43017 | G3: 171.01764 | H3: 175.43083 | I3: 184.61732 | J3: 190.34761 | K3: 188.66465 | L3: 193.96019 | M3: 225.76517 | N3: 205.3844 | O3: 211.75576 | P3: 218.84543 | Q3: 223.23684 | R3: 227.582
A4: Fishing | B4: 19.882251 | C4: 18.789285 | D4: 19.401575 | E4: 21.515773 | F4: 26.284896 | G4: 19.275379 | H4: 16.902112 | I4: 20.017383 | J4: 24.180957 | K4: 21.479261 | L4: 20.08561 | M4: 22.005838 | N4: 20.323987 | O4: 20.951918 | P4: 21.685634 | Q4: 22.521142 | R4: 23.46703
A5: Agriculture sector | B5: =B3-B4 -> 149.81634 | C5: =C3-C4 -> 157.62094 | D5: =D3-D4 -> 161.41802 | E5: =E3-E4 -> 156.15038 | F5: =F3-F4 -> 149.14528 | G5: =G3-G4 -> 151.74226 | H5: =H3-H4 -> 158.52872 | I5: =I3-I4 -> 164.59993 | ... R5: =R3-R4 -> 204.11497
A7: Industrial Sector | B7: 147.37107 | C7: 126.11531 | D7: 136.14788 | E7: 135.4453 | F7: 152.30931 | G7: 166.96926 | H7: 142.39497 | I7: 148.97079 | J7: 150.07564 | K7: 178.55675 | L7: 156.67568 | M7: 139.22309 | N7: 148.38986 | O7: 156.22828 | P7: 165.6293 | Q7: 176.26813 | R7: 188.4493
A8: Mining and Quarrying | B8: 8.3748478 | C8: 6.2277372 | D8: 6.5018693 | E8: 6.5964839 | F8: 5.8829426 | G8: 6.0752275 | H8: 6.7012654 | I8: 4.07248 | J8: 3.582104 | K8: 3.8959102 | L8: 4.1629465 | M8: 3.1365906 | N8: 3.4661345 | O8: 3.742383 | P8: 4.0685145 | Q8: 4.4472404 | R8: 4.8901624
A9: Manufacturing | B9: 52.579929 | C9: 53.620971 | D9: 54.105167 | E9: 55.742488 | F9: 59.881518 | G9: 60.803691 | H9: 59.722468 | I9: 56.849823 | J9: 58.88822 | K9: 63.242166 | L9: 50.450671 | M9: 43.844426 | N9: 44.219703 | O9: 44.743526 | P9: 45.577923 | Q9: 46.669029 | R9: 48.119752
A10: Electricity, water and waste | B10: 19.182777 | C10: 19.968971 | D10: 20.672116 | E10: 21.032341 | F10: 22.600144 | G10: 24.670702 | H10: 24.959273 | I10: 27.186355 | J10: 29.580339 | K10: 29.81205 | L10: 31.140483 | M10: 32.849121 | N10: 34.470554 | O10: 35.857304 | P10: 37.611802 | Q10: 39.403252 | R10: 41.251593
A11: Construction with PG | B11: 67.23352 | C11: 46.297629 | D11: 54.868731 | E11: 52.07399 | F11: 63.944706 | G11: 75.41964 | H11: 51.011965 | I11: 60.86213 | J11: 58.024978 | K11: 81.606622 | L11: 70.921576 | M11: 59.392947 | N11: 66.233466 | O11: 71.885067 | P11: 78.371059 | Q11: 85.748612 | R11: 94.187788
A13: Services | B13: 462.77236 | C13: 478.94222 | D13: 473.85559 | E13: 479.52048 | F13: 506.13364 | G13: 514.32219 | H13: 531.45008 | I13: 518.2907 | J13: 531.94016 | K13: 504.30046 | L13: 494.74864 | M13: 480.03326 | N13: 502.81265 | O13: 526.9486 | P13: 552.14494 | Q13: 579.36163 | R13: 614.38254
A14: Wholesale and retail | B14: 85.622069 | C14: 85.890326 | D14: 83.220297 | E14: 85.403676 | F14: 98.05526 | G14: 100.57109 | H14: 106.83039 | I14: 107.28075 | J14: 109.9771 | K14: 95.342798 | L14: 94.480372 | M14: 98.027347 | N14: 103.96124 | O14: 113.08472 | P14: 120.44521 | Q14: 128.28478 | R14: 141.766
A15: Transport and stroage | B15: 26.502738 | C15: 28.73089 | D15: 30.113165 | E15: 31.6649 | F15: 31.04777 | G15: 36.307791 | H15: 37.83137 | I15: 35.803383 | J15: 31.581557 | K15: 20.697273 | L15: 27.928567 | M15: 26.693429 | N15: 27.686276 | O15: 28.755321 | P15: 29.971259 | Q15: 31.281275 | R15: 32.736331
A16: Accommodation and food services | B16: 16.397103 | C16: 23.0714 | D16: 22.110733 | E16: 23.722849 | F16: 27.660261 | G16: 30.039452 | H16: 32.26387 | I16: 31.204923 | J16: 22.636194 | K16: 9.6439821 | L16: 9.2481585 | M16: 22.896288 | N16: 28.981748 | O16: 31.509971 | P16: 34.247998 | Q16: 37.513236 | R16: 41.40666
A17: Information and communication | B17: 23.965787 | C17: 24.623403 | D17: 19.694139 | E17: 22.221173 | F17: 22.696005 | G17: 22.541018 | H17: 24.644849 | I17: 24.515023 | J17: 31.979585 | K17: 28.384082 | L17: 33.523449 | M17: 26.693429 | N17: 27.686276 | O17: 28.755321 | P17: 29.971259 | Q17: 31.281275 | R17: 32.736331
A18: Financial and insurance activities | B18: 51.565478 | C18: 49.954849 | D18: 50.521214 | E18: 46.339033 | F18: 50.133918 | G18: 48.000121 | H18: 50.141445 | I18: 50.215538 | J18: 52.714182 | K18: 51.086318 | L18: 45.328479 | M18: 51.338974 | N18: 53.191208 | O18: 55.219836 | P18: 58.348185 | Q18: 61.458669 | R18: 64.749817
A19: Real estate activities | B19: 89.851459 | C19: 91.181959 | D19: 90.65428 | E19: 92.446127 | F19: 92.024895 | G19: 93.156887 | H19: 91.58141 | I19: 82.754757 | J19: 91.229375 | K19: 92.221385 | L19: 69.589777 | M19: 57.635425 | N19: 58.498389 | O19: 59.447125 | P19: 60.371771 | Q19: 61.373632 | R19: 62.489311
... A28: Other service activities | B28: 15.622307 | C28: 16.946642 | D28: 18.004236 | E28: 17.277097 | F28: 17.493388 | G28: 16.892726 | H28: 17.491225 | I28: 16.944047 | J28: 16.867938 | K28: 15.142074 | L28: 13.078175 | M28: 11.599664 | N28: 11.911286 | O28: 12.295455 | P28: 12.764931 | Q28: 13.309675 | R28: 14.184604
A30: GDP at factor cost | B30: =SUM(B3,B7,B13) -> 779.84202 | C30: =SUM(C3,C7,C13) -> 781.46775 | D30: =SUM(D3,D7,D13) -> 790.82306 | E30: =SUM(E3,E7,E13) -> 792.63194 | F30: =SUM(F3,F7,F13) -> 833.87312 | G30: =SUM(G3,G7,G13) -> 852.30909 | H30: =SUM(H3,H7,H13) -> 849.27589 | I30: =SUM(I3,I7,I13) -> 851.8788 | ... R30: =SUM(R3,R7,R13) -> 1030.4138
A31: add taxes (VAT, excise) | B31: 113.40877 | C31: 115.73105 | D31: 123.33268 | E31: 131.70366 | F31: 152.04009 | G31: 165.28878 | H31: 175.26784 | I31: 170.54906 | J31: 168.26164 | K31: 172.83243 | L31: 175.00135 | M31: 196.81656 | N31: 203.5 | O31: 194 | P31: 190 | Q31: 189 | R31: 183
A32: less subsidies on products | B32: 0.39245479 | C32: 0.96864186 | D32: 0.085755992 | E32: 0.085210143 | F32: 0.67427298 | G32: 0.80846416 | H32: 0.76338098 | I32: 0.78145856 | J32: 0.7586428 | K32: 0.71732133 | L32: 0.85543941 | M32: 1.0590751 | N32: 1.1 | O32: 1.1 | P32: 2 | Q32: 2 | R32: 2
A33: GDP at market prices | B33: =SUM(B30:B31)-B32 -> 892.85834 | C33: =SUM(C30:C31)-C32 -> 896.23017 | D33: =SUM(D30:D31)-D32 -> 914.06999 | E33: =SUM(E30:E31)-E32 -> 924.25039 | F33: =SUM(F30:F31)-F32 -> 985.23894 | G33: =SUM(G30:G31)-G32 -> 1016.7894 | H33: =SUM(H30:H31)-H32 -> 1023.7803 | I33: =SUM(I30:I31)-I32 -> 1021.6464 | ... R33: =SUM(R30:R31)-R32 -> 1211.4138
B37: 11/12 | C37: 12/13 | D37: 13/14 | E37: 014/15 | F37: 15/16 | G37: 16/17 | H37: 17/18 | I37: 18/19 | J37: 19/20r | K37: 20/21 | L37: 21/22 | M37: 22/23p | N37: 23/24f | O37: 24/25f | P37: 25/26f | Q37: 26/27f | R37: 27/28f
A38: GDP growth | C38: =(C33/B33-1)*100 -> 0.37764393 | D38: =(D33/C33-1)*100 -> 1.9905402 | E38: =(E33/D33-1)*100 -> 1.1137441 | F38: =(F33/E33-1)*100 -> 6.5987044 | G38: =(G33/F33-1)*100 -> 3.2023165 | H38: =(H33/G33-1)*100 -> 0.68755058 | I38: =(I33/H33-1)*100 -> -0.20843749 | J38: =(J33/I33-1)*100 -> 1.7833949 | ... R38: =(R33/Q33-1)*100 -> 3.9067272
A39: MOF GDP | H39: 0.5 | I39: -0.3 | J39: 1.8 | K39: -0.9 | L39: -2.1 | M39: 2.8 | N39: 1.7 | O39: 2.7 | P39: 3.4 | Q39: 3.7 | R39: 3.9
A40: IMF GDP | L40: -2.3 | M40: 2.1 | N40: 2.7 | O40: 2.3
A41: NRBT | F41: 6.6 | G41: 3.2 | H41: 0.53 | I41: -0.29 | J41: 1.81 | K41: -0.93 | L41: -2.13 | M41: 2.79 | N41: 1.72 | O41: 2.65 | P41: 2.45
A42: Statistics | D42: 1.9905402 | E42: 1.1137441 | F42: 6.5987044 | G42: 3.2023165 | H42: 0.52782727 | I42: -0.28520879 | J42: 1.8061874 | K42: -0.9349263 | L42: -2.1285445 | M42: 2.7901437 | N42: 1.7165411
A44: Primary
A45: Secondary
A46: Tertiary

Sheet Monthly indicators
B1: 37987 | C1: 38018 | D1: 38047 | E1: 38078 | F1: 38108 | G1: 38139 | H1: 38169 | I1: 38200 | J1: 38231 | K1: 38261 | L1: 38292 | M1: 38322 | N1: 38353 | O1: 38384 | P1: 38412 | Q1: 38443 | R1: 38473 | S1: 38504 | T1: 38534 | U1: 38565 | V1: 38596 | W1: 38626 | X1: 38657 | Y1: 38687 | Z1: 38718 | AA1: 38749 | AB1: 38777 | AC1: 38808 | AD1: 38838 | AE1: 38869 | AF1: 38899 | AG1: 38930 | AH1: 38961 | AI1: 38991 | AJ1: 39022 | AK1: 39052 | AL1: 39083 | AM1: 39114 | AN1: 39142 | AO1: 39173 | AP1: 39203 | AQ1: 39234 | AR1: 39264 | AS1: 39295 | AT1: 39326 | AU1: 39356 | AV1: 39387 | AW1: 39417 | AX1: 39448 | AY1: 39479 | AZ1: 39508 | BA1: 39539 | BB1: 39569 | BC1: 39600 | BD1: 39630 | BE1: 39661 | BF1: 39692 | BG1: 39722 | BH1: 39753 | BI1: 39783 | BJ1: 39814 | BK1: 39845 | BL1: 39873 | BM1: 39904 | BN1: 39934 | BO1: 39965 | BP1: 39995 | BQ1: 40026 | BR1: 40057 | BS1: 40087 | BT1: 40118 | BU1: 40148 | BV1: 40179 | BW1: 40210 | BX1: 40238 | BY1: 40269 | BZ1: 40299 | CA1: 40330 | CB1: 40360 | CC1: 40391 | CD1: 40422 | CE1: 40452 | CF1: 40483 | CG1: 40513 | CH1: 40544 | CI1: 40575 | CJ1: 40603 | CK1: 40634 | CL1: 40664 | CM1: 40695 | CN1: 40725 | CO1: 40756 | CP1: 40787 | CQ1: 40817 | CR1: 40848 | CS1: 40878 | CT1: 40909 | CU1: 40940 | CV1: 40969 | CW1: 41000 | CX1: 41030 | CY1: 41061 | CZ1: 41091 | DA1: 41122 | DB1: 41153 | DC1: 41183 | DD1: 41214 | DE1: 41244 | DF1: 41275 | DG1: 41306 | DH1: 41334 | DI1: 41365 | DJ1: 41395 | DK1: 41426 | DL1: 41456 | DM1: 41487 | DN1: 41518 | DO1: 41548 | DP1: 41579 | DQ1: 41609 | DR1: 41640 | DS1: 41671 | DT1: 41699 | DU1: 41730 | DV1: 41760 | DW1: 41791 | DX1: 41821 | DY1: 41852 | DZ1: 41883 | EA1: 41913 | EB1: 41944 | EC1: 41974 | ED1: 42005 | EE1: 42036 | EF1: 42064 | EG1: 42095 | EH1: 42125 | EI1: 42156 | EJ1: 42186 | EK1: 42217 | EL1: 42248 | EM1: 42278 | EN1: 42309 | EO1: 42339 | EP1: 42370 | EQ1: 42401 | ER1: 42430 | ES1: 42461 | ET1: 42491 | EU1: 42522 | EV1: 42552 | EW1: 42583 | EX1: 42614 | EY1: 42644 | EZ1: 42675 | FA1: 42705 | FB1: 42736 | FC1: 42767 | FD1: 42795 | FE1: 42826 | FF1: 42856 | FG1: 42887 | FH1: 42917 | FI1: 42948 | FJ1: 42979 | FK1: 43009 | FL1: 43040 | FM1: 43070 | FN1: 43101 | FO1: 43132 | FP1: 43160 | FQ1: 43191 | FR1: 43221 | FS1: 43252 | FT1: 43282 | FU1: 43313 | FV1: 43344 | FW1: 43374 | FX1: 43405 | FY1: 43435 | FZ1: 43466 | GA1: 43497 | GB1: 43525 | GC1: 43556 | GD1: 43586 | GE1: 43617 | GF1: 43647 | GG1: 43678 | GH1: 43709 | GI1: 43739 | GJ1: 43770 | GK1: 43800 | GL1: 43831 | GM1: 43862 | GN1: 43891 | GO1: 43922 | GP1: 43952 | GQ1: 43983 | GR1: 44013 | GS1: 44044 | GT1: 44075 | GU1: 44105 | GV1: 44136 | GW1: 44166 | GX1: 44197 | GY1: 44228 | GZ1: 44256 | HA1: 44287 | HB1: 44317 | HC1: 44348 | HD1: 44378 | HE1: 44409 | HF1: 44440 | HG1: 44470 | HH1: 44501 | HI1: 44531 | HJ1: 44562 | HK1: 44593 | HL1: 44621 | HM1: 44652 | HN1: 44682 | HO1: 44713 | HP1: 44743 | HQ1: 44774 | HR1: 44805 | HS1: 44835 | HT1: 44866 | HU1: 44896 | HV1: 44927 | HW1: 44958 | HX1: 44986 | HY1: 45017 | HZ1: 45047 | IA1: 45078 | IB1: 45108 | IC1: 45139 | ID1: 45170 | IE1: 45200 | IF1: 45231 | IG1: 45261 | IH1: 45292 | II1: 45323 | IJ1: 45352 | IK1: 45383 | IL1: 45413 | IM1: 45444 | IN1: 45474 | IO1: 45505 | IP1: 45536 | IQ1: 45566 | IR1: 45597 | IS1: 45627 | IT1: 45658 | IU1: 45689 | IV1: 45717 | IW1: 45748 | IX1: 45778 | IY1: 45809 | IZ1: 45839 | JA1: 45870 | JB1: 45901 | JC1: 45931 | JD1: 45962 | JE1: 45992 | JF1: 46023 | JG1: 46054 | JH1: 46082 | JI1: 46113 | JJ1: 46143 | JK1: 46174 | JL1: 46204 | JM1: 46235 | JN1: 46266 | JO1: 46296 | JP1: 46327 | JQ1: 46357
A2: Monetary variables
A3: Foreign Reserves | B3: 54.9 | C3: 54.3 | D3: 56.3 | E3: 60.4 | F3: 63.9 | G3: 89.7 | H3: 89.5 | I3: 78.4 | J3: 79 | K3: 87.1 | L3: 91.5 | M3: 93.4 | N3: 87.1 | O3: 85.4 | P3: 80.9 | Q3: 83.2 | R3: 85.9 | S3: 82.121 | T3: 80.694 | U3: 81.5 | V3: 82.8 | W3: 82.4 | X3: 81.8 | Y3: 85.7 | Z3: 87.2 | AA3: 82.4 | AB3: 77.4 | AC3: 83.9 | AD3: 84.2 | AE3: 83.2 | AF3: 86.3 | AG3: 85.7 | AH3: 85.3 | AI3: 89.2 | AJ3: 84.6 | AK3: 84.2 | AL3: 85.4 | AM3: 84.2 | AN3: 90.4 | AO3: 80.6 | AP3: 84.9 | AQ3: 91.6 | AR3: 90.3 | AS3: 97.7 | AT3: 104.8 | AU3: 109 | AV3: 94.8 | AW3: 114.6 | AX3: 113.1 | AY3: 101.8 | AZ3: 96.3 | BA3: 89.7 | BB3: 89.5 | BC3: 89.1 | BD3: 86.2 | BE3: 91.3 | BF3: 128.5 | BG3: 121.6 | BH3: 122.7 | BI3: 123.9 | BJ3: 130.4 | BK3: 131.1 | BL3: 130.6 | BM3: 132.6 | BN3: 132.1 | BO3: 136.3 | BP3: 139.4 | BQ3: 159.2 | BR3: 163.3 | BS3: 160.7 | BT3: 159.9 | BU3: 160.4 | BV3: 160.8 | BW3: 153.5 | BX3: 155.5 | BY3: 161.4 | BZ3: 166.7 | CA3: 170.5 | CB3: 178 | CC3: 174.1 | CD3: 172.7 | CE3: 176.5 | CF3: 168 | CG3: 177.5 | CH3: 165.2 | CI3: 158.8 | CJ3: 157.1 | CK3: 160.1 | CL3: 170.2 | CM3: 203.8 | CN3: 197.6 | CO3: 212.4 | CP3: 208.1 | CQ3: 213.9 | CR3: 212.9 | CS3: 226 | CT3: 229.5 | CU3: 230.6 | CV3: 239.2 | CW3: 240.3 | CX3: 245 | CY3: 246.1 | CZ3: 251.1 | DA3: 252.7 | DB3: 247.9 | DC3: 246.2 | DD3: 253.7 | DE3: 257.3 | DF3: 260.3 | DG3: 258 | DH3: 244.8 | DI3: 258.4 | DJ3: 259.2 | DK3: 263.3 | DL3: 252.69805 | DM3: 256.2 | DN3: 254.2 | DO3: 260.6 | DP3: 265.4 | DQ3: 271.8 | DR3: 276.7 | DS3: 281.1 | DT3: 274.8 | DU3: 267.9 | DV3: 266.8 | DW3: 274.4 | DX3: 280.4 | DY3: 283.9 | DZ3: 270.9 | EA3: 271.5 | EB3: 267.9 | EC3: 293.6 | ED3: 287.2 | EE3: 281.3 | EF3: 270.2 | EG3: 272.1 | EH3: 281.1 | EI3: 289.7 | EJ3: 302.6 | EK3: 310.9 | EL3: 311.7 | EM3: 315.8 | EN3: 319 | EO3: 327.8 | EP3: 326.3 | EQ3: 328.5 | ER3: 317.3 | ES3: 322.9 | ET3: 330.7 | EU3: 354.9 | EV3: 367.4 | EW3: 366.3 | EX3: 363.7 | EY3: 367 | EZ3: 360.9 | FA3: 378.8 | FB3: 380.8 | FC3: 377.7 | FD3: 366 | FE3: 371.7 | FF3: 392.3 | FG3: 407.9 | FH3: 408.9 | FI3: 405 | FJ3: 403 | FK3: 413.6 | FL3: 424.8 | FM3: 422.6 | FN3: 424.1 | FO3: 448 | FP3: 447.7 | FQ3: 445.9 | FR3: 441.9 | FS3: 468.7 | FT3: 476.5 | FU3: 475 | FV3: 452.2 | FW3: 457.3 | FX3: 468.7 | FY3: 478.5 | FZ3: 478.9 | GA3: 473.5 | GB3: 465 | GC3: 464.2 | GD3: 468.3 | GE3: 484.3 | GF3: 492.9 | GG3: 491.8 | GH3: 490.8 | GI3: 489.3 | GJ3: 489.5 | GK3: 487.4 | GL3: 482.9 | GM3: 479.8 | GN3: 457.5 | GO3: 475.1 | GP3: 489.6 | GQ3: 543.8 | GR3: 555.9 | GS3: 556.1 | GT3: 576.5 | GU3: 581.6 | GV3: 590.2 | GW3: 675.6 | GX3: 705.3 | GY3: 692.4 | GZ3: 685.7 | HA3: 679.7 | HB3: 689.5 | HC3: 715.2 | HD3: 704.8 | HE3: 751.7 | HF3: 757 | HG3: 757 | HH3: 783.9 | HI3: 817.5 | HJ3: 856.1 | HK3: 867.3 | HL3: 861.4 | HM3: 884 | HN3: 880.4 | HO3: 871.2 | HP3: 884.8 | HQ3: 871 | HR3: 895.3 | HS3: 877 | HT3: 866.2 | HU3: 868.9 | HV3: 911.1 | HW3: 911.2 | HX3: 883.7 | HY3: 860.5 | HZ3: 864.8 | IA3: 921.4 | IB3: 945.2 | IC3: 920 | ID3: 886.1 | IE3: 891.2 | IF3: 892 | IG3: 901.7 | IH3: 894.7 | II3: 891.4 | IJ3: 868.7 | IK3: 904.8 | IL3: 893 | IM3: 924.3 | IN3: 909.1 | IO3: 905.5 | IP3: 887.4 | IQ3: 898.2 | IR3: 892.2 | IS3: 889.1 | IT3: 878 | IU3: 865.4 | IV3: 842.6 | IW3: 867.6 | IX3: 871.5 | IY3: 925.1 | IZ3: 921 | JA3: 921.1 | JB3: 897.2 | JC3: 939.5 | JD3: 940.3 | JE3: 961,7 | JF3: 958.6 | JG3: 959.6 | JH3: 924.5 | JI3: 938.9 | JJ3: 970.9
A4: Import cover | B4: 3.3 | C4: 3.4 | D4: 3.4 | E4: 3.6 | F4: 3.9 | G4: 5.4 | H4: 5.5 | I4: 4.8 | J4: 4.8 | K4: 5.4 | L4: 5.3 | M4: 5.4 | N4: 5 | O4: 4.8 | P4: 4.5 | Q4: 4.7 | R4: 4.7 | S4: 4.4 | T4: 4.3 | U4: 4.3 | V4: 4.3 | W4: 4.2 | X4: 4.2 | Y4: 4.4 | Z4: 4.5 | AA4: 4.3 | AB4: 3.9 | AC4: 4.2 | AD4: 4.3 | AE4: 4.3 | AF4: 4.4 | AG4: 4.3 | AH4: 4.2 | AI4: 4.4 | AJ4: 4.3 | AK4: 4.3 | AL4: 4.3 | AM4: 4.2 | AN4: 4.5 | AO4: 4 | AP4: 4.1 | AQ4: 4.4 | AR4: 4.2 | AS4: 4.4 | AT4: 4.8 | AU4: 4.8 | AV4: 4 | AW4: 4.9 | AX4: 4.8 | AY4: 4.6 | AZ4: 4.1 | BA4: 3.6 | BB4: 3.6 | BC4: 3.5 | BD4: 3.3 | BE4: 3.6 | BF4: 5 | BG4: 4.8 | BH4: 4.9 | BI4: 4.6 | BJ4: 4.8 | BK4: 4.9 | BL4: 4.9 | BM4: 5.1 | BN4: 5 | BO4: 5.3 | BP4: 5.6 | BQ4: 6.5 | BR4: 6.7 | BS4: 6.7 | BT4: 6.7 | BU4: 6.8 | BV4: 6.6 | BW4: 6.2 | BX4: 6.2 | BY4: 6.3 | BZ4: 6.6 | CA4: 7.1 | CB4: 7.4144921 | CC4: 7.1968389 | CD4: 7.0980639 | CE4: 7.2389723 | CF4: 6.8364944 | CG4: 7.0582376 | CH4: 6.5 | CI4: 6.2 | CJ4: 6.0948848 | CK4: 6.3 | CL4: 6.5009958 | CM4: 7.6934505 | CN4: 7.5069763 | CO4: 8.0659795 | CP4: 7.8 | CQ4: 8 | CR4: 7.8 | CS4: 8.2 | CT4: 8.2 | CU4: 8.2 | CV4: 8.6 | CW4: 8.4916067 | CX4: 8.4708495 | CY4: 8.5494487 | CZ4: 8.6405513 | DA4: 8.5746951 | DB4: 8.511346 | DC4: 8.5 | DD4: 8.8 | DE4: 9 | DF4: 9.1 | DG4: 8.9 | DH4: 8.5 | DI4: 9 | DJ4: 9.1 | DK4: 9.1 | DL4: 8.8 | DM4: 9 | DN4: 8.9 | DO4: 8.9 | DP4: 9 | DQ4: 9.3 | DR4: 9.4 | DS4: 9.4 | DT4: 9.1 | DU4: 8.9 | DV4: 8.9 | DW4: 9.1 | DX4: 9.1 | DY4: 9.1 | DZ4: 8.4 | EA4: 8.2 | EB4: 8 | EC4: 8.7 | ED4: 8.5 | EE4: 8.3 | EF4: 7.9 | EG4: 7.9 | EH4: 8 | EI4: 8.1 | EJ4: 8.5 | EK4: 8.6 | EL4: 8.6 | EM4: 8.8 | EN4: 8.9 | EO4: 8.9 | EP4: 8.8 | EQ4: 7.1 | ER4: 6.7 | ES4: 6.7 | ET4: 6.8 | EU4: 7.2 | EV4: 7.4 | EW4: 7.2 | EX4: 6.9 | EY4: 7 | EZ4: 6.7 | FA4: 7.1 | FB4: 7.1 | FC4: 6.9 | FD4: 6.7 | FE4: 6.7 | FF4: 7.1 | FG4: 7.5 | FH4: 7.5 | FI4: 7.4 | FJ4: 7.3 | FK4: 7.5 | FL4: 7.7 | FM4: 7.6 | FN4: 7.4 | FO4: 7.9 | FP4: 7.8 | FQ4: 8 | FR4: 7.5 | FS4: 8 | FT4: 8.2 | FU4: 8.1 | FV4: 7.8 | FW4: 7.7 | FX4: 8.2 | FY4: 8.4 | FZ4: 8.1 | GA4: 7.9 | GB4: 7.8 | GC4: 7.5 | GD4: 7.5 | GE4: 7.9 | GF4: 8 | GG4: 8.1 | GH4: 8 | GI4: 7.5 | GJ4: 7.4 | GK4: 7.4 | GL4: 7.4 | GM4: 7.4 | GN4: 7.1 | GO4: 7.7 | GP4: 8.2 | GQ4: 9.2 | GR4: 9.5 | GS4: 9.6 | GT4: 10 | GU4: 9.7 | GV4: 10.9 | GW4: 12.5 | GX4: 12 | GY4: 11.7 | GZ4: 12.2 | HA4: 11.9 | HB4: 14.7 | HC4: 11.8 | HD4: 11.5 | HE4: 12.1 | HF4: 12.4 | HG4: 12.8 | HH4: 13 | HI4: 13.4 | HJ4: 13.9 | HK4: 14.4 | HL4: 14.5 | HM4: 14.9 | HN4: 14.7 | HO4: 14.4 | HP4: 14.4 | HQ4: 14 | HR4: 13.7 | HS4: 13.9 | HT4: 12.6 | HU4: 13.4 | HV4: 12.8 | HW4: 12.6 | HX4: 12 | HY4: 11.4 | HZ4: 11.5 | IA4: 12 | IB4: 12.3 | IC4: 11.9 | ID4: 11.4 | IE4: 11.4 | IF4: 11.4 | IG4: 11.6 | IH4: 11.5 | II4: 11.5 | IJ4: 11.1 | IK4: 11.6 | IL4: 11.5 | IM4: 11.9 | IN4: 11.5 | IO4: 10.4 | IP4: 10.2 | IQ4: 10.3 | IR4: 10.3 | IS4: 10.2 | IT4: 10.1 | IU4: 9.9 | IV4: 9.7 | IW4: 10 | IX4: 10 | IY4: 10.6 | IZ4: 10.7 | JA4: 10.7 | JB4: 10.4 | JC4: 10.9 | JD4: 10.9 | JE4: 11.2 | JF4: 11.1 | JG4: 11.2 | JH4: 10.8 | JI4: 10.9 | JJ4: 11.3
A6: CPI | FB6: 90 | FC6: 93.3 | FD6: 93.7 | FE6: 94.2 | FF6: 94.5 | FG6: 95.2 | FH6: 95 | FI6: 94.8 | FJ6: 94.7 | FK6: 94.8 | FL6: 94.2 | FM6: 94.9 | FN6: 95.7 | FO6: 96.7 | FP6: 98.4 | FQ6: 98.6 | FR6: 98 | FS6: 98 | FT6: 100.5 | FU6: 100.6 | FV6: 100 | FW6: 100.7 | FX6: 100.3 | FY6: 99.5 | FZ6: 99.7 | GA6: 99.9 | GB6: 100.4 | GC6: 98.8 | GD6: 99.6 | GE6: 99.8 | GF6: 100 | GG6: 100.5 | GH6: 100.4 | GI6: 100.9 | GJ6: 100.4 | GK6: 100.7 | GL6: 100.3 | GM6: 100.6 | GN6: 100.8 | GO6: 100 | GP6: 99.6 | GQ6: 98.4 | GR6: 98.9 | GS6: 98.8 | GT6: 99.4 | GU6: 99.3 | GV6: 99.7 | GW6: 98.023641 | GX6: 98.023641 | GY6: 97.207036 | GZ6: 98.893564 | HA6: 99.1441 | HB6: 98.12135 | HC6: 99.612839 | HD6: 99.88718 | HE6: 98.955141 | HF6: 100.00152 | HG6: 101.09825 | HH6: 100.49676 | HI6: 103.55503 | HJ6: 104.22408 | HK6: 105.12191 | HL6: 104.84071 | HM6: 107.97665 | HN6: 107.79655 | HO6: 109.47137 | HP6: 110.60802 | HQ6: 112.12377 | HR6: 114.03745 | HS6: 117.85216 | HT6: 114.68193 | HU6: 116.60489 | HV6: 116.74122 | HW6: 116.69726 | HX6: 116.37802 | HY6: 118.19505 | HZ6: 121.13635 | IA6: 124.46553 | IB6: 123.71518 | IC6: 124.41829 | ID6: 124.91507 | IE6: 125.03037 | IF6: 123.21942 | IG6: 125.29115 | IH6: 126.5903 | II6: 124.79981 | IJ6: 125.18665 | IK6: 126.72398 | IL6: 129.18648 | IM6: 132.41933 | IN6: 128.84887 | IO6: 127.01434 | IP6: 126.22508 | IQ6: 125.46827 | IR6: 129.3 | IS6: 132.85546 | IT6: 133.44605 | IU6: 129.8002 | IV6: 129.05528 | IW6: 129.4115 | IX6: 130.34551 | IY6: 133.79223 | IZ6: 131.17618 | JA6: 130.15206 | JB6: 130.56967 | JC6: 130.5 | JD6: 133.8 | JE6: 136.9 | JF6: 136.1 | JG6: 133 | JH6: 134.9 | JI6: 136.5 | JJ6: 140.7 | JK6: 143.3
A7: Imported (Composition) | JJ7: 68.7 | JK7: =JK6*JL7 -> 69.5 | JL7: 0.48499651
A8: Local (Composition) | JJ8: =JJ6-JJ7 -> 72 | JK8: =JK6-JK7 -> 73.8 | JL8: =1-JL7 -> 0.51500349
A10: Annual Inflation rate | FD10: =IH6/FB6-1 -> 0.4065589 | FN10: =(FN6/FB6-1)*10^2 -> 6.3333333 | FO10: =(FO6/FC6-1)*10^2 -> 3.6441586 | FP10: =(FP6/FD6-1)*10^2 -> 5.0160085 | FQ10: =(FQ6/FE6-1)*10^2 -> 4.670913 | FR10: =(FR6/FF6-1)*10^2 -> 3.7037037 | FS10: =(FS6/FG6-1)*10^2 -> 2.9411765 | FT10: =(FT6/FH6-1)*10^2 -> 5.7894737 | FU10: =(FU6/FI6-1)*10^2 -> 6.1181435 | ... JK10: =(JK6/IY6-1)*10^2 -> 7.1063671
A11: Monthly inflation rate | GX11: =(GX6/GW6-1)*100 -> 0 | GY11: =(GY6/GX6-1)*100 -> -0.83306988 | GZ11: =(GZ6/GY6-1)*100 -> 1.7349859 | HA11: =(HA6/GZ6-1)*100 -> 0.2533394 | HB11: =(HB6/HA6-1)*100 -> -1.0315792 | HC11: =(HC6/HB6-1)*100 -> 1.5200451 | HD11: =(HD6/HC6-1)*100 -> 0.27540721 | HE11: =(HE6/HD6-1)*100 -> -0.93309156 | ... JK11: =(JK6/JJ6-1)*100 -> 1.8479033
A13: Imported inflation (yoy) | GX13: =(GX17/GL17-1)*100 -> -4.7480504 | GY13: =(GY17/GM17-1)*100 -> -3.8701279 | GZ13: =(GZ17/GN17-1)*100 -> -2.685668 | HA13: =(HA17/GO17-1)*100 -> -2.0353906 | HB13: =(HB17/GP17-1)*100 -> -0.67590702 | HC13: =(HC17/GQ17-1)*100 -> 0.63804243 | HD13: =(HD17/GR17-1)*100 -> -1.0955541 | HE13: =(HE17/GS17-1)*100 -> -1.2792243 | ... JK13: =(JK17/IY17-1)*100 -> 13.128696
A14: Local Inflation (yoy) | GX14: =(GX18/GL18-1)*100 -> 0.45012126 | GY14: =(GY18/GM18-1)*100 -> -2.9549981 | GZ14: =(GZ18/GN18-1)*100 -> -0.95903174 | HA14: =(HA18/GO18-1)*100 -> 0.5624969 | HB14: =(HB18/GP18-1)*100 -> -2.4494703 | HC14: =(HC18/GQ18-1)*100 -> 1.8540762 | HD14: =(HD18/GR18-1)*100 -> 3.5098799 | HE14: =(HE18/GS18-1)*100 -> 2.0347597 | ... JK14: =(JK18/IY18-1)*100 -> 1.9408769
A16: Component
A17: Imported | FB17: 88.8 | FC17: 90.4 | FD17: 90.9 | FE17: 90.8 | FF17: 91 | FG17: 91.6 | FH17: 92.9 | FI17: 94.1 | FJ17: 94.9 | FK17: 95.7 | FL17: 95.5 | FM17: 95.9 | FN17: 97 | FO17: 97.7 | FP17: 97.6 | FQ17: 97.4 | FR17: 97.8 | FS17: 98.2 | FT17: 99.2 | FU17: 99.3 | FV17: 100 | FW17: 100.3 | FX17: 99.9 | FY17: 98.7 | FZ17: 97.3 | GA17: 96.8 | GB17: 97.1 | GC17: 97.7 | GD17: 99.5 | GE17: 100.1 | GF17: 100.3 | GG17: 101.1 | GH17: 101.6 | GI17: 101.8 | GJ17: 101 | GK17: 100.7 | GL17: 100.7 | GM17: 100.8 | GN17: 100.9 | GO17: 100.9 | GP17: 99.7 | GQ17: 98.5 | GR17: 100.2 | GS17: 100.9 | GT17: 101.1 | GU17: 101.3 | GV17: 101.3 | GW17: 95.918713 | GX17: 95.918713 | GY17: 96.898911 | GZ17: 98.190161 | HA17: 98.846291 | HB17: 99.026121 | HC17: 99.128472 | HD17: 99.102255 | HE17: 99.609263 | HF17: 100 | HG17: 100.60325 | HH17: 101.75136 | HI17: 102.81623 | HJ17: 102.72151 | HK17: 103.50314 | HL17: 104.7645 | HM17: 107.819 | HN17: 108.79657 | HO17: 109.89632 | HP17: 111.86065 | HQ17: 111.37176 | HR17: 110.54645 | HS17: 109.86353 | HT17: 109.85783 | HU17: 109.75757 | HV17: 109.33471 | HW17: 110.6543 | HX17: 111.08537 | HY17: 111.37781 | HZ17: 111.77172 | IA17: 113.967 | IB17: 113.82744 | IC17: 114.23363 | ID17: 115.72693 | IE17: 115.70226 | IF17: 115.43426 | IG17: 114.63036 | IH17: 114.0552 | II17: 114.57721 | IJ17: 114.89513 | IK17: 115.11907 | IL17: 115.35839 | IM17: 116.02094 | IN17: 115.25291 | IO17: 115.74924 | IP17: 116.41254 | IQ17: 115.62305 | IR17: 116.67692 | IS17: 120.65525 | IT17: 118.01683 | IU17: 118.25464 | IV17: 118.41371 | IW17: 118.75277 | IX17: 119.49674 | IY17: 119.50991 | IZ17: 119.66233 | JA17: 120.30422 | JB17: 120.46506 | JC17: 120.3 | JD17: 126 | JE17: 127.3 | JF17: 125.1 | JG17: 123.8 | JH17: 126.6 | JI17: 129.3 | JJ17: 133.5 | JK17: 135.2 | JM17: 133.5
A18: Local | FB18: 91.7 | FC18: 97.5 | FD18: 97.6 | FE18: 98.9 | FF18: 99.3 | FG18: 100.2 | FH18: 97.8 | FI18: 95.9 | FJ18: 94.6 | FK18: 93.6 | FL18: 92.6 | FM18: 93.6 | FN18: 94.2 | FO18: 95.6 | FP18: 99.3 | FQ18: 100 | FR18: 98.2 | FS18: 97.8 | FT18: 102.1 | FU18: 102.2 | FV18: 100 | FW18: 101.1 | FX18: 100.8 | FY18: 100.3 | FZ18: 102.8 | GA18: 103.7 | GB18: 104.3 | GC18: 99.9 | GD18: 99.7 | GE18: 99.4 | GF18: 99.6 | GG18: 99.6 | GH18: 98.9 | GI18: 99.8 | GJ18: 99.7 | GK18: 100.4 | GL18: 99.8 | GM18: 100.5 | GN18: 100.6 | GO18: 98.9 | GP18: 99.6 | GQ18: 98.3 | GR18: 97.3 | GS18: 96.3 | GT18: 97.4 | GU18: 96.9 | GV18: 97.6 | GW18: 100.24922 | GX18: 100.24922 | GY18: 97.530227 | GZ18: 99.635214 | HA18: 99.456309 | HB18: 97.160328 | HC18: 100.12256 | HD18: 100.71511 | HE18: 98.259474 | HF18: 100 | HG18: 101.61917 | HH18: 99.165278 | HI18: 104.33402 | HJ18: 105.8117 | HK18: 106.83254 | HL18: 104.91812 | HM18: 108.14019 | HN18: 106.73438 | HO18: 109.01801 | HP18: 109.27831 | HQ18: 112.91648 | HR18: 117.73008 | HS18: 126.30664 | HT18: 119.78599 | HU18: 123.85103 | HV18: 124.57941 | HW18: 123.09176 | HX18: 121.97811 | HY18: 125.40928 | HZ18: 131.04761 | IA18: 135.57724 | IB18: 134.18021 | IC18: 135.19768 | ID18: 134.63934 | IE18: 134.90286 | IF18: 131.45831 | IG18: 136.57463 | IH18: 139.85822 | II18: 135.61935 | IJ18: 136.07916 | IK18: 139.00703 | IL18: 136.07916 | IM18: 149.77742 | IN18: 143.23993 | IO18: 138.93759 | IP18: 136.61043 | IQ18: 135.88823 | IR18: 140.56464 | IS18: 145.76859 | IT18: 149.77798 | IU18: 142.03504 | IV18: 140.31828 | IW18: 140.69267 | IX18: 141.82785 | IY18: 148.90984 | IZ18: 143.36267 | JA18: 140.57467 | JB18: 141.26412 | JC18: 141.2 | JD18: 142.4 | JE18: 147.1 | JF18: 146.7 | JG18: 142.7 | JH18: 143.8 | JI18: 144.2 | JJ18: 148.2 | JK18: 151.8 | JO18: 2021
A20: PACCOICOP groups (proportion of all items)
A21: Food and non-alcoholic beverages | FJ21: 94.3 | FK21: 93.9 | FL21: 91.8 | FM21: 92.7 | FN21: 94.1 | FO21: 96.3 | FP21: 100.4 | FQ21: 100.8 | FR21: 98.7 | FS21: 97.6 | FT21: 101.2 | FU21: 100.8 | FV21: 100 | FW21: 101.2 | FX21: 99.8 | FY21: 99 | FZ21: 100.1 | GA21: 101.1 | GB21: 102.2 | GC21: 98.1 | GD21: 99.5 | GE21: 99.6 | GF21: 100.8 | GG21: 102.2 | GH21: 102 | GI21: 102.8 | GJ21: 100.7 | GK21: 101.4 | GL21: 100.5 | GM21: 101.6 | GN21: 102.3 | GO21: 102.8 | GP21: 104 | GQ21: 102.6 | GR21: 103.5 | GS21: 102.1 | GT21: 102.9 | GU21: 102.8 | GV21: 103.2 | GW21: 105.2 | GX21: 42.260865 | GY21: 41.12072 | GZ21: 42.48065 | HA21: 42.451648 | HB21: 41.159528 | HC21: 42.812331 | HD21: 42.756259 | HE21: 41.708855 | HF21: 42.608204 | HG21: 43.637565 | HH21: 42.455233 | HI21: 45.162595 | HJ21: 45.704499 | HK21: 46.298752 | HL21: 45.322759 | HM21: 47.335216 | HN21: 46.409909 | HO21: 47.447362 | HP21: 46.586861 | HQ21: 48.423364 | HR21: 49.308024 | HS21: 52.521679 | HT21: 49.09536 | HU21: 51.001231 | HV21: 52.177176 | HW21: 52.184484 | HX21: 51.840365 | HY21: 52.813362 | HZ21: 53.957741 | IA21: 56.467319 | IB21: 56.043983 | IC21: 56.476214 | ID21: 56.196019 | IE21: 55.060667 | IF21: 53.4413 | IG21: 55.90449 | IH21: 57.168305 | II21: 55.383394 | IJ21: 55.529741 | IK21: 57.670927 | IL21: 59.949124 | IM21: 63.125227 | IN21: 59.858991 | IO21: 58.109036 | IP21: 57.138607 | IQ21: 56.393092 | IR21: 59.621101 | IS21: 61.181108 | IT21: 61.351122 | IU21: 57.206953 | IV21: 56.15904 | IW21: 55.853162 | IX21: 56.495352 | IY21: 59.833206 | IZ21: 57.834474 | JA21: 56.692948 | JB21: 57.228651 | JC21: 56.7 | JD21: 57.4 | JE21: 60 | JF21: 59 | JG21: 56.5 | JH21: 56.9 | JI21: 57 | JJ21: 57.7 | JK21: 59.3 | JM21: =JK21/(JO21/10^2) -> 139.20188 | JO21: 42.6
A22: Alcohol beverages, tobacco and kava | FJ22: 85.1 | FK22: 85.6 | FL22: 85.8 | FM22: 86.2 | FN22: 85.8 | FO22: 85.8 | FP22: 86.2 | FQ22: 87.1 | FR22: 88.4 | FS22: 91 | FT22: 96.7 | FU22: 99.3 | FV22: 100 | FW22: 99.6 | FX22: 99.8 | FY22: 99.6 | FZ22: 100.1 | GA22: 100.2 | GB22: 99.7 | GC22: 98.1 | GD22: 97.7 | GE22: 97.2 | GF22: 97.5 | GG22: 97.3 | GH22: 96.8 | GI22: 96.5 | GJ22: 96.6 | GK22: 95.1 | GL22: 95.5 | GM22: 94.7 | GN22: 94.7 | GO22: 93.9 | GP22: 95.5 | GQ22: 99.4 | GR22: 100.3 | GS22: 100.3 | GT22: 100.4 | GU22: 100 | GV22: 100.1 | GW22: 100.3 | GX22: 5.6918377 | GY22: 5.6901778 | GZ22: 5.6928128 | HA22: 5.6918253 | HB22: 5.6933655 | HC22: 5.5391992 | HD22: 5.5409965 | HE22: 5.5428057 | HF22: 5.5985062 | HG22: 5.4460122 | HH22: 5.443924 | HI22: 5.5286314 | HJ22: 5.4653847 | HK22: 5.4729647 | HL22: 5.5617397 | HM22: 5.5633521 | HN22: 5.6256677 | HO22: 5.6724782 | HP22: 5.734255 | HQ22: 5.731175 | HR22: 5.7279617 | HS22: 5.7203538 | HT22: 5.7324998 | HU22: 5.7430099 | HV22: 5.7309259 | HW22: 5.6444392 | HX22: 5.7029064 | HY22: 5.7068371 | HZ22: 5.6960558 | IA22: 5.7035632 | IB22: 5.7304807 | IC22: 5.7374316 | ID22: 5.7380066 | IE22: 6.0269462 | IF22: 5.9681569 | IG22: 5.9615295 | IH22: 5.9682426 | II22: 5.964834 | IJ22: 5.9626691 | IK22: 5.949148 | IL22: 5.9616725 | IM22: 6.0453964 | IN22: 6.8731412 | IO22: 6.9846158 | IP22: 6.9814198 | IQ22: 7.2495198 | IR22: 7.2312376 | IS22: 7.2372125 | IT22: 7.4035607 | IU22: 7.85072 | IV22: 7.8293764 | IW22: 7.907721 | IX22: 7.9915733 | IY22: 8.2342695 | IZ22: 8.3326599 | JA22: 8.3409728 | JB22: 8.3385842 | JC22: 8.5 | JD22: 8.6 | JE22: 8.8 | JF22: 8.8 | JG22: 8.9 | JH22: 8.9 | JI22: 9 | JJ22: 9 | JK22: 9 | JM22: =JK22/(JO22/10^2) -> 160.71429 | JO22: 5.6
A23: Clothing and footwear | FJ23: 95 | FK23: 96 | FL23: 96.1 | FM23: 96.1 | FN23: 98.2 | FO23: 98.2 | FP23: 98.2 | FQ23: 98.2 | FR23: 98.2 | FS23: 97.8 | FT23: 99.2 | FU23: 99.6 | FV23: 100 | FW23: 100.1 | FX23: 100.3 | FY23: 100.3 | FZ23: 102.6 | GA23: 102.9 | GB23: 101.5 | GC23: 101.5 | GD23: 101.5 | GE23: 101.5 | GF23: 102.1 | GG23: 102.1 | GH23: 103.8 | GI23: 103.8 | GJ23: 103.9 | GK23: 104.3 | GL23: 105.5 | GM23: 106.1 | GN23: 106.1 | GO23: 106.5 | GP23: 108.8 | GQ23: 109.1 | GR23: 109.1 | GS23: 110.5 | GT23: 110.5 | GU23: 112.6 | GV23: 112.6 | GW23: 112.6 | GX23: 2.841289 | GY23: 2.8345268 | GZ23: 2.8363482 | HA23: 2.8363482 | HB23: 2.8389322 | HC23: 2.8389322 | HD23: 2.8389322 | HE23: 2.8394721 | HF23: 2.8449004 | HG23: 2.8449004 | HH23: 2.8449004 | HI23: 2.8449004 | HJ23: 2.853566 | HK23: 2.853566 | HL23: 2.853566 | HM23: 2.853566 | HN23: 2.9064457 | HO23: 2.9120447 | HP23: 2.9169392 | HQ23: 2.9161474 | HR23: 2.9161474 | HS23: 2.8878012 | HT23: 2.8878012 | HU23: 2.8862627 | HV23: 2.8862627 | HW23: 2.8817061 | HX23: 2.8192465 | HY23: 2.8694283 | HZ23: 2.9778651 | IA23: 3.1189158 | IB23: 3.1224656 | IC23: 3.1157212 | ID23: 3.1273942 | IE23: 3.0770363 | IF23: 3.0770363 | IG23: 3.0770363 | IH23: 3.0259074 | II23: 3.0328323 | IJ23: 3.0417509 | IK23: 3.0417509 | IL23: 3.0417509 | IM23: 3.00061 | IN23: 3.1471886 | IO23: 3.1601812 | IP23: 3.1680191 | IQ23: 3.2630289 | IR23: 3.265285 | IS23: 3.3490705 | IT23: 3.4705854 | IU23: 3.455129 | IV23: 3.4183149 | IW23: 3.4221561 | IX23: 3.6215561 | IY23: 3.6734886 | IZ23: 3.6802206 | JA23: 3.6859602 | JB23: 3.6790747 | JC23: 3.7 | JD23: 3.7 | JE23: 3.7 | JF23: 3.7 | JG23: 3.7 | JH23: 3.7 | JI23: 3.7 | JJ23: 3.7 | JK23: 2.8 | JM23: =JK23/(JO23/10^2) -> 100 | JO23: 2.8
A24: Housing, water, electricity and gas | FJ24: 98.1 | FK24: 97.6 | FL24: 97.7 | FM24: 98.3 | FN24: 98.6 | FO24: 99.9 | FP24: 99.9 | FQ24: 99.8 | FR24: 99.4 | FS24: 99.4 | FT24: 99.4 | FU24: 99.5 | FV24: 100 | FW24: 100.5 | FX24: 100.2 | FY24: 100.5 | FZ24: 101 | GA24: 101.5 | GB24: 100.9 | GC24: 98.9 | GD24: 98.9 | GE24: 100.2 | GF24: 100.3 | GG24: 100.3 | GH24: 99 | GI24: 100 | GJ24: 100.4 | GK24: 100.8 | GL24: 100.5 | GM24: 100.6 | GN24: 102.6 | GO24: 98.9 | GP24: 99.2 | GQ24: 96.9 | GR24: 89.7 | GS24: 89.2 | GT24: 89.2 | GU24: 89.1 | GV24: 90.6 | GW24: 93.8 | GX24: 5.7983162 | GY24: 5.8517267 | GZ24: 5.9634479 | HA24: 5.9856916 | HB24: 6.1685255 | HC24: 6.1787632 | HD24: 6.5743021 | HE24: 6.6417412 | HF24: 6.6275093 | HG24: 6.6931389 | HH24: 7.0419333 | HI24: 7.0127598 | HJ24: 7.2770332 | HK24: 7.4241708 | HL24: 7.5592827 | HM24: 7.9110405 | HN24: 8.1830022 | HO24: 8.3611228 | HP24: 9.4284189 | HQ24: 9.157157 | HR24: 9.1099395 | HS24: 9.3185951 | HT24: 9.3450114 | HU24: 9.266582 | HV24: 8.3001372 | HW24: 8.3211567 | HX24: 8.2526946 | HY24: 7.6914538 | HZ24: 7.7122163 | IA24: 7.6023917 | IB24: 7.4008001 | IC24: 7.5418449 | ID24: 7.797685 | IE24: 8.402139 | IF24: 8.2825805 | IG24: 8.1586326 | IH24: 8.3922841 | II24: 8.4301944 | IJ24: 8.4648011 | IK24: 7.741501 | IL24: 7.741501 | IM24: 7.6879338 | IN24: 7.9334737 | IO24: 7.9474304 | IP24: 7.9144016 | IQ24: 7.7317224 | IR24: 7.5841352 | IS24: 7.5533323 | IT24: 7.4973035 | IU24: 7.5148195 | IV24: 7.5638017 | IW24: 7.952124 | IX24: 7.9312841 | IY24: 7.846248 | IZ24: 7.2040623 | JA24: 7.2215792 | JB24: 7.2497337 | JC24: 7.6 | JD24: 7.6 | JE24: 7.6 | JF24: 7.5 | JG24: 7.5 | JH24: 7.4 | JI24: 7.9 | JJ24: 9.9 | JK24: 10.3 | JM24: =JK24/(JO24/10^2) -> 156.06061 | JO24: 6.6
A25: Furnishing, household equipment and hosehold maintenance | FJ25: 99.7 | FK25: 98 | FL25: 99.2 | FM25: 99 | FN25: 99 | FO25: 99.1 | FP25: 99.5 | FQ25: 99.1 | FR25: 99.1 | FS25: 98.9 | FT25: 99.3 | FU25: 99.5 | FV25: 100 | FW25: 99.7 | FX25: 99.7 | FY25: 99.5 | FZ25: 99.8 | GA25: 100.1 | GB25: 100.5 | GC25: 100.6 | GD25: 100.7 | GE25: 100.8 | GF25: 101.7 | GG25: 101.7 | GH25: 102 | GI25: 102 | GJ25: 102.1 | GK25: 100.5 | GL25: 100.5 | GM25: 100.2 | GN25: 100.3 | GO25: 102.2 | GP25: 103.3 | GQ25: 103.3 | GR25: 102.5 | GS25: 102.5 | GT25: 102.7 | GU25: 103.4 | GV25: 104.1 | GW25: 104.4 | GX25: 3.1275623 | GY25: 3.1275623 | GZ25: 3.1275623 | HA25: 3.1275623 | HB25: 3.1284488 | HC25: 3.1284488 | HD25: 3.1543384 | HE25: 3.160267 | HF25: 3.1671874 | HG25: 3.1671874 | HH25: 3.1671874 | HI25: 3.202811 | HJ25: 3.2204244 | HK25: 3.2301986 | HL25: 3.231427 | HM25: 3.3193132 | HN25: 3.3239982 | HO25: 3.3239982 | HP25: 3.3084324 | HQ25: 3.3036061 | HR25: 3.3036061 | HS25: 3.3036061 | HT25: 3.3171271 | HU25: 3.329075 | HV25: 3.3232195 | HW25: 3.3475704 | HX25: 3.3687442 | HY25: 3.3678663 | HZ25: 3.3684822 | IA25: 3.4551445 | IB25: 3.4519756 | IC25: 3.5181295 | ID25: 3.593063 | IE25: 3.5875302 | IF25: 3.5843442 | IG25: 3.58494 | IH25: 3.6173872 | II25: 3.6158102 | IJ25: 3.5934891 | IK25: 3.5914033 | IL25: 3.6263285 | IM25: 3.6855669 | IN25: 3.7329362 | IO25: 3.7322236 | IP25: 3.7794175 | IQ25: 3.9233831 | IR25: 4.0405841 | IS25: 4.0876048 | IT25: 4.0814972 | IU25: 4.0831056 | IV25: 4.1224019 | IW25: 4.1595872 | IX25: 4.2103995 | IY25: 4.2364268 | IZ25: 4.2141864 | JA25: 4.2002369 | JB25: 4.1741671 | JC25: 4.2 | JD25: 4.3 | JE25: 4.3 | JF25: 4.3 | JG25: 4.2 | JH25: 4.2 | JI25: 4.2 | JJ25: 4.2 | JK25: 4.2 | JM25: =JK25/(JO25/10^2) -> 131.25 | JO25: 3.2
A26: Health | FJ26: 99.3 | FK26: 99.3 | FL26: 99.3 | FM26: 99.3 | FN26: 101.7 | FO26: 101.7 | FP26: 101.7 | FQ26: 101.7 | FR26: 101.7 | FS26: 101.7 | FT26: 101.7 | FU26: 100 | FV26: 100 | FW26: 100 | FX26: 100 | FY26: 100 | FZ26: 100 | GA26: 100 | GB26: 100 | GC26: 100 | GD26: 100 | GE26: 100 | GF26: 100 | GG26: 100 | GH26: 100 | GI26: 100 | GJ26: 100 | GK26: 100 | GL26: 100 | GM26: 100 | GN26: 100 | GO26: 100 | GP26: 100 | GQ26: 100 | GR26: 100 | GS26: 100 | GT26: 100 | GU26: 100 | GV26: 100 | GW26: 100 | GX26: 0.16781668 | GY26: 0.16781668 | GZ26: 0.16781668 | HA26: 0.16781668 | HB26: 0.16781668 | HC26: 0.16781668 | HD26: 0.16781668 | HE26: 0.16781668 | HF26: 0.16781668 | HG26: 0.16781668 | HH26: 0.16781668 | HI26: 0.16781668 | HJ26: 0.16781668 | HK26: 0.16781668 | HL26: 0.16781668 | HM26: 0.16781668 | HN26: 0.16781668 | HO26: 0.16781668 | HP26: 0.16781668 | HQ26: 0.19474225 | HR26: 0.21744155 | HS26: 0.21744155 | HT26: 0.21744155 | HU26: 0.21744155 | HV26: 0.21744155 | HW26: 0.21744155 | HX26: 0.21744155 | HY26: 0.21744155 | HZ26: 0.21744155 | IA26: 0.21744155 | IB26: 0.21744155 | IC26: 0.21744155 | ID26: 0.21744155 | IE26: 0.21744155 | IF26: 0.21744155 | IG26: 0.21744155 | IH26: 0.21744155 | II26: 0.21744155 | IJ26: 0.21744155 | IK26: 0.21744155 | IL26: 0.21744155 | IM26: 0.21744155 | IN26: 0.21744155 | IO26: 0.21493152 | IP26: 0.21493152 | IQ26: 0.21493152 | IR26: 0.21493152 | IS26: 0.21493152 | IT26: 0.21493152 | IU26: 0.21493152 | IV26: 0.21597602 | IW26: 0.21597602 | IX26: 0.21597602 | IY26: 0.21597602 | IZ26: 0.21597602 | JA26: 0.21597602 | JB26: 0.21493152 | JC26: 0.2 | JD26: 0.2 | JE26: 0.2 | JF26: 0.2 | JG26: 0.2 | JH26: 0.2 | JI26: 0.2 | JJ26: 0.2 | JK26: 0.2 | JM26: =JK26/(JO26/10^2) -> 100 | JO26: 0.2
A27: Transportation | FJ27: 90.6 | FK27: 92 | FL27: 93.1 | FM27: 94.6 | FN27: 96 | FO27: 96.1 | FP27: 96.3 | FQ27: 96.1 | FR27: 97 | FS27: 98.1 | FT27: 100.4 | FU27: 99.8 | FV27: 100 | FW27: 101.1 | FX27: 102.2 | FY27: 98.5 | FZ27: 94.4 | GA27: 92.4 | GB27: 93.9 | GC27: 96.3 | GD27: 98.5 | GE27: 99 | GF27: 97.1 | GG27: 96.4 | GH27: 97.4 | GI27: 98.3 | GJ27: 99.4 | GK27: 99.7 | GL27: 99.7 | GM27: 99.6 | GN27: 97.4 | GO27: 94.7 | GP27: 87.6 | GQ27: 82.3 | GR27: 87.2 | GS27: 90.2 | GT27: 91.8 | GU27: 91.6 | GV27: 91.3 | GW27: 91.5 | GX27: 12.41416 | GY27: 12.646262 | GZ27: 12.85735 | HA27: 13.044616 | HB27: 13.128057 | HC27: 13.119463 | HD27: 13.033305 | HE27: 13.078559 | HF27: 13.17626 | HG27: 13.226074 | HH27: 13.464128 | HI27: 13.644573 | HJ27: 13.52471 | HK27: 13.602301 | HL27: 14.063187 | HM27: 14.662248 | HN27: 14.965151 | HO27: 15.365363 | HP27: 15.545854 | HQ27: 15.41069 | HR27: 15.361056 | HS27: 15.183885 | HT27: 15.365104 | HU27: 15.410216 | HV27: 15.273609 | HW27: 15.182273 | HX27: 15.251332 | HY27: 15.204879 | HZ27: 15.166296 | IA27: 15.862663 | IB27: 15.69421 | IC27: 15.752046 | ID27: 16.10904 | IE27: 16.525223 | IF27: 16.508204 | IG27: 16.239301 | IH27: 16.008128 | II27: 15.948879 | IJ27: 16.156572 | IK27: 16.291309 | IL27: 16.352698 | IM27: 16.282375 | IN27: 16.081741 | IO27: 16.165965 | IP27: 16.167832 | IQ27: 15.67882 | IR27: 15.670064 | IS27: 17.561518 | IT27: 15.887161 | IU27: 15.933104 | IV27: 16.265499 | IW27: 16.411582 | IX27: 16.341515 | IY27: 16.171763 | IZ27: 15.973533 | JA27: 16.046001 | JB27: 15.817046 | JC27: 15.8 | JD27: 17.9 | JE27: 18.2 | JF27: 16.8 | JG27: 16.5 | JH27: 18 | JI27: 18.9 | JJ27: 20.2 | JK27: 20.6 | JM27: =JK27/(JO27/10^2) -> 156.06061 | JO27: 13.2
A28: Communications | FJ28: 111.6 | FK28: 111.6 | FL28: 111.6 | FM28: 111.6 | FN28: 111.6 | FO28: 111.6 | FP28: 109.3 | FQ28: 109.3 | FR28: 109.3 | FS28: 109.3 | FT28: 109.3 | FU28: 109.3 | FV28: 100 | FW28: 100 | FX28: 100 | FY28: 100 | FZ28: 100 | GA28: 100 | GB28: 100 | GC28: 100 | GD28: 100 | GE28: 100 | GF28: 100 | GG28: 100 | GH28: 100 | GI28: 100 | GJ28: 101.6 | GK28: 101.6 | GL28: 101.6 | GM28: 101.6 | GN28: 101.6 | GO28: 99.9 | GP28: 99.9 | GQ28: 99.9 | GR28: 99.9 | GS28: 99.9 | GT28: 99.9 | GU28: 99.9 | GV28: 99.9 | GW28: 99.9 | GX28: 3.6946544 | GY28: 3.6997401 | GZ28: 3.6949957 | HA28: 3.6931064 | HB28: 3.6916981 | HC28: 3.6765056 | HD28: 3.6664698 | HE28: 3.659714 | HF28: 3.6552832 | HG28: 3.6599417 | HH28: 3.656026 | HI28: 3.651455 | HJ28: 3.654308 | HK28: 3.6527552 | HL28: 3.6615468 | HM28: 3.6645991 | HN28: 3.6529318 | HO28: 3.6533524 | HP28: 3.6462075 | HQ28: 3.6509208 | HR28: 3.6476797 | HS28: 4.2496462 | HT28: 4.2565556 | HU28: 4.2569751 | HV28: 4.2674799 | HW28: 4.2676402 | HX28: 4.2553998 | HY28: 4.2561623 | HZ28: 4.2532776 | IA28: 4.2554758 | IB28: 4.2547104 | IC28: 4.2434413 | ID28: 4.2497211 | IE28: 4.2457143 | IF28: 4.2526781 | IG28: 4.2607953 | IH28: 4.2594928 | II28: 4.2530833 | IJ28: 4.2545137 | IK28: 4.2555667 | IL28: 4.2555667 | IM28: 4.251768 | IN28: 4.251768 | IO28: 4.237208 | IP28: 4.237208 | IQ28: 4.2709286 | IR28: 4.2709286 | IS28: 4.2447525 | IT28: 4.2420342 | IU28: 4.2420342 | IV28: 4.2270764 | IW28: 4.2270764 | IX28: 4.2419868 | IY28: 4.2419868 | IZ28: 4.2419868 | JA28: 4.2419868 | JB28: 4.2419868 | JC28: 4.2 | JD28: 4.2 | JE28: 4.2 | JF28: 4.2 | JG28: 4.2 | JH28: 4.2 | JI28: 4.2 | JJ28: 4.2 | JK28: 4.2 | JM28: =JK28/(JO28/10^2) -> 113.51351 | JO28: 3.7
A29: Recreation and culture | FJ29: 99.9 | FK29: 99.9 | FL29: 99.9 | FM29: 99.9 | FN29: 100 | FO29: 100 | FP29: 100 | FQ29: 100 | FR29: 100 | FS29: 100 | FT29: 100 | FU29: 100 | FV29: 100 | FW29: 100 | FX29: 100 | FY29: 100 | FZ29: 103.6 | GA29: 103.6 | GB29: 103.6 | GC29: 103.6 | GD29: 103.6 | GE29: 103.6 | GF29: 103.6 | GG29: 103.6 | GH29: 103.6 | GI29: 103.6 | GJ29: 103.6 | GK29: 103.6 | GL29: 103.6 | GM29: 103.6 | GN29: 103.6 | GO29: 103.6 | GP29: 103.6 | GQ29: 103.6 | GR29: 103.6 | GS29: 103.6 | GT29: 103.6 | GU29: 103.6 | GV29: 103.6 | GW29: 103.6 | GX29: 0.64037914 | GY29: 0.64651885 | GZ29: 0.64709269 | HA29: 0.64709269 | HB29: 0.64658535 | HC29: 0.64698949 | HD29: 0.64854284 | HE29: 0.64969391 | HF29: 0.64963755 | HG29: 0.64963755 | HH29: 0.64963755 | HI29: 0.66379559 | HJ29: 0.66422639 | HK29: 0.66422639 | HL29: 0.66422639 | HM29: 0.67767266 | HN29: 0.67761722 | HO29: 0.67986613 | HP29: 0.68391648 | HQ29: 0.68485115 | HR29: 0.68559754 | HS29: 0.68559754 | HT29: 0.68495723 | HU29: 0.68365712 | HV29: 0.6860363 | HW29: 0.68686828 | HX29: 0.68686828 | HY29: 0.68729324 | HZ29: 0.72637162 | IA29: 0.72550996 | IB29: 0.72397927 | IC29: 0.72682262 | ID29: 0.72682262 | IE29: 0.72758636 | IF29: 0.72758636 | IG29: 0.72689776 | IH29: 0.72492395 | II29: 0.72492395 | IJ29: 0.73429921 | IK29: 0.73553735 | IL29: 0.73596493 | IM29: 0.73708552 | IN29: 0.73708552 | IO29: 0.73708552 | IP29: 0.73708552 | IQ29: 0.78062159 | IR29: 0.78062159 | IS29: 0.78062159 | IT29: 0.79224163 | IU29: 0.79224163 | IV29: 0.80080157 | IW29: 0.78884683 | IX29: 0.87757909 | IY29: 0.88875337 | IZ29: 0.85334877 | JA29: 0.82196845 | JB29: 0.80216057 | JC29: 0.8 | JD29: 0.8 | JE29: 0.8 | JF29: 0.8 | JG29: 0.8 | JH29: 0.8 | JI29: 0.8 | JJ29: 0.8 | JK29: 0.8 | JM29: =JK29/(JO29/10^2) -> 133.33333 | JO29: 0.6
A30: Education | FJ30: 100 | FK30: 100 | FL30: 100 | FM30: 100 | FN30: 100 | FO30: 100 | FP30: 100 | FQ30: 100 | FR30: 100 | FS30: 100 | FT30: 100 | FU30: 100 | FV30: 100 | FW30: 100 | FX30: 100 | FY30: 100 | FZ30: 104.2 | GA30: 104.2 | GB30: 104.2 | GC30: 104.2 | GD30: 104.2 | GE30: 104.2 | GF30: 104.2 | GG30: 104.2 | GH30: 104.2 | GI30: 104.2 | GJ30: 104.2 | GK30: 104.2 | GL30: 104.2 | GM30: 104.8 | GN30: 104.8 | GO30: 104.8 | GP30: 104.8 | GQ30: 104.8 | GR30: 104.8 | GS30: 104.8 | GT30: 104.8 | GU30: 104.8 | GV30: 104.8 | GW30: 104.8 | GX30: 1.2060818 | GY30: 1.2060818 | GZ30: 1.2060818 | HA30: 1.2060818 | HB30: 1.2060818 | HC30: 1.2060818 | HD30: 1.2060818 | HE30: 1.2060818 | HF30: 1.2060818 | HG30: 1.2060818 | HH30: 1.2060818 | HI30: 1.2060818 | HJ30: 1.2060818 | HK30: 1.2060818 | HL30: 1.2060818 | HM30: 1.2060818 | HN30: 1.2060818 | HO30: 1.2060818 | HP30: 1.2060818 | HQ30: 1.2060818 | HR30: 1.2060818 | HS30: 1.2060818 | HT30: 1.2060818 | HU30: 1.2060818 | HV30: 1.2880204 | HW30: 1.2880204 | HX30: 1.2880204 | HY30: 1.2880204 | HZ30: 1.2880204 | IA30: 1.2880204 | IB30: 1.2880204 | IC30: 1.2880204 | ID30: 1.2880204 | IE30: 1.2880204 | IF30: 1.2880204 | IG30: 1.2880204 | IH30: 1.251472 | II30: 1.251472 | IJ30: 1.251472 | IK30: 1.251472 | IL30: 1.251472 | IM30: 1.251472 | IN30: 1.251472 | IO30: 1.251472 | IP30: 1.251472 | IQ30: 1.251472 | IR30: 1.251472 | IS30: 1.251472 | IT30: 1.2753298 | IU30: 1.2753298 | IV30: 1.279025 | IW30: 1.279025 | IX30: 1.279025 | IY30: 1.279025 | IZ30: 1.279025 | JA30: 1.279025 | JB30: 1.279025 | JC30: 1.3 | JD30: 1.3 | JE30: 1.3 | JF30: 1.3 | JG30: 1.3 | JH30: 1.3 | JI30: 1.3 | JJ30: 1.3 | JK30: 1.3 | JM30: =JK30/(JO30/10^2) -> 108.33333 | JO30: 1.2
A31: Restaurants and hotels | FJ31: 100 | FK31: 100 | FL31: 100 | FM31: 100 | FN31: 100 | FO31: 100 | FP31: 100 | FQ31: 100 | FR31: 100 | FS31: 100 | FT31: 100 | FU31: 100 | FV31: 100 | FW31: 101.3 | FX31: 101.3 | FY31: 101.3 | FZ31: 108.2 | GA31: 108.2 | GB31: 108.2 | GC31: 108.2 | GD31: 108.2 | GE31: 108.2 | GF31: 108.2 | GG31: 108.2 | GH31: 108.2 | GI31: 108.2 | GJ31: 108.2 | GK31: 108.2 | GL31: 108.2 | GM31: 108.2 | GN31: 108.2 | GO31: 108.2 | GP31: 108.2 | GQ31: 108.2 | GR31: 108.2 | GS31: 108.2 | GT31: 108.2 | GU31: 108.2 | GV31: 108.2 | GW31: 108.2 | GX31: 14.950022 | GY31: 14.950022 | GZ31: 14.950022 | HA31: 14.950022 | HB31: 14.950022 | HC31: 14.950022 | HD31: 14.950022 | HE31: 14.950022 | HF31: 14.950022 | HG31: 14.950022 | HH31: 14.950022 | HI31: 14.950022 | HJ31: 14.950022 | HK31: 14.950022 | HL31: 14.950022 | HM31: 14.950022 | HN31: 14.950022 | HO31: 14.950022 | HP31: 15.632335 | HQ31: 15.632335 | HR31: 16.693882 | HS31: 16.693882 | HT31: 16.693882 | HU31: 16.693882 | HV31: 16.693882 | HW31: 16.693882 | HX31: 16.693882 | HY31: 18.104044 | HZ31: 19.787937 | IA31: 19.787937 | IB31: 19.787937 | IC31: 19.787937 | ID31: 19.787937 | IE31: 19.787937 | IF31: 19.787937 | IG31: 19.787937 | IH31: 19.787937 | II31: 19.787937 | IJ31: 19.787937 | IK31: 19.787937 | IL31: 19.787937 | IM31: 19.787937 | IN31: 18.462851 | IO31: 18.091868 | IP31: 18.091868 | IQ31: 18.191732 | IR31: 17.576438 | IS31: 18.564763 | IT31: 20.377015 | IU31: 20.377015 | IV31: 20.624544 | IW31: 20.624544 | IX31: 20.624544 | IY31: 20.624544 | IZ31: 20.624544 | JA31: 20.624544 | JB31: 20.444659 | JC31: 20.4 | JD31: 20.4 | JE31: 20.4 | JF31: 22.1 | JG31: 22.1 | JH31: 22.1 | JI31: 22.1 | JJ31: 22.1 | JK31: 22.4 | JM31: =JK31/(JO31/10^2) -> 149.33333 | JO31: 15
A32: Misc. goods and services | FJ32: 99.4 | FK32: 99.6 | FL32: 99.8 | FM32: 99.8 | FN32: 100 | FO32: 99.7 | FP32: 100.1 | FQ32: 100.1 | FR32: 99.5 | FS32: 100.3 | FT32: 99.8 | FU32: 99.6 | FV32: 100 | FW32: 99.7 | FX32: 99.7 | FY32: 101 | FZ32: 101 | GA32: 101 | GB32: 99.8 | GC32: 99.8 | GD32: 98.8 | GE32: 98.8 | GF32: 98.6 | GG32: 98.9 | GH32: 98.9 | GI32: 99.3 | GJ32: 99.7 | GK32: 99.8 | GL32: 99.9 | GM32: 100 | GN32: 100.8 | GO32: 99.7 | GP32: 100.2 | GQ32: 100.3 | GR32: 100.6 | GS32: 100.8 | GT32: 100.8 | GU32: 100.8 | GV32: 100.9 | GW32: 101.4 | GX32: 5.2306569 | GY32: 5.2658809 | GZ32: 5.2693845 | HA32: 5.342289 | HB32: 5.342289 | HC32: 5.3482851 | HD32: 5.3501127 | HE32: 5.3501127 | HF32: 5.3501127 | HG32: 5.4498709 | HH32: 5.4498709 | HI32: 5.519591 | HJ32: 5.5360065 | HK32: 5.5990548 | HL32: 5.5990548 | HM32: 5.6657258 | HN32: 5.7279096 | HO32: 5.7318602 | HP32: 5.7509071 | HQ32: 5.8127044 | HR32: 5.8600353 | HS32: 5.863586 | HT32: 5.8801092 | HU32: 5.9104802 | HV32: 5.8970326 | HW32: 5.9817812 | HX32: 6.001122 | HY32: 5.9882591 | HZ32: 5.9846433 | IA32: 5.9811478 | IB32: 5.9991719 | IC32: 6.0132388 | ID32: 6.0839138 | IE32: 6.0841326 | IF32: 6.0841326 | IG32: 6.0841326 | IH32: 6.1687794 | II32: 6.1890047 | IJ32: 6.1919673 | IK32: 6.1899855 | IL32: 6.2650271 | IM32: 6.3465153 | IN32: 6.3007812 | IO32: 6.3823242 | IP32: 6.5428205 | IQ32: 6.5190151 | IR32: 6.7749414 | IS32: 6.8290688 | IT32: 6.839362 | IU32: 6.8548138 | IV32: 6.8368988 | IW32: 6.8571841 | IX32: 6.9383913 | IY32: 6.9713016 | IZ32: 7.1123511 | JA32: 7.136954 | JB32: 7.0996541 | JC32: 7.1 | JD32: 7.5 | JE32: 7.4 | JF32: 7.3 | JG32: 7.1 | JH32: 7.1 | JI32: 7.2 | JJ32: 7.2 | JK32: 7.2 | JM32: =JK32/(JO32/10^2) -> 133.33333 | JO32: 5.4
A35: Broad Money | BX35: 284.7 | BY35: 285.1 | BZ35: 289.1 | CA35: 291.5 | CB35: 291.2 | CC35: 288.9 | CD35: 286.8 | CE35: 302.5 | CF35: 297.3 | CG35: 305.5 | CH35: 297.5 | CI35: 287.9 | CJ35: 285.1 | CK35: 296 | CL35: 291.6 | CM35: 299.2 | CN35: 306.4 | CO35: 294.2 | CP35: 289.6 | CQ35: 296.2 | CR35: 295.15042 | CS35: 299.88445 | CT35: 289.8532 | CU35: 277.76306 | CV35: 283.5471 | CW35: 288.69166 | CX35: 294.25329 | CY35: 293.22898 | CZ35: 304.73567 | DA35: 308.23201 | DB35: 306.76097 | DC35: 302.26363 | DD35: 307.37866 | DE35: 317.12564 | DF35: 309.20876 | DG35: 306.8843 | DH35: 307.30253 | DI35: 309.29315 | DJ35: 310.87033 | DK35: 314.52342 | DL35: 315.41413 | DM35: 318.69258 | DN35: 315.6 | DO35: 319.3 | DP35: 323.2 | DQ35: 329.7 | DR35: 325.7 | DS35: 327.8 | DT35: 328.6 | DU35: 330.6 | DV35: 329.5 | DW35: 340 | DX35: 333.5 | DY35: 334.6 | DZ35: 341.4 | EA35: 339.3 | EB35: 342 | EC35: 351.9 | ED35: 348.5 | EE35: 349.3 | EF35: 342.9 | EG35: 351.2 | EH35: 355.5 | EI35: 348 | EJ35: 357.2 | EK35: 366.3 | EL35: 363.6 | EM35: 369.2 | EN35: 371.5 | EO35: 450.2 | EP35: 447.5 | EQ35: 456.5 | ER35: 451.6 | ES35: 453.7 | ET35: 460.5 | EU35: 470.5 | EV35: 478 | EW35: 491 | EX35: 496.2 | EY35: 501.2 | EZ35: 493.6 | FA35: 512.2 | FB35: 512 | FC35: 510.2 | FD35: 503.6 | FE35: 509.9 | FF35: 517.6 | FG35: 534.9 | FH35: 533.2 | FI35: 552.3 | FJ35: 549.7 | FK35: 553.6 | FL35: 553.3 | FM35: 560.6 | FN35: 552.5 | FO35: 558.2 | FP35: 558.7 | FQ35: 547.1 | FR35: 561.5 | FS35: 575.4 | FT35: 506.5 | FU35: 606 | FV35: 592.5 | FW35: 595.8 | FX35: 593.2 | FY35: 605.3 | FZ35: 598.3 | GA35: 589 | GB35: 583.5 | GC35: 585.9 | GD35: 584.8 | GE35: 600.1 | GF35: 598.1 | GG35: 608.6 | GH35: 594.5 | GI35: 592.5 | GJ35: 605.6 | GK35: 602.2 | GL35: 592.5 | GM35: 590.2 | GN35: 596.4 | GO35: 581.6 | GP35: 592.2 | GQ35: 607.1 | GR35: 616.9 | GS35: 624.7 | GT35: 640.8 | GU35: 655.2 | GV35: 681.4 | GW35: 707.5 | GX35: 706.9 | GY35: 703.4 | GZ35: 707.6 | HA35: 712.3 | HB35: 724.7 | HC35: 765.2 | HD35: 769.7 | HE35: 779.2 | HF35: 783.8 | HG35: 789.7 | HH35: 807.2 | HI35: 821.5 | HJ35: 832.8 | HK35: 851.2 | HL35: 844.9 | HM35: 844.3 | HN35: 842.8 | HO35: 846.7 | HP35: 846.2 | HQ35: 843.5 | HR35: 843.4 | HS35: 843.4 | HT35: 844 | HU35: 851.2 | HV35: 844 | HW35: 845.9 | HX35: 843.6 | HY35: 836.8 | HZ35: 822.3 | IA35: 841.8 | IB35: 856.8 | IC35: 854.7 | ID35: 847.8 | IE35: 844.9 | IF35: 855.7 | IG35: 868.1 | IH35: 846.2 | II35: 849.5 | IJ35: 853 | IK35: 849.5 | IL35: 889.2 | IM35: 906.1 | IN35: 885.6 | IO35: 893.2 | IP35: 901.6 | IQ35: 906.3 | IR35: 910.7 | IS35: 937.5 | IT35: 922.5 | IU35: 914.8 | IV35: 914.1 | IW35: 914.6 | IX35: 931.9 | IY35: 945.8 | IZ35: 950.3 | JA35: 955.3 | JB35: 964.2 | JC35: 999 | JD35: 942.1257 | JE35: 971.25 | JF35: 988.92 | JG35: 993.4728 | JH35: 1004.2 | JI35: 998.3
A39: Remittances | ED39: 14.54 | EE39: 28.52 | EF39: 45.08 | EG39: 61.34 | EH39: 81.19 | EI39: 100.4 | EJ39: 122.24 | EK39: 144.96 | EL39: 164.34 | EM39: 186.31 | EN39: 204.986 | EO39: 232.076 | EP39: 234.836 | EQ39: 239.406 | ER39: 242.256 | ES39: 246.376 | ET39: 251.246 | EU39: 256.176 | EV39: 256.472 | EW39: 258.542 | EX39: 262.092 | EY39: 263.322 | EZ39: 266.906 | FA39: 269.826 | FB39: 273.752 | FC39: 273.837 | FD39: 276.847 | FE39: 277.987 | FF39: 281.767 | FG39: 284.167 | FH39: 287.491 | FI39: 291.117 | FJ39: 294.177 | FK39: 299.177 | FL39: 303.597 | FM39: 307.147 | FN39: 311.021 | FO39: 316.566 | FP39: 322.196 | FQ39: 326.876 | FR39: 333.636 | FS39: 337.896 | FT39: 342.536 | FU39: 345.72 | FV39: 347.43 | FW39: 347.43 | FX39: 351.35 | FY39: 350.39 | FZ39: 350.19 | GA39: 350.21 | GB39: 349.56 | GC39: 350.86 | GD39: 350.4 | GE39: 346.6 | GF39: 348.7 | GG39: 349.9 | GH39: 348.7 | GI39: 349.9 | GJ39: 348.4 | GK39: 348.2 | GL39: 350.4 | GM39: 351 | GN39: 349.7 | GO39: 345.7 | GP39: 345.9 | GQ39: 350.8 | GR39: 356.1 | GS39: 359.7 | GT39: 369.2 | GU39: 378.5 | GV39: 386.5 | GW39: 397.9 | GX39: 403.2 | GY39: 411.2 | GZ39: 428.6 | HA39: 447.6 | HB39: 455.3 | HC39: 461.1 | HD39: 465.5 | HE39: 472.33 | HF39: 480.43 | HG39: 485.63 | HH39: 490.04 | HI39: 498.19 | HJ39: 494.85 | HK39: 489.73 | HL39: 478.62 | HM39: 474.86 | HN39: 471.85 | HO39: 472.34 | HP39: 472.5 | HQ39: 476.85 | HR39: 476.41 | HS39: 473.6 | HT39: 474.58 | HU39: 475.18 | HV39: 484.1 | HW39: 494.12 | HX39: 506.22 | HY39: 507.31 | HZ39: 517.99 | IA39: 528.93 | IB39: 537.04 | IC39: 537.68 | ID39: 537.12 | IE39: 539.03 | IF39: 539.74 | IG39: 538.09 | IH39: 536.46729 | II39: 533.62339 | IJ39: 529.40825 | IK39: 529.65436 | IL39: 523.65573 | IM39: 521.13351 | IN39: 520.59376 | IO39: 521.44853 | IP39: 520.58334 | IQ39: 524.22649 | IR39: 524.91648 | IS39: 524.76839 | IT39: 527.80401 | IU39: 530.61651 | IV39: 533.68455 | IW39: 536.65648 | IX39: 541.74616 | IY39: 540.65693 | IZ39: 543.79448 | JA39: 546.9236
EN41: 42309 | EO41: 42339 | EP41: 42370 | EQ41: 42401 | ER41: 42430 | ES41: 42461 | ET41: 42491 | EU41: 42522 | EV41: 42552 | EW41: 42583 | EX41: 42614 | EY41: 42644 | EZ41: 42675 | FA41: 42705 | FB41: 42736 | FC41: 42767 | FD41: 42795 | FE41: 42826 | FF41: 42856 | FG41: 42887 | FH41: 42917 | FI41: 42948 | FJ41: 42979 | FK41: 43009 | FL41: 43040 | FM41: 43070 | FN41: 43101 | FO41: 43132 | FP41: 43160 | FQ41: 43191 | FR41: 43221 | FS41: 43252 | FT41: 43282 | FU41: 43313 | FV41: 43344 | FW41: 43374 | FX41: 43405 | FY41: 43435 | FZ41: 43466 | GA41: 43497 | GB41: 43525 | GC41: 43556 | GD41: 43586 | GE41: 43617 | GF41: 43647 | GG41: 43678 | GH41: 43709 | GI41: 43739 | GJ41: 43770 | GK41: 43800 | GL41: 43831 | GM41: 43862 | GN41: 43891 | GO41: 43922 | GP41: 43952 | GQ41: 43983 | GR41: 44013 | GS41: 44044 | GT41: 44075 | GU41: 44105 | GV41: 44136 | GW41: 44166 | GX41: 44197 | GY41: 44228 | GZ41: 44256 | HA41: 44287 | HB41: 44317 | HC41: 44348 | HD41: 44378 | HE41: 44409 | HF41: 44440 | HG41: 44470 | HH41: 44501 | HI41: 44531 | HJ41: 44562 | HK41: 44593 | HL41: 44621 | HM41: 44652 | HN41: 44682 | HO41: 44713 | HP41: 44743 | HQ41: 44774 | HR41: 44805 | HS41: 44835 | HT41: 44866 | HU41: 44896 | HV41: 44927 | HW41: 44958 | HX41: 44986 | HY41: 45017 | HZ41: 45047 | IA41: 45078 | IB41: 45108 | IC41: 45139 | ID41: 45170 | IE41: 45200 | IF41: 45231 | IG41: 45261 | IH41: 45292 | II41: 45323 | IJ41: 45352 | IK41: 45383 | IL41: 45413 | IM41: 45444 | IN41: 45474 | IO41: 45505 | IP41: 45536 | IQ41: 45566 | IR41: 45597 | IS41: 45627 | IT41: 45658 | IU41: 45689 | IV41: 45717 | IW41: 45748 | IX41: 45778 | IY41: 45809 | IZ41: 45839 | JA41: 45870 | JB41: 45901 | JC41: 45931 | JD41: 45962
EM42: Foreign Reserves | EN42: 319 | EO42: 327.8 | EP42: 326.3 | EQ42: 328.5 | ER42: 317.3 | ES42: 322.9 | ET42: 330.7 | EU42: 354.9 | EV42: 367.4 | EW42: 366.3 | EX42: 363.7 | EY42: 367 | EZ42: 360.9 | FA42: 378.8 | FB42: 380.8 | FC42: 377.7 | FD42: 366 | FE42: 371.7 | FF42: 392.3 | FG42: 407.9 | FH42: 408.9 | FI42: 405 | FJ42: 403 | FK42: 413.6 | FL42: 424.8 | FM42: 422.6 | FN42: 424.1 | FO42: 448 | FP42: 447.7 | FQ42: 445.9 | FR42: 441.9 | FS42: 468.7 | FT42: 476.5 | FU42: 475 | FV42: 452.2 | FW42: 457.3 | FX42: 468.7 | FY42: 478.5 | FZ42: 478.9 | GA42: 473.5 | GB42: 465 | GC42: 464.2 | GD42: 468.3 | GE42: 484.3 | GF42: 492.9 | GG42: 491.8 | GH42: 490.8 | GI42: 489.3 | GJ42: 489.5 | GK42: 487.4 | GL42: 482.9 | GM42: 479.8 | GN42: 457.5 | GO42: 475.1 | GP42: 489.6 | GQ42: 543.8 | GR42: 555.9 | GS42: 556.1 | GT42: 576.5 | GU42: 581.6 | GV42: 590.2 | GW42: 675.6 | GX42: 705.3 | GY42: 692.4 | GZ42: 685.7 | HA42: 679.7 | HB42: 689.5 | HC42: 715.2 | HD42: 704.8 | HE42: 751.7 | HF42: 757 | HG42: 757 | HH42: 783.9 | HI42: 817.5 | HJ42: 856.1 | HK42: 867.3 | HL42: 861.4 | HM42: 884 | HN42: 880.4 | HO42: 871.2 | HP42: 884.8 | HQ42: 871 | HR42: 895.3 | HS42: 877 | HT42: 866.2 | HU42: 868.9 | HV42: 911.1 | HW42: 911.2 | HX42: 883.7 | HY42: 860.5 | HZ42: 864.8 | IA42: 921.4 | IB42: 945.2 | IC42: 920 | ID42: 886.1 | IE42: 891.2 | IF42: 892 | IG42: 901.7 | IH42: 894.7 | II42: 891.4 | IJ42: 868.7 | IK42: 904.8 | IL42: 893 | IM42: 924.3 | IN42: 909.1 | IO42: 905.5 | IP42: 887.4 | IQ42: 898.2 | IR42: 892.2 | IS42: 889.1 | IT42: 878 | IU42: 865.4 | IV42: 842.6 | IW42: 867.6 | IX42: 871.5 | IY42: 925.1 | IZ42: 921 | JA42: 921.1 | JB42: 897.2 | JC42: 939.5 | JD42: 940.3
EM43: Import Cover | EN43: 8.9 | EO43: 8.9 | EP43: 8.8 | EQ43: 7.1 | ER43: 6.7 | ES43: 6.7 | ET43: 6.8 | EU43: 7.2 | EV43: 7.4 | EW43: 7.2 | EX43: 6.9 | EY43: 7 | EZ43: 6.7 | FA43: 7.1 | FB43: 7.1 | FC43: 6.9 | FD43: 6.7 | FE43: 6.7 | FF43: 7.1 | FG43: 7.5 | FH43: 7.5 | FI43: 7.4 | FJ43: 7.3 | FK43: 7.5 | FL43: 7.7 | FM43: 7.6 | FN43: 7.4 | FO43: 7.9 | FP43: 7.8 | FQ43: 8 | FR43: 7.5 | FS43: 8 | FT43: 8.2 | FU43: 8.1 | FV43: 7.8 | FW43: 7.7 | FX43: 8.2 | FY43: 8.4 | FZ43: 8.1 | GA43: 7.9 | GB43: 7.8 | GC43: 7.5 | GD43: 7.5 | GE43: 7.9 | GF43: 8 | GG43: 8.1 | GH43: 8 | GI43: 7.5 | GJ43: 7.4 | GK43: 7.4 | GL43: 7.4 | GM43: 7.4 | GN43: 7.1 | GO43: 7.7 | GP43: 8.2 | GQ43: 9.2 | GR43: 9.5 | GS43: 9.6 | GT43: 10 | GU43: 9.7 | GV43: 10.9 | GW43: 12.5 | GX43: 12 | GY43: 11.7 | GZ43: 12.2 | HA43: 11.9 | HB43: 14.7 | HC43: 11.8 | HD43: 11.5 | HE43: 12.1 | HF43: 12.4 | HG43: 12.8 | HH43: 13 | HI43: 13.4 | HJ43: 13.9 | HK43: 14.4 | HL43: 14.5 | HM43: 14.9 | HN43: 14.7 | HO43: 14.4 | HP43: 14.4 | HQ43: 14 | HR43: 13.7 | HS43: 13.9 | HT43: 12.6 | HU43: 13.4 | HV43: 12.8 | HW43: 12.6 | HX43: 12 | HY43: 11.4 | HZ43: 11.5 | IA43: 12 | IB43: 12.3 | IC43: 11.9 | ID43: 11.4 | IE43: 11.4 | IF43: 11.4 | IG43: 11.6 | IH43: 11.5 | II43: 11.5 | IJ43: 11.1 | IK43: 11.6 | IL43: 11.5 | IM43: 11.9 | IN43: 11.5 | IO43: 10.4 | IP43: 10.2 | IQ43: 10.3 | IR43: 10.3 | IS43: 10.2 | IT43: 10.1 | IU43: 9.9 | IV43: 9.7 | IW43: 10 | IX43: 10 | IY43: 10.6 | IZ43: 10.7 | JA43: 10.7 | JB43: 10.4 | JC43: 10.9
EN44: 12.4 | EO44: 12.5 | EP44: 12.6 | EQ44: 9.7 | ER44: 9.3 | ES44: 9.4 | ET44: 9.5 | EU44: 10.1 | EV44: 10.4 | EW44: 10.2 | EX44: 10 | EY44: 10 | EZ44: 9.7 | FA44: 10.1 | FB44: 10.1 | FC44: 9.8 | FD44: 9.4 | FE44: 9.4 | FF44: 9.8 | FG44: 10.1 | FH44: 10 | FI44: 9.9 | FJ44: 9.7 | FK44: 9.9 | FL44: 10.1 | FM44: 9.9 | FN44: 9.9 | FO44: 10.3 | FP44: 10.2 | FQ44: 10.1 | FR44: 9.9 | FS44: 10.4 | FT44: 10.5 | FU44: 10.3 | FV44: 9.7 | FW44: 9.7 | FX44: 9.9 | FY44: 10 | FZ44: 9.9 | GA44: 9.6 | GB44: 9.4 | GC44: 9.3 | GD44: 9.3 | GE44: 9.6 | GF44: 9.7 | GG44: 9.6 | GH44: 9.6 | GI44: 9.5 | GJ44: 9.6 | GK44: 9.5 | GL44: 9.4 | GM44: 9.4 | GN44: 9 | GO44: 9.4 | GP44: 9.7 | GQ44: 10.8 | GR44: 9.6 | GS44: 9.7 | GT44: 10.1 | GU44: 9.8 | GV44: 9 | GW44: 14.1 | GX44: 14.8 | GY44: 14.6 | GZ44: 14.6 | HA44: 14.5 | HB44: 11.6 | HC44: 15.3 | HD44: 15 | HE44: 15.9 | HF44: 15.9 | HG44: 9.3 | HH44: 16.1 | HI44: 16.5 | HJ44: 17 | HK44: 17.1 | HL44: 16.8 | HM44: 17.1 | HN44: 16.8 | HO44: 16.4 | HP44: 16.4 | HQ44: 16 | HR44: 16.2 | HS44: 15.6 | HT44: 15.2 | HU44: 15 | HV44: 15.4 | HW44: 15 | HX44: 14.2 | HY44: 13.5 | HZ44: 13.2 | IA44: 13.8 | IB44: 13.8 | IC44: 13.2 | ID44: 12.4 | IE44: 12.3 | IF44: 12.1 | IG44: 12 | IH44: 11.8 | II44: 11.6 | IJ44: 11.2 | IK44: 11.6 | IL44: 11.4 | IM44: 11.7 | IN44: 11.5 | IO44: 11.4 | IP44: 11.1 | IQ44: 11.2 | IR44: 11.1 | IS44: 11 | IT44: 10.8 | IU44: 10.6 | IV44: 10.2 | IW44: 10.5 | IX44: 10.5 | IY44: 11 | IZ44: 10.9 | JA44: 10.8 | JB44: 10.4 | JC44: 10.9 | JD44: 10.9
IQ52: Year | IR52: 45292 | IS52: 45323 | IT52: 45352 | IU52: 45383 | IV52: 45413 | IW52: 45444 | IX52: 45474 | IY52: 45505 | IZ52: 45536 | JA52: 45566 | JB52: 45597 | JC52: 45627 | JD52: 45658 | JE52: 45689 | JF52: 45717 | JG52: 45748 | JH52: 45778 | JI52: 45809 | JJ52: 45839 | JK52: 45870 | JL52: 45901 | JM52: 45931 | JN52: 45962 | JO52: 45992 | JP52: 46023 | JQ52: 46054 | JR52: 46082 | JS52: 46113 | JT52: 46143 | JU52: 46174
IQ53: All items CPI | IR53: 8.4366751 | IS53: 6.9432167 | IT53: 7.5689816 | IU53: 7.2159806 | IV53: 6.6455162 | IW53: 6.3903632 | IX53: 4.1496083 | IY53: 2.0865516 | IZ53: 1.0487266 | JA53: 0.35022944 | JB53: 4.9347603 | JC53: 6.0373792 | JD53: 5.4156989 | JE53: 4.0067298 | JF53: 3.090283 | JG53: 2.120771 | JH53: 0.89716967 | JI53: 1.0367859 | JJ53: 1.8062297 | JK53: 2.4703699 | JL53: 3.4419388 | JM53: 4.0103628 | JN53: 3.4802784 | JO53: 3.0443193 | JP53: 1.9887809 | JQ53: 2.4651753 | JR53: 4.5288534 | JS53: 5.4774851 | JT53: 7.9438825 | JU53: 7.1063671
IQ54: Inflation | IR54: 126.5903 | IS54: 124.79981 | IT54: 125.18665 | IU54: 126.72398 | IV54: 129.18648 | IW54: 132.41933 | IX54: 128.84887 | IY54: 127.01434 | IZ54: 126.22508 | JA54: 125.46827 | JB54: 129.3 | JC54: 132.85546 | JD54: 133.44605 | JE54: 129.8002 | JF54: 129.05528 | JG54: 129.4115 | JH54: 130.34551 | JI54: 133.79223 | JJ54: 131.17618 | JK54: 130.15206 | JL54: 130.56967 | JM54: 130.5 | JN54: 133.8 | JO54: 136.9 | JP54: 136.1 | JQ54: 133 | JR54: 134.9 | JS54: 136.5 | JT54: 140.7 | JU54: 143.3
IQ55: Imported inflation | IR55: 4.3174637 | IS55: 3.545196 | IT55: 3.4295747 | IU55: 3.3590717 | IV55: 3.2089233 | IW55: 1.8022252 | IX55: 1.2523104 | IY55: 1.3267701 | IZ55: 0.59244026 | JA55: -0.068454805 | JB55: 1.0765126 | JC55: 5.2559272 | JD55: 3.4734344 | JE55: 3.209563 | JF55: 3.0624274 | JG55: 3.1564766 | JH55: 3.5873874 | JI55: 3.0071876 | JJ55: 3.8258605 | JK55: 3.9352074 | JL55: 3.4811706 | JM55: 4.0449951 | JN55: 7.990507 | JO55: 5.5072193 | JP55: 6.0018308 | JQ55: 4.6893421 | JR55: 6.9132957 | JS55: 8.881667 | JT55: 11.718529 | JU55: 13.128696
IQ56: Local inflation | IR56: 12.264309 | IS56: 10.177439 | IT56: 11.560312 | IU56: 10.842691 | IV56: 3.8394844 | IW56: 10.473871 | IX56: 6.7519014 | IY56: 2.7662527 | IZ56: 1.4639717 | JA56: 0.73042924 | JB56: 6.9271629 | JC56: 6.731822 | JD56: 7.0927259 | JE56: 4.7306586 | JF56: 3.1151845 | JG56: 1.2126339 | JH56: 4.2245164 | JI56: -0.57924398 | JJ56: 0.085691317 | JK56: 1.178281 | JL56: 3.4065424 | JM56: 3.9089283 | JN56: 1.3057064 | JO56: 0.91336929 | JP56: -2.0550277 | JQ56: 0.4681651 | JR56: 2.4813007 | JS56: 2.4929002 | JT56: 4.4928756 | JU56: 1.9408769
