Workbook

Sheet DQAF_Input
A1: Navigation: Use the + / – buttons in the left margin to expand/collapse each indicator section. Tip: Expand one indicator at a time. | S1: SCORE_NUM | T1: TARGET_SCORE_NUM | U1: ADJ_WEIGHT | V1: TOTAL_WEIGHT | W1: WEIGHT_SHARE | X1: WEIGHTED_SCORE | Y1: NR_FLAG | Z1: NR_SEQ | AA1: ADJ_WEIGHT_TGT | AB1: TOTAL_WEIGHT_TGT | AC1: WEIGHT_SHARE_TGT | AD1: WEIGHTED_SCORE_TGT | AE1: NR_FLAG_TGT | AF1: DIFF_FLAG | AG1: DIFF_SEQ
A2: Quality Indicator | B2: DIM_ID | C2: ELEM_ID | D2: QIND_ID | E2: RBP_ID | F2: Standards and Codes (S&C) | G2: WEIGHT | H2: Current Observance | J2: Target Observance | K2: COMMENT | L2: REFERENCES | M2: SCORE | N2: TARGET_SCORE | O2: KEY_TYPE | P2: STANDARD | Q2: E_DESC | R2: SORT_ORDER
F3: The responsibility for collecting, processing, and disseminating official statistics is clearly specified in law
A4: The responsibility for collecting, processing, and disseminating official statistics is clearly specified in law | B4: 1 | C4: 1_1 | D4: 1_1_1 | E4: 1_1_1_1 | F4: Does a law, such as a statistical law or other relevant law, establish a clear legal framework for the development, production, and dissemination of official statistics? | G4: 50 | H4: Highly - This recommendation / best practice is implemented but minor gaps exist in coverage and/or the consistency of its application across the program / organization | J4: Fully - This recommendation / best practice is fully implemented | K4: The Tonga Strategy for Development of Statistics (TSDS) 2019-2023 aims to manage the production and dissessmination of accessible, quality, and accurate statistical information efficiently and effectively | L4: Explicit statement of objective and scope of the national statistical system, covering all key statistical activities (Articles 1–2 GLOS). European Statistical Code of Practice Principle 1 | M4: =IFERROR(INDEX(__key!$D:$D,MATCH(O4&"|"&SUBSTITUTE(H4,",",";"), __key!$E:$E, 0)), "") -> 4 | N4: =IFERROR(INDEX(__key!$D:$D,MATCH(O4&"|"&SUBSTITUTE(J4,",",";"), __key!$E:$E, 0)), "") -> 5 | O4: BP | Q4: The legal framework defining the national statistical system is comprehensive | R4: 1111 | S4: =IFERROR(1*M4,0) -> 4 | T4: =IFERROR(1*N4,0) -> 5 | U4: =IFERROR(IF(ISNUMBER(SEARCH("Not Relevant",H4)),0,VALUE(G4)),"") -> 50 | V4: =IFERROR(SUMIF($D:$D,D4,$U:$U),"") -> 150 | W4: =IF(OR(V4=0,V4=""),"",U4/V4) -> 0.33333333 | X4: =IF(OR(M4="",W4=""),"",VALUE(M4)*W4) -> 1.3333333 | Y4: =IFERROR(ISNUMBER(SEARCH("Not Relevant",H4)),FALSE) -> FALSE | Z4: =IF(Y4, COUNTIF($Y$2:Y4, TRUE), "") | AA4: =IFERROR(IF(ISNUMBER(SEARCH("Not Relevant",J4)),0,VALUE(G4)),"") -> 50 | AB4: =IFERROR(SUMIF($D:$D,D4,$AA:$AA),"") -> 150 | AC4: =IF(OR(AB4=0,AB4=""),"",AA4/AB4) -> 0.33333333 | AD4: =IF(OR(N4="",AC4=""),"",VALUE(N4)*AC4) -> 1.6666667 | AE4: =IFERROR(ISNUMBER(SEARCH("Not Relevant",J4)),FALSE) -> FALSE | AF4: =IF(OR(H4="",J4=""),FALSE,IF(H4<>J4,TRUE,FALSE)) -> TRUE | AG4: =IF(AF4, COUNTIF($AF$2:AF4, TRUE), "") -> 1
A5: The responsibility for collecting, processing, and disseminating official statistics is clearly specified in law | B5: 1 | C5: 1_1 | D5: 1_1_1 | E5: 1_1_1_2 | F5: Does a law, such as a statistical law or other relevant law, clearly define “official statistics” and distinguish them from other statistics (administrative or private)? | G5: 10 | H5: Highly - This recommendation / best practice is implemented but minor gaps exist in coverage and/or the consistency of its application across the program / organization | J5: Fully - This recommendation / best practice is fully implemented | K5: Official statistics is defined in the Statistics Act revision 2016 as "statistics produced by any department to inform the Government and people of Tonga about the economic, social, cultural and environmental conditions of the Kingdom and the activities, performance and impact of the Government, and to measure economic and social progress of the people of Tonga;" It is clearly defined that the TSD is the principal authority for official statistics. However, its distinction from other types of data is not explicitly mentioned and this could be clarified | L5: Explicit statement of objective and scope of the national statistical system, covering all key statistical activities (Articles 1–2 GLOS). European Statistical Code of Practice Principle 1 | M5: =IFERROR(INDEX(__key!$D:$D,MATCH(O5&"|"&SUBSTITUTE(H5,",",";"), __key!$E:$E, 0)), "") -> 4 | N5: =IFERROR(INDEX(__key!$D:$D,MATCH(O5&"|"&SUBSTITUTE(J5,",",";"), __key!$E:$E, 0)), "") -> 5 | O5: BP | Q5: The legal framework defining the national statistical system is comprehensive | R5: 1112 | S5: =IFERROR(1*M5,0) -> 4 | T5: =IFERROR(1*N5,0) -> 5 | U5: =IFERROR(IF(ISNUMBER(SEARCH("Not Relevant",H5)),0,VALUE(G5)),"") -> 10 | V5: =IFERROR(SUMIF($D:$D,D5,$U:$U),"") -> 150 | W5: =IF(OR(V5=0,V5=""),"",U5/V5) -> 0.066666667 | X5: =IF(OR(M5="",W5=""),"",VALUE(M5)*W5) -> 0.26666667 | Y5: =IFERROR(ISNUMBER(SEARCH("Not Relevant",H5)),FALSE) -> FALSE | Z5: =IF(Y5, COUNTIF($Y$2:Y5, TRUE), "") | AA5: =IFERROR(IF(ISNUMBER(SEARCH("Not Relevant",J5)),0,VALUE(G5)),"") -> 10 | AB5: =IFERROR(SUMIF($D:$D,D5,$AA:$AA),"") -> 150 | AC5: =IF(OR(AB5=0,AB5=""),"",AA5/AB5) -> 0.066666667 | AD5: =IF(OR(N5="",AC5=""),"",VALUE(N5)*AC5) -> 0.33333333 | AE5: =IFERROR(ISNUMBER(SEARCH("Not Relevant",J5)),FALSE) -> FALSE | AF5: =IF(OR(H5="",J5=""),FALSE,IF(H5<>J5,TRUE,FALSE)) -> TRUE | AG5: =IF(AF5, COUNTIF($AF$2:AF5, TRUE), "") -> 2
A6: The responsibility for collecting, processing, and disseminating official statistics is clearly specified in law | B6: 1 | C6: 1_1 | D6: 1_1_1 | E6: 1_1_1_3 | F6: Is the Fundamental Principle of Official Statistics - Relevance, Impartiality and Equal Access embedded in the law, such as a statistical law or other relevant law? | G6: 1 | H6: Highly - This recommendation / best practice is implemented but minor gaps exist in coverage and/or the consistency of its application across the program / organization | J6: =IF(H6="","",H6) -> Highly - This recommendation / best practice is implemented but minor gaps exist in coverage and/or the consistency of its application across the program / organization | K6: Yes, outlined in TSDS and Statistical Act 2020 is commited to providing data with improved accessibility, unbiased, and relevant publication of its statistics. | L6: Core statistical principles are fully recognized and legally binding (Article 3 GLOS). European Statistical Code of Practice Principle 1 | M6: =IFERROR(INDEX(__key!$D:$D,MATCH(O6&"|"&SUBSTITUTE(H6,",",";"), __key!$E:$E, 0)), "") -> 4 | N6: =IFERROR(INDEX(__key!$D:$D,MATCH(O6&"|"&SUBSTITUTE(J6,",",";"), __key!$E:$E, 0)), "") -> 4 | O6: BP | Q6: The legal framework defining the national statistical system is comprehensive | R6: 1113 | S6: =IFERROR(1*M6,0) -> 4 | T6: =IFERROR(1*N6,0) -> 4 | U6: =IFERROR(IF(ISNUMBER(SEARCH("Not Relevant",H6)),0,VALUE(G6)),"") -> 1 | V6: =IFERROR(SUMIF($D:$D,D6,$U:$U),"") -> 150 | W6: =IF(OR(V6=0,V6=""),"",U6/V6) -> 0.0066666667 | X6: =IF(OR(M6="",W6=""),"",VALUE(M6)*W6) -> 0.026666667 | Y6: =IFERROR(ISNUMBER(SEARCH("Not Relevant",H6)),FALSE) -> FALSE | Z6: =IF(Y6, COUNTIF($Y$2:Y6, TRUE), "") | AA6: =IFERROR(IF(ISNUMBER(SEARCH("Not Relevant",J6)),0,VALUE(G6)),"") -> 1 | AB6: =IFERROR(SUMIF($D:$D,D6,$AA:$AA),"") -> 150 | AC6: =IF(OR(AB6=0,AB6=""),"",AA6/AB6) -> 0.0066666667 | AD6: =IF(OR(N6="",AC6=""),"",VALUE(N6)*AC6) -> 0.026666667 | AE6: =IFERROR(ISNUMBER(SEARCH("Not Relevant",J6)),FALSE) -> FALSE | AF6: =IF(OR(H6="",J6=""),FALSE,IF(H6<>J6,TRUE,FALSE)) -> FALSE | AG6: =IF(AF6, COUNTIF($AF$2:AF6, TRUE), "")
A7: The responsibility for collecting, processing, and disseminating official statistics is clearly specified in law | B7: 1 | C7: 1_1 | D7: 1_1_1 | E7: 1_1_1_4 | F7: Does a law, such as a statistical law or other relevant law, provide a clear mandate for producers to collect data (including compulsory surveys when necessary) if such data are not otherwise available? | G7: 50 | H7: Highly - This recommendation / best practice is implemented but minor gaps exist in coverage and/or the consistency of its application across the program / organization | J7: Fully - This recommendation / best practice is fully implemented | K7: Part II of the Statistic Act 2016 outlines the TSD may collect data from people, businesses or organisations for purposes relating to compiling, analyzing and publishing official statistics | L7: National authority is provided legal authority to conduct surveys, define methodologies, and require responses, minimizing duplication and burden (Articles 15–16 GLOS). European Statistical Code of Practice Principle 1 | M7: =IFERROR(INDEX(__key!$D:$D,MATCH(O7&"|"&SUBSTITUTE(H7,",",";"), __key!$E:$E, 0)), "") -> 4 | N7: =IFERROR(INDEX(__key!$D:$D,MATCH(O7&"|"&SUBSTITUTE(J7,",",";"), __key!$E:$E, 0)), "") -> 5 | O7: BP | Q7: The legal framework defining the national statistical system is comprehensive | R7: 1114 | S7: =IFERROR(1*M7,0) -> 4 | T7: =IFERROR(1*N7,0) -> 5 | U7: =IFERROR(IF(ISNUMBER(SEARCH("Not Relevant",H7)),0,VALUE(G7)),"") -> 50 | V7: =IFERROR(SUMIF($D:$D,D7,$U:$U),"") -> 150 | W7: =IF(OR(V7=0,V7=""),"",U7/V7) -> 0.33333333 | X7: =IF(OR(M7="",W7=""),"",VALUE(M7)*W7) -> 1.3333333 | Y7: =IFERROR(ISNUMBER(SEARCH("Not Relevant",H7)),FALSE) -> FALSE | Z7: =IF(Y7, COUNTIF($Y$2:Y7, TRUE), "") | AA7: =IFERROR(IF(ISNUMBER(SEARCH("Not Relevant",J7)),0,VALUE(G7)),"") -> 50 | AB7: =IFERROR(SUMIF($D:$D,D7,$AA:$AA),"") -> 150 | AC7: =IF(OR(AB7=0,AB7=""),"",AA7/AB7) -> 0.33333333 | AD7: =IF(OR(N7="",AC7=""),"",VALUE(N7)*AC7) -> 1.6666667 | AE7: =IFERROR(ISNUMBER(SEARCH("Not Relevant",J7)),FALSE) -> FALSE | AF7: =IF(OR(H7="",J7=""),FALSE,IF(H7<>J7,TRUE,FALSE)) -> TRUE | AG7: =IF(AF7, COUNTIF($AF$2:AF7, TRUE), "") -> 3
A8: The responsibility for collecting, processing, and disseminating official statistics is clearly specified in law | B8: 1 | C8: 1_1 | D8: 1_1_1 | E8: 1_1_1_5 | F8: Does the law, such as a statistical law or other relevant law, override conflicting provisions in other legislation, or require that other laws comply with statistical requirements where needed? | G8: 30 | J8: =IF(H8="","",H8) | K8: Not sure | L8: The law must prevail over secrecy or confidentiality rules that impede statistical work, unless explicitly exempt (Articles 17, 37 GLOS). European Statistical Code of Practice Principle 1 | M8: =IFERROR(INDEX(__key!$D:$D,MATCH(O8&"|"&SUBSTITUTE(H8,",",";"), __key!$E:$E, 0)), "") | N8: =IFERROR(INDEX(__key!$D:$D,MATCH(O8&"|"&SUBSTITUTE(J8,",",";"), __key!$E:$E, 0)), "") | O8: BP | Q8: The legal framework defining the national statistical system is comprehensive | R8: 1115 | S8: =IFERROR(1*M8,0) -> 0 | T8: =IFERROR(1*N8,0) -> 0 | U8: =IFERROR(IF(ISNUMBER(SEARCH("Not Relevant",H8)),0,VALUE(G8)),"") -> 30 | V8: =IFERROR(SUMIF($D:$D,D8,$U:$U),"") -> 150 | W8: =IF(OR(V8=0,V8=""),"",U8/V8) -> 0.2 | X8: =IF(OR(M8="",W8=""),"",VALUE(M8)*W8) | Y8: =IFERROR(ISNUMBER(SEARCH("Not Relevant",H8)),FALSE) -> FALSE | Z8: =IF(Y8, COUNTIF($Y$2:Y8, TRUE), "") | AA8: =IFERROR(IF(ISNUMBER(SEARCH("Not Relevant",J8)),0,VALUE(G8)),"") -> 30 | AB8: =IFERROR(SUMIF($D:$D,D8,$AA:$AA),"") -> 150 | AC8: =IF(OR(AB8=0,AB8=""),"",AA8/AB8) -> 0.2 | AD8: =IF(OR(N8="",AC8=""),"",VALUE(N8)*AC8) | AE8: =IFERROR(ISNUMBER(SEARCH("Not Relevant",J8)),FALSE) -> FALSE | AF8: =IF(OR(H8="",J8=""),FALSE,IF(H8<>J8,TRUE,FALSE)) -> FALSE | AG8: =IF(AF8, COUNTIF($AF$2:AF8, TRUE), "")
A9: The responsibility for collecting, processing, and disseminating official statistics is clearly specified in law | B9: 1 | C9: 1_1 | D9: 1_1_1 | E9: 1_1_1_6 | F9: When was the statistical law or other relevant law last updated? | H9: Highly - Between the last 6 and 10 years | J9: Fully - Within the last five years | K9: The Statistical Act in 2020 is referenced as the latest revision of the 2015 Act, however, only the 2016 revision of the Statistical Act 2015 is found online- and is referenced throughout this document | L9: European Statistical Code of Practice Principle 1 | M9: =IFERROR(INDEX(__key!$D:$D,MATCH(O9&"|"&SUBSTITUTE(H9,",",";"), __key!$E:$E, 0)), "") -> 4 | N9: =IFERROR(INDEX(__key!$D:$D,MATCH(O9&"|"&SUBSTITUTE(J9,",",";"), __key!$E:$E, 0)), "") -> 5 | O9: TP | Q9: The legal framework defining the national statistical system is comprehensive | R9: 1116 | S9: =IFERROR(1*M9,0) -> 4 | T9: =IFERROR(1*N9,0) -> 5 | U9: =IFERROR(IF(ISNUMBER(SEARCH("Not Relevant",H9)),0,VALUE(G9)),"") -> 0 | V9: =IFERROR(SUMIF($D:$D,D9,$U:$U),"") -> 150 | W9: =IF(OR(V9=0,V9=""),"",U9/V9) -> 0 | X9: =IF(OR(M9="",W9=""),"",VALUE(M9)*W9) -> 0 | Y9: =IFERROR(ISNUMBER(SEARCH("Not Relevant",H9)),FALSE) -> FALSE | Z9: =IF(Y9, COUNTIF($Y$2:Y9, TRUE), "") | AA9: =IFERROR(IF(ISNUMBER(SEARCH("Not Relevant",J9)),0,VALUE(G9)),"") -> 0 | AB9: =IFERROR(SUMIF($D:$D,D9,$AA:$AA),"") -> 150 | AC9: =IF(OR(AB9=0,AB9=""),"",AA9/AB9) -> 0 | AD9: =IF(OR(N9="",AC9=""),"",VALUE(N9)*AC9) -> 0 | AE9: =IFERROR(ISNUMBER(SEARCH("Not Relevant",J9)),FALSE) -> FALSE | AF9: =IF(OR(H9="",J9=""),FALSE,IF(H9<>J9,TRUE,FALSE)) -> TRUE | AG9: =IF(AF9, COUNTIF($AF$2:AF9, TRUE), "") -> 4
A10: The responsibility for collecting, processing, and disseminating official statistics is clearly specified in law | B10: 1 | C10: 1_1 | D10: 1_1_1 | E10: 1_1_1_7 | F10: Is the Fundamental Principle of Official Statistics - Professional Standards, Scientific Principles, and Professional Ethics embedded in the law, such as a statistical law or other relevant law? | G10: 1 | H10: Highly - This recommendation / best practice is implemented but minor gaps exist in coverage and/or the consistency of its application across the program / organization | J10: Fully - This recommendation / best practice is fully implemented | K10: Part II Section 5(1) of the Statistical Act inculcates the scientific integrity of methods used, the protection against disclosing identifiable information and other professional standards | L10: European Statistical Code of Practice Principle 1 | M10: =IFERROR(INDEX(__key!$D:$D,MATCH(O10&"|"&SUBSTITUTE(H10,",",";"), __key!$E:$E, 0)), "") -> 4 | N10: =IFERROR(INDEX(__key!$D:$D,MATCH(O10&"|"&SUBSTITUTE(J10,",",";"), __key!$E:$E, 0)), "") -> 5 | O10: BP | Q10: The legal framework defining the national statistical system is comprehensive | R10: 1117 | S10: =IFERROR(1*M10,0) -> 4 | T10: =IFERROR(1*N10,0) -> 5 | U10: =IFERROR(IF(ISNUMBER(SEARCH("Not Relevant",H10)),0,VALUE(G10)),"") -> 1 | V10: =IFERROR(SUMIF($D:$D,D10,$U:$U),"") -> 150 | W10: =IF(OR(V10=0,V10=""),"",U10/V10) -> 0.0066666667 | X10: =IF(OR(M10="",W10=""),"",VALUE(M10)*W10) -> 0.026666667 | Y10: =IFERROR(ISNUMBER(SEARCH("Not Relevant",H10)),FALSE) -> FALSE | Z10: =IF(Y10, COUNTIF($Y$2:Y10, TRUE), "") | AA10: =IFERROR(IF(ISNUMBER(SEARCH("Not Relevant",J10)),0,VALUE(G10)),"") -> 1 | AB10: =IFERROR(SUMIF($D:$D,D10,$AA:$AA),"") -> 150 | AC10: =IF(OR(AB10=0,AB10=""),"",AA10/AB10) -> 0.0066666667 | AD10: =IF(OR(N10="",AC10=""),"",VALUE(N10)*AC10) -> 0.033333333 | AE10: =IFERROR(ISNUMBER(SEARCH("Not Relevant",J10)),FALSE) -> FALSE | AF10: =IF(OR(H10="",J10=""),FALSE,IF(H10<>J10,TRUE,FALSE)) -> TRUE | AG10: =IF(AF10, COUNTIF($AF$2:AF10, TRUE), "") -> 5
A11: The responsibility for collecting, processing, and disseminating official statistics is clearly specified in law | B11: 1 | C11: 1_1 | D11: 1_1_1 | E11: 1_1_1_8 | F11: Is the Fundamental Principle of Official Statistics - Accountability and Transparency embedded in the law, such as a statistical law or other relevant law? | G11: 1 | J11: =IF(H11="","",H11) | L11: European Statistical Code of Practice Principle 1 | M11: =IFERROR(INDEX(__key!$D:$D,MATCH(O11&"|"&SUBSTITUTE(H11,",",";"), __key!$E:$E, 0)), "") | N11: =IFERROR(INDEX(__key!$D:$D,MATCH(O11&"|"&SUBSTITUTE(J11,",",";"), __key!$E:$E, 0)), "") | O11: BP | Q11: The legal framework defining the national statistical system is comprehensive | R11: 1118 | S11: =IFERROR(1*M11,0) -> 0 | T11: =IFERROR(1*N11,0) -> 0 | U11: =IFERROR(IF(ISNUMBER(SEARCH("Not Relevant",H11)),0,VALUE(G11)),"") -> 1 | V11: =IFERROR(SUMIF($D:$D,D11,$U:$U),"") -> 150 | W11: =IF(OR(V11=0,V11=""),"",U11/V11) -> 0.0066666667 | X11: =IF(OR(M11="",W11=""),"",VALUE(M11)*W11) | Y11: =IFERROR(ISNUMBER(SEARCH("Not Relevant",H11)),FALSE) -> FALSE | Z11: =IF(Y11, COUNTIF($Y$2:Y11, TRUE), "") | AA11: =IFERROR(IF(ISNUMBER(SEARCH("Not Relevant",J11)),0,VALUE(G11)),"") -> 1 | AB11: =IFERROR(SUMIF($D:$D,D11,$AA:$AA),"") -> 150 | AC11: =IF(OR(AB11=0,AB11=""),"",AA11/AB11) -> 0.0066666667 | AD11: =IF(OR(N11="",AC11=""),"",VALUE(N11)*AC11) | AE11: =IFERROR(ISNUMBER(SEARCH("Not Relevant",J11)),FALSE) -> FALSE | AF11: =IF(OR(H11="",J11=""),FALSE,IF(H11<>J11,TRUE,FALSE)) -> FALSE | AG11: =IF(AF11, COUNTIF($AF$2:AF11, TRUE), "")
A12: The responsibility for collecting, processing, and disseminating official statistics is clearly specified in law | B12: 1 | C12: 1_1 | D12: 1_1_1 | E12: 1_1_1_9 | F12: Is the Fundamental Principle of Official Statistics - Prevention of Misuse embedded in the law, such as a statistical law or other relevant law? | G12: 1 | H12: Fully - This recommendation / best practice is fully implemented | J12: =IF(H12="","",H12) -> Fully - This recommendation / best practice is fully implemented | K12: Part IV of the Statistical Act, Section 10, describes the legal oath required by all employees to protect the use of information and its confidentiality. Part VIII reveals the penalties and imprisonment punishment for those who commit offences against misuse of data. | L12: European Statistical Code of Practice Principle 1 | M12: =IFERROR(INDEX(__key!$D:$D,MATCH(O12&"|"&SUBSTITUTE(H12,",",";"), __key!$E:$E, 0)), "") -> 5 | N12: =IFERROR(INDEX(__key!$D:$D,MATCH(O12&"|"&SUBSTITUTE(J12,",",";"), __key!$E:$E, 0)), "") -> 5 | O12: BP | Q12: The legal framework defining the national statistical system is comprehensive | R12: 1119 | S12: =IFERROR(1*M12,0) -> 5 | T12: =IFERROR(1*N12,0) -> 5 | U12: =IFERROR(IF(ISNUMBER(SEARCH("Not Relevant",H12)),0,VALUE(G12)),"") -> 1 | V12: =IFERROR(SUMIF($D:$D,D12,$U:$U),"") -> 150 | W12: =IF(OR(V12=0,V12=""),"",U12/V12) -> 0.0066666667 | X12: =IF(OR(M12="",W12=""),"",VALUE(M12)*W12) -> 0.033333333 | Y12: =IFERROR(ISNUMBER(SEARCH("Not Relevant",H12)),FALSE) -> FALSE | Z12: =IF(Y12, COUNTIF($Y$2:Y12, TRUE), "") | AA12: =IFERROR(IF(ISNUMBER(SEARCH("Not Relevant",J12)),0,VALUE(G12)),"") -> 1 | AB12: =IFERROR(SUMIF($D:$D,D12,$AA:$AA),"") -> 150 | AC12: =IF(OR(AB12=0,AB12=""),"",AA12/AB12) -> 0.0066666667 | AD12: =IF(OR(N12="",AC12=""),"",VALUE(N12)*AC12) -> 0.033333333 | AE12: =IFERROR(ISNUMBER(SEARCH("Not Relevant",J12)),FALSE) -> FALSE | AF12: =IF(OR(H12="",J12=""),FALSE,IF(H12<>J12,TRUE,FALSE)) -> FALSE | AG12: =IF(AF12, COUNTIF($AF$2:AF12, TRUE), "")
A13: The responsibility for collecting, processing, and disseminating official statistics is clearly specified in law | B13: 1 | C13: 1_1 | D13: 1_1_1 | E13: 1_1_1_10 | F13: Is the Fundamental Principle of Official Statistics - Sources of Official Statistics embedded in the law, such as a statistical law or other relevant law? | G13: 1 | H13: Highly - This recommendation / best practice is implemented but minor gaps exist in coverage and/or the consistency of its application across the program / organization | J13: =IF(H13="","",H13) -> Highly - This recommendation / best practice is implemented but minor gaps exist in coverage and/or the consistency of its application across the program / organization | K13: Again, the sources of official statistics may be collected from respondents including persons, businesses or organisations. | L13: European Statistical Code of Practice Principle 1 | M13: =IFERROR(INDEX(__key!$D:$D,MATCH(O13&"|"&SUBSTITUTE(H13,",",";"), __key!$E:$E, 0)), "") -> 4 | N13: =IFERROR(INDEX(__key!$D:$D,MATCH(O13&"|"&SUBSTITUTE(J13,",",";"), __key!$E:$E, 0)), "") -> 4 | O13: BP | Q13: The legal framework defining the national statistical system is comprehensive | R13: 11110 | S13: =IFERROR(1*M13,0) -> 4 | T13: =IFERROR(1*N13,0) -> 4 | U13: =IFERROR(IF(ISNUMBER(SEARCH("Not Relevant",H13)),0,VALUE(G13)),"") -> 1 | V13: =IFERROR(SUMIF($D:$D,D13,$U:$U),"") -> 150 | W13: =IF(OR(V13=0,V13=""),"",U13/V13) -> 0.0066666667 | X13: =IF(OR(M13="",W13=""),"",VALUE(M13)*W13) -> 0.026666667 | Y13: =IFERROR(ISNUMBER(SEARCH("Not Relevant",H13)),FALSE) -> FALSE | Z13: =IF(Y13, COUNTIF($Y$2:Y13, TRUE), "") | AA13: =IFERROR(IF(ISNUMBER(SEARCH("Not Relevant",J13)),0,VALUE(G13)),"") -> 1 | AB13: =IFERROR(SUMIF($D:$D,D13,$AA:$AA),"") -> 150 | AC13: =IF(OR(AB13=0,AB13=""),"",AA13/AB13) -> 0.0066666667 | AD13: =IF(OR(N13="",AC13=""),"",VALUE(N13)*AC13) -> 0.026666667 | AE13: =IFERROR(ISNUMBER(SEARCH("Not Relevant",J13)),FALSE) -> FALSE | AF13: =IF(OR(H13="",J13=""),FALSE,IF(H13<>J13,TRUE,FALSE)) -> FALSE | AG13: =IF(AF13, COUNTIF($AF$2:AF13, TRUE), "")
A14: The responsibility for collecting, processing, and disseminating official statistics is clearly specified in law | B14: 1 | C14: 1_1 | D14: 1_1_1 | E14: 1_1_1_11 | F14: Is the Fundamental Principle of Official Statistics - Confidentiality embedded in the law, such as a statistical law or other relevant law? | G14: 1 | H14: Fully - This recommendation / best practice is fully implemented | J14: Fully - This recommendation / best practice is fully implemented | K14: Part IV Section 11 clearly outlines protection measures against the disclosure of respondent information, with data being used only for statistical purposes and to prevent identification of any person. | L14: European Statistical Code of Practice Principle 1 | M14: =IFERROR(INDEX(__key!$D:$D,MATCH(O14&"|"&SUBSTITUTE(H14,",",";"), __key!$E:$E, 0)), "") -> 5 | N14: =IFERROR(INDEX(__key!$D:$D,MATCH(O14&"|"&SUBSTITUTE(J14,",",";"), __key!$E:$E, 0)), "") -> 5 | O14: BP | Q14: The legal framework defining the national statistical system is comprehensive | R14: 11111 | S14: =IFERROR(1*M14,0) -> 5 | T14: =IFERROR(1*N14,0) -> 5 | U14: =IFERROR(IF(ISNUMBER(SEARCH("Not Relevant",H14)),0,VALUE(G14)),"") -> 1 | V14: =IFERROR(SUMIF($D:$D,D14,$U:$U),"") -> 150 | W14: =IF(OR(V14=0,V14=""),"",U14/V14) -> 0.0066666667 | X14: =IF(OR(M14="",W14=""),"",VALUE(M14)*W14) -> 0.033333333 | Y14: =IFERROR(ISNUMBER(SEARCH("Not Relevant",H14)),FALSE) -> FALSE | Z14: =IF(Y14, COUNTIF($Y$2:Y14, TRUE), "") | AA14: =IFERROR(IF(ISNUMBER(SEARCH("Not Relevant",J14)),0,VALUE(G14)),"") -> 1 | AB14: =IFERROR(SUMIF($D:$D,D14,$AA:$AA),"") -> 150 | AC14: =IF(OR(AB14=0,AB14=""),"",AA14/AB14) -> 0.0066666667 | AD14: =IF(OR(N14="",AC14=""),"",VALUE(N14)*AC14) -> 0.033333333 | AE14: =IFERROR(ISNUMBER(SEARCH("Not Relevant",J14)),FALSE) -> FALSE | AF14: =IF(OR(H14="",J14=""),FALSE,IF(H14<>J14,TRUE,FALSE)) -> FALSE | AG14: =IF(AF14, COUNTIF($AF$2:AF14, TRUE), "")
A15: The responsibility for collecting, processing, and disseminating official statistics is clearly specified in law | B15: 1 | C15: 1_1 | D15: 1_1_1 | E15: 1_1_1_12 | F15: Is the Fundamental Principle of Official Statistics - Legislation embedded in the law, such as a statistical law or other relevant law? | G15: 1 | J15: =IF(H15="","",H15) | L15: European Statistical Code of Practice Principle 1 | M15: =IFERROR(INDEX(__key!$D:$D,MATCH(O15&"|"&SUBSTITUTE(H15,",",";"), __key!$E:$E, 0)), "") | N15: =IFERROR(INDEX(__key!$D:$D,MATCH(O15&"|"&SUBSTITUTE(J15,",",";"), __key!$E:$E, 0)), "") | O15: BP | Q15: The legal framework defining the national statistical system is comprehensive | R15: 11112 | S15: =IFERROR(1*M15,0) -> 0 | T15: =IFERROR(1*N15,0) -> 0 | U15: =IFERROR(IF(ISNUMBER(SEARCH("Not Relevant",H15)),0,VALUE(G15)),"") -> 1 | V15: =IFERROR(SUMIF($D:$D,D15,$U:$U),"") -> 150 | W15: =IF(OR(V15=0,V15=""),"",U15/V15) -> 0.0066666667 | X15: =IF(OR(M15="",W15=""),"",VALUE(M15)*W15) | Y15: =IFERROR(ISNUMBER(SEARCH("Not Relevant",H15)),FALSE) -> FALSE | Z15: =IF(Y15, COUNTIF($Y$2:Y15, TRUE), "") | AA15: =IFERROR(IF(ISNUMBER(SEARCH("Not Relevant",J15)),0,VALUE(G15)),"") -> 1 | AB15: =IFERROR(SUMIF($D:$D,D15,$AA:$AA),"") -> 150 | AC15: =IF(OR(AB15=0,AB15=""),"",AA15/AB15) -> 0.0066666667 | AD15: =IF(OR(N15="",AC15=""),"",VALUE(N15)*AC15) | AE15: =IFERROR(ISNUMBER(SEARCH("Not Relevant",J15)),FALSE) -> FALSE | AF15: =IF(OR(H15="",J15=""),FALSE,IF(H15<>J15,TRUE,FALSE)) -> FALSE | AG15: =IF(AF15, COUNTIF($AF$2:AF15, TRUE), "")
A16: The responsibility for collecting, processing, and disseminating official statistics is clearly specified in law | B16: 1 | C16: 1_1 | D16: 1_1_1 | E16: 1_1_1_13 | F16: Is the Fundamental Principle of Official Statistics - National Coordination embedded in the law, such as a statistical law or other relevant law? | G16: 1 | J16: =IF(H16="","",H16) | L16: European Statistical Code of Practice Principle 1 | M16: =IFERROR(INDEX(__key!$D:$D,MATCH(O16&"|"&SUBSTITUTE(H16,",",";"), __key!$E:$E, 0)), "") | N16: =IFERROR(INDEX(__key!$D:$D,MATCH(O16&"|"&SUBSTITUTE(J16,",",";"), __key!$E:$E, 0)), "") | O16: BP | Q16: The legal framework defining the national statistical system is comprehensive | R16: 11113 | S16: =IFERROR(1*M16,0) -> 0 | T16: =IFERROR(1*N16,0) -> 0 | U16: =IFERROR(IF(ISNUMBER(SEARCH("Not Relevant",H16)),0,VALUE(G16)),"") -> 1 | V16: =IFERROR(SUMIF($D:$D,D16,$U:$U),"") -> 150 | W16: =IF(OR(V16=0,V16=""),"",U16/V16) -> 0.0066666667 | X16: =IF(OR(M16="",W16=""),"",VALUE(M16)*W16) | Y16: =IFERROR(ISNUMBER(SEARCH("Not Relevant",H16)),FALSE) -> FALSE | Z16: =IF(Y16, COUNTIF($Y$2:Y16, TRUE), "") | AA16: =IFERROR(IF(ISNUMBER(SEARCH("Not Relevant",J16)),0,VALUE(G16)),"") -> 1 | AB16: =IFERROR(SUMIF($D:$D,D16,$AA:$AA),"") -> 150 | AC16: =IF(OR(AB16=0,AB16=""),"",AA16/AB16) -> 0.0066666667 | AD16: =IF(OR(N16="",AC16=""),"",VALUE(N16)*AC16) | AE16: =IFERROR(ISNUMBER(SEARCH("Not Relevant",J16)),FALSE) -> FALSE | AF16: =IF(OR(H16="",J16=""),FALSE,IF(H16<>J16,TRUE,FALSE)) -> FALSE | AG16: =IF(AF16, COUNTIF($AF$2:AF16, TRUE), "")
A17: The responsibility for collecting, processing, and disseminating official statistics is clearly specified in law | B17: 1 | C17: 1_1 | D17: 1_1_1 | E17: 1_1_1_14 | F17: Is the Fundamental Principle of Official Statistics - Use of International Standards embedded in the law, such as a statistical law or other relevant law? | G17: 1 | H17: Highly - This recommendation / best practice is implemented but minor gaps exist in coverage and/or the consistency of its application across the program / organization | J17: Fully - This recommendation / best practice is fully implemented | L17: European Statistical Code of Practice Principle 1 | M17: =IFERROR(INDEX(__key!$D:$D,MATCH(O17&"|"&SUBSTITUTE(H17,",",";"), __key!$E:$E, 0)), "") -> 4 | N17: =IFERROR(INDEX(__key!$D:$D,MATCH(O17&"|"&SUBSTITUTE(J17,",",";"), __key!$E:$E, 0)), "") -> 5 | O17: BP | Q17: The legal framework defining the national statistical system is comprehensive | R17: 11114 | S17: =IFERROR(1*M17,0) -> 4 | T17: =IFERROR(1*N17,0) -> 5 | U17: =IFERROR(IF(ISNUMBER(SEARCH("Not Relevant",H17)),0,VALUE(G17)),"") -> 1 | V17: =IFERROR(SUMIF($D:$D,D17,$U:$U),"") -> 150 | W17: =IF(OR(V17=0,V17=""),"",U17/V17) -> 0.0066666667 | X17: =IF(OR(M17="",W17=""),"",VALUE(M17)*W17) -> 0.026666667 | Y17: =IFERROR(ISNUMBER(SEARCH("Not Relevant",H17)),FALSE) -> FALSE | Z17: =IF(Y17, COUNTIF($Y$2:Y17, TRUE), "") | AA17: =IFERROR(IF(ISNUMBER(SEARCH("Not Relevant",J17)),0,VALUE(G17)),"") -> 1 | AB17: =IFERROR(SUMIF($D:$D,D17,$AA:$AA),"") -> 150 | AC17: =IF(OR(AB17=0,AB17=""),"",AA17/AB17) -> 0.0066666667 | AD17: =IF(OR(N17="",AC17=""),"",VALUE(N17)*AC17) -> 0.033333333 | AE17: =IFERROR(ISNUMBER(SEARCH("Not Relevant",J17)),FALSE) -> FALSE | AF17: =IF(OR(H17="",J17=""),FALSE,IF(H17<>J17,TRUE,FALSE)) -> TRUE | AG17: =IF(AF17, COUNTIF($AF$2:AF17, TRUE), "") -> 6
A18: The responsibility for collecting, processing, and disseminating official statistics is clearly specified in law | B18: 1 | C18: 1_1 | D18: 1_1_1 | E18: 1_1_1_15 | F18: Is the Fundamental Principle of Official Statistics - International Cooperation embedded in the law, such as a statistical law or other relevant law? | G18: 1 | H18: Highly - This recommendation / best practice is implemented but minor gaps exist in coverage and/or the consistency of its application across the program / organization | J18: Fully - This recommendation / best practice is fully implemented | K18: Part II Section 5(3d) outlines the coordination of international cooperation including Pacific regional collaboration on standards and information management | L18: European Statistical Code of Practice Principle 1 | M18: =IFERROR(INDEX(__key!$D:$D,MATCH(O18&"|"&SUBSTITUTE(H18,",",";"), __key!$E:$E, 0)), "") -> 4 | N18: =IFERROR(INDEX(__key!$D:$D,MATCH(O18&"|"&SUBSTITUTE(J18,",",";"), __key!$E:$E, 0)), "") -> 5 | O18: BP | Q18: The legal framework defining the national statistical system is comprehensive | R18: 11115 | S18: =IFERROR(1*M18,0) -> 4 | T18: =IFERROR(1*N18,0) -> 5 | U18: =IFERROR(IF(ISNUMBER(SEARCH("Not Relevant",H18)),0,VALUE(G18)),"") -> 1 | V18: =IFERROR(SUMIF($D:$D,D18,$U:$U),"") -> 150 | W18: =IF(OR(V18=0,V18=""),"",U18/V18) -> 0.0066666667 | X18: =IF(OR(M18="",W18=""),"",VALUE(M18)*W18) -> 0.026666667 | Y18: =IFERROR(ISNUMBER(SEARCH("Not Relevant",H18)),FALSE) -> FALSE | Z18: =IF(Y18, COUNTIF($Y$2:Y18, TRUE), "") | AA18: =IFERROR(IF(ISNUMBER(SEARCH("Not Relevant",J18)),0,VALUE(G18)),"") -> 1 | AB18: =IFERROR(SUMIF($D:$D,D18,$AA:$AA),"") -> 150 | AC18: =IF(OR(AB18=0,AB18=""),"",AA18/AB18) -> 0.0066666667 | AD18: =IF(OR(N18="",AC18=""),"",VALUE(N18)*AC18) -> 0.033333333 | AE18: =IFERROR(ISNUMBER(SEARCH("Not Relevant",J18)),FALSE) -> FALSE | AF18: =IF(OR(H18="",J18=""),FALSE,IF(H18<>J18,TRUE,FALSE)) -> TRUE | AG18: =IF(AF18, COUNTIF($AF$2:AF18, TRUE), "") -> 7
F19: The statistical organization operates independently and is free from political influence
A20: The statistical organization operates independently and is free from political influence | B20: 1 | C20: 1_2 | D20: 1_2_1 | E20: 1_2_1_1 | F20: Is there a National Statistical Office (NSO), department or organizational unit designated as a professionally independent body and the leading authority of the system? | G20: 20 | H20: Fully - This recommendation / best practice is fully implemented | J20: =IF(H20="","",H20) -> Fully - This recommendation / best practice is fully implemented | K20: Yes, the Tonga Statistical Department is the principal authority for the publication of official statistics | L20: NSO is recognized under the highest authority (e.g., Prime Minister, President), with legal independence and a clear coordination mandate (Article 5 GLOS). European Statistical Code of Practice Principle 1 | M20: =IFERROR(INDEX(__key!$D:$D,MATCH(O20&"|"&SUBSTITUTE(H20,",",";"), __key!$E:$E, 0)), "") -> 5 | N20: =IFERROR(INDEX(__key!$D:$D,MATCH(O20&"|"&SUBSTITUTE(J20,",",";"), __key!$E:$E, 0)), "") -> 5 | O20: BP | Q20: Professional independence is ensured | R20: 1211 | S20: =IFERROR(1*M20,0) -> 5 | T20: =IFERROR(1*N20,0) -> 5 | U20: =IFERROR(IF(ISNUMBER(SEARCH("Not Relevant",H20)),0,VALUE(G20)),"") -> 20 | V20: =IFERROR(SUMIF($D:$D,D20,$U:$U),"") -> 200 | W20: =IF(OR(V20=0,V20=""),"",U20/V20) -> 0.1 | X20: =IF(OR(M20="",W20=""),"",VALUE(M20)*W20) -> 0.5 | Y20: =IFERROR(ISNUMBER(SEARCH("Not Relevant",H20)),FALSE) -> FALSE | Z20: =IF(Y20, COUNTIF($Y$2:Y20, TRUE), "") | AA20: =IFERROR(IF(ISNUMBER(SEARCH("Not Relevant",J20)),0,VALUE(G20)),"") -> 20 | AB20: =IFERROR(SUMIF($D:$D,D20,$AA:$AA),"") -> 200 | AC20: =IF(OR(AB20=0,AB20=""),"",AA20/AB20) -> 0.1 | AD20: =IF(OR(N20="",AC20=""),"",VALUE(N20)*AC20) -> 0.5 | AE20: =IFERROR(ISNUMBER(SEARCH("Not Relevant",J20)),FALSE) -> FALSE | AF20: =IF(OR(H20="",J20=""),FALSE,IF(H20<>J20,TRUE,FALSE)) -> FALSE | AG20: =IF(AF20, COUNTIF($AF$2:AF20, TRUE), "")
A21: The statistical organization operates independently and is free from political influence | B21: 1 | C21: 1_2 | D21: 1_2_1 | E21: 1_2_1_2 | F21: Does the National Statistical Office, department, or organizational unit have full autonomy over statistical methods, data sources, content, and timing of releases (free from political/administrative interference)? | G21: 80 | H21: Fully - This recommendation / best practice is fully implemented | J21: =IF(H21="","",H21) -> Fully - This recommendation / best practice is fully implemented | K21: Section 6 of Government Statistician (GS) responsibilities highlihgt the autonomy of the GS over managing statistical methods, content and timing of releases | L21: The law guarantees professional independence in day-to-day operations and releases (Articles 3.1a, 5 GLOS). European Statistical Code of Practice Principle 1 | M21: =IFERROR(INDEX(__key!$D:$D,MATCH(O21&"|"&SUBSTITUTE(H21,",",";"), __key!$E:$E, 0)), "") -> 5 | N21: =IFERROR(INDEX(__key!$D:$D,MATCH(O21&"|"&SUBSTITUTE(J21,",",";"), __key!$E:$E, 0)), "") -> 5 | O21: BP | Q21: Professional independence is ensured | R21: 1212 | S21: =IFERROR(1*M21,0) -> 5 | T21: =IFERROR(1*N21,0) -> 5 | U21: =IFERROR(IF(ISNUMBER(SEARCH("Not Relevant",H21)),0,VALUE(G21)),"") -> 80 | V21: =IFERROR(SUMIF($D:$D,D21,$U:$U),"") -> 200 | W21: =IF(OR(V21=0,V21=""),"",U21/V21) -> 0.4 | X21: =IF(OR(M21="",W21=""),"",VALUE(M21)*W21) -> 2 | Y21: =IFERROR(ISNUMBER(SEARCH("Not Relevant",H21)),FALSE) -> FALSE | Z21: =IF(Y21, COUNTIF($Y$2:Y21, TRUE), "") | AA21: =IFERROR(IF(ISNUMBER(SEARCH("Not Relevant",J21)),0,VALUE(G21)),"") -> 80 | AB21: =IFERROR(SUMIF($D:$D,D21,$AA:$AA),"") -> 200 | AC21: =IF(OR(AB21=0,AB21=""),"",AA21/AB21) -> 0.4 | AD21: =IF(OR(N21="",AC21=""),"",VALUE(N21)*AC21) -> 2 | AE21: =IFERROR(ISNUMBER(SEARCH("Not Relevant",J21)),FALSE) -> FALSE | AF21: =IF(OR(H21="",J21=""),FALSE,IF(H21<>J21,TRUE,FALSE)) -> FALSE | AG21: =IF(AF21, COUNTIF($AF$2:AF21, TRUE), "")
A22: The statistical organization operates independently and is free from political influence | B22: 1 | C22: 1_2 | D22: 1_2_1 | E22: 1_2_1_3 | F22: Is the head of the statistical organization (e.g. Chief Statistician, Departmental Director, Director General, Statistical Unit Head), appointed through an open, merit-based process for a fixed term, with strictly limited grounds for dismissal? | G22: 50 | H22: Highly - This recommendation / best practice is implemented but minor gaps exist in coverage and/or the consistency of its application across the program / organization | J22: Fully - This recommendation / best practice is fully implemented | K22: Section 4 covers the appointment of the Government Statistician, however, its contents arent very detailed in its selection. | L22: Transparent appointment with legal protection of tenure (Article 6 GLOS). European Statistical Code of Practice Principle 1 | M22: =IFERROR(INDEX(__key!$D:$D,MATCH(O22&"|"&SUBSTITUTE(H22,",",";"), __key!$E:$E, 0)), "") -> 4 | N22: =IFERROR(INDEX(__key!$D:$D,MATCH(O22&"|"&SUBSTITUTE(J22,",",";"), __key!$E:$E, 0)), "") -> 5 | O22: BP | Q22: Professional independence is ensured | R22: 1213 | S22: =IFERROR(1*M22,0) -> 4 | T22: =IFERROR(1*N22,0) -> 5 | U22: =IFERROR(IF(ISNUMBER(SEARCH("Not Relevant",H22)),0,VALUE(G22)),"") -> 50 | V22: =IFERROR(SUMIF($D:$D,D22,$U:$U),"") -> 200 | W22: =IF(OR(V22=0,V22=""),"",U22/V22) -> 0.25 | X22: =IF(OR(M22="",W22=""),"",VALUE(M22)*W22) -> 1 | Y22: =IFERROR(ISNUMBER(SEARCH("Not Relevant",H22)),FALSE) -> FALSE | Z22: =IF(Y22, COUNTIF($Y$2:Y22, TRUE), "") | AA22: =IFERROR(IF(ISNUMBER(SEARCH("Not Relevant",J22)),0,VALUE(G22)),"") -> 50 | AB22: =IFERROR(SUMIF($D:$D,D22,$AA:$AA),"") -> 200 | AC22: =IF(OR(AB22=0,AB22=""),"",AA22/AB22) -> 0.25 | AD22: =IF(OR(N22="",AC22=""),"",VALUE(N22)*AC22) -> 1.25 | AE22: =IFERROR(ISNUMBER(SEARCH("Not Relevant",J22)),FALSE) -> FALSE | AF22: =IF(OR(H22="",J22=""),FALSE,IF(H22<>J22,TRUE,FALSE)) -> TRUE | AG22: =IF(AF22, COUNTIF($AF$2:AF22, TRUE), "") -> 8
A23: The statistical organization operates independently and is free from political influence | B23: 1 | C23: 1_2 | D23: 1_2_1 | E23: 1_2_1_4 | F23: Does the head of the statistical organization (e.g., Chief Statistician, Departmental Director, Director General, Statistical Unit Head) have full authority over organizational structure and staffing within the organization? | G23: 50 | J23: =IF(H23="","",H23) | L23: Chief Statistician independently decides on NSO structure, staffing, and statistical standards (Articles 6.3–6.5 GLOS). European Statistical Code of Practice Principle 1 | M23: =IFERROR(INDEX(__key!$D:$D,MATCH(O23&"|"&SUBSTITUTE(H23,",",";"), __key!$E:$E, 0)), "") | N23: =IFERROR(INDEX(__key!$D:$D,MATCH(O23&"|"&SUBSTITUTE(J23,",",";"), __key!$E:$E, 0)), "") | O23: BP | Q23: Professional independence is ensured | R23: 1214 | S23: =IFERROR(1*M23,0) -> 0 | T23: =IFERROR(1*N23,0) -> 0 | U23: =IFERROR(IF(ISNUMBER(SEARCH("Not Relevant",H23)),0,VALUE(G23)),"") -> 50 | V23: =IFERROR(SUMIF($D:$D,D23,$U:$U),"") -> 200 | W23: =IF(OR(V23=0,V23=""),"",U23/V23) -> 0.25 | X23: =IF(OR(M23="",W23=""),"",VALUE(M23)*W23) | Y23: =IFERROR(ISNUMBER(SEARCH("Not Relevant",H23)),FALSE) -> FALSE | Z23: =IF(Y23, COUNTIF($Y$2:Y23, TRUE), "") | AA23: =IFERROR(IF(ISNUMBER(SEARCH("Not Relevant",J23)),0,VALUE(G23)),"") -> 50 | AB23: =IFERROR(SUMIF($D:$D,D23,$AA:$AA),"") -> 200 | AC23: =IF(OR(AB23=0,AB23=""),"",AA23/AB23) -> 0.25 | AD23: =IF(OR(N23="",AC23=""),"",VALUE(N23)*AC23) | AE23: =IFERROR(ISNUMBER(SEARCH("Not Relevant",J23)),FALSE) -> FALSE | AF23: =IF(OR(H23="",J23=""),FALSE,IF(H23<>J23,TRUE,FALSE)) -> FALSE | AG23: =IF(AF23, COUNTIF($AF$2:AF23, TRUE), "")
F24: Data sharing and coordination among data-producing agencies are effective
A25: Data sharing and coordination among data-producing agencies are effective | B25: 1 | C25: 1_3 | D25: 1_3_1 | E25: 1_3_1_1 | F25: Are statistical producers (e.g., national statistical office, line ministries, central bank) clearly identified in the law and required to follow the principles of official statistics? | G25: 20 | J25: =IF(H25="","",H25) | L25: Entities producing official statistics must meet the same standards and be supervised/coordinated by the NSO (Articles 2.1, 7 GLOS). European Statistical Code of Practice Principle 2 | M25: =IFERROR(INDEX(__key!$D:$D,MATCH(O25&"|"&SUBSTITUTE(H25,",",";"), __key!$E:$E, 0)), "") | N25: =IFERROR(INDEX(__key!$D:$D,MATCH(O25&"|"&SUBSTITUTE(J25,",",";"), __key!$E:$E, 0)), "") | O25: BP | Q25: Effective coordination of the national statistical system | R25: 1311 | S25: =IFERROR(1*M25,0) -> 0 | T25: =IFERROR(1*N25,0) -> 0 | U25: =IFERROR(IF(ISNUMBER(SEARCH("Not Relevant",H25)),0,VALUE(G25)),"") -> 20 | V25: =IFERROR(SUMIF($D:$D,D25,$U:$U),"") -> 135 | W25: =IF(OR(V25=0,V25=""),"",U25/V25) -> 0.14814815 | X25: =IF(OR(M25="",W25=""),"",VALUE(M25)*W25) | Y25: =IFERROR(ISNUMBER(SEARCH("Not Relevant",H25)),FALSE) -> FALSE | Z25: =IF(Y25, COUNTIF($Y$2:Y25, TRUE), "") | AA25: =IFERROR(IF(ISNUMBER(SEARCH("Not Relevant",J25)),0,VALUE(G25)),"") -> 20 | AB25: =IFERROR(SUMIF($D:$D,D25,$AA:$AA),"") -> 135 | AC25: =IF(OR(AB25=0,AB25=""),"",AA25/AB25) -> 0.14814815 | AD25: =IF(OR(N25="",AC25=""),"",VALUE(N25)*AC25) | AE25: =IFERROR(ISNUMBER(SEARCH("Not Relevant",J25)),FALSE) -> FALSE | AF25: =IF(OR(H25="",J25=""),FALSE,IF(H25<>J25,TRUE,FALSE)) -> FALSE | AG25: =IF(AF25, COUNTIF($AF$2:AF25, TRUE), "")
A26: Data sharing and coordination among data-producing agencies are effective | B26: 1 | C26: 1_3 | D26: 1_3_1 | E26: 1_3_1_2 | F26: Does a governmental policy exist that assigns a body (e.g., NSO) the authority to coordinate the national statistical system, including issuing common standards, methods, and classifications? | G26: 15 | J26: =IF(H26="","",H26) | L26: NSO is empowered to set standards for official statistics across agencies, ensuring uniformity and avoiding duplication (Articles 5.2, 10 GLOS). European Statistical Code of Practice Principle 2 | M26: =IFERROR(INDEX(__key!$D:$D,MATCH(O26&"|"&SUBSTITUTE(H26,",",";"), __key!$E:$E, 0)), "") | N26: =IFERROR(INDEX(__key!$D:$D,MATCH(O26&"|"&SUBSTITUTE(J26,",",";"), __key!$E:$E, 0)), "") | O26: BP | Q26: Effective coordination of the national statistical system | R26: 1312 | S26: =IFERROR(1*M26,0) -> 0 | T26: =IFERROR(1*N26,0) -> 0 | U26: =IFERROR(IF(ISNUMBER(SEARCH("Not Relevant",H26)),0,VALUE(G26)),"") -> 15 | V26: =IFERROR(SUMIF($D:$D,D26,$U:$U),"") -> 135 | W26: =IF(OR(V26=0,V26=""),"",U26/V26) -> 0.11111111 | X26: =IF(OR(M26="",W26=""),"",VALUE(M26)*W26) | Y26: =IFERROR(ISNUMBER(SEARCH("Not Relevant",H26)),FALSE) -> FALSE | Z26: =IF(Y26, COUNTIF($Y$2:Y26, TRUE), "") | AA26: =IFERROR(IF(ISNUMBER(SEARCH("Not Relevant",J26)),0,VALUE(G26)),"") -> 15 | AB26: =IFERROR(SUMIF($D:$D,D26,$AA:$AA),"") -> 135 | AC26: =IF(OR(AB26=0,AB26=""),"",AA26/AB26) -> 0.11111111 | AD26: =IF(OR(N26="",AC26=""),"",VALUE(N26)*AC26) | AE26: =IFERROR(ISNUMBER(SEARCH("Not Relevant",J26)),FALSE) -> FALSE | AF26: =IF(OR(H26="",J26=""),FALSE,IF(H26<>J26,TRUE,FALSE)) -> FALSE | AG26: =IF(AF26, COUNTIF($AF$2:AF26, TRUE), "")
A27: Data sharing and coordination among data-producing agencies are effective | B27: 1 | C27: 1_3 | D27: 1_3_1 | E27: 1_3_1_3 | F27: Do public administrative data producer(s) have a legal obligation to share data with the NSO and other official producers? | G27: 30 | J27: =IF(H27="","",H27) | L27: Public authorities must give producers access to existing data free of charge; changes in admin data systems should be pre-consulted (Article 17 GLOS). European Statistical Code of Practice Principle 2 | M27: =IFERROR(INDEX(__key!$D:$D,MATCH(O27&"|"&SUBSTITUTE(H27,",",";"), __key!$E:$E, 0)), "") | N27: =IFERROR(INDEX(__key!$D:$D,MATCH(O27&"|"&SUBSTITUTE(J27,",",";"), __key!$E:$E, 0)), "") | O27: DS | Q27: Effective coordination of the national statistical system | R27: 1313 | S27: =IFERROR(1*M27,0) -> 0 | T27: =IFERROR(1*N27,0) -> 0 | U27: =IFERROR(IF(ISNUMBER(SEARCH("Not Relevant",H27)),0,VALUE(G27)),"") -> 30 | V27: =IFERROR(SUMIF($D:$D,D27,$U:$U),"") -> 135 | W27: =IF(OR(V27=0,V27=""),"",U27/V27) -> 0.22222222 | X27: =IF(OR(M27="",W27=""),"",VALUE(M27)*W27) | Y27: =IFERROR(ISNUMBER(SEARCH("Not Relevant",H27)),FALSE) -> FALSE | Z27: =IF(Y27, COUNTIF($Y$2:Y27, TRUE), "") | AA27: =IFERROR(IF(ISNUMBER(SEARCH("Not Relevant",J27)),0,VALUE(G27)),"") -> 30 | AB27: =IFERROR(SUMIF($D:$D,D27,$AA:$AA),"") -> 135 | AC27: =IF(OR(AB27=0,AB27=""),"",AA27/AB27) -> 0.22222222 | AD27: =IF(OR(N27="",AC27=""),"",VALUE(N27)*AC27) | AE27: =IFERROR(ISNUMBER(SEARCH("Not Relevant",J27)),FALSE) -> FALSE | AF27: =IF(OR(H27="",J27=""),FALSE,IF(H27<>J27,TRUE,FALSE)) -> FALSE | AG27: =IF(AF27, COUNTIF($AF$2:AF27, TRUE), "")
A28: Data sharing and coordination among data-producing agencies are effective | B28: 1 | C28: 1_3 | D28: 1_3_1 | E28: 1_3_1_4 | F28: Have MOUs or some other form of data exchange agreements been established with customs authorities? | G28: 5 | J28: =IF(H28="","",H28) | L28: European Statistical Code of Practice Principle 2 | M28: =IFERROR(INDEX(__key!$D:$D,MATCH(O28&"|"&SUBSTITUTE(H28,",",";"), __key!$E:$E, 0)), "") | N28: =IFERROR(INDEX(__key!$D:$D,MATCH(O28&"|"&SUBSTITUTE(J28,",",";"), __key!$E:$E, 0)), "") | O28: BP | Q28: Effective coordination of the national statistical system | R28: 1314 | S28: =IFERROR(1*M28,0) -> 0 | T28: =IFERROR(1*N28,0) -> 0 | U28: =IFERROR(IF(ISNUMBER(SEARCH("Not Relevant",H28)),0,VALUE(G28)),"") -> 5 | V28: =IFERROR(SUMIF($D:$D,D28,$U:$U),"") -> 135 | W28: =IF(OR(V28=0,V28=""),"",U28/V28) -> 0.037037037 | X28: =IF(OR(M28="",W28=""),"",VALUE(M28)*W28) | Y28: =IFERROR(ISNUMBER(SEARCH("Not Relevant",H28)),FALSE) -> FALSE | Z28: =IF(Y28, COUNTIF($Y$2:Y28, TRUE), "") | AA28: =IFERROR(IF(ISNUMBER(SEARCH("Not Relevant",J28)),0,VALUE(G28)),"") -> 5 | AB28: =IFERROR(SUMIF($D:$D,D28,$AA:$AA),"") -> 135 | AC28: =IF(OR(AB28=0,AB28=""),"",AA28/AB28) -> 0.037037037 | AD28: =IF(OR(N28="",AC28=""),"",VALUE(N28)*AC28) | AE28: =IFERROR(ISNUMBER(SEARCH("Not Relevant",J28)),FALSE) -> FALSE | AF28: =IF(OR(H28="",J28=""),FALSE,IF(H28<>J28,TRUE,FALSE)) -> FALSE | AG28: =IF(AF28, COUNTIF($AF$2:AF28, TRUE), "")
A29: Data sharing and coordination among data-producing agencies are effective | B29: 1 | C29: 1_3 | D29: 1_3_1 | E29: 1_3_1_5 | F29: What is the date the most recent data sharing agreement has been signed with customs authorities? | G29: 5 | J29: =IF(H29="","",H29) | L29: European Statistical Code of Practice Principle 2 | M29: =IFERROR(INDEX(__key!$D:$D,MATCH(O29&"|"&SUBSTITUTE(H29,",",";"), __key!$E:$E, 0)), "") | N29: =IFERROR(INDEX(__key!$D:$D,MATCH(O29&"|"&SUBSTITUTE(J29,",",";"), __key!$E:$E, 0)), "") | O29: TP | Q29: Effective coordination of the national statistical system | R29: 1315 | S29: =IFERROR(1*M29,0) -> 0 | T29: =IFERROR(1*N29,0) -> 0 | U29: =IFERROR(IF(ISNUMBER(SEARCH("Not Relevant",H29)),0,VALUE(G29)),"") -> 5 | V29: =IFERROR(SUMIF($D:$D,D29,$U:$U),"") -> 135 | W29: =IF(OR(V29=0,V29=""),"",U29/V29) -> 0.037037037 | X29: =IF(OR(M29="",W29=""),"",VALUE(M29)*W29) | Y29: =IFERROR(ISNUMBER(SEARCH("Not Relevant",H29)),FALSE) -> FALSE | Z29: =IF(Y29, COUNTIF($Y$2:Y29, TRUE), "") | AA29: =IFERROR(IF(ISNUMBER(SEARCH("Not Relevant",J29)),0,VALUE(G29)),"") -> 5 | AB29: =IFERROR(SUMIF($D:$D,D29,$AA:$AA),"") -> 135 | AC29: =IF(OR(AB29=0,AB29=""),"",AA29/AB29) -> 0.037037037 | AD29: =IF(OR(N29="",AC29=""),"",VALUE(N29)*AC29) | AE29: =IFERROR(ISNUMBER(SEARCH("Not Relevant",J29)),FALSE) -> FALSE | AF29: =IF(OR(H29="",J29=""),FALSE,IF(H29<>J29,TRUE,FALSE)) -> FALSE | AG29: =IF(AF29, COUNTIF($AF$2:AF29, TRUE), "")
A30: Data sharing and coordination among data-producing agencies are effective | B30: 1 | C30: 1_3 | D30: 1_3_1 | E30: 1_3_1_6 | F30: Have MOUs or some other form of data exchange agreements have been established with tax authorities? | G30: 5 | J30: =IF(H30="","",H30) | L30: European Statistical Code of Practice Principle 2 | M30: =IFERROR(INDEX(__key!$D:$D,MATCH(O30&"|"&SUBSTITUTE(H30,",",";"), __key!$E:$E, 0)), "") | N30: =IFERROR(INDEX(__key!$D:$D,MATCH(O30&"|"&SUBSTITUTE(J30,",",";"), __key!$E:$E, 0)), "") | O30: BP | Q30: Effective coordination of the national statistical system | R30: 1316 | S30: =IFERROR(1*M30,0) -> 0 | T30: =IFERROR(1*N30,0) -> 0 | U30: =IFERROR(IF(ISNUMBER(SEARCH("Not Relevant",H30)),0,VALUE(G30)),"") -> 5 | V30: =IFERROR(SUMIF($D:$D,D30,$U:$U),"") -> 135 | W30: =IF(OR(V30=0,V30=""),"",U30/V30) -> 0.037037037 | X30: =IF(OR(M30="",W30=""),"",VALUE(M30)*W30) | Y30: =IFERROR(ISNUMBER(SEARCH("Not Relevant",H30)),FALSE) -> FALSE | Z30: =IF(Y30, COUNTIF($Y$2:Y30, TRUE), "") | AA30: =IFERROR(IF(ISNUMBER(SEARCH("Not Relevant",J30)),0,VALUE(G30)),"") -> 5 | AB30: =IFERROR(SUMIF($D:$D,D30,$AA:$AA),"") -> 135 | AC30: =IF(OR(AB30=0,AB30=""),"",AA30/AB30) -> 0.037037037 | AD30: =IF(OR(N30="",AC30=""),"",VALUE(N30)*AC30) | AE30: =IFERROR(ISNUMBER(SEARCH("Not Relevant",J30)),FALSE) -> FALSE | AF30: =IF(OR(H30="",J30=""),FALSE,IF(H30<>J30,TRUE,FALSE)) -> FALSE | AG30: =IF(AF30, COUNTIF($AF$2:AF30, TRUE), "")
A31: Data sharing and coordination among data-producing agencies are effective | B31: 1 | C31: 1_3 | D31: 1_3_1 | E31: 1_3_1_7 | F31: What is the date the most recent data sharing agreement has been signed with tax authorities? | G31: 5 | J31: =IF(H31="","",H31) | L31: European Statistical Code of Practice Principle 2 | M31: =IFERROR(INDEX(__key!$D:$D,MATCH(O31&"|"&SUBSTITUTE(H31,",",";"), __key!$E:$E, 0)), "") | N31: =IFERROR(INDEX(__key!$D:$D,MATCH(O31&"|"&SUBSTITUTE(J31,",",";"), __key!$E:$E, 0)), "") | O31: TP | Q31: Effective coordination of the national statistical system | R31: 1317 | S31: =IFERROR(1*M31,0) -> 0 | T31: =IFERROR(1*N31,0) -> 0 | U31: =IFERROR(IF(ISNUMBER(SEARCH("Not Relevant",H31)),0,VALUE(G31)),"") -> 5 | V31: =IFERROR(SUMIF($D:$D,D31,$U:$U),"") -> 135 | W31: =IF(OR(V31=0,V31=""),"",U31/V31) -> 0.037037037 | X31: =IF(OR(M31="",W31=""),"",VALUE(M31)*W31) | Y31: =IFERROR(ISNUMBER(SEARCH("Not Relevant",H31)),FALSE) -> FALSE | Z31: =IF(Y31, COUNTIF($Y$2:Y31, TRUE), "") | AA31: =IFERROR(IF(ISNUMBER(SEARCH("Not Relevant",J31)),0,VALUE(G31)),"") -> 5 | AB31: =IFERROR(SUMIF($D:$D,D31,$AA:$AA),"") -> 135 | AC31: =IF(OR(AB31=0,AB31=""),"",AA31/AB31) -> 0.037037037 | AD31: =IF(OR(N31="",AC31=""),"",VALUE(N31)*AC31) | AE31: =IFERROR(ISNUMBER(SEARCH("Not Relevant",J31)),FALSE) -> FALSE | AF31: =IF(OR(H31="",J31=""),FALSE,IF(H31<>J31,TRUE,FALSE)) -> FALSE | AG31: =IF(AF31, COUNTIF($AF$2:AF31, TRUE), "")
A32: Data sharing and coordination among data-producing agencies are effective | B32: 1 | C32: 1_3 | D32: 1_3_1 | E32: 1_3_1_8 | F32: Have MOUs or some other form of data exchange agreements been established with social security authorities? | G32: 5 | J32: =IF(H32="","",H32) | L32: European Statistical Code of Practice Principle 2 | M32: =IFERROR(INDEX(__key!$D:$D,MATCH(O32&"|"&SUBSTITUTE(H32,",",";"), __key!$E:$E, 0)), "") | N32: =IFERROR(INDEX(__key!$D:$D,MATCH(O32&"|"&SUBSTITUTE(J32,",",";"), __key!$E:$E, 0)), "") | O32: BP | Q32: Effective coordination of the national statistical system | R32: 1318 | S32: =IFERROR(1*M32,0) -> 0 | T32: =IFERROR(1*N32,0) -> 0 | U32: =IFERROR(IF(ISNUMBER(SEARCH("Not Relevant",H32)),0,VALUE(G32)),"") -> 5 | V32: =IFERROR(SUMIF($D:$D,D32,$U:$U),"") -> 135 | W32: =IF(OR(V32=0,V32=""),"",U32/V32) -> 0.037037037 | X32: =IF(OR(M32="",W32=""),"",VALUE(M32)*W32) | Y32: =IFERROR(ISNUMBER(SEARCH("Not Relevant",H32)),FALSE) -> FALSE | Z32: =IF(Y32, COUNTIF($Y$2:Y32, TRUE), "") | AA32: =IFERROR(IF(ISNUMBER(SEARCH("Not Relevant",J32)),0,VALUE(G32)),"") -> 5 | AB32: =IFERROR(SUMIF($D:$D,D32,$AA:$AA),"") -> 135 | AC32: =IF(OR(AB32=0,AB32=""),"",AA32/AB32) -> 0.037037037 | AD32: =IF(OR(N32="",AC32=""),"",VALUE(N32)*AC32) | AE32: =IFERROR(ISNUMBER(SEARCH("Not Relevant",J32)),FALSE) -> FALSE | AF32: =IF(OR(H32="",J32=""),FALSE,IF(H32<>J32,TRUE,FALSE)) -> FALSE | AG32: =IF(AF32, COUNTIF($AF$2:AF32, TRUE), "")
A33: Data sharing and coordination among data-producing agencies are effective | B33: 1 | C33: 1_3 | D33: 1_3_1 | E33: 1_3_1_9 | F33: What is the date the most recent data sharing agreement has been signed with social security authorities? | G33: 5 | J33: =IF(H33="","",H33) | L33: European Statistical Code of Practice Principle 2 | M33: =IFERROR(INDEX(__key!$D:$D,MATCH(O33&"|"&SUBSTITUTE(H33,",",";"), __key!$E:$E, 0)), "") | N33: =IFERROR(INDEX(__key!$D:$D,MATCH(O33&"|"&SUBSTITUTE(J33,",",";"), __key!$E:$E, 0)), "") | O33: TP | Q33: Effective coordination of the national statistical system | R33: 1319 | S33: =IFERROR(1*M33,0) -> 0 | T33: =IFERROR(1*N33,0) -> 0 | U33: =IFERROR(IF(ISNUMBER(SEARCH("Not Relevant",H33)),0,VALUE(G33)),"") -> 5 | V33: =IFERROR(SUMIF($D:$D,D33,$U:$U),"") -> 135 | W33: =IF(OR(V33=0,V33=""),"",U33/V33) -> 0.037037037 | X33: =IF(OR(M33="",W33=""),"",VALUE(M33)*W33) | Y33: =IFERROR(ISNUMBER(SEARCH("Not Relevant",H33)),FALSE) -> FALSE | Z33: =IF(Y33, COUNTIF($Y$2:Y33, TRUE), "") | AA33: =IFERROR(IF(ISNUMBER(SEARCH("Not Relevant",J33)),0,VALUE(G33)),"") -> 5 | AB33: =IFERROR(SUMIF($D:$D,D33,$AA:$AA),"") -> 135 | AC33: =IF(OR(AB33=0,AB33=""),"",AA33/AB33) -> 0.037037037 | AD33: =IF(OR(N33="",AC33=""),"",VALUE(N33)*AC33) | AE33: =IFERROR(ISNUMBER(SEARCH("Not Relevant",J33)),FALSE) -> FALSE | AF33: =IF(OR(H33="",J33=""),FALSE,IF(H33<>J33,TRUE,FALSE)) -> FALSE | AG33: =IF(AF33, COUNTIF($AF$2:AF33, TRUE), "")
A34: Data sharing and coordination among data-producing agencies are effective | B34: 1 | C34: 1_3 | D34: 1_3_1 | E34: 1_3_1_10 | F34: Have MOUs or some other form of data exchange agreements been established with land registry authorities? | G34: 5 | J34: =IF(H34="","",H34) | L34: European Statistical Code of Practice Principle 2 | M34: =IFERROR(INDEX(__key!$D:$D,MATCH(O34&"|"&SUBSTITUTE(H34,",",";"), __key!$E:$E, 0)), "") | N34: =IFERROR(INDEX(__key!$D:$D,MATCH(O34&"|"&SUBSTITUTE(J34,",",";"), __key!$E:$E, 0)), "") | O34: BP | Q34: Effective coordination of the national statistical system | R34: 13110 | S34: =IFERROR(1*M34,0) -> 0 | T34: =IFERROR(1*N34,0) -> 0 | U34: =IFERROR(IF(ISNUMBER(SEARCH("Not Relevant",H34)),0,VALUE(G34)),"") -> 5 | V34: =IFERROR(SUMIF($D:$D,D34,$U:$U),"") -> 135 | W34: =IF(OR(V34=0,V34=""),"",U34/V34) -> 0.037037037 | X34: =IF(OR(M34="",W34=""),"",VALUE(M34)*W34) | Y34: =IFERROR(ISNUMBER(SEARCH("Not Relevant",H34)),FALSE) -> FALSE | Z34: =IF(Y34, COUNTIF($Y$2:Y34, TRUE), "") | AA34: =IFERROR(IF(ISNUMBER(SEARCH("Not Relevant",J34)),0,VALUE(G34)),"") -> 5 | AB34: =IFERROR(SUMIF($D:$D,D34,$AA:$AA),"") -> 135 | AC34: =IF(OR(AB34=0,AB34=""),"",AA34/AB34) -> 0.037037037 | AD34: =IF(OR(N34="",AC34=""),"",VALUE(N34)*AC34) | AE34: =IFERROR(ISNUMBER(SEARCH("Not Relevant",J34)),FALSE) -> FALSE | AF34: =IF(OR(H34="",J34=""),FALSE,IF(H34<>J34,TRUE,FALSE)) -> FALSE | AG34: =IF(AF34, COUNTIF($AF$2:AF34, TRUE), "")
A35: Data sharing and coordination among data-producing agencies are effective | B35: 1 | C35: 1_3 | D35: 1_3_1 | E35: 1_3_1_11 | F35: What is the date the most recent data sharing agreement has been signed with land registry authorities? | G35: 5 | J35: =IF(H35="","",H35) | L35: European Statistical Code of Practice Principle 2 | M35: =IFERROR(INDEX(__key!$D:$D,MATCH(O35&"|"&SUBSTITUTE(H35,",",";"), __key!$E:$E, 0)), "") | N35: =IFERROR(INDEX(__key!$D:$D,MATCH(O35&"|"&SUBSTITUTE(J35,",",";"), __key!$E:$E, 0)), "") | O35: TP | Q35: Effective coordination of the national statistical system | R35: 13111 | S35: =IFERROR(1*M35,0) -> 0 | T35: =IFERROR(1*N35,0) -> 0 | U35: =IFERROR(IF(ISNUMBER(SEARCH("Not Relevant",H35)),0,VALUE(G35)),"") -> 5 | V35: =IFERROR(SUMIF($D:$D,D35,$U:$U),"") -> 135 | W35: =IF(OR(V35=0,V35=""),"",U35/V35) -> 0.037037037 | X35: =IF(OR(M35="",W35=""),"",VALUE(M35)*W35) | Y35: =IFERROR(ISNUMBER(SEARCH("Not Relevant",H35)),FALSE) -> FALSE | Z35: =IF(Y35, COUNTIF($Y$2:Y35, TRUE), "") | AA35: =IFERROR(IF(ISNUMBER(SEARCH("Not Relevant",J35)),0,VALUE(G35)),"") -> 5 | AB35: =IFERROR(SUMIF($D:$D,D35,$AA:$AA),"") -> 135 | AC35: =IF(OR(AB35=0,AB35=""),"",AA35/AB35) -> 0.037037037 | AD35: =IF(OR(N35="",AC35=""),"",VALUE(N35)*AC35) | AE35: =IFERROR(ISNUMBER(SEARCH("Not Relevant",J35)),FALSE) -> FALSE | AF35: =IF(OR(H35="",J35=""),FALSE,IF(H35<>J35,TRUE,FALSE)) -> FALSE | AG35: =IF(AF35, COUNTIF($AF$2:AF35, TRUE), "")
A36: Data sharing and coordination among data-producing agencies are effective | B36: 1 | C36: 1_3 | D36: 1_3_1 | E36: 1_3_1_12 | F36: Have MOUs or some other form of data exchange agreements been established with private sector entities? | G36: 5 | J36: =IF(H36="","",H36) | L36: European Statistical Code of Practice Principle 2 | M36: =IFERROR(INDEX(__key!$D:$D,MATCH(O36&"|"&SUBSTITUTE(H36,",",";"), __key!$E:$E, 0)), "") | N36: =IFERROR(INDEX(__key!$D:$D,MATCH(O36&"|"&SUBSTITUTE(J36,",",";"), __key!$E:$E, 0)), "") | O36: BP | Q36: Effective coordination of the national statistical system | R36: 13112 | S36: =IFERROR(1*M36,0) -> 0 | T36: =IFERROR(1*N36,0) -> 0 | U36: =IFERROR(IF(ISNUMBER(SEARCH("Not Relevant",H36)),0,VALUE(G36)),"") -> 5 | V36: =IFERROR(SUMIF($D:$D,D36,$U:$U),"") -> 135 | W36: =IF(OR(V36=0,V36=""),"",U36/V36) -> 0.037037037 | X36: =IF(OR(M36="",W36=""),"",VALUE(M36)*W36) | Y36: =IFERROR(ISNUMBER(SEARCH("Not Relevant",H36)),FALSE) -> FALSE | Z36: =IF(Y36, COUNTIF($Y$2:Y36, TRUE), "") | AA36: =IFERROR(IF(ISNUMBER(SEARCH("Not Relevant",J36)),0,VALUE(G36)),"") -> 5 | AB36: =IFERROR(SUMIF($D:$D,D36,$AA:$AA),"") -> 135 | AC36: =IF(OR(AB36=0,AB36=""),"",AA36/AB36) -> 0.037037037 | AD36: =IF(OR(N36="",AC36=""),"",VALUE(N36)*AC36) | AE36: =IFERROR(ISNUMBER(SEARCH("Not Relevant",J36)),FALSE) -> FALSE | AF36: =IF(OR(H36="",J36=""),FALSE,IF(H36<>J36,TRUE,FALSE)) -> FALSE | AG36: =IF(AF36, COUNTIF($AF$2:AF36, TRUE), "")
... A41: Data sharing and coordination among data-producing agencies are effective | B41: 1 | C41: 1_3 | D41: 1_3_1 | E41: 1_3_1_17 | F41: Does the agency seek external expert assistance when needed, for evaluating statistical methodologies and systems? | G41: 5 | J41: =IF(H41="","",H41) | L41: Generally recognized as a good practice: External audits or peer reviews (e.g., from international agencies) can validate and help improve technical methods and compilation systems. European Statistical Code of Practice Principle 2 | M41: =IFERROR(INDEX(__key!$D:$D,MATCH(O41&"|"&SUBSTITUTE(H41,",",";"), __key!$E:$E, 0)), "") | N41: =IFERROR(INDEX(__key!$D:$D,MATCH(O41&"|"&SUBSTITUTE(J41,",",";"), __key!$E:$E, 0)), "") | O41: BP | Q41: Effective coordination of the national statistical system | R41: 13117 | S41: =IFERROR(1*M41,0) -> 0 | T41: =IFERROR(1*N41,0) -> 0 | U41: =IFERROR(IF(ISNUMBER(SEARCH("Not Relevant",H41)),0,VALUE(G41)),"") -> 5 | V41: =IFERROR(SUMIF($D:$D,D41,$U:$U),"") -> 135 | W41: =IF(OR(V41=0,V41=""),"",U41/V41) -> 0.037037037 | X41: =IF(OR(M41="",W41=""),"",VALUE(M41)*W41) | Y41: =IFERROR(ISNUMBER(SEARCH("Not Relevant",H41)),FALSE) -> FALSE | Z41: =IF(Y41, COUNTIF($Y$2:Y41, TRUE), "") | AA41: =IFERROR(IF(ISNUMBER(SEARCH("Not Relevant",J41)),0,VALUE(G41)),"") -> 5 | AB41: =IFERROR(SUMIF($D:$D,D41,$AA:$AA),"") -> 135 | AC41: =IF(OR(AB41=0,AB41=""),"",AA41/AB41) -> 0.037037037 | AD41: =IF(OR(N41="",AC41=""),"",VALUE(N41)*AC41) | AE41: =IFERROR(ISNUMBER(SEARCH("Not Relevant",J41)),FALSE) -> FALSE | AF41: =IF(OR(H41="",J41=""),FALSE,IF(H41<>J41,TRUE,FALSE)) -> FALSE | AG41: =IF(AF41, COUNTIF($AF$2:AF41, TRUE), "")
F42: Individual reporters’ data are kept confidential and used for statistical purposes only
A43: Individual reporters’ data are kept confidential and used for statistical purposes only | B43: 1 | C43: 1_4 | D43: 1_4_1 | E43: 1_4_1_1 | F43: Is the security and integrity of data and their transmission guaranteed by appropriate policies and practices? | G43: 20 | J43: =IF(H43="","",H43) | L43: UN NQAF (7.5) Assuring statistical confidentiality and data security. European Statistical Code of Practice Principle 5 | M43: =IFERROR(INDEX(__key!$D:$D,MATCH(O43&"|"&SUBSTITUTE(H43,",",";"), __key!$E:$E, 0)), "") | N43: =IFERROR(INDEX(__key!$D:$D,MATCH(O43&"|"&SUBSTITUTE(J43,",",";"), __key!$E:$E, 0)), "") | O43: BP | Q43: Statistical confidentiality and data security are assured | R43: 1411 | S43: =IFERROR(1*M43,0) -> 0 | T43: =IFERROR(1*N43,0) -> 0 | U43: =IFERROR(IF(ISNUMBER(SEARCH("Not Relevant",H43)),0,VALUE(G43)),"") -> 20 | V43: =IFERROR(SUMIF($D:$D,D43,$U:$U),"") -> 100 | W43: =IF(OR(V43=0,V43=""),"",U43/V43) -> 0.2 | X43: =IF(OR(M43="",W43=""),"",VALUE(M43)*W43) | Y43: =IFERROR(ISNUMBER(SEARCH("Not Relevant",H43)),FALSE) -> FALSE | Z43: =IF(Y43, COUNTIF($Y$2:Y43, TRUE), "") | AA43: =IFERROR(IF(ISNUMBER(SEARCH("Not Relevant",J43)),0,VALUE(G43)),"") -> 20 | AB43: =IFERROR(SUMIF($D:$D,D43,$AA:$AA),"") -> 100 | AC43: =IF(OR(AB43=0,AB43=""),"",AA43/AB43) -> 0.2 | AD43: =IF(OR(N43="",AC43=""),"",VALUE(N43)*AC43) | AE43: =IFERROR(ISNUMBER(SEARCH("Not Relevant",J43)),FALSE) -> FALSE | AF43: =IF(OR(H43="",J43=""),FALSE,IF(H43<>J43,TRUE,FALSE)) -> FALSE | AG43: =IF(AF43, COUNTIF($AF$2:AF43, TRUE), "")
A44: Individual reporters’ data are kept confidential and used for statistical purposes only | B44: 1 | C44: 1_4 | D44: 1_4_1 | E44: 1_4_1_2 | F44: Is the identification risk of individual respondents assessed and managed? | G44: 20 | J44: =IF(H44="","",H44) | L44: UN NQAF (7.6) The identification risk of individual respondents is assessed and managed. European Statistical Code of Practice Principle 5 | M44: =IFERROR(INDEX(__key!$D:$D,MATCH(O44&"|"&SUBSTITUTE(H44,",",";"), __key!$E:$E, 0)), "") | N44: =IFERROR(INDEX(__key!$D:$D,MATCH(O44&"|"&SUBSTITUTE(J44,",",";"), __key!$E:$E, 0)), "") | O44: BP | Q44: Statistical confidentiality and data security are assured | R44: 1412 | S44: =IFERROR(1*M44,0) -> 0 | T44: =IFERROR(1*N44,0) -> 0 | U44: =IFERROR(IF(ISNUMBER(SEARCH("Not Relevant",H44)),0,VALUE(G44)),"") -> 20 | V44: =IFERROR(SUMIF($D:$D,D44,$U:$U),"") -> 100 | W44: =IF(OR(V44=0,V44=""),"",U44/V44) -> 0.2 | X44: =IF(OR(M44="",W44=""),"",VALUE(M44)*W44) | Y44: =IFERROR(ISNUMBER(SEARCH("Not Relevant",H44)),FALSE) -> FALSE | Z44: =IF(Y44, COUNTIF($Y$2:Y44, TRUE), "") | AA44: =IFERROR(IF(ISNUMBER(SEARCH("Not Relevant",J44)),0,VALUE(G44)),"") -> 20 | AB44: =IFERROR(SUMIF($D:$D,D44,$AA:$AA),"") -> 100 | AC44: =IF(OR(AB44=0,AB44=""),"",AA44/AB44) -> 0.2 | AD44: =IF(OR(N44="",AC44=""),"",VALUE(N44)*AC44) | AE44: =IFERROR(ISNUMBER(SEARCH("Not Relevant",J44)),FALSE) -> FALSE | AF44: =IF(OR(H44="",J44=""),FALSE,IF(H44<>J44,TRUE,FALSE)) -> FALSE | AG44: =IF(AF44, COUNTIF($AF$2:AF44, TRUE), "")
A45: Individual reporters’ data are kept confidential and used for statistical purposes only | B45: 1 | C45: 1_4 | D45: 1_4_1 | E45: 1_4_1_3 | F45: Is statistical confidentiality explicitly guaranteed by law or an equivalent legal instrument? | G45: 20 | J45: =IF(H45="","",H45) | L45: UN NQAF (7.1) / UN Fundamental Principle #6: Legal provisions ensuring confidentiality encourage accurate responses from data providers and maintain trust in official statistics. European Statistical Code of Practice Principle 5 | M45: =IFERROR(INDEX(__key!$D:$D,MATCH(O45&"|"&SUBSTITUTE(H45,",",";"), __key!$E:$E, 0)), "") | N45: =IFERROR(INDEX(__key!$D:$D,MATCH(O45&"|"&SUBSTITUTE(J45,",",";"), __key!$E:$E, 0)), "") | O45: BP | Q45: Statistical confidentiality and data security are assured | R45: 1413 | S45: =IFERROR(1*M45,0) -> 0 | T45: =IFERROR(1*N45,0) -> 0 | U45: =IFERROR(IF(ISNUMBER(SEARCH("Not Relevant",H45)),0,VALUE(G45)),"") -> 20 | V45: =IFERROR(SUMIF($D:$D,D45,$U:$U),"") -> 100 | W45: =IF(OR(V45=0,V45=""),"",U45/V45) -> 0.2 | X45: =IF(OR(M45="",W45=""),"",VALUE(M45)*W45) | Y45: =IFERROR(ISNUMBER(SEARCH("Not Relevant",H45)),FALSE) -> FALSE | Z45: =IF(Y45, COUNTIF($Y$2:Y45, TRUE), "") | AA45: =IFERROR(IF(ISNUMBER(SEARCH("Not Relevant",J45)),0,VALUE(G45)),"") -> 20 | AB45: =IFERROR(SUMIF($D:$D,D45,$AA:$AA),"") -> 100 | AC45: =IF(OR(AB45=0,AB45=""),"",AA45/AB45) -> 0.2 | AD45: =IF(OR(N45="",AC45=""),"",VALUE(N45)*AC45) | AE45: =IFERROR(ISNUMBER(SEARCH("Not Relevant",J45)),FALSE) -> FALSE | AF45: =IF(OR(H45="",J45=""),FALSE,IF(H45<>J45,TRUE,FALSE)) -> FALSE | AG45: =IF(AF45, COUNTIF($AF$2:AF45, TRUE), "")
A46: Individual reporters’ data are kept confidential and used for statistical purposes only | B46: 1 | C46: 1_4 | D46: 1_4_1 | E46: 1_4_1_4 | F46: Are the data collected by the national statistical system used exclusively for statistical purposes, and not shared with other authorities including for enforcement, regulatory or administrative decisions? | G46: 20 | J46: =IF(H46="","",H46) | L46: Confidentiality provisions must be robust; no data sharing with third parties for non-statistical use (Articles 3.1(f), 20–21 GLOS). European Statistical Code of Practice Principle 5 | M46: =IFERROR(INDEX(__key!$D:$D,MATCH(O46&"|"&SUBSTITUTE(H46,",",";"), __key!$E:$E, 0)), "") | N46: =IFERROR(INDEX(__key!$D:$D,MATCH(O46&"|"&SUBSTITUTE(J46,",",";"), __key!$E:$E, 0)), "") | O46: BP | Q46: Statistical confidentiality and data security are assured | R46: 1414 | S46: =IFERROR(1*M46,0) -> 0 | T46: =IFERROR(1*N46,0) -> 0 | U46: =IFERROR(IF(ISNUMBER(SEARCH("Not Relevant",H46)),0,VALUE(G46)),"") -> 20 | V46: =IFERROR(SUMIF($D:$D,D46,$U:$U),"") -> 100 | W46: =IF(OR(V46=0,V46=""),"",U46/V46) -> 0.2 | X46: =IF(OR(M46="",W46=""),"",VALUE(M46)*W46) | Y46: =IFERROR(ISNUMBER(SEARCH("Not Relevant",H46)),FALSE) -> FALSE | Z46: =IF(Y46, COUNTIF($Y$2:Y46, TRUE), "") | AA46: =IFERROR(IF(ISNUMBER(SEARCH("Not Relevant",J46)),0,VALUE(G46)),"") -> 20 | AB46: =IFERROR(SUMIF($D:$D,D46,$AA:$AA),"") -> 100 | AC46: =IF(OR(AB46=0,AB46=""),"",AA46/AB46) -> 0.2 | AD46: =IF(OR(N46="",AC46=""),"",VALUE(N46)*AC46) | AE46: =IFERROR(ISNUMBER(SEARCH("Not Relevant",J46)),FALSE) -> FALSE | AF46: =IF(OR(H46="",J46=""),FALSE,IF(H46<>J46,TRUE,FALSE)) -> FALSE | AG46: =IF(AF46, COUNTIF($AF$2:AF46, TRUE), "")
A47: Individual reporters’ data are kept confidential and used for statistical purposes only | B47: 1 | C47: 1_4 | D47: 1_4_1 | E47: 1_4_1_5 | F47: Are there documented standards, guidelines, and procedures to ensure statistical confidentiality is applied consistently across the agency’s data handling processes? | G47: 20 | J47: =IF(H47="","",H47) | L47: UN NQAF (7.2): Best practice includes formal rules on data protection, staff training on confidentiality, and robust IT security measures. European Statistical Code of Practice Principle 5 | M47: =IFERROR(INDEX(__key!$D:$D,MATCH(O47&"|"&SUBSTITUTE(H47,",",";"), __key!$E:$E, 0)), "") | N47: =IFERROR(INDEX(__key!$D:$D,MATCH(O47&"|"&SUBSTITUTE(J47,",",";"), __key!$E:$E, 0)), "") | O47: SGPP | Q47: Statistical confidentiality and data security are assured | R47: 1415 | S47: =IFERROR(1*M47,0) -> 0 | T47: =IFERROR(1*N47,0) -> 0 | U47: =IFERROR(IF(ISNUMBER(SEARCH("Not Relevant",H47)),0,VALUE(G47)),"") -> 20 | V47: =IFERROR(SUMIF($D:$D,D47,$U:$U),"") -> 100 | W47: =IF(OR(V47=0,V47=""),"",U47/V47) -> 0.2 | X47: =IF(OR(M47="",W47=""),"",VALUE(M47)*W47) | Y47: =IFERROR(ISNUMBER(SEARCH("Not Relevant",H47)),FALSE) -> FALSE | Z47: =IF(Y47, COUNTIF($Y$2:Y47, TRUE), "") | AA47: =IFERROR(IF(ISNUMBER(SEARCH("Not Relevant",J47)),0,VALUE(G47)),"") -> 20 | AB47: =IFERROR(SUMIF($D:$D,D47,$AA:$AA),"") -> 100 | AC47: =IF(OR(AB47=0,AB47=""),"",AA47/AB47) -> 0.2 | AD47: =IF(OR(N47="",AC47=""),"",VALUE(N47)*AC47) | AE47: =IFERROR(ISNUMBER(SEARCH("Not Relevant",J47)),FALSE) -> FALSE | AF47: =IF(OR(H47="",J47=""),FALSE,IF(H47<>J47,TRUE,FALSE)) -> FALSE | AG47: =IF(AF47, COUNTIF($AF$2:AF47, TRUE), "")
F48: Access to data is restricted to individuals who require access to carry out their statistical functions.
A49: Access to data is restricted to individuals who require access to carry out their statistical functions. | B49: 1 | C49: 1_4 | D49: 1_4_2 | E49: 1_4_2_1 | F49: Is access to individual data restricted to staff who require the information in the performance of their statistical duties? | G49: 15 | J49: =IF(H49="","",H49) | L49: European Statistical Code of Practice Principle 5 | M49: =IFERROR(INDEX(__key!$D:$D,MATCH(O49&"|"&SUBSTITUTE(H49,",",";"), __key!$E:$E, 0)), "") | N49: =IFERROR(INDEX(__key!$D:$D,MATCH(O49&"|"&SUBSTITUTE(J49,",",";"), __key!$E:$E, 0)), "") | O49: BP | Q49: Statistical confidentiality and data security are assured | R49: 1421 | S49: =IFERROR(1*M49,0) -> 0 | T49: =IFERROR(1*N49,0) -> 0 | U49: =IFERROR(IF(ISNUMBER(SEARCH("Not Relevant",H49)),0,VALUE(G49)),"") -> 15 | V49: =IFERROR(SUMIF($D:$D,D49,$U:$U),"") -> 70 | W49: =IF(OR(V49=0,V49=""),"",U49/V49) -> 0.21428571 | X49: =IF(OR(M49="",W49=""),"",VALUE(M49)*W49) | Y49: =IFERROR(ISNUMBER(SEARCH("Not Relevant",H49)),FALSE) -> FALSE | Z49: =IF(Y49, COUNTIF($Y$2:Y49, TRUE), "") | AA49: =IFERROR(IF(ISNUMBER(SEARCH("Not Relevant",J49)),0,VALUE(G49)),"") -> 15 | AB49: =IFERROR(SUMIF($D:$D,D49,$AA:$AA),"") -> 70 | AC49: =IF(OR(AB49=0,AB49=""),"",AA49/AB49) -> 0.21428571 | AD49: =IF(OR(N49="",AC49=""),"",VALUE(N49)*AC49) | AE49: =IFERROR(ISNUMBER(SEARCH("Not Relevant",J49)),FALSE) -> FALSE | AF49: =IF(OR(H49="",J49=""),FALSE,IF(H49<>J49,TRUE,FALSE)) -> FALSE | AG49: =IF(AF49, COUNTIF($AF$2:AF49, TRUE), "")
A50: Access to data is restricted to individuals who require access to carry out their statistical functions. | B50: 1 | C50: 1_4 | D50: 1_4_2 | E50: 1_4_2_2 | F50: Are special aggregation rules used to prevent residual disclosure when aggregations of survey or other confidential data are disseminated? | G50: 15 | J50: =IF(H50="","",H50) | L50: European Statistical Code of Practice Principle 5 | M50: =IFERROR(INDEX(__key!$D:$D,MATCH(O50&"|"&SUBSTITUTE(H50,",",";"), __key!$E:$E, 0)), "") | N50: =IFERROR(INDEX(__key!$D:$D,MATCH(O50&"|"&SUBSTITUTE(J50,",",";"), __key!$E:$E, 0)), "") | O50: BP | Q50: Statistical confidentiality and data security are assured | R50: 1422 | S50: =IFERROR(1*M50,0) -> 0 | T50: =IFERROR(1*N50,0) -> 0 | U50: =IFERROR(IF(ISNUMBER(SEARCH("Not Relevant",H50)),0,VALUE(G50)),"") -> 15 | V50: =IFERROR(SUMIF($D:$D,D50,$U:$U),"") -> 70 | W50: =IF(OR(V50=0,V50=""),"",U50/V50) -> 0.21428571 | X50: =IF(OR(M50="",W50=""),"",VALUE(M50)*W50) | Y50: =IFERROR(ISNUMBER(SEARCH("Not Relevant",H50)),FALSE) -> FALSE | Z50: =IF(Y50, COUNTIF($Y$2:Y50, TRUE), "") | AA50: =IFERROR(IF(ISNUMBER(SEARCH("Not Relevant",J50)),0,VALUE(G50)),"") -> 15 | AB50: =IFERROR(SUMIF($D:$D,D50,$AA:$AA),"") -> 70 | AC50: =IF(OR(AB50=0,AB50=""),"",AA50/AB50) -> 0.21428571 | AD50: =IF(OR(N50="",AC50=""),"",VALUE(N50)*AC50) | AE50: =IFERROR(ISNUMBER(SEARCH("Not Relevant",J50)),FALSE) -> FALSE | AF50: =IF(OR(H50="",J50=""),FALSE,IF(H50<>J50,TRUE,FALSE)) -> FALSE | AG50: =IF(AF50, COUNTIF($AF$2:AF50, TRUE), "")
A51: Access to data is restricted to individuals who require access to carry out their statistical functions. | B51: 1 | C51: 1_4 | D51: 1_4_2 | E51: 1_4_2_3 | F51: Do staff review all data prepared for dissemination for possible indirect disclosure (residual disclosure) of individual data and design tables and outputs in a way that prevents disclosure. | G51: 15 | J51: =IF(H51="","",H51) | L51: European Statistical Code of Practice Principle 5 | M51: =IFERROR(INDEX(__key!$D:$D,MATCH(O51&"|"&SUBSTITUTE(H51,",",";"), __key!$E:$E, 0)), "") | N51: =IFERROR(INDEX(__key!$D:$D,MATCH(O51&"|"&SUBSTITUTE(J51,",",";"), __key!$E:$E, 0)), "") | O51: BP | Q51: Statistical confidentiality and data security are assured | R51: 1423 | S51: =IFERROR(1*M51,0) -> 0 | T51: =IFERROR(1*N51,0) -> 0 | U51: =IFERROR(IF(ISNUMBER(SEARCH("Not Relevant",H51)),0,VALUE(G51)),"") -> 15 | V51: =IFERROR(SUMIF($D:$D,D51,$U:$U),"") -> 70 | W51: =IF(OR(V51=0,V51=""),"",U51/V51) -> 0.21428571 | X51: =IF(OR(M51="",W51=""),"",VALUE(M51)*W51) | Y51: =IFERROR(ISNUMBER(SEARCH("Not Relevant",H51)),FALSE) -> FALSE | Z51: =IF(Y51, COUNTIF($Y$2:Y51, TRUE), "") | AA51: =IFERROR(IF(ISNUMBER(SEARCH("Not Relevant",J51)),0,VALUE(G51)),"") -> 15 | AB51: =IFERROR(SUMIF($D:$D,D51,$AA:$AA),"") -> 70 | AC51: =IF(OR(AB51=0,AB51=""),"",AA51/AB51) -> 0.21428571 | AD51: =IF(OR(N51="",AC51=""),"",VALUE(N51)*AC51) | AE51: =IFERROR(ISNUMBER(SEARCH("Not Relevant",J51)),FALSE) -> FALSE | AF51: =IF(OR(H51="",J51=""),FALSE,IF(H51<>J51,TRUE,FALSE)) -> FALSE | AG51: =IF(AF51, COUNTIF($AF$2:AF51, TRUE), "")
A52: Access to data is restricted to individuals who require access to carry out their statistical functions. | B52: 1 | C52: 1_4 | D52: 1_4_2 | E52: 1_4_2_4 | F52: Do data retention policies exist, are they followed and is compliance monitored? | G52: 5 | J52: =IF(H52="","",H52) | L52: European Statistical Code of Practice Principle 5 | M52: =IFERROR(INDEX(__key!$D:$D,MATCH(O52&"|"&SUBSTITUTE(H52,",",";"), __key!$E:$E, 0)), "") | N52: =IFERROR(INDEX(__key!$D:$D,MATCH(O52&"|"&SUBSTITUTE(J52,",",";"), __key!$E:$E, 0)), "") | O52: SGPP | Q52: Statistical confidentiality and data security are assured | R52: 1424 | S52: =IFERROR(1*M52,0) -> 0 | T52: =IFERROR(1*N52,0) -> 0 | U52: =IFERROR(IF(ISNUMBER(SEARCH("Not Relevant",H52)),0,VALUE(G52)),"") -> 5 | V52: =IFERROR(SUMIF($D:$D,D52,$U:$U),"") -> 70 | W52: =IF(OR(V52=0,V52=""),"",U52/V52) -> 0.071428571 | X52: =IF(OR(M52="",W52=""),"",VALUE(M52)*W52) | Y52: =IFERROR(ISNUMBER(SEARCH("Not Relevant",H52)),FALSE) -> FALSE | Z52: =IF(Y52, COUNTIF($Y$2:Y52, TRUE), "") | AA52: =IFERROR(IF(ISNUMBER(SEARCH("Not Relevant",J52)),0,VALUE(G52)),"") -> 5 | AB52: =IFERROR(SUMIF($D:$D,D52,$AA:$AA),"") -> 70 | AC52: =IF(OR(AB52=0,AB52=""),"",AA52/AB52) -> 0.071428571 | AD52: =IF(OR(N52="",AC52=""),"",VALUE(N52)*AC52) | AE52: =IFERROR(ISNUMBER(SEARCH("Not Relevant",J52)),FALSE) -> FALSE | AF52: =IF(OR(H52="",J52=""),FALSE,IF(H52<>J52,TRUE,FALSE)) -> FALSE | AG52: =IF(AF52, COUNTIF($AF$2:AF52, TRUE), "")
A53: Access to data is restricted to individuals who require access to carry out their statistical functions. | B53: 1 | C53: 1_4 | D53: 1_4_2 | E53: 1_4_2_5 | F53: Are staff required to sign a confidentiality form as part of their terms of employment? | G53: 10 | J53: =IF(H53="","",H53) | L53: European Statistical Code of Practice Principle 5 | M53: =IFERROR(INDEX(__key!$D:$D,MATCH(O53&"|"&SUBSTITUTE(H53,",",";"), __key!$E:$E, 0)), "") | N53: =IFERROR(INDEX(__key!$D:$D,MATCH(O53&"|"&SUBSTITUTE(J53,",",";"), __key!$E:$E, 0)), "") | O53: BP | Q53: Statistical confidentiality and data security are assured | R53: 1425 | S53: =IFERROR(1*M53,0) -> 0 | T53: =IFERROR(1*N53,0) -> 0 | U53: =IFERROR(IF(ISNUMBER(SEARCH("Not Relevant",H53)),0,VALUE(G53)),"") -> 10 | V53: =IFERROR(SUMIF($D:$D,D53,$U:$U),"") -> 70 | W53: =IF(OR(V53=0,V53=""),"",U53/V53) -> 0.14285714 | X53: =IF(OR(M53="",W53=""),"",VALUE(M53)*W53) | Y53: =IFERROR(ISNUMBER(SEARCH("Not Relevant",H53)),FALSE) -> FALSE | Z53: =IF(Y53, COUNTIF($Y$2:Y53, TRUE), "") | AA53: =IFERROR(IF(ISNUMBER(SEARCH("Not Relevant",J53)),0,VALUE(G53)),"") -> 10 | AB53: =IFERROR(SUMIF($D:$D,D53,$AA:$AA),"") -> 70 | AC53: =IF(OR(AB53=0,AB53=""),"",AA53/AB53) -> 0.14285714 | AD53: =IF(OR(N53="",AC53=""),"",VALUE(N53)*AC53) | AE53: =IFERROR(ISNUMBER(SEARCH("Not Relevant",J53)),FALSE) -> FALSE | AF53: =IF(OR(H53="",J53=""),FALSE,IF(H53<>J53,TRUE,FALSE)) -> FALSE | AG53: =IF(AF53, COUNTIF($AF$2:AF53, TRUE), "")
A54: Access to data is restricted to individuals who require access to carry out their statistical functions. | B54: 1 | C54: 1_4 | D54: 1_4_2 | E54: 1_4_2_6 | F54: Do strict protocols govern microdata access for research or statistical purposes, ensuring confidentiality safeguards (e.g., secure on-site facilities, anonymization protocols)? | G54: 10 | J54: =IF(H54="","",H54) | L54: UN NQAF (7.3): Agencies that provide microdata should have written policies specifying conditions for access, data security, and mandatory confidentiality agreements; European Statistical Code of Practice Principle 5 | M54: =IFERROR(INDEX(__key!$D:$D,MATCH(O54&"|"&SUBSTITUTE(H54,",",";"), __key!$E:$E, 0)), "") | N54: =IFERROR(INDEX(__key!$D:$D,MATCH(O54&"|"&SUBSTITUTE(J54,",",";"), __key!$E:$E, 0)), "") | O54: BPNR | Q54: Statistical confidentiality and data security are assured | R54: 1426 | S54: =IFERROR(1*M54,0) -> 0 | T54: =IFERROR(1*N54,0) -> 0 | U54: =IFERROR(IF(ISNUMBER(SEARCH("Not Relevant",H54)),0,VALUE(G54)),"") -> 10 | V54: =IFERROR(SUMIF($D:$D,D54,$U:$U),"") -> 70 | W54: =IF(OR(V54=0,V54=""),"",U54/V54) -> 0.14285714 | X54: =IF(OR(M54="",W54=""),"",VALUE(M54)*W54) | Y54: =IFERROR(ISNUMBER(SEARCH("Not Relevant",H54)),FALSE) -> FALSE | Z54: =IF(Y54, COUNTIF($Y$2:Y54, TRUE), "") | AA54: =IFERROR(IF(ISNUMBER(SEARCH("Not Relevant",J54)),0,VALUE(G54)),"") -> 10 | AB54: =IFERROR(SUMIF($D:$D,D54,$AA:$AA),"") -> 70 | AC54: =IF(OR(AB54=0,AB54=""),"",AA54/AB54) -> 0.14285714 | AD54: =IF(OR(N54="",AC54=""),"",VALUE(N54)*AC54) | AE54: =IFERROR(ISNUMBER(SEARCH("Not Relevant",J54)),FALSE) -> FALSE | AF54: =IF(OR(H54="",J54=""),FALSE,IF(H54<>J54,TRUE,FALSE)) -> FALSE | AG54: =IF(AF54, COUNTIF($AF$2:AF54, TRUE), "")
F55: Penalties are prescribed for willful breaches of statistical confidentiality
A56: Penalties are prescribed for willful breaches of statistical confidentiality | B56: 1 | C56: 1_4 | D56: 1_4_3 | E56: 1_4_3_1 | F56: Are penalties prescribed for willful breaches of statistical confidentiality, and are these penalties well-known (e.g., in legislation or agency policies)? | G56: 10 | J56: =IF(H56="","",H56) | L56: UN NQAF (7.4) / IMF DQAF: Clear legal/administrative penalties help deter unauthorized data disclosure and reinforce the agency’s commitment to confidentiality; European Statistical Code of Practice Principle 5 | M56: =IFERROR(INDEX(__key!$D:$D,MATCH(O56&"|"&SUBSTITUTE(H56,",",";"), __key!$E:$E, 0)), "") | N56: =IFERROR(INDEX(__key!$D:$D,MATCH(O56&"|"&SUBSTITUTE(J56,",",";"), __key!$E:$E, 0)), "") | O56: BP | Q56: Statistical confidentiality and data security are assured | R56: 1431 | S56: =IFERROR(1*M56,0) -> 0 | T56: =IFERROR(1*N56,0) -> 0 | U56: =IFERROR(IF(ISNUMBER(SEARCH("Not Relevant",H56)),0,VALUE(G56)),"") -> 10 | V56: =IFERROR(SUMIF($D:$D,D56,$U:$U),"") -> 15 | W56: =IF(OR(V56=0,V56=""),"",U56/V56) -> 0.66666667 | X56: =IF(OR(M56="",W56=""),"",VALUE(M56)*W56) | Y56: =IFERROR(ISNUMBER(SEARCH("Not Relevant",H56)),FALSE) -> FALSE | Z56: =IF(Y56, COUNTIF($Y$2:Y56, TRUE), "") | AA56: =IFERROR(IF(ISNUMBER(SEARCH("Not Relevant",J56)),0,VALUE(G56)),"") -> 10 | AB56: =IFERROR(SUMIF($D:$D,D56,$AA:$AA),"") -> 15 | AC56: =IF(OR(AB56=0,AB56=""),"",AA56/AB56) -> 0.66666667 | AD56: =IF(OR(N56="",AC56=""),"",VALUE(N56)*AC56) | AE56: =IFERROR(ISNUMBER(SEARCH("Not Relevant",J56)),FALSE) -> FALSE | AF56: =IF(OR(H56="",J56=""),FALSE,IF(H56<>J56,TRUE,FALSE)) -> FALSE | AG56: =IF(AF56, COUNTIF($AF$2:AF56, TRUE), "")
A57: Penalties are prescribed for willful breaches of statistical confidentiality | B57: 1 | C57: 1_4 | D57: 1_4_3 | E57: 1_4_3_2 | F57: Does the law or relevant organizational policy have provisions that ensure secure data processing/storage? | G57: 5 | J57: =IF(H57="","",H57) | L57: Violations are punishable; producers must protect data from unauthorized access; rules for secure microdata access for research (Articles 22–26, 35 GLOS); European Statistical Code of Practice Principle 5 | M57: =IFERROR(INDEX(__key!$D:$D,MATCH(O57&"|"&SUBSTITUTE(H57,",",";"), __key!$E:$E, 0)), "") | N57: =IFERROR(INDEX(__key!$D:$D,MATCH(O57&"|"&SUBSTITUTE(J57,",",";"), __key!$E:$E, 0)), "") | O57: BP | Q57: Statistical confidentiality and data security are assured | R57: 1432 | S57: =IFERROR(1*M57,0) -> 0 | T57: =IFERROR(1*N57,0) -> 0 | U57: =IFERROR(IF(ISNUMBER(SEARCH("Not Relevant",H57)),0,VALUE(G57)),"") -> 5 | V57: =IFERROR(SUMIF($D:$D,D57,$U:$U),"") -> 15 | W57: =IF(OR(V57=0,V57=""),"",U57/V57) -> 0.33333333 | X57: =IF(OR(M57="",W57=""),"",VALUE(M57)*W57) | Y57: =IFERROR(ISNUMBER(SEARCH("Not Relevant",H57)),FALSE) -> FALSE | Z57: =IF(Y57, COUNTIF($Y$2:Y57, TRUE), "") | AA57: =IFERROR(IF(ISNUMBER(SEARCH("Not Relevant",J57)),0,VALUE(G57)),"") -> 5 | AB57: =IFERROR(SUMIF($D:$D,D57,$AA:$AA),"") -> 15 | AC57: =IF(OR(AB57=0,AB57=""),"",AA57/AB57) -> 0.33333333 | AD57: =IF(OR(N57="",AC57=""),"",VALUE(N57)*AC57) | AE57: =IFERROR(ISNUMBER(SEARCH("Not Relevant",J57)),FALSE) -> FALSE | AF57: =IF(OR(H57="",J57=""),FALSE,IF(H57<>J57,TRUE,FALSE)) -> FALSE | AG57: =IF(AF57, COUNTIF($AF$2:AF57, TRUE), "")
F58: Response burden on data providers is minimized
A59: Response burden on data providers is minimized | B59: 1 | C59: 1_5 | D59: 1_5_1 | E59: 1_5_1_1 | F59: Does the producing agency carefully consider response burden and actively pursue alternative avenues to obtain data through non-survey modalities? | G59: 25 | J59: =IF(H59="","",H59) | L59: European Statistical Code of Practice Principle 9 | M59: =IFERROR(INDEX(__key!$D:$D,MATCH(O59&"|"&SUBSTITUTE(H59,",",";"), __key!$E:$E, 0)), "") | N59: =IFERROR(INDEX(__key!$D:$D,MATCH(O59&"|"&SUBSTITUTE(J59,",",";"), __key!$E:$E, 0)), "") | O59: BP | Q59: Response burden is minimized | R59: 1511 | S59: =IFERROR(1*M59,0) -> 0 | T59: =IFERROR(1*N59,0) -> 0 | U59: =IFERROR(IF(ISNUMBER(SEARCH("Not Relevant",H59)),0,VALUE(G59)),"") -> 25 | V59: =IFERROR(SUMIF($D:$D,D59,$U:$U),"") -> 45 | W59: =IF(OR(V59=0,V59=""),"",U59/V59) -> 0.55555556 | X59: =IF(OR(M59="",W59=""),"",VALUE(M59)*W59) | Y59: =IFERROR(ISNUMBER(SEARCH("Not Relevant",H59)),FALSE) -> FALSE | Z59: =IF(Y59, COUNTIF($Y$2:Y59, TRUE), "") | AA59: =IFERROR(IF(ISNUMBER(SEARCH("Not Relevant",J59)),0,VALUE(G59)),"") -> 25 | AB59: =IFERROR(SUMIF($D:$D,D59,$AA:$AA),"") -> 45 | AC59: =IF(OR(AB59=0,AB59=""),"",AA59/AB59) -> 0.55555556 | AD59: =IF(OR(N59="",AC59=""),"",VALUE(N59)*AC59) | AE59: =IFERROR(ISNUMBER(SEARCH("Not Relevant",J59)),FALSE) -> FALSE | AF59: =IF(OR(H59="",J59=""),FALSE,IF(H59<>J59,TRUE,FALSE)) -> FALSE | AG59: =IF(AF59, COUNTIF($AF$2:AF59, TRUE), "")
A60: Response burden on data providers is minimized | B60: 1 | C60: 1_5 | D60: 1_5_1 | E60: 1_5_1_2 | F60: Does the data producing agency provide assistance to respondents with completing and submitting forms and clearly states the purpose and authority under which collection is being undertaken. | G60: 10 | J60: =IF(H60="","",H60) | L60: European Statistical Code of Practice Principle 9 | M60: =IFERROR(INDEX(__key!$D:$D,MATCH(O60&"|"&SUBSTITUTE(H60,",",";"), __key!$E:$E, 0)), "") | N60: =IFERROR(INDEX(__key!$D:$D,MATCH(O60&"|"&SUBSTITUTE(J60,",",";"), __key!$E:$E, 0)), "") | O60: BP | Q60: Response burden is minimized | R60: 1512 | S60: =IFERROR(1*M60,0) -> 0 | T60: =IFERROR(1*N60,0) -> 0 | U60: =IFERROR(IF(ISNUMBER(SEARCH("Not Relevant",H60)),0,VALUE(G60)),"") -> 10 | V60: =IFERROR(SUMIF($D:$D,D60,$U:$U),"") -> 45 | W60: =IF(OR(V60=0,V60=""),"",U60/V60) -> 0.22222222 | X60: =IF(OR(M60="",W60=""),"",VALUE(M60)*W60) | Y60: =IFERROR(ISNUMBER(SEARCH("Not Relevant",H60)),FALSE) -> FALSE | Z60: =IF(Y60, COUNTIF($Y$2:Y60, TRUE), "") | AA60: =IFERROR(IF(ISNUMBER(SEARCH("Not Relevant",J60)),0,VALUE(G60)),"") -> 10 | AB60: =IFERROR(SUMIF($D:$D,D60,$AA:$AA),"") -> 45 | AC60: =IF(OR(AB60=0,AB60=""),"",AA60/AB60) -> 0.22222222 | AD60: =IF(OR(N60="",AC60=""),"",VALUE(N60)*AC60) | AE60: =IFERROR(ISNUMBER(SEARCH("Not Relevant",J60)),FALSE) -> FALSE | AF60: =IF(OR(H60="",J60=""),FALSE,IF(H60<>J60,TRUE,FALSE)) -> FALSE | AG60: =IF(AF60, COUNTIF($AF$2:AF60, TRUE), "")
A61: Response burden on data providers is minimized | B61: 1 | C61: 1_5 | D61: 1_5_1 | E61: 1_5_1_3 | F61: Does the data-producing agency seek to secure cooperation by creating goodwill through registering and dealing with respondents’ complaints, indicating the purpose of the data collection, informing respondents of measures to limit response burden, raising awareness of the importance of good quality statistics, and providing respondents with data upon request? | G61: 10 | J61: =IF(H61="","",H61) | L61: European Statistical Code of Practice Principle 9 | M61: =IFERROR(INDEX(__key!$D:$D,MATCH(O61&"|"&SUBSTITUTE(H61,",",";"), __key!$E:$E, 0)), "") | N61: =IFERROR(INDEX(__key!$D:$D,MATCH(O61&"|"&SUBSTITUTE(J61,",",";"), __key!$E:$E, 0)), "") | O61: BP | Q61: Response burden is minimized | R61: 1513 | S61: =IFERROR(1*M61,0) -> 0 | T61: =IFERROR(1*N61,0) -> 0 | U61: =IFERROR(IF(ISNUMBER(SEARCH("Not Relevant",H61)),0,VALUE(G61)),"") -> 10 | V61: =IFERROR(SUMIF($D:$D,D61,$U:$U),"") -> 45 | W61: =IF(OR(V61=0,V61=""),"",U61/V61) -> 0.22222222 | X61: =IF(OR(M61="",W61=""),"",VALUE(M61)*W61) | Y61: =IFERROR(ISNUMBER(SEARCH("Not Relevant",H61)),FALSE) -> FALSE | Z61: =IF(Y61, COUNTIF($Y$2:Y61, TRUE), "") | AA61: =IFERROR(IF(ISNUMBER(SEARCH("Not Relevant",J61)),0,VALUE(G61)),"") -> 10 | AB61: =IFERROR(SUMIF($D:$D,D61,$AA:$AA),"") -> 45 | AC61: =IF(OR(AB61=0,AB61=""),"",AA61/AB61) -> 0.22222222 | AD61: =IF(OR(N61="",AC61=""),"",VALUE(N61)*AC61) | AE61: =IFERROR(ISNUMBER(SEARCH("Not Relevant",J61)),FALSE) -> FALSE | AF61: =IF(OR(H61="",J61=""),FALSE,IF(H61<>J61,TRUE,FALSE)) -> FALSE | AG61: =IF(AF61, COUNTIF($AF$2:AF61, TRUE), "")
F62: Staffing levels are commensurate with the scope of the statistical program(s) managed by the organization.
A63: Staffing levels are commensurate with the scope of the statistical program(s) managed by the organization. | B63: 1 | C63: 1_6 | D63: 1_6_1 | E63: 1_6_1_1 | F63: How many staff are working in this institution? | J63: =IF(H63="","",H63) | L63: European Statistical Code of Practice Principle 3 | M63: =IFERROR(INDEX(__key!$D:$D,MATCH(O63&"|"&SUBSTITUTE(H63,",",";"), __key!$E:$E, 0)), "") | N63: =IFERROR(INDEX(__key!$D:$D,MATCH(O63&"|"&SUBSTITUTE(J63,",",";"), __key!$E:$E, 0)), "") | O63: NUM | Q63: Human resources are adequate | R63: 1611 | S63: =IFERROR(1*M63,0) -> 0 | T63: =IFERROR(1*N63,0) -> 0 | U63: =IFERROR(IF(ISNUMBER(SEARCH("Not Relevant",H63)),0,VALUE(G63)),"") -> 0 | V63: =IFERROR(SUMIF($D:$D,D63,$U:$U),"") -> 160 | W63: =IF(OR(V63=0,V63=""),"",U63/V63) -> 0 | X63: =IF(OR(M63="",W63=""),"",VALUE(M63)*W63) | Y63: =IFERROR(ISNUMBER(SEARCH("Not Relevant",H63)),FALSE) -> FALSE | Z63: =IF(Y63, COUNTIF($Y$2:Y63, TRUE), "") | AA63: =IFERROR(IF(ISNUMBER(SEARCH("Not Relevant",J63)),0,VALUE(G63)),"") -> 0 | AB63: =IFERROR(SUMIF($D:$D,D63,$AA:$AA),"") -> 160 | AC63: =IF(OR(AB63=0,AB63=""),"",AA63/AB63) -> 0 | AD63: =IF(OR(N63="",AC63=""),"",VALUE(N63)*AC63) | AE63: =IFERROR(ISNUMBER(SEARCH("Not Relevant",J63)),FALSE) -> FALSE | AF63: =IF(OR(H63="",J63=""),FALSE,IF(H63<>J63,TRUE,FALSE)) -> FALSE | AG63: =IF(AF63, COUNTIF($AF$2:AF63, TRUE), "")
A64: Staffing levels are commensurate with the scope of the statistical program(s) managed by the organization. | B64: 1 | C64: 1_6 | D64: 1_6_1 | E64: 1_6_1_2 | F64: Is the number of staff assigned to this statistical program(s) sufficient to meet the quality requirements (scope, timeliness, frequency, accuracy and reliability, serviceability, and accessibility) of the statistical program(s)? | G64: 10 | J64: =IF(H64="","",H64) | L64: European Statistical Code of Practice Principle 9 | M64: =IFERROR(INDEX(__key!$D:$D,MATCH(O64&"|"&SUBSTITUTE(H64,",",";"), __key!$E:$E, 0)), "") | N64: =IFERROR(INDEX(__key!$D:$D,MATCH(O64&"|"&SUBSTITUTE(J64,",",";"), __key!$E:$E, 0)), "") | O64: RES | Q64: Human resources are adequate | R64: 1612 | S64: =IFERROR(1*M64,0) -> 0 | T64: =IFERROR(1*N64,0) -> 0 | U64: =IFERROR(IF(ISNUMBER(SEARCH("Not Relevant",H64)),0,VALUE(G64)),"") -> 10 | V64: =IFERROR(SUMIF($D:$D,D64,$U:$U),"") -> 160 | W64: =IF(OR(V64=0,V64=""),"",U64/V64) -> 0.0625 | X64: =IF(OR(M64="",W64=""),"",VALUE(M64)*W64) | Y64: =IFERROR(ISNUMBER(SEARCH("Not Relevant",H64)),FALSE) -> FALSE | Z64: =IF(Y64, COUNTIF($Y$2:Y64, TRUE), "") | AA64: =IFERROR(IF(ISNUMBER(SEARCH("Not Relevant",J64)),0,VALUE(G64)),"") -> 10 | AB64: =IFERROR(SUMIF($D:$D,D64,$AA:$AA),"") -> 160 | AC64: =IF(OR(AB64=0,AB64=""),"",AA64/AB64) -> 0.0625 | AD64: =IF(OR(N64="",AC64=""),"",VALUE(N64)*AC64) | AE64: =IFERROR(ISNUMBER(SEARCH("Not Relevant",J64)),FALSE) -> FALSE | AF64: =IF(OR(H64="",J64=""),FALSE,IF(H64<>J64,TRUE,FALSE)) -> FALSE | AG64: =IF(AF64, COUNTIF($AF$2:AF64, TRUE), "")
A65: Staffing levels are commensurate with the scope of the statistical program(s) managed by the organization. | B65: 1 | C65: 1_6 | D65: 1_6_1 | E65: 1_6_1_3 | F65: Do staff qualifications and skills sufficiently cover the methodological and analytical needs of the statistical program(s)? | G65: 10 | J65: =IF(H65="","",H65) | L65: European Statistical Code of Practice Principle 9 | M65: =IFERROR(INDEX(__key!$D:$D,MATCH(O65&"|"&SUBSTITUTE(H65,",",";"), __key!$E:$E, 0)), "") | N65: =IFERROR(INDEX(__key!$D:$D,MATCH(O65&"|"&SUBSTITUTE(J65,",",";"), __key!$E:$E, 0)), "") | O65: RES | Q65: Human resources are adequate | R65: 1613 | S65: =IFERROR(1*M65,0) -> 0 | T65: =IFERROR(1*N65,0) -> 0 | U65: =IFERROR(IF(ISNUMBER(SEARCH("Not Relevant",H65)),0,VALUE(G65)),"") -> 10 | V65: =IFERROR(SUMIF($D:$D,D65,$U:$U),"") -> 160 | W65: =IF(OR(V65=0,V65=""),"",U65/V65) -> 0.0625 | X65: =IF(OR(M65="",W65=""),"",VALUE(M65)*W65) | Y65: =IFERROR(ISNUMBER(SEARCH("Not Relevant",H65)),FALSE) -> FALSE | Z65: =IF(Y65, COUNTIF($Y$2:Y65, TRUE), "") | AA65: =IFERROR(IF(ISNUMBER(SEARCH("Not Relevant",J65)),0,VALUE(G65)),"") -> 10 | AB65: =IFERROR(SUMIF($D:$D,D65,$AA:$AA),"") -> 160 | AC65: =IF(OR(AB65=0,AB65=""),"",AA65/AB65) -> 0.0625 | AD65: =IF(OR(N65="",AC65=""),"",VALUE(N65)*AC65) | AE65: =IFERROR(ISNUMBER(SEARCH("Not Relevant",J65)),FALSE) -> FALSE | AF65: =IF(OR(H65="",J65=""),FALSE,IF(H65<>J65,TRUE,FALSE)) -> FALSE | AG65: =IF(AF65, COUNTIF($AF$2:AF65, TRUE), "")
A66: Staffing levels are commensurate with the scope of the statistical program(s) managed by the organization. | B66: 1 | C66: 1_6 | D66: 1_6_1 | E66: 1_6_1_4 | F66: Does the responsible agency have an adequate number of statisticians to support the scope of the program? | G66: 15 | J66: =IF(H66="","",H66) | L66: European Statistical Code of Practice Principle 9 | M66: =IFERROR(INDEX(__key!$D:$D,MATCH(O66&"|"&SUBSTITUTE(H66,",",";"), __key!$E:$E, 0)), "") | N66: =IFERROR(INDEX(__key!$D:$D,MATCH(O66&"|"&SUBSTITUTE(J66,",",";"), __key!$E:$E, 0)), "") | O66: RESNR | Q66: Human resources are adequate | R66: 1614 | S66: =IFERROR(1*M66,0) -> 0 | T66: =IFERROR(1*N66,0) -> 0 | U66: =IFERROR(IF(ISNUMBER(SEARCH("Not Relevant",H66)),0,VALUE(G66)),"") -> 15 | V66: =IFERROR(SUMIF($D:$D,D66,$U:$U),"") -> 160 | W66: =IF(OR(V66=0,V66=""),"",U66/V66) -> 0.09375 | X66: =IF(OR(M66="",W66=""),"",VALUE(M66)*W66) | Y66: =IFERROR(ISNUMBER(SEARCH("Not Relevant",H66)),FALSE) -> FALSE | Z66: =IF(Y66, COUNTIF($Y$2:Y66, TRUE), "") | AA66: =IFERROR(IF(ISNUMBER(SEARCH("Not Relevant",J66)),0,VALUE(G66)),"") -> 15 | AB66: =IFERROR(SUMIF($D:$D,D66,$AA:$AA),"") -> 160 | AC66: =IF(OR(AB66=0,AB66=""),"",AA66/AB66) -> 0.09375 | AD66: =IF(OR(N66="",AC66=""),"",VALUE(N66)*AC66) | AE66: =IFERROR(ISNUMBER(SEARCH("Not Relevant",J66)),FALSE) -> FALSE | AF66: =IF(OR(H66="",J66=""),FALSE,IF(H66<>J66,TRUE,FALSE)) -> FALSE | AG66: =IF(AF66, COUNTIF($AF$2:AF66, TRUE), "")
A67: Staffing levels are commensurate with the scope of the statistical program(s) managed by the organization. | B67: 1 | C67: 1_6 | D67: 1_6_1 | E67: 1_6_1_5 | F67: Does the responsible agency have an adequate number of Geographic Information Systems (GIS) experts to support economic statistics needs (e.g., national accounts, price indices)? | G67: 5 | J67: =IF(H67="","",H67) | L67: European Statistical Code of Practice Principle 9 | M67: =IFERROR(INDEX(__key!$D:$D,MATCH(O67&"|"&SUBSTITUTE(H67,",",";"), __key!$E:$E, 0)), "") | N67: =IFERROR(INDEX(__key!$D:$D,MATCH(O67&"|"&SUBSTITUTE(J67,",",";"), __key!$E:$E, 0)), "") | O67: RESNR | Q67: Human resources are adequate | R67: 1615 | S67: =IFERROR(1*M67,0) -> 0 | T67: =IFERROR(1*N67,0) -> 0 | U67: =IFERROR(IF(ISNUMBER(SEARCH("Not Relevant",H67)),0,VALUE(G67)),"") -> 5 | V67: =IFERROR(SUMIF($D:$D,D67,$U:$U),"") -> 160 | W67: =IF(OR(V67=0,V67=""),"",U67/V67) -> 0.03125 | X67: =IF(OR(M67="",W67=""),"",VALUE(M67)*W67) | Y67: =IFERROR(ISNUMBER(SEARCH("Not Relevant",H67)),FALSE) -> FALSE | Z67: =IF(Y67, COUNTIF($Y$2:Y67, TRUE), "") | AA67: =IFERROR(IF(ISNUMBER(SEARCH("Not Relevant",J67)),0,VALUE(G67)),"") -> 5 | AB67: =IFERROR(SUMIF($D:$D,D67,$AA:$AA),"") -> 160 | AC67: =IF(OR(AB67=0,AB67=""),"",AA67/AB67) -> 0.03125 | AD67: =IF(OR(N67="",AC67=""),"",VALUE(N67)*AC67) | AE67: =IFERROR(ISNUMBER(SEARCH("Not Relevant",J67)),FALSE) -> FALSE | AF67: =IF(OR(H67="",J67=""),FALSE,IF(H67<>J67,TRUE,FALSE)) -> FALSE | AG67: =IF(AF67, COUNTIF($AF$2:AF67, TRUE), "")
A68: Staffing levels are commensurate with the scope of the statistical program(s) managed by the organization. | B68: 1 | C68: 1_6 | D68: 1_6_1 | E68: 1_6_1_6 | F68: Does the responsible agency have an adequate number of economists to support economic statistics needs (e.g., national accounts, price indices)? | G68: 5 | J68: =IF(H68="","",H68) | L68: European Statistical Code of Practice Principle 9 | M68: =IFERROR(INDEX(__key!$D:$D,MATCH(O68&"|"&SUBSTITUTE(H68,",",";"), __key!$E:$E, 0)), "") | N68: =IFERROR(INDEX(__key!$D:$D,MATCH(O68&"|"&SUBSTITUTE(J68,",",";"), __key!$E:$E, 0)), "") | O68: RESNR | Q68: Human resources are adequate | R68: 1616 | S68: =IFERROR(1*M68,0) -> 0 | T68: =IFERROR(1*N68,0) -> 0 | U68: =IFERROR(IF(ISNUMBER(SEARCH("Not Relevant",H68)),0,VALUE(G68)),"") -> 5 | V68: =IFERROR(SUMIF($D:$D,D68,$U:$U),"") -> 160 | W68: =IF(OR(V68=0,V68=""),"",U68/V68) -> 0.03125 | X68: =IF(OR(M68="",W68=""),"",VALUE(M68)*W68) | Y68: =IFERROR(ISNUMBER(SEARCH("Not Relevant",H68)),FALSE) -> FALSE | Z68: =IF(Y68, COUNTIF($Y$2:Y68, TRUE), "") | AA68: =IFERROR(IF(ISNUMBER(SEARCH("Not Relevant",J68)),0,VALUE(G68)),"") -> 5 | AB68: =IFERROR(SUMIF($D:$D,D68,$AA:$AA),"") -> 160 | AC68: =IF(OR(AB68=0,AB68=""),"",AA68/AB68) -> 0.03125 | AD68: =IF(OR(N68="",AC68=""),"",VALUE(N68)*AC68) | AE68: =IFERROR(ISNUMBER(SEARCH("Not Relevant",J68)),FALSE) -> FALSE | AF68: =IF(OR(H68="",J68=""),FALSE,IF(H68<>J68,TRUE,FALSE)) -> FALSE | AG68: =IF(AF68, COUNTIF($AF$2:AF68, TRUE), "")
A69: Staffing levels are commensurate with the scope of the statistical program(s) managed by the organization. | B69: 1 | C69: 1_6 | D69: 1_6_1 | E69: 1_6_1_7 | F69: Does the responsible agency have an adequate number of sociologists (or social science experts) to support social statistics (e.g., labor force surveys)? | G69: 5 | J69: =IF(H69="","",H69) | L69: European Statistical Code of Practice Principle 9 | M69: =IFERROR(INDEX(__key!$D:$D,MATCH(O69&"|"&SUBSTITUTE(H69,",",";"), __key!$E:$E, 0)), "") | N69: =IFERROR(INDEX(__key!$D:$D,MATCH(O69&"|"&SUBSTITUTE(J69,",",";"), __key!$E:$E, 0)), "") | O69: RESNR | Q69: Human resources are adequate | R69: 1617 | S69: =IFERROR(1*M69,0) -> 0 | T69: =IFERROR(1*N69,0) -> 0 | U69: =IFERROR(IF(ISNUMBER(SEARCH("Not Relevant",H69)),0,VALUE(G69)),"") -> 5 | V69: =IFERROR(SUMIF($D:$D,D69,$U:$U),"") -> 160 | W69: =IF(OR(V69=0,V69=""),"",U69/V69) -> 0.03125 | X69: =IF(OR(M69="",W69=""),"",VALUE(M69)*W69) | Y69: =IFERROR(ISNUMBER(SEARCH("Not Relevant",H69)),FALSE) -> FALSE | Z69: =IF(Y69, COUNTIF($Y$2:Y69, TRUE), "") | AA69: =IFERROR(IF(ISNUMBER(SEARCH("Not Relevant",J69)),0,VALUE(G69)),"") -> 5 | AB69: =IFERROR(SUMIF($D:$D,D69,$AA:$AA),"") -> 160 | AC69: =IF(OR(AB69=0,AB69=""),"",AA69/AB69) -> 0.03125 | AD69: =IF(OR(N69="",AC69=""),"",VALUE(N69)*AC69) | AE69: =IFERROR(ISNUMBER(SEARCH("Not Relevant",J69)),FALSE) -> FALSE | AF69: =IF(OR(H69="",J69=""),FALSE,IF(H69<>J69,TRUE,FALSE)) -> FALSE | AG69: =IF(AF69, COUNTIF($AF$2:AF69, TRUE), "")
A70: Staffing levels are commensurate with the scope of the statistical program(s) managed by the organization. | B70: 1 | C70: 1_6 | D70: 1_6_1 | E70: 1_6_1_8 | F70: Does the responsible agency have an adequate number of data scientists to handle new data sources (big data, administrative data) and advanced analytics? | G70: 5 | J70: =IF(H70="","",H70) | L70: European Statistical Code of Practice Principle 9 | M70: =IFERROR(INDEX(__key!$D:$D,MATCH(O70&"|"&SUBSTITUTE(H70,",",";"), __key!$E:$E, 0)), "") | N70: =IFERROR(INDEX(__key!$D:$D,MATCH(O70&"|"&SUBSTITUTE(J70,",",";"), __key!$E:$E, 0)), "") | O70: RESNR | Q70: Human resources are adequate | R70: 1618 | S70: =IFERROR(1*M70,0) -> 0 | T70: =IFERROR(1*N70,0) -> 0 | U70: =IFERROR(IF(ISNUMBER(SEARCH("Not Relevant",H70)),0,VALUE(G70)),"") -> 5 | V70: =IFERROR(SUMIF($D:$D,D70,$U:$U),"") -> 160 | W70: =IF(OR(V70=0,V70=""),"",U70/V70) -> 0.03125 | X70: =IF(OR(M70="",W70=""),"",VALUE(M70)*W70) | Y70: =IFERROR(ISNUMBER(SEARCH("Not Relevant",H70)),FALSE) -> FALSE | Z70: =IF(Y70, COUNTIF($Y$2:Y70, TRUE), "") | AA70: =IFERROR(IF(ISNUMBER(SEARCH("Not Relevant",J70)),0,VALUE(G70)),"") -> 5 | AB70: =IFERROR(SUMIF($D:$D,D70,$AA:$AA),"") -> 160 | AC70: =IF(OR(AB70=0,AB70=""),"",AA70/AB70) -> 0.03125 | AD70: =IF(OR(N70="",AC70=""),"",VALUE(N70)*AC70) | AE70: =IFERROR(ISNUMBER(SEARCH("Not Relevant",J70)),FALSE) -> FALSE | AF70: =IF(OR(H70="",J70=""),FALSE,IF(H70<>J70,TRUE,FALSE)) -> FALSE | AG70: =IF(AF70, COUNTIF($AF$2:AF70, TRUE), "")
A71: Staffing levels are commensurate with the scope of the statistical program(s) managed by the organization. | B71: 1 | C71: 1_6 | D71: 1_6_1 | E71: 1_6_1_9 | F71: Does the responsible agency have an adequate number of administrative staff to handle new data sources (big data, administrative data) and advanced analytics? | G71: 5 | J71: =IF(H71="","",H71) | L71: European Statistical Code of Practice Principle 9 | M71: =IFERROR(INDEX(__key!$D:$D,MATCH(O71&"|"&SUBSTITUTE(H71,",",";"), __key!$E:$E, 0)), "") | N71: =IFERROR(INDEX(__key!$D:$D,MATCH(O71&"|"&SUBSTITUTE(J71,",",";"), __key!$E:$E, 0)), "") | O71: RESNR | Q71: Human resources are adequate | R71: 1619 | S71: =IFERROR(1*M71,0) -> 0 | T71: =IFERROR(1*N71,0) -> 0 | U71: =IFERROR(IF(ISNUMBER(SEARCH("Not Relevant",H71)),0,VALUE(G71)),"") -> 5 | V71: =IFERROR(SUMIF($D:$D,D71,$U:$U),"") -> 160 | W71: =IF(OR(V71=0,V71=""),"",U71/V71) -> 0.03125 | X71: =IF(OR(M71="",W71=""),"",VALUE(M71)*W71) | Y71: =IFERROR(ISNUMBER(SEARCH("Not Relevant",H71)),FALSE) -> FALSE | Z71: =IF(Y71, COUNTIF($Y$2:Y71, TRUE), "") | AA71: =IFERROR(IF(ISNUMBER(SEARCH("Not Relevant",J71)),0,VALUE(G71)),"") -> 5 | AB71: =IFERROR(SUMIF($D:$D,D71,$AA:$AA),"") -> 160 | AC71: =IF(OR(AB71=0,AB71=""),"",AA71/AB71) -> 0.03125 | AD71: =IF(OR(N71="",AC71=""),"",VALUE(N71)*AC71) | AE71: =IFERROR(ISNUMBER(SEARCH("Not Relevant",J71)),FALSE) -> FALSE | AF71: =IF(OR(H71="",J71=""),FALSE,IF(H71<>J71,TRUE,FALSE)) -> FALSE | AG71: =IF(AF71, COUNTIF($AF$2:AF71, TRUE), "")
A72: Staffing levels are commensurate with the scope of the statistical program(s) managed by the organization. | B72: 1 | C72: 1_6 | D72: 1_6_1 | E72: 1_6_1_10 | F72: Does the responsible agency have an adequate number of data collection and processing staff to handle new data sources (big data, administrative data) and advanced analytics? | G72: 5 | J72: =IF(H72="","",H72) | L72: European Statistical Code of Practice Principle 9 | M72: =IFERROR(INDEX(__key!$D:$D,MATCH(O72&"|"&SUBSTITUTE(H72,",",";"), __key!$E:$E, 0)), "") | N72: =IFERROR(INDEX(__key!$D:$D,MATCH(O72&"|"&SUBSTITUTE(J72,",",";"), __key!$E:$E, 0)), "") | O72: RESNR | Q72: Human resources are adequate | R72: 16110 | S72: =IFERROR(1*M72,0) -> 0 | T72: =IFERROR(1*N72,0) -> 0 | U72: =IFERROR(IF(ISNUMBER(SEARCH("Not Relevant",H72)),0,VALUE(G72)),"") -> 5 | V72: =IFERROR(SUMIF($D:$D,D72,$U:$U),"") -> 160 | W72: =IF(OR(V72=0,V72=""),"",U72/V72) -> 0.03125 | X72: =IF(OR(M72="",W72=""),"",VALUE(M72)*W72) | Y72: =IFERROR(ISNUMBER(SEARCH("Not Relevant",H72)),FALSE) -> FALSE | Z72: =IF(Y72, COUNTIF($Y$2:Y72, TRUE), "") | AA72: =IFERROR(IF(ISNUMBER(SEARCH("Not Relevant",J72)),0,VALUE(G72)),"") -> 5 | AB72: =IFERROR(SUMIF($D:$D,D72,$AA:$AA),"") -> 160 | AC72: =IF(OR(AB72=0,AB72=""),"",AA72/AB72) -> 0.03125 | AD72: =IF(OR(N72="",AC72=""),"",VALUE(N72)*AC72) | AE72: =IFERROR(ISNUMBER(SEARCH("Not Relevant",J72)),FALSE) -> FALSE | AF72: =IF(OR(H72="",J72=""),FALSE,IF(H72<>J72,TRUE,FALSE)) -> FALSE | AG72: =IF(AF72, COUNTIF($AF$2:AF72, TRUE), "")
A73: Staffing levels are commensurate with the scope of the statistical program(s) managed by the organization. | B73: 1 | C73: 1_6 | D73: 1_6_1 | E73: 1_6_1_11 | F73: Does the responsible agency have an adequate number of IT professionals to maintain systems, develop software, and ensure cybersecurity? | G73: 5 | J73: =IF(H73="","",H73) | L73: European Statistical Code of Practice Principle 9 | M73: =IFERROR(INDEX(__key!$D:$D,MATCH(O73&"|"&SUBSTITUTE(H73,",",";"), __key!$E:$E, 0)), "") | N73: =IFERROR(INDEX(__key!$D:$D,MATCH(O73&"|"&SUBSTITUTE(J73,",",";"), __key!$E:$E, 0)), "") | O73: RESNR | Q73: Human resources are adequate | R73: 16111 | S73: =IFERROR(1*M73,0) -> 0 | T73: =IFERROR(1*N73,0) -> 0 | U73: =IFERROR(IF(ISNUMBER(SEARCH("Not Relevant",H73)),0,VALUE(G73)),"") -> 5 | V73: =IFERROR(SUMIF($D:$D,D73,$U:$U),"") -> 160 | W73: =IF(OR(V73=0,V73=""),"",U73/V73) -> 0.03125 | X73: =IF(OR(M73="",W73=""),"",VALUE(M73)*W73) | Y73: =IFERROR(ISNUMBER(SEARCH("Not Relevant",H73)),FALSE) -> FALSE | Z73: =IF(Y73, COUNTIF($Y$2:Y73, TRUE), "") | AA73: =IFERROR(IF(ISNUMBER(SEARCH("Not Relevant",J73)),0,VALUE(G73)),"") -> 5 | AB73: =IFERROR(SUMIF($D:$D,D73,$AA:$AA),"") -> 160 | AC73: =IF(OR(AB73=0,AB73=""),"",AA73/AB73) -> 0.03125 | AD73: =IF(OR(N73="",AC73=""),"",VALUE(N73)*AC73) | AE73: =IFERROR(ISNUMBER(SEARCH("Not Relevant",J73)),FALSE) -> FALSE | AF73: =IF(OR(H73="",J73=""),FALSE,IF(H73<>J73,TRUE,FALSE)) -> FALSE | AG73: =IF(AF73, COUNTIF($AF$2:AF73, TRUE), "")
A74: Staffing levels are commensurate with the scope of the statistical program(s) managed by the organization. | B74: 1 | C74: 1_6 | D74: 1_6_1 | E74: 1_6_1_12 | F74: Does the responsible agency have enough financial sector experts (if needed) to compile specialized financial statistics (e.g., monetary, banking, balance of payments)? | G74: 5 | J74: =IF(H74="","",H74) | L74: European Statistical Code of Practice Principle 9 | M74: =IFERROR(INDEX(__key!$D:$D,MATCH(O74&"|"&SUBSTITUTE(H74,",",";"), __key!$E:$E, 0)), "") | N74: =IFERROR(INDEX(__key!$D:$D,MATCH(O74&"|"&SUBSTITUTE(J74,",",";"), __key!$E:$E, 0)), "") | O74: RESNR | Q74: Human resources are adequate | R74: 16112 | S74: =IFERROR(1*M74,0) -> 0 | T74: =IFERROR(1*N74,0) -> 0 | U74: =IFERROR(IF(ISNUMBER(SEARCH("Not Relevant",H74)),0,VALUE(G74)),"") -> 5 | V74: =IFERROR(SUMIF($D:$D,D74,$U:$U),"") -> 160 | W74: =IF(OR(V74=0,V74=""),"",U74/V74) -> 0.03125 | X74: =IF(OR(M74="",W74=""),"",VALUE(M74)*W74) | Y74: =IFERROR(ISNUMBER(SEARCH("Not Relevant",H74)),FALSE) -> FALSE | Z74: =IF(Y74, COUNTIF($Y$2:Y74, TRUE), "") | AA74: =IFERROR(IF(ISNUMBER(SEARCH("Not Relevant",J74)),0,VALUE(G74)),"") -> 5 | AB74: =IFERROR(SUMIF($D:$D,D74,$AA:$AA),"") -> 160 | AC74: =IF(OR(AB74=0,AB74=""),"",AA74/AB74) -> 0.03125 | AD74: =IF(OR(N74="",AC74=""),"",VALUE(N74)*AC74) | AE74: =IFERROR(ISNUMBER(SEARCH("Not Relevant",J74)),FALSE) -> FALSE | AF74: =IF(OR(H74="",J74=""),FALSE,IF(H74<>J74,TRUE,FALSE)) -> FALSE | AG74: =IF(AF74, COUNTIF($AF$2:AF74, TRUE), "")
A75: Staffing levels are commensurate with the scope of the statistical program(s) managed by the organization. | B75: 1 | C75: 1_6 | D75: 1_6_1 | E75: 1_6_1_13 | F75: Is the management team (number and expertise of managers) sufficient to guide strategy, oversee operations, and handle cross-cutting issues? | G75: 5 | J75: =IF(H75="","",H75) | L75: European Statistical Code of Practice Principle 9 | M75: =IFERROR(INDEX(__key!$D:$D,MATCH(O75&"|"&SUBSTITUTE(H75,",",";"), __key!$E:$E, 0)), "") | N75: =IFERROR(INDEX(__key!$D:$D,MATCH(O75&"|"&SUBSTITUTE(J75,",",";"), __key!$E:$E, 0)), "") | O75: RESNR | Q75: Human resources are adequate | R75: 16113 | S75: =IFERROR(1*M75,0) -> 0 | T75: =IFERROR(1*N75,0) -> 0 | U75: =IFERROR(IF(ISNUMBER(SEARCH("Not Relevant",H75)),0,VALUE(G75)),"") -> 5 | V75: =IFERROR(SUMIF($D:$D,D75,$U:$U),"") -> 160 | W75: =IF(OR(V75=0,V75=""),"",U75/V75) -> 0.03125 | X75: =IF(OR(M75="",W75=""),"",VALUE(M75)*W75) | Y75: =IFERROR(ISNUMBER(SEARCH("Not Relevant",H75)),FALSE) -> FALSE | Z75: =IF(Y75, COUNTIF($Y$2:Y75, TRUE), "") | AA75: =IFERROR(IF(ISNUMBER(SEARCH("Not Relevant",J75)),0,VALUE(G75)),"") -> 5 | AB75: =IFERROR(SUMIF($D:$D,D75,$AA:$AA),"") -> 160 | AC75: =IF(OR(AB75=0,AB75=""),"",AA75/AB75) -> 0.03125 | AD75: =IF(OR(N75="",AC75=""),"",VALUE(N75)*AC75) | AE75: =IFERROR(ISNUMBER(SEARCH("Not Relevant",J75)),FALSE) -> FALSE | AF75: =IF(OR(H75="",J75=""),FALSE,IF(H75<>J75,TRUE,FALSE)) -> FALSE | AG75: =IF(AF75, COUNTIF($AF$2:AF75, TRUE), "")
... A79: Staffing levels are commensurate with the scope of the statistical program(s) managed by the organization. | B79: 1 | C79: 1_6 | D79: 1_6_1 | E79: 1_6_1_17 | F79: Does the responsible agency have workplace programs in place that support staff training, professional development, and career advancement? | G79: 10 | J79: =IF(H79="","",H79) | L79: European Statistical Code of Practice Principle 9 | M79: =IFERROR(INDEX(__key!$D:$D,MATCH(O79&"|"&SUBSTITUTE(H79,",",";"), __key!$E:$E, 0)), "") | N79: =IFERROR(INDEX(__key!$D:$D,MATCH(O79&"|"&SUBSTITUTE(J79,",",";"), __key!$E:$E, 0)), "") | O79: BP | Q79: Human resources are adequate | R79: 16117 | S79: =IFERROR(1*M79,0) -> 0 | T79: =IFERROR(1*N79,0) -> 0 | U79: =IFERROR(IF(ISNUMBER(SEARCH("Not Relevant",H79)),0,VALUE(G79)),"") -> 10 | V79: =IFERROR(SUMIF($D:$D,D79,$U:$U),"") -> 160 | W79: =IF(OR(V79=0,V79=""),"",U79/V79) -> 0.0625 | X79: =IF(OR(M79="",W79=""),"",VALUE(M79)*W79) | Y79: =IFERROR(ISNUMBER(SEARCH("Not Relevant",H79)),FALSE) -> FALSE | Z79: =IF(Y79, COUNTIF($Y$2:Y79, TRUE), "") | AA79: =IFERROR(IF(ISNUMBER(SEARCH("Not Relevant",J79)),0,VALUE(G79)),"") -> 10 | AB79: =IFERROR(SUMIF($D:$D,D79,$AA:$AA),"") -> 160 | AC79: =IF(OR(AB79=0,AB79=""),"",AA79/AB79) -> 0.0625 | AD79: =IF(OR(N79="",AC79=""),"",VALUE(N79)*AC79) | AE79: =IFERROR(ISNUMBER(SEARCH("Not Relevant",J79)),FALSE) -> FALSE | AF79: =IF(OR(H79="",J79=""),FALSE,IF(H79<>J79,TRUE,FALSE)) -> FALSE | AG79: =IF(AF79, COUNTIF($AF$2:AF79, TRUE), "")
A80: Staffing levels are commensurate with the scope of the statistical program(s) managed by the organization. | B80: 1 | C80: 1_6 | D80: 1_6_1 | E80: 1_6_1_18 | F80: How many staff are working in the National Accounts statistical program? | J80: =IF(H80="","",H80) | M80: =IFERROR(INDEX(__key!$D:$D,MATCH(O80&"|"&SUBSTITUTE(H80,",",";"), __key!$E:$E, 0)), "") | N80: =IFERROR(INDEX(__key!$D:$D,MATCH(O80&"|"&SUBSTITUTE(J80,",",";"), __key!$E:$E, 0)), "") | O80: STFLVL | Q80: Human resources are adequate | R80: 16118 | S80: =IFERROR(1*M80,0) -> 0 | T80: =IFERROR(1*N80,0) -> 0 | U80: =IFERROR(IF(ISNUMBER(SEARCH("Not Relevant",H80)),0,VALUE(G80)),"") -> 0 | V80: =IFERROR(SUMIF($D:$D,D80,$U:$U),"") -> 160 | W80: =IF(OR(V80=0,V80=""),"",U80/V80) -> 0 | X80: =IF(OR(M80="",W80=""),"",VALUE(M80)*W80) | Y80: =IFERROR(ISNUMBER(SEARCH("Not Relevant",H80)),FALSE) -> FALSE | Z80: =IF(Y80, COUNTIF($Y$2:Y80, TRUE), "") | AA80: =IFERROR(IF(ISNUMBER(SEARCH("Not Relevant",J80)),0,VALUE(G80)),"") -> 0 | AB80: =IFERROR(SUMIF($D:$D,D80,$AA:$AA),"") -> 160 | AC80: =IF(OR(AB80=0,AB80=""),"",AA80/AB80) -> 0 | AD80: =IF(OR(N80="",AC80=""),"",VALUE(N80)*AC80) | AE80: =IFERROR(ISNUMBER(SEARCH("Not Relevant",J80)),FALSE) -> FALSE | AF80: =IF(OR(H80="",J80=""),FALSE,IF(H80<>J80,TRUE,FALSE)) -> FALSE | AG80: =IF(AF80, COUNTIF($AF$2:AF80, TRUE), "")
A81: Staffing levels are commensurate with the scope of the statistical program(s) managed by the organization. | B81: 1 | C81: 1_6 | D81: 1_6_1 | E81: 1_6_1_19 | F81: How many staff are working in the Balance of Payments / International Investment Position statistical program? | J81: =IF(H81="","",H81) | M81: =IFERROR(INDEX(__key!$D:$D,MATCH(O81&"|"&SUBSTITUTE(H81,",",";"), __key!$E:$E, 0)), "") | N81: =IFERROR(INDEX(__key!$D:$D,MATCH(O81&"|"&SUBSTITUTE(J81,",",";"), __key!$E:$E, 0)), "") | O81: STFLVL | Q81: Human resources are adequate | R81: 16119 | S81: =IFERROR(1*M81,0) -> 0 | T81: =IFERROR(1*N81,0) -> 0 | U81: =IFERROR(IF(ISNUMBER(SEARCH("Not Relevant",H81)),0,VALUE(G81)),"") -> 0 | V81: =IFERROR(SUMIF($D:$D,D81,$U:$U),"") -> 160 | W81: =IF(OR(V81=0,V81=""),"",U81/V81) -> 0 | X81: =IF(OR(M81="",W81=""),"",VALUE(M81)*W81) | Y81: =IFERROR(ISNUMBER(SEARCH("Not Relevant",H81)),FALSE) -> FALSE | Z81: =IF(Y81, COUNTIF($Y$2:Y81, TRUE), "") | AA81: =IFERROR(IF(ISNUMBER(SEARCH("Not Relevant",J81)),0,VALUE(G81)),"") -> 0 | AB81: =IFERROR(SUMIF($D:$D,D81,$AA:$AA),"") -> 160 | AC81: =IF(OR(AB81=0,AB81=""),"",AA81/AB81) -> 0 | AD81: =IF(OR(N81="",AC81=""),"",VALUE(N81)*AC81) | AE81: =IFERROR(ISNUMBER(SEARCH("Not Relevant",J81)),FALSE) -> FALSE | AF81: =IF(OR(H81="",J81=""),FALSE,IF(H81<>J81,TRUE,FALSE)) -> FALSE | AG81: =IF(AF81, COUNTIF($AF$2:AF81, TRUE), "")
A82: Staffing levels are commensurate with the scope of the statistical program(s) managed by the organization. | B82: 1 | C82: 1_6 | D82: 1_6_1 | E82: 1_6_1_20 | F82: How many staff are working in the Government Finance Statistics statistical program? | J82: =IF(H82="","",H82) | M82: =IFERROR(INDEX(__key!$D:$D,MATCH(O82&"|"&SUBSTITUTE(H82,",",";"), __key!$E:$E, 0)), "") | N82: =IFERROR(INDEX(__key!$D:$D,MATCH(O82&"|"&SUBSTITUTE(J82,",",";"), __key!$E:$E, 0)), "") | O82: STFLVL | Q82: Human resources are adequate | R82: 16120 | S82: =IFERROR(1*M82,0) -> 0 | T82: =IFERROR(1*N82,0) -> 0 | U82: =IFERROR(IF(ISNUMBER(SEARCH("Not Relevant",H82)),0,VALUE(G82)),"") -> 0 | V82: =IFERROR(SUMIF($D:$D,D82,$U:$U),"") -> 160 | W82: =IF(OR(V82=0,V82=""),"",U82/V82) -> 0 | X82: =IF(OR(M82="",W82=""),"",VALUE(M82)*W82) | Y82: =IFERROR(ISNUMBER(SEARCH("Not Relevant",H82)),FALSE) -> FALSE | Z82: =IF(Y82, COUNTIF($Y$2:Y82, TRUE), "") | AA82: =IFERROR(IF(ISNUMBER(SEARCH("Not Relevant",J82)),0,VALUE(G82)),"") -> 0 | AB82: =IFERROR(SUMIF($D:$D,D82,$AA:$AA),"") -> 160 | AC82: =IF(OR(AB82=0,AB82=""),"",AA82/AB82) -> 0 | AD82: =IF(OR(N82="",AC82=""),"",VALUE(N82)*AC82) | AE82: =IFERROR(ISNUMBER(SEARCH("Not Relevant",J82)),FALSE) -> FALSE | AF82: =IF(OR(H82="",J82=""),FALSE,IF(H82<>J82,TRUE,FALSE)) -> FALSE | AG82: =IF(AF82, COUNTIF($AF$2:AF82, TRUE), "")
A83: Staffing levels are commensurate with the scope of the statistical program(s) managed by the organization. | B83: 1 | C83: 1_6 | D83: 1_6_1 | E83: 1_6_1_21 | F83: How many staff are working in the Monetary and Financial statistical program? | J83: =IF(H83="","",H83) | M83: =IFERROR(INDEX(__key!$D:$D,MATCH(O83&"|"&SUBSTITUTE(H83,",",";"), __key!$E:$E, 0)), "") | N83: =IFERROR(INDEX(__key!$D:$D,MATCH(O83&"|"&SUBSTITUTE(J83,",",";"), __key!$E:$E, 0)), "") | O83: STFLVL | Q83: Human resources are adequate | R83: 16121 | S83: =IFERROR(1*M83,0) -> 0 | T83: =IFERROR(1*N83,0) -> 0 | U83: =IFERROR(IF(ISNUMBER(SEARCH("Not Relevant",H83)),0,VALUE(G83)),"") -> 0 | V83: =IFERROR(SUMIF($D:$D,D83,$U:$U),"") -> 160 | W83: =IF(OR(V83=0,V83=""),"",U83/V83) -> 0 | X83: =IF(OR(M83="",W83=""),"",VALUE(M83)*W83) | Y83: =IFERROR(ISNUMBER(SEARCH("Not Relevant",H83)),FALSE) -> FALSE | Z83: =IF(Y83, COUNTIF($Y$2:Y83, TRUE), "") | AA83: =IFERROR(IF(ISNUMBER(SEARCH("Not Relevant",J83)),0,VALUE(G83)),"") -> 0 | AB83: =IFERROR(SUMIF($D:$D,D83,$AA:$AA),"") -> 160 | AC83: =IF(OR(AB83=0,AB83=""),"",AA83/AB83) -> 0 | AD83: =IF(OR(N83="",AC83=""),"",VALUE(N83)*AC83) | AE83: =IFERROR(ISNUMBER(SEARCH("Not Relevant",J83)),FALSE) -> FALSE | AF83: =IF(OR(H83="",J83=""),FALSE,IF(H83<>J83,TRUE,FALSE)) -> FALSE | AG83: =IF(AF83, COUNTIF($AF$2:AF83, TRUE), "")
A84: Staffing levels are commensurate with the scope of the statistical program(s) managed by the organization. | B84: 1 | C84: 1_6 | D84: 1_6_1 | E84: 1_6_1_22 | F84: How many staff are working in the Public Sector Debt Statistics statistical program? | J84: =IF(H84="","",H84) | M84: =IFERROR(INDEX(__key!$D:$D,MATCH(O84&"|"&SUBSTITUTE(H84,",",";"), __key!$E:$E, 0)), "") | N84: =IFERROR(INDEX(__key!$D:$D,MATCH(O84&"|"&SUBSTITUTE(J84,",",";"), __key!$E:$E, 0)), "") | O84: STFLVL | Q84: Human resources are adequate | R84: 16122 | S84: =IFERROR(1*M84,0) -> 0 | T84: =IFERROR(1*N84,0) -> 0 | U84: =IFERROR(IF(ISNUMBER(SEARCH("Not Relevant",H84)),0,VALUE(G84)),"") -> 0 | V84: =IFERROR(SUMIF($D:$D,D84,$U:$U),"") -> 160 | W84: =IF(OR(V84=0,V84=""),"",U84/V84) -> 0 | X84: =IF(OR(M84="",W84=""),"",VALUE(M84)*W84) | Y84: =IFERROR(ISNUMBER(SEARCH("Not Relevant",H84)),FALSE) -> FALSE | Z84: =IF(Y84, COUNTIF($Y$2:Y84, TRUE), "") | AA84: =IFERROR(IF(ISNUMBER(SEARCH("Not Relevant",J84)),0,VALUE(G84)),"") -> 0 | AB84: =IFERROR(SUMIF($D:$D,D84,$AA:$AA),"") -> 160 | AC84: =IF(OR(AB84=0,AB84=""),"",AA84/AB84) -> 0 | AD84: =IF(OR(N84="",AC84=""),"",VALUE(N84)*AC84) | AE84: =IFERROR(ISNUMBER(SEARCH("Not Relevant",J84)),FALSE) -> FALSE | AF84: =IF(OR(H84="",J84=""),FALSE,IF(H84<>J84,TRUE,FALSE)) -> FALSE | AG84: =IF(AF84, COUNTIF($AF$2:AF84, TRUE), "")
A85: Staffing levels are commensurate with the scope of the statistical program(s) managed by the organization. | B85: 1 | C85: 1_6 | D85: 1_6_1 | E85: 1_6_1_23 | F85: How many staff are working in the Consumer Prices statistical program? | J85: =IF(H85="","",H85) | M85: =IFERROR(INDEX(__key!$D:$D,MATCH(O85&"|"&SUBSTITUTE(H85,",",";"), __key!$E:$E, 0)), "") | N85: =IFERROR(INDEX(__key!$D:$D,MATCH(O85&"|"&SUBSTITUTE(J85,",",";"), __key!$E:$E, 0)), "") | O85: STFLVL | Q85: Human resources are adequate | R85: 16123 | S85: =IFERROR(1*M85,0) -> 0 | T85: =IFERROR(1*N85,0) -> 0 | U85: =IFERROR(IF(ISNUMBER(SEARCH("Not Relevant",H85)),0,VALUE(G85)),"") -> 0 | V85: =IFERROR(SUMIF($D:$D,D85,$U:$U),"") -> 160 | W85: =IF(OR(V85=0,V85=""),"",U85/V85) -> 0 | X85: =IF(OR(M85="",W85=""),"",VALUE(M85)*W85) | Y85: =IFERROR(ISNUMBER(SEARCH("Not Relevant",H85)),FALSE) -> FALSE | Z85: =IF(Y85, COUNTIF($Y$2:Y85, TRUE), "") | AA85: =IFERROR(IF(ISNUMBER(SEARCH("Not Relevant",J85)),0,VALUE(G85)),"") -> 0 | AB85: =IFERROR(SUMIF($D:$D,D85,$AA:$AA),"") -> 160 | AC85: =IF(OR(AB85=0,AB85=""),"",AA85/AB85) -> 0 | AD85: =IF(OR(N85="",AC85=""),"",VALUE(N85)*AC85) | AE85: =IFERROR(ISNUMBER(SEARCH("Not Relevant",J85)),FALSE) -> FALSE | AF85: =IF(OR(H85="",J85=""),FALSE,IF(H85<>J85,TRUE,FALSE)) -> FALSE | AG85: =IF(AF85, COUNTIF($AF$2:AF85, TRUE), "")
A86: Staffing levels are commensurate with the scope of the statistical program(s) managed by the organization. | B86: 1 | C86: 1_6 | D86: 1_6_1 | E86: 1_6_1_24 | F86: How many staff are working in the Producer Prices statistical program? | J86: =IF(H86="","",H86) | M86: =IFERROR(INDEX(__key!$D:$D,MATCH(O86&"|"&SUBSTITUTE(H86,",",";"), __key!$E:$E, 0)), "") | N86: =IFERROR(INDEX(__key!$D:$D,MATCH(O86&"|"&SUBSTITUTE(J86,",",";"), __key!$E:$E, 0)), "") | O86: STFLVL | Q86: Human resources are adequate | R86: 16124 | S86: =IFERROR(1*M86,0) -> 0 | T86: =IFERROR(1*N86,0) -> 0 | U86: =IFERROR(IF(ISNUMBER(SEARCH("Not Relevant",H86)),0,VALUE(G86)),"") -> 0 | V86: =IFERROR(SUMIF($D:$D,D86,$U:$U),"") -> 160 | W86: =IF(OR(V86=0,V86=""),"",U86/V86) -> 0 | X86: =IF(OR(M86="",W86=""),"",VALUE(M86)*W86) | Y86: =IFERROR(ISNUMBER(SEARCH("Not Relevant",H86)),FALSE) -> FALSE | Z86: =IF(Y86, COUNTIF($Y$2:Y86, TRUE), "") | AA86: =IFERROR(IF(ISNUMBER(SEARCH("Not Relevant",J86)),0,VALUE(G86)),"") -> 0 | AB86: =IFERROR(SUMIF($D:$D,D86,$AA:$AA),"") -> 160 | AC86: =IF(OR(AB86=0,AB86=""),"",AA86/AB86) -> 0 | AD86: =IF(OR(N86="",AC86=""),"",VALUE(N86)*AC86) | AE86: =IFERROR(ISNUMBER(SEARCH("Not Relevant",J86)),FALSE) -> FALSE | AF86: =IF(OR(H86="",J86=""),FALSE,IF(H86<>J86,TRUE,FALSE)) -> FALSE | AG86: =IF(AF86, COUNTIF($AF$2:AF86, TRUE), "")
F87: Computing resources are commensurate with the scope of the statistical program(s) managed by the organization.
A88: Computing resources are commensurate with the scope of the statistical program(s) managed by the organization. | B88: 1 | C88: 1_7 | D88: 1_7_1 | E88: 1_7_1_1 | F88: Are overall computing resources sufficient to compile and disseminate the statistical programs (hardware, software, and network)? | G88: 50 | J88: =IF(H88="","",H88) | L88: European Statistical Code of Practice Principle 9 | M88: =IFERROR(INDEX(__key!$D:$D,MATCH(O88&"|"&SUBSTITUTE(H88,",",";"), __key!$E:$E, 0)), "") | N88: =IFERROR(INDEX(__key!$D:$D,MATCH(O88&"|"&SUBSTITUTE(J88,",",";"), __key!$E:$E, 0)), "") | O88: RES | Q88: Information technology resources are adequate | R88: 1711 | S88: =IFERROR(1*M88,0) -> 0 | T88: =IFERROR(1*N88,0) -> 0 | U88: =IFERROR(IF(ISNUMBER(SEARCH("Not Relevant",H88)),0,VALUE(G88)),"") -> 50 | V88: =IFERROR(SUMIF($D:$D,D88,$U:$U),"") -> 150 | W88: =IF(OR(V88=0,V88=""),"",U88/V88) -> 0.33333333 | X88: =IF(OR(M88="",W88=""),"",VALUE(M88)*W88) | Y88: =IFERROR(ISNUMBER(SEARCH("Not Relevant",H88)),FALSE) -> FALSE | Z88: =IF(Y88, COUNTIF($Y$2:Y88, TRUE), "") | AA88: =IFERROR(IF(ISNUMBER(SEARCH("Not Relevant",J88)),0,VALUE(G88)),"") -> 50 | AB88: =IFERROR(SUMIF($D:$D,D88,$AA:$AA),"") -> 150 | AC88: =IF(OR(AB88=0,AB88=""),"",AA88/AB88) -> 0.33333333 | AD88: =IF(OR(N88="",AC88=""),"",VALUE(N88)*AC88) | AE88: =IFERROR(ISNUMBER(SEARCH("Not Relevant",J88)),FALSE) -> FALSE | AF88: =IF(OR(H88="",J88=""),FALSE,IF(H88<>J88,TRUE,FALSE)) -> FALSE | AG88: =IF(AF88, COUNTIF($AF$2:AF88, TRUE), "")
A89: Computing resources are commensurate with the scope of the statistical program(s) managed by the organization. | B89: 1 | C89: 1_7 | D89: 1_7_1 | E89: 1_7_1_2 | F89: Is the software used for compiling and analyzing statistics effective, regularly updated, and well-adapted to current and emerging tasks? | G89: 30 | J89: =IF(H89="","",H89) | L89: European Statistical Code of Practice Principle 9 | M89: =IFERROR(INDEX(__key!$D:$D,MATCH(O89&"|"&SUBSTITUTE(H89,",",";"), __key!$E:$E, 0)), "") | N89: =IFERROR(INDEX(__key!$D:$D,MATCH(O89&"|"&SUBSTITUTE(J89,",",";"), __key!$E:$E, 0)), "") | O89: RES | Q89: Information technology resources are adequate | R89: 1712 | S89: =IFERROR(1*M89,0) -> 0 | T89: =IFERROR(1*N89,0) -> 0 | U89: =IFERROR(IF(ISNUMBER(SEARCH("Not Relevant",H89)),0,VALUE(G89)),"") -> 30 | V89: =IFERROR(SUMIF($D:$D,D89,$U:$U),"") -> 150 | W89: =IF(OR(V89=0,V89=""),"",U89/V89) -> 0.2 | X89: =IF(OR(M89="",W89=""),"",VALUE(M89)*W89) | Y89: =IFERROR(ISNUMBER(SEARCH("Not Relevant",H89)),FALSE) -> FALSE | Z89: =IF(Y89, COUNTIF($Y$2:Y89, TRUE), "") | AA89: =IFERROR(IF(ISNUMBER(SEARCH("Not Relevant",J89)),0,VALUE(G89)),"") -> 30 | AB89: =IFERROR(SUMIF($D:$D,D89,$AA:$AA),"") -> 150 | AC89: =IF(OR(AB89=0,AB89=""),"",AA89/AB89) -> 0.2 | AD89: =IF(OR(N89="",AC89=""),"",VALUE(N89)*AC89) | AE89: =IFERROR(ISNUMBER(SEARCH("Not Relevant",J89)),FALSE) -> FALSE | AF89: =IF(OR(H89="",J89=""),FALSE,IF(H89<>J89,TRUE,FALSE)) -> FALSE | AG89: =IF(AF89, COUNTIF($AF$2:AF89, TRUE), "")
A90: Computing resources are commensurate with the scope of the statistical program(s) managed by the organization. | B90: 1 | C90: 1_7 | D90: 1_7_1 | E90: 1_7_1_3 | F90: Is hardware (computers, servers) distributed adequately so staff can efficiently collect, process, and manage databases? | G90: 30 | J90: =IF(H90="","",H90) | L90: European Statistical Code of Practice Principle 9 | M90: =IFERROR(INDEX(__key!$D:$D,MATCH(O90&"|"&SUBSTITUTE(H90,",",";"), __key!$E:$E, 0)), "") | N90: =IFERROR(INDEX(__key!$D:$D,MATCH(O90&"|"&SUBSTITUTE(J90,",",";"), __key!$E:$E, 0)), "") | O90: RES | Q90: Information technology resources are adequate | R90: 1713 | S90: =IFERROR(1*M90,0) -> 0 | T90: =IFERROR(1*N90,0) -> 0 | U90: =IFERROR(IF(ISNUMBER(SEARCH("Not Relevant",H90)),0,VALUE(G90)),"") -> 30 | V90: =IFERROR(SUMIF($D:$D,D90,$U:$U),"") -> 150 | W90: =IF(OR(V90=0,V90=""),"",U90/V90) -> 0.2 | X90: =IF(OR(M90="",W90=""),"",VALUE(M90)*W90) | Y90: =IFERROR(ISNUMBER(SEARCH("Not Relevant",H90)),FALSE) -> FALSE | Z90: =IF(Y90, COUNTIF($Y$2:Y90, TRUE), "") | AA90: =IFERROR(IF(ISNUMBER(SEARCH("Not Relevant",J90)),0,VALUE(G90)),"") -> 30 | AB90: =IFERROR(SUMIF($D:$D,D90,$AA:$AA),"") -> 150 | AC90: =IF(OR(AB90=0,AB90=""),"",AA90/AB90) -> 0.2 | AD90: =IF(OR(N90="",AC90=""),"",VALUE(N90)*AC90) | AE90: =IFERROR(ISNUMBER(SEARCH("Not Relevant",J90)),FALSE) -> FALSE | AF90: =IF(OR(H90="",J90=""),FALSE,IF(H90<>J90,TRUE,FALSE)) -> FALSE | AG90: =IF(AF90, COUNTIF($AF$2:AF90, TRUE), "")
A91: Computing resources are commensurate with the scope of the statistical program(s) managed by the organization. | B91: 1 | C91: 1_7 | D91: 1_7_1 | E91: 1_7_1_4 | F91: Are data back-up and disaster recovery measures (e.g., for natural disasters or accidents) in place to protect databases and ensure rapid retrieval of series? | G91: 30 | J91: =IF(H91="","",H91) | L91: European Statistical Code of Practice Principle 9 | M91: =IFERROR(INDEX(__key!$D:$D,MATCH(O91&"|"&SUBSTITUTE(H91,",",";"), __key!$E:$E, 0)), "") | N91: =IFERROR(INDEX(__key!$D:$D,MATCH(O91&"|"&SUBSTITUTE(J91,",",";"), __key!$E:$E, 0)), "") | O91: RES | Q91: Information technology resources are adequate | R91: 1714 | S91: =IFERROR(1*M91,0) -> 0 | T91: =IFERROR(1*N91,0) -> 0 | U91: =IFERROR(IF(ISNUMBER(SEARCH("Not Relevant",H91)),0,VALUE(G91)),"") -> 30 | V91: =IFERROR(SUMIF($D:$D,D91,$U:$U),"") -> 150 | W91: =IF(OR(V91=0,V91=""),"",U91/V91) -> 0.2 | X91: =IF(OR(M91="",W91=""),"",VALUE(M91)*W91) | Y91: =IFERROR(ISNUMBER(SEARCH("Not Relevant",H91)),FALSE) -> FALSE | Z91: =IF(Y91, COUNTIF($Y$2:Y91, TRUE), "") | AA91: =IFERROR(IF(ISNUMBER(SEARCH("Not Relevant",J91)),0,VALUE(G91)),"") -> 30 | AB91: =IFERROR(SUMIF($D:$D,D91,$AA:$AA),"") -> 150 | AC91: =IF(OR(AB91=0,AB91=""),"",AA91/AB91) -> 0.2 | AD91: =IF(OR(N91="",AC91=""),"",VALUE(N91)*AC91) | AE91: =IFERROR(ISNUMBER(SEARCH("Not Relevant",J91)),FALSE) -> FALSE | AF91: =IF(OR(H91="",J91=""),FALSE,IF(H91<>J91,TRUE,FALSE)) -> FALSE | AG91: =IF(AF91, COUNTIF($AF$2:AF91, TRUE), "")
A92: Computing resources are commensurate with the scope of the statistical program(s) managed by the organization. | B92: 1 | C92: 1_7 | D92: 1_7_1 | E92: 1_7_1_5 | F92: Does the statistical organization maintain an IT roadmap and regularly update it to ensure it utilizes the latest technology to process, disseminate, and safeguard national data assets? | G92: 10 | J92: =IF(H92="","",H92) | L92: European Statistical Code of Practice Principle 9 | M92: =IFERROR(INDEX(__key!$D:$D,MATCH(O92&"|"&SUBSTITUTE(H92,",",";"), __key!$E:$E, 0)), "") | N92: =IFERROR(INDEX(__key!$D:$D,MATCH(O92&"|"&SUBSTITUTE(J92,",",";"), __key!$E:$E, 0)), "") | O92: SGPP | Q92: Information technology resources are adequate | R92: 1715 | S92: =IFERROR(1*M92,0) -> 0 | T92: =IFERROR(1*N92,0) -> 0 | U92: =IFERROR(IF(ISNUMBER(SEARCH("Not Relevant",H92)),0,VALUE(G92)),"") -> 10 | V92: =IFERROR(SUMIF($D:$D,D92,$U:$U),"") -> 150 | W92: =IF(OR(V92=0,V92=""),"",U92/V92) -> 0.066666667 | X92: =IF(OR(M92="",W92=""),"",VALUE(M92)*W92) | Y92: =IFERROR(ISNUMBER(SEARCH("Not Relevant",H92)),FALSE) -> FALSE | Z92: =IF(Y92, COUNTIF($Y$2:Y92, TRUE), "") | AA92: =IFERROR(IF(ISNUMBER(SEARCH("Not Relevant",J92)),0,VALUE(G92)),"") -> 10 | AB92: =IFERROR(SUMIF($D:$D,D92,$AA:$AA),"") -> 150 | AC92: =IF(OR(AB92=0,AB92=""),"",AA92/AB92) -> 0.066666667 | AD92: =IF(OR(N92="",AC92=""),"",VALUE(N92)*AC92) | AE92: =IFERROR(ISNUMBER(SEARCH("Not Relevant",J92)),FALSE) -> FALSE | AF92: =IF(OR(H92="",J92=""),FALSE,IF(H92<>J92,TRUE,FALSE)) -> FALSE | AG92: =IF(AF92, COUNTIF($AF$2:AF92, TRUE), "")
F93: Facilities are commensurate with the scope of the statistical program(s) managed by the organization.
A94: Facilities are commensurate with the scope of the statistical program(s) managed by the organization. | B94: 1 | C94: 1_8 | D94: 1_8_1 | E94: 1_8_1_1 | F94: Do office building facilities provide adequate working conditions (lighting, heating/cooling, space) for staff efficiency? | G94: 30 | J94: =IF(H94="","",H94) | L94: European Statistical Code of Practice Principle 9 | M94: =IFERROR(INDEX(__key!$D:$D,MATCH(O94&"|"&SUBSTITUTE(H94,",",";"), __key!$E:$E, 0)), "") | N94: =IFERROR(INDEX(__key!$D:$D,MATCH(O94&"|"&SUBSTITUTE(J94,",",";"), __key!$E:$E, 0)), "") | O94: RES | Q94: Physical infrastructure is adequate | R94: 1811 | S94: =IFERROR(1*M94,0) -> 0 | T94: =IFERROR(1*N94,0) -> 0 | U94: =IFERROR(IF(ISNUMBER(SEARCH("Not Relevant",H94)),0,VALUE(G94)),"") -> 30 | V94: =IFERROR(SUMIF($D:$D,D94,$U:$U),"") -> 50 | W94: =IF(OR(V94=0,V94=""),"",U94/V94) -> 0.6 | X94: =IF(OR(M94="",W94=""),"",VALUE(M94)*W94) | Y94: =IFERROR(ISNUMBER(SEARCH("Not Relevant",H94)),FALSE) -> FALSE | Z94: =IF(Y94, COUNTIF($Y$2:Y94, TRUE), "") | AA94: =IFERROR(IF(ISNUMBER(SEARCH("Not Relevant",J94)),0,VALUE(G94)),"") -> 30 | AB94: =IFERROR(SUMIF($D:$D,D94,$AA:$AA),"") -> 50 | AC94: =IF(OR(AB94=0,AB94=""),"",AA94/AB94) -> 0.6 | AD94: =IF(OR(N94="",AC94=""),"",VALUE(N94)*AC94) | AE94: =IFERROR(ISNUMBER(SEARCH("Not Relevant",J94)),FALSE) -> FALSE | AF94: =IF(OR(H94="",J94=""),FALSE,IF(H94<>J94,TRUE,FALSE)) -> FALSE | AG94: =IF(AF94, COUNTIF($AF$2:AF94, TRUE), "")
A95: Facilities are commensurate with the scope of the statistical program(s) managed by the organization. | B95: 1 | C95: 1_8 | D95: 1_8_1 | E95: 1_8_1_2 | F95: Is the office furniture and equipment (desks, chairs, filing cabinets, telephones, etc.) sufficient to perform required tasks comfortably and effectively? | G95: 10 | J95: =IF(H95="","",H95) | L95: European Statistical Code of Practice Principle 9 | M95: =IFERROR(INDEX(__key!$D:$D,MATCH(O95&"|"&SUBSTITUTE(H95,",",";"), __key!$E:$E, 0)), "") | N95: =IFERROR(INDEX(__key!$D:$D,MATCH(O95&"|"&SUBSTITUTE(J95,",",";"), __key!$E:$E, 0)), "") | O95: RES | Q95: Physical infrastructure is adequate | R95: 1812 | S95: =IFERROR(1*M95,0) -> 0 | T95: =IFERROR(1*N95,0) -> 0 | U95: =IFERROR(IF(ISNUMBER(SEARCH("Not Relevant",H95)),0,VALUE(G95)),"") -> 10 | V95: =IFERROR(SUMIF($D:$D,D95,$U:$U),"") -> 50 | W95: =IF(OR(V95=0,V95=""),"",U95/V95) -> 0.2 | X95: =IF(OR(M95="",W95=""),"",VALUE(M95)*W95) | Y95: =IFERROR(ISNUMBER(SEARCH("Not Relevant",H95)),FALSE) -> FALSE | Z95: =IF(Y95, COUNTIF($Y$2:Y95, TRUE), "") | AA95: =IFERROR(IF(ISNUMBER(SEARCH("Not Relevant",J95)),0,VALUE(G95)),"") -> 10 | AB95: =IFERROR(SUMIF($D:$D,D95,$AA:$AA),"") -> 50 | AC95: =IF(OR(AB95=0,AB95=""),"",AA95/AB95) -> 0.2 | AD95: =IF(OR(N95="",AC95=""),"",VALUE(N95)*AC95) | AE95: =IFERROR(ISNUMBER(SEARCH("Not Relevant",J95)),FALSE) -> FALSE | AF95: =IF(OR(H95="",J95=""),FALSE,IF(H95<>J95,TRUE,FALSE)) -> FALSE | AG95: =IF(AF95, COUNTIF($AF$2:AF95, TRUE), "")
A96: Facilities are commensurate with the scope of the statistical program(s) managed by the organization. | B96: 1 | C96: 1_8 | D96: 1_8_1 | E96: 1_8_1_3 | F96: Are transportation arrangements (e.g., for field data collection) adequate to support the statistical program? | G96: 10 | J96: =IF(H96="","",H96) | L96: European Statistical Code of Practice Principle 9 | M96: =IFERROR(INDEX(__key!$D:$D,MATCH(O96&"|"&SUBSTITUTE(H96,",",";"), __key!$E:$E, 0)), "") | N96: =IFERROR(INDEX(__key!$D:$D,MATCH(O96&"|"&SUBSTITUTE(J96,",",";"), __key!$E:$E, 0)), "") | O96: RES | Q96: Physical infrastructure is adequate | R96: 1813 | S96: =IFERROR(1*M96,0) -> 0 | T96: =IFERROR(1*N96,0) -> 0 | U96: =IFERROR(IF(ISNUMBER(SEARCH("Not Relevant",H96)),0,VALUE(G96)),"") -> 10 | V96: =IFERROR(SUMIF($D:$D,D96,$U:$U),"") -> 50 | W96: =IF(OR(V96=0,V96=""),"",U96/V96) -> 0.2 | X96: =IF(OR(M96="",W96=""),"",VALUE(M96)*W96) | Y96: =IFERROR(ISNUMBER(SEARCH("Not Relevant",H96)),FALSE) -> FALSE | Z96: =IF(Y96, COUNTIF($Y$2:Y96, TRUE), "") | AA96: =IFERROR(IF(ISNUMBER(SEARCH("Not Relevant",J96)),0,VALUE(G96)),"") -> 10 | AB96: =IFERROR(SUMIF($D:$D,D96,$AA:$AA),"") -> 50 | AC96: =IF(OR(AB96=0,AB96=""),"",AA96/AB96) -> 0.2 | AD96: =IF(OR(N96="",AC96=""),"",VALUE(N96)*AC96) | AE96: =IFERROR(ISNUMBER(SEARCH("Not Relevant",J96)),FALSE) -> FALSE | AF96: =IF(OR(H96="",J96=""),FALSE,IF(H96<>J96,TRUE,FALSE)) -> FALSE | AG96: =IF(AF96, COUNTIF($AF$2:AF96, TRUE), "")
F97: Measures to ensure efficient use of resources are implemented.
A98: Measures to ensure efficient use of resources are implemented. | B98: 1 | C98: 1_9 | D98: 1_9_1 | E98: 1_9_1_1 | F98: Do budgeting practices provide clear information to financing authorities and facilitate priority-based discussions (e.g., expansions or cutbacks)? | G98: 10 | J98: =IF(H98="","",H98) | L98: European Statistical Code of Practice Principle 10 | M98: =IFERROR(INDEX(__key!$D:$D,MATCH(O98&"|"&SUBSTITUTE(H98,",",";"), __key!$E:$E, 0)), "") | N98: =IFERROR(INDEX(__key!$D:$D,MATCH(O98&"|"&SUBSTITUTE(J98,",",";"), __key!$E:$E, 0)), "") | O98: BP | Q98: Cost-effectiveness practices are implemented | R98: 1911 | S98: =IFERROR(1*M98,0) -> 0 | T98: =IFERROR(1*N98,0) -> 0 | U98: =IFERROR(IF(ISNUMBER(SEARCH("Not Relevant",H98)),0,VALUE(G98)),"") -> 10 | V98: =IFERROR(SUMIF($D:$D,D98,$U:$U),"") -> 150 | W98: =IF(OR(V98=0,V98=""),"",U98/V98) -> 0.066666667 | X98: =IF(OR(M98="",W98=""),"",VALUE(M98)*W98) | Y98: =IFERROR(ISNUMBER(SEARCH("Not Relevant",H98)),FALSE) -> FALSE | Z98: =IF(Y98, COUNTIF($Y$2:Y98, TRUE), "") | AA98: =IFERROR(IF(ISNUMBER(SEARCH("Not Relevant",J98)),0,VALUE(G98)),"") -> 10 | AB98: =IFERROR(SUMIF($D:$D,D98,$AA:$AA),"") -> 150 | AC98: =IF(OR(AB98=0,AB98=""),"",AA98/AB98) -> 0.066666667 | AD98: =IF(OR(N98="",AC98=""),"",VALUE(N98)*AC98) | AE98: =IFERROR(ISNUMBER(SEARCH("Not Relevant",J98)),FALSE) -> FALSE | AF98: =IF(OR(H98="",J98=""),FALSE,IF(H98<>J98,TRUE,FALSE)) -> FALSE | AG98: =IF(AF98, COUNTIF($AF$2:AF98, TRUE), "")
A99: Measures to ensure efficient use of resources are implemented. | B99: 1 | C99: 1_9 | D99: 1_9_1 | E99: 1_9_1_2 | F99: Is the funding horizon (2–3 years or more) conducive to strategic planning for future statistical developments and innovations? | G99: 10 | J99: =IF(H99="","",H99) | L99: European Statistical Code of Practice Principle 10 | M99: =IFERROR(INDEX(__key!$D:$D,MATCH(O99&"|"&SUBSTITUTE(H99,",",";"), __key!$E:$E, 0)), "") | N99: =IFERROR(INDEX(__key!$D:$D,MATCH(O99&"|"&SUBSTITUTE(J99,",",";"), __key!$E:$E, 0)), "") | O99: BP | Q99: Cost-effectiveness practices are implemented | R99: 1912 | S99: =IFERROR(1*M99,0) -> 0 | T99: =IFERROR(1*N99,0) -> 0 | U99: =IFERROR(IF(ISNUMBER(SEARCH("Not Relevant",H99)),0,VALUE(G99)),"") -> 10 | V99: =IFERROR(SUMIF($D:$D,D99,$U:$U),"") -> 150 | W99: =IF(OR(V99=0,V99=""),"",U99/V99) -> 0.066666667 | X99: =IF(OR(M99="",W99=""),"",VALUE(M99)*W99) | Y99: =IFERROR(ISNUMBER(SEARCH("Not Relevant",H99)),FALSE) -> FALSE | Z99: =IF(Y99, COUNTIF($Y$2:Y99, TRUE), "") | AA99: =IFERROR(IF(ISNUMBER(SEARCH("Not Relevant",J99)),0,VALUE(G99)),"") -> 10 | AB99: =IFERROR(SUMIF($D:$D,D99,$AA:$AA),"") -> 150 | AC99: =IF(OR(AB99=0,AB99=""),"",AA99/AB99) -> 0.066666667 | AD99: =IF(OR(N99="",AC99=""),"",VALUE(N99)*AC99) | AE99: =IFERROR(ISNUMBER(SEARCH("Not Relevant",J99)),FALSE) -> FALSE | AF99: =IF(OR(H99="",J99=""),FALSE,IF(H99<>J99,TRUE,FALSE)) -> FALSE | AG99: =IF(AF99, COUNTIF($AF$2:AF99, TRUE), "")
A100: Measures to ensure efficient use of resources are implemented. | B100: 1 | C100: 1_9 | D100: 1_9_1 | E100: 1_9_1_3 | F100: Are there periodic reviews of staff performance to ensure alignment with goals and encourage efficiency? | G100: 10 | J100: =IF(H100="","",H100) | L100: European Statistical Code of Practice Principle 10 | M100: =IFERROR(INDEX(__key!$D:$D,MATCH(O100&"|"&SUBSTITUTE(H100,",",";"), __key!$E:$E, 0)), "") | N100: =IFERROR(INDEX(__key!$D:$D,MATCH(O100&"|"&SUBSTITUTE(J100,",",";"), __key!$E:$E, 0)), "") | O100: BP | Q100: Cost-effectiveness practices are implemented | R100: 1913 | S100: =IFERROR(1*M100,0) -> 0 | T100: =IFERROR(1*N100,0) -> 0 | U100: =IFERROR(IF(ISNUMBER(SEARCH("Not Relevant",H100)),0,VALUE(G100)),"") -> 10 | V100: =IFERROR(SUMIF($D:$D,D100,$U:$U),"") -> 150 | W100: =IF(OR(V100=0,V100=""),"",U100/V100) -> 0.066666667 | X100: =IF(OR(M100="",W100=""),"",VALUE(M100)*W100) | Y100: =IFERROR(ISNUMBER(SEARCH("Not Relevant",H100)),FALSE) -> FALSE | Z100: =IF(Y100, COUNTIF($Y$2:Y100, TRUE), "") | AA100: =IFERROR(IF(ISNUMBER(SEARCH("Not Relevant",J100)),0,VALUE(G100)),"") -> 10 | AB100: =IFERROR(SUMIF($D:$D,D100,$AA:$AA),"") -> 150 | AC100: =IF(OR(AB100=0,AB100=""),"",AA100/AB100) -> 0.066666667 | AD100: =IF(OR(N100="",AC100=""),"",VALUE(N100)*AC100) | AE100: =IFERROR(ISNUMBER(SEARCH("Not Relevant",J100)),FALSE) -> FALSE | AF100: =IF(OR(H100="",J100=""),FALSE,IF(H100<>J100,TRUE,FALSE)) -> FALSE | AG100: =IF(AF100, COUNTIF($AF$2:AF100, TRUE), "")
A101: Measures to ensure efficient use of resources are implemented. | B101: 1 | C101: 1_9 | D101: 1_9_1 | E101: 1_9_1_4 | F101: Are efficiencies sought through periodic reviews of work processes (e.g., cost-effectiveness of surveys, consistency of methods across datasets)? | G101: 10 | J101: =IF(H101="","",H101) | L101: European Statistical Code of Practice Principle 10 | M101: =IFERROR(INDEX(__key!$D:$D,MATCH(O101&"|"&SUBSTITUTE(H101,",",";"), __key!$E:$E, 0)), "") | N101: =IFERROR(INDEX(__key!$D:$D,MATCH(O101&"|"&SUBSTITUTE(J101,",",";"), __key!$E:$E, 0)), "") | O101: BP | Q101: Cost-effectiveness practices are implemented | R101: 1914 | S101: =IFERROR(1*M101,0) -> 0 | T101: =IFERROR(1*N101,0) -> 0 | U101: =IFERROR(IF(ISNUMBER(SEARCH("Not Relevant",H101)),0,VALUE(G101)),"") -> 10 | V101: =IFERROR(SUMIF($D:$D,D101,$U:$U),"") -> 150 | W101: =IF(OR(V101=0,V101=""),"",U101/V101) -> 0.066666667 | X101: =IF(OR(M101="",W101=""),"",VALUE(M101)*W101) | Y101: =IFERROR(ISNUMBER(SEARCH("Not Relevant",H101)),FALSE) -> FALSE | Z101: =IF(Y101, COUNTIF($Y$2:Y101, TRUE), "") | AA101: =IFERROR(IF(ISNUMBER(SEARCH("Not Relevant",J101)),0,VALUE(G101)),"") -> 10 | AB101: =IFERROR(SUMIF($D:$D,D101,$AA:$AA),"") -> 150 | AC101: =IF(OR(AB101=0,AB101=""),"",AA101/AB101) -> 0.066666667 | AD101: =IF(OR(N101="",AC101=""),"",VALUE(N101)*AC101) | AE101: =IFERROR(ISNUMBER(SEARCH("Not Relevant",J101)),FALSE) -> FALSE | AF101: =IF(OR(H101="",J101=""),FALSE,IF(H101<>J101,TRUE,FALSE)) -> FALSE | AG101: =IF(AF101, COUNTIF($AF$2:AF101, TRUE), "")
A102: Measures to ensure efficient use of resources are implemented. | B102: 1 | C102: 1_9 | D102: 1_9_1 | E102: 1_9_1_5 | F102: Are costing procedures (measuring resources used to compile the statistics) carried out periodically and compared across programs? | G102: 10 | J102: =IF(H102="","",H102) | L102: European Statistical Code of Practice Principle 10 | M102: =IFERROR(INDEX(__key!$D:$D,MATCH(O102&"|"&SUBSTITUTE(H102,",",";"), __key!$E:$E, 0)), "") | N102: =IFERROR(INDEX(__key!$D:$D,MATCH(O102&"|"&SUBSTITUTE(J102,",",";"), __key!$E:$E, 0)), "") | O102: BP | Q102: Cost-effectiveness practices are implemented | R102: 1915 | S102: =IFERROR(1*M102,0) -> 0 | T102: =IFERROR(1*N102,0) -> 0 | U102: =IFERROR(IF(ISNUMBER(SEARCH("Not Relevant",H102)),0,VALUE(G102)),"") -> 10 | V102: =IFERROR(SUMIF($D:$D,D102,$U:$U),"") -> 150 | W102: =IF(OR(V102=0,V102=""),"",U102/V102) -> 0.066666667 | X102: =IF(OR(M102="",W102=""),"",VALUE(M102)*W102) | Y102: =IFERROR(ISNUMBER(SEARCH("Not Relevant",H102)),FALSE) -> FALSE | Z102: =IF(Y102, COUNTIF($Y$2:Y102, TRUE), "") | AA102: =IFERROR(IF(ISNUMBER(SEARCH("Not Relevant",J102)),0,VALUE(G102)),"") -> 10 | AB102: =IFERROR(SUMIF($D:$D,D102,$AA:$AA),"") -> 150 | AC102: =IF(OR(AB102=0,AB102=""),"",AA102/AB102) -> 0.066666667 | AD102: =IF(OR(N102="",AC102=""),"",VALUE(N102)*AC102) | AE102: =IFERROR(ISNUMBER(SEARCH("Not Relevant",J102)),FALSE) -> FALSE | AF102: =IF(OR(H102="",J102=""),FALSE,IF(H102<>J102,TRUE,FALSE)) -> FALSE | AG102: =IF(AF102, COUNTIF($AF$2:AF102, TRUE), "")
A103: Measures to ensure efficient use of resources are implemented. | B103: 1 | C103: 1_9 | D103: 1_9_1 | E103: 1_9_1_6 | F103: Are budgeting procedures in place to help management allocate resources among competing statistical priorities? | G103: 10 | J103: =IF(H103="","",H103) | L103: European Statistical Code of Practice Principle 10 | M103: =IFERROR(INDEX(__key!$D:$D,MATCH(O103&"|"&SUBSTITUTE(H103,",",";"), __key!$E:$E, 0)), "") | N103: =IFERROR(INDEX(__key!$D:$D,MATCH(O103&"|"&SUBSTITUTE(J103,",",";"), __key!$E:$E, 0)), "") | O103: BP | Q103: Cost-effectiveness practices are implemented | R103: 1916 | S103: =IFERROR(1*M103,0) -> 0 | T103: =IFERROR(1*N103,0) -> 0 | U103: =IFERROR(IF(ISNUMBER(SEARCH("Not Relevant",H103)),0,VALUE(G103)),"") -> 10 | V103: =IFERROR(SUMIF($D:$D,D103,$U:$U),"") -> 150 | W103: =IF(OR(V103=0,V103=""),"",U103/V103) -> 0.066666667 | X103: =IF(OR(M103="",W103=""),"",VALUE(M103)*W103) | Y103: =IFERROR(ISNUMBER(SEARCH("Not Relevant",H103)),FALSE) -> FALSE | Z103: =IF(Y103, COUNTIF($Y$2:Y103, TRUE), "") | AA103: =IFERROR(IF(ISNUMBER(SEARCH("Not Relevant",J103)),0,VALUE(G103)),"") -> 10 | AB103: =IFERROR(SUMIF($D:$D,D103,$AA:$AA),"") -> 150 | AC103: =IF(OR(AB103=0,AB103=""),"",AA103/AB103) -> 0.066666667 | AD103: =IF(OR(N103="",AC103=""),"",VALUE(N103)*AC103) | AE103: =IFERROR(ISNUMBER(SEARCH("Not Relevant",J103)),FALSE) -> FALSE | AF103: =IF(OR(H103="",J103=""),FALSE,IF(H103<>J103,TRUE,FALSE)) -> FALSE | AG103: =IF(AF103, COUNTIF($AF$2:AF103, TRUE), "")
A104: Measures to ensure efficient use of resources are implemented. | B104: 1 | C104: 1_9 | D104: 1_9_1 | E104: 1_9_1_7 | F104: Does a resource mobilization strategy (e.g., National Strategy for the Development of Statistics, NSDS) exist to fund the statistical work and development program? | G104: 10 | J104: =IF(H104="","",H104) | L104: European Statistical Code of Practice Principle 10 | M104: =IFERROR(INDEX(__key!$D:$D,MATCH(O104&"|"&SUBSTITUTE(H104,",",";"), __key!$E:$E, 0)), "") | N104: =IFERROR(INDEX(__key!$D:$D,MATCH(O104&"|"&SUBSTITUTE(J104,",",";"), __key!$E:$E, 0)), "") | O104: BP | Q104: Cost-effectiveness practices are implemented | R104: 1917 | S104: =IFERROR(1*M104,0) -> 0 | T104: =IFERROR(1*N104,0) -> 0 | U104: =IFERROR(IF(ISNUMBER(SEARCH("Not Relevant",H104)),0,VALUE(G104)),"") -> 10 | V104: =IFERROR(SUMIF($D:$D,D104,$U:$U),"") -> 150 | W104: =IF(OR(V104=0,V104=""),"",U104/V104) -> 0.066666667 | X104: =IF(OR(M104="",W104=""),"",VALUE(M104)*W104) | Y104: =IFERROR(ISNUMBER(SEARCH("Not Relevant",H104)),FALSE) -> FALSE | Z104: =IF(Y104, COUNTIF($Y$2:Y104, TRUE), "") | AA104: =IFERROR(IF(ISNUMBER(SEARCH("Not Relevant",J104)),0,VALUE(G104)),"") -> 10 | AB104: =IFERROR(SUMIF($D:$D,D104,$AA:$AA),"") -> 150 | AC104: =IF(OR(AB104=0,AB104=""),"",AA104/AB104) -> 0.066666667 | AD104: =IF(OR(N104="",AC104=""),"",VALUE(N104)*AC104) | AE104: =IFERROR(ISNUMBER(SEARCH("Not Relevant",J104)),FALSE) -> FALSE | AF104: =IF(OR(H104="",J104=""),FALSE,IF(H104<>J104,TRUE,FALSE)) -> FALSE | AG104: =IF(AF104, COUNTIF($AF$2:AF104, TRUE), "")
A105: Measures to ensure efficient use of resources are implemented. | B105: 1 | C105: 1_9 | D105: 1_9_1 | E105: 1_9_1_8 | F105: Is the annual work plan feasible given the available resources (staff, budget, IT, etc.)? | G105: 10 | J105: =IF(H105="","",H105) | L105: European Statistical Code of Practice Principle 10 | M105: =IFERROR(INDEX(__key!$D:$D,MATCH(O105&"|"&SUBSTITUTE(H105,",",";"), __key!$E:$E, 0)), "") | N105: =IFERROR(INDEX(__key!$D:$D,MATCH(O105&"|"&SUBSTITUTE(J105,",",";"), __key!$E:$E, 0)), "") | O105: BP | Q105: Cost-effectiveness practices are implemented | R105: 1918 | S105: =IFERROR(1*M105,0) -> 0 | T105: =IFERROR(1*N105,0) -> 0 | U105: =IFERROR(IF(ISNUMBER(SEARCH("Not Relevant",H105)),0,VALUE(G105)),"") -> 10 | V105: =IFERROR(SUMIF($D:$D,D105,$U:$U),"") -> 150 | W105: =IF(OR(V105=0,V105=""),"",U105/V105) -> 0.066666667 | X105: =IF(OR(M105="",W105=""),"",VALUE(M105)*W105) | Y105: =IFERROR(ISNUMBER(SEARCH("Not Relevant",H105)),FALSE) -> FALSE | Z105: =IF(Y105, COUNTIF($Y$2:Y105, TRUE), "") | AA105: =IFERROR(IF(ISNUMBER(SEARCH("Not Relevant",J105)),0,VALUE(G105)),"") -> 10 | AB105: =IFERROR(SUMIF($D:$D,D105,$AA:$AA),"") -> 150 | AC105: =IF(OR(AB105=0,AB105=""),"",AA105/AB105) -> 0.066666667 | AD105: =IF(OR(N105="",AC105=""),"",VALUE(N105)*AC105) | AE105: =IFERROR(ISNUMBER(SEARCH("Not Relevant",J105)),FALSE) -> FALSE | AF105: =IF(OR(H105="",J105=""),FALSE,IF(H105<>J105,TRUE,FALSE)) -> FALSE | AG105: =IF(AF105, COUNTIF($AF$2:AF105, TRUE), "")
A106: Measures to ensure efficient use of resources are implemented. | B106: 1 | C106: 1_9 | D106: 1_9_1 | E106: 1_9_1_9 | F106: Are costs (staff costs and other costs) measured at each stage of the production process for the key statistical outputs? | G106: 10 | J106: =IF(H106="","",H106) | L106: European Statistical Code of Practice Principle 10 | M106: =IFERROR(INDEX(__key!$D:$D,MATCH(O106&"|"&SUBSTITUTE(H106,",",";"), __key!$E:$E, 0)), "") | N106: =IFERROR(INDEX(__key!$D:$D,MATCH(O106&"|"&SUBSTITUTE(J106,",",";"), __key!$E:$E, 0)), "") | O106: BP | Q106: Cost-effectiveness practices are implemented | R106: 1919 | S106: =IFERROR(1*M106,0) -> 0 | T106: =IFERROR(1*N106,0) -> 0 | U106: =IFERROR(IF(ISNUMBER(SEARCH("Not Relevant",H106)),0,VALUE(G106)),"") -> 10 | V106: =IFERROR(SUMIF($D:$D,D106,$U:$U),"") -> 150 | W106: =IF(OR(V106=0,V106=""),"",U106/V106) -> 0.066666667 | X106: =IF(OR(M106="",W106=""),"",VALUE(M106)*W106) | Y106: =IFERROR(ISNUMBER(SEARCH("Not Relevant",H106)),FALSE) -> FALSE | Z106: =IF(Y106, COUNTIF($Y$2:Y106, TRUE), "") | AA106: =IFERROR(IF(ISNUMBER(SEARCH("Not Relevant",J106)),0,VALUE(G106)),"") -> 10 | AB106: =IFERROR(SUMIF($D:$D,D106,$AA:$AA),"") -> 150 | AC106: =IF(OR(AB106=0,AB106=""),"",AA106/AB106) -> 0.066666667 | AD106: =IF(OR(N106="",AC106=""),"",VALUE(N106)*AC106) | AE106: =IFERROR(ISNUMBER(SEARCH("Not Relevant",J106)),FALSE) -> FALSE | AF106: =IF(OR(H106="",J106=""),FALSE,IF(H106<>J106,TRUE,FALSE)) -> FALSE | AG106: =IF(AF106, COUNTIF($AF$2:AF106, TRUE), "")
A107: Measures to ensure efficient use of resources are implemented. | B107: 1 | C107: 1_9 | D107: 1_9_1 | E107: 1_9_1_10 | F107: Is information technology employed effectively to increase efficiency (e.g., use of automation, online data collection, integrated databases)? | G107: 10 | J107: =IF(H107="","",H107) | L107: European Statistical Code of Practice Principle 10 | M107: =IFERROR(INDEX(__key!$D:$D,MATCH(O107&"|"&SUBSTITUTE(H107,",",";"), __key!$E:$E, 0)), "") | N107: =IFERROR(INDEX(__key!$D:$D,MATCH(O107&"|"&SUBSTITUTE(J107,",",";"), __key!$E:$E, 0)), "") | O107: BP | Q107: Cost-effectiveness practices are implemented | R107: 19110 | S107: =IFERROR(1*M107,0) -> 0 | T107: =IFERROR(1*N107,0) -> 0 | U107: =IFERROR(IF(ISNUMBER(SEARCH("Not Relevant",H107)),0,VALUE(G107)),"") -> 10 | V107: =IFERROR(SUMIF($D:$D,D107,$U:$U),"") -> 150 | W107: =IF(OR(V107=0,V107=""),"",U107/V107) -> 0.066666667 | X107: =IF(OR(M107="",W107=""),"",VALUE(M107)*W107) | Y107: =IFERROR(ISNUMBER(SEARCH("Not Relevant",H107)),FALSE) -> FALSE | Z107: =IF(Y107, COUNTIF($Y$2:Y107, TRUE), "") | AA107: =IFERROR(IF(ISNUMBER(SEARCH("Not Relevant",J107)),0,VALUE(G107)),"") -> 10 | AB107: =IFERROR(SUMIF($D:$D,D107,$AA:$AA),"") -> 150 | AC107: =IF(OR(AB107=0,AB107=""),"",AA107/AB107) -> 0.066666667 | AD107: =IF(OR(N107="",AC107=""),"",VALUE(N107)*AC107) | AE107: =IFERROR(ISNUMBER(SEARCH("Not Relevant",J107)),FALSE) -> FALSE | AF107: =IF(OR(H107="",J107=""),FALSE,IF(H107<>J107,TRUE,FALSE)) -> FALSE | AG107: =IF(AF107, COUNTIF($AF$2:AF107, TRUE), "")
...

Sheet __lists
B2: Fully - This recommendation / best practice is fully implemented | C2: Fully - All public administrative data producers have a legal obligations to share relevant data with the NSO and other official data producers | D2: Fully - Recommended revision studies/analysis/roadmaps/standards/guidelines/procedures/policies are documented and available to all staff and posted where the public can access them | E2: Fully - This recommendation / best practice is fully implemented | F2: Fully - Allocated resources are sufficient (quality and quantity) to meet program demands | G2: Fully - Allocated resources are sufficient (quality and quantity) to meet program demands | H2: Fully - Staff compensation is above 95% of similar jobs in the public service.
B3: Highly - This recommendation / best practice is implemented but minor gaps exist in coverage and/or the consistency of its application across the program / organization | C3: Highly - Between 90% and 95% of all public administrative data producers have a legal obligation to share relevant data with the NSO and other official data producers | D3: Highly - Recommended revision studies/analysis/roadmaps/standards/guidelines/procedures/policies are documented are available to all staff but not posted for public access | E3: Highly - This recommendation / best practice is implemented but minor gaps exist in coverage and/or the consistency of its application across the program / organization | F3: Highly - Allocated resources (quality and quantity) can only meet between 90% and 95% of program demands | G3: Highly - Allocated resources (quality and quantity) can only meet between 90% and 95% of program demands | H3: Highly - Staff compensation is between 90% and 95% of similar jobs in the public service
B4: Broadly - This best practice is implemented but some gaps exist in the coverage and consistency of its application across the program / organization | C4: Broadly - Between 80% and 89% of all public administrative data producers have a legal obligation to share relevant data with the NSO and other official data producers | D4: Broadly - Recommended revision studies/analysis/roadmaps/standards/guidelines/procedures/policies are documented and available to a limited set of staff members | E4: Broadly - This best practice is implemented but some gaps exist in the coverage and consistency of its application across the program / organization | F4: Broadly - Allocated resources (quality and quantity) can only meet between 80% and 89% of program demands | G4: Broadly - Allocated resources (quality and quantity) can only meet between 80% and 89% of program demands | H4: Broadly - Staff compensation is between 80% and 89% of similar jobs in the public service
B5: Partially - This best practice is implemented but significant gaps exist in both the coverage and consistency of its application across the program / organization | C5: Partially - Between 50% and 79% of all public administrative data producers have a legal obligation to share relevant data with the NSO and other official data producers | D5: Partially - Recommended revision studies/analysis/roadmaps/standards/guidelines/procedures/policies are not documented | E5: Partially - This best practice is implemented but significant gaps exist in both the coverage and consistency of its application across the program / organization | F5: Partially - Allocated resources (quality and quantity) can only meet between 50% and 79% of program demands | G5: Partially - Allocated resources (quality and quantity) can only meet between 50% and 79% of program demands | H5: Partially - Staff compensation is between 70% and 79% of similar jobs in the public service
B6: Not aligned - This best practice is not implemented | C6: Not aligned - The statistical law does not specify that public administrative data producers have a legal obligation to share relevant data with the NSO and other official data producers | D6: Not aligned - Recommended revision studies/analysis/roadmaps/standards/guidelines/procedures and/or policies do not exist | E6: Not aligned - This best practice is not implemented | F6: Not aligned - Allocated resources (quality and quantity) can only meet less than 50% of program demands. | G6: Not aligned - Allocated resources (quality and quantity) can only meet less than 50% of program demands. | H6: Not aligned - Staff compensation is below 70% of similar jobs in the public service
E7: Not relevant - this best practice is not relevant to our statistical program | G7: Not Relevant - This organization does not produce statistics related to this domain.

Sheet __key
A1: KEY | B1: ANSWER_VALUE | C1: ANSWER_DISPLAY | D1: SCORE | E1: KEYDISPLAY
A2: BP | B2: Fully - This recommendation / best practice is fully implemented | C2: Fully - This recommendation / best practice is fully implemented | D2: 5 | E2: BP|Fully - This recommendation / best practice is fully implemented
A3: BP | B3: Highly - This recommendation / best practice is implemented but minor gaps exist in coverage and/or the consistency of its application across the program / organization | C3: Highly - This recommendation / best practice is implemented but minor gaps exist in coverage and/or the consistency of its application across the program / organization | D3: 4 | E3: BP|Highly - This recommendation / best practice is implemented but minor gaps exist in coverage and/or the consistency of its application across the program / organization
A4: BP | B4: Broadly - This best practice is implemented but some gaps exist in the coverage and consistency of its application across the program / organization | C4: Broadly - This best practice is implemented but some gaps exist in the coverage and consistency of its application across the program / organization | D4: 3 | E4: BP|Broadly - This best practice is implemented but some gaps exist in the coverage and consistency of its application across the program / organization
A5: BP | B5: Partially - This best practice is implemented but significant gaps exist in both the coverage and consistency of its application across the program / organization | C5: Partially - This best practice is implemented but significant gaps exist in both the coverage and consistency of its application across the program / organization | D5: 2 | E5: BP|Partially - This best practice is implemented but significant gaps exist in both the coverage and consistency of its application across the program / organization
A6: BP | B6: Not aligned - This best practice is not implemented | C6: Not aligned - This best practice is not implemented | D6: 0 | E6: BP|Not aligned - This best practice is not implemented
A7: BPNR | B7: Fully - This recommendation / best practice is fully implemented | C7: Fully - This recommendation / best practice is fully implemented | D7: 5 | E7: BPNR|Fully - This recommendation / best practice is fully implemented
A8: BPNR | B8: Highly - This recommendation / best practice is implemented but minor gaps exist in coverage and/or the consistency of its application across the program / organization | C8: Highly - This recommendation / best practice is implemented but minor gaps exist in coverage and/or the consistency of its application across the program / organization | D8: 4 | E8: BPNR|Highly - This recommendation / best practice is implemented but minor gaps exist in coverage and/or the consistency of its application across the program / organization
A9: BPNR | B9: Broadly - This best practice is implemented but some gaps exist in the coverage and consistency of its application across the program / organization | C9: Broadly - This best practice is implemented but some gaps exist in the coverage and consistency of its application across the program / organization | D9: 3 | E9: BPNR|Broadly - This best practice is implemented but some gaps exist in the coverage and consistency of its application across the program / organization
A10: BPNR | B10: Partially - This best practice is implemented but significant gaps exist in both the coverage and consistency of its application across the program / organization | C10: Partially - This best practice is implemented but significant gaps exist in both the coverage and consistency of its application across the program / organization | D10: 2 | E10: BPNR|Partially - This best practice is implemented but significant gaps exist in both the coverage and consistency of its application across the program / organization
A11: BPNR | B11: Not aligned - This best practice is not implemented | C11: Not aligned - This best practice is not implemented | D11: 0 | E11: BPNR|Not aligned - This best practice is not implemented
A12: BPNR | B12: Not relevant - this best practice is not relevant to our statistical program | C12: Not relevant - this best practice is not relevant to our statistical program | E12: BPNR|Not relevant - this best practice is not relevant to our statistical program
A13: CAL | B13: Fully - This concept, accounting rule, valuation method, principle of recording is fully implemented | C13: Fully - This concept; accounting rule; valuation method; principle of recording is fully implemented | D13: 5 | E13: CAL|Fully - This concept; accounting rule; valuation method; principle of recording is fully implemented
A14: CAL | B14: Highly - This concept, accounting rule, valuation method, principle of recording is fully implemented but minor gaps in coverage and/or consistency of application | C14: Highly - This concept; accounting rule; valuation method; principle of recording is fully implemented but minor gaps in coverage and/or consistency of application | D14: 4 | E14: CAL|Highly - This concept; accounting rule; valuation method; principle of recording is fully implemented but minor gaps in coverage and/or consistency of application
A15: CAL | B15: Broadly - This concept, accounting rule, valuation method, principle of recording is consistently implemented but there are some gaps in coverage and consistency of application | C15: Broadly - This concept; accounting rule; valuation method; principle of recording is consistently implemented but there are some gaps in coverage and consistency of application | D15: 3 | E15: CAL|Broadly - This concept; accounting rule; valuation method; principle of recording is consistently implemented but there are some gaps in coverage and consistency of application
A16: CAL | B16: Partially - This concept, accounting rule, valuation method, principle of recording is implemented but there are significant gaps in both coverage and consistency of application | C16: Partially - This concept; accounting rule; valuation method; principle of recording is implemented but there are significant gaps in both coverage and consistency of application | D16: 2 | E16: CAL|Partially - This concept; accounting rule; valuation method; principle of recording is implemented but there are significant gaps in both coverage and consistency of application
A17: CAL | B17: Not aligned - This concept, accounting rule, valuation method, principle of recording is not implemented | C17: Not aligned - This concept; accounting rule; valuation method; principle of recording is not implemented | D17: 0 | E17: CAL|Not aligned - This concept; accounting rule; valuation method; principle of recording is not implemented
A18: CAL | B18: Not relevant - this concept, accounting rule, valuation method, principle of recording is not relevant to our economy | C18: Not relevant - this concept; accounting rule; valuation method; principle of recording is not relevant to our economy | E18: CAL|Not relevant - this concept; accounting rule; valuation method; principle of recording is not relevant to our economy
A19: CLS_GRP | B19: Over 100 classes | C19: Over 100 classes | D19: 5 | E19: CLS_GRP|Over 100 classes
A20: CLS_GRP | B20: Between 50 and 99 classes | C20: Between 50 and 99 classes | D20: 4 | E20: CLS_GRP|Between 50 and 99 classes
A21: CLS_GRP | B21: Between 25 and 49 classes | C21: Between 25 and 49 classes | D21: 3 | E21: CLS_GRP|Between 25 and 49 classes
A22: CLS_GRP | B22: Between 10 and 24 classes | C22: Between 10 and 24 classes | D22: 2 | E22: CLS_GRP|Between 10 and 24 classes
A23: CLS_GRP | B23: Under 10 classes | C23: Under 10 classes | D23: 1 | E23: CLS_GRP|Under 10 classes
A24: CLVL | B24: Fully - Estimates are produced for the lowest level of the classification system (e.g. ISIC 4 digit, COICOP 5-digit or equivalent) | C24: Fully - Estimates are produced for the lowest level of the classification system (e.g. ISIC 4 digit; COICOP 5-digit or equivalent) | D24: 5 | E24: CLVL|Fully - Estimates are produced for the lowest level of the classification system (e.g. ISIC 4 digit; COICOP 5-digit or equivalent)
A25: CLVL | B25: Highly - Estimates are produced up to the third level of detail in the classification system (e.g. ISIC 3 digit, COICOP 4-digit or equivalent) | C25: Highly - Estimates are produced up to the third level of detail in the classification system (e.g. ISIC 3 digit; COICOP 4-digit or equivalent) | D25: 4 | E25: CLVL|Highly - Estimates are produced up to the third level of detail in the classification system (e.g. ISIC 3 digit; COICOP 4-digit or equivalent)
A26: CLVL | B26: Broadly - Estimates are produced up to the second level of detail of the classification system (e.g. ISIC 2 digit, COICOP 3-digit or equivalent) | C26: Broadly - Estimates are produced up to the second level of detail of the classification system (e.g. ISIC 2 digit; COICOP 3-digit or equivalent) | D26: 3 | E26: CLVL|Broadly - Estimates are produced up to the second level of detail of the classification system (e.g. ISIC 2 digit; COICOP 3-digit or equivalent)
A27: CLVL | B27: Partially - Estimates are only produced for the highest level of detail of the classification system (e.g. ISIC 1 digit, COICOP 2-digit or equivalent) | C27: Partially - Estimates are only produced for the highest level of detail of the classification system (e.g. ISIC 1 digit; COICOP 2-digit or equivalent) | D27: 2 | E27: CLVL|Partially - Estimates are only produced for the highest level of detail of the classification system (e.g. ISIC 1 digit; COICOP 2-digit or equivalent)
A28: CLVL | B28: Not aligned - An internationally recognized classification system or national variant is not used to classify transactions, stocks or other flows | C28: Not aligned - An internationally recognized classification system or national variant is not used to classify transactions; stocks or other flows | D28: 0 | E28: CLVL|Not aligned - An internationally recognized classification system or national variant is not used to classify transactions; stocks or other flows
A29: COMP | B29: Fully - Staff compensation is above 95% of similar jobs in the public service. | C29: Fully - Staff compensation is above 95% of similar jobs in the public service. | D29: 5 | E29: COMP|Fully - Staff compensation is above 95% of similar jobs in the public service.
A30: COMP | B30: Highly - Staff compensation is between 90% and 95% of similar jobs in the public service | C30: Highly - Staff compensation is between 90% and 95% of similar jobs in the public service | D30: 4 | E30: COMP|Highly - Staff compensation is between 90% and 95% of similar jobs in the public service
... A43: CVCL | B43: Not aligned - Less than 10% of the recommended detail (accounts, tables, items, classes, sectors, products, instruments, transaction, assets etc.) is covered / estimated | C43: Not aligned - Less than 10% of the recommended detail (accounts; tables; items; classes; sectors; products; instruments; transaction; assets etc.) is covered / estimated | D43: 0 | E43: CVCL|Not aligned - Less than 10% of the recommended detail (accounts; tables; items; classes; sectors; products; instruments; transaction; assets etc.) is covered / estimated
A44: CVCL | B44: Not relevant - The recommended detail (accounts, tables, items, classes, sectors, products, instruments, transactions, assets etc.) is not relevant to our economy | C44: Not relevant - The recommended detail (accounts; tables; items; classes; sectors; products; instruments; transactions; assets etc.) is not relevant to our economy | E44: CVCL|Not relevant - The recommended detail (accounts; tables; items; classes; sectors; products; instruments; transactions; assets etc.) is not relevant to our economy
A45: CVINT | B45: Fully - Most recently published vintage of an international endorsed classification system | C45: Fully - Most recently published vintage of an international endorsed classification system | D45: 5 | E45: CVINT|Fully - Most recently published vintage of an international endorsed classification system
A46: CVINT | B46: Highly - Most recently published vintage of a national variant with slight deviations to the internationally endorsed classification system. | C46: Highly - Most recently published vintage of a national variant with slight deviations to the internationally endorsed classification system. | D46: 4 | E46: CVINT|Highly - Most recently published vintage of a national variant with slight deviations to the internationally endorsed classification system.
A47: CVINT | B47: Broadly - Previously published vintage of an internationally endorsed classification system | C47: Broadly - Previously published vintage of an internationally endorsed classification system | D47: 3 | E47: CVINT|Broadly - Previously published vintage of an internationally endorsed classification system
A48: CVINT | B48: Partially - Previously published vintage of a national variant | C48: Partially - Previously published vintage of a national variant | D48: 2 | E48: CVINT|Partially - Previously published vintage of a national variant
A49: CVINT | B49: Not aligned - only an aggregate value is published. | C49: Not aligned - only an aggregate value is published. | D49: 0 | E49: CVINT|Not aligned - only an aggregate value is published.
A50: CVU | B50: Fully - Over 95% of the recommended (activity, transactions, stocks/flows, territory, population, units) is covered / estimated | C50: Fully - Over 95% of the recommended (activity; transactions; stocks/flows; territory; population; units) is covered / estimated | D50: 5 | E50: CVU|Fully - Over 95% of the recommended (activity; transactions; stocks/flows; territory; population; units) is covered / estimated
A51: CVU | B51: Highly - Between 90% and 94% of the recommended (activity, transactions, stocks/flows, territory, population, units) is covered / estimated | C51: Highly - Between 90% and 94% of the recommended (activity; transactions; stocks/flows; territory; population; units) is covered / estimated | D51: 4 | E51: CVU|Highly - Between 90% and 94% of the recommended (activity; transactions; stocks/flows; territory; population; units) is covered / estimated
A52: CVU | B52: Broadly - Between 80% and 89% of the recommended (activity, transactions, stocks/flows, territory, population, units) is covered / estimated | C52: Broadly - Between 80% and 89% of the recommended (activity; transactions; stocks/flows; territory; population; units) is covered / estimated | D52: 3 | E52: CVU|Broadly - Between 80% and 89% of the recommended (activity; transactions; stocks/flows; territory; population; units) is covered / estimated
A53: CVU | B53: Partially - Between 50% and 79% of the recommended (activity, transactions, stocks/flows, territory, population, units) is covered / estimated | C53: Partially - Between 50% and 79% of the recommended (activity; transactions; stocks/flows; territory; population; units) is covered / estimated | D53: 2 | E53: CVU|Partially - Between 50% and 79% of the recommended (activity; transactions; stocks/flows; territory; population; units) is covered / estimated
A54: CVU | B54: Not aligned - Less then 50% of the recommended (activity, transactions, stocks/flows, territory, population, units) is covered / estimated | C54: Not aligned - Less then 50% of the recommended (activity; transactions; stocks/flows; territory; population; units) is covered / estimated | D54: 0 | E54: CVU|Not aligned - Less then 50% of the recommended (activity; transactions; stocks/flows; territory; population; units) is covered / estimated
A55: CVUNR | B55: Fully - Over 95% of the recommended (activity, transactions, stocks/flows, territory, population, units) is covered / estimated | C55: Fully - Over 95% of the recommended (activity; transactions; stocks/flows; territory; population; units) is covered / estimated | D55: 5 | E55: CVUNR|Fully - Over 95% of the recommended (activity; transactions; stocks/flows; territory; population; units) is covered / estimated
A56: CVUNR | B56: Highly - Between 90% and 94% of the recommended (activity, transactions, stocks/flows, territory, population, units) is covered / estimated | C56: Highly - Between 90% and 94% of the recommended (activity; transactions; stocks/flows; territory; population; units) is covered / estimated | D56: 4 | E56: CVUNR|Highly - Between 90% and 94% of the recommended (activity; transactions; stocks/flows; territory; population; units) is covered / estimated
... A59: CVUNR | B59: Not aligned - Less then 50% of the recommended (activity, transactions, stocks/flows, territory, population, units) is covered / estimated | C59: Not aligned - Less then 50% of the recommended (activity; transactions; stocks/flows; territory; population; units) is covered / estimated | D59: 0 | E59: CVUNR|Not aligned - Less then 50% of the recommended (activity; transactions; stocks/flows; territory; population; units) is covered / estimated
A60: CVUNR | B60: Not relevant - this concept, accounting rule, valuation method, principle of recording is not relevant to our economy | C60: Not relevant - this concept; accounting rule; valuation method; principle of recording is not relevant to our economy | E60: CVUNR|Not relevant - this concept; accounting rule; valuation method; principle of recording is not relevant to our economy
A61: DS | B61: Fully - All public administrative data producers have a legal obligations to share relevant data with the NSO and other official data producers | C61: Fully - All public administrative data producers have a legal obligations to share relevant data with the NSO and other official data producers | D61: 5 | E61: DS|Fully - All public administrative data producers have a legal obligations to share relevant data with the NSO and other official data producers
A62: DS | B62: Highly - Between 90% and 95% of all public administrative data producers have a legal obligation to share relevant data with the NSO and other official data producers | C62: Highly - Between 90% and 95% of all public administrative data producers have a legal obligation to share relevant data with the NSO and other official data producers | D62: 4 | E62: DS|Highly - Between 90% and 95% of all public administrative data producers have a legal obligation to share relevant data with the NSO and other official data producers
A63: DS | B63: Broadly - Between 80% and 89% of all public administrative data producers have a legal obligation to share relevant data with the NSO and other official data producers | C63: Broadly - Between 80% and 89% of all public administrative data producers have a legal obligation to share relevant data with the NSO and other official data producers | D63: 3 | E63: DS|Broadly - Between 80% and 89% of all public administrative data producers have a legal obligation to share relevant data with the NSO and other official data producers
A64: DS | B64: Partially - Between 50% and 79% of all public administrative data producers have a legal obligation to share relevant data with the NSO and other official data producers | C64: Partially - Between 50% and 79% of all public administrative data producers have a legal obligation to share relevant data with the NSO and other official data producers | D64: 2 | E64: DS|Partially - Between 50% and 79% of all public administrative data producers have a legal obligation to share relevant data with the NSO and other official data producers
A65: DS | B65: Not aligned - The statistical law does not specify that public administrative data producers have a legal obligation to share relevant data with the NSO and other official data producers | C65: Not aligned - The statistical law does not specify that public administrative data producers have a legal obligation to share relevant data with the NSO and other official data producers | D65: 0 | E65: DS|Not aligned - The statistical law does not specify that public administrative data producers have a legal obligation to share relevant data with the NSO and other official data producers
A66: EIC | B66: For the calculation of elementary indices, the unweighted geometric mean of price relatives (Jevons) is used. | C66: For the calculation of elementary indices; the unweighted geometric mean of price relatives (Jevons) is used. | D66: 5 | E66: EIC|For the calculation of elementary indices; the unweighted geometric mean of price relatives (Jevons) is used.
A67: EIC | B67: For the calculation of elementary indices, the ratio of the unweighted arithmetic average of prices (Dutot) is used. | C67: For the calculation of elementary indices; the ratio of the unweighted arithmetic average of prices (Dutot) is used. | D67: 2 | E67: EIC|For the calculation of elementary indices; the ratio of the unweighted arithmetic average of prices (Dutot) is used.
A68: EIC | B68: For the calculation of elementary indices, the arithmetic average of price relatives (Carli) is used? | C68: For the calculation of elementary indices; the arithmetic average of price relatives (Carli) is used? | D68: 0 | E68: EIC|For the calculation of elementary indices; the arithmetic average of price relatives (Carli) is used?
A69: ETBV | B69: Fully - Code of ethics and ethical standards are documented and posted publicly where staff can access them, review and certify every year. | C69: Fully - Code of ethics and ethical standards are documented and posted publicly where staff can access them; review and certify every year. | D69: 5 | E69: ETBV|Fully - Code of ethics and ethical standards are documented and posted publicly where staff can access them; review and certify every year.
A70: ETBV | B70: Highly - Code of ethics and ethical standards are documented are available to all staff but not posted for public access and reviewed by staff once per year | C70: Highly - Code of ethics and ethical standards are documented are available to all staff but not posted for public access and reviewed by staff once per year | D70: 4 | E70: ETBV|Highly - Code of ethics and ethical standards are documented are available to all staff but not posted for public access and reviewed by staff once per year
A71: ETBV | B71: Broadly - Code of ethics and ethical standards are documented and available to a limited number of staff members and are reviewed by staff occasionally | C71: Broadly - Code of ethics and ethical standards are documented and available to a limited number of staff members and are reviewed by staff occasionally | D71: 3 | E71: ETBV|Broadly - Code of ethics and ethical standards are documented and available to a limited number of staff members and are reviewed by staff occasionally
A72: ETBV | B72: Partially - Code of ethics and ethical standards are documented and available to a limited number of staff members but are not reviewed | C72: Partially - Code of ethics and ethical standards are documented and available to a limited number of staff members but are not reviewed | D72: 2 | E72: ETBV|Partially - Code of ethics and ethical standards are documented and available to a limited number of staff members but are not reviewed
... A87: FREQNR | B87: Not published | C87: Not published | D87: 0 | E87: FREQNR|Not published
A88: FREQNR | B88: Not relevant | C88: Not relevant | E88: FREQNR|Not relevant
A89: FREQNRDC | B89: Daily | C89: Daily | D89: 5 | E89: FREQNRDC|Daily
A90: FREQNRDC | B90: Monthly | C90: Monthly | D90: 5 | E90: FREQNRDC|Monthly
A91: FREQNRDC | B91: Quarterly | C91: Quarterly | D91: 4 | E91: FREQNRDC|Quarterly
A92: FREQNRDC | B92: Annual | C92: Annual | D92: 3 | E92: FREQNRDC|Annual
A93: FREQNRDC | B93: Bi-Annual | C93: Bi-Annual | D93: 2 | E93: FREQNRDC|Bi-Annual
A94: FREQNRDC | B94: Not aligned - Less than bi-annual | C94: Not aligned - Less than bi-annual | D94: 1 | E94: FREQNRDC|Not aligned - Less than bi-annual
A95: FREQNRDC | B95: Not published | C95: Not published | D95: 0 | E95: FREQNRDC|Not published
A96: FREQNRDC | B96: Not relevant | C96: Not relevant | E96: FREQNRDC|Not relevant
A97: FREQNROFC | B97: Daily | C97: Daily | D97: 5 | E97: FREQNROFC|Daily
A98: FREQNROFC | B98: Monthly | C98: Monthly | D98: 5 | E98: FREQNROFC|Monthly
A99: FREQNROFC | B99: Quarterly | C99: Quarterly | D99: 5 | E99: FREQNROFC|Quarterly
A100: FREQNROFC | B100: Annual | C100: Annual | D100: 3 | E100: FREQNROFC|Annual
A101: FREQNROFC | B101: Bi-Annual | C101: Bi-Annual | D101: 2 | E101: FREQNROFC|Bi-Annual
A102: FREQNROFC | B102: Not aligned - Less than bi-annual | C102: Not aligned - Less than bi-annual | D102: 1 | E102: FREQNROFC|Not aligned - Less than bi-annual
A103: FREQNROFC | B103: Not published | C103: Not published | D103: 0 | E103: FREQNROFC|Not published
A104: FREQNROFC | B104: Not relevant | C104: Not relevant | E104: FREQNROFC|Not relevant
A105: INIT | B105: Fully - National Statistical Organizations have full autonomy in determining data sources, statistical concepts and methods and in hiring staff | C105: Fully - National Statistical Organizations have full autonomy in determining data sources; statistical concepts and methods and in hiring staff | D105: 5 | E105: INIT|Fully - National Statistical Organizations have full autonomy in determining data sources; statistical concepts and methods and in hiring staff
A106: INIT | B106: Highly - National Statistical Organizations have full autonomy in determining data sources, statistical concepts and methods but limited autonomy in hiring staff | C106: Highly - National Statistical Organizations have full autonomy in determining data sources; statistical concepts and methods but limited autonomy in hiring staff | D106: 4 | E106: INIT|Highly - National Statistical Organizations have full autonomy in determining data sources; statistical concepts and methods but limited autonomy in hiring staff
A107: INIT | B107: Broadly - National Statistical Organizations have limited autonomy in determining data sources, statistical concepts and methods and full autonomy in hiring staff | C107: Broadly - National Statistical Organizations have limited autonomy in determining data sources; statistical concepts and methods and full autonomy in hiring staff | D107: 3 | E107: INIT|Broadly - National Statistical Organizations have limited autonomy in determining data sources; statistical concepts and methods and full autonomy in hiring staff
A108: INIT | B108: Partially - National Statistical Organizations have limited autonomy in determining data sources, statistical concepts and methods and in hiring staff | C108: Partially - National Statistical Organizations have limited autonomy in determining data sources; statistical concepts and methods and in hiring staff | D108: 2 | E108: INIT|Partially - National Statistical Organizations have limited autonomy in determining data sources; statistical concepts and methods and in hiring staff
A109: INIT | B109: Not aligned - National Statistical Organizations do not have autonomy in determining data sources, statistical concepts and methods and in hiring staff | C109: Not aligned - National Statistical Organizations do not have autonomy in determining data sources; statistical concepts and methods and in hiring staff | D109: 0 | E109: INIT|Not aligned - National Statistical Organizations do not have autonomy in determining data sources; statistical concepts and methods and in hiring staff
A110: OOH | B110: Rental equivalence used to measure OOH | C110: Rental equivalence used to measure OOH | D110: 5 | E110: OOH|Rental equivalence used to measure OOH
A111: OOH | B111: Net acquisitions approach used to measure OOH | C111: Net acquisitions approach used to measure OOH | D111: 5 | E111: OOH|Net acquisitions approach used to measure OOH
A112: OOH | B112: User cost approach used to measure OOH | C112: User cost approach used to measure OOH | D112: 5 | E112: OOH|User cost approach used to measure OOH
A113: OOH | B113: Payments approach used to measure OOH | C113: Payments approach used to measure OOH | D113: 0 | E113: OOH|Payments approach used to measure OOH
A114: OOH | B114: OOH excluded from the CPI | C114: OOH excluded from the CPI | D114: 0 | E114: OOH|OOH excluded from the CPI
A115: PC | B115: For a monthly CPI, price collection for all good and services takes place during all 4 weeks in the month. | C115: For a monthly CPI; price collection for all good and services takes place during all 4 weeks in the month. | D115: 5 | E115: PC|For a monthly CPI; price collection for all good and services takes place during all 4 weeks in the month.
A116: PC | B116: For a monthly CPI, price collection for all good and services is limited to a period of no more than 3 weeks | C116: For a monthly CPI; price collection for all good and services is limited to a period of no more than 3 weeks | D116: 4 | E116: PC|For a monthly CPI; price collection for all good and services is limited to a period of no more than 3 weeks
... A132: RESNR | B132: Not aligned - Allocated resources (quality and quantity) can only meet less than 50% of program demands. | C132: Not aligned - Allocated resources (quality and quantity) can only meet less than 50% of program demands. | D132: 1 | E132: RESNR|Not aligned - Allocated resources (quality and quantity) can only meet less than 50% of program demands.
A133: RESNR | B133: Not Relevant - This organization does not produce statistics related to this domain. | C133: Not Relevant - This organization does not produce statistics related to this domain. | E133: RESNR|Not Relevant - This organization does not produce statistics related to this domain.
A134: SASDA | B134: Fully - Sub-annual source data are available for every period and fully cover the target population | C134: Fully - Sub-annual source data are available for every period and fully cover the target population | D134: 5 | E134: SASDA|Fully - Sub-annual source data are available for every period and fully cover the target population
A135: SASDA | B135: Highly - Sub-annual source data are available for every period and cover between 90% and 95% of the target population | C135: Highly - Sub-annual source data are available for every period and cover between 90% and 95% of the target population | D135: 4 | E135: SASDA|Highly - Sub-annual source data are available for every period and cover between 90% and 95% of the target population
A136: SASDA | B136: Broadly - Sub-annual source data are available for every period and cover between 80% and 89% of the target population | C136: Broadly - Sub-annual source data are available for every period and cover between 80% and 89% of the target population | D136: 3 | E136: SASDA|Broadly - Sub-annual source data are available for every period and cover between 80% and 89% of the target population
A137: SASDA | B137: Partially - Sub-annual source data are available for every period and cover between 50% and 79% of the population | C137: Partially - Sub-annual source data are available for every period and cover between 50% and 79% of the population | D137: 2 | E137: SASDA|Partially - Sub-annual source data are available for every period and cover between 50% and 79% of the population
A138: SASDA | B138: Not aligned - Sub-annual source data are not avaliable for every period and/or cover less than 50% of the target population. | C138: Not aligned - Sub-annual source data are not avaliable for every period and/or cover less than 50% of the target population. | D138: 0 | E138: SASDA|Not aligned - Sub-annual source data are not avaliable for every period and/or cover less than 50% of the target population.
A139: SASDANR | B139: Fully - Sub-annual source data are available for every period and fully cover the target population | C139: Fully - Sub-annual source data are available for every period and fully cover the target population | D139: 5 | E139: SASDANR|Fully - Sub-annual source data are available for every period and fully cover the target population
A140: SASDANR | B140: Highly - Sub-annual source data are available for every period and cover between 90% and 95% of the target population | C140: Highly - Sub-annual source data are available for every period and cover between 90% and 95% of the target population | D140: 4 | E140: SASDANR|Highly - Sub-annual source data are available for every period and cover between 90% and 95% of the target population
A141: SASDANR | B141: Broadly - Sub-annual source data are available for every period and cover between 80% and 89% of the target population | C141: Broadly - Sub-annual source data are available for every period and cover between 80% and 89% of the target population | D141: 3 | E141: SASDANR|Broadly - Sub-annual source data are available for every period and cover between 80% and 89% of the target population
A142: SASDANR | B142: Partially - Sub-annual source data are available for every period and cover between 50% and 79% of the population | C142: Partially - Sub-annual source data are available for every period and cover between 50% and 79% of the population | D142: 2 | E142: SASDANR|Partially - Sub-annual source data are available for every period and cover between 50% and 79% of the population
A143: SASDANR | B143: Not aligned - Sub-annual source data are not available for every period and cover less than 50% of the target population | C143: Not aligned - Sub-annual source data are not available for every period and cover less than 50% of the target population | D143: 0 | E143: SASDANR|Not aligned - Sub-annual source data are not available for every period and cover less than 50% of the target population
...

Sheet __weights_indicator
A1: ID | B1: Weight
A2: 1_10_1 | B2: 1
A3: 1_11_1 | B3: 1
A4: 1_1_1 | B4: 1
A5: 1_2_1 | B5: 1
A6: 1_3_1 | B6: 1
A7: 1_4_1 | B7: 0.38461538
A8: 1_4_2 | B8: 0.46153846
A9: 1_4_3 | B9: 0.15384615
A10: 1_5_1 | B10: 1
A11: 1_6_1 | B11: 1
A12: 1_7_1 | B12: 1
A13: 1_8_1 | B13: 1
... A70: 5_6_2 | B70: 0.5

Sheet __weights_element
A1: ID | B1: Name | C1: Weight
A2: 1_1 | B2: The legal framework defining the national statistical system is comprehensive | C2: 0.1
A3: 1_2 | B3: Professional independence is ensured | C3: 0.2
A4: 1_3 | B4: Effective coordination of the national statistical system | C4: 0.15
A5: 1_4 | B5: Statistical confidentiality and data security are assured | C5: 0.1
A6: 1_5 | B6: Response burden is minimized | C6: 0.1
A7: 1_6 | B7: Human resources are adequate | C7: 0.15
A8: 1_7 | B8: Information technology resources are adequate | C8: 0.05
A9: 1_8 | B9: Physical infrastructure is adequate | C9: 0.05
A10: 1_9 | B10: Cost-effectiveness practices are implemented | C10: 0.05
A11: 1_10 | B11: Processes are in place to maintain relevance | C11: 0.025
A12: 1_11 | B12: Quality management practices are implemented | C12: 0.025
A13: 2_1 | B13: Institutional integrity is ensured | C13: 0.6
... A32: 5_6 | B32: Assistance to users is provided | C32: 0.05

Sheet __rbp_p
A1: RBP_ID | B1: RBP_P
A2: 1_1_1_1 | B2: A statistical law or other relevant law establishes a clear legal framework for the development, production, and dissemination of official statistics.
A3: 1_1_1_2 | B3: A statistical law or other relevant law clearly defines “official statistics” and distinguishes them from other statistics (e.g., administrative or private statistics).
A4: 1_1_1_3 | B4: The Fundamental Principle of Official Statistics—Relevance, Impartiality, and Equal Access—is embedded in the statistical law or other relevant law.
A5: 1_1_1_4 | B5: The statistical law or other relevant law provides a clear mandate for producers to collect data (including compulsory surveys when necessary) when such data are not otherwise available.
A6: 1_1_1_5 | B6: The statistical law or other relevant law overrides conflicting provisions in other legislation, or requires other laws to comply with statistical requirements where needed.
A7: 1_1_1_6 | B7: The statistical law or other relevant law has been updated recently, and the date of the most recent update is documented.
A8: 1_1_1_7 | B8: The Fundamental Principle of Official Statistics—Professional Standards, Scientific Principles, and Professional Ethics—is embedded in the statistical law or other relevant law.
A9: 1_1_1_8 | B9: The Fundamental Principle of Official Statistics—Accountability and Transparency—is embedded in the statistical law or other relevant law.
A10: 1_1_1_9 | B10: The Fundamental Principle of Official Statistics—Prevention of Misuse—is embedded in the statistical law or other relevant law.
A11: 1_2_1_1 | B11: A National Statistical Office (NSO), department, or organizational unit is designated as a professionally independent body and recognized as the leading authority of the national statistical system.
A12: 1_2_1_2 | B12: The National Statistical Office (or equivalent) has full autonomy over statistical methods, data sources, content, and the timing of releases, free from political or administrative interference.
... A636: 5_2_1_13 | B636: The timeliness of labor market wage/earnings statistics is defined and assessed.

Sheet Maturity by Indicator
A1: QIND_ID | B1: Quality Indicator | C1: Current Maturity (0-100) | D1: Target Maturity (0-100) | E1: S&Cs Observed | F1: Total S&C | G1: % Observed | H1: Fully Observed | I1: % Fully Observed | J1: IND_WEIGHT | K1: WEIGHTED_MATURITY | L1: ELEM_ID | M1: WEIGHTED_MATURITY_TGT
A2: 1_1_1 | B2: =IFERROR(INDEX(DQAF_Input!$A:$A,MATCH(A2,DQAF_Input!$D:$D,0)),"") -> The responsibility for collecting, processing, and disseminating official statistics is clearly specified in law | C2: =IFERROR((SUMIF(DQAF_Input!$D:$D,A2,DQAF_Input!$X:$X)/5)*100,"") -> 62.666667 | D2: =IFERROR((SUMIF(DQAF_Input!$D:$D,A2,DQAF_Input!$AD:$AD)/5)*100,"") -> 77.733333 | E2: =IFERROR(COUNTIFS(DQAF_Input!$D:$D,A2,DQAF_Input!$S:$S,"<>0"),0) -> 11 | F2: =IFERROR(COUNTIF(DQAF_Input!$D:$D,A2),0) -> 15 | G2: =IF(F2=0,"",E2/F2) -> 0.73333333 | H2: =IFERROR(COUNTIFS(DQAF_Input!$D:$D,A2,DQAF_Input!$S:$S,5),0) -> 2 | I2: =IF(F2=0,"",H2/F2) -> 0.13333333 | J2: =IFERROR(INDEX(__weights_indicator!$B:$B,MATCH(A2,__weights_indicator!$A:$A,0)),"") -> 1 | K2: =IF(OR(J2="",C2=""),"",J2*C2) -> 62.666667 | L2: =IFERROR(LEFT(A2,FIND("_",A2,FIND("_",A2)+1)-1),A2) -> 1_1 | M2: =IF(OR(J2="",D2=""),"",J2*D2) -> 77.733333
A3: 1_2_1 | B3: =IFERROR(INDEX(DQAF_Input!$A:$A,MATCH(A3,DQAF_Input!$D:$D,0)),"") -> The statistical organization operates independently and is free from political influence | C3: =IFERROR((SUMIF(DQAF_Input!$D:$D,A3,DQAF_Input!$X:$X)/5)*100,"") -> 70 | D3: =IFERROR((SUMIF(DQAF_Input!$D:$D,A3,DQAF_Input!$AD:$AD)/5)*100,"") -> 75 | E3: =IFERROR(COUNTIFS(DQAF_Input!$D:$D,A3,DQAF_Input!$S:$S,"<>0"),0) -> 3 | F3: =IFERROR(COUNTIF(DQAF_Input!$D:$D,A3),0) -> 4 | G3: =IF(F3=0,"",E3/F3) -> 0.75 | H3: =IFERROR(COUNTIFS(DQAF_Input!$D:$D,A3,DQAF_Input!$S:$S,5),0) -> 2 | I3: =IF(F3=0,"",H3/F3) -> 0.5 | J3: =IFERROR(INDEX(__weights_indicator!$B:$B,MATCH(A3,__weights_indicator!$A:$A,0)),"") -> 1 | K3: =IF(OR(J3="",C3=""),"",J3*C3) -> 70 | L3: =IFERROR(LEFT(A3,FIND("_",A3,FIND("_",A3)+1)-1),A3) -> 1_2 | M3: =IF(OR(J3="",D3=""),"",J3*D3) -> 75
A4: 1_3_1 | B4: =IFERROR(INDEX(DQAF_Input!$A:$A,MATCH(A4,DQAF_Input!$D:$D,0)),"") -> Data sharing and coordination among data-producing agencies are effective | C4: =IFERROR((SUMIF(DQAF_Input!$D:$D,A4,DQAF_Input!$X:$X)/5)*100,"") -> 0 | D4: =IFERROR((SUMIF(DQAF_Input!$D:$D,A4,DQAF_Input!$AD:$AD)/5)*100,"") -> 0 | E4: =IFERROR(COUNTIFS(DQAF_Input!$D:$D,A4,DQAF_Input!$S:$S,"<>0"),0) -> 0 | F4: =IFERROR(COUNTIF(DQAF_Input!$D:$D,A4),0) -> 17 | G4: =IF(F4=0,"",E4/F4) -> 0 | H4: =IFERROR(COUNTIFS(DQAF_Input!$D:$D,A4,DQAF_Input!$S:$S,5),0) -> 0 | I4: =IF(F4=0,"",H4/F4) -> 0 | J4: =IFERROR(INDEX(__weights_indicator!$B:$B,MATCH(A4,__weights_indicator!$A:$A,0)),"") -> 1 | K4: =IF(OR(J4="",C4=""),"",J4*C4) -> 0 | L4: =IFERROR(LEFT(A4,FIND("_",A4,FIND("_",A4)+1)-1),A4) -> 1_3 | M4: =IF(OR(J4="",D4=""),"",J4*D4) -> 0
A5: 1_4_1 | B5: =IFERROR(INDEX(DQAF_Input!$A:$A,MATCH(A5,DQAF_Input!$D:$D,0)),"") -> Individual reporters’ data are kept confidential and used for statistical purposes only | C5: =IFERROR((SUMIF(DQAF_Input!$D:$D,A5,DQAF_Input!$X:$X)/5)*100,"") -> 0 | D5: =IFERROR((SUMIF(DQAF_Input!$D:$D,A5,DQAF_Input!$AD:$AD)/5)*100,"") -> 0 | E5: =IFERROR(COUNTIFS(DQAF_Input!$D:$D,A5,DQAF_Input!$S:$S,"<>0"),0) -> 0 | F5: =IFERROR(COUNTIF(DQAF_Input!$D:$D,A5),0) -> 5 | G5: =IF(F5=0,"",E5/F5) -> 0 | H5: =IFERROR(COUNTIFS(DQAF_Input!$D:$D,A5,DQAF_Input!$S:$S,5),0) -> 0 | I5: =IF(F5=0,"",H5/F5) -> 0 | J5: =IFERROR(INDEX(__weights_indicator!$B:$B,MATCH(A5,__weights_indicator!$A:$A,0)),"") -> 0.38461538 | K5: =IF(OR(J5="",C5=""),"",J5*C5) -> 0 | L5: =IFERROR(LEFT(A5,FIND("_",A5,FIND("_",A5)+1)-1),A5) -> 1_4 | M5: =IF(OR(J5="",D5=""),"",J5*D5) -> 0
A6: 1_4_2 | B6: =IFERROR(INDEX(DQAF_Input!$A:$A,MATCH(A6,DQAF_Input!$D:$D,0)),"") -> Access to data is restricted to individuals who require access to carry out their statistical functions. | C6: =IFERROR((SUMIF(DQAF_Input!$D:$D,A6,DQAF_Input!$X:$X)/5)*100,"") -> 0 | D6: =IFERROR((SUMIF(DQAF_Input!$D:$D,A6,DQAF_Input!$AD:$AD)/5)*100,"") -> 0 | E6: =IFERROR(COUNTIFS(DQAF_Input!$D:$D,A6,DQAF_Input!$S:$S,"<>0"),0) -> 0 | F6: =IFERROR(COUNTIF(DQAF_Input!$D:$D,A6),0) -> 6 | G6: =IF(F6=0,"",E6/F6) -> 0 | H6: =IFERROR(COUNTIFS(DQAF_Input!$D:$D,A6,DQAF_Input!$S:$S,5),0) -> 0 | I6: =IF(F6=0,"",H6/F6) -> 0 | J6: =IFERROR(INDEX(__weights_indicator!$B:$B,MATCH(A6,__weights_indicator!$A:$A,0)),"") -> 0.46153846 | K6: =IF(OR(J6="",C6=""),"",J6*C6) -> 0 | L6: =IFERROR(LEFT(A6,FIND("_",A6,FIND("_",A6)+1)-1),A6) -> 1_4 | M6: =IF(OR(J6="",D6=""),"",J6*D6) -> 0
A7: 1_4_3 | B7: =IFERROR(INDEX(DQAF_Input!$A:$A,MATCH(A7,DQAF_Input!$D:$D,0)),"") -> Penalties are prescribed for willful breaches of statistical confidentiality | C7: =IFERROR((SUMIF(DQAF_Input!$D:$D,A7,DQAF_Input!$X:$X)/5)*100,"") -> 0 | D7: =IFERROR((SUMIF(DQAF_Input!$D:$D,A7,DQAF_Input!$AD:$AD)/5)*100,"") -> 0 | E7: =IFERROR(COUNTIFS(DQAF_Input!$D:$D,A7,DQAF_Input!$S:$S,"<>0"),0) -> 0 | F7: =IFERROR(COUNTIF(DQAF_Input!$D:$D,A7),0) -> 2 | G7: =IF(F7=0,"",E7/F7) -> 0 | H7: =IFERROR(COUNTIFS(DQAF_Input!$D:$D,A7,DQAF_Input!$S:$S,5),0) -> 0 | I7: =IF(F7=0,"",H7/F7) -> 0 | J7: =IFERROR(INDEX(__weights_indicator!$B:$B,MATCH(A7,__weights_indicator!$A:$A,0)),"") -> 0.15384615 | K7: =IF(OR(J7="",C7=""),"",J7*C7) -> 0 | L7: =IFERROR(LEFT(A7,FIND("_",A7,FIND("_",A7)+1)-1),A7) -> 1_4 | M7: =IF(OR(J7="",D7=""),"",J7*D7) -> 0
A8: 1_5_1 | B8: =IFERROR(INDEX(DQAF_Input!$A:$A,MATCH(A8,DQAF_Input!$D:$D,0)),"") -> Response burden on data providers is minimized | C8: =IFERROR((SUMIF(DQAF_Input!$D:$D,A8,DQAF_Input!$X:$X)/5)*100,"") -> 0 | D8: =IFERROR((SUMIF(DQAF_Input!$D:$D,A8,DQAF_Input!$AD:$AD)/5)*100,"") -> 0 | E8: =IFERROR(COUNTIFS(DQAF_Input!$D:$D,A8,DQAF_Input!$S:$S,"<>0"),0) -> 0 | F8: =IFERROR(COUNTIF(DQAF_Input!$D:$D,A8),0) -> 3 | G8: =IF(F8=0,"",E8/F8) -> 0 | H8: =IFERROR(COUNTIFS(DQAF_Input!$D:$D,A8,DQAF_Input!$S:$S,5),0) -> 0 | I8: =IF(F8=0,"",H8/F8) -> 0 | J8: =IFERROR(INDEX(__weights_indicator!$B:$B,MATCH(A8,__weights_indicator!$A:$A,0)),"") -> 1 | K8: =IF(OR(J8="",C8=""),"",J8*C8) -> 0 | L8: =IFERROR(LEFT(A8,FIND("_",A8,FIND("_",A8)+1)-1),A8) -> 1_5 | M8: =IF(OR(J8="",D8=""),"",J8*D8) -> 0
A9: 1_6_1 | B9: =IFERROR(INDEX(DQAF_Input!$A:$A,MATCH(A9,DQAF_Input!$D:$D,0)),"") -> Staffing levels are commensurate with the scope of the statistical program(s) managed by the organization. | C9: =IFERROR((SUMIF(DQAF_Input!$D:$D,A9,DQAF_Input!$X:$X)/5)*100,"") -> 0 | D9: =IFERROR((SUMIF(DQAF_Input!$D:$D,A9,DQAF_Input!$AD:$AD)/5)*100,"") -> 0 | E9: =IFERROR(COUNTIFS(DQAF_Input!$D:$D,A9,DQAF_Input!$S:$S,"<>0"),0) -> 0 | F9: =IFERROR(COUNTIF(DQAF_Input!$D:$D,A9),0) -> 24 | G9: =IF(F9=0,"",E9/F9) -> 0 | H9: =IFERROR(COUNTIFS(DQAF_Input!$D:$D,A9,DQAF_Input!$S:$S,5),0) -> 0 | I9: =IF(F9=0,"",H9/F9) -> 0 | J9: =IFERROR(INDEX(__weights_indicator!$B:$B,MATCH(A9,__weights_indicator!$A:$A,0)),"") -> 1 | K9: =IF(OR(J9="",C9=""),"",J9*C9) -> 0 | L9: =IFERROR(LEFT(A9,FIND("_",A9,FIND("_",A9)+1)-1),A9) -> 1_6 | M9: =IF(OR(J9="",D9=""),"",J9*D9) -> 0
A10: 1_7_1 | B10: =IFERROR(INDEX(DQAF_Input!$A:$A,MATCH(A10,DQAF_Input!$D:$D,0)),"") -> Computing resources are commensurate with the scope of the statistical program(s) managed by the organization. | C10: =IFERROR((SUMIF(DQAF_Input!$D:$D,A10,DQAF_Input!$X:$X)/5)*100,"") -> 0 | D10: =IFERROR((SUMIF(DQAF_Input!$D:$D,A10,DQAF_Input!$AD:$AD)/5)*100,"") -> 0 | E10: =IFERROR(COUNTIFS(DQAF_Input!$D:$D,A10,DQAF_Input!$S:$S,"<>0"),0) -> 0 | F10: =IFERROR(COUNTIF(DQAF_Input!$D:$D,A10),0) -> 5 | G10: =IF(F10=0,"",E10/F10) -> 0 | H10: =IFERROR(COUNTIFS(DQAF_Input!$D:$D,A10,DQAF_Input!$S:$S,5),0) -> 0 | I10: =IF(F10=0,"",H10/F10) -> 0 | J10: =IFERROR(INDEX(__weights_indicator!$B:$B,MATCH(A10,__weights_indicator!$A:$A,0)),"") -> 1 | K10: =IF(OR(J10="",C10=""),"",J10*C10) -> 0 | L10: =IFERROR(LEFT(A10,FIND("_",A10,FIND("_",A10)+1)-1),A10) -> 1_7 | M10: =IF(OR(J10="",D10=""),"",J10*D10) -> 0
A11: 1_8_1 | B11: =IFERROR(INDEX(DQAF_Input!$A:$A,MATCH(A11,DQAF_Input!$D:$D,0)),"") -> Facilities are commensurate with the scope of the statistical program(s) managed by the organization. | C11: =IFERROR((SUMIF(DQAF_Input!$D:$D,A11,DQAF_Input!$X:$X)/5)*100,"") -> 0 | D11: =IFERROR((SUMIF(DQAF_Input!$D:$D,A11,DQAF_Input!$AD:$AD)/5)*100,"") -> 0 | E11: =IFERROR(COUNTIFS(DQAF_Input!$D:$D,A11,DQAF_Input!$S:$S,"<>0"),0) -> 0 | F11: =IFERROR(COUNTIF(DQAF_Input!$D:$D,A11),0) -> 3 | G11: =IF(F11=0,"",E11/F11) -> 0 | H11: =IFERROR(COUNTIFS(DQAF_Input!$D:$D,A11,DQAF_Input!$S:$S,5),0) -> 0 | I11: =IF(F11=0,"",H11/F11) -> 0 | J11: =IFERROR(INDEX(__weights_indicator!$B:$B,MATCH(A11,__weights_indicator!$A:$A,0)),"") -> 1 | K11: =IF(OR(J11="",C11=""),"",J11*C11) -> 0 | L11: =IFERROR(LEFT(A11,FIND("_",A11,FIND("_",A11)+1)-1),A11) -> 1_8 | M11: =IF(OR(J11="",D11=""),"",J11*D11) -> 0
A12: 1_9_1 | B12: =IFERROR(INDEX(DQAF_Input!$A:$A,MATCH(A12,DQAF_Input!$D:$D,0)),"") -> Measures to ensure efficient use of resources are implemented. | C12: =IFERROR((SUMIF(DQAF_Input!$D:$D,A12,DQAF_Input!$X:$X)/5)*100,"") -> 0 | D12: =IFERROR((SUMIF(DQAF_Input!$D:$D,A12,DQAF_Input!$AD:$AD)/5)*100,"") -> 0 | E12: =IFERROR(COUNTIFS(DQAF_Input!$D:$D,A12,DQAF_Input!$S:$S,"<>0"),0) -> 0 | F12: =IFERROR(COUNTIF(DQAF_Input!$D:$D,A12),0) -> 15 | G12: =IF(F12=0,"",E12/F12) -> 0 | H12: =IFERROR(COUNTIFS(DQAF_Input!$D:$D,A12,DQAF_Input!$S:$S,5),0) -> 0 | I12: =IF(F12=0,"",H12/F12) -> 0 | J12: =IFERROR(INDEX(__weights_indicator!$B:$B,MATCH(A12,__weights_indicator!$A:$A,0)),"") -> 1 | K12: =IF(OR(J12="",C12=""),"",J12*C12) -> 0 | L12: =IFERROR(LEFT(A12,FIND("_",A12,FIND("_",A12)+1)-1),A12) -> 1_9 | M12: =IF(OR(J12="",D12=""),"",J12*D12) -> 0
A13: 1_10_1 | B13: =IFERROR(INDEX(DQAF_Input!$A:$A,MATCH(A13,DQAF_Input!$D:$D,0)),"") -> The relevance and practical utility of existing statistics in meeting users’ needs are monitored. | C13: =IFERROR((SUMIF(DQAF_Input!$D:$D,A13,DQAF_Input!$X:$X)/5)*100,"") -> 0 | D13: =IFERROR((SUMIF(DQAF_Input!$D:$D,A13,DQAF_Input!$AD:$AD)/5)*100,"") -> 0 | E13: =IFERROR(COUNTIFS(DQAF_Input!$D:$D,A13,DQAF_Input!$S:$S,"<>0"),0) -> 0 | F13: =IFERROR(COUNTIF(DQAF_Input!$D:$D,A13),0) -> 7 | G13: =IF(F13=0,"",E13/F13) -> 0 | H13: =IFERROR(COUNTIFS(DQAF_Input!$D:$D,A13,DQAF_Input!$S:$S,5),0) -> 0 | I13: =IF(F13=0,"",H13/F13) -> 0 | J13: =IFERROR(INDEX(__weights_indicator!$B:$B,MATCH(A13,__weights_indicator!$A:$A,0)),"") -> 1 | K13: =IF(OR(J13="",C13=""),"",J13*C13) -> 0 | L13: =IFERROR(LEFT(A13,FIND("_",A13,FIND("_",A13)+1)-1),A13) -> 1_10 | M13: =IF(OR(J13="",D13=""),"",J13*D13) -> 0
A14: 1_11_1 | B14: =IFERROR(INDEX(DQAF_Input!$A:$A,MATCH(A14,DQAF_Input!$D:$D,0)),"") -> Quality management practices are implemented | C14: =IFERROR((SUMIF(DQAF_Input!$D:$D,A14,DQAF_Input!$X:$X)/5)*100,"") -> 0 | D14: =IFERROR((SUMIF(DQAF_Input!$D:$D,A14,DQAF_Input!$AD:$AD)/5)*100,"") -> 10 | E14: =IFERROR(COUNTIFS(DQAF_Input!$D:$D,A14,DQAF_Input!$S:$S,"<>0"),0) -> 0 | F14: =IFERROR(COUNTIF(DQAF_Input!$D:$D,A14),0) -> 8 | G14: =IF(F14=0,"",E14/F14) -> 0 | H14: =IFERROR(COUNTIFS(DQAF_Input!$D:$D,A14,DQAF_Input!$S:$S,5),0) -> 0 | I14: =IF(F14=0,"",H14/F14) -> 0 | J14: =IFERROR(INDEX(__weights_indicator!$B:$B,MATCH(A14,__weights_indicator!$A:$A,0)),"") -> 1 | K14: =IF(OR(J14="",C14=""),"",J14*C14) -> 0 | L14: =IFERROR(LEFT(A14,FIND("_",A14,FIND("_",A14)+1)-1),A14) -> 1_11 | M14: =IF(OR(J14="",D14=""),"",J14*D14) -> 10

Sheet Maturity by Element
A1: ID | B1: Element | C1: Current Maturity (0-100) | D1: Target Maturity (0-100) | E1: S&Cs Observed | F1: Total S&C | G1: % Observed | H1: Fully Observed | I1: % Fully Observed | J1: ELEM_WEIGHT | K1: WEIGHTED_ELEM_MATURITY | L1: DIM_ID | M1: WEIGHTED_ELEM_MATURITY_TGT
A2: 1_1 | B2: =IFERROR(INDEX(__weights_element!$B:$B,MATCH(A2,__weights_element!$A:$A,0)),"") -> The legal framework defining the national statistical system is comprehensive | C2: =IFERROR(SUMIF('Maturity by Indicator'!$L:$L,A2,'Maturity by Indicator'!$K:$K),"") -> 62.666667 | D2: =IFERROR(SUMIF('Maturity by Indicator'!$L:$L,A2,'Maturity by Indicator'!$M:$M),"") -> 77.733333 | E2: =IFERROR(COUNTIFS(DQAF_Input!$C:$C,A2,DQAF_Input!$S:$S,"<>0"),0) -> 11 | F2: =IFERROR(COUNTIF(DQAF_Input!$C:$C,A2),0) -> 15 | G2: =IF(F2=0,"",E2/F2) -> 0.73333333 | H2: =IFERROR(COUNTIFS(DQAF_Input!$C:$C,A2,DQAF_Input!$S:$S,5),0) -> 2 | I2: =IF(F2=0,"",H2/F2) -> 0.13333333 | J2: =IFERROR(INDEX(__weights_element!$C:$C,MATCH(A2,__weights_element!$A:$A,0)),"") -> 0.1 | K2: =IF(OR(J2="",C2=""),"",J2*C2) -> 6.2666667 | L2: =IFERROR(LEFT(A2,FIND("_",A2)-1),A2) -> 1 | M2: =IF(OR(J2="",D2=""),"",J2*D2) -> 7.7733333
A3: 1_2 | B3: =IFERROR(INDEX(__weights_element!$B:$B,MATCH(A3,__weights_element!$A:$A,0)),"") -> Professional independence is ensured | C3: =IFERROR(SUMIF('Maturity by Indicator'!$L:$L,A3,'Maturity by Indicator'!$K:$K),"") -> 70 | D3: =IFERROR(SUMIF('Maturity by Indicator'!$L:$L,A3,'Maturity by Indicator'!$M:$M),"") -> 75 | E3: =IFERROR(COUNTIFS(DQAF_Input!$C:$C,A3,DQAF_Input!$S:$S,"<>0"),0) -> 3 | F3: =IFERROR(COUNTIF(DQAF_Input!$C:$C,A3),0) -> 4 | G3: =IF(F3=0,"",E3/F3) -> 0.75 | H3: =IFERROR(COUNTIFS(DQAF_Input!$C:$C,A3,DQAF_Input!$S:$S,5),0) -> 2 | I3: =IF(F3=0,"",H3/F3) -> 0.5 | J3: =IFERROR(INDEX(__weights_element!$C:$C,MATCH(A3,__weights_element!$A:$A,0)),"") -> 0.2 | K3: =IF(OR(J3="",C3=""),"",J3*C3) -> 14 | L3: =IFERROR(LEFT(A3,FIND("_",A3)-1),A3) -> 1 | M3: =IF(OR(J3="",D3=""),"",J3*D3) -> 15
A4: 1_3 | B4: =IFERROR(INDEX(__weights_element!$B:$B,MATCH(A4,__weights_element!$A:$A,0)),"") -> Effective coordination of the national statistical system | C4: =IFERROR(SUMIF('Maturity by Indicator'!$L:$L,A4,'Maturity by Indicator'!$K:$K),"") -> 0 | D4: =IFERROR(SUMIF('Maturity by Indicator'!$L:$L,A4,'Maturity by Indicator'!$M:$M),"") -> 0 | E4: =IFERROR(COUNTIFS(DQAF_Input!$C:$C,A4,DQAF_Input!$S:$S,"<>0"),0) -> 0 | F4: =IFERROR(COUNTIF(DQAF_Input!$C:$C,A4),0) -> 17 | G4: =IF(F4=0,"",E4/F4) -> 0 | H4: =IFERROR(COUNTIFS(DQAF_Input!$C:$C,A4,DQAF_Input!$S:$S,5),0) -> 0 | I4: =IF(F4=0,"",H4/F4) -> 0 | J4: =IFERROR(INDEX(__weights_element!$C:$C,MATCH(A4,__weights_element!$A:$A,0)),"") -> 0.15 | K4: =IF(OR(J4="",C4=""),"",J4*C4) -> 0 | L4: =IFERROR(LEFT(A4,FIND("_",A4)-1),A4) -> 1 | M4: =IF(OR(J4="",D4=""),"",J4*D4) -> 0
A5: 1_4 | B5: =IFERROR(INDEX(__weights_element!$B:$B,MATCH(A5,__weights_element!$A:$A,0)),"") -> Statistical confidentiality and data security are assured | C5: =IFERROR(SUMIF('Maturity by Indicator'!$L:$L,A5,'Maturity by Indicator'!$K:$K),"") -> 0 | D5: =IFERROR(SUMIF('Maturity by Indicator'!$L:$L,A5,'Maturity by Indicator'!$M:$M),"") -> 0 | E5: =IFERROR(COUNTIFS(DQAF_Input!$C:$C,A5,DQAF_Input!$S:$S,"<>0"),0) -> 0 | F5: =IFERROR(COUNTIF(DQAF_Input!$C:$C,A5),0) -> 13 | G5: =IF(F5=0,"",E5/F5) -> 0 | H5: =IFERROR(COUNTIFS(DQAF_Input!$C:$C,A5,DQAF_Input!$S:$S,5),0) -> 0 | I5: =IF(F5=0,"",H5/F5) -> 0 | J5: =IFERROR(INDEX(__weights_element!$C:$C,MATCH(A5,__weights_element!$A:$A,0)),"") -> 0.1 | K5: =IF(OR(J5="",C5=""),"",J5*C5) -> 0 | L5: =IFERROR(LEFT(A5,FIND("_",A5)-1),A5) -> 1 | M5: =IF(OR(J5="",D5=""),"",J5*D5) -> 0
A6: 1_5 | B6: =IFERROR(INDEX(__weights_element!$B:$B,MATCH(A6,__weights_element!$A:$A,0)),"") -> Response burden is minimized | C6: =IFERROR(SUMIF('Maturity by Indicator'!$L:$L,A6,'Maturity by Indicator'!$K:$K),"") -> 0 | D6: =IFERROR(SUMIF('Maturity by Indicator'!$L:$L,A6,'Maturity by Indicator'!$M:$M),"") -> 0 | E6: =IFERROR(COUNTIFS(DQAF_Input!$C:$C,A6,DQAF_Input!$S:$S,"<>0"),0) -> 0 | F6: =IFERROR(COUNTIF(DQAF_Input!$C:$C,A6),0) -> 3 | G6: =IF(F6=0,"",E6/F6) -> 0 | H6: =IFERROR(COUNTIFS(DQAF_Input!$C:$C,A6,DQAF_Input!$S:$S,5),0) -> 0 | I6: =IF(F6=0,"",H6/F6) -> 0 | J6: =IFERROR(INDEX(__weights_element!$C:$C,MATCH(A6,__weights_element!$A:$A,0)),"") -> 0.1 | K6: =IF(OR(J6="",C6=""),"",J6*C6) -> 0 | L6: =IFERROR(LEFT(A6,FIND("_",A6)-1),A6) -> 1 | M6: =IF(OR(J6="",D6=""),"",J6*D6) -> 0
A7: 1_6 | B7: =IFERROR(INDEX(__weights_element!$B:$B,MATCH(A7,__weights_element!$A:$A,0)),"") -> Human resources are adequate | C7: =IFERROR(SUMIF('Maturity by Indicator'!$L:$L,A7,'Maturity by Indicator'!$K:$K),"") -> 0 | D7: =IFERROR(SUMIF('Maturity by Indicator'!$L:$L,A7,'Maturity by Indicator'!$M:$M),"") -> 0 | E7: =IFERROR(COUNTIFS(DQAF_Input!$C:$C,A7,DQAF_Input!$S:$S,"<>0"),0) -> 0 | F7: =IFERROR(COUNTIF(DQAF_Input!$C:$C,A7),0) -> 24 | G7: =IF(F7=0,"",E7/F7) -> 0 | H7: =IFERROR(COUNTIFS(DQAF_Input!$C:$C,A7,DQAF_Input!$S:$S,5),0) -> 0 | I7: =IF(F7=0,"",H7/F7) -> 0 | J7: =IFERROR(INDEX(__weights_element!$C:$C,MATCH(A7,__weights_element!$A:$A,0)),"") -> 0.15 | K7: =IF(OR(J7="",C7=""),"",J7*C7) -> 0 | L7: =IFERROR(LEFT(A7,FIND("_",A7)-1),A7) -> 1 | M7: =IF(OR(J7="",D7=""),"",J7*D7) -> 0
A8: 1_7 | B8: =IFERROR(INDEX(__weights_element!$B:$B,MATCH(A8,__weights_element!$A:$A,0)),"") -> Information technology resources are adequate | C8: =IFERROR(SUMIF('Maturity by Indicator'!$L:$L,A8,'Maturity by Indicator'!$K:$K),"") -> 0 | D8: =IFERROR(SUMIF('Maturity by Indicator'!$L:$L,A8,'Maturity by Indicator'!$M:$M),"") -> 0 | E8: =IFERROR(COUNTIFS(DQAF_Input!$C:$C,A8,DQAF_Input!$S:$S,"<>0"),0) -> 0 | F8: =IFERROR(COUNTIF(DQAF_Input!$C:$C,A8),0) -> 5 | G8: =IF(F8=0,"",E8/F8) -> 0 | H8: =IFERROR(COUNTIFS(DQAF_Input!$C:$C,A8,DQAF_Input!$S:$S,5),0) -> 0 | I8: =IF(F8=0,"",H8/F8) -> 0 | J8: =IFERROR(INDEX(__weights_element!$C:$C,MATCH(A8,__weights_element!$A:$A,0)),"") -> 0.05 | K8: =IF(OR(J8="",C8=""),"",J8*C8) -> 0 | L8: =IFERROR(LEFT(A8,FIND("_",A8)-1),A8) -> 1 | M8: =IF(OR(J8="",D8=""),"",J8*D8) -> 0
A9: 1_8 | B9: =IFERROR(INDEX(__weights_element!$B:$B,MATCH(A9,__weights_element!$A:$A,0)),"") -> Physical infrastructure is adequate | C9: =IFERROR(SUMIF('Maturity by Indicator'!$L:$L,A9,'Maturity by Indicator'!$K:$K),"") -> 0 | D9: =IFERROR(SUMIF('Maturity by Indicator'!$L:$L,A9,'Maturity by Indicator'!$M:$M),"") -> 0 | E9: =IFERROR(COUNTIFS(DQAF_Input!$C:$C,A9,DQAF_Input!$S:$S,"<>0"),0) -> 0 | F9: =IFERROR(COUNTIF(DQAF_Input!$C:$C,A9),0) -> 3 | G9: =IF(F9=0,"",E9/F9) -> 0 | H9: =IFERROR(COUNTIFS(DQAF_Input!$C:$C,A9,DQAF_Input!$S:$S,5),0) -> 0 | I9: =IF(F9=0,"",H9/F9) -> 0 | J9: =IFERROR(INDEX(__weights_element!$C:$C,MATCH(A9,__weights_element!$A:$A,0)),"") -> 0.05 | K9: =IF(OR(J9="",C9=""),"",J9*C9) -> 0 | L9: =IFERROR(LEFT(A9,FIND("_",A9)-1),A9) -> 1 | M9: =IF(OR(J9="",D9=""),"",J9*D9) -> 0
